Workbook
Name AgeRange: RetNorm_Engine!$C$3:INDEX(RetNorm_Engine!$C$3:$XFD$3, COUNTA(RetNorm_Engine!$C$3:$XFD$3))
Name buffer: Inputs!$B$159
Name ChartCash_Early: RetEarly_Engine!$C$201:INDEX(RetEarly_Engine!$C$201:$XFD$201, COUNTA(RetEarly_Engine!$C$201:$XFD$201))
Name ChartCash_Norm: RetNorm_Engine!$C$201:INDEX(RetNorm_Engine!$C$201:$XFD$201, COUNTA(RetNorm_Engine!$C$201:$XFD$201))
Name ChartNW_Early: RetEarly_Engine!$C$202:INDEX(RetEarly_Engine!$C$202:$XFD$202, COUNTA(RetEarly_Engine!$C$202:$XFD$202))
Name ChartNW_Norm: RetNorm_Engine!$C$202:INDEX(RetNorm_Engine!$C$202:$XFD$202, COUNTA(RetNorm_Engine!$C$202:$XFD$202))
Name EndAge: Inputs!$B$134
Name inf: Inputs!$B$145
Name princ: Inputs!$B$147
Name RetAge: Inputs!$B$19
Name rinc: Inputs!$B$155
Name sincr: Inputs!$B$153
Name stinc: Inputs!$B$151

Sheet Inputs
B1: User inputs | D1: User Tooltips | E1: UI Notes | F1: Excel helpers
A2: QUICK START
A4: Your age | B4: 47 | D4: Must be entered
A6: Current net annual income | B6: 60000 | D6: Net of tax, from employment or self-employment
A8: Total cash balances | B8: 200000 | D8: current and savings accounts, bonds, term deposits
A10: Stock market investments | B10: 50000 | D10: Current market value of equity portfolio
A12: Home current market value | B12: 500000 | D12: Leave blank if not a home owner
A14: Home loan (mortgage)
A15: Balance | B15: 120000 | D15: Leave blank if no mortgage | F15: Months remaining | G15: =IFERROR(NPER(B16/12,-B17,B15),"") -> 188.23636
A16: Interest rate | B16: 0.03 | F16: Years remaining | G16: =IFERROR(G15/12,"") -> 15.686363
A17: Monthly repayment | B17: 800
A19: Statutory retirement age | B19: 65 | D19: Year at which pension starts
A21: Annual pension at retirement | B21: 18000 | D21: Net annual state pension entitlement
A23: Housing rent | D23: if not a home owner | E23: show only if not a home owner (B12="")
A25: Annual living expenses | B25: 50000
A28: DEEPER DIVE | E28: Activated only if user wants to
A30: Dependents
A32: Dependent 1
A33: Name | D33: Leave blank if none
A34: Annual cost | D34: Food, education, healthcare, etc. | E34: Hide until user enters dependent name
A35: Years to support | D35: Years from now | E35: Hide until user enters dependent name
A37: Dependent 2
A38: Name | D38: Leave blank if none
A39: Annual cost | D39: Food, education, healthcare, etc. | E39: Hide until user enters dependent name
A40: Years to support | D40: Years from now | E40: Hide until user enters dependent name
A42: Dependent 3
A43: Name | D43: Leave blank if none
A44: Annual cost | D44: Food, education, healthcare, etc. | E44: Hide until user enters dependent name
A45: Years to support | D45: Years from now | E45: Hide until user enters dependent name
A47: Investment Properties
A49: Property 1
A50: Name | B50: Sliema | D50: Leave blank if none
A51: Market value | B51: 300000 | E51: Hide until user enters property name
A52: Annual costs | B52: 500 | D52: Repairs, maintenance, etc. | E52: Hide until user enters property name
A54: Property 2
A55: Name | D55: Leave blank if none
A56: Market value | E56: Hide until user enters property name
A57: Annual costs | D57: Repairs, maintenance, etc. | E57: Hide until user enters property name
A59: Property 3
A60: Name | D60: Leave blank if none
A61: Market value | E61: Hide until user enters property name
A62: Annual costs | D62: Repairs, maintenance, etc. | E62: Hide until user enters property name
A64: Other income
A66: ="Rental income: "&B50 -> Rental income: Sliema | D66: net annual after all costs and tax | E66: Show with property name only if name was entered
A67: ="Rental income: "&B55 -> Rental income: | D67: net annual after all costs and tax | E67: Show with property name only if name was entered
A68: ="Rental income: "&B60 -> Rental income: | D68: net annual after all costs and tax | E68: Show with property name only if name was entered
A70: Other work income (net annual) | D70: Part-time / consulting / side projects etc. Leave blank if none
A71: Continue other work until age | E71: Show only if other work income entered
A73: Other loans
A75: Credit card balances | D75: Assumed cleared in Year 1. Leave blank if none
A77: =B50 & " Property" -> Sliema Property
A78: Balance | D78: Enter 0 or leave blank if none | F78: Months remaining | G78: =IFERROR(NPER(B79/12,-B80,B78),"")
A79: Interest rate | F79: Years remaining | G79: =IFERROR(G78/12,"")
A80: Monthly repayment
A82: =B55 & " Property" -> Property
A83: Balance | D83: Enter 0 or leave blank if none | F83: Months remaining | G83: =IFERROR(NPER(B84/12,-B85,B83),"")
A84: Interest rate | F84: Years remaining | G84: =IFERROR(G83/12,"")
A85: Monthly repayment
A87: =B60& " Property" -> Property
A88: Balance | D88: Enter 0 or leave blank if none | F88: Months remaining | G88: =IFERROR(NPER(B89/12,-B90,B88),"")
A89: Interest rate | F89: Years remaining | G89: =IFERROR(G88/12,"")
A90: Monthly repayment
A92: Other loan
A93: Balance | D93: Leave blank if none | F93: Months remaining | G93: =IFERROR(NPER(B94/12,-B95,B93),"")
A94: Interest rate | F94: Years remaining | G94: =IFERROR(G93/12,"")
A95: Monthly repayment
A97: Major life income events
A99: Income Event 1
A100: Name | D100: Leave blank if none
A101: Amount | D101: Enter 0 or leave blank if none
A102: Year
A104: Income Event 2
A105: Name | D105: Leave blank if none
A106: Amount | D106: Enter 0 or leave blank if none
A107: Year
A109: Income Event 3
A110: Name | D110: Leave blank if none
A111: Amount | D111: Enter 0 or leave blank if none
A112: Year
A114: Major life expense events
A116: Expense Event 1
A117: Name | D117: Leave blank if none
A118: Amount | D118: Enter 0 or leave blank if none
A119: Year
A121: Expense Event 2
A122: Name | D122: Leave blank if none
A123: Amount | D123: Enter 0 or leave blank if none
A124: Year
A126: Expense Event 3
A127: Name | D127: Leave blank if none
A128: Amount | D128: Enter 0 or leave blank if none
A129: Year
A132: FINER DETAILS | C132: Defaults | E132: Works behind the scenes, show and allow edit if user wants to
A134: Plan to live until age | B134: 94 | C134: 85
A136: Spending adjustment (at today's euros)
A137: from now to 65 | B137: 0 | C137: 0 | D137: more / less than current
A138: from 66-75 | B138: -0.1 | C138: -0.1 | D138: more / less than current
A139: from age 76 | B139: -0.2 | C139: -0.2 | D139: more / less than current
A141: Other post-retirement income | D141: Enter 0 or leave blank if none
A142: From age
...

Sheet Output
V2: Retire at | AA2: ="Retire at "&RetEarly_Engine!B3 -> Retire at 59
V3: =RetEarly_Engine!B3 -> 59 | AA3: ="Retire at "&RetAge -> Retire at 65

Sheet RetNorm_Engine
B1: 0 | C1: 1 | D1: =C1+1 -> 2 | E1: =D1+1 -> 3 | F1: =E1+1 -> 4 | G1: =F1+1 -> 5 | H1: =G1+1 -> 6 | I1: =H1+1 -> 7 | J1: =I1+1 -> 8 | K1: =J1+1 -> 9 | ... AW1: =AV1+1 -> 47
B2: Year | C2: =YEAR(TODAY())+1 -> 2027 | D2: =C2+1 -> 2028 | E2: =D2+1 -> 2029 | F2: =E2+1 -> 2030 | G2: =F2+1 -> 2031 | H2: =G2+1 -> 2032 | I2: =H2+1 -> 2033 | J2: =I2+1 -> 2034 | K2: =J2+1 -> 2035 | ... AW2: =AV2+1 -> 2073
B3: =Inputs!B19 -> 65 | C3: =Inputs!B4+1 -> 48 | D3: =C3+1 -> 49 | E3: =D3+1 -> 50 | F3: =E3+1 -> 51 | G3: =F3+1 -> 52 | H3: =G3+1 -> 53 | I3: =H3+1 -> 54 | J3: =I3+1 -> 55 | K3: =J3+1 -> 56 | ... AW3: =AV3+1 -> 94
A4: Inflows
A5: Net employment / self-employment income | C5: =IF(AND(Inputs!$B$19>C3,$B$3>C3),Inputs!$B$6*(1+sincr)^B1,0) -> 60000 | D5: =IF(AND(Inputs!$B$19>D3,$B$3>D3),Inputs!$B$6*(1+sincr)^C1,0) -> 61800 | E5: =IF(AND(Inputs!$B$19>E3,$B$3>E3),Inputs!$B$6*(1+sincr)^D1,0) -> 63654 | F5: =IF(AND(Inputs!$B$19>F3,$B$3>F3),Inputs!$B$6*(1+sincr)^E1,0) -> 65563.62 | G5: =IF(AND(Inputs!$B$19>G3,$B$3>G3),Inputs!$B$6*(1+sincr)^F1,0) -> 67530.529 | H5: =IF(AND(Inputs!$B$19>H3,$B$3>H3),Inputs!$B$6*(1+sincr)^G1,0) -> 69556.444 | I5: =IF(AND(Inputs!$B$19>I3,$B$3>I3),Inputs!$B$6*(1+sincr)^H1,0) -> 71643.138 | J5: =IF(AND(Inputs!$B$19>J3,$B$3>J3),Inputs!$B$6*(1+sincr)^I1,0) -> 73792.432 | ... AW5: =IF(AND(Inputs!$B$19>AW3,$B$3>AW3),Inputs!$B$6*(1+sincr)^AV1,0) -> 0
A6: Net from other work | C6: =IF(C$3<=Inputs!$B$71,Inputs!$B$70,0)*(1+inf)^B$1 -> 0 | D6: =IF(D$3<=Inputs!$B$71,Inputs!$B$70,0)*(1+inf)^C$1 -> 0 | E6: =IF(E$3<=Inputs!$B$71,Inputs!$B$70,0)*(1+inf)^D$1 -> 0 | F6: =IF(F$3<=Inputs!$B$71,Inputs!$B$70,0)*(1+inf)^E$1 -> 0 | G6: =IF(G$3<=Inputs!$B$71,Inputs!$B$70,0)*(1+inf)^F$1 -> 0 | H6: =IF(H$3<=Inputs!$B$71,Inputs!$B$70,0)*(1+inf)^G$1 -> 0 | I6: =IF(I$3<=Inputs!$B$71,Inputs!$B$70,0)*(1+inf)^H$1 -> 0 | J6: =IF(J$3<=Inputs!$B$71,Inputs!$B$70,0)*(1+inf)^I$1 -> 0 | ... AW6: =IF(AW$3<=Inputs!$B$71,Inputs!$B$70,0)*(1+inf)^AV$1 -> 0
A7: Net rental income from other properties
A8: =TEXT(Inputs!$B$50,"") -> Sliema | C8: =Inputs!B66 -> 0 | D8: =C8*(1+rinc) -> 0 | E8: =D8*(1+rinc) -> 0 | F8: =E8*(1+rinc) -> 0 | G8: =F8*(1+rinc) -> 0 | H8: =G8*(1+rinc) -> 0 | I8: =H8*(1+rinc) -> 0 | J8: =I8*(1+rinc) -> 0 | K8: =J8*(1+rinc) -> 0 | ... AW8: =AV8*(1+rinc) -> 0
A9: =TEXT(Inputs!$B$55,"") | C9: =Inputs!B67 -> 0 | D9: =C9*(1+rinc) -> 0 | E9: =D9*(1+rinc) -> 0 | F9: =E9*(1+rinc) -> 0 | G9: =F9*(1+rinc) -> 0 | H9: =G9*(1+rinc) -> 0 | I9: =H9*(1+rinc) -> 0 | J9: =I9*(1+rinc) -> 0 | K9: =J9*(1+rinc) -> 0 | ... AW9: =AV9*(1+rinc) -> 0
A10: =TEXT(Inputs!$B$60,"") | C10: =Inputs!B68 -> 0 | D10: =C10*(1+rinc) -> 0 | E10: =D10*(1+rinc) -> 0 | F10: =E10*(1+rinc) -> 0 | G10: =F10*(1+rinc) -> 0 | H10: =G10*(1+rinc) -> 0 | I10: =H10*(1+rinc) -> 0 | J10: =I10*(1+rinc) -> 0 | K10: =J10*(1+rinc) -> 0 | ... AW10: =AV10*(1+rinc) -> 0
A11: Full pension | C11: =IF(C$3<Inputs!$B$19,0,Inputs!$B$21)*(1+inf)^B$1 -> 0 | D11: =IF(D$3<Inputs!$B$19,0,Inputs!$B$21)*(1+inf)^C$1 -> 0 | E11: =IF(E$3<Inputs!$B$19,0,Inputs!$B$21)*(1+inf)^D$1 -> 0 | F11: =IF(F$3<Inputs!$B$19,0,Inputs!$B$21)*(1+inf)^E$1 -> 0 | G11: =IF(G$3<Inputs!$B$19,0,Inputs!$B$21)*(1+inf)^F$1 -> 0 | H11: =IF(H$3<Inputs!$B$19,0,Inputs!$B$21)*(1+inf)^G$1 -> 0 | I11: =IF(I$3<Inputs!$B$19,0,Inputs!$B$21)*(1+inf)^H$1 -> 0 | J11: =IF(J$3<Inputs!$B$19,0,Inputs!$B$21)*(1+inf)^I$1 -> 0 | ... AW11: =IF(AW$3<Inputs!$B$19,0,Inputs!$B$21)*(1+inf)^AV$1 -> 56049.315
A12: Pension reduction from early retirement | C12: =MIN(0,MAX(-IF(C11=0,0,(Inputs!$B$19-INDEX(3:3,MATCH(0,5:5,0))))*Inputs!$B$157*(1+inf)^B$1,-C11)) -> 0 | D12: =MIN(0,MAX(-IF(D11=0,0,(Inputs!$B$19-INDEX(3:3,MATCH(0,5:5,0))))*Inputs!$B$157*(1+inf)^C$1,-D11)) -> 0 | E12: =MIN(0,MAX(-IF(E11=0,0,(Inputs!$B$19-INDEX(3:3,MATCH(0,5:5,0))))*Inputs!$B$157*(1+inf)^D$1,-E11)) -> 0 | F12: =MIN(0,MAX(-IF(F11=0,0,(Inputs!$B$19-INDEX(3:3,MATCH(0,5:5,0))))*Inputs!$B$157*(1+inf)^E$1,-F11)) -> 0 | G12: =MIN(0,MAX(-IF(G11=0,0,(Inputs!$B$19-INDEX(3:3,MATCH(0,5:5,0))))*Inputs!$B$157*(1+inf)^F$1,-G11)) -> 0 | H12: =MIN(0,MAX(-IF(H11=0,0,(Inputs!$B$19-INDEX(3:3,MATCH(0,5:5,0))))*Inputs!$B$157*(1+inf)^G$1,-H11)) -> 0 | I12: =MIN(0,MAX(-IF(I11=0,0,(Inputs!$B$19-INDEX(3:3,MATCH(0,5:5,0))))*Inputs!$B$157*(1+inf)^H$1,-I11)) -> 0 | J12: =MIN(0,MAX(-IF(J11=0,0,(Inputs!$B$19-INDEX(3:3,MATCH(0,5:5,0))))*Inputs!$B$157*(1+inf)^I$1,-J11)) -> 0 | ... AW12: =MIN(0,MAX(-IF(AW11=0,0,(Inputs!$B$19-INDEX(3:3,MATCH(0,5:5,0))))*Inputs!$B$157*(1+inf)^AV$1,-AW11)) -> 0
A13: Other post-retirement income | C13: =IF(AND(C$3>=Inputs!$B$142,C$3<=Inputs!$B$143),Inputs!$B$141*(1+inf)^B$1,0) -> 0 | D13: =IF(AND(D$3>=Inputs!$B$142,D$3<=Inputs!$B$143),Inputs!$B$141*(1+inf)^C$1,0) -> 0 | E13: =IF(AND(E$3>=Inputs!$B$142,E$3<=Inputs!$B$143),Inputs!$B$141*(1+inf)^D$1,0) -> 0 | F13: =IF(AND(F$3>=Inputs!$B$142,F$3<=Inputs!$B$143),Inputs!$B$141*(1+inf)^E$1,0) -> 0 | G13: =IF(AND(G$3>=Inputs!$B$142,G$3<=Inputs!$B$143),Inputs!$B$141*(1+inf)^F$1,0) -> 0 | H13: =IF(AND(H$3>=Inputs!$B$142,H$3<=Inputs!$B$143),Inputs!$B$141*(1+inf)^G$1,0) -> 0 | I13: =IF(AND(I$3>=Inputs!$B$142,I$3<=Inputs!$B$143),Inputs!$B$141*(1+inf)^H$1,0) -> 0 | J13: =IF(AND(J$3>=Inputs!$B$142,J$3<=Inputs!$B$143),Inputs!$B$141*(1+inf)^I$1,0) -> 0 | ... AW13: =IF(AND(AW$3>=Inputs!$B$142,AW$3<=Inputs!$B$143),Inputs!$B$141*(1+inf)^AV$1,0) -> 0
A14: Major one-off income events
A15: =TEXT(Inputs!B100,"") | C15: =IF(C$2=Inputs!$B102,Inputs!$B101,0)*(1+inf)^B$1 -> 0 | D15: =IF(D$2=Inputs!$B102,Inputs!$B101,0)*(1+inf)^C$1 -> 0 | E15: =IF(E$2=Inputs!$B102,Inputs!$B101,0)*(1+inf)^D$1 -> 0 | F15: =IF(F$2=Inputs!$B102,Inputs!$B101,0)*(1+inf)^E$1 -> 0 | G15: =IF(G$2=Inputs!$B102,Inputs!$B101,0)*(1+inf)^F$1 -> 0 | H15: =IF(H$2=Inputs!$B102,Inputs!$B101,0)*(1+inf)^G$1 -> 0 | I15: =IF(I$2=Inputs!$B102,Inputs!$B101,0)*(1+inf)^H$1 -> 0 | J15: =IF(J$2=Inputs!$B102,Inputs!$B101,0)*(1+inf)^I$1 -> 0 | ... AW15: =IF(AW$2=Inputs!$B102,Inputs!$B101,0)*(1+inf)^AV$1 -> 0
A16: =TEXT(Inputs!B105,"") | C16: =IF(C$2=Inputs!$B107,Inputs!$B106,0)*(1+inf)^B$1 -> 0 | D16: =IF(D$2=Inputs!$B107,Inputs!$B106,0)*(1+inf)^C$1 -> 0 | E16: =IF(E$2=Inputs!$B107,Inputs!$B106,0)*(1+inf)^D$1 -> 0 | F16: =IF(F$2=Inputs!$B107,Inputs!$B106,0)*(1+inf)^E$1 -> 0 | G16: =IF(G$2=Inputs!$B107,Inputs!$B106,0)*(1+inf)^F$1 -> 0 | H16: =IF(H$2=Inputs!$B107,Inputs!$B106,0)*(1+inf)^G$1 -> 0 | I16: =IF(I$2=Inputs!$B107,Inputs!$B106,0)*(1+inf)^H$1 -> 0 | J16: =IF(J$2=Inputs!$B107,Inputs!$B106,0)*(1+inf)^I$1 -> 0 | ... AW16: =IF(AW$2=Inputs!$B107,Inputs!$B106,0)*(1+inf)^AV$1 -> 0
A17: =TEXT(Inputs!B110,"") | C17: =IF(C$2=Inputs!$B112,Inputs!$B111,0)*(1+inf)^B$1 -> 0 | D17: =IF(D$2=Inputs!$B112,Inputs!$B111,0)*(1+inf)^C$1 -> 0 | E17: =IF(E$2=Inputs!$B112,Inputs!$B111,0)*(1+inf)^D$1 -> 0 | F17: =IF(F$2=Inputs!$B112,Inputs!$B111,0)*(1+inf)^E$1 -> 0 | G17: =IF(G$2=Inputs!$B112,Inputs!$B111,0)*(1+inf)^F$1 -> 0 | H17: =IF(H$2=Inputs!$B112,Inputs!$B111,0)*(1+inf)^G$1 -> 0 | I17: =IF(I$2=Inputs!$B112,Inputs!$B111,0)*(1+inf)^H$1 -> 0 | J17: =IF(J$2=Inputs!$B112,Inputs!$B111,0)*(1+inf)^I$1 -> 0 | ... AW17: =IF(AW$2=Inputs!$B112,Inputs!$B111,0)*(1+inf)^AV$1 -> 0
A18: Interest on cash balances | C18: =MAX(AVERAGE(C49,C49+SUM(C5:C17)-C46)*Inputs!$B$149,0) -> 4998.75 | D18: =MAX(AVERAGE(D49,D49+SUM(D5:D17)-D46)*Inputs!$B$149,0) -> 5127.9375 | E18: =MAX(AVERAGE(E49,E49+SUM(E5:E17)-E46)*Inputs!$B$149,0) -> 5274.0727 | F18: =MAX(AVERAGE(F49,F49+SUM(F5:F17)-F46)*Inputs!$B$149,0) -> 5438.1505 | G18: =MAX(AVERAGE(G49,G49+SUM(G5:G17)-G46)*Inputs!$B$149,0) -> 5621.212 | H18: =MAX(AVERAGE(H49,H49+SUM(H5:H17)-H46)*Inputs!$B$149,0) -> 5824.3462 | I18: =MAX(AVERAGE(I49,I49+SUM(I5:I17)-I46)*Inputs!$B$149,0) -> 6048.6917 | J18: =MAX(AVERAGE(J49,J49+SUM(J5:J17)-J46)*Inputs!$B$149,0) -> 6295.4392 | ... AW18: =MAX(AVERAGE(AW49,AW49+SUM(AW5:AW17)-AW46)*Inputs!$B$149,0) -> 0
C19: =SUM(C4:C18) -> 64998.75 | D19: =SUM(D4:D18) -> 66927.938 | E19: =SUM(E4:E18) -> 68928.073 | F19: =SUM(F4:F18) -> 71001.77 | G19: =SUM(G4:G18) -> 73151.741 | H19: =SUM(H4:H18) -> 75380.791 | I19: =SUM(I4:I18) -> 77691.829 | J19: =SUM(J4:J18) -> 80087.871 | ... AW19: =SUM(AW4:AW18) -> 56049.315
A20: Outflows
A21: Credit cards cleared | C21: =Inputs!B75 -> 0 | D21: 0 | E21: 0 | F21: 0 | G21: 0 | H21: 0 | I21: 0 | J21: 0 | K21: 0 | L21: 0 | M21: 0 | N21: 0 | O21: 0 | P21: 0 | Q21: 0 | R21: 0 | S21: 0 | T21: 0 | U21: 0 | V21: 0 | W21: 0 | X21: 0 | Y21: 0 | Z21: 0 | AA21: 0 | AB21: 0 | AC21: 0 | AD21: 0 | AE21: 0 | AF21: 0 | AG21: 0 | AH21: 0 | AI21: 0 | AJ21: 0 | AK21: 0 | AL21: 0 | AM21: 0 | AN21: 0 | AO21: 0 | AP21: 0 | AQ21: 0 | AR21: 0 | AS21: 0 | AT21: 0 | AU21: 0 | AV21: 0 | AW21: 0
A22: Home loan repayment | C22: =MAX(IF(C$1*12<=Inputs!$G$15,12,(Inputs!$G$15-B$1*12)),0)*Inputs!$B$17 -> 9600 | D22: =MAX(IF(D$1*12<=Inputs!$G$15,12,(Inputs!$G$15-C$1*12)),0)*Inputs!$B$17 -> 9600 | E22: =MAX(IF(E$1*12<=Inputs!$G$15,12,(Inputs!$G$15-D$1*12)),0)*Inputs!$B$17 -> 9600 | F22: =MAX(IF(F$1*12<=Inputs!$G$15,12,(Inputs!$G$15-E$1*12)),0)*Inputs!$B$17 -> 9600 | G22: =MAX(IF(G$1*12<=Inputs!$G$15,12,(Inputs!$G$15-F$1*12)),0)*Inputs!$B$17 -> 9600 | H22: =MAX(IF(H$1*12<=Inputs!$G$15,12,(Inputs!$G$15-G$1*12)),0)*Inputs!$B$17 -> 9600 | I22: =MAX(IF(I$1*12<=Inputs!$G$15,12,(Inputs!$G$15-H$1*12)),0)*Inputs!$B$17 -> 9600 | J22: =MAX(IF(J$1*12<=Inputs!$G$15,12,(Inputs!$G$15-I$1*12)),0)*Inputs!$B$17 -> 9600 | ... AW22: =MAX(IF(AW$1*12<=Inputs!$G$15,12,(Inputs!$G$15-AV$1*12)),0)*Inputs!$B$17 -> 0
A23: Other property loans repayments
A24: =TEXT(Inputs!$B$50,"") -> Sliema | C24: =MAX(IF(C$1*12<=Inputs!$G$78,12,(Inputs!$G$78-B$1*12)),0)*Inputs!$B$80 -> 0 | D24: =MAX(IF(D$1*12<=Inputs!$G$78,12,(Inputs!$G$78-C$1*12)),0)*Inputs!$B$80 -> 0 | E24: =MAX(IF(E$1*12<=Inputs!$G$78,12,(Inputs!$G$78-D$1*12)),0)*Inputs!$B$80 -> 0 | F24: =MAX(IF(F$1*12<=Inputs!$G$78,12,(Inputs!$G$78-E$1*12)),0)*Inputs!$B$80 -> 0 | G24: =MAX(IF(G$1*12<=Inputs!$G$78,12,(Inputs!$G$78-F$1*12)),0)*Inputs!$B$80 -> 0 | H24: =MAX(IF(H$1*12<=Inputs!$G$78,12,(Inputs!$G$78-G$1*12)),0)*Inputs!$B$80 -> 0 | I24: =MAX(IF(I$1*12<=Inputs!$G$78,12,(Inputs!$G$78-H$1*12)),0)*Inputs!$B$80 -> 0 | J24: =MAX(IF(J$1*12<=Inputs!$G$78,12,(Inputs!$G$78-I$1*12)),0)*Inputs!$B$80 -> 0 | ... AW24: =MAX(IF(AW$1*12<=Inputs!$G$78,12,(Inputs!$G$78-AV$1*12)),0)*Inputs!$B$80 -> 0
A25: =TEXT(Inputs!$B$55,"") | C25: =MAX(IF(C$1*12<=Inputs!$G$83,12,(Inputs!$G$83-B$1*12)),0)*Inputs!$B$85 -> 0 | D25: =MAX(IF(D$1*12<=Inputs!$G$83,12,(Inputs!$G$83-C$1*12)),0)*Inputs!$B$85 -> 0 | E25: =MAX(IF(E$1*12<=Inputs!$G$83,12,(Inputs!$G$83-D$1*12)),0)*Inputs!$B$85 -> 0 | F25: =MAX(IF(F$1*12<=Inputs!$G$83,12,(Inputs!$G$83-E$1*12)),0)*Inputs!$B$85 -> 0 | G25: =MAX(IF(G$1*12<=Inputs!$G$83,12,(Inputs!$G$83-F$1*12)),0)*Inputs!$B$85 -> 0 | H25: =MAX(IF(H$1*12<=Inputs!$G$83,12,(Inputs!$G$83-G$1*12)),0)*Inputs!$B$85 -> 0 | I25: =MAX(IF(I$1*12<=Inputs!$G$83,12,(Inputs!$G$83-H$1*12)),0)*Inputs!$B$85 -> 0 | J25: =MAX(IF(J$1*12<=Inputs!$G$83,12,(Inputs!$G$83-I$1*12)),0)*Inputs!$B$85 -> 0 | ... AW25: =MAX(IF(AW$1*12<=Inputs!$G$83,12,(Inputs!$G$83-AV$1*12)),0)*Inputs!$B$85 -> 0
A26: =TEXT(Inputs!$B$60,"") | C26: =MAX(IF(C$1*12<=Inputs!$G$88,12,(Inputs!$G$88-B$1*12)),0)*Inputs!$B$90 -> 0 | D26: =MAX(IF(D$1*12<=Inputs!$G$88,12,(Inputs!$G$88-C$1*12)),0)*Inputs!$B$90 -> 0 | E26: =MAX(IF(E$1*12<=Inputs!$G$88,12,(Inputs!$G$88-D$1*12)),0)*Inputs!$B$90 -> 0 | F26: =MAX(IF(F$1*12<=Inputs!$G$88,12,(Inputs!$G$88-E$1*12)),0)*Inputs!$B$90 -> 0 | G26: =MAX(IF(G$1*12<=Inputs!$G$88,12,(Inputs!$G$88-F$1*12)),0)*Inputs!$B$90 -> 0 | H26: =MAX(IF(H$1*12<=Inputs!$G$88,12,(Inputs!$G$88-G$1*12)),0)*Inputs!$B$90 -> 0 | I26: =MAX(IF(I$1*12<=Inputs!$G$88,12,(Inputs!$G$88-H$1*12)),0)*Inputs!$B$90 -> 0 | J26: =MAX(IF(J$1*12<=Inputs!$G$88,12,(Inputs!$G$88-I$1*12)),0)*Inputs!$B$90 -> 0 | ... AW26: =MAX(IF(AW$1*12<=Inputs!$G$88,12,(Inputs!$G$88-AV$1*12)),0)*Inputs!$B$90 -> 0
A27: Other loan repayment | C27: =MAX(IF(C$1*12<=Inputs!$G$93,12,(Inputs!$G$93-B$1*12)),0)*Inputs!$B$95 -> 0 | D27: =MAX(IF(D$1*12<=Inputs!$G$93,12,(Inputs!$G$93-C$1*12)),0)*Inputs!$B$95 -> 0 | E27: =MAX(IF(E$1*12<=Inputs!$G$93,12,(Inputs!$G$93-D$1*12)),0)*Inputs!$B$95 -> 0 | F27: =MAX(IF(F$1*12<=Inputs!$G$93,12,(Inputs!$G$93-E$1*12)),0)*Inputs!$B$95 -> 0 | G27: =MAX(IF(G$1*12<=Inputs!$G$93,12,(Inputs!$G$93-F$1*12)),0)*Inputs!$B$95 -> 0 | H27: =MAX(IF(H$1*12<=Inputs!$G$93,12,(Inputs!$G$93-G$1*12)),0)*Inputs!$B$95 -> 0 | I27: =MAX(IF(I$1*12<=Inputs!$G$93,12,(Inputs!$G$93-H$1*12)),0)*Inputs!$B$95 -> 0 | J27: =MAX(IF(J$1*12<=Inputs!$G$93,12,(Inputs!$G$93-I$1*12)),0)*Inputs!$B$95 -> 0 | ... AW27: =MAX(IF(AW$1*12<=Inputs!$G$93,12,(Inputs!$G$93-AV$1*12)),0)*Inputs!$B$95 -> 0
A28: Dependents cost
A29: =TEXT(Inputs!B33,"") | C29: =IF(Inputs!$B$35>=C$1,Inputs!$B$34,0)*(1+inf)^B$1 -> 0 | D29: =IF(Inputs!$B$35>=D$1,Inputs!$B$34,0)*(1+inf)^C$1 -> 0 | E29: =IF(Inputs!$B$35>=E$1,Inputs!$B$34,0)*(1+inf)^D$1 -> 0 | F29: =IF(Inputs!$B$35>=F$1,Inputs!$B$34,0)*(1+inf)^E$1 -> 0 | G29: =IF(Inputs!$B$35>=G$1,Inputs!$B$34,0)*(1+inf)^F$1 -> 0 | H29: =IF(Inputs!$B$35>=H$1,Inputs!$B$34,0)*(1+inf)^G$1 -> 0 | I29: =IF(Inputs!$B$35>=I$1,Inputs!$B$34,0)*(1+inf)^H$1 -> 0 | J29: =IF(Inputs!$B$35>=J$1,Inputs!$B$34,0)*(1+inf)^I$1 -> 0 | ... AW29: =IF(Inputs!$B$35>=AW$1,Inputs!$B$34,0)*(1+inf)^AV$1 -> 0
A30: =TEXT(Inputs!B38,"") | C30: =IF(Inputs!$B$40>=C$1,Inputs!$B$39,0)*(1+inf)^B$1 -> 0 | D30: =IF(Inputs!$B$40>=D$1,Inputs!$B$39,0)*(1+inf)^C$1 -> 0 | E30: =IF(Inputs!$B$40>=E$1,Inputs!$B$39,0)*(1+inf)^D$1 -> 0 | F30: =IF(Inputs!$B$40>=F$1,Inputs!$B$39,0)*(1+inf)^E$1 -> 0 | G30: =IF(Inputs!$B$40>=G$1,Inputs!$B$39,0)*(1+inf)^F$1 -> 0 | H30: =IF(Inputs!$B$40>=H$1,Inputs!$B$39,0)*(1+inf)^G$1 -> 0 | I30: =IF(Inputs!$B$40>=I$1,Inputs!$B$39,0)*(1+inf)^H$1 -> 0 | J30: =IF(Inputs!$B$40>=J$1,Inputs!$B$39,0)*(1+inf)^I$1 -> 0 | ... AW30: =IF(Inputs!$B$40>=AW$1,Inputs!$B$39,0)*(1+inf)^AV$1 -> 0
A31: =TEXT(Inputs!B43,"") | C31: =IF(Inputs!$B$45>=C$1,Inputs!$B$44,0)*(1+inf)^B$1 -> 0 | D31: =IF(Inputs!$B$45>=D$1,Inputs!$B$44,0)*(1+inf)^C$1 -> 0 | E31: =IF(Inputs!$B$45>=E$1,Inputs!$B$44,0)*(1+inf)^D$1 -> 0 | F31: =IF(Inputs!$B$45>=F$1,Inputs!$B$44,0)*(1+inf)^E$1 -> 0 | G31: =IF(Inputs!$B$45>=G$1,Inputs!$B$44,0)*(1+inf)^F$1 -> 0 | H31: =IF(Inputs!$B$45>=H$1,Inputs!$B$44,0)*(1+inf)^G$1 -> 0 | I31: =IF(Inputs!$B$45>=I$1,Inputs!$B$44,0)*(1+inf)^H$1 -> 0 | J31: =IF(Inputs!$B$45>=J$1,Inputs!$B$44,0)*(1+inf)^I$1 -> 0 | ... AW31: =IF(Inputs!$B$45>=AW$1,Inputs!$B$44,0)*(1+inf)^AV$1 -> 0
A32: Housing rent | C32: =Inputs!$B$23*(1+inf)^B$1 -> 0 | D32: =Inputs!$B$23*(1+inf)^C$1 -> 0 | E32: =Inputs!$B$23*(1+inf)^D$1 -> 0 | F32: =Inputs!$B$23*(1+inf)^E$1 -> 0 | G32: =Inputs!$B$23*(1+inf)^F$1 -> 0 | H32: =Inputs!$B$23*(1+inf)^G$1 -> 0 | I32: =Inputs!$B$23*(1+inf)^H$1 -> 0 | J32: =Inputs!$B$23*(1+inf)^I$1 -> 0 | ... AW32: =Inputs!$B$23*(1+inf)^AV$1 -> 0
A33: Other property costs
A34: =TEXT(Inputs!$B$50,"") -> Sliema | C34: =Inputs!$B52*(1+inf)^B$1 -> 500 | D34: =Inputs!$B52*(1+inf)^C$1 -> 512.5 | E34: =Inputs!$B52*(1+inf)^D$1 -> 525.3125 | F34: =Inputs!$B52*(1+inf)^E$1 -> 538.44531 | G34: =Inputs!$B52*(1+inf)^F$1 -> 551.90645 | H34: =Inputs!$B52*(1+inf)^G$1 -> 565.70411 | I34: =Inputs!$B52*(1+inf)^H$1 -> 579.84671 | J34: =Inputs!$B52*(1+inf)^I$1 -> 594.34288 | ... AW34: =Inputs!$B52*(1+inf)^AV$1 -> 1556.9254
A35: =TEXT(Inputs!$B$55,"") | C35: =Inputs!$B57*(1+inf)^B$1 -> 0 | D35: =Inputs!$B57*(1+inf)^C$1 -> 0 | E35: =Inputs!$B57*(1+inf)^D$1 -> 0 | F35: =Inputs!$B57*(1+inf)^E$1 -> 0 | G35: =Inputs!$B57*(1+inf)^F$1 -> 0 | H35: =Inputs!$B57*(1+inf)^G$1 -> 0 | I35: =Inputs!$B57*(1+inf)^H$1 -> 0 | J35: =Inputs!$B57*(1+inf)^I$1 -> 0 | ... AW35: =Inputs!$B57*(1+inf)^AV$1 -> 0
A36: =TEXT(Inputs!$B$60,"") | C36: =Inputs!$B62*(1+inf)^B$1 -> 0 | D36: =Inputs!$B62*(1+inf)^C$1 -> 0 | E36: =Inputs!$B62*(1+inf)^D$1 -> 0 | F36: =Inputs!$B62*(1+inf)^E$1 -> 0 | G36: =Inputs!$B62*(1+inf)^F$1 -> 0 | H36: =Inputs!$B62*(1+inf)^G$1 -> 0 | I36: =Inputs!$B62*(1+inf)^H$1 -> 0 | J36: =Inputs!$B62*(1+inf)^I$1 -> 0 | ... AW36: =Inputs!$B62*(1+inf)^AV$1 -> 0
A37: Living expenses
A38: Current baseline | C38: =Inputs!$B$25*(1+inf)^B$1 -> 50000 | D38: =Inputs!$B$25*(1+inf)^C$1 -> 51250 | E38: =Inputs!$B$25*(1+inf)^D$1 -> 52531.25 | F38: =Inputs!$B$25*(1+inf)^E$1 -> 53844.531 | G38: =Inputs!$B$25*(1+inf)^F$1 -> 55190.645 | H38: =Inputs!$B$25*(1+inf)^G$1 -> 56570.411 | I38: =Inputs!$B$25*(1+inf)^H$1 -> 57984.671 | J38: =Inputs!$B$25*(1+inf)^I$1 -> 59434.288 | ... AW38: =Inputs!$B$25*(1+inf)^AV$1 -> 155692.54
A39: ="Adjustment "&Inputs!A137 -> Adjustment from now to 65 | C39: =IF(C$3<=65,Inputs!$B$137*C$38,0) -> 0 | D39: =IF(D$3<=65,Inputs!$B$137*D$38,0) -> 0 | E39: =IF(E$3<=65,Inputs!$B$137*E$38,0) -> 0 | F39: =IF(F$3<=65,Inputs!$B$137*F$38,0) -> 0 | G39: =IF(G$3<=65,Inputs!$B$137*G$38,0) -> 0 | H39: =IF(H$3<=65,Inputs!$B$137*H$38,0) -> 0 | I39: =IF(I$3<=65,Inputs!$B$137*I$38,0) -> 0 | J39: =IF(J$3<=65,Inputs!$B$137*J$38,0) -> 0 | ... AW39: =IF(AW$3<=65,Inputs!$B$137*AW$38,0) -> 0
A40: ="Adjustment "&Inputs!A138 -> Adjustment from 66-75 | C40: =IF(AND(C$3>65,C$3<=75),Inputs!$B$138*C38,0) -> 0 | D40: =IF(AND(D$3>65,D$3<=75),Inputs!$B$138*D38,0) -> 0 | E40: =IF(AND(E$3>65,E$3<=75),Inputs!$B$138*E38,0) -> 0 | F40: =IF(AND(F$3>65,F$3<=75),Inputs!$B$138*F38,0) -> 0 | G40: =IF(AND(G$3>65,G$3<=75),Inputs!$B$138*G38,0) -> 0 | H40: =IF(AND(H$3>65,H$3<=75),Inputs!$B$138*H38,0) -> 0 | I40: =IF(AND(I$3>65,I$3<=75),Inputs!$B$138*I38,0) -> 0 | J40: =IF(AND(J$3>65,J$3<=75),Inputs!$B$138*J38,0) -> 0 | ... AW40: =IF(AND(AW$3>65,AW$3<=75),Inputs!$B$138*AW38,0) -> 0
A41: ="Adjustment "&Inputs!A139 -> Adjustment from age 76 | C41: =IF(C$3>75,Inputs!$B$139*C$38,0) -> 0 | D41: =IF(D$3>75,Inputs!$B$139*D$38,0) -> 0 | E41: =IF(E$3>75,Inputs!$B$139*E$38,0) -> 0 | F41: =IF(F$3>75,Inputs!$B$139*F$38,0) -> 0 | G41: =IF(G$3>75,Inputs!$B$139*G$38,0) -> 0 | H41: =IF(H$3>75,Inputs!$B$139*H$38,0) -> 0 | I41: =IF(I$3>75,Inputs!$B$139*I$38,0) -> 0 | J41: =IF(J$3>75,Inputs!$B$139*J$38,0) -> 0 | ... AW41: =IF(AW$3>75,Inputs!$B$139*AW$38,0) -> -31138.509
A42: Major one-off expense events
A43: =TEXT(Inputs!$B$117,"") | C43: =IF(C$2=Inputs!$B119,Inputs!$B118,0)*(1+inf)^B$1 -> 0 | D43: =IF(D$2=Inputs!$B119,Inputs!$B118,0)*(1+inf)^C$1 -> 0 | E43: =IF(E$2=Inputs!$B119,Inputs!$B118,0)*(1+inf)^D$1 -> 0 | F43: =IF(F$2=Inputs!$B119,Inputs!$B118,0)*(1+inf)^E$1 -> 0 | G43: =IF(G$2=Inputs!$B119,Inputs!$B118,0)*(1+inf)^F$1 -> 0 | H43: =IF(H$2=Inputs!$B119,Inputs!$B118,0)*(1+inf)^G$1 -> 0 | I43: =IF(I$2=Inputs!$B119,Inputs!$B118,0)*(1+inf)^H$1 -> 0 | J43: =IF(J$2=Inputs!$B119,Inputs!$B118,0)*(1+inf)^I$1 -> 0 | ... AW43: =IF(AW$2=Inputs!$B119,Inputs!$B118,0)*(1+inf)^AV$1 -> 0
A44: =TEXT(Inputs!$B$122,"") | C44: =IF(C$2=Inputs!$B124,Inputs!$B123,0)*(1+inf)^B$1 -> 0 | D44: =IF(D$2=Inputs!$B124,Inputs!$B123,0)*(1+inf)^C$1 -> 0 | E44: =IF(E$2=Inputs!$B124,Inputs!$B123,0)*(1+inf)^D$1 -> 0 | F44: =IF(F$2=Inputs!$B124,Inputs!$B123,0)*(1+inf)^E$1 -> 0 | G44: =IF(G$2=Inputs!$B124,Inputs!$B123,0)*(1+inf)^F$1 -> 0 | H44: =IF(H$2=Inputs!$B124,Inputs!$B123,0)*(1+inf)^G$1 -> 0 | I44: =IF(I$2=Inputs!$B124,Inputs!$B123,0)*(1+inf)^H$1 -> 0 | J44: =IF(J$2=Inputs!$B124,Inputs!$B123,0)*(1+inf)^I$1 -> 0 | ... AW44: =IF(AW$2=Inputs!$B124,Inputs!$B123,0)*(1+inf)^AV$1 -> 0
A45: =TEXT(Inputs!$B$127,"") | C45: =IF(C$2=Inputs!$B129,Inputs!$B128,0)*(1+inf)^B$1 -> 0 | D45: =IF(D$2=Inputs!$B129,Inputs!$B128,0)*(1+inf)^C$1 -> 0 | E45: =IF(E$2=Inputs!$B129,Inputs!$B128,0)*(1+inf)^D$1 -> 0 | F45: =IF(F$2=Inputs!$B129,Inputs!$B128,0)*(1+inf)^E$1 -> 0 | G45: =IF(G$2=Inputs!$B129,Inputs!$B128,0)*(1+inf)^F$1 -> 0 | H45: =IF(H$2=Inputs!$B129,Inputs!$B128,0)*(1+inf)^G$1 -> 0 | I45: =IF(I$2=Inputs!$B129,Inputs!$B128,0)*(1+inf)^H$1 -> 0 | J45: =IF(J$2=Inputs!$B129,Inputs!$B128,0)*(1+inf)^I$1 -> 0 | ... AW45: =IF(AW$2=Inputs!$B129,Inputs!$B128,0)*(1+inf)^AV$1 -> 0
C46: =SUM(C20:C45) -> 60100 | D46: =SUM(D20:D45) -> 61362.5 | E46: =SUM(E20:E45) -> 62656.562 | F46: =SUM(F20:F45) -> 63982.977 | G46: =SUM(G20:G45) -> 65342.551 | H46: =SUM(H20:H45) -> 66736.115 | I46: =SUM(I20:I45) -> 68164.518 | J46: =SUM(J20:J45) -> 69628.631 | ... AW46: =SUM(AW20:AW45) -> 126110.96
A48: Net Cash Flow | C48: =C19-C46 -> 4898.75 | D48: =D19-D46 -> 5565.4375 | E48: =E19-E46 -> 6271.5102 | F48: =F19-F46 -> 7018.7939 | G48: =G19-G46 -> 7809.1896 | H48: =H19-H46 -> 8644.6759 | I48: =I19-I46 -> 9527.3119 | J48: =J19-J46 -> 10459.241 | ... AW48: =AW19-AW46 -> -70061.644
A49: Cash b/fwd | C49: =Inputs!B8 -> 200000 | D49: =C50 -> 204898.75 | E49: =D50 -> 210464.19 | F49: =E50 -> 216735.7 | G49: =F50 -> 223754.49 | H49: =G50 -> 231563.68 | I49: =H50 -> 240208.36 | J49: =I50 -> 249735.67 | K49: =J50 -> 260194.91 | ... AW49: =AV50 -> -1062302.9
A50: Cash c/fwd | C50: =SUM(C48:C49) -> 204898.75 | D50: =SUM(D48:D49) -> 210464.19 | E50: =SUM(E48:E49) -> 216735.7 | F50: =SUM(F48:F49) -> 223754.49 | G50: =SUM(G48:G49) -> 231563.68 | H50: =SUM(H48:H49) -> 240208.36 | I50: =SUM(I48:I49) -> 249735.67 | J50: =SUM(J48:J49) -> 260194.91 | ... AW50: =SUM(AW48:AW49) -> -1132364.6
A52: Net Worth before liquidations
A53: Cash | C53: =C50 -> 204898.75 | D53: =D50 -> 210464.19 | E53: =E50 -> 216735.7 | F53: =F50 -> 223754.49 | G53: =G50 -> 231563.68 | H53: =H50 -> 240208.36 | I53: =I50 -> 249735.67 | J53: =J50 -> 260194.91 | ... AW53: =AW50 -> -1132364.6
A54: Home | C54: =Inputs!B12*(1+princ) -> 515000 | D54: =C54*(1+princ) -> 530450 | E54: =D54*(1+princ) -> 546363.5 | F54: =E54*(1+princ) -> 562754.41 | G54: =F54*(1+princ) -> 579637.04 | H54: =G54*(1+princ) -> 597026.15 | I54: =H54*(1+princ) -> 614936.93 | J54: =I54*(1+princ) -> 633385.04 | K54: =J54*(1+princ) -> 652386.59 | ... AW54: =AV54*(1+princ) -> 2005947.5
A55: Other property
A56: =TEXT(Inputs!$B$50,"") -> Sliema | C56: =Inputs!B51*(1+princ) -> 309000 | D56: =C56*(1+princ) -> 318270 | E56: =D56*(1+princ) -> 327818.1 | F56: =E56*(1+princ) -> 337652.64 | G56: =F56*(1+princ) -> 347782.22 | H56: =G56*(1+princ) -> 358215.69 | I56: =H56*(1+princ) -> 368962.16 | J56: =I56*(1+princ) -> 380031.02 | K56: =J56*(1+princ) -> 391431.96 | ... AW56: =AV56*(1+princ) -> 1203568.5
A57: =TEXT(Inputs!$B$55,"") | C57: =Inputs!B56*(1+princ) -> 0 | D57: =C57*(1+princ) -> 0 | E57: =D57*(1+princ) -> 0 | F57: =E57*(1+princ) -> 0 | G57: =F57*(1+princ) -> 0 | H57: =G57*(1+princ) -> 0 | I57: =H57*(1+princ) -> 0 | J57: =I57*(1+princ) -> 0 | K57: =J57*(1+princ) -> 0 | ... AW57: =AV57*(1+princ) -> 0
A58: =TEXT(Inputs!$B$60,"") | C58: =Inputs!B61*(1+princ) -> 0 | D58: =C58*(1+princ) -> 0 | E58: =D58*(1+princ) -> 0 | F58: =E58*(1+princ) -> 0 | G58: =F58*(1+princ) -> 0 | H58: =G58*(1+princ) -> 0 | I58: =H58*(1+princ) -> 0 | J58: =I58*(1+princ) -> 0 | K58: =J58*(1+princ) -> 0 | ... AW58: =AV58*(1+princ) -> 0
A59: Stock market equity investments | C59: =Inputs!B10*(1+stinc) -> 54000 | D59: =C59*(1+stinc) -> 58320 | E59: =D59*(1+stinc) -> 62985.6 | F59: =E59*(1+stinc) -> 68024.448 | G59: =F59*(1+stinc) -> 73466.404 | H59: =G59*(1+stinc) -> 79343.716 | I59: =H59*(1+stinc) -> 85691.213 | J59: =I59*(1+stinc) -> 92546.511 | K59: =J59*(1+stinc) -> 99950.231 | ... AW59: =AV59*(1+stinc) -> 1861600.6
A60: Home loan | C60: =-MAX(FV(Inputs!$B16/12,C$1*12,Inputs!$B17,-Inputs!$B15),0) -> -113916.81 | D60: =-MAX(FV(Inputs!$B16/12,D$1*12,Inputs!$B17,-Inputs!$B15),0) -> -107648.59 | E60: =-MAX(FV(Inputs!$B16/12,E$1*12,Inputs!$B17,-Inputs!$B15),0) -> -101189.72 | F60: =-MAX(FV(Inputs!$B16/12,F$1*12,Inputs!$B17,-Inputs!$B15),0) -> -94534.396 | G60: =-MAX(FV(Inputs!$B16/12,G$1*12,Inputs!$B17,-Inputs!$B15),0) -> -87676.644 | H60: =-MAX(FV(Inputs!$B16/12,H$1*12,Inputs!$B17,-Inputs!$B15),0) -> -80610.306 | I60: =-MAX(FV(Inputs!$B16/12,I$1*12,Inputs!$B17,-Inputs!$B15),0) -> -73329.04 | J60: =-MAX(FV(Inputs!$B16/12,J$1*12,Inputs!$B17,-Inputs!$B15),0) -> -65826.307 | ... AW60: =-MAX(FV(Inputs!$B16/12,AW$1*12,Inputs!$B17,-Inputs!$B15),0) -> 0
A61: Other property loans
A62: =TEXT(Inputs!$B$50,"") -> Sliema | C62: =-MAX(FV(Inputs!$B79/12,C$1*12,Inputs!$B80,-Inputs!$B78),0) -> 0 | D62: =-MAX(FV(Inputs!$B79/12,D$1*12,Inputs!$B80,-Inputs!$B78),0) -> 0 | E62: =-MAX(FV(Inputs!$B79/12,E$1*12,Inputs!$B80,-Inputs!$B78),0) -> 0 | F62: =-MAX(FV(Inputs!$B79/12,F$1*12,Inputs!$B80,-Inputs!$B78),0) -> 0 | G62: =-MAX(FV(Inputs!$B79/12,G$1*12,Inputs!$B80,-Inputs!$B78),0) -> 0 | H62: =-MAX(FV(Inputs!$B79/12,H$1*12,Inputs!$B80,-Inputs!$B78),0) -> 0 | I62: =-MAX(FV(Inputs!$B79/12,I$1*12,Inputs!$B80,-Inputs!$B78),0) -> 0 | J62: =-MAX(FV(Inputs!$B79/12,J$1*12,Inputs!$B80,-Inputs!$B78),0) -> 0 | ... AW62: =-MAX(FV(Inputs!$B79/12,AW$1*12,Inputs!$B80,-Inputs!$B78),0) -> 0
A63: =TEXT(Inputs!$B$55,"") | C63: =-MAX(FV(Inputs!$B84/12,C$1*12,Inputs!$B85,-Inputs!$B83),0) -> 0 | D63: =-MAX(FV(Inputs!$B84/12,D$1*12,Inputs!$B85,-Inputs!$B83),0) -> 0 | E63: =-MAX(FV(Inputs!$B84/12,E$1*12,Inputs!$B85,-Inputs!$B83),0) -> 0 | F63: =-MAX(FV(Inputs!$B84/12,F$1*12,Inputs!$B85,-Inputs!$B83),0) -> 0 | G63: =-MAX(FV(Inputs!$B84/12,G$1*12,Inputs!$B85,-Inputs!$B83),0) -> 0 | H63: =-MAX(FV(Inputs!$B84/12,H$1*12,Inputs!$B85,-Inputs!$B83),0) -> 0 | I63: =-MAX(FV(Inputs!$B84/12,I$1*12,Inputs!$B85,-Inputs!$B83),0) -> 0 | J63: =-MAX(FV(Inputs!$B84/12,J$1*12,Inputs!$B85,-Inputs!$B83),0) -> 0 | ... AW63: =-MAX(FV(Inputs!$B84/12,AW$1*12,Inputs!$B85,-Inputs!$B83),0) -> 0
A64: =TEXT(Inputs!$B$60,"") | C64: =-MAX(FV(Inputs!$B89/12,C$1*12,Inputs!$B90,-Inputs!$B88),0) -> 0 | D64: =-MAX(FV(Inputs!$B89/12,D$1*12,Inputs!$B90,-Inputs!$B88),0) -> 0 | E64: =-MAX(FV(Inputs!$B89/12,E$1*12,Inputs!$B90,-Inputs!$B88),0) -> 0 | F64: =-MAX(FV(Inputs!$B89/12,F$1*12,Inputs!$B90,-Inputs!$B88),0) -> 0 | G64: =-MAX(FV(Inputs!$B89/12,G$1*12,Inputs!$B90,-Inputs!$B88),0) -> 0 | H64: =-MAX(FV(Inputs!$B89/12,H$1*12,Inputs!$B90,-Inputs!$B88),0) -> 0 | I64: =-MAX(FV(Inputs!$B89/12,I$1*12,Inputs!$B90,-Inputs!$B88),0) -> 0 | J64: =-MAX(FV(Inputs!$B89/12,J$1*12,Inputs!$B90,-Inputs!$B88),0) -> 0 | ... AW64: =-MAX(FV(Inputs!$B89/12,AW$1*12,Inputs!$B90,-Inputs!$B88),0) -> 0
A65: Other loan | C65: =-MAX(FV(Inputs!$B94/12,C$1*12,Inputs!$B95,-Inputs!$B93),0) -> 0 | D65: =-MAX(FV(Inputs!$B94/12,D$1*12,Inputs!$B95,-Inputs!$B93),0) -> 0 | E65: =-MAX(FV(Inputs!$B94/12,E$1*12,Inputs!$B95,-Inputs!$B93),0) -> 0 | F65: =-MAX(FV(Inputs!$B94/12,F$1*12,Inputs!$B95,-Inputs!$B93),0) -> 0 | G65: =-MAX(FV(Inputs!$B94/12,G$1*12,Inputs!$B95,-Inputs!$B93),0) -> 0 | H65: =-MAX(FV(Inputs!$B94/12,H$1*12,Inputs!$B95,-Inputs!$B93),0) -> 0 | I65: =-MAX(FV(Inputs!$B94/12,I$1*12,Inputs!$B95,-Inputs!$B93),0) -> 0 | J65: =-MAX(FV(Inputs!$B94/12,J$1*12,Inputs!$B95,-Inputs!$B93),0) -> 0 | ... AW65: =-MAX(FV(Inputs!$B94/12,AW$1*12,Inputs!$B95,-Inputs!$B93),0) -> 0
C66: =SUM(C52:C65) -> 968981.94 | D66: =SUM(D52:D65) -> 1009855.6 | E66: =SUM(E52:E65) -> 1052713.2 | F66: =SUM(F52:F65) -> 1097651.6 | G66: =SUM(G52:G65) -> 1144772.7 | H66: =SUM(H52:H65) -> 1194183.6 | I66: =SUM(I52:I65) -> 1245996.9 | J66: =SUM(J52:J65) -> 1300331.2 | ... AW66: =SUM(AW52:AW65) -> 3938752
A68: Cash available (after buffer) | C68: =C53-buffer -> 184898.75 | D68: =D53-buffer -> 190464.19 | E68: =E53-buffer -> 196735.7 | F68: =F53-buffer -> 203754.49 | G68: =G53-buffer -> 211563.68 | H68: =H53-buffer -> 220208.36 | I68: =I53-buffer -> 229735.67 | J68: =J53-buffer -> 240194.91 | ... AW68: =AW53-buffer -> -1152364.6
A69: Liquidation required | C69: =IF(C68<0,-C68,0) -> 0 | D69: =IF(D68+SUM($C69:C69)<0,-(D68+SUM($C69:C69)),0) -> 0 | E69: =IF(E68+SUM($C69:D69)<0,-(E68+SUM($C69:D69)),0) -> 0 | F69: =IF(F68+SUM($C69:E69)<0,-(F68+SUM($C69:E69)),0) -> 0 | G69: =IF(G68+SUM($C69:F69)<0,-(G68+SUM($C69:F69)),0) -> 0 | H69: =IF(H68+SUM($C69:G69)<0,-(H68+SUM($C69:G69)),0) -> 0 | I69: =IF(I68+SUM($C69:H69)<0,-(I68+SUM($C69:H69)),0) -> 0 | J69: =IF(J68+SUM($C69:I69)<0,-(J68+SUM($C69:I69)),0) -> 0 | K69: =IF(K68+SUM($C69:J69)<0,-(K68+SUM($C69:J69)),0) -> 0 | ... AW69: =IF(AW68+SUM($C69:AV69)<0,-(AW68+SUM($C69:AV69)),0) -> 70061.644
A71: Liquidations
A73: Stock market equity
A74: b/fwd | C74: =C59 -> 54000 | D74: =C77 -> 54000 | E74: =D77 -> 58320 | F74: =E77 -> 62985.6 | G74: =F77 -> 68024.448 | H74: =G77 -> 73466.404 | I74: =H77 -> 79343.716 | J74: =I77 -> 85691.213 | K74: =J77 -> 92546.511 | ... AW74: =AV77 -> 0
A75: Disposals | C75: =-MIN( IF(C74>C69/ (1 - Inputs!$B$161), C69/ (1 - Inputs!$B$161), C74), C74/ (1 - Inputs!$B$161) ) -> 0 | D75: =-MIN( IF(D74>D69/ (1 - Inputs!$B$161), D69/ (1 - Inputs!$B$161), D74), D74/ (1 - Inputs!$B$161) ) -> 0 | E75: =-MIN( IF(E74>E69/ (1 - Inputs!$B$161), E69/ (1 - Inputs!$B$161), E74), E74/ (1 - Inputs!$B$161) ) -> 0 | F75: =-MIN( IF(F74>F69/ (1 - Inputs!$B$161), F69/ (1 - Inputs!$B$161), F74), F74/ (1 - Inputs!$B$161) ) -> 0 | G75: =-MIN( IF(G74>G69/ (1 - Inputs!$B$161), G69/ (1 - Inputs!$B$161), G74), G74/ (1 - Inputs!$B$161) ) -> 0 | H75: =-MIN( IF(H74>H69/ (1 - Inputs!$B$161), H69/ (1 - Inputs!$B$161), H74), H74/ (1 - Inputs!$B$161) ) -> 0 | I75: =-MIN( IF(I74>I69/ (1 - Inputs!$B$161), I69/ (1 - Inputs!$B$161), I74), I74/ (1 - Inputs!$B$161) ) -> 0 | J75: =-MIN( IF(J74>J69/ (1 - Inputs!$B$161), J69/ (1 - Inputs!$B$161), J74), J74/ (1 - Inputs!$B$161) ) -> 0 | ... AW75: =-MIN( IF(AW74>AW69/ (1 - Inputs!$B$161), AW69/ (1 - Inputs!$B$161), AW74), AW74/ (1 - Inputs!$B$161) ) -> 0
A76: Growth | C76: 0 | D76: =SUM(D74:D75)*stinc -> 4320 | E76: =SUM(E74:E75)*stinc -> 4665.6 | F76: =SUM(F74:F75)*stinc -> 5038.848 | G76: =SUM(G74:G75)*stinc -> 5441.9558 | H76: =SUM(H74:H75)*stinc -> 5877.3123 | I76: =SUM(I74:I75)*stinc -> 6347.4973 | J76: =SUM(J74:J75)*stinc -> 6855.2971 | K76: =SUM(K74:K75)*stinc -> 7403.7208 | ... AW76: =SUM(AW74:AW75)*stinc -> 0
A77: c/fwd | C77: =SUM(C74:C76) -> 54000 | D77: =SUM(D74:D76) -> 58320 | E77: =SUM(E74:E76) -> 62985.6 | F77: =SUM(F74:F76) -> 68024.448 | G77: =SUM(G74:G76) -> 73466.404 | H77: =SUM(H74:H76) -> 79343.716 | I77: =SUM(I74:I76) -> 85691.213 | J77: =SUM(J74:J76) -> 92546.511 | ... AW77: =SUM(AW74:AW76) -> 0
A78: Disposal costs | C78: =C75*Inputs!$B$161 -> 0 | D78: =D75*Inputs!$B$161 -> 0 | E78: =E75*Inputs!$B$161 -> 0 | F78: =F75*Inputs!$B$161 -> 0 | G78: =G75*Inputs!$B$161 -> 0 | H78: =H75*Inputs!$B$161 -> 0 | I78: =I75*Inputs!$B$161 -> 0 | J78: =J75*Inputs!$B$161 -> 0 | ... AW78: =AW75*Inputs!$B$161 -> 0
A79: Net proceeds | C79: =-C75+C78 -> 0 | D79: =-D75+D78 -> 0 | E79: =-E75+E78 -> 0 | F79: =-F75+F78 -> 0 | G79: =-G75+G78 -> 0 | H79: =-H75+H78 -> 0 | I79: =-I75+I78 -> 0 | J79: =-J75+J78 -> 0 | ... AW79: =-AW75+AW78 -> 0
A81: Cash available (after buffer) | C81: =C68+SUM($C79:C79) -> 184898.75 | D81: =D68+SUM($C79:D79) -> 190464.19 | E81: =E68+SUM($C79:E79) -> 196735.7 | F81: =F68+SUM($C79:F79) -> 203754.49 | G81: =G68+SUM($C79:G79) -> 211563.68 | H81: =H68+SUM($C79:H79) -> 220208.36 | I81: =I68+SUM($C79:I79) -> 229735.67 | J81: =J68+SUM($C79:J79) -> 240194.91 | ... AW81: =AW68+SUM($C79:AW79) -> -639688.21
A82: Liquidation required | C82: =IF(C81<0,C81,0) -> 0 | D82: =IF(D81+SUM($C82:C82)<0,-(D81+SUM($C82:C82)),0) -> 0 | E82: =IF(E81+SUM($C82:D82)<0,-(E81+SUM($C82:D82)),0) -> 0 | F82: =IF(F81+SUM($C82:E82)<0,-(F81+SUM($C82:E82)),0) -> 0 | G82: =IF(G81+SUM($C82:F82)<0,-(G81+SUM($C82:F82)),0) -> 0 | H82: =IF(H81+SUM($C82:G82)<0,-(H81+SUM($C82:G82)),0) -> 0 | I82: =IF(I81+SUM($C82:H82)<0,-(I81+SUM($C82:H82)),0) -> 0 | J82: =IF(J81+SUM($C82:I82)<0,-(J81+SUM($C82:I82)),0) -> 0 | K82: =IF(K81+SUM($C82:J82)<0,-(K81+SUM($C82:J82)),0) -> 0 | ... AW82: =IF(AW81+SUM($C82:AV82)<0,-(AW81+SUM($C82:AV82)),0) -> 70061.644
A84: =IF(Inputs!$B$165=6,IFERROR(_xlfn.XLOOKUP($B84,Inputs!$B$166:$B$168,Inputs!$A$166:$A$168,,0,1),""),IFERROR(_xlfn.XLOOKUP($B84,Inputs!$C$166:$C$168,Inputs!$A$166:$A$168,,0,1),"")) -> Sliema | B84: 1
A85: b/fwd | C85: =IFERROR(VLOOKUP($A84,$A$52:$H$66,C$1+2,FALSE),0) -> 309000 | D85: =C88 -> 309000 | E85: =D88 -> 318270 | F85: =E88 -> 327818.1 | G85: =F88 -> 337652.64 | H85: =G88 -> 347782.22 | I85: =H88 -> 358215.69 | J85: =I88 -> 368962.16 | K85: =J88 -> 380031.02 | ... AW85: =AV88 -> 0
A86: Disposals | C86: =-IF(SUM(C82:D82)>0,C85,0) -> 0 | D86: =-IF(E82>0,D85,0) -> 0 | E86: =-IF(F82>0,E85,0) -> 0 | F86: =-IF(G82>0,F85,0) -> 0 | G86: =-IF(H82>0,G85,0) -> 0 | H86: =-IF(I82>0,H85,0) -> 0 | I86: =-IF(J82>0,I85,0) -> 0 | J86: =-IF(K82>0,J85,0) -> 0 | K86: =-IF(L82>0,K85,0) -> 0 | ... AW86: =-IF(AX82>0,AW85,0) -> 0
A87: Growth | C87: 0 | D87: =SUM(D85:D86)*princ -> 9270 | E87: =SUM(E85:E86)*princ -> 9548.1 | F87: =SUM(F85:F86)*princ -> 9834.543 | G87: =SUM(G85:G86)*princ -> 10129.579 | H87: =SUM(H85:H86)*princ -> 10433.467 | I87: =SUM(I85:I86)*princ -> 10746.471 | J87: =SUM(J85:J86)*princ -> 11068.865 | K87: =SUM(K85:K86)*princ -> 11400.931 | ... AW87: =SUM(AW85:AW86)*princ -> 0
A88: c/fwd | C88: =SUM(C85:C87) -> 309000 | D88: =SUM(D85:D87) -> 318270 | E88: =SUM(E85:E87) -> 327818.1 | F88: =SUM(F85:F87) -> 337652.64 | G88: =SUM(G85:G87) -> 347782.22 | H88: =SUM(H85:H87) -> 358215.69 | I88: =SUM(I85:I87) -> 368962.16 | J88: =SUM(J85:J87) -> 380031.02 | ... AW88: =SUM(AW85:AW87) -> 0
A89: Disposal costs | C89: =C86*Inputs!$B$163 -> 0 | D89: =D86*Inputs!$B$163 -> 0 | E89: =E86*Inputs!$B$163 -> 0 | F89: =F86*Inputs!$B$163 -> 0 | G89: =G86*Inputs!$B$163 -> 0 | H89: =H86*Inputs!$B$163 -> 0 | I89: =I86*Inputs!$B$163 -> 0 | J89: =J86*Inputs!$B$163 -> 0 | ... AW89: =AW86*Inputs!$B$163 -> 0
A90: Rental income foregone | C90: =IFERROR(-IF(C85=0,VLOOKUP($A84,$7:$10,C$1+2,FALSE),0),0) -> 0 | D90: =IFERROR(-IF(D85=0,VLOOKUP($A84,$7:$10,D$1+2,FALSE),0),0) -> 0 | E90: =IFERROR(-IF(E85=0,VLOOKUP($A84,$7:$10,E$1+2,FALSE),0),0) -> 0 | F90: =IFERROR(-IF(F85=0,VLOOKUP($A84,$7:$10,F$1+2,FALSE),0),0) -> 0 | G90: =IFERROR(-IF(G85=0,VLOOKUP($A84,$7:$10,G$1+2,FALSE),0),0) -> 0 | H90: =IFERROR(-IF(H85=0,VLOOKUP($A84,$7:$10,H$1+2,FALSE),0),0) -> 0 | I90: =IFERROR(-IF(I85=0,VLOOKUP($A84,$7:$10,I$1+2,FALSE),0),0) -> 0 | J90: =IFERROR(-IF(J85=0,VLOOKUP($A84,$7:$10,J$1+2,FALSE),0),0) -> 0 | ... AW90: =IFERROR(-IF(AW85=0,VLOOKUP($A84,$7:$10,AW$1+2,FALSE),0),0) -> 0
A91: Annual cost saved | C91: =IFERROR(IF(C85=0,VLOOKUP($A84,$33:$36,C$1+2,FALSE),0),0) -> 0 | D91: =IFERROR(IF(D85=0,VLOOKUP($A84,$33:$36,D$1+2,FALSE),0),0) -> 0 | E91: =IFERROR(IF(E85=0,VLOOKUP($A84,$33:$36,E$1+2,FALSE),0),0) -> 0 | F91: =IFERROR(IF(F85=0,VLOOKUP($A84,$33:$36,F$1+2,FALSE),0),0) -> 0 | G91: =IFERROR(IF(G85=0,VLOOKUP($A84,$33:$36,G$1+2,FALSE),0),0) -> 0 | H91: =IFERROR(IF(H85=0,VLOOKUP($A84,$33:$36,H$1+2,FALSE),0),0) -> 0 | I91: =IFERROR(IF(I85=0,VLOOKUP($A84,$33:$36,I$1+2,FALSE),0),0) -> 0 | J91: =IFERROR(IF(J85=0,VLOOKUP($A84,$33:$36,J$1+2,FALSE),0),0) -> 0 | ... AW91: =IFERROR(IF(AW85=0,VLOOKUP($A84,$33:$36,AW$1+2,FALSE),0),0) -> 1556.9254
A92: Loan repayment | B92: =A84 -> Sliema | C92: =IF(AND(C85>0,C88=0),VLOOKUP($A84,$61:$64,C$1+2,FALSE),0) -> 0 | D92: =IF(AND(D85>0,D88=0),VLOOKUP($A84,$61:$64,D$1+2,FALSE),0) -> 0 | E92: =IF(AND(E85>0,E88=0),VLOOKUP($A84,$61:$64,E$1+2,FALSE),0) -> 0 | F92: =IF(AND(F85>0,F88=0),VLOOKUP($A84,$61:$64,F$1+2,FALSE),0) -> 0 | G92: =IF(AND(G85>0,G88=0),VLOOKUP($A84,$61:$64,G$1+2,FALSE),0) -> 0 | H92: =IF(AND(H85>0,H88=0),VLOOKUP($A84,$61:$64,H$1+2,FALSE),0) -> 0 | I92: =IF(AND(I85>0,I88=0),VLOOKUP($A84,$61:$64,I$1+2,FALSE),0) -> 0 | J92: =IF(AND(J85>0,J88=0),VLOOKUP($A84,$61:$64,J$1+2,FALSE),0) -> 0 | ... AW92: =IF(AND(AW85>0,AW88=0),VLOOKUP($A84,$61:$64,AW$1+2,FALSE),0) -> 0
A93: Net proceeds | C93: =-C86+SUM(C89:C92) -> 0 | D93: =-D86+SUM(D89:D92) -> 0 | E93: =-E86+SUM(E89:E92) -> 0 | F93: =-F86+SUM(F89:F92) -> 0 | G93: =-G86+SUM(G89:G92) -> 0 | H93: =-H86+SUM(H89:H92) -> 0 | I93: =-I86+SUM(I89:I92) -> 0 | J93: =-J86+SUM(J89:J92) -> 0 | ... AW93: =-AW86+SUM(AW89:AW92) -> 1556.9254
A95: Cash available (after buffer) | C95: =C81+SUM($C93:C93) -> 184898.75 | D95: =D81+SUM($C93:D93) -> 190464.19 | E95: =E81+SUM($C93:E93) -> 196735.7 | F95: =F81+SUM($C93:F93) -> 203754.49 | G95: =G81+SUM($C93:G93) -> 211563.68 | H95: =H81+SUM($C93:H93) -> 220208.36 | I95: =I81+SUM($C93:I93) -> 229735.67 | J95: =J81+SUM($C93:J93) -> 240194.91 | ... AW95: =AW81+SUM($C93:AW93) -> 93029.947
A96: Extra cash | C96: =MAX(C95+buffer,0)-MAX(C$81+buffer,0) -> 0 | D96: =MAX(D95+buffer,0)-MAX(D$81+buffer,0) -> 0 | E96: =MAX(E95+buffer,0)-MAX(E$81+buffer,0) -> 0 | F96: =MAX(F95+buffer,0)-MAX(F$81+buffer,0) -> 0 | G96: =MAX(G95+buffer,0)-MAX(G$81+buffer,0) -> 0 | H96: =MAX(H95+buffer,0)-MAX(H$81+buffer,0) -> 0 | I96: =MAX(I95+buffer,0)-MAX(I$81+buffer,0) -> 0 | J96: =MAX(J95+buffer,0)-MAX(J$81+buffer,0) -> 0 | ... AW96: =MAX(AW95+buffer,0)-MAX(AW$81+buffer,0) -> 113029.95
A97: Extra interest | C97: =C96*Inputs!$B$149 -> 0 | D97: =D96*Inputs!$B$149 -> 0 | E97: =E96*Inputs!$B$149 -> 0 | F97: =F96*Inputs!$B$149 -> 0 | G97: =G96*Inputs!$B$149 -> 0 | H97: =H96*Inputs!$B$149 -> 0 | I97: =I96*Inputs!$B$149 -> 0 | J97: =J96*Inputs!$B$149 -> 0 | ... AW97: =AW96*Inputs!$B$149 -> 2825.7487
A98: Cash available (after extra interest) | C98: =C95+SUM($C97:C97) -> 184898.75 | D98: =D95+SUM($C97:D97) -> 190464.19 | E98: =E95+SUM($C97:E97) -> 196735.7 | F98: =F95+SUM($C97:F97) -> 203754.49 | G98: =G95+SUM($C97:G97) -> 211563.68 | H98: =H95+SUM($C97:H97) -> 220208.36 | I98: =I95+SUM($C97:I97) -> 229735.67 | J98: =J95+SUM($C97:J97) -> 240194.91 | ... AW98: =AW95+SUM($C97:AW97) -> 229457.67
A99: Liquidation required | C99: =IF(C98<0,C95,0) -> 0 | D99: =IF(D98+SUM($C99:C99)<0,-(D98+SUM($C99:C99)),0) -> 0 | E99: =IF(E98+SUM($C99:D99)<0,-(E98+SUM($C99:D99)),0) -> 0 | F99: =IF(F98+SUM($C99:E99)<0,-(F98+SUM($C99:E99)),0) -> 0 | G99: =IF(G98+SUM($C99:F99)<0,-(G98+SUM($C99:F99)),0) -> 0 | H99: =IF(H98+SUM($C99:G99)<0,-(H98+SUM($C99:G99)),0) -> 0 | I99: =IF(I98+SUM($C99:H99)<0,-(I98+SUM($C99:H99)),0) -> 0 | J99: =IF(J98+SUM($C99:I99)<0,-(J98+SUM($C99:I99)),0) -> 0 | K99: =IF(K98+SUM($C99:J99)<0,-(K98+SUM($C99:J99)),0) -> 0 | ... AW99: =IF(AW98+SUM($C99:AV99)<0,-(AW98+SUM($C99:AV99)),0) -> 0
A101: =IF(Inputs!$B$165=6,IFERROR(_xlfn.XLOOKUP($B101,Inputs!$B$166:$B$168,Inputs!$A$166:$A$168,,0,1),""),IFERROR(_xlfn.XLOOKUP($B101,Inputs!$C$166:$C$168,Inputs!$A$166:$A$168,,0,1),"")) | B101: 2
A102: b/fwd | C102: =IFERROR(VLOOKUP($A101,$A$52:$H$66,C$1+2,FALSE),0) -> 0 | D102: =C105 -> 0 | E102: =D105 -> 0 | F102: =E105 -> 0 | G102: =F105 -> 0 | H102: =G105 -> 0 | I102: =H105 -> 0 | J102: =I105 -> 0 | K102: =J105 -> 0 | ... AW102: =AV105 -> 0
A103: Disposals | C103: =-IF(SUM(C99:D99)>0,C102,0) -> 0 | D103: =-IF(E99>0,D102,0) -> 0 | E103: =-IF(F99>0,E102,0) -> 0 | F103: =-IF(G99>0,F102,0) -> 0 | G103: =-IF(H99>0,G102,0) -> 0 | H103: =-IF(I99>0,H102,0) -> 0 | I103: =-IF(J99>0,I102,0) -> 0 | J103: =-IF(K99>0,J102,0) -> 0 | K103: =-IF(L99>0,K102,0) -> 0 | ... AW103: =-IF(AX99>0,AW102,0) -> 0
A104: Growth | C104: 0 | D104: =SUM(D102:D103)*princ -> 0 | E104: =SUM(E102:E103)*princ -> 0 | F104: =SUM(F102:F103)*princ -> 0 | G104: =SUM(G102:G103)*princ -> 0 | H104: =SUM(H102:H103)*princ -> 0 | I104: =SUM(I102:I103)*princ -> 0 | J104: =SUM(J102:J103)*princ -> 0 | K104: =SUM(K102:K103)*princ -> 0 | ... AW104: =SUM(AW102:AW103)*princ -> 0
A105: c/fwd | C105: =SUM(C102:C104) -> 0 | D105: =SUM(D102:D104) -> 0 | E105: =SUM(E102:E104) -> 0 | F105: =SUM(F102:F104) -> 0 | G105: =SUM(G102:G104) -> 0 | H105: =SUM(H102:H104) -> 0 | I105: =SUM(I102:I104) -> 0 | J105: =SUM(J102:J104) -> 0 | ... AW105: =SUM(AW102:AW104) -> 0
A106: Disposal costs | C106: =C103*Inputs!$B$163 -> 0 | D106: =D103*Inputs!$B$163 -> 0 | E106: =E103*Inputs!$B$163 -> 0 | F106: =F103*Inputs!$B$163 -> 0 | G106: =G103*Inputs!$B$163 -> 0 | H106: =H103*Inputs!$B$163 -> 0 | I106: =I103*Inputs!$B$163 -> 0 | J106: =J103*Inputs!$B$163 -> 0 | ... AW106: =AW103*Inputs!$B$163 -> 0
A107: Rental income foregone | C107: =IFERROR(-IF(C102=0,VLOOKUP($A101,$7:$10,C$1+2,FALSE),0),0) -> 0 | D107: =IFERROR(-IF(D102=0,VLOOKUP($A101,$7:$10,D$1+2,FALSE),0),0) -> 0 | E107: =IFERROR(-IF(E102=0,VLOOKUP($A101,$7:$10,E$1+2,FALSE),0),0) -> 0 | F107: =IFERROR(-IF(F102=0,VLOOKUP($A101,$7:$10,F$1+2,FALSE),0),0) -> 0 | G107: =IFERROR(-IF(G102=0,VLOOKUP($A101,$7:$10,G$1+2,FALSE),0),0) -> 0 | H107: =IFERROR(-IF(H102=0,VLOOKUP($A101,$7:$10,H$1+2,FALSE),0),0) -> 0 | I107: =IFERROR(-IF(I102=0,VLOOKUP($A101,$7:$10,I$1+2,FALSE),0),0) -> 0 | J107: =IFERROR(-IF(J102=0,VLOOKUP($A101,$7:$10,J$1+2,FALSE),0),0) -> 0 | ... AW107: =IFERROR(-IF(AW102=0,VLOOKUP($A101,$7:$10,AW$1+2,FALSE),0),0) -> 0
A108: Annual cost saved | C108: =IFERROR(IF(C102=0,VLOOKUP($A101,$33:$36,C$1+2,FALSE),0),0) -> 0 | D108: =IFERROR(IF(D102=0,VLOOKUP($A101,$33:$36,D$1+2,FALSE),0),0) -> 0 | E108: =IFERROR(IF(E102=0,VLOOKUP($A101,$33:$36,E$1+2,FALSE),0),0) -> 0 | F108: =IFERROR(IF(F102=0,VLOOKUP($A101,$33:$36,F$1+2,FALSE),0),0) -> 0 | G108: =IFERROR(IF(G102=0,VLOOKUP($A101,$33:$36,G$1+2,FALSE),0),0) -> 0 | H108: =IFERROR(IF(H102=0,VLOOKUP($A101,$33:$36,H$1+2,FALSE),0),0) -> 0 | I108: =IFERROR(IF(I102=0,VLOOKUP($A101,$33:$36,I$1+2,FALSE),0),0) -> 0 | J108: =IFERROR(IF(J102=0,VLOOKUP($A101,$33:$36,J$1+2,FALSE),0),0) -> 0 | ... AW108: =IFERROR(IF(AW102=0,VLOOKUP($A101,$33:$36,AW$1+2,FALSE),0),0) -> 0
A109: Loan repayment | B109: =A101 | C109: =IF(AND(C102>0,C105=0),VLOOKUP($A101,$61:$64,C$1+2,FALSE),0) -> 0 | D109: =IF(AND(D102>0,D105=0),VLOOKUP($A101,$61:$64,D$1+2,FALSE),0) -> 0 | E109: =IF(AND(E102>0,E105=0),VLOOKUP($A101,$61:$64,E$1+2,FALSE),0) -> 0 | F109: =IF(AND(F102>0,F105=0),VLOOKUP($A101,$61:$64,F$1+2,FALSE),0) -> 0 | G109: =IF(AND(G102>0,G105=0),VLOOKUP($A101,$61:$64,G$1+2,FALSE),0) -> 0 | H109: =IF(AND(H102>0,H105=0),VLOOKUP($A101,$61:$64,H$1+2,FALSE),0) -> 0 | I109: =IF(AND(I102>0,I105=0),VLOOKUP($A101,$61:$64,I$1+2,FALSE),0) -> 0 | J109: =IF(AND(J102>0,J105=0),VLOOKUP($A101,$61:$64,J$1+2,FALSE),0) -> 0 | ... AW109: =IF(AND(AW102>0,AW105=0),VLOOKUP($A101,$61:$64,AW$1+2,FALSE),0) -> 0
...

Sheet RetEarly_Engine
B1: 0 | C1: 1 | D1: =C1+1 -> 2 | E1: =D1+1 -> 3 | F1: =E1+1 -> 4 | G1: =F1+1 -> 5 | H1: =G1+1 -> 6 | I1: =H1+1 -> 7 | J1: =I1+1 -> 8 | K1: =J1+1 -> 9 | ... AW1: =AV1+1 -> 47
B2: Year | C2: =YEAR(TODAY())+1 -> 2027 | D2: =C2+1 -> 2028 | E2: =D2+1 -> 2029 | F2: =E2+1 -> 2030 | G2: =F2+1 -> 2031 | H2: =G2+1 -> 2032 | I2: =H2+1 -> 2033 | J2: =I2+1 -> 2034 | K2: =J2+1 -> 2035 | ... AW2: =AV2+1 -> 2073
B3: 59 | C3: =Inputs!B4+1 -> 48 | D3: =C3+1 -> 49 | E3: =D3+1 -> 50 | F3: =E3+1 -> 51 | G3: =F3+1 -> 52 | H3: =G3+1 -> 53 | I3: =H3+1 -> 54 | J3: =I3+1 -> 55 | K3: =J3+1 -> 56 | ... AW3: =AV3+1 -> 94
A4: Inflows
A5: Net employment / self-employment income | C5: =IF(AND(Inputs!$B$19>C3,$B$3>C3),Inputs!$B$6*(1+sincr)^B1,0) -> 60000 | D5: =IF(AND(Inputs!$B$19>D3,$B$3>D3),Inputs!$B$6*(1+sincr)^C1,0) -> 61800 | E5: =IF(AND(Inputs!$B$19>E3,$B$3>E3),Inputs!$B$6*(1+sincr)^D1,0) -> 63654 | F5: =IF(AND(Inputs!$B$19>F3,$B$3>F3),Inputs!$B$6*(1+sincr)^E1,0) -> 65563.62 | G5: =IF(AND(Inputs!$B$19>G3,$B$3>G3),Inputs!$B$6*(1+sincr)^F1,0) -> 67530.529 | H5: =IF(AND(Inputs!$B$19>H3,$B$3>H3),Inputs!$B$6*(1+sincr)^G1,0) -> 69556.444 | I5: =IF(AND(Inputs!$B$19>I3,$B$3>I3),Inputs!$B$6*(1+sincr)^H1,0) -> 71643.138 | J5: =IF(AND(Inputs!$B$19>J3,$B$3>J3),Inputs!$B$6*(1+sincr)^I1,0) -> 73792.432 | ... AW5: =IF(AND(Inputs!$B$19>AW3,$B$3>AW3),Inputs!$B$6*(1+sincr)^AV1,0) -> 0
A6: Net from other work | C6: =IF(C$3<=Inputs!$B$71,Inputs!$B$70,0)*(1+inf)^B$1 -> 0 | D6: =IF(D$3<=Inputs!$B$71,Inputs!$B$70,0)*(1+inf)^C$1 -> 0 | E6: =IF(E$3<=Inputs!$B$71,Inputs!$B$70,0)*(1+inf)^D$1 -> 0 | F6: =IF(F$3<=Inputs!$B$71,Inputs!$B$70,0)*(1+inf)^E$1 -> 0 | G6: =IF(G$3<=Inputs!$B$71,Inputs!$B$70,0)*(1+inf)^F$1 -> 0 | H6: =IF(H$3<=Inputs!$B$71,Inputs!$B$70,0)*(1+inf)^G$1 -> 0 | I6: =IF(I$3<=Inputs!$B$71,Inputs!$B$70,0)*(1+inf)^H$1 -> 0 | J6: =IF(J$3<=Inputs!$B$71,Inputs!$B$70,0)*(1+inf)^I$1 -> 0 | ... AW6: =IF(AW$3<=Inputs!$B$71,Inputs!$B$70,0)*(1+inf)^AV$1 -> 0
A7: Net rental income from other properties
A8: =TEXT(Inputs!$B$50,"") -> Sliema | C8: =Inputs!B66 -> 0 | D8: =C8*(1+rinc) -> 0 | E8: =D8*(1+rinc) -> 0 | F8: =E8*(1+rinc) -> 0 | G8: =F8*(1+rinc) -> 0 | H8: =G8*(1+rinc) -> 0 | I8: =H8*(1+rinc) -> 0 | J8: =I8*(1+rinc) -> 0 | K8: =J8*(1+rinc) -> 0 | ... AW8: =AV8*(1+rinc) -> 0
A9: =TEXT(Inputs!$B$55,"") | C9: =Inputs!B67 -> 0 | D9: =C9*(1+rinc) -> 0 | E9: =D9*(1+rinc) -> 0 | F9: =E9*(1+rinc) -> 0 | G9: =F9*(1+rinc) -> 0 | H9: =G9*(1+rinc) -> 0 | I9: =H9*(1+rinc) -> 0 | J9: =I9*(1+rinc) -> 0 | K9: =J9*(1+rinc) -> 0 | ... AW9: =AV9*(1+rinc) -> 0
A10: =TEXT(Inputs!$B$60,"") | C10: =Inputs!B68 -> 0 | D10: =C10*(1+rinc) -> 0 | E10: =D10*(1+rinc) -> 0 | F10: =E10*(1+rinc) -> 0 | G10: =F10*(1+rinc) -> 0 | H10: =G10*(1+rinc) -> 0 | I10: =H10*(1+rinc) -> 0 | J10: =I10*(1+rinc) -> 0 | K10: =J10*(1+rinc) -> 0 | ... AW10: =AV10*(1+rinc) -> 0
A11: Full pension | C11: =IF(C$3<Inputs!$B$19,0,Inputs!$B$21)*(1+inf)^B$1 -> 0 | D11: =IF(D$3<Inputs!$B$19,0,Inputs!$B$21)*(1+inf)^C$1 -> 0 | E11: =IF(E$3<Inputs!$B$19,0,Inputs!$B$21)*(1+inf)^D$1 -> 0 | F11: =IF(F$3<Inputs!$B$19,0,Inputs!$B$21)*(1+inf)^E$1 -> 0 | G11: =IF(G$3<Inputs!$B$19,0,Inputs!$B$21)*(1+inf)^F$1 -> 0 | H11: =IF(H$3<Inputs!$B$19,0,Inputs!$B$21)*(1+inf)^G$1 -> 0 | I11: =IF(I$3<Inputs!$B$19,0,Inputs!$B$21)*(1+inf)^H$1 -> 0 | J11: =IF(J$3<Inputs!$B$19,0,Inputs!$B$21)*(1+inf)^I$1 -> 0 | ... AW11: =IF(AW$3<Inputs!$B$19,0,Inputs!$B$21)*(1+inf)^AV$1 -> 56049.315
A12: Pension reduction from early retirement | C12: =MIN(0,MAX(-IF(C11=0,0,(Inputs!$B$19-INDEX(3:3,MATCH(0,5:5,0))))*Inputs!$B$157*(1+inf)^B$1,-C11)) -> 0 | D12: =MIN(0,MAX(-IF(D11=0,0,(Inputs!$B$19-INDEX(3:3,MATCH(0,5:5,0))))*Inputs!$B$157*(1+inf)^C$1,-D11)) -> 0 | E12: =MIN(0,MAX(-IF(E11=0,0,(Inputs!$B$19-INDEX(3:3,MATCH(0,5:5,0))))*Inputs!$B$157*(1+inf)^D$1,-E11)) -> 0 | F12: =MIN(0,MAX(-IF(F11=0,0,(Inputs!$B$19-INDEX(3:3,MATCH(0,5:5,0))))*Inputs!$B$157*(1+inf)^E$1,-F11)) -> 0 | G12: =MIN(0,MAX(-IF(G11=0,0,(Inputs!$B$19-INDEX(3:3,MATCH(0,5:5,0))))*Inputs!$B$157*(1+inf)^F$1,-G11)) -> 0 | H12: =MIN(0,MAX(-IF(H11=0,0,(Inputs!$B$19-INDEX(3:3,MATCH(0,5:5,0))))*Inputs!$B$157*(1+inf)^G$1,-H11)) -> 0 | I12: =MIN(0,MAX(-IF(I11=0,0,(Inputs!$B$19-INDEX(3:3,MATCH(0,5:5,0))))*Inputs!$B$157*(1+inf)^H$1,-I11)) -> 0 | J12: =MIN(0,MAX(-IF(J11=0,0,(Inputs!$B$19-INDEX(3:3,MATCH(0,5:5,0))))*Inputs!$B$157*(1+inf)^I$1,-J11)) -> 0 | ... AW12: =MIN(0,MAX(-IF(AW11=0,0,(Inputs!$B$19-INDEX(3:3,MATCH(0,5:5,0))))*Inputs!$B$157*(1+inf)^AV$1,-AW11)) -> -5604.9315
A13: Other post-retirement income | C13: =IF(AND(C$3>=Inputs!$B$142,C$3<=Inputs!$B$143),Inputs!$B$141*(1+inf)^B$1,0) -> 0 | D13: =IF(AND(D$3>=Inputs!$B$142,D$3<=Inputs!$B$143),Inputs!$B$141*(1+inf)^C$1,0) -> 0 | E13: =IF(AND(E$3>=Inputs!$B$142,E$3<=Inputs!$B$143),Inputs!$B$141*(1+inf)^D$1,0) -> 0 | F13: =IF(AND(F$3>=Inputs!$B$142,F$3<=Inputs!$B$143),Inputs!$B$141*(1+inf)^E$1,0) -> 0 | G13: =IF(AND(G$3>=Inputs!$B$142,G$3<=Inputs!$B$143),Inputs!$B$141*(1+inf)^F$1,0) -> 0 | H13: =IF(AND(H$3>=Inputs!$B$142,H$3<=Inputs!$B$143),Inputs!$B$141*(1+inf)^G$1,0) -> 0 | I13: =IF(AND(I$3>=Inputs!$B$142,I$3<=Inputs!$B$143),Inputs!$B$141*(1+inf)^H$1,0) -> 0 | J13: =IF(AND(J$3>=Inputs!$B$142,J$3<=Inputs!$B$143),Inputs!$B$141*(1+inf)^I$1,0) -> 0 | ... AW13: =IF(AND(AW$3>=Inputs!$B$142,AW$3<=Inputs!$B$143),Inputs!$B$141*(1+inf)^AV$1,0) -> 0
A14: Major one-off income events
A15: =TEXT(Inputs!B100,"") | C15: =IF(C$2=Inputs!$B102,Inputs!$B101,0)*(1+inf)^B$1 -> 0 | D15: =IF(D$2=Inputs!$B102,Inputs!$B101,0)*(1+inf)^C$1 -> 0 | E15: =IF(E$2=Inputs!$B102,Inputs!$B101,0)*(1+inf)^D$1 -> 0 | F15: =IF(F$2=Inputs!$B102,Inputs!$B101,0)*(1+inf)^E$1 -> 0 | G15: =IF(G$2=Inputs!$B102,Inputs!$B101,0)*(1+inf)^F$1 -> 0 | H15: =IF(H$2=Inputs!$B102,Inputs!$B101,0)*(1+inf)^G$1 -> 0 | I15: =IF(I$2=Inputs!$B102,Inputs!$B101,0)*(1+inf)^H$1 -> 0 | J15: =IF(J$2=Inputs!$B102,Inputs!$B101,0)*(1+inf)^I$1 -> 0 | ... AW15: =IF(AW$2=Inputs!$B102,Inputs!$B101,0)*(1+inf)^AV$1 -> 0
A16: =TEXT(Inputs!B105,"") | C16: =IF(C$2=Inputs!$B107,Inputs!$B106,0)*(1+inf)^B$1 -> 0 | D16: =IF(D$2=Inputs!$B107,Inputs!$B106,0)*(1+inf)^C$1 -> 0 | E16: =IF(E$2=Inputs!$B107,Inputs!$B106,0)*(1+inf)^D$1 -> 0 | F16: =IF(F$2=Inputs!$B107,Inputs!$B106,0)*(1+inf)^E$1 -> 0 | G16: =IF(G$2=Inputs!$B107,Inputs!$B106,0)*(1+inf)^F$1 -> 0 | H16: =IF(H$2=Inputs!$B107,Inputs!$B106,0)*(1+inf)^G$1 -> 0 | I16: =IF(I$2=Inputs!$B107,Inputs!$B106,0)*(1+inf)^H$1 -> 0 | J16: =IF(J$2=Inputs!$B107,Inputs!$B106,0)*(1+inf)^I$1 -> 0 | ... AW16: =IF(AW$2=Inputs!$B107,Inputs!$B106,0)*(1+inf)^AV$1 -> 0
A17: =TEXT(Inputs!B110,"") | C17: =IF(C$2=Inputs!$B112,Inputs!$B111,0)*(1+inf)^B$1 -> 0 | D17: =IF(D$2=Inputs!$B112,Inputs!$B111,0)*(1+inf)^C$1 -> 0 | E17: =IF(E$2=Inputs!$B112,Inputs!$B111,0)*(1+inf)^D$1 -> 0 | F17: =IF(F$2=Inputs!$B112,Inputs!$B111,0)*(1+inf)^E$1 -> 0 | G17: =IF(G$2=Inputs!$B112,Inputs!$B111,0)*(1+inf)^F$1 -> 0 | H17: =IF(H$2=Inputs!$B112,Inputs!$B111,0)*(1+inf)^G$1 -> 0 | I17: =IF(I$2=Inputs!$B112,Inputs!$B111,0)*(1+inf)^H$1 -> 0 | J17: =IF(J$2=Inputs!$B112,Inputs!$B111,0)*(1+inf)^I$1 -> 0 | ... AW17: =IF(AW$2=Inputs!$B112,Inputs!$B111,0)*(1+inf)^AV$1 -> 0
A18: Interest on cash balances | C18: =MAX(AVERAGE(C49,C49+SUM(C5:C17)-C46)*Inputs!$B$149,0) -> 4998.75 | D18: =MAX(AVERAGE(D49,D49+SUM(D5:D17)-D46)*Inputs!$B$149,0) -> 5127.9375 | E18: =MAX(AVERAGE(E49,E49+SUM(E5:E17)-E46)*Inputs!$B$149,0) -> 5274.0727 | F18: =MAX(AVERAGE(F49,F49+SUM(F5:F17)-F46)*Inputs!$B$149,0) -> 5438.1505 | G18: =MAX(AVERAGE(G49,G49+SUM(G5:G17)-G46)*Inputs!$B$149,0) -> 5621.212 | H18: =MAX(AVERAGE(H49,H49+SUM(H5:H17)-H46)*Inputs!$B$149,0) -> 5824.3462 | I18: =MAX(AVERAGE(I49,I49+SUM(I5:I17)-I46)*Inputs!$B$149,0) -> 6048.6917 | J18: =MAX(AVERAGE(J49,J49+SUM(J5:J17)-J46)*Inputs!$B$149,0) -> 6295.4392 | ... AW18: =MAX(AVERAGE(AW49,AW49+SUM(AW5:AW17)-AW46)*Inputs!$B$149,0) -> 0
C19: =SUM(C4:C18) -> 64998.75 | D19: =SUM(D4:D18) -> 66927.938 | E19: =SUM(E4:E18) -> 68928.073 | F19: =SUM(F4:F18) -> 71001.77 | G19: =SUM(G4:G18) -> 73151.741 | H19: =SUM(H4:H18) -> 75380.791 | I19: =SUM(I4:I18) -> 77691.829 | J19: =SUM(J4:J18) -> 80087.871 | ... AW19: =SUM(AW4:AW18) -> 50444.384
A20: Outflows
A21: Credit cards cleared | C21: =Inputs!B75 -> 0 | D21: 0 | E21: 0 | F21: 0 | G21: 0 | H21: 0 | I21: 0 | J21: 0 | K21: 0 | L21: 0 | M21: 0 | N21: 0 | O21: 0 | P21: 0 | Q21: 0 | R21: 0 | S21: 0 | T21: 0 | U21: 0 | V21: 0 | W21: 0 | X21: 0 | Y21: 0 | Z21: 0 | AA21: 0 | AB21: 0 | AC21: 0 | AD21: 0 | AE21: 0 | AF21: 0 | AG21: 0 | AH21: 0 | AI21: 0 | AJ21: 0 | AK21: 0 | AL21: 0 | AM21: 0 | AN21: 0 | AO21: 0 | AP21: 0 | AQ21: 0 | AR21: 0 | AS21: 0 | AT21: 0 | AU21: 0 | AV21: 0 | AW21: 0
A22: Home loan repayment | C22: =MAX(IF(C$1*12<=Inputs!$G$15,12,(Inputs!$G$15-B$1*12)),0)*Inputs!$B$17 -> 9600 | D22: =MAX(IF(D$1*12<=Inputs!$G$15,12,(Inputs!$G$15-C$1*12)),0)*Inputs!$B$17 -> 9600 | E22: =MAX(IF(E$1*12<=Inputs!$G$15,12,(Inputs!$G$15-D$1*12)),0)*Inputs!$B$17 -> 9600 | F22: =MAX(IF(F$1*12<=Inputs!$G$15,12,(Inputs!$G$15-E$1*12)),0)*Inputs!$B$17 -> 9600 | G22: =MAX(IF(G$1*12<=Inputs!$G$15,12,(Inputs!$G$15-F$1*12)),0)*Inputs!$B$17 -> 9600 | H22: =MAX(IF(H$1*12<=Inputs!$G$15,12,(Inputs!$G$15-G$1*12)),0)*Inputs!$B$17 -> 9600 | I22: =MAX(IF(I$1*12<=Inputs!$G$15,12,(Inputs!$G$15-H$1*12)),0)*Inputs!$B$17 -> 9600 | J22: =MAX(IF(J$1*12<=Inputs!$G$15,12,(Inputs!$G$15-I$1*12)),0)*Inputs!$B$17 -> 9600 | ... AW22: =MAX(IF(AW$1*12<=Inputs!$G$15,12,(Inputs!$G$15-AV$1*12)),0)*Inputs!$B$17 -> 0
A23: Other property loans repayments
A24: =TEXT(Inputs!$B$50,"") -> Sliema | C24: =MAX(IF(C$1*12<=Inputs!$G$78,12,(Inputs!$G$78-B$1*12)),0)*Inputs!$B$80 -> 0 | D24: =MAX(IF(D$1*12<=Inputs!$G$78,12,(Inputs!$G$78-C$1*12)),0)*Inputs!$B$80 -> 0 | E24: =MAX(IF(E$1*12<=Inputs!$G$78,12,(Inputs!$G$78-D$1*12)),0)*Inputs!$B$80 -> 0 | F24: =MAX(IF(F$1*12<=Inputs!$G$78,12,(Inputs!$G$78-E$1*12)),0)*Inputs!$B$80 -> 0 | G24: =MAX(IF(G$1*12<=Inputs!$G$78,12,(Inputs!$G$78-F$1*12)),0)*Inputs!$B$80 -> 0 | H24: =MAX(IF(H$1*12<=Inputs!$G$78,12,(Inputs!$G$78-G$1*12)),0)*Inputs!$B$80 -> 0 | I24: =MAX(IF(I$1*12<=Inputs!$G$78,12,(Inputs!$G$78-H$1*12)),0)*Inputs!$B$80 -> 0 | J24: =MAX(IF(J$1*12<=Inputs!$G$78,12,(Inputs!$G$78-I$1*12)),0)*Inputs!$B$80 -> 0 | ... AW24: =MAX(IF(AW$1*12<=Inputs!$G$78,12,(Inputs!$G$78-AV$1*12)),0)*Inputs!$B$80 -> 0
A25: =TEXT(Inputs!$B$55,"") | C25: =MAX(IF(C$1*12<=Inputs!$G$83,12,(Inputs!$G$83-B$1*12)),0)*Inputs!$B$85 -> 0 | D25: =MAX(IF(D$1*12<=Inputs!$G$83,12,(Inputs!$G$83-C$1*12)),0)*Inputs!$B$85 -> 0 | E25: =MAX(IF(E$1*12<=Inputs!$G$83,12,(Inputs!$G$83-D$1*12)),0)*Inputs!$B$85 -> 0 | F25: =MAX(IF(F$1*12<=Inputs!$G$83,12,(Inputs!$G$83-E$1*12)),0)*Inputs!$B$85 -> 0 | G25: =MAX(IF(G$1*12<=Inputs!$G$83,12,(Inputs!$G$83-F$1*12)),0)*Inputs!$B$85 -> 0 | H25: =MAX(IF(H$1*12<=Inputs!$G$83,12,(Inputs!$G$83-G$1*12)),0)*Inputs!$B$85 -> 0 | I25: =MAX(IF(I$1*12<=Inputs!$G$83,12,(Inputs!$G$83-H$1*12)),0)*Inputs!$B$85 -> 0 | J25: =MAX(IF(J$1*12<=Inputs!$G$83,12,(Inputs!$G$83-I$1*12)),0)*Inputs!$B$85 -> 0 | ... AW25: =MAX(IF(AW$1*12<=Inputs!$G$83,12,(Inputs!$G$83-AV$1*12)),0)*Inputs!$B$85 -> 0
A26: =TEXT(Inputs!$B$60,"") | C26: =MAX(IF(C$1*12<=Inputs!$G$88,12,(Inputs!$G$88-B$1*12)),0)*Inputs!$B$90 -> 0 | D26: =MAX(IF(D$1*12<=Inputs!$G$88,12,(Inputs!$G$88-C$1*12)),0)*Inputs!$B$90 -> 0 | E26: =MAX(IF(E$1*12<=Inputs!$G$88,12,(Inputs!$G$88-D$1*12)),0)*Inputs!$B$90 -> 0 | F26: =MAX(IF(F$1*12<=Inputs!$G$88,12,(Inputs!$G$88-E$1*12)),0)*Inputs!$B$90 -> 0 | G26: =MAX(IF(G$1*12<=Inputs!$G$88,12,(Inputs!$G$88-F$1*12)),0)*Inputs!$B$90 -> 0 | H26: =MAX(IF(H$1*12<=Inputs!$G$88,12,(Inputs!$G$88-G$1*12)),0)*Inputs!$B$90 -> 0 | I26: =MAX(IF(I$1*12<=Inputs!$G$88,12,(Inputs!$G$88-H$1*12)),0)*Inputs!$B$90 -> 0 | J26: =MAX(IF(J$1*12<=Inputs!$G$88,12,(Inputs!$G$88-I$1*12)),0)*Inputs!$B$90 -> 0 | ... AW26: =MAX(IF(AW$1*12<=Inputs!$G$88,12,(Inputs!$G$88-AV$1*12)),0)*Inputs!$B$90 -> 0
A27: Other loan repayment | C27: =MAX(IF(C$1*12<=Inputs!$G$93,12,(Inputs!$G$93-B$1*12)),0)*Inputs!$B$95 -> 0 | D27: =MAX(IF(D$1*12<=Inputs!$G$93,12,(Inputs!$G$93-C$1*12)),0)*Inputs!$B$95 -> 0 | E27: =MAX(IF(E$1*12<=Inputs!$G$93,12,(Inputs!$G$93-D$1*12)),0)*Inputs!$B$95 -> 0 | F27: =MAX(IF(F$1*12<=Inputs!$G$93,12,(Inputs!$G$93-E$1*12)),0)*Inputs!$B$95 -> 0 | G27: =MAX(IF(G$1*12<=Inputs!$G$93,12,(Inputs!$G$93-F$1*12)),0)*Inputs!$B$95 -> 0 | H27: =MAX(IF(H$1*12<=Inputs!$G$93,12,(Inputs!$G$93-G$1*12)),0)*Inputs!$B$95 -> 0 | I27: =MAX(IF(I$1*12<=Inputs!$G$93,12,(Inputs!$G$93-H$1*12)),0)*Inputs!$B$95 -> 0 | J27: =MAX(IF(J$1*12<=Inputs!$G$93,12,(Inputs!$G$93-I$1*12)),0)*Inputs!$B$95 -> 0 | ... AW27: =MAX(IF(AW$1*12<=Inputs!$G$93,12,(Inputs!$G$93-AV$1*12)),0)*Inputs!$B$95 -> 0
A28: Dependents cost
A29: =TEXT(Inputs!B33,"") | C29: =IF(Inputs!$B$35>=C$1,Inputs!$B$34,0)*(1+inf)^B$1 -> 0 | D29: =IF(Inputs!$B$35>=D$1,Inputs!$B$34,0)*(1+inf)^C$1 -> 0 | E29: =IF(Inputs!$B$35>=E$1,Inputs!$B$34,0)*(1+inf)^D$1 -> 0 | F29: =IF(Inputs!$B$35>=F$1,Inputs!$B$34,0)*(1+inf)^E$1 -> 0 | G29: =IF(Inputs!$B$35>=G$1,Inputs!$B$34,0)*(1+inf)^F$1 -> 0 | H29: =IF(Inputs!$B$35>=H$1,Inputs!$B$34,0)*(1+inf)^G$1 -> 0 | I29: =IF(Inputs!$B$35>=I$1,Inputs!$B$34,0)*(1+inf)^H$1 -> 0 | J29: =IF(Inputs!$B$35>=J$1,Inputs!$B$34,0)*(1+inf)^I$1 -> 0 | ... AW29: =IF(Inputs!$B$35>=AW$1,Inputs!$B$34,0)*(1+inf)^AV$1 -> 0
A30: =TEXT(Inputs!B38,"") | C30: =IF(Inputs!$B$40>=C$1,Inputs!$B$39,0)*(1+inf)^B$1 -> 0 | D30: =IF(Inputs!$B$40>=D$1,Inputs!$B$39,0)*(1+inf)^C$1 -> 0 | E30: =IF(Inputs!$B$40>=E$1,Inputs!$B$39,0)*(1+inf)^D$1 -> 0 | F30: =IF(Inputs!$B$40>=F$1,Inputs!$B$39,0)*(1+inf)^E$1 -> 0 | G30: =IF(Inputs!$B$40>=G$1,Inputs!$B$39,0)*(1+inf)^F$1 -> 0 | H30: =IF(Inputs!$B$40>=H$1,Inputs!$B$39,0)*(1+inf)^G$1 -> 0 | I30: =IF(Inputs!$B$40>=I$1,Inputs!$B$39,0)*(1+inf)^H$1 -> 0 | J30: =IF(Inputs!$B$40>=J$1,Inputs!$B$39,0)*(1+inf)^I$1 -> 0 | ... AW30: =IF(Inputs!$B$40>=AW$1,Inputs!$B$39,0)*(1+inf)^AV$1 -> 0
A31: =TEXT(Inputs!B43,"") | C31: =IF(Inputs!$B$45>=C$1,Inputs!$B$44,0)*(1+inf)^B$1 -> 0 | D31: =IF(Inputs!$B$45>=D$1,Inputs!$B$44,0)*(1+inf)^C$1 -> 0 | E31: =IF(Inputs!$B$45>=E$1,Inputs!$B$44,0)*(1+inf)^D$1 -> 0 | F31: =IF(Inputs!$B$45>=F$1,Inputs!$B$44,0)*(1+inf)^E$1 -> 0 | G31: =IF(Inputs!$B$45>=G$1,Inputs!$B$44,0)*(1+inf)^F$1 -> 0 | H31: =IF(Inputs!$B$45>=H$1,Inputs!$B$44,0)*(1+inf)^G$1 -> 0 | I31: =IF(Inputs!$B$45>=I$1,Inputs!$B$44,0)*(1+inf)^H$1 -> 0 | J31: =IF(Inputs!$B$45>=J$1,Inputs!$B$44,0)*(1+inf)^I$1 -> 0 | ... AW31: =IF(Inputs!$B$45>=AW$1,Inputs!$B$44,0)*(1+inf)^AV$1 -> 0
A32: Housing rent | C32: =Inputs!$B$23*(1+inf)^B$1 -> 0 | D32: =Inputs!$B$23*(1+inf)^C$1 -> 0 | E32: =Inputs!$B$23*(1+inf)^D$1 -> 0 | F32: =Inputs!$B$23*(1+inf)^E$1 -> 0 | G32: =Inputs!$B$23*(1+inf)^F$1 -> 0 | H32: =Inputs!$B$23*(1+inf)^G$1 -> 0 | I32: =Inputs!$B$23*(1+inf)^H$1 -> 0 | J32: =Inputs!$B$23*(1+inf)^I$1 -> 0 | ... AW32: =Inputs!$B$23*(1+inf)^AV$1 -> 0
A33: Other property costs
A34: =TEXT(Inputs!$B$50,"") -> Sliema | C34: =Inputs!$B52*(1+inf)^B$1 -> 500 | D34: =Inputs!$B52*(1+inf)^C$1 -> 512.5 | E34: =Inputs!$B52*(1+inf)^D$1 -> 525.3125 | F34: =Inputs!$B52*(1+inf)^E$1 -> 538.44531 | G34: =Inputs!$B52*(1+inf)^F$1 -> 551.90645 | H34: =Inputs!$B52*(1+inf)^G$1 -> 565.70411 | I34: =Inputs!$B52*(1+inf)^H$1 -> 579.84671 | J34: =Inputs!$B52*(1+inf)^I$1 -> 594.34288 | ... AW34: =Inputs!$B52*(1+inf)^AV$1 -> 1556.9254
A35: =TEXT(Inputs!$B$55,"") | C35: =Inputs!$B57*(1+inf)^B$1 -> 0 | D35: =Inputs!$B57*(1+inf)^C$1 -> 0 | E35: =Inputs!$B57*(1+inf)^D$1 -> 0 | F35: =Inputs!$B57*(1+inf)^E$1 -> 0 | G35: =Inputs!$B57*(1+inf)^F$1 -> 0 | H35: =Inputs!$B57*(1+inf)^G$1 -> 0 | I35: =Inputs!$B57*(1+inf)^H$1 -> 0 | J35: =Inputs!$B57*(1+inf)^I$1 -> 0 | ... AW35: =Inputs!$B57*(1+inf)^AV$1 -> 0
A36: =TEXT(Inputs!$B$60,"") | C36: =Inputs!$B62*(1+inf)^B$1 -> 0 | D36: =Inputs!$B62*(1+inf)^C$1 -> 0 | E36: =Inputs!$B62*(1+inf)^D$1 -> 0 | F36: =Inputs!$B62*(1+inf)^E$1 -> 0 | G36: =Inputs!$B62*(1+inf)^F$1 -> 0 | H36: =Inputs!$B62*(1+inf)^G$1 -> 0 | I36: =Inputs!$B62*(1+inf)^H$1 -> 0 | J36: =Inputs!$B62*(1+inf)^I$1 -> 0 | ... AW36: =Inputs!$B62*(1+inf)^AV$1 -> 0
A37: Living expenses
A38: Current baseline | C38: =Inputs!$B$25*(1+inf)^B$1 -> 50000 | D38: =Inputs!$B$25*(1+inf)^C$1 -> 51250 | E38: =Inputs!$B$25*(1+inf)^D$1 -> 52531.25 | F38: =Inputs!$B$25*(1+inf)^E$1 -> 53844.531 | G38: =Inputs!$B$25*(1+inf)^F$1 -> 55190.645 | H38: =Inputs!$B$25*(1+inf)^G$1 -> 56570.411 | I38: =Inputs!$B$25*(1+inf)^H$1 -> 57984.671 | J38: =Inputs!$B$25*(1+inf)^I$1 -> 59434.288 | ... AW38: =Inputs!$B$25*(1+inf)^AV$1 -> 155692.54
A39: ="Adjustment "&Inputs!A137 -> Adjustment from now to 65 | C39: =IF(C$3<=65,Inputs!$B$137*C$38,0) -> 0 | D39: =IF(D$3<=65,Inputs!$B$137*D$38,0) -> 0 | E39: =IF(E$3<=65,Inputs!$B$137*E$38,0) -> 0 | F39: =IF(F$3<=65,Inputs!$B$137*F$38,0) -> 0 | G39: =IF(G$3<=65,Inputs!$B$137*G$38,0) -> 0 | H39: =IF(H$3<=65,Inputs!$B$137*H$38,0) -> 0 | I39: =IF(I$3<=65,Inputs!$B$137*I$38,0) -> 0 | J39: =IF(J$3<=65,Inputs!$B$137*J$38,0) -> 0 | ... AW39: =IF(AW$3<=65,Inputs!$B$137*AW$38,0) -> 0
A40: ="Adjustment "&Inputs!A138 -> Adjustment from 66-75 | C40: =IF(AND(C$3>65,C$3<=75),Inputs!$B$138*C38,0) -> 0 | D40: =IF(AND(D$3>65,D$3<=75),Inputs!$B$138*D38,0) -> 0 | E40: =IF(AND(E$3>65,E$3<=75),Inputs!$B$138*E38,0) -> 0 | F40: =IF(AND(F$3>65,F$3<=75),Inputs!$B$138*F38,0) -> 0 | G40: =IF(AND(G$3>65,G$3<=75),Inputs!$B$138*G38,0) -> 0 | H40: =IF(AND(H$3>65,H$3<=75),Inputs!$B$138*H38,0) -> 0 | I40: =IF(AND(I$3>65,I$3<=75),Inputs!$B$138*I38,0) -> 0 | J40: =IF(AND(J$3>65,J$3<=75),Inputs!$B$138*J38,0) -> 0 | ... AW40: =IF(AND(AW$3>65,AW$3<=75),Inputs!$B$138*AW38,0) -> 0
A41: ="Adjustment "&Inputs!A139 -> Adjustment from age 76 | C41: =IF(C$3>75,Inputs!$B$139*C$38,0) -> 0 | D41: =IF(D$3>75,Inputs!$B$139*D$38,0) -> 0 | E41: =IF(E$3>75,Inputs!$B$139*E$38,0) -> 0 | F41: =IF(F$3>75,Inputs!$B$139*F$38,0) -> 0 | G41: =IF(G$3>75,Inputs!$B$139*G$38,0) -> 0 | H41: =IF(H$3>75,Inputs!$B$139*H$38,0) -> 0 | I41: =IF(I$3>75,Inputs!$B$139*I$38,0) -> 0 | J41: =IF(J$3>75,Inputs!$B$139*J$38,0) -> 0 | ... AW41: =IF(AW$3>75,Inputs!$B$139*AW$38,0) -> -31138.509
A42: Major one-off expense events
A43: =TEXT(Inputs!$B$117,"") | C43: =IF(C$2=Inputs!$B119,Inputs!$B118,0)*(1+inf)^B$1 -> 0 | D43: =IF(D$2=Inputs!$B119,Inputs!$B118,0)*(1+inf)^C$1 -> 0 | E43: =IF(E$2=Inputs!$B119,Inputs!$B118,0)*(1+inf)^D$1 -> 0 | F43: =IF(F$2=Inputs!$B119,Inputs!$B118,0)*(1+inf)^E$1 -> 0 | G43: =IF(G$2=Inputs!$B119,Inputs!$B118,0)*(1+inf)^F$1 -> 0 | H43: =IF(H$2=Inputs!$B119,Inputs!$B118,0)*(1+inf)^G$1 -> 0 | I43: =IF(I$2=Inputs!$B119,Inputs!$B118,0)*(1+inf)^H$1 -> 0 | J43: =IF(J$2=Inputs!$B119,Inputs!$B118,0)*(1+inf)^I$1 -> 0 | ... AW43: =IF(AW$2=Inputs!$B119,Inputs!$B118,0)*(1+inf)^AV$1 -> 0
A44: =TEXT(Inputs!$B$122,"") | C44: =IF(C$2=Inputs!$B124,Inputs!$B123,0)*(1+inf)^B$1 -> 0 | D44: =IF(D$2=Inputs!$B124,Inputs!$B123,0)*(1+inf)^C$1 -> 0 | E44: =IF(E$2=Inputs!$B124,Inputs!$B123,0)*(1+inf)^D$1 -> 0 | F44: =IF(F$2=Inputs!$B124,Inputs!$B123,0)*(1+inf)^E$1 -> 0 | G44: =IF(G$2=Inputs!$B124,Inputs!$B123,0)*(1+inf)^F$1 -> 0 | H44: =IF(H$2=Inputs!$B124,Inputs!$B123,0)*(1+inf)^G$1 -> 0 | I44: =IF(I$2=Inputs!$B124,Inputs!$B123,0)*(1+inf)^H$1 -> 0 | J44: =IF(J$2=Inputs!$B124,Inputs!$B123,0)*(1+inf)^I$1 -> 0 | ... AW44: =IF(AW$2=Inputs!$B124,Inputs!$B123,0)*(1+inf)^AV$1 -> 0
A45: =TEXT(Inputs!$B$127,"") | C45: =IF(C$2=Inputs!$B129,Inputs!$B128,0)*(1+inf)^B$1 -> 0 | D45: =IF(D$2=Inputs!$B129,Inputs!$B128,0)*(1+inf)^C$1 -> 0 | E45: =IF(E$2=Inputs!$B129,Inputs!$B128,0)*(1+inf)^D$1 -> 0 | F45: =IF(F$2=Inputs!$B129,Inputs!$B128,0)*(1+inf)^E$1 -> 0 | G45: =IF(G$2=Inputs!$B129,Inputs!$B128,0)*(1+inf)^F$1 -> 0 | H45: =IF(H$2=Inputs!$B129,Inputs!$B128,0)*(1+inf)^G$1 -> 0 | I45: =IF(I$2=Inputs!$B129,Inputs!$B128,0)*(1+inf)^H$1 -> 0 | J45: =IF(J$2=Inputs!$B129,Inputs!$B128,0)*(1+inf)^I$1 -> 0 | ... AW45: =IF(AW$2=Inputs!$B129,Inputs!$B128,0)*(1+inf)^AV$1 -> 0
C46: =SUM(C20:C45) -> 60100 | D46: =SUM(D20:D45) -> 61362.5 | E46: =SUM(E20:E45) -> 62656.562 | F46: =SUM(F20:F45) -> 63982.977 | G46: =SUM(G20:G45) -> 65342.551 | H46: =SUM(H20:H45) -> 66736.115 | I46: =SUM(I20:I45) -> 68164.518 | J46: =SUM(J20:J45) -> 69628.631 | ... AW46: =SUM(AW20:AW45) -> 126110.96
A48: Net Cash Flow | C48: =C19-C46 -> 4898.75 | D48: =D19-D46 -> 5565.4375 | E48: =E19-E46 -> 6271.5102 | F48: =F19-F46 -> 7018.7939 | G48: =G19-G46 -> 7809.1896 | H48: =H19-H46 -> 8644.6759 | I48: =I19-I46 -> 9527.3119 | J48: =J19-J46 -> 10459.241 | ... AW48: =AW19-AW46 -> -75666.576
A49: Cash b/fwd | C49: =Inputs!B8 -> 200000 | D49: =C50 -> 204898.75 | E49: =D50 -> 210464.19 | F49: =E50 -> 216735.7 | G49: =F50 -> 223754.49 | H49: =G50 -> 231563.68 | I49: =H50 -> 240208.36 | J49: =I50 -> 249735.67 | K49: =J50 -> 260194.91 | ... AW49: =AV50 -> -1805684.8
A50: Cash c/fwd | C50: =SUM(C48:C49) -> 204898.75 | D50: =SUM(D48:D49) -> 210464.19 | E50: =SUM(E48:E49) -> 216735.7 | F50: =SUM(F48:F49) -> 223754.49 | G50: =SUM(G48:G49) -> 231563.68 | H50: =SUM(H48:H49) -> 240208.36 | I50: =SUM(I48:I49) -> 249735.67 | J50: =SUM(J48:J49) -> 260194.91 | ... AW50: =SUM(AW48:AW49) -> -1881351.4
A52: Net Worth before liquidations
A53: Cash | C53: =C50 -> 204898.75 | D53: =D50 -> 210464.19 | E53: =E50 -> 216735.7 | F53: =F50 -> 223754.49 | G53: =G50 -> 231563.68 | H53: =H50 -> 240208.36 | I53: =I50 -> 249735.67 | J53: =J50 -> 260194.91 | ... AW53: =AW50 -> -1881351.4
A54: Home | C54: =Inputs!B12*(1+princ) -> 515000 | D54: =C54*(1+princ) -> 530450 | E54: =D54*(1+princ) -> 546363.5 | F54: =E54*(1+princ) -> 562754.41 | G54: =F54*(1+princ) -> 579637.04 | H54: =G54*(1+princ) -> 597026.15 | I54: =H54*(1+princ) -> 614936.93 | J54: =I54*(1+princ) -> 633385.04 | K54: =J54*(1+princ) -> 652386.59 | ... AW54: =AV54*(1+princ) -> 2005947.5
A55: Other property
A56: =TEXT(Inputs!$B$50,"") -> Sliema | C56: =Inputs!B51*(1+princ) -> 309000 | D56: =C56*(1+princ) -> 318270 | E56: =D56*(1+princ) -> 327818.1 | F56: =E56*(1+princ) -> 337652.64 | G56: =F56*(1+princ) -> 347782.22 | H56: =G56*(1+princ) -> 358215.69 | I56: =H56*(1+princ) -> 368962.16 | J56: =I56*(1+princ) -> 380031.02 | K56: =J56*(1+princ) -> 391431.96 | ... AW56: =AV56*(1+princ) -> 1203568.5
A57: =TEXT(Inputs!$B$55,"") | C57: =Inputs!B56*(1+princ) -> 0 | D57: =C57*(1+princ) -> 0 | E57: =D57*(1+princ) -> 0 | F57: =E57*(1+princ) -> 0 | G57: =F57*(1+princ) -> 0 | H57: =G57*(1+princ) -> 0 | I57: =H57*(1+princ) -> 0 | J57: =I57*(1+princ) -> 0 | K57: =J57*(1+princ) -> 0 | ... AW57: =AV57*(1+princ) -> 0
A58: =TEXT(Inputs!$B$60,"") | C58: =Inputs!B61*(1+princ) -> 0 | D58: =C58*(1+princ) -> 0 | E58: =D58*(1+princ) -> 0 | F58: =E58*(1+princ) -> 0 | G58: =F58*(1+princ) -> 0 | H58: =G58*(1+princ) -> 0 | I58: =H58*(1+princ) -> 0 | J58: =I58*(1+princ) -> 0 | K58: =J58*(1+princ) -> 0 | ... AW58: =AV58*(1+princ) -> 0
A59: Stock market equity investments | C59: =Inputs!B10*(1+stinc) -> 54000 | D59: =C59*(1+stinc) -> 58320 | E59: =D59*(1+stinc) -> 62985.6 | F59: =E59*(1+stinc) -> 68024.448 | G59: =F59*(1+stinc) -> 73466.404 | H59: =G59*(1+stinc) -> 79343.716 | I59: =H59*(1+stinc) -> 85691.213 | J59: =I59*(1+stinc) -> 92546.511 | K59: =J59*(1+stinc) -> 99950.231 | ... AW59: =AV59*(1+stinc) -> 1861600.6
A60: Home loan | C60: =-MAX(FV(Inputs!$B16/12,C$1*12,Inputs!$B17,-Inputs!$B15),0) -> -113916.81 | D60: =-MAX(FV(Inputs!$B16/12,D$1*12,Inputs!$B17,-Inputs!$B15),0) -> -107648.59 | E60: =-MAX(FV(Inputs!$B16/12,E$1*12,Inputs!$B17,-Inputs!$B15),0) -> -101189.72 | F60: =-MAX(FV(Inputs!$B16/12,F$1*12,Inputs!$B17,-Inputs!$B15),0) -> -94534.396 | G60: =-MAX(FV(Inputs!$B16/12,G$1*12,Inputs!$B17,-Inputs!$B15),0) -> -87676.644 | H60: =-MAX(FV(Inputs!$B16/12,H$1*12,Inputs!$B17,-Inputs!$B15),0) -> -80610.306 | I60: =-MAX(FV(Inputs!$B16/12,I$1*12,Inputs!$B17,-Inputs!$B15),0) -> -73329.04 | J60: =-MAX(FV(Inputs!$B16/12,J$1*12,Inputs!$B17,-Inputs!$B15),0) -> -65826.307 | ... AW60: =-MAX(FV(Inputs!$B16/12,AW$1*12,Inputs!$B17,-Inputs!$B15),0) -> 0
A61: Other property loans
A62: =TEXT(Inputs!$B$50,"") -> Sliema | C62: =-MAX(FV(Inputs!$B79/12,C$1*12,Inputs!$B80,-Inputs!$B78),0) -> 0 | D62: =-MAX(FV(Inputs!$B79/12,D$1*12,Inputs!$B80,-Inputs!$B78),0) -> 0 | E62: =-MAX(FV(Inputs!$B79/12,E$1*12,Inputs!$B80,-Inputs!$B78),0) -> 0 | F62: =-MAX(FV(Inputs!$B79/12,F$1*12,Inputs!$B80,-Inputs!$B78),0) -> 0 | G62: =-MAX(FV(Inputs!$B79/12,G$1*12,Inputs!$B80,-Inputs!$B78),0) -> 0 | H62: =-MAX(FV(Inputs!$B79/12,H$1*12,Inputs!$B80,-Inputs!$B78),0) -> 0 | I62: =-MAX(FV(Inputs!$B79/12,I$1*12,Inputs!$B80,-Inputs!$B78),0) -> 0 | J62: =-MAX(FV(Inputs!$B79/12,J$1*12,Inputs!$B80,-Inputs!$B78),0) -> 0 | ... AW62: =-MAX(FV(Inputs!$B79/12,AW$1*12,Inputs!$B80,-Inputs!$B78),0) -> 0
A63: =TEXT(Inputs!$B$55,"") | C63: =-MAX(FV(Inputs!$B84/12,C$1*12,Inputs!$B85,-Inputs!$B83),0) -> 0 | D63: =-MAX(FV(Inputs!$B84/12,D$1*12,Inputs!$B85,-Inputs!$B83),0) -> 0 | E63: =-MAX(FV(Inputs!$B84/12,E$1*12,Inputs!$B85,-Inputs!$B83),0) -> 0 | F63: =-MAX(FV(Inputs!$B84/12,F$1*12,Inputs!$B85,-Inputs!$B83),0) -> 0 | G63: =-MAX(FV(Inputs!$B84/12,G$1*12,Inputs!$B85,-Inputs!$B83),0) -> 0 | H63: =-MAX(FV(Inputs!$B84/12,H$1*12,Inputs!$B85,-Inputs!$B83),0) -> 0 | I63: =-MAX(FV(Inputs!$B84/12,I$1*12,Inputs!$B85,-Inputs!$B83),0) -> 0 | J63: =-MAX(FV(Inputs!$B84/12,J$1*12,Inputs!$B85,-Inputs!$B83),0) -> 0 | ... AW63: =-MAX(FV(Inputs!$B84/12,AW$1*12,Inputs!$B85,-Inputs!$B83),0) -> 0
A64: =TEXT(Inputs!$B$60,"") | C64: =-MAX(FV(Inputs!$B89/12,C$1*12,Inputs!$B90,-Inputs!$B88),0) -> 0 | D64: =-MAX(FV(Inputs!$B89/12,D$1*12,Inputs!$B90,-Inputs!$B88),0) -> 0 | E64: =-MAX(FV(Inputs!$B89/12,E$1*12,Inputs!$B90,-Inputs!$B88),0) -> 0 | F64: =-MAX(FV(Inputs!$B89/12,F$1*12,Inputs!$B90,-Inputs!$B88),0) -> 0 | G64: =-MAX(FV(Inputs!$B89/12,G$1*12,Inputs!$B90,-Inputs!$B88),0) -> 0 | H64: =-MAX(FV(Inputs!$B89/12,H$1*12,Inputs!$B90,-Inputs!$B88),0) -> 0 | I64: =-MAX(FV(Inputs!$B89/12,I$1*12,Inputs!$B90,-Inputs!$B88),0) -> 0 | J64: =-MAX(FV(Inputs!$B89/12,J$1*12,Inputs!$B90,-Inputs!$B88),0) -> 0 | ... AW64: =-MAX(FV(Inputs!$B89/12,AW$1*12,Inputs!$B90,-Inputs!$B88),0) -> 0
A65: Other loan | C65: =-MAX(FV(Inputs!$B94/12,C$1*12,Inputs!$B95,-Inputs!$B93),0) -> 0 | D65: =-MAX(FV(Inputs!$B94/12,D$1*12,Inputs!$B95,-Inputs!$B93),0) -> 0 | E65: =-MAX(FV(Inputs!$B94/12,E$1*12,Inputs!$B95,-Inputs!$B93),0) -> 0 | F65: =-MAX(FV(Inputs!$B94/12,F$1*12,Inputs!$B95,-Inputs!$B93),0) -> 0 | G65: =-MAX(FV(Inputs!$B94/12,G$1*12,Inputs!$B95,-Inputs!$B93),0) -> 0 | H65: =-MAX(FV(Inputs!$B94/12,H$1*12,Inputs!$B95,-Inputs!$B93),0) -> 0 | I65: =-MAX(FV(Inputs!$B94/12,I$1*12,Inputs!$B95,-Inputs!$B93),0) -> 0 | J65: =-MAX(FV(Inputs!$B94/12,J$1*12,Inputs!$B95,-Inputs!$B93),0) -> 0 | ... AW65: =-MAX(FV(Inputs!$B94/12,AW$1*12,Inputs!$B95,-Inputs!$B93),0) -> 0
C66: =SUM(C52:C65) -> 968981.94 | D66: =SUM(D52:D65) -> 1009855.6 | E66: =SUM(E52:E65) -> 1052713.2 | F66: =SUM(F52:F65) -> 1097651.6 | G66: =SUM(G52:G65) -> 1144772.7 | H66: =SUM(H52:H65) -> 1194183.6 | I66: =SUM(I52:I65) -> 1245996.9 | J66: =SUM(J52:J65) -> 1300331.2 | ... AW66: =SUM(AW52:AW65) -> 3189765.2
A68: Cash available (after buffer) | C68: =C53-buffer -> 184898.75 | D68: =D53-buffer -> 190464.19 | E68: =E53-buffer -> 196735.7 | F68: =F53-buffer -> 203754.49 | G68: =G53-buffer -> 211563.68 | H68: =H53-buffer -> 220208.36 | I68: =I53-buffer -> 229735.67 | J68: =J53-buffer -> 240194.91 | ... AW68: =AW53-buffer -> -1901351.4
A69: Liquidation required | C69: =IF(C68<0,-C68,0) -> 0 | D69: =IF(D68+SUM($C69:C69)<0,-(D68+SUM($C69:C69)),0) -> 0 | E69: =IF(E68+SUM($C69:D69)<0,-(E68+SUM($C69:D69)),0) -> 0 | F69: =IF(F68+SUM($C69:E69)<0,-(F68+SUM($C69:E69)),0) -> 0 | G69: =IF(G68+SUM($C69:F69)<0,-(G68+SUM($C69:F69)),0) -> 0 | H69: =IF(H68+SUM($C69:G69)<0,-(H68+SUM($C69:G69)),0) -> 0 | I69: =IF(I68+SUM($C69:H69)<0,-(I68+SUM($C69:H69)),0) -> 0 | J69: =IF(J68+SUM($C69:I69)<0,-(J68+SUM($C69:I69)),0) -> 0 | K69: =IF(K68+SUM($C69:J69)<0,-(K68+SUM($C69:J69)),0) -> 0 | ... AW69: =IF(AW68+SUM($C69:AV69)<0,-(AW68+SUM($C69:AV69)),0) -> 75666.576
A71: Liquidations
A73: Stock market equity
A74: b/fwd | C74: =C59 -> 54000 | D74: =C77 -> 54000 | E74: =D77 -> 58320 | F74: =E77 -> 62985.6 | G74: =F77 -> 68024.448 | H74: =G77 -> 73466.404 | I74: =H77 -> 79343.716 | J74: =I77 -> 85691.213 | K74: =J77 -> 92546.511 | ... AW74: =AV77 -> 0
A75: Disposals | C75: =-MIN( IF(C74>C69/ (1 - Inputs!$B$161), C69/ (1 - Inputs!$B$161), C74), C74/ (1 - Inputs!$B$161) ) -> 0 | D75: =-MIN( IF(D74>D69/ (1 - Inputs!$B$161), D69/ (1 - Inputs!$B$161), D74), D74/ (1 - Inputs!$B$161) ) -> 0 | E75: =-MIN( IF(E74>E69/ (1 - Inputs!$B$161), E69/ (1 - Inputs!$B$161), E74), E74/ (1 - Inputs!$B$161) ) -> 0 | F75: =-MIN( IF(F74>F69/ (1 - Inputs!$B$161), F69/ (1 - Inputs!$B$161), F74), F74/ (1 - Inputs!$B$161) ) -> 0 | G75: =-MIN( IF(G74>G69/ (1 - Inputs!$B$161), G69/ (1 - Inputs!$B$161), G74), G74/ (1 - Inputs!$B$161) ) -> 0 | H75: =-MIN( IF(H74>H69/ (1 - Inputs!$B$161), H69/ (1 - Inputs!$B$161), H74), H74/ (1 - Inputs!$B$161) ) -> 0 | I75: =-MIN( IF(I74>I69/ (1 - Inputs!$B$161), I69/ (1 - Inputs!$B$161), I74), I74/ (1 - Inputs!$B$161) ) -> 0 | J75: =-MIN( IF(J74>J69/ (1 - Inputs!$B$161), J69/ (1 - Inputs!$B$161), J74), J74/ (1 - Inputs!$B$161) ) -> 0 | ... AW75: =-MIN( IF(AW74>AW69/ (1 - Inputs!$B$161), AW69/ (1 - Inputs!$B$161), AW74), AW74/ (1 - Inputs!$B$161) ) -> 0
A76: Growth | C76: 0 | D76: =SUM(D74:D75)*stinc -> 4320 | E76: =SUM(E74:E75)*stinc -> 4665.6 | F76: =SUM(F74:F75)*stinc -> 5038.848 | G76: =SUM(G74:G75)*stinc -> 5441.9558 | H76: =SUM(H74:H75)*stinc -> 5877.3123 | I76: =SUM(I74:I75)*stinc -> 6347.4973 | J76: =SUM(J74:J75)*stinc -> 6855.2971 | K76: =SUM(K74:K75)*stinc -> 7403.7208 | ... AW76: =SUM(AW74:AW75)*stinc -> 0
A77: c/fwd | C77: =SUM(C74:C76) -> 54000 | D77: =SUM(D74:D76) -> 58320 | E77: =SUM(E74:E76) -> 62985.6 | F77: =SUM(F74:F76) -> 68024.448 | G77: =SUM(G74:G76) -> 73466.404 | H77: =SUM(H74:H76) -> 79343.716 | I77: =SUM(I74:I76) -> 85691.213 | J77: =SUM(J74:J76) -> 92546.511 | ... AW77: =SUM(AW74:AW76) -> 0
A78: Disposal costs | C78: =C75*Inputs!$B$161 -> 0 | D78: =D75*Inputs!$B$161 -> 0 | E78: =E75*Inputs!$B$161 -> 0 | F78: =F75*Inputs!$B$161 -> 0 | G78: =G75*Inputs!$B$161 -> 0 | H78: =H75*Inputs!$B$161 -> 0 | I78: =I75*Inputs!$B$161 -> 0 | J78: =J75*Inputs!$B$161 -> 0 | ... AW78: =AW75*Inputs!$B$161 -> 0
A79: Net proceeds | C79: =-C75+C78 -> 0 | D79: =-D75+D78 -> 0 | E79: =-E75+E78 -> 0 | F79: =-F75+F78 -> 0 | G79: =-G75+G78 -> 0 | H79: =-H75+H78 -> 0 | I79: =-I75+I78 -> 0 | J79: =-J75+J78 -> 0 | ... AW79: =-AW75+AW78 -> 0
A81: Cash available (after buffer) | C81: =C68+SUM($C79:C79) -> 184898.75 | D81: =D68+SUM($C79:D79) -> 190464.19 | E81: =E68+SUM($C79:E79) -> 196735.7 | F81: =F68+SUM($C79:F79) -> 203754.49 | G81: =G68+SUM($C79:G79) -> 211563.68 | H81: =H68+SUM($C79:H79) -> 220208.36 | I81: =I68+SUM($C79:I79) -> 229735.67 | J81: =J68+SUM($C79:J79) -> 240194.91 | ... AW81: =AW68+SUM($C79:AW79) -> -1748451.1
A82: Liquidation required | C82: =IF(C81<0,C81,0) -> 0 | D82: =IF(D81+SUM($C82:C82)<0,-(D81+SUM($C82:C82)),0) -> 0 | E82: =IF(E81+SUM($C82:D82)<0,-(E81+SUM($C82:D82)),0) -> 0 | F82: =IF(F81+SUM($C82:E82)<0,-(F81+SUM($C82:E82)),0) -> 0 | G82: =IF(G81+SUM($C82:F82)<0,-(G81+SUM($C82:F82)),0) -> 0 | H82: =IF(H81+SUM($C82:G82)<0,-(H81+SUM($C82:G82)),0) -> 0 | I82: =IF(I81+SUM($C82:H82)<0,-(I81+SUM($C82:H82)),0) -> 0 | J82: =IF(J81+SUM($C82:I82)<0,-(J81+SUM($C82:I82)),0) -> 0 | K82: =IF(K81+SUM($C82:J82)<0,-(K81+SUM($C82:J82)),0) -> 0 | ... AW82: =IF(AW81+SUM($C82:AV82)<0,-(AW81+SUM($C82:AV82)),0) -> 75666.576
A84: =IF(Inputs!$B$165=6,IFERROR(_xlfn.XLOOKUP($B84,Inputs!$B$166:$B$168,Inputs!$A$166:$A$168,,0,1),""),IFERROR(_xlfn.XLOOKUP($B84,Inputs!$C$166:$C$168,Inputs!$A$166:$A$168,,0,1),"")) -> Sliema | B84: 1
A85: b/fwd | C85: =IFERROR(VLOOKUP($A84,$A$52:$H$66,C$1+2,FALSE),0) -> 309000 | D85: =C88 -> 309000 | E85: =D88 -> 318270 | F85: =E88 -> 327818.1 | G85: =F88 -> 337652.64 | H85: =G88 -> 347782.22 | I85: =H88 -> 358215.69 | J85: =I88 -> 368962.16 | K85: =J88 -> 380031.02 | ... AW85: =AV88 -> 0
A86: Disposals | C86: =-IF(SUM(C82:D82)>0,C85,0) -> 0 | D86: =-IF(E82>0,D85,0) -> 0 | E86: =-IF(F82>0,E85,0) -> 0 | F86: =-IF(G82>0,F85,0) -> 0 | G86: =-IF(H82>0,G85,0) -> 0 | H86: =-IF(I82>0,H85,0) -> 0 | I86: =-IF(J82>0,I85,0) -> 0 | J86: =-IF(K82>0,J85,0) -> 0 | K86: =-IF(L82>0,K85,0) -> 0 | ... AW86: =-IF(AX82>0,AW85,0) -> 0
A87: Growth | C87: 0 | D87: =SUM(D85:D86)*princ -> 9270 | E87: =SUM(E85:E86)*princ -> 9548.1 | F87: =SUM(F85:F86)*princ -> 9834.543 | G87: =SUM(G85:G86)*princ -> 10129.579 | H87: =SUM(H85:H86)*princ -> 10433.467 | I87: =SUM(I85:I86)*princ -> 10746.471 | J87: =SUM(J85:J86)*princ -> 11068.865 | K87: =SUM(K85:K86)*princ -> 11400.931 | ... AW87: =SUM(AW85:AW86)*princ -> 0
A88: c/fwd | C88: =SUM(C85:C87) -> 309000 | D88: =SUM(D85:D87) -> 318270 | E88: =SUM(E85:E87) -> 327818.1 | F88: =SUM(F85:F87) -> 337652.64 | G88: =SUM(G85:G87) -> 347782.22 | H88: =SUM(H85:H87) -> 358215.69 | I88: =SUM(I85:I87) -> 368962.16 | J88: =SUM(J85:J87) -> 380031.02 | ... AW88: =SUM(AW85:AW87) -> 0
A89: Disposal costs | C89: =C86*Inputs!$B$163 -> 0 | D89: =D86*Inputs!$B$163 -> 0 | E89: =E86*Inputs!$B$163 -> 0 | F89: =F86*Inputs!$B$163 -> 0 | G89: =G86*Inputs!$B$163 -> 0 | H89: =H86*Inputs!$B$163 -> 0 | I89: =I86*Inputs!$B$163 -> 0 | J89: =J86*Inputs!$B$163 -> 0 | ... AW89: =AW86*Inputs!$B$163 -> 0
A90: Rental income foregone | C90: =IFERROR(-IF(C85=0,VLOOKUP($A84,$7:$10,C$1+2,FALSE),0),0) -> 0 | D90: =IFERROR(-IF(D85=0,VLOOKUP($A84,$7:$10,D$1+2,FALSE),0),0) -> 0 | E90: =IFERROR(-IF(E85=0,VLOOKUP($A84,$7:$10,E$1+2,FALSE),0),0) -> 0 | F90: =IFERROR(-IF(F85=0,VLOOKUP($A84,$7:$10,F$1+2,FALSE),0),0) -> 0 | G90: =IFERROR(-IF(G85=0,VLOOKUP($A84,$7:$10,G$1+2,FALSE),0),0) -> 0 | H90: =IFERROR(-IF(H85=0,VLOOKUP($A84,$7:$10,H$1+2,FALSE),0),0) -> 0 | I90: =IFERROR(-IF(I85=0,VLOOKUP($A84,$7:$10,I$1+2,FALSE),0),0) -> 0 | J90: =IFERROR(-IF(J85=0,VLOOKUP($A84,$7:$10,J$1+2,FALSE),0),0) -> 0 | ... AW90: =IFERROR(-IF(AW85=0,VLOOKUP($A84,$7:$10,AW$1+2,FALSE),0),0) -> 0
A91: Annual cost saved | C91: =IFERROR(IF(C85=0,VLOOKUP($A84,$33:$36,C$1+2,FALSE),0),0) -> 0 | D91: =IFERROR(IF(D85=0,VLOOKUP($A84,$33:$36,D$1+2,FALSE),0),0) -> 0 | E91: =IFERROR(IF(E85=0,VLOOKUP($A84,$33:$36,E$1+2,FALSE),0),0) -> 0 | F91: =IFERROR(IF(F85=0,VLOOKUP($A84,$33:$36,F$1+2,FALSE),0),0) -> 0 | G91: =IFERROR(IF(G85=0,VLOOKUP($A84,$33:$36,G$1+2,FALSE),0),0) -> 0 | H91: =IFERROR(IF(H85=0,VLOOKUP($A84,$33:$36,H$1+2,FALSE),0),0) -> 0 | I91: =IFERROR(IF(I85=0,VLOOKUP($A84,$33:$36,I$1+2,FALSE),0),0) -> 0 | J91: =IFERROR(IF(J85=0,VLOOKUP($A84,$33:$36,J$1+2,FALSE),0),0) -> 0 | ... AW91: =IFERROR(IF(AW85=0,VLOOKUP($A84,$33:$36,AW$1+2,FALSE),0),0) -> 1556.9254
A92: Loan repayment | B92: =A84 -> Sliema | C92: =IF(AND(C85>0,C88=0),VLOOKUP($A84,$61:$64,C$1+2,FALSE),0) -> 0 | D92: =IF(AND(D85>0,D88=0),VLOOKUP($A84,$61:$64,D$1+2,FALSE),0) -> 0 | E92: =IF(AND(E85>0,E88=0),VLOOKUP($A84,$61:$64,E$1+2,FALSE),0) -> 0 | F92: =IF(AND(F85>0,F88=0),VLOOKUP($A84,$61:$64,F$1+2,FALSE),0) -> 0 | G92: =IF(AND(G85>0,G88=0),VLOOKUP($A84,$61:$64,G$1+2,FALSE),0) -> 0 | H92: =IF(AND(H85>0,H88=0),VLOOKUP($A84,$61:$64,H$1+2,FALSE),0) -> 0 | I92: =IF(AND(I85>0,I88=0),VLOOKUP($A84,$61:$64,I$1+2,FALSE),0) -> 0 | J92: =IF(AND(J85>0,J88=0),VLOOKUP($A84,$61:$64,J$1+2,FALSE),0) -> 0 | ... AW92: =IF(AND(AW85>0,AW88=0),VLOOKUP($A84,$61:$64,AW$1+2,FALSE),0) -> 0
A93: Net proceeds | C93: =-C86+SUM(C89:C92) -> 0 | D93: =-D86+SUM(D89:D92) -> 0 | E93: =-E86+SUM(E89:E92) -> 0 | F93: =-F86+SUM(F89:F92) -> 0 | G93: =-G86+SUM(G89:G92) -> 0 | H93: =-H86+SUM(H89:H92) -> 0 | I93: =-I86+SUM(I89:I92) -> 0 | J93: =-J86+SUM(J89:J92) -> 0 | ... AW93: =-AW86+SUM(AW89:AW92) -> 1556.9254
A95: Cash available (after buffer) | C95: =C81+SUM($C93:C93) -> 184898.75 | D95: =D81+SUM($C93:D93) -> 190464.19 | E95: =E81+SUM($C93:E93) -> 196735.7 | F95: =F81+SUM($C93:F93) -> 203754.49 | G95: =G81+SUM($C93:G93) -> 211563.68 | H95: =H81+SUM($C93:H93) -> 220208.36 | I95: =I81+SUM($C93:I93) -> 229735.67 | J95: =J81+SUM($C93:J93) -> 240194.91 | ... AW95: =AW81+SUM($C93:AW93) -> -1317025.6
A96: Extra cash | C96: =MAX(C95+buffer,0)-MAX(C$81+buffer,0) -> 0 | D96: =MAX(D95+buffer,0)-MAX(D$81+buffer,0) -> 0 | E96: =MAX(E95+buffer,0)-MAX(E$81+buffer,0) -> 0 | F96: =MAX(F95+buffer,0)-MAX(F$81+buffer,0) -> 0 | G96: =MAX(G95+buffer,0)-MAX(G$81+buffer,0) -> 0 | H96: =MAX(H95+buffer,0)-MAX(H$81+buffer,0) -> 0 | I96: =MAX(I95+buffer,0)-MAX(I$81+buffer,0) -> 0 | J96: =MAX(J95+buffer,0)-MAX(J$81+buffer,0) -> 0 | ... AW96: =MAX(AW95+buffer,0)-MAX(AW$81+buffer,0) -> 0
A97: Extra interest | C97: =C96*Inputs!$B$149 -> 0 | D97: =D96*Inputs!$B$149 -> 0 | E97: =E96*Inputs!$B$149 -> 0 | F97: =F96*Inputs!$B$149 -> 0 | G97: =G96*Inputs!$B$149 -> 0 | H97: =H96*Inputs!$B$149 -> 0 | I97: =I96*Inputs!$B$149 -> 0 | J97: =J96*Inputs!$B$149 -> 0 | ... AW97: =AW96*Inputs!$B$149 -> 0
A98: Cash available (after extra interest) | C98: =C95+SUM($C97:C97) -> 184898.75 | D98: =D95+SUM($C97:D97) -> 190464.19 | E98: =E95+SUM($C97:E97) -> 196735.7 | F98: =F95+SUM($C97:F97) -> 203754.49 | G98: =G95+SUM($C97:G97) -> 211563.68 | H98: =H95+SUM($C97:H97) -> 220208.36 | I98: =I95+SUM($C97:I97) -> 229735.67 | J98: =J95+SUM($C97:J97) -> 240194.91 | ... AW98: =AW95+SUM($C97:AW97) -> -1261463.3
A99: Liquidation required | C99: =IF(C98<0,C95,0) -> 0 | D99: =IF(D98+SUM($C99:C99)<0,-(D98+SUM($C99:C99)),0) -> 0 | E99: =IF(E98+SUM($C99:D99)<0,-(E98+SUM($C99:D99)),0) -> 0 | F99: =IF(F98+SUM($C99:E99)<0,-(F98+SUM($C99:E99)),0) -> 0 | G99: =IF(G98+SUM($C99:F99)<0,-(G98+SUM($C99:F99)),0) -> 0 | H99: =IF(H98+SUM($C99:G99)<0,-(H98+SUM($C99:G99)),0) -> 0 | I99: =IF(I98+SUM($C99:H99)<0,-(I98+SUM($C99:H99)),0) -> 0 | J99: =IF(J98+SUM($C99:I99)<0,-(J98+SUM($C99:I99)),0) -> 0 | K99: =IF(K98+SUM($C99:J99)<0,-(K98+SUM($C99:J99)),0) -> 0 | ... AW99: =IF(AW98+SUM($C99:AV99)<0,-(AW98+SUM($C99:AV99)),0) -> 74109.65
A101: =IF(Inputs!$B$165=6,IFERROR(_xlfn.XLOOKUP($B101,Inputs!$B$166:$B$168,Inputs!$A$166:$A$168,,0,1),""),IFERROR(_xlfn.XLOOKUP($B101,Inputs!$C$166:$C$168,Inputs!$A$166:$A$168,,0,1),"")) | B101: 2
A102: b/fwd | C102: =IFERROR(VLOOKUP($A101,$A$52:$H$66,C$1+2,FALSE),0) -> 0 | D102: =C105 -> 0 | E102: =D105 -> 0 | F102: =E105 -> 0 | G102: =F105 -> 0 | H102: =G105 -> 0 | I102: =H105 -> 0 | J102: =I105 -> 0 | K102: =J105 -> 0 | ... AW102: =AV105 -> 0
A103: Disposals | C103: =-IF(SUM(C99:D99)>0,C102,0) -> 0 | D103: =-IF(E99>0,D102,0) -> 0 | E103: =-IF(F99>0,E102,0) -> 0 | F103: =-IF(G99>0,F102,0) -> 0 | G103: =-IF(H99>0,G102,0) -> 0 | H103: =-IF(I99>0,H102,0) -> 0 | I103: =-IF(J99>0,I102,0) -> 0 | J103: =-IF(K99>0,J102,0) -> 0 | K103: =-IF(L99>0,K102,0) -> 0 | ... AW103: =-IF(AX99>0,AW102,0) -> 0
A104: Growth | C104: 0 | D104: =SUM(D102:D103)*princ -> 0 | E104: =SUM(E102:E103)*princ -> 0 | F104: =SUM(F102:F103)*princ -> 0 | G104: =SUM(G102:G103)*princ -> 0 | H104: =SUM(H102:H103)*princ -> 0 | I104: =SUM(I102:I103)*princ -> 0 | J104: =SUM(J102:J103)*princ -> 0 | K104: =SUM(K102:K103)*princ -> 0 | ... AW104: =SUM(AW102:AW103)*princ -> 0
A105: c/fwd | C105: =SUM(C102:C104) -> 0 | D105: =SUM(D102:D104) -> 0 | E105: =SUM(E102:E104) -> 0 | F105: =SUM(F102:F104) -> 0 | G105: =SUM(G102:G104) -> 0 | H105: =SUM(H102:H104) -> 0 | I105: =SUM(I102:I104) -> 0 | J105: =SUM(J102:J104) -> 0 | ... AW105: =SUM(AW102:AW104) -> 0
A106: Disposal costs | C106: =C103*Inputs!$B$163 -> 0 | D106: =D103*Inputs!$B$163 -> 0 | E106: =E103*Inputs!$B$163 -> 0 | F106: =F103*Inputs!$B$163 -> 0 | G106: =G103*Inputs!$B$163 -> 0 | H106: =H103*Inputs!$B$163 -> 0 | I106: =I103*Inputs!$B$163 -> 0 | J106: =J103*Inputs!$B$163 -> 0 | ... AW106: =AW103*Inputs!$B$163 -> 0
A107: Rental income foregone | C107: =IFERROR(-IF(C102=0,VLOOKUP($A101,$7:$10,C$1+2,FALSE),0),0) -> 0 | D107: =IFERROR(-IF(D102=0,VLOOKUP($A101,$7:$10,D$1+2,FALSE),0),0) -> 0 | E107: =IFERROR(-IF(E102=0,VLOOKUP($A101,$7:$10,E$1+2,FALSE),0),0) -> 0 | F107: =IFERROR(-IF(F102=0,VLOOKUP($A101,$7:$10,F$1+2,FALSE),0),0) -> 0 | G107: =IFERROR(-IF(G102=0,VLOOKUP($A101,$7:$10,G$1+2,FALSE),0),0) -> 0 | H107: =IFERROR(-IF(H102=0,VLOOKUP($A101,$7:$10,H$1+2,FALSE),0),0) -> 0 | I107: =IFERROR(-IF(I102=0,VLOOKUP($A101,$7:$10,I$1+2,FALSE),0),0) -> 0 | J107: =IFERROR(-IF(J102=0,VLOOKUP($A101,$7:$10,J$1+2,FALSE),0),0) -> 0 | ... AW107: =IFERROR(-IF(AW102=0,VLOOKUP($A101,$7:$10,AW$1+2,FALSE),0),0) -> 0
A108: Annual cost saved | C108: =IFERROR(IF(C102=0,VLOOKUP($A101,$33:$36,C$1+2,FALSE),0),0) -> 0 | D108: =IFERROR(IF(D102=0,VLOOKUP($A101,$33:$36,D$1+2,FALSE),0),0) -> 0 | E108: =IFERROR(IF(E102=0,VLOOKUP($A101,$33:$36,E$1+2,FALSE),0),0) -> 0 | F108: =IFERROR(IF(F102=0,VLOOKUP($A101,$33:$36,F$1+2,FALSE),0),0) -> 0 | G108: =IFERROR(IF(G102=0,VLOOKUP($A101,$33:$36,G$1+2,FALSE),0),0) -> 0 | H108: =IFERROR(IF(H102=0,VLOOKUP($A101,$33:$36,H$1+2,FALSE),0),0) -> 0 | I108: =IFERROR(IF(I102=0,VLOOKUP($A101,$33:$36,I$1+2,FALSE),0),0) -> 0 | J108: =IFERROR(IF(J102=0,VLOOKUP($A101,$33:$36,J$1+2,FALSE),0),0) -> 0 | ... AW108: =IFERROR(IF(AW102=0,VLOOKUP($A101,$33:$36,AW$1+2,FALSE),0),0) -> 0
A109: Loan repayment | B109: =A101 | C109: =IF(AND(C102>0,C105=0),VLOOKUP($A101,$61:$64,C$1+2,FALSE),0) -> 0 | D109: =IF(AND(D102>0,D105=0),VLOOKUP($A101,$61:$64,D$1+2,FALSE),0) -> 0 | E109: =IF(AND(E102>0,E105=0),VLOOKUP($A101,$61:$64,E$1+2,FALSE),0) -> 0 | F109: =IF(AND(F102>0,F105=0),VLOOKUP($A101,$61:$64,F$1+2,FALSE),0) -> 0 | G109: =IF(AND(G102>0,G105=0),VLOOKUP($A101,$61:$64,G$1+2,FALSE),0) -> 0 | H109: =IF(AND(H102>0,H105=0),VLOOKUP($A101,$61:$64,H$1+2,FALSE),0) -> 0 | I109: =IF(AND(I102>0,I105=0),VLOOKUP($A101,$61:$64,I$1+2,FALSE),0) -> 0 | J109: =IF(AND(J102>0,J105=0),VLOOKUP($A101,$61:$64,J$1+2,FALSE),0) -> 0 | ... AW109: =IF(AND(AW102>0,AW105=0),VLOOKUP($A101,$61:$64,AW$1+2,FALSE),0) -> 0
...
