Workbook
Name A1inc: Inputs!$B$89
Name A2inc: Inputs!$B$94
Name A3inc: Inputs!$B$99
Name A4inc: Inputs!$B$104
Name A5inc: Inputs!$B$109
Name AgeRange: RetNorm_Engine!$C$3:INDEX(RetNorm_Engine!$C$3:$XFD$3, COUNTA(RetNorm_Engine!$C$3:$XFD$3))
Name AssVar: Inputs!$A$307:$C$316
Name buffer: Inputs!$B$279
Name ChartCash_Early: RetEarly_Engine!$C$381:INDEX(RetEarly_Engine!$C$381:$XFD$381, COUNTA(RetEarly_Engine!$C$381:$XFD$381))
Name ChartCash_Norm: RetNorm_Engine!$C$381:INDEX(RetNorm_Engine!$C$381:$XFD$381, COUNTA(RetNorm_Engine!$C$381:$XFD$381))
Name ChartNW_Early: RetEarly_Engine!$C$382:INDEX(RetEarly_Engine!$C$382:$XFD$382, COUNTA(RetEarly_Engine!$C$382:$XFD$382))
Name ChartNW_Norm: RetNorm_Engine!$C$382:INDEX(RetNorm_Engine!$C$382:$XFD$382, COUNTA(RetNorm_Engine!$C$382:$XFD$382))
Name DCoth: Inputs!$B$287
Name DCprop: Inputs!$B$285
Name EndAge: Inputs!$B$254
Name inf: Inputs!$B$265
Name legacy: Inputs!$B$281
Name MthOff: Inputs!$B$303
Name MthRem: Inputs!$B$302
Name princ: Inputs!$B$267
Name ProRate: Inputs!$B$304
Name RetAge: Inputs!$B$19
Name rinc: Inputs!$B$275
Name sincr: Inputs!$B$273
Name stinc: Inputs!$B$271

Sheet Inputs
B1: User inputs | D1: User Tooltips | E1: UI Notes | F1: Excel helpers
A2: QUICK START
A4: Your age | B4: 48 | D4: Must be entered
A6: Current net annual income | B6: 80000 | D6: Net of tax, from employment or self-employment
A8: Total cash balances | B8: 50000 | D8: current and savings accounts, bonds, term deposits
A10: Stock market investments | B10: 30000 | D10: Current market value of equity portfolio
A12: Home current market value | B12: 500000 | D12: Leave blank if not a home owner
A14: Home loan (mortgage)
A15: Balance | B15: 50000 | D15: Leave blank if no mortgage | F15: Months remaining | G15: =IFERROR(NPER(B16/12,-B17,B15),"") -> 215.86799
A16: Interest rate | B16: 0.03 | F16: Years remaining | G16: =IFERROR(G15/12,"") -> 17.988999
A17: Monthly repayment | B17: 300
A19: Statutory retirement age | B19: 65 | D19: Year at which pension starts
A21: Annual pension at retirement | B21: 16000 | D21: Net annual state pension entitlement
A23: Home monthly rent | D23: if not a home owner | E23: show only if not a home owner (B12="")
A25: Annual living expenses | B25: 50000
A28: DEEPER DIVE | E28: Activated only if user wants to
A30: Dependents
A32: Dependent 1
A33: Name | B33: John | D33: Leave blank if none
A34: Annual cost | B34: 2000 | D34: Food, education, healthcare, etc. | E34: Hide until user enters dependent name
A35: Years to support | B35: 3 | D35: Years from now | E35: Hide until user enters dependent name
A37: Dependent 2
A38: Name | B38: Jack | D38: Leave blank if none
A39: Annual cost | B39: 1000 | D39: Food, education, healthcare, etc. | E39: Hide until user enters dependent name
A40: Years to support | B40: 5 | D40: Years from now | E40: Hide until user enters dependent name
A42: Dependent 3
A43: Name | B43: Bill | D43: Leave blank if none
A44: Annual cost | B44: 4000 | D44: Food, education, healthcare, etc. | E44: Hide until user enters dependent name
A45: Years to support | B45: 2 | D45: Years from now | E45: Hide until user enters dependent name
A47: Dependent 4
A48: Name | B48: Stephen | D48: Leave blank if none
A49: Annual cost | B49: 2500 | D49: Food, education, healthcare, etc. | E49: Hide until user enters dependent name
A50: Years to support | B50: 3 | D50: Years from now | E50: Hide until user enters dependent name
A52: Dependent 5
A53: Name | B53: Jane | D53: Leave blank if none
A54: Annual cost | B54: 2860 | D54: Food, education, healthcare, etc. | E54: Hide until user enters dependent name
A55: Years to support | B55: 6 | D55: Years from now | E55: Hide until user enters dependent name
A57: Investment Properties
A59: Property 1
A60: Name | B60: Sliema | D60: Leave blank if none
A61: Market value | B61: 300000 | E61: Hide until user enters property name
A62: Annual costs | B62: 5000 | D62: Repairs, maintenance, etc. | E62: Hide until user enters property name
A64: Property 2
A65: Name | B65: Gzira | D65: Leave blank if none
A66: Market value | B66: 150000 | E66: Hide until user enters property name
A67: Annual costs | B67: 2000 | D67: Repairs, maintenance, etc. | E67: Hide until user enters property name
A69: Property 3
A70: Name | B70: Qormi | D70: Leave blank if none
A71: Market value | B71: 220000 | E71: Hide until user enters property name
A72: Annual costs | B72: 1200 | D72: Repairs, maintenance, etc. | E72: Hide until user enters property name
A74: Property 4
A75: Name | B75: Gudja | D75: Leave blank if none
A76: Market value | B76: 80000 | E76: Hide until user enters property name
A77: Annual costs | B77: 1000 | D77: Repairs, maintenance, etc. | E77: Hide until user enters property name
A79: Property 5
A80: Name | B80: Marsa | D80: Leave blank if none
A81: Market value | B81: 120000 | E81: Hide until user enters property name
A82: Annual costs | B82: 800 | D82: Repairs, maintenance, etc. | E82: Hide until user enters property name
A84: Other Assets of Value
A86: Asset 1
A87: Name | B87: Jewelry | D87: Leave blank if none
A88: Market value | B88: 50000 | E88: Hide until user enters asset name
A89: Annual appreciation / depreciation | B89: 0.02 | D89: posiytive if it asset value grows, negative if asset depreciates | E89: Hide until user enters asset name
A91: Asset 2
A92: Name | B92: Car | D92: Leave blank if none
A93: Market value | B93: 40000 | E93: Hide until user enters asset name
A94: Annual appreciation / depreciation | B94: -0.05 | D94: posiytive if it asset value grows, negative if asset depreciates | E94: Hide until user enters asset name
A96: Asset 3
A97: Name | B97: Painting | D97: Leave blank if none
A98: Market value | B98: 20000 | E98: Hide until user enters asset name
A99: Annual appreciation / depreciation | B99: 0.03 | D99: posiytive if it asset value grows, negative if asset depreciates | E99: Hide until user enters asset name
A101: Asset 4
A102: Name | B102: Boat | D102: Leave blank if none
A103: Market value | B103: 180000 | E103: Hide until user enters asset name
A104: Annual appreciation / depreciation | B104: -0.05 | D104: posiytive if it asset value grows, negative if asset depreciates | E104: Hide until user enters asset name
A106: Asset 5
A107: Name | B107: Antiques | D107: Leave blank if none
A108: Market value | B108: 82000 | E108: Hide until user enters asset name
A109: Annual appreciation / depreciation | B109: 0.02 | D109: posiytive if it asset value grows, negative if asset depreciates | E109: Hide until user enters asset name
A111: Other income
A113: ="Rental income: "&B60 -> Rental income: Sliema | B113: 12000 | D113: net annual after all costs and tax | E113: Show with property name only if name was entered
A114: ="Rental income: "&B65 -> Rental income: Gzira | B114: 10000 | D114: net annual after all costs and tax | E114: Show with property name only if name was entered
A115: ="Rental income: "&B70 -> Rental income: Qormi | B115: 8000 | D115: net annual after all costs and tax | E115: Show with property name only if name was entered
A116: ="Rental income: "&B75 -> Rental income: Gudja | B116: 5000 | D116: net annual after all costs and tax | E116: Show with property name only if name was entered
A117: ="Rental income: "&B80 -> Rental income: Marsa | B117: 6500 | D117: net annual after all costs and tax | E117: Show with property name only if name was entered
A119: Other work income (net annual) | B119: 2000 | D119: Part-time / consulting / side projects etc. Leave blank if none
A120: Continue other work until age | B120: 58 | E120: Show only if other work income entered
A122: Loans
A124: Credit card balances | B124: 1000 | D124: Assumed cleared in Year 1. Leave blank if none
A126: =B60 & " Property" -> Sliema Property
A127: Balance | B127: 50000 | D127: Enter 0 or leave blank if none | F127: Months remaining | G127: =IFERROR(NPER(B128/12,-B129,B127),"") -> 115.21661
A128: Interest rate | B128: 0.03 | F128: Years remaining | G128: =IFERROR(G127/12,"") -> 9.6013842
A129: Monthly repayment | B129: 500
A131: =B65 & " Property" -> Gzira Property
A132: Balance | B132: 8500 | D132: Enter 0 or leave blank if none | F132: Months remaining | G132: =IFERROR(NPER(B133/12,-B134,B132),"") -> 44.117015
A133: Interest rate | B133: 0.02 | F133: Years remaining | G133: =IFERROR(G132/12,"") -> 3.6764179
A134: Monthly repayment | B134: 200
A136: =B70& " Property" -> Qormi Property
A137: Balance | B137: 15000 | D137: Enter 0 or leave blank if none | F137: Months remaining | G137: =IFERROR(NPER(B138/12,-B139,B137),"") -> 69.187439
A138: Interest rate | B138: 0.05 | F138: Years remaining | G138: =IFERROR(G137/12,"") -> 5.7656199
...

Sheet Output
V2: Retire at | AA2: ="Retire at "&RetEarly_Engine!B3 -> Retire at 49
V3: =RetEarly_Engine!B3 -> 49 | AA3: ="Retire at "&RetAge -> Retire at 65

Sheet RetNorm_Engine
B1: 0 | C1: 1 | D1: =C1+1 -> 2 | E1: =D1+1 -> 3 | F1: =E1+1 -> 4 | G1: =F1+1 -> 5 | H1: =G1+1 -> 6 | I1: =H1+1 -> 7 | J1: =I1+1 -> 8 | K1: =J1+1 -> 9 | ... AM1: =AL1+1 -> 37
B2: Year | C2: =YEAR(TODAY()) -> 2026 | D2: =C2+1 -> 2027 | E2: =D2+1 -> 2028 | F2: =E2+1 -> 2029 | G2: =F2+1 -> 2030 | H2: =G2+1 -> 2031 | I2: =H2+1 -> 2032 | J2: =I2+1 -> 2033 | K2: =J2+1 -> 2034 | ... AM2: =AL2+1 -> 2062
B3: =Inputs!B19 -> 65 | C3: =Inputs!B4 -> 48 | D3: =C3+1 -> 49 | E3: =D3+1 -> 50 | F3: =E3+1 -> 51 | G3: =F3+1 -> 52 | H3: =G3+1 -> 53 | I3: =H3+1 -> 54 | J3: =I3+1 -> 55 | K3: =J3+1 -> 56 | ... AM3: =AL3+1 -> 84
A4: Inflows
A5: Net employment / self-employment income | C5: =IF(AND(Inputs!$B$19>C3,$B$3>C3),Inputs!$B$6*(1+sincr)^B1,0)*ProRate -> 60000 | D5: =IF(AND(Inputs!$B$19>D3,$B$3>D3),Inputs!$B$6*(1+sincr)^C1,0) -> 82400 | E5: =IF(AND(Inputs!$B$19>E3,$B$3>E3),Inputs!$B$6*(1+sincr)^D1,0) -> 84872 | F5: =IF(AND(Inputs!$B$19>F3,$B$3>F3),Inputs!$B$6*(1+sincr)^E1,0) -> 87418.16 | G5: =IF(AND(Inputs!$B$19>G3,$B$3>G3),Inputs!$B$6*(1+sincr)^F1,0) -> 90040.705 | H5: =IF(AND(Inputs!$B$19>H3,$B$3>H3),Inputs!$B$6*(1+sincr)^G1,0) -> 92741.926 | I5: =IF(AND(Inputs!$B$19>I3,$B$3>I3),Inputs!$B$6*(1+sincr)^H1,0) -> 95524.184 | J5: =IF(AND(Inputs!$B$19>J3,$B$3>J3),Inputs!$B$6*(1+sincr)^I1,0) -> 98389.909 | K5: =IF(AND(Inputs!$B$19>K3,$B$3>K3),Inputs!$B$6*(1+sincr)^J1,0) -> 101341.61 | ... AM5: =IF(AND(Inputs!$B$19>AM3,$B$3>AM3),Inputs!$B$6*(1+sincr)^AL1,0) -> 0
A6: Net from other work | C6: =IF(C$3<=Inputs!$B$120,Inputs!$B$119,0)*(1+inf)^B$1*ProRate -> 1500 | D6: =IF(D$3<=Inputs!$B$120,Inputs!$B$119,0)*(1+inf)^C$1 -> 2050 | E6: =IF(E$3<=Inputs!$B$120,Inputs!$B$119,0)*(1+inf)^D$1 -> 2101.25 | F6: =IF(F$3<=Inputs!$B$120,Inputs!$B$119,0)*(1+inf)^E$1 -> 2153.7812 | G6: =IF(G$3<=Inputs!$B$120,Inputs!$B$119,0)*(1+inf)^F$1 -> 2207.6258 | H6: =IF(H$3<=Inputs!$B$120,Inputs!$B$119,0)*(1+inf)^G$1 -> 2262.8164 | I6: =IF(I$3<=Inputs!$B$120,Inputs!$B$119,0)*(1+inf)^H$1 -> 2319.3868 | J6: =IF(J$3<=Inputs!$B$120,Inputs!$B$119,0)*(1+inf)^I$1 -> 2377.3715 | K6: =IF(K$3<=Inputs!$B$120,Inputs!$B$119,0)*(1+inf)^J$1 -> 2436.8058 | ... AM6: =IF(AM$3<=Inputs!$B$120,Inputs!$B$119,0)*(1+inf)^AL$1 -> 0
A7: Net rental income from other properties
A8: =TEXT(Inputs!$B$60,"") -> Sliema | C8: =Inputs!B113*ProRate -> 9000 | D8: =C8*(1+rinc) -> 9270 | E8: =D8*(1+rinc) -> 9548.1 | F8: =E8*(1+rinc) -> 9834.543 | G8: =F8*(1+rinc) -> 10129.579 | H8: =G8*(1+rinc) -> 10433.467 | I8: =H8*(1+rinc) -> 10746.471 | J8: =I8*(1+rinc) -> 11068.865 | K8: =J8*(1+rinc) -> 11400.931 | ... AM8: =AL8*(1+rinc) -> 26084.505
A9: =TEXT(Inputs!$B$65,"") -> Gzira | C9: =Inputs!B114*ProRate -> 7500 | D9: =C9*(1+rinc) -> 7725 | E9: =D9*(1+rinc) -> 7956.75 | F9: =E9*(1+rinc) -> 8195.4525 | G9: =F9*(1+rinc) -> 8441.3161 | H9: =G9*(1+rinc) -> 8694.5556 | I9: =H9*(1+rinc) -> 8955.3922 | J9: =I9*(1+rinc) -> 9224.054 | K9: =J9*(1+rinc) -> 9500.7756 | ... AM9: =AL9*(1+rinc) -> 21737.087
A10: =TEXT(Inputs!$B$70,"") -> Qormi | C10: =Inputs!B115*ProRate -> 6000 | D10: =C10*(1+rinc) -> 6180 | E10: =D10*(1+rinc) -> 6365.4 | F10: =E10*(1+rinc) -> 6556.362 | G10: =F10*(1+rinc) -> 6753.0529 | H10: =G10*(1+rinc) -> 6955.6444 | I10: =H10*(1+rinc) -> 7164.3138 | J10: =I10*(1+rinc) -> 7379.2432 | K10: =J10*(1+rinc) -> 7600.6205 | ... AM10: =AL10*(1+rinc) -> 17389.67
A11: =TEXT(Inputs!$B$75,"") -> Gudja | C11: =Inputs!B116*ProRate -> 3750 | D11: =C11*(1+rinc) -> 3862.5 | E11: =D11*(1+rinc) -> 3978.375 | F11: =E11*(1+rinc) -> 4097.7262 | G11: =F11*(1+rinc) -> 4220.658 | H11: =G11*(1+rinc) -> 4347.2778 | I11: =H11*(1+rinc) -> 4477.6961 | J11: =I11*(1+rinc) -> 4612.027 | K11: =J11*(1+rinc) -> 4750.3878 | ... AM11: =AL11*(1+rinc) -> 10868.544
A12: =TEXT(Inputs!$B$80,"") -> Marsa | C12: =Inputs!B117*ProRate -> 4875 | D12: =C12*(1+rinc) -> 5021.25 | E12: =D12*(1+rinc) -> 5171.8875 | F12: =E12*(1+rinc) -> 5327.0441 | G12: =F12*(1+rinc) -> 5486.8554 | H12: =G12*(1+rinc) -> 5651.4611 | I12: =H12*(1+rinc) -> 5821.0049 | J12: =I12*(1+rinc) -> 5995.6351 | K12: =J12*(1+rinc) -> 6175.5041 | ... AM12: =AL12*(1+rinc) -> 14129.107
A13: Full pension | C13: =IF(C$3<Inputs!$B$19,0,Inputs!$B$21)*(1+inf)^B$1*ProRate -> 0 | D13: =IF(D$3<Inputs!$B$19,0,Inputs!$B$21)*(1+inf)^C$1 -> 0 | E13: =IF(E$3<Inputs!$B$19,0,Inputs!$B$21)*(1+inf)^D$1 -> 0 | F13: =IF(F$3<Inputs!$B$19,0,Inputs!$B$21)*(1+inf)^E$1 -> 0 | G13: =IF(G$3<Inputs!$B$19,0,Inputs!$B$21)*(1+inf)^F$1 -> 0 | H13: =IF(H$3<Inputs!$B$19,0,Inputs!$B$21)*(1+inf)^G$1 -> 0 | I13: =IF(I$3<Inputs!$B$19,0,Inputs!$B$21)*(1+inf)^H$1 -> 0 | J13: =IF(J$3<Inputs!$B$19,0,Inputs!$B$21)*(1+inf)^I$1 -> 0 | K13: =IF(K$3<Inputs!$B$19,0,Inputs!$B$21)*(1+inf)^J$1 -> 0 | ... AM13: =IF(AM$3<Inputs!$B$19,0,Inputs!$B$21)*(1+inf)^AL$1 -> 38920.565
A14: Pension reduction from early retirement | C14: =MIN(0,MAX(-IF(C13=0,0,(Inputs!$B$19-INDEX(3:3,MATCH(0,5:5,0))))*Inputs!$B$277*(1+inf)^B$1*ProRate,-C13)) -> 0 | D14: =MIN(0,MAX(-IF(D13=0,0,(Inputs!$B$19-INDEX(3:3,MATCH(0,5:5,0))))*Inputs!$B$277*(1+inf)^C$1,-D13)) -> 0 | E14: =MIN(0,MAX(-IF(E13=0,0,(Inputs!$B$19-INDEX(3:3,MATCH(0,5:5,0))))*Inputs!$B$277*(1+inf)^D$1,-E13)) -> 0 | F14: =MIN(0,MAX(-IF(F13=0,0,(Inputs!$B$19-INDEX(3:3,MATCH(0,5:5,0))))*Inputs!$B$277*(1+inf)^E$1,-F13)) -> 0 | G14: =MIN(0,MAX(-IF(G13=0,0,(Inputs!$B$19-INDEX(3:3,MATCH(0,5:5,0))))*Inputs!$B$277*(1+inf)^F$1,-G13)) -> 0 | H14: =MIN(0,MAX(-IF(H13=0,0,(Inputs!$B$19-INDEX(3:3,MATCH(0,5:5,0))))*Inputs!$B$277*(1+inf)^G$1,-H13)) -> 0 | I14: =MIN(0,MAX(-IF(I13=0,0,(Inputs!$B$19-INDEX(3:3,MATCH(0,5:5,0))))*Inputs!$B$277*(1+inf)^H$1,-I13)) -> 0 | J14: =MIN(0,MAX(-IF(J13=0,0,(Inputs!$B$19-INDEX(3:3,MATCH(0,5:5,0))))*Inputs!$B$277*(1+inf)^I$1,-J13)) -> 0 | K14: =MIN(0,MAX(-IF(K13=0,0,(Inputs!$B$19-INDEX(3:3,MATCH(0,5:5,0))))*Inputs!$B$277*(1+inf)^J$1,-K13)) -> 0 | ... AM14: =MIN(0,MAX(-IF(AM13=0,0,(Inputs!$B$19-INDEX(3:3,MATCH(0,5:5,0))))*Inputs!$B$277*(1+inf)^AL$1,-AM13)) -> 0
A15: Other post-retirement income | C15: =IF(AND(C$3>=Inputs!$B$262,C$3<=Inputs!$B$263),Inputs!$B$261*(1+inf)^B$1,0)*ProRate -> 0 | D15: =IF(AND(D$3>=Inputs!$B$262,D$3<=Inputs!$B$263),Inputs!$B$261*(1+inf)^C$1,0) -> 0 | E15: =IF(AND(E$3>=Inputs!$B$262,E$3<=Inputs!$B$263),Inputs!$B$261*(1+inf)^D$1,0) -> 0 | F15: =IF(AND(F$3>=Inputs!$B$262,F$3<=Inputs!$B$263),Inputs!$B$261*(1+inf)^E$1,0) -> 0 | G15: =IF(AND(G$3>=Inputs!$B$262,G$3<=Inputs!$B$263),Inputs!$B$261*(1+inf)^F$1,0) -> 0 | H15: =IF(AND(H$3>=Inputs!$B$262,H$3<=Inputs!$B$263),Inputs!$B$261*(1+inf)^G$1,0) -> 0 | I15: =IF(AND(I$3>=Inputs!$B$262,I$3<=Inputs!$B$263),Inputs!$B$261*(1+inf)^H$1,0) -> 0 | J15: =IF(AND(J$3>=Inputs!$B$262,J$3<=Inputs!$B$263),Inputs!$B$261*(1+inf)^I$1,0) -> 0 | K15: =IF(AND(K$3>=Inputs!$B$262,K$3<=Inputs!$B$263),Inputs!$B$261*(1+inf)^J$1,0) -> 0 | ... AM15: =IF(AND(AM$3>=Inputs!$B$262,AM$3<=Inputs!$B$263),Inputs!$B$261*(1+inf)^AL$1,0) -> 0
A16: Major one-off income events
A17: =TEXT(Inputs!B184,"") -> Inheritance | C17: =IF(C$2=Inputs!$B186,Inputs!$B185,0)*(1+inf)^B$1 -> 0 | D17: =IF(D$2=Inputs!$B186,Inputs!$B185,0)*(1+inf)^C$1 -> 0 | E17: =IF(E$2=Inputs!$B186,Inputs!$B185,0)*(1+inf)^D$1 -> 0 | F17: =IF(F$2=Inputs!$B186,Inputs!$B185,0)*(1+inf)^E$1 -> 0 | G17: =IF(G$2=Inputs!$B186,Inputs!$B185,0)*(1+inf)^F$1 -> 0 | H17: =IF(H$2=Inputs!$B186,Inputs!$B185,0)*(1+inf)^G$1 -> 0 | I17: =IF(I$2=Inputs!$B186,Inputs!$B185,0)*(1+inf)^H$1 -> 0 | J17: =IF(J$2=Inputs!$B186,Inputs!$B185,0)*(1+inf)^I$1 -> 0 | ... AM17: =IF(AM$2=Inputs!$B186,Inputs!$B185,0)*(1+inf)^AL$1 -> 0
A18: =TEXT(Inputs!B189,"") -> Sell Painting | C18: =IF(C$2=Inputs!$B191,Inputs!$B190,0)*(1+inf)^B$1 -> 0 | D18: =IF(D$2=Inputs!$B191,Inputs!$B190,0)*(1+inf)^C$1 -> 0 | E18: =IF(E$2=Inputs!$B191,Inputs!$B190,0)*(1+inf)^D$1 -> 0 | F18: =IF(F$2=Inputs!$B191,Inputs!$B190,0)*(1+inf)^E$1 -> 10768.906 | G18: =IF(G$2=Inputs!$B191,Inputs!$B190,0)*(1+inf)^F$1 -> 0 | H18: =IF(H$2=Inputs!$B191,Inputs!$B190,0)*(1+inf)^G$1 -> 0 | I18: =IF(I$2=Inputs!$B191,Inputs!$B190,0)*(1+inf)^H$1 -> 0 | J18: =IF(J$2=Inputs!$B191,Inputs!$B190,0)*(1+inf)^I$1 -> 0 | ... AM18: =IF(AM$2=Inputs!$B191,Inputs!$B190,0)*(1+inf)^AL$1 -> 0
A19: =TEXT(Inputs!B194,"") -> Sell Jewels | C19: =IF(C$2=Inputs!$B196,Inputs!$B195,0)*(1+inf)^B$1 -> 0 | D19: =IF(D$2=Inputs!$B196,Inputs!$B195,0)*(1+inf)^C$1 -> 0 | E19: =IF(E$2=Inputs!$B196,Inputs!$B195,0)*(1+inf)^D$1 -> 0 | F19: =IF(F$2=Inputs!$B196,Inputs!$B195,0)*(1+inf)^E$1 -> 0 | G19: =IF(G$2=Inputs!$B196,Inputs!$B195,0)*(1+inf)^F$1 -> 0 | H19: =IF(H$2=Inputs!$B196,Inputs!$B195,0)*(1+inf)^G$1 -> 0 | I19: =IF(I$2=Inputs!$B196,Inputs!$B195,0)*(1+inf)^H$1 -> 5798.4671 | J19: =IF(J$2=Inputs!$B196,Inputs!$B195,0)*(1+inf)^I$1 -> 0 | ... AM19: =IF(AM$2=Inputs!$B196,Inputs!$B195,0)*(1+inf)^AL$1 -> 0
A20: Sale of home (downsizing) | C20: =IF(AND(Inputs!$B$217<>"",C$2=Inputs!$B$217,Inputs!$B$12>0),(IF(B$1=0,Inputs!$B$12*(1+princ)^ProRate,B69*(1+princ)))*(1-DCprop),0) -> 0 | D20: =IF(AND(Inputs!$B$217<>"",D$2=Inputs!$B$217,Inputs!$B$12>0),(IF(C$1=0,Inputs!$B$12*(1+princ)^ProRate,C69*(1+princ)))*(1-DCprop),0) -> 0 | E20: =IF(AND(Inputs!$B$217<>"",E$2=Inputs!$B$217,Inputs!$B$12>0),(IF(D$1=0,Inputs!$B$12*(1+princ)^ProRate,D69*(1+princ)))*(1-DCprop),0) -> 0 | F20: =IF(AND(Inputs!$B$217<>"",F$2=Inputs!$B$217,Inputs!$B$12>0),(IF(E$1=0,Inputs!$B$12*(1+princ)^ProRate,E69*(1+princ)))*(1-DCprop),0) -> 0 | G20: =IF(AND(Inputs!$B$217<>"",G$2=Inputs!$B$217,Inputs!$B$12>0),(IF(F$1=0,Inputs!$B$12*(1+princ)^ProRate,F69*(1+princ)))*(1-DCprop),0) -> 489064.06 | H20: =IF(AND(Inputs!$B$217<>"",H$2=Inputs!$B$217,Inputs!$B$12>0),(IF(G$1=0,Inputs!$B$12*(1+princ)^ProRate,G69*(1+princ)))*(1-DCprop),0) -> 0 | I20: =IF(AND(Inputs!$B$217<>"",I$2=Inputs!$B$217,Inputs!$B$12>0),(IF(H$1=0,Inputs!$B$12*(1+princ)^ProRate,H69*(1+princ)))*(1-DCprop),0) -> 0 | J20: =IF(AND(Inputs!$B$217<>"",J$2=Inputs!$B$217,Inputs!$B$12>0),(IF(I$1=0,Inputs!$B$12*(1+princ)^ProRate,I69*(1+princ)))*(1-DCprop),0) -> 0 | ... AM20: =IF(AND(Inputs!$B$217<>"",AM$2=Inputs!$B$217,Inputs!$B$12>0),(IF(AL$1=0,Inputs!$B$12*(1+princ)^ProRate,AL69*(1+princ)))*(1-DCprop),0) -> 0
A21: Interest on cash balances | C21: =MAX(AVERAGE(C64,C64+SUM(C5:C20)-C61)*Inputs!$B$269,0) -> 1433.4375 | D21: =MAX(AVERAGE(D64,D64+SUM(D5:D20)-D61)*Inputs!$B$269,0) -> 1803.9578 | E21: =MAX(AVERAGE(E64,E64+SUM(E5:E20)-E61)*Inputs!$B$269,0) -> 2224.4666 | F21: =MAX(AVERAGE(F64,F64+SUM(F5:F20)-F61)*Inputs!$B$269,0) -> 2498.7337 | G21: =MAX(AVERAGE(G64,G64+SUM(G5:G20)-G61)*Inputs!$B$269,0) -> 4971.3944 | H21: =MAX(AVERAGE(H64,H64+SUM(H5:H20)-H61)*Inputs!$B$269,0) -> 7993.1111 | I21: =MAX(AVERAGE(I64,I64+SUM(I5:I20)-I61)*Inputs!$B$269,0) -> 9391.8702 | J21: =MAX(AVERAGE(J64,J64+SUM(J5:J20)-J61)*Inputs!$B$269,0) -> 11096.575 | ... AM21: =MAX(AVERAGE(AM64,AM64+SUM(AM5:AM20)-AM61)*Inputs!$B$269,0) -> 61628.564
C22: =SUM(C4:C21) -> 94058.438 | D22: =SUM(D4:D21) -> 118312.71 | E22: =SUM(E4:E21) -> 122218.23 | F22: =SUM(F4:F21) -> 136850.71 | G22: =SUM(G4:G21) -> 621315.25 | H22: =SUM(H4:H21) -> 139080.26 | I22: =SUM(I4:I21) -> 150198.79 | J22: =SUM(J4:J21) -> 150143.68 | ... AM22: =SUM(AM4:AM21) -> 190758.04
A23: Outflows
A24: Credit cards cleared | C24: =Inputs!B124 -> 1000 | D24: 0 | E24: 0 | F24: 0 | G24: 0 | H24: 0 | I24: 0 | J24: 0 | K24: 0 | L24: 0 | M24: 0 | N24: 0 | O24: 0 | P24: 0 | Q24: 0 | R24: 0 | S24: 0 | T24: 0 | U24: 0 | V24: 0 | W24: 0 | X24: 0 | Y24: 0 | Z24: 0 | AA24: 0 | AB24: 0 | AC24: 0 | AD24: 0 | AE24: 0 | AF24: 0 | AG24: 0 | AH24: 0 | AI24: 0 | AJ24: 0 | AK24: 0 | AL24: 0 | AM24: 0
A25: Home loan repayment | C25: =IF(AND(Inputs!$B$217<>"",C$2=Inputs!$B$217,Inputs!$B$12>0,Inputs!$B$15>0),MIN(IF(B$1=0,MthRem,12),MAX(Inputs!$G$15-IF(B$1=0,0,B$1*12+MthOff),0))*Inputs!$B$17+MAX(FV(Inputs!$B$16/12,C$1*12+MthOff,Inputs!$B$17,-Inputs!$B$15),0),IF(AND(Inputs!$B$217<>"",C$2>Inputs!$B$217,Inputs!$B$12>0),0,MIN(IF(B$1=0,MthRem,12),MAX(Inputs!$G$15-IF(B$1=0,0,B$1*12+MthOff),0))*Inputs!$B$17)) -> 2700 | D25: =IF(AND(Inputs!$B$217<>"",D$2=Inputs!$B$217,Inputs!$B$12>0,Inputs!$B$15>0),MIN(IF(C$1=0,MthRem,12),MAX(Inputs!$G$15-IF(C$1=0,0,C$1*12+MthOff),0))*Inputs!$B$17+MAX(FV(Inputs!$B$16/12,D$1*12+MthOff,Inputs!$B$17,-Inputs!$B$15),0),IF(AND(Inputs!$B$217<>"",D$2>Inputs!$B$217,Inputs!$B$12>0),0,MIN(IF(C$1=0,MthRem,12),MAX(Inputs!$G$15-IF(C$1=0,0,C$1*12+MthOff),0))*Inputs!$B$17)) -> 3600 | E25: =IF(AND(Inputs!$B$217<>"",E$2=Inputs!$B$217,Inputs!$B$12>0,Inputs!$B$15>0),MIN(IF(D$1=0,MthRem,12),MAX(Inputs!$G$15-IF(D$1=0,0,D$1*12+MthOff),0))*Inputs!$B$17+MAX(FV(Inputs!$B$16/12,E$1*12+MthOff,Inputs!$B$17,-Inputs!$B$15),0),IF(AND(Inputs!$B$217<>"",E$2>Inputs!$B$217,Inputs!$B$12>0),0,MIN(IF(D$1=0,MthRem,12),MAX(Inputs!$G$15-IF(D$1=0,0,D$1*12+MthOff),0))*Inputs!$B$17)) -> 3600 | F25: =IF(AND(Inputs!$B$217<>"",F$2=Inputs!$B$217,Inputs!$B$12>0,Inputs!$B$15>0),MIN(IF(E$1=0,MthRem,12),MAX(Inputs!$G$15-IF(E$1=0,0,E$1*12+MthOff),0))*Inputs!$B$17+MAX(FV(Inputs!$B$16/12,F$1*12+MthOff,Inputs!$B$17,-Inputs!$B$15),0),IF(AND(Inputs!$B$217<>"",F$2>Inputs!$B$217,Inputs!$B$12>0),0,MIN(IF(E$1=0,MthRem,12),MAX(Inputs!$G$15-IF(E$1=0,0,E$1*12+MthOff),0))*Inputs!$B$17)) -> 3600 | G25: =IF(AND(Inputs!$B$217<>"",G$2=Inputs!$B$217,Inputs!$B$12>0,Inputs!$B$15>0),MIN(IF(F$1=0,MthRem,12),MAX(Inputs!$G$15-IF(F$1=0,0,F$1*12+MthOff),0))*Inputs!$B$17+MAX(FV(Inputs!$B$16/12,G$1*12+MthOff,Inputs!$B$17,-Inputs!$B$15),0),IF(AND(Inputs!$B$217<>"",G$2>Inputs!$B$217,Inputs!$B$12>0),0,MIN(IF(F$1=0,MthRem,12),MAX(Inputs!$G$15-IF(F$1=0,0,F$1*12+MthOff),0))*Inputs!$B$17)) -> 42893.638 | H25: =IF(AND(Inputs!$B$217<>"",H$2=Inputs!$B$217,Inputs!$B$12>0,Inputs!$B$15>0),MIN(IF(G$1=0,MthRem,12),MAX(Inputs!$G$15-IF(G$1=0,0,G$1*12+MthOff),0))*Inputs!$B$17+MAX(FV(Inputs!$B$16/12,H$1*12+MthOff,Inputs!$B$17,-Inputs!$B$15),0),IF(AND(Inputs!$B$217<>"",H$2>Inputs!$B$217,Inputs!$B$12>0),0,MIN(IF(G$1=0,MthRem,12),MAX(Inputs!$G$15-IF(G$1=0,0,G$1*12+MthOff),0))*Inputs!$B$17)) -> 0 | I25: =IF(AND(Inputs!$B$217<>"",I$2=Inputs!$B$217,Inputs!$B$12>0,Inputs!$B$15>0),MIN(IF(H$1=0,MthRem,12),MAX(Inputs!$G$15-IF(H$1=0,0,H$1*12+MthOff),0))*Inputs!$B$17+MAX(FV(Inputs!$B$16/12,I$1*12+MthOff,Inputs!$B$17,-Inputs!$B$15),0),IF(AND(Inputs!$B$217<>"",I$2>Inputs!$B$217,Inputs!$B$12>0),0,MIN(IF(H$1=0,MthRem,12),MAX(Inputs!$G$15-IF(H$1=0,0,H$1*12+MthOff),0))*Inputs!$B$17)) -> 0 | J25: =IF(AND(Inputs!$B$217<>"",J$2=Inputs!$B$217,Inputs!$B$12>0,Inputs!$B$15>0),MIN(IF(I$1=0,MthRem,12),MAX(Inputs!$G$15-IF(I$1=0,0,I$1*12+MthOff),0))*Inputs!$B$17+MAX(FV(Inputs!$B$16/12,J$1*12+MthOff,Inputs!$B$17,-Inputs!$B$15),0),IF(AND(Inputs!$B$217<>"",J$2>Inputs!$B$217,Inputs!$B$12>0),0,MIN(IF(I$1=0,MthRem,12),MAX(Inputs!$G$15-IF(I$1=0,0,I$1*12+MthOff),0))*Inputs!$B$17)) -> 0 | ... AM25: =IF(AND(Inputs!$B$217<>"",AM$2=Inputs!$B$217,Inputs!$B$12>0,Inputs!$B$15>0),MIN(IF(AL$1=0,MthRem,12),MAX(Inputs!$G$15-IF(AL$1=0,0,AL$1*12+MthOff),0))*Inputs!$B$17+MAX(FV(Inputs!$B$16/12,AM$1*12+MthOff,Inputs!$B$17,-Inputs!$B$15),0),IF(AND(Inputs!$B$217<>"",AM$2>Inputs!$B$217,Inputs!$B$12>0),0,MIN(IF(AL$1=0,MthRem,12),MAX(Inputs!$G$15-IF(AL$1=0,0,AL$1*12+MthOff),0))*Inputs!$B$17)) -> 0
A26: Other asset loans repayments
A27: =TEXT(Inputs!$B$60,"") -> Sliema | C27: =MIN(IF(B$1=0,MthRem,12), MAX(Inputs!$G$127-IF(B$1=0,0,B$1*12+MthOff), 0))*Inputs!$B$129 -> 4500 | D27: =MIN(IF(C$1=0,MthRem,12), MAX(Inputs!$G$127-IF(C$1=0,0,C$1*12+MthOff), 0))*Inputs!$B$129 -> 6000 | E27: =MIN(IF(D$1=0,MthRem,12), MAX(Inputs!$G$127-IF(D$1=0,0,D$1*12+MthOff), 0))*Inputs!$B$129 -> 6000 | F27: =MIN(IF(E$1=0,MthRem,12), MAX(Inputs!$G$127-IF(E$1=0,0,E$1*12+MthOff), 0))*Inputs!$B$129 -> 6000 | G27: =MIN(IF(F$1=0,MthRem,12), MAX(Inputs!$G$127-IF(F$1=0,0,F$1*12+MthOff), 0))*Inputs!$B$129 -> 6000 | H27: =MIN(IF(G$1=0,MthRem,12), MAX(Inputs!$G$127-IF(G$1=0,0,G$1*12+MthOff), 0))*Inputs!$B$129 -> 6000 | I27: =MIN(IF(H$1=0,MthRem,12), MAX(Inputs!$G$127-IF(H$1=0,0,H$1*12+MthOff), 0))*Inputs!$B$129 -> 6000 | J27: =MIN(IF(I$1=0,MthRem,12), MAX(Inputs!$G$127-IF(I$1=0,0,I$1*12+MthOff), 0))*Inputs!$B$129 -> 6000 | ... AM27: =MIN(IF(AL$1=0,MthRem,12), MAX(Inputs!$G$127-IF(AL$1=0,0,AL$1*12+MthOff), 0))*Inputs!$B$129 -> 0
A28: =TEXT(Inputs!$B$65,"") -> Gzira | C28: =MIN(IF(B$1=0,MthRem,12), MAX(Inputs!$G$132-IF(B$1=0,0,B$1*12+MthOff), 0))*Inputs!$B$134 -> 1800 | D28: =MIN(IF(C$1=0,MthRem,12), MAX(Inputs!$G$132-IF(C$1=0,0,C$1*12+MthOff), 0))*Inputs!$B$134 -> 2400 | E28: =MIN(IF(D$1=0,MthRem,12), MAX(Inputs!$G$132-IF(D$1=0,0,D$1*12+MthOff), 0))*Inputs!$B$134 -> 2400 | F28: =MIN(IF(E$1=0,MthRem,12), MAX(Inputs!$G$132-IF(E$1=0,0,E$1*12+MthOff), 0))*Inputs!$B$134 -> 2223.4029 | G28: =MIN(IF(F$1=0,MthRem,12), MAX(Inputs!$G$132-IF(F$1=0,0,F$1*12+MthOff), 0))*Inputs!$B$134 -> 0 | H28: =MIN(IF(G$1=0,MthRem,12), MAX(Inputs!$G$132-IF(G$1=0,0,G$1*12+MthOff), 0))*Inputs!$B$134 -> 0 | I28: =MIN(IF(H$1=0,MthRem,12), MAX(Inputs!$G$132-IF(H$1=0,0,H$1*12+MthOff), 0))*Inputs!$B$134 -> 0 | J28: =MIN(IF(I$1=0,MthRem,12), MAX(Inputs!$G$132-IF(I$1=0,0,I$1*12+MthOff), 0))*Inputs!$B$134 -> 0 | ... AM28: =MIN(IF(AL$1=0,MthRem,12), MAX(Inputs!$G$132-IF(AL$1=0,0,AL$1*12+MthOff), 0))*Inputs!$B$134 -> 0
A29: =TEXT(Inputs!$B$70,"") -> Qormi | C29: =MIN(IF(B$1=0,MthRem,12), MAX(Inputs!$G$137-IF(B$1=0,0,B$1*12+MthOff), 0))*Inputs!$B$139 -> 2250 | D29: =MIN(IF(C$1=0,MthRem,12), MAX(Inputs!$G$137-IF(C$1=0,0,C$1*12+MthOff), 0))*Inputs!$B$139 -> 3000 | E29: =MIN(IF(D$1=0,MthRem,12), MAX(Inputs!$G$137-IF(D$1=0,0,D$1*12+MthOff), 0))*Inputs!$B$139 -> 3000 | F29: =MIN(IF(E$1=0,MthRem,12), MAX(Inputs!$G$137-IF(E$1=0,0,E$1*12+MthOff), 0))*Inputs!$B$139 -> 3000 | G29: =MIN(IF(F$1=0,MthRem,12), MAX(Inputs!$G$137-IF(F$1=0,0,F$1*12+MthOff), 0))*Inputs!$B$139 -> 3000 | H29: =MIN(IF(G$1=0,MthRem,12), MAX(Inputs!$G$137-IF(G$1=0,0,G$1*12+MthOff), 0))*Inputs!$B$139 -> 3000 | I29: =MIN(IF(H$1=0,MthRem,12), MAX(Inputs!$G$137-IF(H$1=0,0,H$1*12+MthOff), 0))*Inputs!$B$139 -> 46.859686 | J29: =MIN(IF(I$1=0,MthRem,12), MAX(Inputs!$G$137-IF(I$1=0,0,I$1*12+MthOff), 0))*Inputs!$B$139 -> 0 | ... AM29: =MIN(IF(AL$1=0,MthRem,12), MAX(Inputs!$G$137-IF(AL$1=0,0,AL$1*12+MthOff), 0))*Inputs!$B$139 -> 0
A30: =TEXT(Inputs!$B$75,"") -> Gudja | C30: =MIN(IF(B$1=0,MthRem,12), MAX(Inputs!$G$142-IF(B$1=0,0,B$1*12+MthOff), 0))*Inputs!$B$144 -> 720 | D30: =MIN(IF(C$1=0,MthRem,12), MAX(Inputs!$G$142-IF(C$1=0,0,C$1*12+MthOff), 0))*Inputs!$B$144 -> 960 | E30: =MIN(IF(D$1=0,MthRem,12), MAX(Inputs!$G$142-IF(D$1=0,0,D$1*12+MthOff), 0))*Inputs!$B$144 -> 960 | F30: =MIN(IF(E$1=0,MthRem,12), MAX(Inputs!$G$142-IF(E$1=0,0,E$1*12+MthOff), 0))*Inputs!$B$144 -> 960 | G30: =MIN(IF(F$1=0,MthRem,12), MAX(Inputs!$G$142-IF(F$1=0,0,F$1*12+MthOff), 0))*Inputs!$B$144 -> 960 | H30: =MIN(IF(G$1=0,MthRem,12), MAX(Inputs!$G$142-IF(G$1=0,0,G$1*12+MthOff), 0))*Inputs!$B$144 -> 368.25859 | I30: =MIN(IF(H$1=0,MthRem,12), MAX(Inputs!$G$142-IF(H$1=0,0,H$1*12+MthOff), 0))*Inputs!$B$144 -> 0 | J30: =MIN(IF(I$1=0,MthRem,12), MAX(Inputs!$G$142-IF(I$1=0,0,I$1*12+MthOff), 0))*Inputs!$B$144 -> 0 | ... AM30: =MIN(IF(AL$1=0,MthRem,12), MAX(Inputs!$G$142-IF(AL$1=0,0,AL$1*12+MthOff), 0))*Inputs!$B$144 -> 0
A31: =TEXT(Inputs!$B$80,"") -> Marsa | C31: =MIN(IF(B$1=0,MthRem,12), MAX(Inputs!$G$147-IF(B$1=0,0,B$1*12+MthOff), 0))*Inputs!$B$149 -> 1080 | D31: =MIN(IF(C$1=0,MthRem,12), MAX(Inputs!$G$147-IF(C$1=0,0,C$1*12+MthOff), 0))*Inputs!$B$149 -> 1440 | E31: =MIN(IF(D$1=0,MthRem,12), MAX(Inputs!$G$147-IF(D$1=0,0,D$1*12+MthOff), 0))*Inputs!$B$149 -> 1440 | F31: =MIN(IF(E$1=0,MthRem,12), MAX(Inputs!$G$147-IF(E$1=0,0,E$1*12+MthOff), 0))*Inputs!$B$149 -> 1440 | G31: =MIN(IF(F$1=0,MthRem,12), MAX(Inputs!$G$147-IF(F$1=0,0,F$1*12+MthOff), 0))*Inputs!$B$149 -> 1440 | H31: =MIN(IF(G$1=0,MthRem,12), MAX(Inputs!$G$147-IF(G$1=0,0,G$1*12+MthOff), 0))*Inputs!$B$149 -> 1440 | I31: =MIN(IF(H$1=0,MthRem,12), MAX(Inputs!$G$147-IF(H$1=0,0,H$1*12+MthOff), 0))*Inputs!$B$149 -> 1440 | J31: =MIN(IF(I$1=0,MthRem,12), MAX(Inputs!$G$147-IF(I$1=0,0,I$1*12+MthOff), 0))*Inputs!$B$149 -> 909.24881 | ... AM31: =MIN(IF(AL$1=0,MthRem,12), MAX(Inputs!$G$147-IF(AL$1=0,0,AL$1*12+MthOff), 0))*Inputs!$B$149 -> 0
A32: =TEXT(Inputs!$B$87,"") -> Jewelry | C32: =MIN(IF(B$1=0,MthRem,12), MAX(Inputs!$G$152-IF(B$1=0,0,B$1*12+MthOff), 0))*Inputs!$B$154 -> 675 | D32: =MIN(IF(C$1=0,MthRem,12), MAX(Inputs!$G$152-IF(C$1=0,0,C$1*12+MthOff), 0))*Inputs!$B$154 -> 900 | E32: =MIN(IF(D$1=0,MthRem,12), MAX(Inputs!$G$152-IF(D$1=0,0,D$1*12+MthOff), 0))*Inputs!$B$154 -> 900 | F32: =MIN(IF(E$1=0,MthRem,12), MAX(Inputs!$G$152-IF(E$1=0,0,E$1*12+MthOff), 0))*Inputs!$B$154 -> 138.60288 | G32: =MIN(IF(F$1=0,MthRem,12), MAX(Inputs!$G$152-IF(F$1=0,0,F$1*12+MthOff), 0))*Inputs!$B$154 -> 0 | H32: =MIN(IF(G$1=0,MthRem,12), MAX(Inputs!$G$152-IF(G$1=0,0,G$1*12+MthOff), 0))*Inputs!$B$154 -> 0 | I32: =MIN(IF(H$1=0,MthRem,12), MAX(Inputs!$G$152-IF(H$1=0,0,H$1*12+MthOff), 0))*Inputs!$B$154 -> 0 | J32: =MIN(IF(I$1=0,MthRem,12), MAX(Inputs!$G$152-IF(I$1=0,0,I$1*12+MthOff), 0))*Inputs!$B$154 -> 0 | ... AM32: =MIN(IF(AL$1=0,MthRem,12), MAX(Inputs!$G$152-IF(AL$1=0,0,AL$1*12+MthOff), 0))*Inputs!$B$154 -> 0
A33: =TEXT(Inputs!$B$92,"") -> Car | C33: =MIN(IF(B$1=0,MthRem,12), MAX(Inputs!$G$157-IF(B$1=0,0,B$1*12+MthOff), 0))*Inputs!$B$159 -> 774 | D33: =MIN(IF(C$1=0,MthRem,12), MAX(Inputs!$G$157-IF(C$1=0,0,C$1*12+MthOff), 0))*Inputs!$B$159 -> 1032 | E33: =MIN(IF(D$1=0,MthRem,12), MAX(Inputs!$G$157-IF(D$1=0,0,D$1*12+MthOff), 0))*Inputs!$B$159 -> 1032 | F33: =MIN(IF(E$1=0,MthRem,12), MAX(Inputs!$G$157-IF(E$1=0,0,E$1*12+MthOff), 0))*Inputs!$B$159 -> 1032 | G33: =MIN(IF(F$1=0,MthRem,12), MAX(Inputs!$G$157-IF(F$1=0,0,F$1*12+MthOff), 0))*Inputs!$B$159 -> 1032 | H33: =MIN(IF(G$1=0,MthRem,12), MAX(Inputs!$G$157-IF(G$1=0,0,G$1*12+MthOff), 0))*Inputs!$B$159 -> 1032 | I33: =MIN(IF(H$1=0,MthRem,12), MAX(Inputs!$G$157-IF(H$1=0,0,H$1*12+MthOff), 0))*Inputs!$B$159 -> 449.79405 | J33: =MIN(IF(I$1=0,MthRem,12), MAX(Inputs!$G$157-IF(I$1=0,0,I$1*12+MthOff), 0))*Inputs!$B$159 -> 0 | ... AM33: =MIN(IF(AL$1=0,MthRem,12), MAX(Inputs!$G$157-IF(AL$1=0,0,AL$1*12+MthOff), 0))*Inputs!$B$159 -> 0
A34: =TEXT(Inputs!$B$97,"") -> Painting | C34: =MIN(IF(B$1=0,MthRem,12), MAX(Inputs!$G$162-IF(B$1=0,0,B$1*12+MthOff), 0))*Inputs!$B$164 -> 1125 | D34: =MIN(IF(C$1=0,MthRem,12), MAX(Inputs!$G$162-IF(C$1=0,0,C$1*12+MthOff), 0))*Inputs!$B$164 -> 1500 | E34: =MIN(IF(D$1=0,MthRem,12), MAX(Inputs!$G$162-IF(D$1=0,0,D$1*12+MthOff), 0))*Inputs!$B$164 -> 1500 | F34: =MIN(IF(E$1=0,MthRem,12), MAX(Inputs!$G$162-IF(E$1=0,0,E$1*12+MthOff), 0))*Inputs!$B$164 -> 1500 | G34: =MIN(IF(F$1=0,MthRem,12), MAX(Inputs!$G$162-IF(F$1=0,0,F$1*12+MthOff), 0))*Inputs!$B$164 -> 1500 | H34: =MIN(IF(G$1=0,MthRem,12), MAX(Inputs!$G$162-IF(G$1=0,0,G$1*12+MthOff), 0))*Inputs!$B$164 -> 1500 | I34: =MIN(IF(H$1=0,MthRem,12), MAX(Inputs!$G$162-IF(H$1=0,0,H$1*12+MthOff), 0))*Inputs!$B$164 -> 23.429843 | J34: =MIN(IF(I$1=0,MthRem,12), MAX(Inputs!$G$162-IF(I$1=0,0,I$1*12+MthOff), 0))*Inputs!$B$164 -> 0 | ... AM34: =MIN(IF(AL$1=0,MthRem,12), MAX(Inputs!$G$162-IF(AL$1=0,0,AL$1*12+MthOff), 0))*Inputs!$B$164 -> 0
A35: =TEXT(Inputs!$B$102,"") -> Boat | C35: =MIN(IF(B$1=0,MthRem,12), MAX(Inputs!$G$167-IF(B$1=0,0,B$1*12+MthOff), 0))*Inputs!$B$169 -> 5616 | D35: =MIN(IF(C$1=0,MthRem,12), MAX(Inputs!$G$167-IF(C$1=0,0,C$1*12+MthOff), 0))*Inputs!$B$169 -> 7488 | E35: =MIN(IF(D$1=0,MthRem,12), MAX(Inputs!$G$167-IF(D$1=0,0,D$1*12+MthOff), 0))*Inputs!$B$169 -> 7488 | F35: =MIN(IF(E$1=0,MthRem,12), MAX(Inputs!$G$167-IF(E$1=0,0,E$1*12+MthOff), 0))*Inputs!$B$169 -> 7488 | G35: =MIN(IF(F$1=0,MthRem,12), MAX(Inputs!$G$167-IF(F$1=0,0,F$1*12+MthOff), 0))*Inputs!$B$169 -> 7488 | H35: =MIN(IF(G$1=0,MthRem,12), MAX(Inputs!$G$167-IF(G$1=0,0,G$1*12+MthOff), 0))*Inputs!$B$169 -> 7488 | I35: =MIN(IF(H$1=0,MthRem,12), MAX(Inputs!$G$167-IF(H$1=0,0,H$1*12+MthOff), 0))*Inputs!$B$169 -> 5289.2926 | J35: =MIN(IF(I$1=0,MthRem,12), MAX(Inputs!$G$167-IF(I$1=0,0,I$1*12+MthOff), 0))*Inputs!$B$169 -> 0 | ... AM35: =MIN(IF(AL$1=0,MthRem,12), MAX(Inputs!$G$167-IF(AL$1=0,0,AL$1*12+MthOff), 0))*Inputs!$B$169 -> 0
A36: =TEXT(Inputs!$B$107,"") -> Antiques | C36: =MIN(IF(B$1=0,MthRem,12), MAX(Inputs!$G$172-IF(B$1=0,0,B$1*12+MthOff), 0))*Inputs!$B$174 -> 990 | D36: =MIN(IF(C$1=0,MthRem,12), MAX(Inputs!$G$172-IF(C$1=0,0,C$1*12+MthOff), 0))*Inputs!$B$174 -> 1320 | E36: =MIN(IF(D$1=0,MthRem,12), MAX(Inputs!$G$172-IF(D$1=0,0,D$1*12+MthOff), 0))*Inputs!$B$174 -> 1320 | F36: =MIN(IF(E$1=0,MthRem,12), MAX(Inputs!$G$172-IF(E$1=0,0,E$1*12+MthOff), 0))*Inputs!$B$174 -> 349.16176 | G36: =MIN(IF(F$1=0,MthRem,12), MAX(Inputs!$G$172-IF(F$1=0,0,F$1*12+MthOff), 0))*Inputs!$B$174 -> 0 | H36: =MIN(IF(G$1=0,MthRem,12), MAX(Inputs!$G$172-IF(G$1=0,0,G$1*12+MthOff), 0))*Inputs!$B$174 -> 0 | I36: =MIN(IF(H$1=0,MthRem,12), MAX(Inputs!$G$172-IF(H$1=0,0,H$1*12+MthOff), 0))*Inputs!$B$174 -> 0 | J36: =MIN(IF(I$1=0,MthRem,12), MAX(Inputs!$G$172-IF(I$1=0,0,I$1*12+MthOff), 0))*Inputs!$B$174 -> 0 | ... AM36: =MIN(IF(AL$1=0,MthRem,12), MAX(Inputs!$G$172-IF(AL$1=0,0,AL$1*12+MthOff), 0))*Inputs!$B$174 -> 0
A37: Other loan repayment | C37: =MIN(IF(B$1=0,MthRem,12), MAX(Inputs!$G$177-IF(B$1=0,0,B$1*12+MthOff), 0))*Inputs!$B$179 -> 450 | D37: =MIN(IF(C$1=0,MthRem,12), MAX(Inputs!$G$177-IF(C$1=0,0,C$1*12+MthOff), 0))*Inputs!$B$179 -> 600 | E37: =MIN(IF(D$1=0,MthRem,12), MAX(Inputs!$G$177-IF(D$1=0,0,D$1*12+MthOff), 0))*Inputs!$B$179 -> 600 | F37: =MIN(IF(E$1=0,MthRem,12), MAX(Inputs!$G$177-IF(E$1=0,0,E$1*12+MthOff), 0))*Inputs!$B$179 -> 600 | G37: =MIN(IF(F$1=0,MthRem,12), MAX(Inputs!$G$177-IF(F$1=0,0,F$1*12+MthOff), 0))*Inputs!$B$179 -> 600 | H37: =MIN(IF(G$1=0,MthRem,12), MAX(Inputs!$G$177-IF(G$1=0,0,G$1*12+MthOff), 0))*Inputs!$B$179 -> 600 | I37: =MIN(IF(H$1=0,MthRem,12), MAX(Inputs!$G$177-IF(H$1=0,0,H$1*12+MthOff), 0))*Inputs!$B$179 -> 600 | J37: =MIN(IF(I$1=0,MthRem,12), MAX(Inputs!$G$177-IF(I$1=0,0,I$1*12+MthOff), 0))*Inputs!$B$179 -> 600 | ... AM37: =MIN(IF(AL$1=0,MthRem,12), MAX(Inputs!$G$177-IF(AL$1=0,0,AL$1*12+MthOff), 0))*Inputs!$B$179 -> 0
A38: Dependents cost
A39: =TEXT(Inputs!B33,"") -> John | C39: =IF(Inputs!$B$35>=C$1,Inputs!$B$34,0)*(1+inf)^B$1*ProRate -> 1500 | D39: =IF(Inputs!$B$35>=D$1,Inputs!$B$34,0)*(1+inf)^C$1 -> 2050 | E39: =IF(Inputs!$B$35>=E$1,Inputs!$B$34,0)*(1+inf)^D$1 -> 2101.25 | F39: =IF(Inputs!$B$35>=F$1,Inputs!$B$34,0)*(1+inf)^E$1 -> 0 | G39: =IF(Inputs!$B$35>=G$1,Inputs!$B$34,0)*(1+inf)^F$1 -> 0 | H39: =IF(Inputs!$B$35>=H$1,Inputs!$B$34,0)*(1+inf)^G$1 -> 0 | I39: =IF(Inputs!$B$35>=I$1,Inputs!$B$34,0)*(1+inf)^H$1 -> 0 | J39: =IF(Inputs!$B$35>=J$1,Inputs!$B$34,0)*(1+inf)^I$1 -> 0 | K39: =IF(Inputs!$B$35>=K$1,Inputs!$B$34,0)*(1+inf)^J$1 -> 0 | ... AM39: =IF(Inputs!$B$35>=AM$1,Inputs!$B$34,0)*(1+inf)^AL$1 -> 0
A40: =TEXT(Inputs!B38,"") -> Jack | C40: =IF(Inputs!$B$40>=C$1,Inputs!$B$39,0)*(1+inf)^B$1*ProRate -> 750 | D40: =IF(Inputs!$B$40>=D$1,Inputs!$B$39,0)*(1+inf)^C$1 -> 1025 | E40: =IF(Inputs!$B$40>=E$1,Inputs!$B$39,0)*(1+inf)^D$1 -> 1050.625 | F40: =IF(Inputs!$B$40>=F$1,Inputs!$B$39,0)*(1+inf)^E$1 -> 1076.8906 | G40: =IF(Inputs!$B$40>=G$1,Inputs!$B$39,0)*(1+inf)^F$1 -> 1103.8129 | H40: =IF(Inputs!$B$40>=H$1,Inputs!$B$39,0)*(1+inf)^G$1 -> 0 | I40: =IF(Inputs!$B$40>=I$1,Inputs!$B$39,0)*(1+inf)^H$1 -> 0 | J40: =IF(Inputs!$B$40>=J$1,Inputs!$B$39,0)*(1+inf)^I$1 -> 0 | K40: =IF(Inputs!$B$40>=K$1,Inputs!$B$39,0)*(1+inf)^J$1 -> 0 | ... AM40: =IF(Inputs!$B$40>=AM$1,Inputs!$B$39,0)*(1+inf)^AL$1 -> 0
A41: =TEXT(Inputs!B43,"") -> Bill | C41: =IF(Inputs!$B$45>=C$1,Inputs!$B$44,0)*(1+inf)^B$1*ProRate -> 3000 | D41: =IF(Inputs!$B$45>=D$1,Inputs!$B$44,0)*(1+inf)^C$1 -> 4100 | E41: =IF(Inputs!$B$45>=E$1,Inputs!$B$44,0)*(1+inf)^D$1 -> 0 | F41: =IF(Inputs!$B$45>=F$1,Inputs!$B$44,0)*(1+inf)^E$1 -> 0 | G41: =IF(Inputs!$B$45>=G$1,Inputs!$B$44,0)*(1+inf)^F$1 -> 0 | H41: =IF(Inputs!$B$45>=H$1,Inputs!$B$44,0)*(1+inf)^G$1 -> 0 | I41: =IF(Inputs!$B$45>=I$1,Inputs!$B$44,0)*(1+inf)^H$1 -> 0 | J41: =IF(Inputs!$B$45>=J$1,Inputs!$B$44,0)*(1+inf)^I$1 -> 0 | K41: =IF(Inputs!$B$45>=K$1,Inputs!$B$44,0)*(1+inf)^J$1 -> 0 | ... AM41: =IF(Inputs!$B$45>=AM$1,Inputs!$B$44,0)*(1+inf)^AL$1 -> 0
A42: =TEXT(Inputs!B48,"") -> Stephen | C42: =IF(Inputs!$B$50>=C$1,Inputs!$B$49,0)*(1+inf)^B$1*ProRate -> 1875 | D42: =IF(Inputs!$B$50>=D$1,Inputs!$B$49,0)*(1+inf)^C$1 -> 2562.5 | E42: =IF(Inputs!$B$50>=E$1,Inputs!$B$49,0)*(1+inf)^D$1 -> 2626.5625 | F42: =IF(Inputs!$B$50>=F$1,Inputs!$B$49,0)*(1+inf)^E$1 -> 0 | G42: =IF(Inputs!$B$50>=G$1,Inputs!$B$49,0)*(1+inf)^F$1 -> 0 | H42: =IF(Inputs!$B$50>=H$1,Inputs!$B$49,0)*(1+inf)^G$1 -> 0 | I42: =IF(Inputs!$B$50>=I$1,Inputs!$B$49,0)*(1+inf)^H$1 -> 0 | J42: =IF(Inputs!$B$50>=J$1,Inputs!$B$49,0)*(1+inf)^I$1 -> 0 | K42: =IF(Inputs!$B$50>=K$1,Inputs!$B$49,0)*(1+inf)^J$1 -> 0 | ... AM42: =IF(Inputs!$B$50>=AM$1,Inputs!$B$49,0)*(1+inf)^AL$1 -> 0
A43: =TEXT(Inputs!B53,"") -> Jane | C43: =IF(Inputs!$B$55>=C$1,Inputs!$B$54,0)*(1+inf)^B$1*ProRate -> 2145 | D43: =IF(Inputs!$B$55>=D$1,Inputs!$B$54,0)*(1+inf)^C$1 -> 2931.5 | E43: =IF(Inputs!$B$55>=E$1,Inputs!$B$54,0)*(1+inf)^D$1 -> 3004.7875 | F43: =IF(Inputs!$B$55>=F$1,Inputs!$B$54,0)*(1+inf)^E$1 -> 3079.9072 | G43: =IF(Inputs!$B$55>=G$1,Inputs!$B$54,0)*(1+inf)^F$1 -> 3156.9049 | H43: =IF(Inputs!$B$55>=H$1,Inputs!$B$54,0)*(1+inf)^G$1 -> 3235.8275 | I43: =IF(Inputs!$B$55>=I$1,Inputs!$B$54,0)*(1+inf)^H$1 -> 0 | J43: =IF(Inputs!$B$55>=J$1,Inputs!$B$54,0)*(1+inf)^I$1 -> 0 | K43: =IF(Inputs!$B$55>=K$1,Inputs!$B$54,0)*(1+inf)^J$1 -> 0 | ... AM43: =IF(Inputs!$B$55>=AM$1,Inputs!$B$54,0)*(1+inf)^AL$1 -> 0
A44: Home rent | C44: =IF(AND(Inputs!$B$217<>"",C$2>=Inputs!$B$217),IF(OR(Inputs!$B$12<=0,UPPER(Inputs!$B$219)="RENT"),Inputs!$B$223*12*(1+inf)^B$1*IF(B$1=0,ProRate,1),0),Inputs!$B$23*12*(1+inf)^B$1*IF(B$1=0,ProRate,1)) -> 0 | D44: =IF(AND(Inputs!$B$217<>"",D$2>=Inputs!$B$217),IF(OR(Inputs!$B$12<=0,UPPER(Inputs!$B$219)="RENT"),Inputs!$B$223*12*(1+inf)^C$1*IF(C$1=0,ProRate,1),0),Inputs!$B$23*12*(1+inf)^C$1*IF(C$1=0,ProRate,1)) -> 0 | E44: =IF(AND(Inputs!$B$217<>"",E$2>=Inputs!$B$217),IF(OR(Inputs!$B$12<=0,UPPER(Inputs!$B$219)="RENT"),Inputs!$B$223*12*(1+inf)^D$1*IF(D$1=0,ProRate,1),0),Inputs!$B$23*12*(1+inf)^D$1*IF(D$1=0,ProRate,1)) -> 0 | F44: =IF(AND(Inputs!$B$217<>"",F$2>=Inputs!$B$217),IF(OR(Inputs!$B$12<=0,UPPER(Inputs!$B$219)="RENT"),Inputs!$B$223*12*(1+inf)^E$1*IF(E$1=0,ProRate,1),0),Inputs!$B$23*12*(1+inf)^E$1*IF(E$1=0,ProRate,1)) -> 0 | G44: =IF(AND(Inputs!$B$217<>"",G$2>=Inputs!$B$217),IF(OR(Inputs!$B$12<=0,UPPER(Inputs!$B$219)="RENT"),Inputs!$B$223*12*(1+inf)^F$1*IF(F$1=0,ProRate,1),0),Inputs!$B$23*12*(1+inf)^F$1*IF(F$1=0,ProRate,1)) -> 0 | H44: =IF(AND(Inputs!$B$217<>"",H$2>=Inputs!$B$217),IF(OR(Inputs!$B$12<=0,UPPER(Inputs!$B$219)="RENT"),Inputs!$B$223*12*(1+inf)^G$1*IF(G$1=0,ProRate,1),0),Inputs!$B$23*12*(1+inf)^G$1*IF(G$1=0,ProRate,1)) -> 0 | I44: =IF(AND(Inputs!$B$217<>"",I$2>=Inputs!$B$217),IF(OR(Inputs!$B$12<=0,UPPER(Inputs!$B$219)="RENT"),Inputs!$B$223*12*(1+inf)^H$1*IF(H$1=0,ProRate,1),0),Inputs!$B$23*12*(1+inf)^H$1*IF(H$1=0,ProRate,1)) -> 0 | J44: =IF(AND(Inputs!$B$217<>"",J$2>=Inputs!$B$217),IF(OR(Inputs!$B$12<=0,UPPER(Inputs!$B$219)="RENT"),Inputs!$B$223*12*(1+inf)^I$1*IF(I$1=0,ProRate,1),0),Inputs!$B$23*12*(1+inf)^I$1*IF(I$1=0,ProRate,1)) -> 0 | ... AM44: =IF(AND(Inputs!$B$217<>"",AM$2>=Inputs!$B$217),IF(OR(Inputs!$B$12<=0,UPPER(Inputs!$B$219)="RENT"),Inputs!$B$223*12*(1+inf)^AL$1*IF(AL$1=0,ProRate,1),0),Inputs!$B$23*12*(1+inf)^AL$1*IF(AL$1=0,ProRate,1)) -> 0
A45: Other property costs
A46: =TEXT(Inputs!$B$60,"") -> Sliema | C46: =Inputs!$B62*(1+inf)^B$1*ProRate -> 3750 | D46: =Inputs!$B62*(1+inf)^C$1 -> 5125 | E46: =Inputs!$B62*(1+inf)^D$1 -> 5253.125 | F46: =Inputs!$B62*(1+inf)^E$1 -> 5384.4531 | G46: =Inputs!$B62*(1+inf)^F$1 -> 5519.0645 | H46: =Inputs!$B62*(1+inf)^G$1 -> 5657.0411 | I46: =Inputs!$B62*(1+inf)^H$1 -> 5798.4671 | J46: =Inputs!$B62*(1+inf)^I$1 -> 5943.4288 | K46: =Inputs!$B62*(1+inf)^J$1 -> 6092.0145 | ... AM46: =Inputs!$B62*(1+inf)^AL$1 -> 12162.677
A47: =TEXT(Inputs!$B$65,"") -> Gzira | C47: =Inputs!$B67*(1+inf)^B$1*ProRate -> 1500 | D47: =Inputs!$B67*(1+inf)^C$1 -> 2050 | E47: =Inputs!$B67*(1+inf)^D$1 -> 2101.25 | F47: =Inputs!$B67*(1+inf)^E$1 -> 2153.7812 | G47: =Inputs!$B67*(1+inf)^F$1 -> 2207.6258 | H47: =Inputs!$B67*(1+inf)^G$1 -> 2262.8164 | I47: =Inputs!$B67*(1+inf)^H$1 -> 2319.3868 | J47: =Inputs!$B67*(1+inf)^I$1 -> 2377.3715 | K47: =Inputs!$B67*(1+inf)^J$1 -> 2436.8058 | ... AM47: =Inputs!$B67*(1+inf)^AL$1 -> 4865.0706
A48: =TEXT(Inputs!$B$70,"") -> Qormi | C48: =Inputs!$B72*(1+inf)^B$1*ProRate -> 900 | D48: =Inputs!$B72*(1+inf)^C$1 -> 1230 | E48: =Inputs!$B72*(1+inf)^D$1 -> 1260.75 | F48: =Inputs!$B72*(1+inf)^E$1 -> 1292.2687 | G48: =Inputs!$B72*(1+inf)^F$1 -> 1324.5755 | H48: =Inputs!$B72*(1+inf)^G$1 -> 1357.6899 | I48: =Inputs!$B72*(1+inf)^H$1 -> 1391.6321 | J48: =Inputs!$B72*(1+inf)^I$1 -> 1426.4229 | K48: =Inputs!$B72*(1+inf)^J$1 -> 1462.0835 | ... AM48: =Inputs!$B72*(1+inf)^AL$1 -> 2919.0424
A49: =TEXT(Inputs!$B$75,"") -> Gudja | C49: =Inputs!$B77*(1+inf)^B$1*ProRate -> 750 | D49: =Inputs!$B77*(1+inf)^C$1 -> 1025 | E49: =Inputs!$B77*(1+inf)^D$1 -> 1050.625 | F49: =Inputs!$B77*(1+inf)^E$1 -> 1076.8906 | G49: =Inputs!$B77*(1+inf)^F$1 -> 1103.8129 | H49: =Inputs!$B77*(1+inf)^G$1 -> 1131.4082 | I49: =Inputs!$B77*(1+inf)^H$1 -> 1159.6934 | J49: =Inputs!$B77*(1+inf)^I$1 -> 1188.6858 | K49: =Inputs!$B77*(1+inf)^J$1 -> 1218.4029 | ... AM49: =Inputs!$B77*(1+inf)^AL$1 -> 2432.5353
A50: =TEXT(Inputs!$B$80,"") -> Marsa | C50: =Inputs!$B82*(1+inf)^B$1*ProRate -> 600 | D50: =Inputs!$B82*(1+inf)^C$1 -> 820 | E50: =Inputs!$B82*(1+inf)^D$1 -> 840.5 | F50: =Inputs!$B82*(1+inf)^E$1 -> 861.5125 | G50: =Inputs!$B82*(1+inf)^F$1 -> 883.05031 | H50: =Inputs!$B82*(1+inf)^G$1 -> 905.12657 | I50: =Inputs!$B82*(1+inf)^H$1 -> 927.75473 | J50: =Inputs!$B82*(1+inf)^I$1 -> 950.9486 | K50: =Inputs!$B82*(1+inf)^J$1 -> 974.72232 | ... AM50: =Inputs!$B82*(1+inf)^AL$1 -> 1946.0283
A51: Living expenses
A52: Current baseline | C52: =Inputs!$B$25*(1+inf)^B$1*ProRate -> 37500 | D52: =Inputs!$B$25*(1+inf)^C$1 -> 51250 | E52: =Inputs!$B$25*(1+inf)^D$1 -> 52531.25 | F52: =Inputs!$B$25*(1+inf)^E$1 -> 53844.531 | G52: =Inputs!$B$25*(1+inf)^F$1 -> 55190.645 | H52: =Inputs!$B$25*(1+inf)^G$1 -> 56570.411 | I52: =Inputs!$B$25*(1+inf)^H$1 -> 57984.671 | J52: =Inputs!$B$25*(1+inf)^I$1 -> 59434.288 | K52: =Inputs!$B$25*(1+inf)^J$1 -> 60920.145 | ... AM52: =Inputs!$B$25*(1+inf)^AL$1 -> 121626.77
A53: ="Adjustment "&Inputs!A257 -> Adjustment from now to 65 | C53: =IF(C$3<=65,Inputs!$B$257*C$52,0) -> 0 | D53: =IF(D$3<=65,Inputs!$B$257*D$52,0) -> 0 | E53: =IF(E$3<=65,Inputs!$B$257*E$52,0) -> 0 | F53: =IF(F$3<=65,Inputs!$B$257*F$52,0) -> 0 | G53: =IF(G$3<=65,Inputs!$B$257*G$52,0) -> 0 | H53: =IF(H$3<=65,Inputs!$B$257*H$52,0) -> 0 | I53: =IF(I$3<=65,Inputs!$B$257*I$52,0) -> 0 | J53: =IF(J$3<=65,Inputs!$B$257*J$52,0) -> 0 | ... AM53: =IF(AM$3<=65,Inputs!$B$257*AM$52,0) -> 0
A54: ="Adjustment "&Inputs!A258 -> Adjustment from 66-75 | C54: =IF(AND(C$3>65,C$3<=75),Inputs!$B$258*C52,0) -> 0 | D54: =IF(AND(D$3>65,D$3<=75),Inputs!$B$258*D52,0) -> 0 | E54: =IF(AND(E$3>65,E$3<=75),Inputs!$B$258*E52,0) -> 0 | F54: =IF(AND(F$3>65,F$3<=75),Inputs!$B$258*F52,0) -> 0 | G54: =IF(AND(G$3>65,G$3<=75),Inputs!$B$258*G52,0) -> 0 | H54: =IF(AND(H$3>65,H$3<=75),Inputs!$B$258*H52,0) -> 0 | I54: =IF(AND(I$3>65,I$3<=75),Inputs!$B$258*I52,0) -> 0 | J54: =IF(AND(J$3>65,J$3<=75),Inputs!$B$258*J52,0) -> 0 | ... AM54: =IF(AND(AM$3>65,AM$3<=75),Inputs!$B$258*AM52,0) -> 0
A55: ="Adjustment "&Inputs!A259 -> Adjustment from age 76 | C55: =IF(C$3>75,Inputs!$B$259*C$52,0) -> 0 | D55: =IF(D$3>75,Inputs!$B$259*D$52,0) -> 0 | E55: =IF(E$3>75,Inputs!$B$259*E$52,0) -> 0 | F55: =IF(F$3>75,Inputs!$B$259*F$52,0) -> 0 | G55: =IF(G$3>75,Inputs!$B$259*G$52,0) -> 0 | H55: =IF(H$3>75,Inputs!$B$259*H$52,0) -> 0 | I55: =IF(I$3>75,Inputs!$B$259*I$52,0) -> 0 | J55: =IF(J$3>75,Inputs!$B$259*J$52,0) -> 0 | ... AM55: =IF(AM$3>75,Inputs!$B$259*AM$52,0) -> -24325.353
A56: Major one-off expense events
A57: =TEXT(Inputs!$B$201,"") -> Wedding | C57: =IF(C$2=Inputs!$B203,Inputs!$B202,0)*(1+inf)^B$1 -> 0 | D57: =IF(D$2=Inputs!$B203,Inputs!$B202,0)*(1+inf)^C$1 -> 0 | E57: =IF(E$2=Inputs!$B203,Inputs!$B202,0)*(1+inf)^D$1 -> 0 | F57: =IF(F$2=Inputs!$B203,Inputs!$B202,0)*(1+inf)^E$1 -> 0 | G57: =IF(G$2=Inputs!$B203,Inputs!$B202,0)*(1+inf)^F$1 -> 0 | H57: =IF(H$2=Inputs!$B203,Inputs!$B202,0)*(1+inf)^G$1 -> 0 | I57: =IF(I$2=Inputs!$B203,Inputs!$B202,0)*(1+inf)^H$1 -> 0 | J57: =IF(J$2=Inputs!$B203,Inputs!$B202,0)*(1+inf)^I$1 -> 0 | ... AM57: =IF(AM$2=Inputs!$B203,Inputs!$B202,0)*(1+inf)^AL$1 -> 0
A58: =TEXT(Inputs!$B$206,"") -> New Car | C58: =IF(C$2=Inputs!$B208,Inputs!$B207,0)*(1+inf)^B$1 -> 0 | D58: =IF(D$2=Inputs!$B208,Inputs!$B207,0)*(1+inf)^C$1 -> 0 | E58: =IF(E$2=Inputs!$B208,Inputs!$B207,0)*(1+inf)^D$1 -> 0 | F58: =IF(F$2=Inputs!$B208,Inputs!$B207,0)*(1+inf)^E$1 -> 37691.172 | G58: =IF(G$2=Inputs!$B208,Inputs!$B207,0)*(1+inf)^F$1 -> 0 | H58: =IF(H$2=Inputs!$B208,Inputs!$B207,0)*(1+inf)^G$1 -> 0 | I58: =IF(I$2=Inputs!$B208,Inputs!$B207,0)*(1+inf)^H$1 -> 0 | J58: =IF(J$2=Inputs!$B208,Inputs!$B207,0)*(1+inf)^I$1 -> 0 | ... AM58: =IF(AM$2=Inputs!$B208,Inputs!$B207,0)*(1+inf)^AL$1 -> 0
A59: =TEXT(Inputs!$B$211,"") -> New AC | C59: =IF(C$2=Inputs!$B213,Inputs!$B212,0)*(1+inf)^B$1 -> 0 | D59: =IF(D$2=Inputs!$B213,Inputs!$B212,0)*(1+inf)^C$1 -> 0 | E59: =IF(E$2=Inputs!$B213,Inputs!$B212,0)*(1+inf)^D$1 -> 0 | F59: =IF(F$2=Inputs!$B213,Inputs!$B212,0)*(1+inf)^E$1 -> 0 | G59: =IF(G$2=Inputs!$B213,Inputs!$B212,0)*(1+inf)^F$1 -> 0 | H59: =IF(H$2=Inputs!$B213,Inputs!$B212,0)*(1+inf)^G$1 -> 0 | I59: =IF(I$2=Inputs!$B213,Inputs!$B212,0)*(1+inf)^H$1 -> 0 | J59: =IF(J$2=Inputs!$B213,Inputs!$B212,0)*(1+inf)^I$1 -> 0 | ... AM59: =IF(AM$2=Inputs!$B213,Inputs!$B212,0)*(1+inf)^AL$1 -> 0
A60: Purchase of home (downsizing) | C60: =IF(AND(Inputs!$B$217<>"",C$2=Inputs!$B$217,Inputs!$B$12>0,UPPER(Inputs!$B$219)="BUY"),Inputs!$B$221*(1+princ)^(ProRate+C$1-1),0) -> 0 | D60: =IF(AND(Inputs!$B$217<>"",D$2=Inputs!$B$217,Inputs!$B$12>0,UPPER(Inputs!$B$219)="BUY"),Inputs!$B$221*(1+princ)^(ProRate+D$1-1),0) -> 0 | E60: =IF(AND(Inputs!$B$217<>"",E$2=Inputs!$B$217,Inputs!$B$12>0,UPPER(Inputs!$B$219)="BUY"),Inputs!$B$221*(1+princ)^(ProRate+E$1-1),0) -> 0 | F60: =IF(AND(Inputs!$B$217<>"",F$2=Inputs!$B$217,Inputs!$B$12>0,UPPER(Inputs!$B$219)="BUY"),Inputs!$B$221*(1+princ)^(ProRate+F$1-1),0) -> 0 | G60: =IF(AND(Inputs!$B$217<>"",G$2=Inputs!$B$217,Inputs!$B$12>0,UPPER(Inputs!$B$219)="BUY"),Inputs!$B$221*(1+princ)^(ProRate+G$1-1),0) -> 287684.74 | H60: =IF(AND(Inputs!$B$217<>"",H$2=Inputs!$B$217,Inputs!$B$12>0,UPPER(Inputs!$B$219)="BUY"),Inputs!$B$221*(1+princ)^(ProRate+H$1-1),0) -> 0 | I60: =IF(AND(Inputs!$B$217<>"",I$2=Inputs!$B$217,Inputs!$B$12>0,UPPER(Inputs!$B$219)="BUY"),Inputs!$B$221*(1+princ)^(ProRate+I$1-1),0) -> 0 | J60: =IF(AND(Inputs!$B$217<>"",J$2=Inputs!$B$217,Inputs!$B$12>0,UPPER(Inputs!$B$219)="BUY"),Inputs!$B$221*(1+princ)^(ProRate+J$1-1),0) -> 0 | ... AM60: =IF(AND(Inputs!$B$217<>"",AM$2=Inputs!$B$217,Inputs!$B$12>0,UPPER(Inputs!$B$219)="BUY"),Inputs!$B$221*(1+princ)^(ProRate+AM$1-1),0) -> 0
C61: =SUM(C23:C60) -> 77950 | D61: =SUM(D23:D60) -> 104409 | E61: =SUM(E23:E60) -> 102060.72 | F61: =SUM(F23:F60) -> 134792.57 | G61: =SUM(G23:G60) -> 423087.87 | H61: =SUM(H23:H60) -> 92548.579 | I61: =SUM(I23:I60) -> 83430.981 | J61: =SUM(J23:J60) -> 78830.394 | ... AM61: =SUM(AM23:AM60) -> 121626.77
A63: Net Cash Flow | C63: =C22-C61 -> 16108.438 | D63: =D22-D61 -> 13903.708 | E63: =E22-E61 -> 20157.504 | F63: =F22-F61 -> 2058.1344 | G63: =G22-G61 -> 198227.38 | H63: =H22-H61 -> 46531.68 | I63: =I22-I61 -> 66767.804 | J63: =J22-J61 -> 71313.286 | ... AM63: =AM22-AM61 -> 69131.276
A64: Cash b/fwd | C64: =Inputs!B8 -> 50000 | D64: =C65 -> 66108.438 | E64: =D65 -> 80012.145 | F64: =E65 -> 100169.65 | G64: =F65 -> 102227.78 | H64: =G65 -> 300455.16 | I64: =H65 -> 346986.84 | J64: =I65 -> 413754.64 | K64: =J65 -> 485067.93 | ... AM64: =AL65 -> 2461391.2
A65: Cash c/fwd | C65: =SUM(C63:C64) -> 66108.438 | D65: =SUM(D63:D64) -> 80012.145 | E65: =SUM(E63:E64) -> 100169.65 | F65: =SUM(F63:F64) -> 102227.78 | G65: =SUM(G63:G64) -> 300455.16 | H65: =SUM(H63:H64) -> 346986.84 | I65: =SUM(I63:I64) -> 413754.64 | J65: =SUM(J63:J64) -> 485067.93 | ... AM65: =SUM(AM63:AM64) -> 2530522.5
A67: Net Worth before liquidations
A68: Cash | C68: =C65 -> 66108.438 | D68: =D65 -> 80012.145 | E68: =E65 -> 100169.65 | F68: =F65 -> 102227.78 | G68: =G65 -> 300455.16 | H68: =H65 -> 346986.84 | I68: =I65 -> 413754.64 | J68: =J65 -> 485067.93 | ... AM68: =AM65 -> 2530522.5
A69: Home | C69: =IF(AND(Inputs!$B$217<>"",C$2>=Inputs!$B$217),IF(AND(Inputs!$B$12>0,UPPER(Inputs!$B$219)="BUY"),IF(C$2=Inputs!$B$217,Inputs!$B$221*(1+princ)^(ProRate+C$1-1),B69*(1+princ)),0),IF(Inputs!$B$12>0,IF(B$1=0,Inputs!$B$12*(1+princ)^ProRate,B69*(1+princ)),0)) -> 511208.33 | D69: =IF(AND(Inputs!$B$217<>"",D$2>=Inputs!$B$217),IF(AND(Inputs!$B$12>0,UPPER(Inputs!$B$219)="BUY"),IF(D$2=Inputs!$B$217,Inputs!$B$221*(1+princ)^(ProRate+D$1-1),C69*(1+princ)),0),IF(Inputs!$B$12>0,IF(C$1=0,Inputs!$B$12*(1+princ)^ProRate,C69*(1+princ)),0)) -> 526544.58 | E69: =IF(AND(Inputs!$B$217<>"",E$2>=Inputs!$B$217),IF(AND(Inputs!$B$12>0,UPPER(Inputs!$B$219)="BUY"),IF(E$2=Inputs!$B$217,Inputs!$B$221*(1+princ)^(ProRate+E$1-1),D69*(1+princ)),0),IF(Inputs!$B$12>0,IF(D$1=0,Inputs!$B$12*(1+princ)^ProRate,D69*(1+princ)),0)) -> 542340.92 | F69: =IF(AND(Inputs!$B$217<>"",F$2>=Inputs!$B$217),IF(AND(Inputs!$B$12>0,UPPER(Inputs!$B$219)="BUY"),IF(F$2=Inputs!$B$217,Inputs!$B$221*(1+princ)^(ProRate+F$1-1),E69*(1+princ)),0),IF(Inputs!$B$12>0,IF(E$1=0,Inputs!$B$12*(1+princ)^ProRate,E69*(1+princ)),0)) -> 558611.15 | G69: =IF(AND(Inputs!$B$217<>"",G$2>=Inputs!$B$217),IF(AND(Inputs!$B$12>0,UPPER(Inputs!$B$219)="BUY"),IF(G$2=Inputs!$B$217,Inputs!$B$221*(1+princ)^(ProRate+G$1-1),F69*(1+princ)),0),IF(Inputs!$B$12>0,IF(F$1=0,Inputs!$B$12*(1+princ)^ProRate,F69*(1+princ)),0)) -> 287684.74 | H69: =IF(AND(Inputs!$B$217<>"",H$2>=Inputs!$B$217),IF(AND(Inputs!$B$12>0,UPPER(Inputs!$B$219)="BUY"),IF(H$2=Inputs!$B$217,Inputs!$B$221*(1+princ)^(ProRate+H$1-1),G69*(1+princ)),0),IF(Inputs!$B$12>0,IF(G$1=0,Inputs!$B$12*(1+princ)^ProRate,G69*(1+princ)),0)) -> 296315.28 | I69: =IF(AND(Inputs!$B$217<>"",I$2>=Inputs!$B$217),IF(AND(Inputs!$B$12>0,UPPER(Inputs!$B$219)="BUY"),IF(I$2=Inputs!$B$217,Inputs!$B$221*(1+princ)^(ProRate+I$1-1),H69*(1+princ)),0),IF(Inputs!$B$12>0,IF(H$1=0,Inputs!$B$12*(1+princ)^ProRate,H69*(1+princ)),0)) -> 305204.74 | J69: =IF(AND(Inputs!$B$217<>"",J$2>=Inputs!$B$217),IF(AND(Inputs!$B$12>0,UPPER(Inputs!$B$219)="BUY"),IF(J$2=Inputs!$B$217,Inputs!$B$221*(1+princ)^(ProRate+J$1-1),I69*(1+princ)),0),IF(Inputs!$B$12>0,IF(I$1=0,Inputs!$B$12*(1+princ)^ProRate,I69*(1+princ)),0)) -> 314360.88 | ... AM69: =IF(AND(Inputs!$B$217<>"",AM$2>=Inputs!$B$217),IF(AND(Inputs!$B$12>0,UPPER(Inputs!$B$219)="BUY"),IF(AM$2=Inputs!$B$217,Inputs!$B$221*(1+princ)^(ProRate+AM$1-1),AL69*(1+princ)),0),IF(Inputs!$B$12>0,IF(AL$1=0,Inputs!$B$12*(1+princ)^ProRate,AL69*(1+princ)),0)) -> 740812.01
A70: Other property
A71: =TEXT(Inputs!$B$60,"") -> Sliema | C71: =Inputs!B61*(1+princ)^ProRate -> 306725 | D71: =C71*(1+princ) -> 315926.75 | E71: =D71*(1+princ) -> 325404.55 | F71: =E71*(1+princ) -> 335166.69 | G71: =F71*(1+princ) -> 345221.69 | H71: =G71*(1+princ) -> 355578.34 | I71: =H71*(1+princ) -> 366245.69 | J71: =I71*(1+princ) -> 377233.06 | K71: =J71*(1+princ) -> 388550.05 | ... AM71: =AL71*(1+princ) -> 888974.42
A72: =TEXT(Inputs!$B$65,"") -> Gzira | C72: =Inputs!B66*(1+princ)^ProRate -> 153362.5 | D72: =C72*(1+princ) -> 157963.37 | E72: =D72*(1+princ) -> 162702.28 | F72: =E72*(1+princ) -> 167583.34 | G72: =F72*(1+princ) -> 172610.84 | H72: =G72*(1+princ) -> 177789.17 | I72: =H72*(1+princ) -> 183122.84 | J72: =I72*(1+princ) -> 188616.53 | K72: =J72*(1+princ) -> 194275.03 | ... AM72: =AL72*(1+princ) -> 444487.21
A73: =TEXT(Inputs!$B$70,"") -> Qormi | C73: =Inputs!B71*(1+princ)^ProRate -> 224931.67 | D73: =C73*(1+princ) -> 231679.62 | E73: =D73*(1+princ) -> 238630 | F73: =E73*(1+princ) -> 245788.9 | G73: =F73*(1+princ) -> 253162.57 | H73: =G73*(1+princ) -> 260757.45 | I73: =H73*(1+princ) -> 268580.17 | J73: =I73*(1+princ) -> 276637.58 | K73: =J73*(1+princ) -> 284936.7 | ... AM73: =AL73*(1+princ) -> 651914.57
A74: =TEXT(Inputs!$B$75,"") -> Gudja | C74: =Inputs!B76*(1+princ)^ProRate -> 81793.333 | D74: =C74*(1+princ) -> 84247.133 | E74: =D74*(1+princ) -> 86774.547 | F74: =E74*(1+princ) -> 89377.783 | G74: =F74*(1+princ) -> 92059.117 | H74: =G74*(1+princ) -> 94820.89 | I74: =H74*(1+princ) -> 97665.517 | J74: =I74*(1+princ) -> 100595.48 | K74: =J74*(1+princ) -> 103613.35 | ... AM74: =AL74*(1+princ) -> 237059.84
A75: =TEXT(Inputs!$B$80,"") -> Marsa | C75: =Inputs!B81*(1+princ)^ProRate -> 122690 | D75: =C75*(1+princ) -> 126370.7 | E75: =D75*(1+princ) -> 130161.82 | F75: =E75*(1+princ) -> 134066.68 | G75: =F75*(1+princ) -> 138088.68 | H75: =G75*(1+princ) -> 142231.34 | I75: =H75*(1+princ) -> 146498.28 | J75: =I75*(1+princ) -> 150893.22 | K75: =J75*(1+princ) -> 155420.02 | ... AM75: =AL75*(1+princ) -> 355589.77
A76: Other assets of value
A77: =TEXT(Inputs!$B$87,"") -> Jewelry | C77: =Inputs!B88*(1+A1inc)^ProRate -> 50748.14 | D77: =C77*(1+A1inc) -> 51763.103 | E77: =D77*(1+A1inc) -> 52798.365 | F77: =E77*(1+A1inc) -> 53854.333 | G77: =F77*(1+A1inc) -> 54931.419 | H77: =G77*(1+A1inc) -> 56030.048 | I77: =H77*(1+A1inc) -> 57150.649 | J77: =I77*(1+A1inc) -> 58293.662 | K77: =J77*(1+A1inc) -> 59459.535 | ... AM77: =AL77*(1+A1inc) -> 103520.49
A78: =TEXT(Inputs!$B$92,"") -> Car | C78: =Inputs!B93*(1+A2inc)^ProRate -> 38490.424 | D78: =C78*(1+A2inc) -> 36565.903 | E78: =D78*(1+A2inc) -> 34737.608 | F78: =E78*(1+A2inc) -> 33000.727 | G78: =F78*(1+A2inc) -> 31350.691 | H78: =G78*(1+A2inc) -> 29783.156 | I78: =H78*(1+A2inc) -> 28293.999 | J78: =I78*(1+A2inc) -> 26879.299 | K78: =J78*(1+A2inc) -> 25535.334 | ... AM78: =AL78*(1+A2inc) -> 6072.9889
A79: =TEXT(Inputs!$B$97,"") -> Painting | C79: =Inputs!B98*(1+A3inc)^ProRate -> 20448.333 | D79: =C79*(1+A3inc) -> 21061.783 | E79: =D79*(1+A3inc) -> 21693.637 | F79: =E79*(1+A3inc) -> 22344.446 | G79: =F79*(1+A3inc) -> 23014.779 | H79: =G79*(1+A3inc) -> 23705.223 | I79: =H79*(1+A3inc) -> 24416.379 | J79: =I79*(1+A3inc) -> 25148.871 | K79: =J79*(1+A3inc) -> 25903.337 | ... AM79: =AL79*(1+A3inc) -> 59264.961
A80: =TEXT(Inputs!$B$102,"") -> Boat | C80: =Inputs!B103*(1+A4inc)^ProRate -> 173206.91 | D80: =C80*(1+A4inc) -> 164546.56 | E80: =D80*(1+A4inc) -> 156319.23 | F80: =E80*(1+A4inc) -> 148503.27 | G80: =F80*(1+A4inc) -> 141078.11 | H80: =G80*(1+A4inc) -> 134024.2 | I80: =H80*(1+A4inc) -> 127322.99 | J80: =I80*(1+A4inc) -> 120956.84 | K80: =J80*(1+A4inc) -> 114909 | ... AM80: =AL80*(1+A4inc) -> 27328.45
A81: =TEXT(Inputs!$B$107,"") -> Antiques | C81: =Inputs!B108*(1+A5inc)^ProRate -> 83226.95 | D81: =C81*(1+A5inc) -> 84891.489 | E81: =D81*(1+A5inc) -> 86589.319 | F81: =E81*(1+A5inc) -> 88321.106 | G81: =F81*(1+A5inc) -> 90087.528 | H81: =G81*(1+A5inc) -> 91889.278 | I81: =H81*(1+A5inc) -> 93727.064 | J81: =I81*(1+A5inc) -> 95601.605 | K81: =J81*(1+A5inc) -> 97513.637 | ... AM81: =AL81*(1+A5inc) -> 169773.6
A82: Stock market equity investments | C82: =Inputs!B10*(1+stinc)^ProRate -> 31782.574 | D82: =C82*(1+IF(AND(Inputs!$B$228<>"",D$2=Inputs!$B$228),-Inputs!$B$229,IF(AND(Inputs!$B$228<>"",D$2>Inputs!$B$228,D$2<=Inputs!$B$228+Inputs!$B$230),(1/(1-Inputs!$B$229))^(1/Inputs!$B$230)-1,IF(AND(Inputs!$B$233<>"",D$2=Inputs!$B$233),-Inputs!$B$234,IF(AND(Inputs!$B$233<>"",D$2>Inputs!$B$233,D$2<=Inputs!$B$233+Inputs!$B$235),(1/(1-Inputs!$B$234))^(1/Inputs!$B$235)-1,IF(AND(Inputs!$B$238<>"",D$2=Inputs!$B$238),-Inputs!$B$239,IF(AND(Inputs!$B$238<>"",D$2>Inputs!$B$238,D$2<=Inputs!$B$238+Inputs!$B$240),(1/(1-Inputs!$B$239))^(1/Inputs!$B$240)-1,IF(AND(Inputs!$B$243<>"",D$2=Inputs!$B$243),-Inputs!$B$244,IF(AND(Inputs!$B$243<>"",D$2>Inputs!$B$243,D$2<=Inputs!$B$243+Inputs!$B$245),(1/(1-Inputs!$B$244))^(1/Inputs!$B$245)-1,IF(AND(Inputs!$B$248<>"",D$2=Inputs!$B$248),-Inputs!$B$249,IF(AND(Inputs!$B$248<>"",D$2>Inputs!$B$248,D$2<=Inputs!$B$248+Inputs!$B$250),(1/(1-Inputs!$B$249))^(1/Inputs!$B$250)-1,stinc))))))))))) -> 27015.188 | E82: =D82*(1+IF(AND(Inputs!$B$228<>"",E$2=Inputs!$B$228),-Inputs!$B$229,IF(AND(Inputs!$B$228<>"",E$2>Inputs!$B$228,E$2<=Inputs!$B$228+Inputs!$B$230),(1/(1-Inputs!$B$229))^(1/Inputs!$B$230)-1,IF(AND(Inputs!$B$233<>"",E$2=Inputs!$B$233),-Inputs!$B$234,IF(AND(Inputs!$B$233<>"",E$2>Inputs!$B$233,E$2<=Inputs!$B$233+Inputs!$B$235),(1/(1-Inputs!$B$234))^(1/Inputs!$B$235)-1,IF(AND(Inputs!$B$238<>"",E$2=Inputs!$B$238),-Inputs!$B$239,IF(AND(Inputs!$B$238<>"",E$2>Inputs!$B$238,E$2<=Inputs!$B$238+Inputs!$B$240),(1/(1-Inputs!$B$239))^(1/Inputs!$B$240)-1,IF(AND(Inputs!$B$243<>"",E$2=Inputs!$B$243),-Inputs!$B$244,IF(AND(Inputs!$B$243<>"",E$2>Inputs!$B$243,E$2<=Inputs!$B$243+Inputs!$B$245),(1/(1-Inputs!$B$244))^(1/Inputs!$B$245)-1,IF(AND(Inputs!$B$248<>"",E$2=Inputs!$B$248),-Inputs!$B$249,IF(AND(Inputs!$B$248<>"",E$2>Inputs!$B$248,E$2<=Inputs!$B$248+Inputs!$B$250),(1/(1-Inputs!$B$249))^(1/Inputs!$B$250)-1,stinc))))))))))) -> 31782.574 | F82: =E82*(1+IF(AND(Inputs!$B$228<>"",F$2=Inputs!$B$228),-Inputs!$B$229,IF(AND(Inputs!$B$228<>"",F$2>Inputs!$B$228,F$2<=Inputs!$B$228+Inputs!$B$230),(1/(1-Inputs!$B$229))^(1/Inputs!$B$230)-1,IF(AND(Inputs!$B$233<>"",F$2=Inputs!$B$233),-Inputs!$B$234,IF(AND(Inputs!$B$233<>"",F$2>Inputs!$B$233,F$2<=Inputs!$B$233+Inputs!$B$235),(1/(1-Inputs!$B$234))^(1/Inputs!$B$235)-1,IF(AND(Inputs!$B$238<>"",F$2=Inputs!$B$238),-Inputs!$B$239,IF(AND(Inputs!$B$238<>"",F$2>Inputs!$B$238,F$2<=Inputs!$B$238+Inputs!$B$240),(1/(1-Inputs!$B$239))^(1/Inputs!$B$240)-1,IF(AND(Inputs!$B$243<>"",F$2=Inputs!$B$243),-Inputs!$B$244,IF(AND(Inputs!$B$243<>"",F$2>Inputs!$B$243,F$2<=Inputs!$B$243+Inputs!$B$245),(1/(1-Inputs!$B$244))^(1/Inputs!$B$245)-1,IF(AND(Inputs!$B$248<>"",F$2=Inputs!$B$248),-Inputs!$B$249,IF(AND(Inputs!$B$248<>"",F$2>Inputs!$B$248,F$2<=Inputs!$B$248+Inputs!$B$250),(1/(1-Inputs!$B$249))^(1/Inputs!$B$250)-1,stinc))))))))))) -> 34325.18 | G82: =F82*(1+IF(AND(Inputs!$B$228<>"",G$2=Inputs!$B$228),-Inputs!$B$229,IF(AND(Inputs!$B$228<>"",G$2>Inputs!$B$228,G$2<=Inputs!$B$228+Inputs!$B$230),(1/(1-Inputs!$B$229))^(1/Inputs!$B$230)-1,IF(AND(Inputs!$B$233<>"",G$2=Inputs!$B$233),-Inputs!$B$234,IF(AND(Inputs!$B$233<>"",G$2>Inputs!$B$233,G$2<=Inputs!$B$233+Inputs!$B$235),(1/(1-Inputs!$B$234))^(1/Inputs!$B$235)-1,IF(AND(Inputs!$B$238<>"",G$2=Inputs!$B$238),-Inputs!$B$239,IF(AND(Inputs!$B$238<>"",G$2>Inputs!$B$238,G$2<=Inputs!$B$238+Inputs!$B$240),(1/(1-Inputs!$B$239))^(1/Inputs!$B$240)-1,IF(AND(Inputs!$B$243<>"",G$2=Inputs!$B$243),-Inputs!$B$244,IF(AND(Inputs!$B$243<>"",G$2>Inputs!$B$243,G$2<=Inputs!$B$243+Inputs!$B$245),(1/(1-Inputs!$B$244))^(1/Inputs!$B$245)-1,IF(AND(Inputs!$B$248<>"",G$2=Inputs!$B$248),-Inputs!$B$249,IF(AND(Inputs!$B$248<>"",G$2>Inputs!$B$248,G$2<=Inputs!$B$248+Inputs!$B$250),(1/(1-Inputs!$B$249))^(1/Inputs!$B$250)-1,stinc))))))))))) -> 37071.195 | H82: =G82*(1+IF(AND(Inputs!$B$228<>"",H$2=Inputs!$B$228),-Inputs!$B$229,IF(AND(Inputs!$B$228<>"",H$2>Inputs!$B$228,H$2<=Inputs!$B$228+Inputs!$B$230),(1/(1-Inputs!$B$229))^(1/Inputs!$B$230)-1,IF(AND(Inputs!$B$233<>"",H$2=Inputs!$B$233),-Inputs!$B$234,IF(AND(Inputs!$B$233<>"",H$2>Inputs!$B$233,H$2<=Inputs!$B$233+Inputs!$B$235),(1/(1-Inputs!$B$234))^(1/Inputs!$B$235)-1,IF(AND(Inputs!$B$238<>"",H$2=Inputs!$B$238),-Inputs!$B$239,IF(AND(Inputs!$B$238<>"",H$2>Inputs!$B$238,H$2<=Inputs!$B$238+Inputs!$B$240),(1/(1-Inputs!$B$239))^(1/Inputs!$B$240)-1,IF(AND(Inputs!$B$243<>"",H$2=Inputs!$B$243),-Inputs!$B$244,IF(AND(Inputs!$B$243<>"",H$2>Inputs!$B$243,H$2<=Inputs!$B$243+Inputs!$B$245),(1/(1-Inputs!$B$244))^(1/Inputs!$B$245)-1,IF(AND(Inputs!$B$248<>"",H$2=Inputs!$B$248),-Inputs!$B$249,IF(AND(Inputs!$B$248<>"",H$2>Inputs!$B$248,H$2<=Inputs!$B$248+Inputs!$B$250),(1/(1-Inputs!$B$249))^(1/Inputs!$B$250)-1,stinc))))))))))) -> 40036.89 | I82: =H82*(1+IF(AND(Inputs!$B$228<>"",I$2=Inputs!$B$228),-Inputs!$B$229,IF(AND(Inputs!$B$228<>"",I$2>Inputs!$B$228,I$2<=Inputs!$B$228+Inputs!$B$230),(1/(1-Inputs!$B$229))^(1/Inputs!$B$230)-1,IF(AND(Inputs!$B$233<>"",I$2=Inputs!$B$233),-Inputs!$B$234,IF(AND(Inputs!$B$233<>"",I$2>Inputs!$B$233,I$2<=Inputs!$B$233+Inputs!$B$235),(1/(1-Inputs!$B$234))^(1/Inputs!$B$235)-1,IF(AND(Inputs!$B$238<>"",I$2=Inputs!$B$238),-Inputs!$B$239,IF(AND(Inputs!$B$238<>"",I$2>Inputs!$B$238,I$2<=Inputs!$B$238+Inputs!$B$240),(1/(1-Inputs!$B$239))^(1/Inputs!$B$240)-1,IF(AND(Inputs!$B$243<>"",I$2=Inputs!$B$243),-Inputs!$B$244,IF(AND(Inputs!$B$243<>"",I$2>Inputs!$B$243,I$2<=Inputs!$B$243+Inputs!$B$245),(1/(1-Inputs!$B$244))^(1/Inputs!$B$245)-1,IF(AND(Inputs!$B$248<>"",I$2=Inputs!$B$248),-Inputs!$B$249,IF(AND(Inputs!$B$248<>"",I$2>Inputs!$B$248,I$2<=Inputs!$B$248+Inputs!$B$250),(1/(1-Inputs!$B$249))^(1/Inputs!$B$250)-1,stinc))))))))))) -> 32029.512 | J82: =I82*(1+IF(AND(Inputs!$B$228<>"",J$2=Inputs!$B$228),-Inputs!$B$229,IF(AND(Inputs!$B$228<>"",J$2>Inputs!$B$228,J$2<=Inputs!$B$228+Inputs!$B$230),(1/(1-Inputs!$B$229))^(1/Inputs!$B$230)-1,IF(AND(Inputs!$B$233<>"",J$2=Inputs!$B$233),-Inputs!$B$234,IF(AND(Inputs!$B$233<>"",J$2>Inputs!$B$233,J$2<=Inputs!$B$233+Inputs!$B$235),(1/(1-Inputs!$B$234))^(1/Inputs!$B$235)-1,IF(AND(Inputs!$B$238<>"",J$2=Inputs!$B$238),-Inputs!$B$239,IF(AND(Inputs!$B$238<>"",J$2>Inputs!$B$238,J$2<=Inputs!$B$238+Inputs!$B$240),(1/(1-Inputs!$B$239))^(1/Inputs!$B$240)-1,IF(AND(Inputs!$B$243<>"",J$2=Inputs!$B$243),-Inputs!$B$244,IF(AND(Inputs!$B$243<>"",J$2>Inputs!$B$243,J$2<=Inputs!$B$243+Inputs!$B$245),(1/(1-Inputs!$B$244))^(1/Inputs!$B$245)-1,IF(AND(Inputs!$B$248<>"",J$2=Inputs!$B$248),-Inputs!$B$249,IF(AND(Inputs!$B$248<>"",J$2>Inputs!$B$248,J$2<=Inputs!$B$248+Inputs!$B$250),(1/(1-Inputs!$B$249))^(1/Inputs!$B$250)-1,stinc))))))))))) -> 34502.746 | K82: =J82*(1+IF(AND(Inputs!$B$228<>"",K$2=Inputs!$B$228),-Inputs!$B$229,IF(AND(Inputs!$B$228<>"",K$2>Inputs!$B$228,K$2<=Inputs!$B$228+Inputs!$B$230),(1/(1-Inputs!$B$229))^(1/Inputs!$B$230)-1,IF(AND(Inputs!$B$233<>"",K$2=Inputs!$B$233),-Inputs!$B$234,IF(AND(Inputs!$B$233<>"",K$2>Inputs!$B$233,K$2<=Inputs!$B$233+Inputs!$B$235),(1/(1-Inputs!$B$234))^(1/Inputs!$B$235)-1,IF(AND(Inputs!$B$238<>"",K$2=Inputs!$B$238),-Inputs!$B$239,IF(AND(Inputs!$B$238<>"",K$2>Inputs!$B$238,K$2<=Inputs!$B$238+Inputs!$B$240),(1/(1-Inputs!$B$239))^(1/Inputs!$B$240)-1,IF(AND(Inputs!$B$243<>"",K$2=Inputs!$B$243),-Inputs!$B$244,IF(AND(Inputs!$B$243<>"",K$2>Inputs!$B$243,K$2<=Inputs!$B$243+Inputs!$B$245),(1/(1-Inputs!$B$244))^(1/Inputs!$B$245)-1,IF(AND(Inputs!$B$248<>"",K$2=Inputs!$B$248),-Inputs!$B$249,IF(AND(Inputs!$B$248<>"",K$2>Inputs!$B$248,K$2<=Inputs!$B$248+Inputs!$B$250),(1/(1-Inputs!$B$249))^(1/Inputs!$B$250)-1,stinc))))))))))) -> 37166.957 | ... AM82: =AL82*(1+IF(AND(Inputs!$B$228<>"",AM$2=Inputs!$B$228),-Inputs!$B$229,IF(AND(Inputs!$B$228<>"",AM$2>Inputs!$B$228,AM$2<=Inputs!$B$228+Inputs!$B$230),(1/(1-Inputs!$B$229))^(1/Inputs!$B$230)-1,IF(AND(Inputs!$B$233<>"",AM$2=Inputs!$B$233),-Inputs!$B$234,IF(AND(Inputs!$B$233<>"",AM$2>Inputs!$B$233,AM$2<=Inputs!$B$233+Inputs!$B$235),(1/(1-Inputs!$B$234))^(1/Inputs!$B$235)-1,IF(AND(Inputs!$B$238<>"",AM$2=Inputs!$B$238),-Inputs!$B$239,IF(AND(Inputs!$B$238<>"",AM$2>Inputs!$B$238,AM$2<=Inputs!$B$238+Inputs!$B$240),(1/(1-Inputs!$B$239))^(1/Inputs!$B$240)-1,IF(AND(Inputs!$B$243<>"",AM$2=Inputs!$B$243),-Inputs!$B$244,IF(AND(Inputs!$B$243<>"",AM$2>Inputs!$B$243,AM$2<=Inputs!$B$243+Inputs!$B$245),(1/(1-Inputs!$B$244))^(1/Inputs!$B$245)-1,IF(AND(Inputs!$B$248<>"",AM$2=Inputs!$B$248),-Inputs!$B$249,IF(AND(Inputs!$B$248<>"",AM$2>Inputs!$B$248,AM$2<=Inputs!$B$248+Inputs!$B$250),(1/(1-Inputs!$B$249))^(1/Inputs!$B$250)-1,stinc))))))))))) -> 108885.28
A83: Home loan | C83: =IF(AND(Inputs!$B$217<>"",C$2>=Inputs!$B$217,Inputs!$B$12>0),0,-MAX(FV(Inputs!$B$16/12,C$1*12+MthOff,Inputs!$B$17,-Inputs!$B$15),0)) -> -48409.158 | D83: =IF(AND(Inputs!$B$217<>"",D$2>=Inputs!$B$217,Inputs!$B$12>0),0,-MAX(FV(Inputs!$B$16/12,D$1*12+MthOff,Inputs!$B$17,-Inputs!$B$15),0)) -> -46231.654 | E83: =IF(AND(Inputs!$B$217<>"",E$2>=Inputs!$B$217,Inputs!$B$12>0),0,-MAX(FV(Inputs!$B$16/12,E$1*12+MthOff,Inputs!$B$17,-Inputs!$B$15),0)) -> -43987.919 | F83: =IF(AND(Inputs!$B$217<>"",F$2>=Inputs!$B$217,Inputs!$B$12>0),0,-MAX(FV(Inputs!$B$16/12,F$1*12+MthOff,Inputs!$B$17,-Inputs!$B$15),0)) -> -41675.939 | G83: =IF(AND(Inputs!$B$217<>"",G$2>=Inputs!$B$217,Inputs!$B$12>0),0,-MAX(FV(Inputs!$B$16/12,G$1*12+MthOff,Inputs!$B$17,-Inputs!$B$15),0)) -> 0 | H83: =IF(AND(Inputs!$B$217<>"",H$2>=Inputs!$B$217,Inputs!$B$12>0),0,-MAX(FV(Inputs!$B$16/12,H$1*12+MthOff,Inputs!$B$17,-Inputs!$B$15),0)) -> 0 | I83: =IF(AND(Inputs!$B$217<>"",I$2>=Inputs!$B$217,Inputs!$B$12>0),0,-MAX(FV(Inputs!$B$16/12,I$1*12+MthOff,Inputs!$B$17,-Inputs!$B$15),0)) -> 0 | J83: =IF(AND(Inputs!$B$217<>"",J$2>=Inputs!$B$217,Inputs!$B$12>0),0,-MAX(FV(Inputs!$B$16/12,J$1*12+MthOff,Inputs!$B$17,-Inputs!$B$15),0)) -> 0 | ... AM83: =IF(AND(Inputs!$B$217<>"",AM$2>=Inputs!$B$217,Inputs!$B$12>0),0,-MAX(FV(Inputs!$B$16/12,AM$1*12+MthOff,Inputs!$B$17,-Inputs!$B$15),0)) -> 0
A84: Other asset loans
A85: =TEXT(Inputs!$B$60,"") -> Sliema | C85: =-MAX(FV(Inputs!$B128/12,C$1*12+MthOff,Inputs!$B129,-Inputs!$B127),0) -> -46591.052 | D85: =-MAX(FV(Inputs!$B128/12,D$1*12+MthOff,Inputs!$B129,-Inputs!$B127),0) -> -41924.972 | E85: =-MAX(FV(Inputs!$B128/12,E$1*12+MthOff,Inputs!$B129,-Inputs!$B127),0) -> -37116.969 | F85: =-MAX(FV(Inputs!$B128/12,F$1*12+MthOff,Inputs!$B129,-Inputs!$B127),0) -> -32162.726 | G85: =-MAX(FV(Inputs!$B128/12,G$1*12+MthOff,Inputs!$B129,-Inputs!$B127),0) -> -27057.795 | H85: =-MAX(FV(Inputs!$B128/12,H$1*12+MthOff,Inputs!$B129,-Inputs!$B127),0) -> -21797.592 | I85: =-MAX(FV(Inputs!$B128/12,I$1*12+MthOff,Inputs!$B129,-Inputs!$B127),0) -> -16377.395 | J85: =-MAX(FV(Inputs!$B128/12,J$1*12+MthOff,Inputs!$B129,-Inputs!$B127),0) -> -10792.338 | ... AM85: =-MAX(FV(Inputs!$B128/12,AM$1*12+MthOff,Inputs!$B129,-Inputs!$B127),0) -> 0
A86: =TEXT(Inputs!$B$65,"") -> Gzira | C86: =-MAX(FV(Inputs!$B133/12,C$1*12+MthOff,Inputs!$B134,-Inputs!$B132),0) -> -6816.3065 | D86: =-MAX(FV(Inputs!$B133/12,D$1*12+MthOff,Inputs!$B134,-Inputs!$B132),0) -> -4531.7666 | E86: =-MAX(FV(Inputs!$B133/12,E$1*12+MthOff,Inputs!$B134,-Inputs!$B132),0) -> -2201.1147 | F86: =-MAX(FV(Inputs!$B133/12,F$1*12+MthOff,Inputs!$B134,-Inputs!$B132),0) -> 0 | G86: =-MAX(FV(Inputs!$B133/12,G$1*12+MthOff,Inputs!$B134,-Inputs!$B132),0) -> 0 | H86: =-MAX(FV(Inputs!$B133/12,H$1*12+MthOff,Inputs!$B134,-Inputs!$B132),0) -> 0 | I86: =-MAX(FV(Inputs!$B133/12,I$1*12+MthOff,Inputs!$B134,-Inputs!$B132),0) -> 0 | J86: =-MAX(FV(Inputs!$B133/12,J$1*12+MthOff,Inputs!$B134,-Inputs!$B132),0) -> 0 | ... AM86: =-MAX(FV(Inputs!$B133/12,AM$1*12+MthOff,Inputs!$B134,-Inputs!$B132),0) -> 0
A87: =TEXT(Inputs!$B$70,"") -> Qormi | C87: =-MAX(FV(Inputs!$B138/12,C$1*12+MthOff,Inputs!$B139,-Inputs!$B137),0) -> -13284.1 | D87: =-MAX(FV(Inputs!$B138/12,D$1*12+MthOff,Inputs!$B139,-Inputs!$B137),0) -> -10894.026 | E87: =-MAX(FV(Inputs!$B138/12,E$1*12+MthOff,Inputs!$B139,-Inputs!$B137),0) -> -8381.6709 | F87: =-MAX(FV(Inputs!$B138/12,F$1*12+MthOff,Inputs!$B139,-Inputs!$B137),0) -> -5740.7792 | G87: =-MAX(FV(Inputs!$B138/12,G$1*12+MthOff,Inputs!$B139,-Inputs!$B137),0) -> -2964.7745 | H87: =-MAX(FV(Inputs!$B138/12,H$1*12+MthOff,Inputs!$B139,-Inputs!$B137),0) -> -46.744114 | I87: =-MAX(FV(Inputs!$B138/12,I$1*12+MthOff,Inputs!$B139,-Inputs!$B137),0) -> 0 | J87: =-MAX(FV(Inputs!$B138/12,J$1*12+MthOff,Inputs!$B139,-Inputs!$B137),0) -> 0 | ... AM87: =-MAX(FV(Inputs!$B138/12,AM$1*12+MthOff,Inputs!$B139,-Inputs!$B137),0) -> 0
A88: =TEXT(Inputs!$B$75,"") -> Gudja | C88: =-MAX(FV(Inputs!$B143/12,C$1*12+MthOff,Inputs!$B144,-Inputs!$B142),0) -> -4025.8511 | D88: =-MAX(FV(Inputs!$B143/12,D$1*12+MthOff,Inputs!$B144,-Inputs!$B142),0) -> -3138.2612 | E88: =-MAX(FV(Inputs!$B143/12,E$1*12+MthOff,Inputs!$B144,-Inputs!$B142),0) -> -2232.756 | F88: =-MAX(FV(Inputs!$B143/12,F$1*12+MthOff,Inputs!$B144,-Inputs!$B142),0) -> -1308.9736 | G88: =-MAX(FV(Inputs!$B143/12,G$1*12+MthOff,Inputs!$B144,-Inputs!$B142),0) -> -366.54534 | H88: =-MAX(FV(Inputs!$B143/12,H$1*12+MthOff,Inputs!$B144,-Inputs!$B142),0) -> 0 | I88: =-MAX(FV(Inputs!$B143/12,I$1*12+MthOff,Inputs!$B144,-Inputs!$B142),0) -> 0 | J88: =-MAX(FV(Inputs!$B143/12,J$1*12+MthOff,Inputs!$B144,-Inputs!$B142),0) -> 0 | ... AM88: =-MAX(FV(Inputs!$B143/12,AM$1*12+MthOff,Inputs!$B144,-Inputs!$B142),0) -> 0
A89: =TEXT(Inputs!$B$80,"") -> Marsa | C89: =-MAX(FV(Inputs!$B148/12,C$1*12+MthOff,Inputs!$B149,-Inputs!$B147),0) -> -8649.5822 | D89: =-MAX(FV(Inputs!$B148/12,D$1*12+MthOff,Inputs!$B149,-Inputs!$B147),0) -> -7452.7016 | E89: =-MAX(FV(Inputs!$B148/12,E$1*12+MthOff,Inputs!$B149,-Inputs!$B147),0) -> -6219.4167 | F89: =-MAX(FV(Inputs!$B148/12,F$1*12+MthOff,Inputs!$B149,-Inputs!$B147),0) -> -4948.6203 | G89: =-MAX(FV(Inputs!$B148/12,G$1*12+MthOff,Inputs!$B149,-Inputs!$B147),0) -> -3639.1714 | H89: =-MAX(FV(Inputs!$B148/12,H$1*12+MthOff,Inputs!$B149,-Inputs!$B147),0) -> -2289.8943 | I89: =-MAX(FV(Inputs!$B148/12,I$1*12+MthOff,Inputs!$B149,-Inputs!$B147),0) -> -899.57773 | J89: =-MAX(FV(Inputs!$B148/12,J$1*12+MthOff,Inputs!$B149,-Inputs!$B147),0) -> 0 | ... AM89: =-MAX(FV(Inputs!$B148/12,AM$1*12+MthOff,Inputs!$B149,-Inputs!$B147),0) -> 0
A90: =TEXT(Inputs!$B$87,"") -> Jewelry | C90: =-MAX(FV(Inputs!$B153/12,C$1*12+MthOff,Inputs!$B154,-Inputs!$B152),0) -> -1875.0263 | D90: =-MAX(FV(Inputs!$B153/12,D$1*12+MthOff,Inputs!$B154,-Inputs!$B152),0) -> -1019.5783 | E90: =-MAX(FV(Inputs!$B153/12,E$1*12+MthOff,Inputs!$B154,-Inputs!$B152),0) -> -138.11102 | F90: =-MAX(FV(Inputs!$B153/12,F$1*12+MthOff,Inputs!$B154,-Inputs!$B152),0) -> 0 | G90: =-MAX(FV(Inputs!$B153/12,G$1*12+MthOff,Inputs!$B154,-Inputs!$B152),0) -> 0 | H90: =-MAX(FV(Inputs!$B153/12,H$1*12+MthOff,Inputs!$B154,-Inputs!$B152),0) -> 0 | I90: =-MAX(FV(Inputs!$B153/12,I$1*12+MthOff,Inputs!$B154,-Inputs!$B152),0) -> 0 | J90: =-MAX(FV(Inputs!$B153/12,J$1*12+MthOff,Inputs!$B154,-Inputs!$B152),0) -> 0 | ... AM90: =-MAX(FV(Inputs!$B153/12,AM$1*12+MthOff,Inputs!$B154,-Inputs!$B152),0) -> 0
A91: =TEXT(Inputs!$B$92,"") -> Car | C91: =-MAX(FV(Inputs!$B158/12,C$1*12+MthOff,Inputs!$B159,-Inputs!$B157),0) -> -5311.4222 | D91: =-MAX(FV(Inputs!$B158/12,D$1*12+MthOff,Inputs!$B159,-Inputs!$B157),0) -> -4377.1171 | E91: =-MAX(FV(Inputs!$B158/12,E$1*12+MthOff,Inputs!$B159,-Inputs!$B157),0) -> -3423.9536 | F91: =-MAX(FV(Inputs!$B158/12,F$1*12+MthOff,Inputs!$B159,-Inputs!$B157),0) -> -2451.5512 | G91: =-MAX(FV(Inputs!$B158/12,G$1*12+MthOff,Inputs!$B159,-Inputs!$B157),0) -> -1459.5214 | H91: =-MAX(FV(Inputs!$B158/12,H$1*12+MthOff,Inputs!$B159,-Inputs!$B157),0) -> -447.46816 | I91: =-MAX(FV(Inputs!$B158/12,I$1*12+MthOff,Inputs!$B159,-Inputs!$B157),0) -> 0 | J91: =-MAX(FV(Inputs!$B158/12,J$1*12+MthOff,Inputs!$B159,-Inputs!$B157),0) -> 0 | ... AM91: =-MAX(FV(Inputs!$B158/12,AM$1*12+MthOff,Inputs!$B159,-Inputs!$B157),0) -> 0
A92: =TEXT(Inputs!$B$97,"") -> Painting | C92: =-MAX(FV(Inputs!$B163/12,C$1*12+MthOff,Inputs!$B164,-Inputs!$B162),0) -> -6642.0499 | D92: =-MAX(FV(Inputs!$B163/12,D$1*12+MthOff,Inputs!$B164,-Inputs!$B162),0) -> -5447.0129 | E92: =-MAX(FV(Inputs!$B163/12,E$1*12+MthOff,Inputs!$B164,-Inputs!$B162),0) -> -4190.8354 | F92: =-MAX(FV(Inputs!$B163/12,F$1*12+MthOff,Inputs!$B164,-Inputs!$B162),0) -> -2870.3896 | G92: =-MAX(FV(Inputs!$B163/12,G$1*12+MthOff,Inputs!$B164,-Inputs!$B162),0) -> -1482.3872 | H92: =-MAX(FV(Inputs!$B163/12,H$1*12+MthOff,Inputs!$B164,-Inputs!$B162),0) -> -23.372057 | I92: =-MAX(FV(Inputs!$B163/12,I$1*12+MthOff,Inputs!$B164,-Inputs!$B162),0) -> 0 | J92: =-MAX(FV(Inputs!$B163/12,J$1*12+MthOff,Inputs!$B164,-Inputs!$B162),0) -> 0 | ... AM92: =-MAX(FV(Inputs!$B163/12,AM$1*12+MthOff,Inputs!$B164,-Inputs!$B162),0) -> 0
A93: =TEXT(Inputs!$B$102,"") -> Boat | C93: =-MAX(FV(Inputs!$B168/12,C$1*12+MthOff,Inputs!$B169,-Inputs!$B167),0) -> -36106.783 | D93: =-MAX(FV(Inputs!$B168/12,D$1*12+MthOff,Inputs!$B169,-Inputs!$B167),0) -> -30636.379 | E93: =-MAX(FV(Inputs!$B168/12,E$1*12+MthOff,Inputs!$B169,-Inputs!$B167),0) -> -24828.573 | F93: =-MAX(FV(Inputs!$B168/12,F$1*12+MthOff,Inputs!$B169,-Inputs!$B167),0) -> -18662.554 | G93: =-MAX(FV(Inputs!$B168/12,G$1*12+MthOff,Inputs!$B169,-Inputs!$B167),0) -> -12116.229 | H93: =-MAX(FV(Inputs!$B168/12,H$1*12+MthOff,Inputs!$B169,-Inputs!$B167),0) -> -5166.1406 | I93: =-MAX(FV(Inputs!$B168/12,I$1*12+MthOff,Inputs!$B169,-Inputs!$B167),0) -> 0 | J93: =-MAX(FV(Inputs!$B168/12,J$1*12+MthOff,Inputs!$B169,-Inputs!$B167),0) -> 0 | ... AM93: =-MAX(FV(Inputs!$B168/12,AM$1*12+MthOff,Inputs!$B169,-Inputs!$B167),0) -> 0
A94: =TEXT(Inputs!$B$107,"") -> Antiques | C94: =-MAX(FV(Inputs!$B173/12,C$1*12+MthOff,Inputs!$B174,-Inputs!$B172),0) -> -2886.402 | D94: =-MAX(FV(Inputs!$B173/12,D$1*12+MthOff,Inputs!$B174,-Inputs!$B172),0) -> -1635.8926 | E94: =-MAX(FV(Inputs!$B173/12,E$1*12+MthOff,Inputs!$B174,-Inputs!$B172),0) -> -347.34775 | F94: =-MAX(FV(Inputs!$B173/12,F$1*12+MthOff,Inputs!$B174,-Inputs!$B172),0) -> 0 | G94: =-MAX(FV(Inputs!$B173/12,G$1*12+MthOff,Inputs!$B174,-Inputs!$B172),0) -> 0 | H94: =-MAX(FV(Inputs!$B173/12,H$1*12+MthOff,Inputs!$B174,-Inputs!$B172),0) -> 0 | I94: =-MAX(FV(Inputs!$B173/12,I$1*12+MthOff,Inputs!$B174,-Inputs!$B172),0) -> 0 | J94: =-MAX(FV(Inputs!$B173/12,J$1*12+MthOff,Inputs!$B174,-Inputs!$B172),0) -> 0 | ... AM94: =-MAX(FV(Inputs!$B173/12,AM$1*12+MthOff,Inputs!$B174,-Inputs!$B172),0) -> 0
A95: Other loan | C95: =-MAX(FV(Inputs!$B178/12,C$1*12+MthOff,Inputs!$B179,-Inputs!$B177),0) -> -3724.5365 | D95: =-MAX(FV(Inputs!$B178/12,D$1*12+MthOff,Inputs!$B179,-Inputs!$B177),0) -> -3337.4797 | E95: =-MAX(FV(Inputs!$B178/12,E$1*12+MthOff,Inputs!$B179,-Inputs!$B177),0) -> -2926.55 | F95: =-MAX(FV(Inputs!$B178/12,F$1*12+MthOff,Inputs!$B179,-Inputs!$B177),0) -> -2490.2751 | G95: =-MAX(FV(Inputs!$B178/12,G$1*12+MthOff,Inputs!$B179,-Inputs!$B177),0) -> -2027.0917 | H95: =-MAX(FV(Inputs!$B178/12,H$1*12+MthOff,Inputs!$B179,-Inputs!$B177),0) -> -1535.3401 | I95: =-MAX(FV(Inputs!$B178/12,I$1*12+MthOff,Inputs!$B179,-Inputs!$B177),0) -> -1013.2584 | J95: =-MAX(FV(Inputs!$B178/12,J$1*12+MthOff,Inputs!$B179,-Inputs!$B177),0) -> -458.97588 | ... AM95: =-MAX(FV(Inputs!$B178/12,AM$1*12+MthOff,Inputs!$B179,-Inputs!$B177),0) -> 0
C96: =SUM(C67:C95) -> 1680400.3 | D96: =SUM(D67:D95) -> 1747961.5 | E96: =SUM(E67:E95) -> 1834109.3 | F96: =SUM(F67:F95) -> 1900859.6 | G96: =SUM(G67:G95) -> 1915703 | H96: =SUM(H67:H95) -> 2018641.6 | I96: =SUM(I67:I95) -> 2125722.2 | J96: =SUM(J67:J95) -> 2243536.4 | ... AM96: =SUM(AM67:AM95) -> 6324206.1
A98: Cash available (after buffer) | C98: =C68-buffer -> 16108.438 | D98: =D68-buffer -> 30012.145 | E98: =E68-buffer -> 50169.649 | F98: =F68-buffer -> 52227.784 | G98: =G68-buffer -> 250455.16 | H98: =H68-buffer -> 296986.84 | I98: =I68-buffer -> 363754.64 | J98: =J68-buffer -> 435067.93 | ... AM98: =AM68-buffer -> 2480522.5
A99: Liquidation required | C99: =IF(C98<0,-C98,0) -> 0 | D99: =IF(D98+SUM($C99:C99)<0,-(D98+SUM($C99:C99)),0) -> 0 | E99: =IF(E98+SUM($C99:D99)<0,-(E98+SUM($C99:D99)),0) -> 0 | F99: =IF(F98+SUM($C99:E99)<0,-(F98+SUM($C99:E99)),0) -> 0 | G99: =IF(G98+SUM($C99:F99)<0,-(G98+SUM($C99:F99)),0) -> 0 | H99: =IF(H98+SUM($C99:G99)<0,-(H98+SUM($C99:G99)),0) -> 0 | I99: =IF(I98+SUM($C99:H99)<0,-(I98+SUM($C99:H99)),0) -> 0 | J99: =IF(J98+SUM($C99:I99)<0,-(J98+SUM($C99:I99)),0) -> 0 | K99: =IF(K98+SUM($C99:J99)<0,-(K98+SUM($C99:J99)),0) -> 0 | ... AM99: =IF(AM98+SUM($C99:AL99)<0,-(AM98+SUM($C99:AL99)),0) -> 0
A101: Liquidations
A103: Stock market equity
A104: b/fwd | C104: =C82 -> 31782.574 | D104: =C107 -> 31782.574 | E104: =D107 -> 27015.188 | F104: =E107 -> 31782.574 | G104: =F107 -> 34325.18 | H104: =G107 -> 37071.195 | I104: =H107 -> 40036.89 | J104: =I107 -> 32029.512 | K104: =J107 -> 34502.746 | ... AM104: =AL107 -> 100819.7
A105: Disposals | C105: =-MIN(C104, C99/(1-Inputs!$B$283)) -> 0 | D105: =-MIN(D104, D99/(1-Inputs!$B$283)) -> 0 | E105: =-MIN(E104, E99/(1-Inputs!$B$283)) -> 0 | F105: =-MIN(F104, F99/(1-Inputs!$B$283)) -> 0 | G105: =-MIN(G104, G99/(1-Inputs!$B$283)) -> 0 | H105: =-MIN(H104, H99/(1-Inputs!$B$283)) -> 0 | I105: =-MIN(I104, I99/(1-Inputs!$B$283)) -> 0 | J105: =-MIN(J104, J99/(1-Inputs!$B$283)) -> 0 | ... AM105: =-MIN(AM104, AM99/(1-Inputs!$B$283)) -> 0
...

Sheet RetEarly_Engine
B1: 0 | C1: 1 | D1: =C1+1 -> 2 | E1: =D1+1 -> 3 | F1: =E1+1 -> 4 | G1: =F1+1 -> 5 | H1: =G1+1 -> 6 | I1: =H1+1 -> 7 | J1: =I1+1 -> 8 | K1: =J1+1 -> 9 | ... AM1: =AL1+1 -> 37
B2: Year | C2: =YEAR(TODAY()) -> 2026 | D2: =C2+1 -> 2027 | E2: =D2+1 -> 2028 | F2: =E2+1 -> 2029 | G2: =F2+1 -> 2030 | H2: =G2+1 -> 2031 | I2: =H2+1 -> 2032 | J2: =I2+1 -> 2033 | K2: =J2+1 -> 2034 | ... AM2: =AL2+1 -> 2062
B3: 49 | C3: =Inputs!B4 -> 48 | D3: =C3+1 -> 49 | E3: =D3+1 -> 50 | F3: =E3+1 -> 51 | G3: =F3+1 -> 52 | H3: =G3+1 -> 53 | I3: =H3+1 -> 54 | J3: =I3+1 -> 55 | K3: =J3+1 -> 56 | ... AM3: =AL3+1 -> 84
A4: Inflows
A5: Net employment / self-employment income | C5: =IF(AND(Inputs!$B$19>C3,$B$3>C3),Inputs!$B$6*(1+sincr)^B1,0)*ProRate -> 60000 | D5: =IF(AND(Inputs!$B$19>D3,$B$3>D3),Inputs!$B$6*(1+sincr)^C1,0) -> 0 | E5: =IF(AND(Inputs!$B$19>E3,$B$3>E3),Inputs!$B$6*(1+sincr)^D1,0) -> 0 | F5: =IF(AND(Inputs!$B$19>F3,$B$3>F3),Inputs!$B$6*(1+sincr)^E1,0) -> 0 | G5: =IF(AND(Inputs!$B$19>G3,$B$3>G3),Inputs!$B$6*(1+sincr)^F1,0) -> 0 | H5: =IF(AND(Inputs!$B$19>H3,$B$3>H3),Inputs!$B$6*(1+sincr)^G1,0) -> 0 | I5: =IF(AND(Inputs!$B$19>I3,$B$3>I3),Inputs!$B$6*(1+sincr)^H1,0) -> 0 | J5: =IF(AND(Inputs!$B$19>J3,$B$3>J3),Inputs!$B$6*(1+sincr)^I1,0) -> 0 | K5: =IF(AND(Inputs!$B$19>K3,$B$3>K3),Inputs!$B$6*(1+sincr)^J1,0) -> 0 | ... AM5: =IF(AND(Inputs!$B$19>AM3,$B$3>AM3),Inputs!$B$6*(1+sincr)^AL1,0) -> 0
A6: Net from other work | C6: =IF(C$3<=Inputs!$B$120,Inputs!$B$119,0)*(1+inf)^B$1*ProRate -> 1500 | D6: =IF(D$3<=Inputs!$B$120,Inputs!$B$119,0)*(1+inf)^C$1 -> 2050 | E6: =IF(E$3<=Inputs!$B$120,Inputs!$B$119,0)*(1+inf)^D$1 -> 2101.25 | F6: =IF(F$3<=Inputs!$B$120,Inputs!$B$119,0)*(1+inf)^E$1 -> 2153.7812 | G6: =IF(G$3<=Inputs!$B$120,Inputs!$B$119,0)*(1+inf)^F$1 -> 2207.6258 | H6: =IF(H$3<=Inputs!$B$120,Inputs!$B$119,0)*(1+inf)^G$1 -> 2262.8164 | I6: =IF(I$3<=Inputs!$B$120,Inputs!$B$119,0)*(1+inf)^H$1 -> 2319.3868 | J6: =IF(J$3<=Inputs!$B$120,Inputs!$B$119,0)*(1+inf)^I$1 -> 2377.3715 | K6: =IF(K$3<=Inputs!$B$120,Inputs!$B$119,0)*(1+inf)^J$1 -> 2436.8058 | ... AM6: =IF(AM$3<=Inputs!$B$120,Inputs!$B$119,0)*(1+inf)^AL$1 -> 0
A7: Net rental income from other properties
A8: =TEXT(Inputs!$B$60,"") -> Sliema | C8: =Inputs!B113*ProRate -> 9000 | D8: =C8*(1+rinc) -> 9270 | E8: =D8*(1+rinc) -> 9548.1 | F8: =E8*(1+rinc) -> 9834.543 | G8: =F8*(1+rinc) -> 10129.579 | H8: =G8*(1+rinc) -> 10433.467 | I8: =H8*(1+rinc) -> 10746.471 | J8: =I8*(1+rinc) -> 11068.865 | K8: =J8*(1+rinc) -> 11400.931 | ... AM8: =AL8*(1+rinc) -> 26084.505
A9: =TEXT(Inputs!$B$65,"") -> Gzira | C9: =Inputs!B114*ProRate -> 7500 | D9: =C9*(1+rinc) -> 7725 | E9: =D9*(1+rinc) -> 7956.75 | F9: =E9*(1+rinc) -> 8195.4525 | G9: =F9*(1+rinc) -> 8441.3161 | H9: =G9*(1+rinc) -> 8694.5556 | I9: =H9*(1+rinc) -> 8955.3922 | J9: =I9*(1+rinc) -> 9224.054 | K9: =J9*(1+rinc) -> 9500.7756 | ... AM9: =AL9*(1+rinc) -> 21737.087
A10: =TEXT(Inputs!$B$70,"") -> Qormi | C10: =Inputs!B115*ProRate -> 6000 | D10: =C10*(1+rinc) -> 6180 | E10: =D10*(1+rinc) -> 6365.4 | F10: =E10*(1+rinc) -> 6556.362 | G10: =F10*(1+rinc) -> 6753.0529 | H10: =G10*(1+rinc) -> 6955.6444 | I10: =H10*(1+rinc) -> 7164.3138 | J10: =I10*(1+rinc) -> 7379.2432 | K10: =J10*(1+rinc) -> 7600.6205 | ... AM10: =AL10*(1+rinc) -> 17389.67
A11: =TEXT(Inputs!$B$75,"") -> Gudja | C11: =Inputs!B116*ProRate -> 3750 | D11: =C11*(1+rinc) -> 3862.5 | E11: =D11*(1+rinc) -> 3978.375 | F11: =E11*(1+rinc) -> 4097.7262 | G11: =F11*(1+rinc) -> 4220.658 | H11: =G11*(1+rinc) -> 4347.2778 | I11: =H11*(1+rinc) -> 4477.6961 | J11: =I11*(1+rinc) -> 4612.027 | K11: =J11*(1+rinc) -> 4750.3878 | ... AM11: =AL11*(1+rinc) -> 10868.544
A12: =TEXT(Inputs!$B$80,"") -> Marsa | C12: =Inputs!B117*ProRate -> 4875 | D12: =C12*(1+rinc) -> 5021.25 | E12: =D12*(1+rinc) -> 5171.8875 | F12: =E12*(1+rinc) -> 5327.0441 | G12: =F12*(1+rinc) -> 5486.8554 | H12: =G12*(1+rinc) -> 5651.4611 | I12: =H12*(1+rinc) -> 5821.0049 | J12: =I12*(1+rinc) -> 5995.6351 | K12: =J12*(1+rinc) -> 6175.5041 | ... AM12: =AL12*(1+rinc) -> 14129.107
A13: Full pension | C13: =IF(C$3<Inputs!$B$19,0,Inputs!$B$21)*(1+inf)^B$1*ProRate -> 0 | D13: =IF(D$3<Inputs!$B$19,0,Inputs!$B$21)*(1+inf)^C$1 -> 0 | E13: =IF(E$3<Inputs!$B$19,0,Inputs!$B$21)*(1+inf)^D$1 -> 0 | F13: =IF(F$3<Inputs!$B$19,0,Inputs!$B$21)*(1+inf)^E$1 -> 0 | G13: =IF(G$3<Inputs!$B$19,0,Inputs!$B$21)*(1+inf)^F$1 -> 0 | H13: =IF(H$3<Inputs!$B$19,0,Inputs!$B$21)*(1+inf)^G$1 -> 0 | I13: =IF(I$3<Inputs!$B$19,0,Inputs!$B$21)*(1+inf)^H$1 -> 0 | J13: =IF(J$3<Inputs!$B$19,0,Inputs!$B$21)*(1+inf)^I$1 -> 0 | K13: =IF(K$3<Inputs!$B$19,0,Inputs!$B$21)*(1+inf)^J$1 -> 0 | ... AM13: =IF(AM$3<Inputs!$B$19,0,Inputs!$B$21)*(1+inf)^AL$1 -> 38920.565
A14: Pension reduction from early retirement | C14: =MIN(0,MAX(-IF(C13=0,0,(Inputs!$B$19-INDEX(3:3,MATCH(0,5:5,0))))*Inputs!$B$277*(1+inf)^B$1*ProRate,-C13)) -> 0 | D14: =MIN(0,MAX(-IF(D13=0,0,(Inputs!$B$19-INDEX(3:3,MATCH(0,5:5,0))))*Inputs!$B$277*(1+inf)^C$1,-D13)) -> 0 | E14: =MIN(0,MAX(-IF(E13=0,0,(Inputs!$B$19-INDEX(3:3,MATCH(0,5:5,0))))*Inputs!$B$277*(1+inf)^D$1,-E13)) -> 0 | F14: =MIN(0,MAX(-IF(F13=0,0,(Inputs!$B$19-INDEX(3:3,MATCH(0,5:5,0))))*Inputs!$B$277*(1+inf)^E$1,-F13)) -> 0 | G14: =MIN(0,MAX(-IF(G13=0,0,(Inputs!$B$19-INDEX(3:3,MATCH(0,5:5,0))))*Inputs!$B$277*(1+inf)^F$1,-G13)) -> 0 | H14: =MIN(0,MAX(-IF(H13=0,0,(Inputs!$B$19-INDEX(3:3,MATCH(0,5:5,0))))*Inputs!$B$277*(1+inf)^G$1,-H13)) -> 0 | I14: =MIN(0,MAX(-IF(I13=0,0,(Inputs!$B$19-INDEX(3:3,MATCH(0,5:5,0))))*Inputs!$B$277*(1+inf)^H$1,-I13)) -> 0 | J14: =MIN(0,MAX(-IF(J13=0,0,(Inputs!$B$19-INDEX(3:3,MATCH(0,5:5,0))))*Inputs!$B$277*(1+inf)^I$1,-J13)) -> 0 | K14: =MIN(0,MAX(-IF(K13=0,0,(Inputs!$B$19-INDEX(3:3,MATCH(0,5:5,0))))*Inputs!$B$277*(1+inf)^J$1,-K13)) -> 0 | ... AM14: =MIN(0,MAX(-IF(AM13=0,0,(Inputs!$B$19-INDEX(3:3,MATCH(0,5:5,0))))*Inputs!$B$277*(1+inf)^AL$1,-AM13)) -> -11676.17
A15: Other post-retirement income | C15: =IF(AND(C$3>=Inputs!$B$262,C$3<=Inputs!$B$263),Inputs!$B$261*(1+inf)^B$1,0)*ProRate -> 0 | D15: =IF(AND(D$3>=Inputs!$B$262,D$3<=Inputs!$B$263),Inputs!$B$261*(1+inf)^C$1,0) -> 0 | E15: =IF(AND(E$3>=Inputs!$B$262,E$3<=Inputs!$B$263),Inputs!$B$261*(1+inf)^D$1,0) -> 0 | F15: =IF(AND(F$3>=Inputs!$B$262,F$3<=Inputs!$B$263),Inputs!$B$261*(1+inf)^E$1,0) -> 0 | G15: =IF(AND(G$3>=Inputs!$B$262,G$3<=Inputs!$B$263),Inputs!$B$261*(1+inf)^F$1,0) -> 0 | H15: =IF(AND(H$3>=Inputs!$B$262,H$3<=Inputs!$B$263),Inputs!$B$261*(1+inf)^G$1,0) -> 0 | I15: =IF(AND(I$3>=Inputs!$B$262,I$3<=Inputs!$B$263),Inputs!$B$261*(1+inf)^H$1,0) -> 0 | J15: =IF(AND(J$3>=Inputs!$B$262,J$3<=Inputs!$B$263),Inputs!$B$261*(1+inf)^I$1,0) -> 0 | K15: =IF(AND(K$3>=Inputs!$B$262,K$3<=Inputs!$B$263),Inputs!$B$261*(1+inf)^J$1,0) -> 0 | ... AM15: =IF(AND(AM$3>=Inputs!$B$262,AM$3<=Inputs!$B$263),Inputs!$B$261*(1+inf)^AL$1,0) -> 0
A16: Major one-off income events
A17: =TEXT(Inputs!B184,"") -> Inheritance | C17: =IF(C$2=Inputs!$B186,Inputs!$B185,0)*(1+inf)^B$1 -> 0 | D17: =IF(D$2=Inputs!$B186,Inputs!$B185,0)*(1+inf)^C$1 -> 0 | E17: =IF(E$2=Inputs!$B186,Inputs!$B185,0)*(1+inf)^D$1 -> 0 | F17: =IF(F$2=Inputs!$B186,Inputs!$B185,0)*(1+inf)^E$1 -> 0 | G17: =IF(G$2=Inputs!$B186,Inputs!$B185,0)*(1+inf)^F$1 -> 0 | H17: =IF(H$2=Inputs!$B186,Inputs!$B185,0)*(1+inf)^G$1 -> 0 | I17: =IF(I$2=Inputs!$B186,Inputs!$B185,0)*(1+inf)^H$1 -> 0 | J17: =IF(J$2=Inputs!$B186,Inputs!$B185,0)*(1+inf)^I$1 -> 0 | ... AM17: =IF(AM$2=Inputs!$B186,Inputs!$B185,0)*(1+inf)^AL$1 -> 0
A18: =TEXT(Inputs!B189,"") -> Sell Painting | C18: =IF(C$2=Inputs!$B191,Inputs!$B190,0)*(1+inf)^B$1 -> 0 | D18: =IF(D$2=Inputs!$B191,Inputs!$B190,0)*(1+inf)^C$1 -> 0 | E18: =IF(E$2=Inputs!$B191,Inputs!$B190,0)*(1+inf)^D$1 -> 0 | F18: =IF(F$2=Inputs!$B191,Inputs!$B190,0)*(1+inf)^E$1 -> 10768.906 | G18: =IF(G$2=Inputs!$B191,Inputs!$B190,0)*(1+inf)^F$1 -> 0 | H18: =IF(H$2=Inputs!$B191,Inputs!$B190,0)*(1+inf)^G$1 -> 0 | I18: =IF(I$2=Inputs!$B191,Inputs!$B190,0)*(1+inf)^H$1 -> 0 | J18: =IF(J$2=Inputs!$B191,Inputs!$B190,0)*(1+inf)^I$1 -> 0 | ... AM18: =IF(AM$2=Inputs!$B191,Inputs!$B190,0)*(1+inf)^AL$1 -> 0
A19: =TEXT(Inputs!B194,"") -> Sell Jewels | C19: =IF(C$2=Inputs!$B196,Inputs!$B195,0)*(1+inf)^B$1 -> 0 | D19: =IF(D$2=Inputs!$B196,Inputs!$B195,0)*(1+inf)^C$1 -> 0 | E19: =IF(E$2=Inputs!$B196,Inputs!$B195,0)*(1+inf)^D$1 -> 0 | F19: =IF(F$2=Inputs!$B196,Inputs!$B195,0)*(1+inf)^E$1 -> 0 | G19: =IF(G$2=Inputs!$B196,Inputs!$B195,0)*(1+inf)^F$1 -> 0 | H19: =IF(H$2=Inputs!$B196,Inputs!$B195,0)*(1+inf)^G$1 -> 0 | I19: =IF(I$2=Inputs!$B196,Inputs!$B195,0)*(1+inf)^H$1 -> 5798.4671 | J19: =IF(J$2=Inputs!$B196,Inputs!$B195,0)*(1+inf)^I$1 -> 0 | ... AM19: =IF(AM$2=Inputs!$B196,Inputs!$B195,0)*(1+inf)^AL$1 -> 0
A20: Sale of home (downsizing) | C20: =IF(AND(Inputs!$B$217<>"",C$2=Inputs!$B$217,Inputs!$B$12>0),(IF(B$1=0,Inputs!$B$12*(1+princ)^ProRate,B69*(1+princ)))*(1-DCprop),0) -> 0 | D20: =IF(AND(Inputs!$B$217<>"",D$2=Inputs!$B$217,Inputs!$B$12>0),(IF(C$1=0,Inputs!$B$12*(1+princ)^ProRate,C69*(1+princ)))*(1-DCprop),0) -> 0 | E20: =IF(AND(Inputs!$B$217<>"",E$2=Inputs!$B$217,Inputs!$B$12>0),(IF(D$1=0,Inputs!$B$12*(1+princ)^ProRate,D69*(1+princ)))*(1-DCprop),0) -> 0 | F20: =IF(AND(Inputs!$B$217<>"",F$2=Inputs!$B$217,Inputs!$B$12>0),(IF(E$1=0,Inputs!$B$12*(1+princ)^ProRate,E69*(1+princ)))*(1-DCprop),0) -> 0 | G20: =IF(AND(Inputs!$B$217<>"",G$2=Inputs!$B$217,Inputs!$B$12>0),(IF(F$1=0,Inputs!$B$12*(1+princ)^ProRate,F69*(1+princ)))*(1-DCprop),0) -> 489064.06 | H20: =IF(AND(Inputs!$B$217<>"",H$2=Inputs!$B$217,Inputs!$B$12>0),(IF(G$1=0,Inputs!$B$12*(1+princ)^ProRate,G69*(1+princ)))*(1-DCprop),0) -> 0 | I20: =IF(AND(Inputs!$B$217<>"",I$2=Inputs!$B$217,Inputs!$B$12>0),(IF(H$1=0,Inputs!$B$12*(1+princ)^ProRate,H69*(1+princ)))*(1-DCprop),0) -> 0 | J20: =IF(AND(Inputs!$B$217<>"",J$2=Inputs!$B$217,Inputs!$B$12>0),(IF(I$1=0,Inputs!$B$12*(1+princ)^ProRate,I69*(1+princ)))*(1-DCprop),0) -> 0 | ... AM20: =IF(AND(Inputs!$B$217<>"",AM$2=Inputs!$B$217,Inputs!$B$12>0),(IF(AL$1=0,Inputs!$B$12*(1+princ)^ProRate,AL69*(1+princ)))*(1-DCprop),0) -> 0
A21: Interest on cash balances | C21: =MAX(AVERAGE(C64,C64+SUM(C5:C20)-C61)*Inputs!$B$269,0) -> 1433.4375 | D21: =MAX(AVERAGE(D64,D64+SUM(D5:D20)-D61)*Inputs!$B$269,0) -> 773.95781 | E21: =MAX(AVERAGE(E64,E64+SUM(E5:E20)-E61)*Inputs!$B$269,0) -> 0 | F21: =MAX(AVERAGE(F64,F64+SUM(F5:F20)-F61)*Inputs!$B$269,0) -> 0 | G21: =MAX(AVERAGE(G64,G64+SUM(G5:G20)-G61)*Inputs!$B$269,0) -> 0 | H21: =MAX(AVERAGE(H64,H64+SUM(H5:H20)-H61)*Inputs!$B$269,0) -> 0 | I21: =MAX(AVERAGE(I64,I64+SUM(I5:I20)-I61)*Inputs!$B$269,0) -> 0 | J21: =MAX(AVERAGE(J64,J64+SUM(J5:J20)-J61)*Inputs!$B$269,0) -> 0 | ... AM21: =MAX(AVERAGE(AM64,AM64+SUM(AM5:AM20)-AM61)*Inputs!$B$269,0) -> 0
C22: =SUM(C4:C21) -> 94058.438 | D22: =SUM(D4:D21) -> 34882.708 | E22: =SUM(E4:E21) -> 35121.762 | F22: =SUM(F4:F21) -> 46933.815 | G22: =SUM(G4:G21) -> 526303.15 | H22: =SUM(H4:H21) -> 38345.222 | I22: =SUM(I4:I21) -> 45282.732 | J22: =SUM(J4:J21) -> 40657.196 | ... AM22: =SUM(AM4:AM21) -> 117453.31
A23: Outflows
A24: Credit cards cleared | C24: =Inputs!B124 -> 1000 | D24: 0 | E24: 0 | F24: 0 | G24: 0 | H24: 0 | I24: 0 | J24: 0 | K24: 0 | L24: 0 | M24: 0 | N24: 0 | O24: 0 | P24: 0 | Q24: 0 | R24: 0 | S24: 0 | T24: 0 | U24: 0 | V24: 0 | W24: 0 | X24: 0 | Y24: 0 | Z24: 0 | AA24: 0 | AB24: 0 | AC24: 0 | AD24: 0 | AE24: 0 | AF24: 0 | AG24: 0 | AH24: 0 | AI24: 0 | AJ24: 0 | AK24: 0 | AL24: 0 | AM24: 0
A25: Home loan repayment | C25: =IF(AND(Inputs!$B$217<>"",C$2=Inputs!$B$217,Inputs!$B$12>0,Inputs!$B$15>0),MIN(IF(B$1=0,MthRem,12),MAX(Inputs!$G$15-IF(B$1=0,0,B$1*12+MthOff),0))*Inputs!$B$17+MAX(FV(Inputs!$B$16/12,C$1*12+MthOff,Inputs!$B$17,-Inputs!$B$15),0),IF(AND(Inputs!$B$217<>"",C$2>Inputs!$B$217,Inputs!$B$12>0),0,MIN(IF(B$1=0,MthRem,12),MAX(Inputs!$G$15-IF(B$1=0,0,B$1*12+MthOff),0))*Inputs!$B$17)) -> 2700 | D25: =IF(AND(Inputs!$B$217<>"",D$2=Inputs!$B$217,Inputs!$B$12>0,Inputs!$B$15>0),MIN(IF(C$1=0,MthRem,12),MAX(Inputs!$G$15-IF(C$1=0,0,C$1*12+MthOff),0))*Inputs!$B$17+MAX(FV(Inputs!$B$16/12,D$1*12+MthOff,Inputs!$B$17,-Inputs!$B$15),0),IF(AND(Inputs!$B$217<>"",D$2>Inputs!$B$217,Inputs!$B$12>0),0,MIN(IF(C$1=0,MthRem,12),MAX(Inputs!$G$15-IF(C$1=0,0,C$1*12+MthOff),0))*Inputs!$B$17)) -> 3600 | E25: =IF(AND(Inputs!$B$217<>"",E$2=Inputs!$B$217,Inputs!$B$12>0,Inputs!$B$15>0),MIN(IF(D$1=0,MthRem,12),MAX(Inputs!$G$15-IF(D$1=0,0,D$1*12+MthOff),0))*Inputs!$B$17+MAX(FV(Inputs!$B$16/12,E$1*12+MthOff,Inputs!$B$17,-Inputs!$B$15),0),IF(AND(Inputs!$B$217<>"",E$2>Inputs!$B$217,Inputs!$B$12>0),0,MIN(IF(D$1=0,MthRem,12),MAX(Inputs!$G$15-IF(D$1=0,0,D$1*12+MthOff),0))*Inputs!$B$17)) -> 3600 | F25: =IF(AND(Inputs!$B$217<>"",F$2=Inputs!$B$217,Inputs!$B$12>0,Inputs!$B$15>0),MIN(IF(E$1=0,MthRem,12),MAX(Inputs!$G$15-IF(E$1=0,0,E$1*12+MthOff),0))*Inputs!$B$17+MAX(FV(Inputs!$B$16/12,F$1*12+MthOff,Inputs!$B$17,-Inputs!$B$15),0),IF(AND(Inputs!$B$217<>"",F$2>Inputs!$B$217,Inputs!$B$12>0),0,MIN(IF(E$1=0,MthRem,12),MAX(Inputs!$G$15-IF(E$1=0,0,E$1*12+MthOff),0))*Inputs!$B$17)) -> 3600 | G25: =IF(AND(Inputs!$B$217<>"",G$2=Inputs!$B$217,Inputs!$B$12>0,Inputs!$B$15>0),MIN(IF(F$1=0,MthRem,12),MAX(Inputs!$G$15-IF(F$1=0,0,F$1*12+MthOff),0))*Inputs!$B$17+MAX(FV(Inputs!$B$16/12,G$1*12+MthOff,Inputs!$B$17,-Inputs!$B$15),0),IF(AND(Inputs!$B$217<>"",G$2>Inputs!$B$217,Inputs!$B$12>0),0,MIN(IF(F$1=0,MthRem,12),MAX(Inputs!$G$15-IF(F$1=0,0,F$1*12+MthOff),0))*Inputs!$B$17)) -> 42893.638 | H25: =IF(AND(Inputs!$B$217<>"",H$2=Inputs!$B$217,Inputs!$B$12>0,Inputs!$B$15>0),MIN(IF(G$1=0,MthRem,12),MAX(Inputs!$G$15-IF(G$1=0,0,G$1*12+MthOff),0))*Inputs!$B$17+MAX(FV(Inputs!$B$16/12,H$1*12+MthOff,Inputs!$B$17,-Inputs!$B$15),0),IF(AND(Inputs!$B$217<>"",H$2>Inputs!$B$217,Inputs!$B$12>0),0,MIN(IF(G$1=0,MthRem,12),MAX(Inputs!$G$15-IF(G$1=0,0,G$1*12+MthOff),0))*Inputs!$B$17)) -> 0 | I25: =IF(AND(Inputs!$B$217<>"",I$2=Inputs!$B$217,Inputs!$B$12>0,Inputs!$B$15>0),MIN(IF(H$1=0,MthRem,12),MAX(Inputs!$G$15-IF(H$1=0,0,H$1*12+MthOff),0))*Inputs!$B$17+MAX(FV(Inputs!$B$16/12,I$1*12+MthOff,Inputs!$B$17,-Inputs!$B$15),0),IF(AND(Inputs!$B$217<>"",I$2>Inputs!$B$217,Inputs!$B$12>0),0,MIN(IF(H$1=0,MthRem,12),MAX(Inputs!$G$15-IF(H$1=0,0,H$1*12+MthOff),0))*Inputs!$B$17)) -> 0 | J25: =IF(AND(Inputs!$B$217<>"",J$2=Inputs!$B$217,Inputs!$B$12>0,Inputs!$B$15>0),MIN(IF(I$1=0,MthRem,12),MAX(Inputs!$G$15-IF(I$1=0,0,I$1*12+MthOff),0))*Inputs!$B$17+MAX(FV(Inputs!$B$16/12,J$1*12+MthOff,Inputs!$B$17,-Inputs!$B$15),0),IF(AND(Inputs!$B$217<>"",J$2>Inputs!$B$217,Inputs!$B$12>0),0,MIN(IF(I$1=0,MthRem,12),MAX(Inputs!$G$15-IF(I$1=0,0,I$1*12+MthOff),0))*Inputs!$B$17)) -> 0 | ... AM25: =IF(AND(Inputs!$B$217<>"",AM$2=Inputs!$B$217,Inputs!$B$12>0,Inputs!$B$15>0),MIN(IF(AL$1=0,MthRem,12),MAX(Inputs!$G$15-IF(AL$1=0,0,AL$1*12+MthOff),0))*Inputs!$B$17+MAX(FV(Inputs!$B$16/12,AM$1*12+MthOff,Inputs!$B$17,-Inputs!$B$15),0),IF(AND(Inputs!$B$217<>"",AM$2>Inputs!$B$217,Inputs!$B$12>0),0,MIN(IF(AL$1=0,MthRem,12),MAX(Inputs!$G$15-IF(AL$1=0,0,AL$1*12+MthOff),0))*Inputs!$B$17)) -> 0
A26: Other asset loans repayments
A27: =TEXT(Inputs!$B$60,"") -> Sliema | C27: =MIN(IF(B$1=0,MthRem,12), MAX(Inputs!$G$127-IF(B$1=0,0,B$1*12+MthOff), 0))*Inputs!$B$129 -> 4500 | D27: =MIN(IF(C$1=0,MthRem,12), MAX(Inputs!$G$127-IF(C$1=0,0,C$1*12+MthOff), 0))*Inputs!$B$129 -> 6000 | E27: =MIN(IF(D$1=0,MthRem,12), MAX(Inputs!$G$127-IF(D$1=0,0,D$1*12+MthOff), 0))*Inputs!$B$129 -> 6000 | F27: =MIN(IF(E$1=0,MthRem,12), MAX(Inputs!$G$127-IF(E$1=0,0,E$1*12+MthOff), 0))*Inputs!$B$129 -> 6000 | G27: =MIN(IF(F$1=0,MthRem,12), MAX(Inputs!$G$127-IF(F$1=0,0,F$1*12+MthOff), 0))*Inputs!$B$129 -> 6000 | H27: =MIN(IF(G$1=0,MthRem,12), MAX(Inputs!$G$127-IF(G$1=0,0,G$1*12+MthOff), 0))*Inputs!$B$129 -> 6000 | I27: =MIN(IF(H$1=0,MthRem,12), MAX(Inputs!$G$127-IF(H$1=0,0,H$1*12+MthOff), 0))*Inputs!$B$129 -> 6000 | J27: =MIN(IF(I$1=0,MthRem,12), MAX(Inputs!$G$127-IF(I$1=0,0,I$1*12+MthOff), 0))*Inputs!$B$129 -> 6000 | ... AM27: =MIN(IF(AL$1=0,MthRem,12), MAX(Inputs!$G$127-IF(AL$1=0,0,AL$1*12+MthOff), 0))*Inputs!$B$129 -> 0
A28: =TEXT(Inputs!$B$65,"") -> Gzira | C28: =MIN(IF(B$1=0,MthRem,12), MAX(Inputs!$G$132-IF(B$1=0,0,B$1*12+MthOff), 0))*Inputs!$B$134 -> 1800 | D28: =MIN(IF(C$1=0,MthRem,12), MAX(Inputs!$G$132-IF(C$1=0,0,C$1*12+MthOff), 0))*Inputs!$B$134 -> 2400 | E28: =MIN(IF(D$1=0,MthRem,12), MAX(Inputs!$G$132-IF(D$1=0,0,D$1*12+MthOff), 0))*Inputs!$B$134 -> 2400 | F28: =MIN(IF(E$1=0,MthRem,12), MAX(Inputs!$G$132-IF(E$1=0,0,E$1*12+MthOff), 0))*Inputs!$B$134 -> 2223.4029 | G28: =MIN(IF(F$1=0,MthRem,12), MAX(Inputs!$G$132-IF(F$1=0,0,F$1*12+MthOff), 0))*Inputs!$B$134 -> 0 | H28: =MIN(IF(G$1=0,MthRem,12), MAX(Inputs!$G$132-IF(G$1=0,0,G$1*12+MthOff), 0))*Inputs!$B$134 -> 0 | I28: =MIN(IF(H$1=0,MthRem,12), MAX(Inputs!$G$132-IF(H$1=0,0,H$1*12+MthOff), 0))*Inputs!$B$134 -> 0 | J28: =MIN(IF(I$1=0,MthRem,12), MAX(Inputs!$G$132-IF(I$1=0,0,I$1*12+MthOff), 0))*Inputs!$B$134 -> 0 | ... AM28: =MIN(IF(AL$1=0,MthRem,12), MAX(Inputs!$G$132-IF(AL$1=0,0,AL$1*12+MthOff), 0))*Inputs!$B$134 -> 0
A29: =TEXT(Inputs!$B$70,"") -> Qormi | C29: =MIN(IF(B$1=0,MthRem,12), MAX(Inputs!$G$137-IF(B$1=0,0,B$1*12+MthOff), 0))*Inputs!$B$139 -> 2250 | D29: =MIN(IF(C$1=0,MthRem,12), MAX(Inputs!$G$137-IF(C$1=0,0,C$1*12+MthOff), 0))*Inputs!$B$139 -> 3000 | E29: =MIN(IF(D$1=0,MthRem,12), MAX(Inputs!$G$137-IF(D$1=0,0,D$1*12+MthOff), 0))*Inputs!$B$139 -> 3000 | F29: =MIN(IF(E$1=0,MthRem,12), MAX(Inputs!$G$137-IF(E$1=0,0,E$1*12+MthOff), 0))*Inputs!$B$139 -> 3000 | G29: =MIN(IF(F$1=0,MthRem,12), MAX(Inputs!$G$137-IF(F$1=0,0,F$1*12+MthOff), 0))*Inputs!$B$139 -> 3000 | H29: =MIN(IF(G$1=0,MthRem,12), MAX(Inputs!$G$137-IF(G$1=0,0,G$1*12+MthOff), 0))*Inputs!$B$139 -> 3000 | I29: =MIN(IF(H$1=0,MthRem,12), MAX(Inputs!$G$137-IF(H$1=0,0,H$1*12+MthOff), 0))*Inputs!$B$139 -> 46.859686 | J29: =MIN(IF(I$1=0,MthRem,12), MAX(Inputs!$G$137-IF(I$1=0,0,I$1*12+MthOff), 0))*Inputs!$B$139 -> 0 | ... AM29: =MIN(IF(AL$1=0,MthRem,12), MAX(Inputs!$G$137-IF(AL$1=0,0,AL$1*12+MthOff), 0))*Inputs!$B$139 -> 0
A30: =TEXT(Inputs!$B$75,"") -> Gudja | C30: =MIN(IF(B$1=0,MthRem,12), MAX(Inputs!$G$142-IF(B$1=0,0,B$1*12+MthOff), 0))*Inputs!$B$144 -> 720 | D30: =MIN(IF(C$1=0,MthRem,12), MAX(Inputs!$G$142-IF(C$1=0,0,C$1*12+MthOff), 0))*Inputs!$B$144 -> 960 | E30: =MIN(IF(D$1=0,MthRem,12), MAX(Inputs!$G$142-IF(D$1=0,0,D$1*12+MthOff), 0))*Inputs!$B$144 -> 960 | F30: =MIN(IF(E$1=0,MthRem,12), MAX(Inputs!$G$142-IF(E$1=0,0,E$1*12+MthOff), 0))*Inputs!$B$144 -> 960 | G30: =MIN(IF(F$1=0,MthRem,12), MAX(Inputs!$G$142-IF(F$1=0,0,F$1*12+MthOff), 0))*Inputs!$B$144 -> 960 | H30: =MIN(IF(G$1=0,MthRem,12), MAX(Inputs!$G$142-IF(G$1=0,0,G$1*12+MthOff), 0))*Inputs!$B$144 -> 368.25859 | I30: =MIN(IF(H$1=0,MthRem,12), MAX(Inputs!$G$142-IF(H$1=0,0,H$1*12+MthOff), 0))*Inputs!$B$144 -> 0 | J30: =MIN(IF(I$1=0,MthRem,12), MAX(Inputs!$G$142-IF(I$1=0,0,I$1*12+MthOff), 0))*Inputs!$B$144 -> 0 | ... AM30: =MIN(IF(AL$1=0,MthRem,12), MAX(Inputs!$G$142-IF(AL$1=0,0,AL$1*12+MthOff), 0))*Inputs!$B$144 -> 0
A31: =TEXT(Inputs!$B$80,"") -> Marsa | C31: =MIN(IF(B$1=0,MthRem,12), MAX(Inputs!$G$147-IF(B$1=0,0,B$1*12+MthOff), 0))*Inputs!$B$149 -> 1080 | D31: =MIN(IF(C$1=0,MthRem,12), MAX(Inputs!$G$147-IF(C$1=0,0,C$1*12+MthOff), 0))*Inputs!$B$149 -> 1440 | E31: =MIN(IF(D$1=0,MthRem,12), MAX(Inputs!$G$147-IF(D$1=0,0,D$1*12+MthOff), 0))*Inputs!$B$149 -> 1440 | F31: =MIN(IF(E$1=0,MthRem,12), MAX(Inputs!$G$147-IF(E$1=0,0,E$1*12+MthOff), 0))*Inputs!$B$149 -> 1440 | G31: =MIN(IF(F$1=0,MthRem,12), MAX(Inputs!$G$147-IF(F$1=0,0,F$1*12+MthOff), 0))*Inputs!$B$149 -> 1440 | H31: =MIN(IF(G$1=0,MthRem,12), MAX(Inputs!$G$147-IF(G$1=0,0,G$1*12+MthOff), 0))*Inputs!$B$149 -> 1440 | I31: =MIN(IF(H$1=0,MthRem,12), MAX(Inputs!$G$147-IF(H$1=0,0,H$1*12+MthOff), 0))*Inputs!$B$149 -> 1440 | J31: =MIN(IF(I$1=0,MthRem,12), MAX(Inputs!$G$147-IF(I$1=0,0,I$1*12+MthOff), 0))*Inputs!$B$149 -> 909.24881 | ... AM31: =MIN(IF(AL$1=0,MthRem,12), MAX(Inputs!$G$147-IF(AL$1=0,0,AL$1*12+MthOff), 0))*Inputs!$B$149 -> 0
A32: =TEXT(Inputs!$B$87,"") -> Jewelry | C32: =MIN(IF(B$1=0,MthRem,12), MAX(Inputs!$G$152-IF(B$1=0,0,B$1*12+MthOff), 0))*Inputs!$B$154 -> 675 | D32: =MIN(IF(C$1=0,MthRem,12), MAX(Inputs!$G$152-IF(C$1=0,0,C$1*12+MthOff), 0))*Inputs!$B$154 -> 900 | E32: =MIN(IF(D$1=0,MthRem,12), MAX(Inputs!$G$152-IF(D$1=0,0,D$1*12+MthOff), 0))*Inputs!$B$154 -> 900 | F32: =MIN(IF(E$1=0,MthRem,12), MAX(Inputs!$G$152-IF(E$1=0,0,E$1*12+MthOff), 0))*Inputs!$B$154 -> 138.60288 | G32: =MIN(IF(F$1=0,MthRem,12), MAX(Inputs!$G$152-IF(F$1=0,0,F$1*12+MthOff), 0))*Inputs!$B$154 -> 0 | H32: =MIN(IF(G$1=0,MthRem,12), MAX(Inputs!$G$152-IF(G$1=0,0,G$1*12+MthOff), 0))*Inputs!$B$154 -> 0 | I32: =MIN(IF(H$1=0,MthRem,12), MAX(Inputs!$G$152-IF(H$1=0,0,H$1*12+MthOff), 0))*Inputs!$B$154 -> 0 | J32: =MIN(IF(I$1=0,MthRem,12), MAX(Inputs!$G$152-IF(I$1=0,0,I$1*12+MthOff), 0))*Inputs!$B$154 -> 0 | ... AM32: =MIN(IF(AL$1=0,MthRem,12), MAX(Inputs!$G$152-IF(AL$1=0,0,AL$1*12+MthOff), 0))*Inputs!$B$154 -> 0
A33: =TEXT(Inputs!$B$92,"") -> Car | C33: =MIN(IF(B$1=0,MthRem,12), MAX(Inputs!$G$157-IF(B$1=0,0,B$1*12+MthOff), 0))*Inputs!$B$159 -> 774 | D33: =MIN(IF(C$1=0,MthRem,12), MAX(Inputs!$G$157-IF(C$1=0,0,C$1*12+MthOff), 0))*Inputs!$B$159 -> 1032 | E33: =MIN(IF(D$1=0,MthRem,12), MAX(Inputs!$G$157-IF(D$1=0,0,D$1*12+MthOff), 0))*Inputs!$B$159 -> 1032 | F33: =MIN(IF(E$1=0,MthRem,12), MAX(Inputs!$G$157-IF(E$1=0,0,E$1*12+MthOff), 0))*Inputs!$B$159 -> 1032 | G33: =MIN(IF(F$1=0,MthRem,12), MAX(Inputs!$G$157-IF(F$1=0,0,F$1*12+MthOff), 0))*Inputs!$B$159 -> 1032 | H33: =MIN(IF(G$1=0,MthRem,12), MAX(Inputs!$G$157-IF(G$1=0,0,G$1*12+MthOff), 0))*Inputs!$B$159 -> 1032 | I33: =MIN(IF(H$1=0,MthRem,12), MAX(Inputs!$G$157-IF(H$1=0,0,H$1*12+MthOff), 0))*Inputs!$B$159 -> 449.79405 | J33: =MIN(IF(I$1=0,MthRem,12), MAX(Inputs!$G$157-IF(I$1=0,0,I$1*12+MthOff), 0))*Inputs!$B$159 -> 0 | ... AM33: =MIN(IF(AL$1=0,MthRem,12), MAX(Inputs!$G$157-IF(AL$1=0,0,AL$1*12+MthOff), 0))*Inputs!$B$159 -> 0
A34: =TEXT(Inputs!$B$97,"") -> Painting | C34: =MIN(IF(B$1=0,MthRem,12), MAX(Inputs!$G$162-IF(B$1=0,0,B$1*12+MthOff), 0))*Inputs!$B$164 -> 1125 | D34: =MIN(IF(C$1=0,MthRem,12), MAX(Inputs!$G$162-IF(C$1=0,0,C$1*12+MthOff), 0))*Inputs!$B$164 -> 1500 | E34: =MIN(IF(D$1=0,MthRem,12), MAX(Inputs!$G$162-IF(D$1=0,0,D$1*12+MthOff), 0))*Inputs!$B$164 -> 1500 | F34: =MIN(IF(E$1=0,MthRem,12), MAX(Inputs!$G$162-IF(E$1=0,0,E$1*12+MthOff), 0))*Inputs!$B$164 -> 1500 | G34: =MIN(IF(F$1=0,MthRem,12), MAX(Inputs!$G$162-IF(F$1=0,0,F$1*12+MthOff), 0))*Inputs!$B$164 -> 1500 | H34: =MIN(IF(G$1=0,MthRem,12), MAX(Inputs!$G$162-IF(G$1=0,0,G$1*12+MthOff), 0))*Inputs!$B$164 -> 1500 | I34: =MIN(IF(H$1=0,MthRem,12), MAX(Inputs!$G$162-IF(H$1=0,0,H$1*12+MthOff), 0))*Inputs!$B$164 -> 23.429843 | J34: =MIN(IF(I$1=0,MthRem,12), MAX(Inputs!$G$162-IF(I$1=0,0,I$1*12+MthOff), 0))*Inputs!$B$164 -> 0 | ... AM34: =MIN(IF(AL$1=0,MthRem,12), MAX(Inputs!$G$162-IF(AL$1=0,0,AL$1*12+MthOff), 0))*Inputs!$B$164 -> 0
A35: =TEXT(Inputs!$B$102,"") -> Boat | C35: =MIN(IF(B$1=0,MthRem,12), MAX(Inputs!$G$167-IF(B$1=0,0,B$1*12+MthOff), 0))*Inputs!$B$169 -> 5616 | D35: =MIN(IF(C$1=0,MthRem,12), MAX(Inputs!$G$167-IF(C$1=0,0,C$1*12+MthOff), 0))*Inputs!$B$169 -> 7488 | E35: =MIN(IF(D$1=0,MthRem,12), MAX(Inputs!$G$167-IF(D$1=0,0,D$1*12+MthOff), 0))*Inputs!$B$169 -> 7488 | F35: =MIN(IF(E$1=0,MthRem,12), MAX(Inputs!$G$167-IF(E$1=0,0,E$1*12+MthOff), 0))*Inputs!$B$169 -> 7488 | G35: =MIN(IF(F$1=0,MthRem,12), MAX(Inputs!$G$167-IF(F$1=0,0,F$1*12+MthOff), 0))*Inputs!$B$169 -> 7488 | H35: =MIN(IF(G$1=0,MthRem,12), MAX(Inputs!$G$167-IF(G$1=0,0,G$1*12+MthOff), 0))*Inputs!$B$169 -> 7488 | I35: =MIN(IF(H$1=0,MthRem,12), MAX(Inputs!$G$167-IF(H$1=0,0,H$1*12+MthOff), 0))*Inputs!$B$169 -> 5289.2926 | J35: =MIN(IF(I$1=0,MthRem,12), MAX(Inputs!$G$167-IF(I$1=0,0,I$1*12+MthOff), 0))*Inputs!$B$169 -> 0 | ... AM35: =MIN(IF(AL$1=0,MthRem,12), MAX(Inputs!$G$167-IF(AL$1=0,0,AL$1*12+MthOff), 0))*Inputs!$B$169 -> 0
A36: =TEXT(Inputs!$B$107,"") -> Antiques | C36: =MIN(IF(B$1=0,MthRem,12), MAX(Inputs!$G$172-IF(B$1=0,0,B$1*12+MthOff), 0))*Inputs!$B$174 -> 990 | D36: =MIN(IF(C$1=0,MthRem,12), MAX(Inputs!$G$172-IF(C$1=0,0,C$1*12+MthOff), 0))*Inputs!$B$174 -> 1320 | E36: =MIN(IF(D$1=0,MthRem,12), MAX(Inputs!$G$172-IF(D$1=0,0,D$1*12+MthOff), 0))*Inputs!$B$174 -> 1320 | F36: =MIN(IF(E$1=0,MthRem,12), MAX(Inputs!$G$172-IF(E$1=0,0,E$1*12+MthOff), 0))*Inputs!$B$174 -> 349.16176 | G36: =MIN(IF(F$1=0,MthRem,12), MAX(Inputs!$G$172-IF(F$1=0,0,F$1*12+MthOff), 0))*Inputs!$B$174 -> 0 | H36: =MIN(IF(G$1=0,MthRem,12), MAX(Inputs!$G$172-IF(G$1=0,0,G$1*12+MthOff), 0))*Inputs!$B$174 -> 0 | I36: =MIN(IF(H$1=0,MthRem,12), MAX(Inputs!$G$172-IF(H$1=0,0,H$1*12+MthOff), 0))*Inputs!$B$174 -> 0 | J36: =MIN(IF(I$1=0,MthRem,12), MAX(Inputs!$G$172-IF(I$1=0,0,I$1*12+MthOff), 0))*Inputs!$B$174 -> 0 | ... AM36: =MIN(IF(AL$1=0,MthRem,12), MAX(Inputs!$G$172-IF(AL$1=0,0,AL$1*12+MthOff), 0))*Inputs!$B$174 -> 0
A37: Other loan repayment | C37: =MIN(IF(B$1=0,MthRem,12), MAX(Inputs!$G$177-IF(B$1=0,0,B$1*12+MthOff), 0))*Inputs!$B$179 -> 450 | D37: =MIN(IF(C$1=0,MthRem,12), MAX(Inputs!$G$177-IF(C$1=0,0,C$1*12+MthOff), 0))*Inputs!$B$179 -> 600 | E37: =MIN(IF(D$1=0,MthRem,12), MAX(Inputs!$G$177-IF(D$1=0,0,D$1*12+MthOff), 0))*Inputs!$B$179 -> 600 | F37: =MIN(IF(E$1=0,MthRem,12), MAX(Inputs!$G$177-IF(E$1=0,0,E$1*12+MthOff), 0))*Inputs!$B$179 -> 600 | G37: =MIN(IF(F$1=0,MthRem,12), MAX(Inputs!$G$177-IF(F$1=0,0,F$1*12+MthOff), 0))*Inputs!$B$179 -> 600 | H37: =MIN(IF(G$1=0,MthRem,12), MAX(Inputs!$G$177-IF(G$1=0,0,G$1*12+MthOff), 0))*Inputs!$B$179 -> 600 | I37: =MIN(IF(H$1=0,MthRem,12), MAX(Inputs!$G$177-IF(H$1=0,0,H$1*12+MthOff), 0))*Inputs!$B$179 -> 600 | J37: =MIN(IF(I$1=0,MthRem,12), MAX(Inputs!$G$177-IF(I$1=0,0,I$1*12+MthOff), 0))*Inputs!$B$179 -> 600 | ... AM37: =MIN(IF(AL$1=0,MthRem,12), MAX(Inputs!$G$177-IF(AL$1=0,0,AL$1*12+MthOff), 0))*Inputs!$B$179 -> 0
A38: Dependents cost
A39: =TEXT(Inputs!B33,"") -> John | C39: =IF(Inputs!$B$35>=C$1,Inputs!$B$34,0)*(1+inf)^B$1*ProRate -> 1500 | D39: =IF(Inputs!$B$35>=D$1,Inputs!$B$34,0)*(1+inf)^C$1 -> 2050 | E39: =IF(Inputs!$B$35>=E$1,Inputs!$B$34,0)*(1+inf)^D$1 -> 2101.25 | F39: =IF(Inputs!$B$35>=F$1,Inputs!$B$34,0)*(1+inf)^E$1 -> 0 | G39: =IF(Inputs!$B$35>=G$1,Inputs!$B$34,0)*(1+inf)^F$1 -> 0 | H39: =IF(Inputs!$B$35>=H$1,Inputs!$B$34,0)*(1+inf)^G$1 -> 0 | I39: =IF(Inputs!$B$35>=I$1,Inputs!$B$34,0)*(1+inf)^H$1 -> 0 | J39: =IF(Inputs!$B$35>=J$1,Inputs!$B$34,0)*(1+inf)^I$1 -> 0 | K39: =IF(Inputs!$B$35>=K$1,Inputs!$B$34,0)*(1+inf)^J$1 -> 0 | ... AM39: =IF(Inputs!$B$35>=AM$1,Inputs!$B$34,0)*(1+inf)^AL$1 -> 0
A40: =TEXT(Inputs!B38,"") -> Jack | C40: =IF(Inputs!$B$40>=C$1,Inputs!$B$39,0)*(1+inf)^B$1*ProRate -> 750 | D40: =IF(Inputs!$B$40>=D$1,Inputs!$B$39,0)*(1+inf)^C$1 -> 1025 | E40: =IF(Inputs!$B$40>=E$1,Inputs!$B$39,0)*(1+inf)^D$1 -> 1050.625 | F40: =IF(Inputs!$B$40>=F$1,Inputs!$B$39,0)*(1+inf)^E$1 -> 1076.8906 | G40: =IF(Inputs!$B$40>=G$1,Inputs!$B$39,0)*(1+inf)^F$1 -> 1103.8129 | H40: =IF(Inputs!$B$40>=H$1,Inputs!$B$39,0)*(1+inf)^G$1 -> 0 | I40: =IF(Inputs!$B$40>=I$1,Inputs!$B$39,0)*(1+inf)^H$1 -> 0 | J40: =IF(Inputs!$B$40>=J$1,Inputs!$B$39,0)*(1+inf)^I$1 -> 0 | K40: =IF(Inputs!$B$40>=K$1,Inputs!$B$39,0)*(1+inf)^J$1 -> 0 | ... AM40: =IF(Inputs!$B$40>=AM$1,Inputs!$B$39,0)*(1+inf)^AL$1 -> 0
A41: =TEXT(Inputs!B43,"") -> Bill | C41: =IF(Inputs!$B$45>=C$1,Inputs!$B$44,0)*(1+inf)^B$1*ProRate -> 3000 | D41: =IF(Inputs!$B$45>=D$1,Inputs!$B$44,0)*(1+inf)^C$1 -> 4100 | E41: =IF(Inputs!$B$45>=E$1,Inputs!$B$44,0)*(1+inf)^D$1 -> 0 | F41: =IF(Inputs!$B$45>=F$1,Inputs!$B$44,0)*(1+inf)^E$1 -> 0 | G41: =IF(Inputs!$B$45>=G$1,Inputs!$B$44,0)*(1+inf)^F$1 -> 0 | H41: =IF(Inputs!$B$45>=H$1,Inputs!$B$44,0)*(1+inf)^G$1 -> 0 | I41: =IF(Inputs!$B$45>=I$1,Inputs!$B$44,0)*(1+inf)^H$1 -> 0 | J41: =IF(Inputs!$B$45>=J$1,Inputs!$B$44,0)*(1+inf)^I$1 -> 0 | K41: =IF(Inputs!$B$45>=K$1,Inputs!$B$44,0)*(1+inf)^J$1 -> 0 | ... AM41: =IF(Inputs!$B$45>=AM$1,Inputs!$B$44,0)*(1+inf)^AL$1 -> 0
A42: =TEXT(Inputs!B48,"") -> Stephen | C42: =IF(Inputs!$B$50>=C$1,Inputs!$B$49,0)*(1+inf)^B$1*ProRate -> 1875 | D42: =IF(Inputs!$B$50>=D$1,Inputs!$B$49,0)*(1+inf)^C$1 -> 2562.5 | E42: =IF(Inputs!$B$50>=E$1,Inputs!$B$49,0)*(1+inf)^D$1 -> 2626.5625 | F42: =IF(Inputs!$B$50>=F$1,Inputs!$B$49,0)*(1+inf)^E$1 -> 0 | G42: =IF(Inputs!$B$50>=G$1,Inputs!$B$49,0)*(1+inf)^F$1 -> 0 | H42: =IF(Inputs!$B$50>=H$1,Inputs!$B$49,0)*(1+inf)^G$1 -> 0 | I42: =IF(Inputs!$B$50>=I$1,Inputs!$B$49,0)*(1+inf)^H$1 -> 0 | J42: =IF(Inputs!$B$50>=J$1,Inputs!$B$49,0)*(1+inf)^I$1 -> 0 | K42: =IF(Inputs!$B$50>=K$1,Inputs!$B$49,0)*(1+inf)^J$1 -> 0 | ... AM42: =IF(Inputs!$B$50>=AM$1,Inputs!$B$49,0)*(1+inf)^AL$1 -> 0
A43: =TEXT(Inputs!B53,"") -> Jane | C43: =IF(Inputs!$B$55>=C$1,Inputs!$B$54,0)*(1+inf)^B$1*ProRate -> 2145 | D43: =IF(Inputs!$B$55>=D$1,Inputs!$B$54,0)*(1+inf)^C$1 -> 2931.5 | E43: =IF(Inputs!$B$55>=E$1,Inputs!$B$54,0)*(1+inf)^D$1 -> 3004.7875 | F43: =IF(Inputs!$B$55>=F$1,Inputs!$B$54,0)*(1+inf)^E$1 -> 3079.9072 | G43: =IF(Inputs!$B$55>=G$1,Inputs!$B$54,0)*(1+inf)^F$1 -> 3156.9049 | H43: =IF(Inputs!$B$55>=H$1,Inputs!$B$54,0)*(1+inf)^G$1 -> 3235.8275 | I43: =IF(Inputs!$B$55>=I$1,Inputs!$B$54,0)*(1+inf)^H$1 -> 0 | J43: =IF(Inputs!$B$55>=J$1,Inputs!$B$54,0)*(1+inf)^I$1 -> 0 | K43: =IF(Inputs!$B$55>=K$1,Inputs!$B$54,0)*(1+inf)^J$1 -> 0 | ... AM43: =IF(Inputs!$B$55>=AM$1,Inputs!$B$54,0)*(1+inf)^AL$1 -> 0
A44: Home rent | C44: =IF(AND(Inputs!$B$217<>"",C$2>=Inputs!$B$217),IF(OR(Inputs!$B$12<=0,UPPER(Inputs!$B$219)="RENT"),Inputs!$B$223*12*(1+inf)^B$1*IF(B$1=0,ProRate,1),0),Inputs!$B$23*12*(1+inf)^B$1*IF(B$1=0,ProRate,1)) -> 0 | D44: =IF(AND(Inputs!$B$217<>"",D$2>=Inputs!$B$217),IF(OR(Inputs!$B$12<=0,UPPER(Inputs!$B$219)="RENT"),Inputs!$B$223*12*(1+inf)^C$1*IF(C$1=0,ProRate,1),0),Inputs!$B$23*12*(1+inf)^C$1*IF(C$1=0,ProRate,1)) -> 0 | E44: =IF(AND(Inputs!$B$217<>"",E$2>=Inputs!$B$217),IF(OR(Inputs!$B$12<=0,UPPER(Inputs!$B$219)="RENT"),Inputs!$B$223*12*(1+inf)^D$1*IF(D$1=0,ProRate,1),0),Inputs!$B$23*12*(1+inf)^D$1*IF(D$1=0,ProRate,1)) -> 0 | F44: =IF(AND(Inputs!$B$217<>"",F$2>=Inputs!$B$217),IF(OR(Inputs!$B$12<=0,UPPER(Inputs!$B$219)="RENT"),Inputs!$B$223*12*(1+inf)^E$1*IF(E$1=0,ProRate,1),0),Inputs!$B$23*12*(1+inf)^E$1*IF(E$1=0,ProRate,1)) -> 0 | G44: =IF(AND(Inputs!$B$217<>"",G$2>=Inputs!$B$217),IF(OR(Inputs!$B$12<=0,UPPER(Inputs!$B$219)="RENT"),Inputs!$B$223*12*(1+inf)^F$1*IF(F$1=0,ProRate,1),0),Inputs!$B$23*12*(1+inf)^F$1*IF(F$1=0,ProRate,1)) -> 0 | H44: =IF(AND(Inputs!$B$217<>"",H$2>=Inputs!$B$217),IF(OR(Inputs!$B$12<=0,UPPER(Inputs!$B$219)="RENT"),Inputs!$B$223*12*(1+inf)^G$1*IF(G$1=0,ProRate,1),0),Inputs!$B$23*12*(1+inf)^G$1*IF(G$1=0,ProRate,1)) -> 0 | I44: =IF(AND(Inputs!$B$217<>"",I$2>=Inputs!$B$217),IF(OR(Inputs!$B$12<=0,UPPER(Inputs!$B$219)="RENT"),Inputs!$B$223*12*(1+inf)^H$1*IF(H$1=0,ProRate,1),0),Inputs!$B$23*12*(1+inf)^H$1*IF(H$1=0,ProRate,1)) -> 0 | J44: =IF(AND(Inputs!$B$217<>"",J$2>=Inputs!$B$217),IF(OR(Inputs!$B$12<=0,UPPER(Inputs!$B$219)="RENT"),Inputs!$B$223*12*(1+inf)^I$1*IF(I$1=0,ProRate,1),0),Inputs!$B$23*12*(1+inf)^I$1*IF(I$1=0,ProRate,1)) -> 0 | ... AM44: =IF(AND(Inputs!$B$217<>"",AM$2>=Inputs!$B$217),IF(OR(Inputs!$B$12<=0,UPPER(Inputs!$B$219)="RENT"),Inputs!$B$223*12*(1+inf)^AL$1*IF(AL$1=0,ProRate,1),0),Inputs!$B$23*12*(1+inf)^AL$1*IF(AL$1=0,ProRate,1)) -> 0
A45: Other property costs
A46: =TEXT(Inputs!$B$60,"") -> Sliema | C46: =Inputs!$B62*(1+inf)^B$1*ProRate -> 3750 | D46: =Inputs!$B62*(1+inf)^C$1 -> 5125 | E46: =Inputs!$B62*(1+inf)^D$1 -> 5253.125 | F46: =Inputs!$B62*(1+inf)^E$1 -> 5384.4531 | G46: =Inputs!$B62*(1+inf)^F$1 -> 5519.0645 | H46: =Inputs!$B62*(1+inf)^G$1 -> 5657.0411 | I46: =Inputs!$B62*(1+inf)^H$1 -> 5798.4671 | J46: =Inputs!$B62*(1+inf)^I$1 -> 5943.4288 | K46: =Inputs!$B62*(1+inf)^J$1 -> 6092.0145 | ... AM46: =Inputs!$B62*(1+inf)^AL$1 -> 12162.677
A47: =TEXT(Inputs!$B$65,"") -> Gzira | C47: =Inputs!$B67*(1+inf)^B$1*ProRate -> 1500 | D47: =Inputs!$B67*(1+inf)^C$1 -> 2050 | E47: =Inputs!$B67*(1+inf)^D$1 -> 2101.25 | F47: =Inputs!$B67*(1+inf)^E$1 -> 2153.7812 | G47: =Inputs!$B67*(1+inf)^F$1 -> 2207.6258 | H47: =Inputs!$B67*(1+inf)^G$1 -> 2262.8164 | I47: =Inputs!$B67*(1+inf)^H$1 -> 2319.3868 | J47: =Inputs!$B67*(1+inf)^I$1 -> 2377.3715 | K47: =Inputs!$B67*(1+inf)^J$1 -> 2436.8058 | ... AM47: =Inputs!$B67*(1+inf)^AL$1 -> 4865.0706
A48: =TEXT(Inputs!$B$70,"") -> Qormi | C48: =Inputs!$B72*(1+inf)^B$1*ProRate -> 900 | D48: =Inputs!$B72*(1+inf)^C$1 -> 1230 | E48: =Inputs!$B72*(1+inf)^D$1 -> 1260.75 | F48: =Inputs!$B72*(1+inf)^E$1 -> 1292.2687 | G48: =Inputs!$B72*(1+inf)^F$1 -> 1324.5755 | H48: =Inputs!$B72*(1+inf)^G$1 -> 1357.6899 | I48: =Inputs!$B72*(1+inf)^H$1 -> 1391.6321 | J48: =Inputs!$B72*(1+inf)^I$1 -> 1426.4229 | K48: =Inputs!$B72*(1+inf)^J$1 -> 1462.0835 | ... AM48: =Inputs!$B72*(1+inf)^AL$1 -> 2919.0424
A49: =TEXT(Inputs!$B$75,"") -> Gudja | C49: =Inputs!$B77*(1+inf)^B$1*ProRate -> 750 | D49: =Inputs!$B77*(1+inf)^C$1 -> 1025 | E49: =Inputs!$B77*(1+inf)^D$1 -> 1050.625 | F49: =Inputs!$B77*(1+inf)^E$1 -> 1076.8906 | G49: =Inputs!$B77*(1+inf)^F$1 -> 1103.8129 | H49: =Inputs!$B77*(1+inf)^G$1 -> 1131.4082 | I49: =Inputs!$B77*(1+inf)^H$1 -> 1159.6934 | J49: =Inputs!$B77*(1+inf)^I$1 -> 1188.6858 | K49: =Inputs!$B77*(1+inf)^J$1 -> 1218.4029 | ... AM49: =Inputs!$B77*(1+inf)^AL$1 -> 2432.5353
A50: =TEXT(Inputs!$B$80,"") -> Marsa | C50: =Inputs!$B82*(1+inf)^B$1*ProRate -> 600 | D50: =Inputs!$B82*(1+inf)^C$1 -> 820 | E50: =Inputs!$B82*(1+inf)^D$1 -> 840.5 | F50: =Inputs!$B82*(1+inf)^E$1 -> 861.5125 | G50: =Inputs!$B82*(1+inf)^F$1 -> 883.05031 | H50: =Inputs!$B82*(1+inf)^G$1 -> 905.12657 | I50: =Inputs!$B82*(1+inf)^H$1 -> 927.75473 | J50: =Inputs!$B82*(1+inf)^I$1 -> 950.9486 | K50: =Inputs!$B82*(1+inf)^J$1 -> 974.72232 | ... AM50: =Inputs!$B82*(1+inf)^AL$1 -> 1946.0283
A51: Living expenses
A52: Current baseline | C52: =Inputs!$B$25*(1+inf)^B$1*ProRate -> 37500 | D52: =Inputs!$B$25*(1+inf)^C$1 -> 51250 | E52: =Inputs!$B$25*(1+inf)^D$1 -> 52531.25 | F52: =Inputs!$B$25*(1+inf)^E$1 -> 53844.531 | G52: =Inputs!$B$25*(1+inf)^F$1 -> 55190.645 | H52: =Inputs!$B$25*(1+inf)^G$1 -> 56570.411 | I52: =Inputs!$B$25*(1+inf)^H$1 -> 57984.671 | J52: =Inputs!$B$25*(1+inf)^I$1 -> 59434.288 | K52: =Inputs!$B$25*(1+inf)^J$1 -> 60920.145 | ... AM52: =Inputs!$B$25*(1+inf)^AL$1 -> 121626.77
A53: ="Adjustment "&Inputs!A257 -> Adjustment from now to 65 | C53: =IF(C$3<=65,Inputs!$B$257*C$52,0) -> 0 | D53: =IF(D$3<=65,Inputs!$B$257*D$52,0) -> 0 | E53: =IF(E$3<=65,Inputs!$B$257*E$52,0) -> 0 | F53: =IF(F$3<=65,Inputs!$B$257*F$52,0) -> 0 | G53: =IF(G$3<=65,Inputs!$B$257*G$52,0) -> 0 | H53: =IF(H$3<=65,Inputs!$B$257*H$52,0) -> 0 | I53: =IF(I$3<=65,Inputs!$B$257*I$52,0) -> 0 | J53: =IF(J$3<=65,Inputs!$B$257*J$52,0) -> 0 | ... AM53: =IF(AM$3<=65,Inputs!$B$257*AM$52,0) -> 0
A54: ="Adjustment "&Inputs!A258 -> Adjustment from 66-75 | C54: =IF(AND(C$3>65,C$3<=75),Inputs!$B$258*C52,0) -> 0 | D54: =IF(AND(D$3>65,D$3<=75),Inputs!$B$258*D52,0) -> 0 | E54: =IF(AND(E$3>65,E$3<=75),Inputs!$B$258*E52,0) -> 0 | F54: =IF(AND(F$3>65,F$3<=75),Inputs!$B$258*F52,0) -> 0 | G54: =IF(AND(G$3>65,G$3<=75),Inputs!$B$258*G52,0) -> 0 | H54: =IF(AND(H$3>65,H$3<=75),Inputs!$B$258*H52,0) -> 0 | I54: =IF(AND(I$3>65,I$3<=75),Inputs!$B$258*I52,0) -> 0 | J54: =IF(AND(J$3>65,J$3<=75),Inputs!$B$258*J52,0) -> 0 | ... AM54: =IF(AND(AM$3>65,AM$3<=75),Inputs!$B$258*AM52,0) -> 0
A55: ="Adjustment "&Inputs!A259 -> Adjustment from age 76 | C55: =IF(C$3>75,Inputs!$B$259*C$52,0) -> 0 | D55: =IF(D$3>75,Inputs!$B$259*D$52,0) -> 0 | E55: =IF(E$3>75,Inputs!$B$259*E$52,0) -> 0 | F55: =IF(F$3>75,Inputs!$B$259*F$52,0) -> 0 | G55: =IF(G$3>75,Inputs!$B$259*G$52,0) -> 0 | H55: =IF(H$3>75,Inputs!$B$259*H$52,0) -> 0 | I55: =IF(I$3>75,Inputs!$B$259*I$52,0) -> 0 | J55: =IF(J$3>75,Inputs!$B$259*J$52,0) -> 0 | ... AM55: =IF(AM$3>75,Inputs!$B$259*AM$52,0) -> -24325.353
A56: Major one-off expense events
A57: =TEXT(Inputs!$B$201,"") -> Wedding | C57: =IF(C$2=Inputs!$B203,Inputs!$B202,0)*(1+inf)^B$1 -> 0 | D57: =IF(D$2=Inputs!$B203,Inputs!$B202,0)*(1+inf)^C$1 -> 0 | E57: =IF(E$2=Inputs!$B203,Inputs!$B202,0)*(1+inf)^D$1 -> 0 | F57: =IF(F$2=Inputs!$B203,Inputs!$B202,0)*(1+inf)^E$1 -> 0 | G57: =IF(G$2=Inputs!$B203,Inputs!$B202,0)*(1+inf)^F$1 -> 0 | H57: =IF(H$2=Inputs!$B203,Inputs!$B202,0)*(1+inf)^G$1 -> 0 | I57: =IF(I$2=Inputs!$B203,Inputs!$B202,0)*(1+inf)^H$1 -> 0 | J57: =IF(J$2=Inputs!$B203,Inputs!$B202,0)*(1+inf)^I$1 -> 0 | ... AM57: =IF(AM$2=Inputs!$B203,Inputs!$B202,0)*(1+inf)^AL$1 -> 0
A58: =TEXT(Inputs!$B$206,"") -> New Car | C58: =IF(C$2=Inputs!$B208,Inputs!$B207,0)*(1+inf)^B$1 -> 0 | D58: =IF(D$2=Inputs!$B208,Inputs!$B207,0)*(1+inf)^C$1 -> 0 | E58: =IF(E$2=Inputs!$B208,Inputs!$B207,0)*(1+inf)^D$1 -> 0 | F58: =IF(F$2=Inputs!$B208,Inputs!$B207,0)*(1+inf)^E$1 -> 37691.172 | G58: =IF(G$2=Inputs!$B208,Inputs!$B207,0)*(1+inf)^F$1 -> 0 | H58: =IF(H$2=Inputs!$B208,Inputs!$B207,0)*(1+inf)^G$1 -> 0 | I58: =IF(I$2=Inputs!$B208,Inputs!$B207,0)*(1+inf)^H$1 -> 0 | J58: =IF(J$2=Inputs!$B208,Inputs!$B207,0)*(1+inf)^I$1 -> 0 | ... AM58: =IF(AM$2=Inputs!$B208,Inputs!$B207,0)*(1+inf)^AL$1 -> 0
A59: =TEXT(Inputs!$B$211,"") -> New AC | C59: =IF(C$2=Inputs!$B213,Inputs!$B212,0)*(1+inf)^B$1 -> 0 | D59: =IF(D$2=Inputs!$B213,Inputs!$B212,0)*(1+inf)^C$1 -> 0 | E59: =IF(E$2=Inputs!$B213,Inputs!$B212,0)*(1+inf)^D$1 -> 0 | F59: =IF(F$2=Inputs!$B213,Inputs!$B212,0)*(1+inf)^E$1 -> 0 | G59: =IF(G$2=Inputs!$B213,Inputs!$B212,0)*(1+inf)^F$1 -> 0 | H59: =IF(H$2=Inputs!$B213,Inputs!$B212,0)*(1+inf)^G$1 -> 0 | I59: =IF(I$2=Inputs!$B213,Inputs!$B212,0)*(1+inf)^H$1 -> 0 | J59: =IF(J$2=Inputs!$B213,Inputs!$B212,0)*(1+inf)^I$1 -> 0 | ... AM59: =IF(AM$2=Inputs!$B213,Inputs!$B212,0)*(1+inf)^AL$1 -> 0
A60: Purchase of home (downsizing) | C60: =IF(AND(Inputs!$B$217<>"",C$2=Inputs!$B$217,Inputs!$B$12>0,UPPER(Inputs!$B$219)="BUY"),Inputs!$B$221*(1+princ)^(ProRate+C$1-1),0) -> 0 | D60: =IF(AND(Inputs!$B$217<>"",D$2=Inputs!$B$217,Inputs!$B$12>0,UPPER(Inputs!$B$219)="BUY"),Inputs!$B$221*(1+princ)^(ProRate+D$1-1),0) -> 0 | E60: =IF(AND(Inputs!$B$217<>"",E$2=Inputs!$B$217,Inputs!$B$12>0,UPPER(Inputs!$B$219)="BUY"),Inputs!$B$221*(1+princ)^(ProRate+E$1-1),0) -> 0 | F60: =IF(AND(Inputs!$B$217<>"",F$2=Inputs!$B$217,Inputs!$B$12>0,UPPER(Inputs!$B$219)="BUY"),Inputs!$B$221*(1+princ)^(ProRate+F$1-1),0) -> 0 | G60: =IF(AND(Inputs!$B$217<>"",G$2=Inputs!$B$217,Inputs!$B$12>0,UPPER(Inputs!$B$219)="BUY"),Inputs!$B$221*(1+princ)^(ProRate+G$1-1),0) -> 287684.74 | H60: =IF(AND(Inputs!$B$217<>"",H$2=Inputs!$B$217,Inputs!$B$12>0,UPPER(Inputs!$B$219)="BUY"),Inputs!$B$221*(1+princ)^(ProRate+H$1-1),0) -> 0 | I60: =IF(AND(Inputs!$B$217<>"",I$2=Inputs!$B$217,Inputs!$B$12>0,UPPER(Inputs!$B$219)="BUY"),Inputs!$B$221*(1+princ)^(ProRate+I$1-1),0) -> 0 | J60: =IF(AND(Inputs!$B$217<>"",J$2=Inputs!$B$217,Inputs!$B$12>0,UPPER(Inputs!$B$219)="BUY"),Inputs!$B$221*(1+princ)^(ProRate+J$1-1),0) -> 0 | ... AM60: =IF(AND(Inputs!$B$217<>"",AM$2=Inputs!$B$217,Inputs!$B$12>0,UPPER(Inputs!$B$219)="BUY"),Inputs!$B$221*(1+princ)^(ProRate+AM$1-1),0) -> 0
C61: =SUM(C23:C60) -> 77950 | D61: =SUM(D23:D60) -> 104409 | E61: =SUM(E23:E60) -> 102060.72 | F61: =SUM(F23:F60) -> 134792.57 | G61: =SUM(G23:G60) -> 423087.87 | H61: =SUM(H23:H60) -> 92548.579 | I61: =SUM(I23:I60) -> 83430.981 | J61: =SUM(J23:J60) -> 78830.394 | ... AM61: =SUM(AM23:AM60) -> 121626.77
A63: Net Cash Flow | C63: =C22-C61 -> 16108.438 | D63: =D22-D61 -> -69526.292 | E63: =E22-E61 -> -66938.962 | F63: =F22-F61 -> -87858.759 | G63: =G22-G61 -> 103215.28 | H63: =H22-H61 -> -54203.357 | I63: =I22-I61 -> -38148.25 | J63: =J22-J61 -> -38173.198 | ... AM63: =AM22-AM61 -> -4173.4573
A64: Cash b/fwd | C64: =Inputs!B8 -> 50000 | D64: =C65 -> 66108.438 | E64: =D65 -> -3417.8547 | F64: =E65 -> -70356.817 | G64: =F65 -> -158215.58 | H64: =G65 -> -55000.3 | I64: =H65 -> -109203.66 | J64: =I65 -> -147351.91 | K64: =J65 -> -185525.1 | ... AM64: =AL65 -> -536086.09
A65: Cash c/fwd | C65: =SUM(C63:C64) -> 66108.438 | D65: =SUM(D63:D64) -> -3417.8547 | E65: =SUM(E63:E64) -> -70356.817 | F65: =SUM(F63:F64) -> -158215.58 | G65: =SUM(G63:G64) -> -55000.3 | H65: =SUM(H63:H64) -> -109203.66 | I65: =SUM(I63:I64) -> -147351.91 | J65: =SUM(J63:J64) -> -185525.1 | ... AM65: =SUM(AM63:AM64) -> -540259.55
A67: Net Worth before liquidations
A68: Cash | C68: =C65 -> 66108.438 | D68: =D65 -> -3417.8547 | E68: =E65 -> -70356.817 | F68: =F65 -> -158215.58 | G68: =G65 -> -55000.3 | H68: =H65 -> -109203.66 | I68: =I65 -> -147351.91 | J68: =J65 -> -185525.1 | ... AM68: =AM65 -> -540259.55
A69: Home | C69: =IF(AND(Inputs!$B$217<>"",C$2>=Inputs!$B$217),IF(AND(Inputs!$B$12>0,UPPER(Inputs!$B$219)="BUY"),IF(C$2=Inputs!$B$217,Inputs!$B$221*(1+princ)^(ProRate+C$1-1),B69*(1+princ)),0),IF(Inputs!$B$12>0,IF(B$1=0,Inputs!$B$12*(1+princ)^ProRate,B69*(1+princ)),0)) -> 511208.33 | D69: =IF(AND(Inputs!$B$217<>"",D$2>=Inputs!$B$217),IF(AND(Inputs!$B$12>0,UPPER(Inputs!$B$219)="BUY"),IF(D$2=Inputs!$B$217,Inputs!$B$221*(1+princ)^(ProRate+D$1-1),C69*(1+princ)),0),IF(Inputs!$B$12>0,IF(C$1=0,Inputs!$B$12*(1+princ)^ProRate,C69*(1+princ)),0)) -> 526544.58 | E69: =IF(AND(Inputs!$B$217<>"",E$2>=Inputs!$B$217),IF(AND(Inputs!$B$12>0,UPPER(Inputs!$B$219)="BUY"),IF(E$2=Inputs!$B$217,Inputs!$B$221*(1+princ)^(ProRate+E$1-1),D69*(1+princ)),0),IF(Inputs!$B$12>0,IF(D$1=0,Inputs!$B$12*(1+princ)^ProRate,D69*(1+princ)),0)) -> 542340.92 | F69: =IF(AND(Inputs!$B$217<>"",F$2>=Inputs!$B$217),IF(AND(Inputs!$B$12>0,UPPER(Inputs!$B$219)="BUY"),IF(F$2=Inputs!$B$217,Inputs!$B$221*(1+princ)^(ProRate+F$1-1),E69*(1+princ)),0),IF(Inputs!$B$12>0,IF(E$1=0,Inputs!$B$12*(1+princ)^ProRate,E69*(1+princ)),0)) -> 558611.15 | G69: =IF(AND(Inputs!$B$217<>"",G$2>=Inputs!$B$217),IF(AND(Inputs!$B$12>0,UPPER(Inputs!$B$219)="BUY"),IF(G$2=Inputs!$B$217,Inputs!$B$221*(1+princ)^(ProRate+G$1-1),F69*(1+princ)),0),IF(Inputs!$B$12>0,IF(F$1=0,Inputs!$B$12*(1+princ)^ProRate,F69*(1+princ)),0)) -> 287684.74 | H69: =IF(AND(Inputs!$B$217<>"",H$2>=Inputs!$B$217),IF(AND(Inputs!$B$12>0,UPPER(Inputs!$B$219)="BUY"),IF(H$2=Inputs!$B$217,Inputs!$B$221*(1+princ)^(ProRate+H$1-1),G69*(1+princ)),0),IF(Inputs!$B$12>0,IF(G$1=0,Inputs!$B$12*(1+princ)^ProRate,G69*(1+princ)),0)) -> 296315.28 | I69: =IF(AND(Inputs!$B$217<>"",I$2>=Inputs!$B$217),IF(AND(Inputs!$B$12>0,UPPER(Inputs!$B$219)="BUY"),IF(I$2=Inputs!$B$217,Inputs!$B$221*(1+princ)^(ProRate+I$1-1),H69*(1+princ)),0),IF(Inputs!$B$12>0,IF(H$1=0,Inputs!$B$12*(1+princ)^ProRate,H69*(1+princ)),0)) -> 305204.74 | J69: =IF(AND(Inputs!$B$217<>"",J$2>=Inputs!$B$217),IF(AND(Inputs!$B$12>0,UPPER(Inputs!$B$219)="BUY"),IF(J$2=Inputs!$B$217,Inputs!$B$221*(1+princ)^(ProRate+J$1-1),I69*(1+princ)),0),IF(Inputs!$B$12>0,IF(I$1=0,Inputs!$B$12*(1+princ)^ProRate,I69*(1+princ)),0)) -> 314360.88 | ... AM69: =IF(AND(Inputs!$B$217<>"",AM$2>=Inputs!$B$217),IF(AND(Inputs!$B$12>0,UPPER(Inputs!$B$219)="BUY"),IF(AM$2=Inputs!$B$217,Inputs!$B$221*(1+princ)^(ProRate+AM$1-1),AL69*(1+princ)),0),IF(Inputs!$B$12>0,IF(AL$1=0,Inputs!$B$12*(1+princ)^ProRate,AL69*(1+princ)),0)) -> 740812.01
A70: Other property
A71: =TEXT(Inputs!$B$60,"") -> Sliema | C71: =Inputs!B61*(1+princ)^ProRate -> 306725 | D71: =C71*(1+princ) -> 315926.75 | E71: =D71*(1+princ) -> 325404.55 | F71: =E71*(1+princ) -> 335166.69 | G71: =F71*(1+princ) -> 345221.69 | H71: =G71*(1+princ) -> 355578.34 | I71: =H71*(1+princ) -> 366245.69 | J71: =I71*(1+princ) -> 377233.06 | K71: =J71*(1+princ) -> 388550.05 | ... AM71: =AL71*(1+princ) -> 888974.42
A72: =TEXT(Inputs!$B$65,"") -> Gzira | C72: =Inputs!B66*(1+princ)^ProRate -> 153362.5 | D72: =C72*(1+princ) -> 157963.37 | E72: =D72*(1+princ) -> 162702.28 | F72: =E72*(1+princ) -> 167583.34 | G72: =F72*(1+princ) -> 172610.84 | H72: =G72*(1+princ) -> 177789.17 | I72: =H72*(1+princ) -> 183122.84 | J72: =I72*(1+princ) -> 188616.53 | K72: =J72*(1+princ) -> 194275.03 | ... AM72: =AL72*(1+princ) -> 444487.21
A73: =TEXT(Inputs!$B$70,"") -> Qormi | C73: =Inputs!B71*(1+princ)^ProRate -> 224931.67 | D73: =C73*(1+princ) -> 231679.62 | E73: =D73*(1+princ) -> 238630 | F73: =E73*(1+princ) -> 245788.9 | G73: =F73*(1+princ) -> 253162.57 | H73: =G73*(1+princ) -> 260757.45 | I73: =H73*(1+princ) -> 268580.17 | J73: =I73*(1+princ) -> 276637.58 | K73: =J73*(1+princ) -> 284936.7 | ... AM73: =AL73*(1+princ) -> 651914.57
A74: =TEXT(Inputs!$B$75,"") -> Gudja | C74: =Inputs!B76*(1+princ)^ProRate -> 81793.333 | D74: =C74*(1+princ) -> 84247.133 | E74: =D74*(1+princ) -> 86774.547 | F74: =E74*(1+princ) -> 89377.783 | G74: =F74*(1+princ) -> 92059.117 | H74: =G74*(1+princ) -> 94820.89 | I74: =H74*(1+princ) -> 97665.517 | J74: =I74*(1+princ) -> 100595.48 | K74: =J74*(1+princ) -> 103613.35 | ... AM74: =AL74*(1+princ) -> 237059.84
A75: =TEXT(Inputs!$B$80,"") -> Marsa | C75: =Inputs!B81*(1+princ)^ProRate -> 122690 | D75: =C75*(1+princ) -> 126370.7 | E75: =D75*(1+princ) -> 130161.82 | F75: =E75*(1+princ) -> 134066.68 | G75: =F75*(1+princ) -> 138088.68 | H75: =G75*(1+princ) -> 142231.34 | I75: =H75*(1+princ) -> 146498.28 | J75: =I75*(1+princ) -> 150893.22 | K75: =J75*(1+princ) -> 155420.02 | ... AM75: =AL75*(1+princ) -> 355589.77
A76: Other assets of value
A77: =TEXT(Inputs!$B$87,"") -> Jewelry | C77: =Inputs!B88*(1+A1inc)^ProRate -> 50748.14 | D77: =C77*(1+A1inc) -> 51763.103 | E77: =D77*(1+A1inc) -> 52798.365 | F77: =E77*(1+A1inc) -> 53854.333 | G77: =F77*(1+A1inc) -> 54931.419 | H77: =G77*(1+A1inc) -> 56030.048 | I77: =H77*(1+A1inc) -> 57150.649 | J77: =I77*(1+A1inc) -> 58293.662 | K77: =J77*(1+A1inc) -> 59459.535 | ... AM77: =AL77*(1+A1inc) -> 103520.49
A78: =TEXT(Inputs!$B$92,"") -> Car | C78: =Inputs!B93*(1+A2inc)^ProRate -> 38490.424 | D78: =C78*(1+A2inc) -> 36565.903 | E78: =D78*(1+A2inc) -> 34737.608 | F78: =E78*(1+A2inc) -> 33000.727 | G78: =F78*(1+A2inc) -> 31350.691 | H78: =G78*(1+A2inc) -> 29783.156 | I78: =H78*(1+A2inc) -> 28293.999 | J78: =I78*(1+A2inc) -> 26879.299 | K78: =J78*(1+A2inc) -> 25535.334 | ... AM78: =AL78*(1+A2inc) -> 6072.9889
A79: =TEXT(Inputs!$B$97,"") -> Painting | C79: =Inputs!B98*(1+A3inc)^ProRate -> 20448.333 | D79: =C79*(1+A3inc) -> 21061.783 | E79: =D79*(1+A3inc) -> 21693.637 | F79: =E79*(1+A3inc) -> 22344.446 | G79: =F79*(1+A3inc) -> 23014.779 | H79: =G79*(1+A3inc) -> 23705.223 | I79: =H79*(1+A3inc) -> 24416.379 | J79: =I79*(1+A3inc) -> 25148.871 | K79: =J79*(1+A3inc) -> 25903.337 | ... AM79: =AL79*(1+A3inc) -> 59264.961
A80: =TEXT(Inputs!$B$102,"") -> Boat | C80: =Inputs!B103*(1+A4inc)^ProRate -> 173206.91 | D80: =C80*(1+A4inc) -> 164546.56 | E80: =D80*(1+A4inc) -> 156319.23 | F80: =E80*(1+A4inc) -> 148503.27 | G80: =F80*(1+A4inc) -> 141078.11 | H80: =G80*(1+A4inc) -> 134024.2 | I80: =H80*(1+A4inc) -> 127322.99 | J80: =I80*(1+A4inc) -> 120956.84 | K80: =J80*(1+A4inc) -> 114909 | ... AM80: =AL80*(1+A4inc) -> 27328.45
A81: =TEXT(Inputs!$B$107,"") -> Antiques | C81: =Inputs!B108*(1+A5inc)^ProRate -> 83226.95 | D81: =C81*(1+A5inc) -> 84891.489 | E81: =D81*(1+A5inc) -> 86589.319 | F81: =E81*(1+A5inc) -> 88321.106 | G81: =F81*(1+A5inc) -> 90087.528 | H81: =G81*(1+A5inc) -> 91889.278 | I81: =H81*(1+A5inc) -> 93727.064 | J81: =I81*(1+A5inc) -> 95601.605 | K81: =J81*(1+A5inc) -> 97513.637 | ... AM81: =AL81*(1+A5inc) -> 169773.6
A82: Stock market equity investments | C82: =Inputs!B10*(1+stinc)^ProRate -> 31782.574 | D82: =C82*(1+IF(AND(Inputs!$B$228<>"",D$2=Inputs!$B$228),-Inputs!$B$229,IF(AND(Inputs!$B$228<>"",D$2>Inputs!$B$228,D$2<=Inputs!$B$228+Inputs!$B$230),(1/(1-Inputs!$B$229))^(1/Inputs!$B$230)-1,IF(AND(Inputs!$B$233<>"",D$2=Inputs!$B$233),-Inputs!$B$234,IF(AND(Inputs!$B$233<>"",D$2>Inputs!$B$233,D$2<=Inputs!$B$233+Inputs!$B$235),(1/(1-Inputs!$B$234))^(1/Inputs!$B$235)-1,IF(AND(Inputs!$B$238<>"",D$2=Inputs!$B$238),-Inputs!$B$239,IF(AND(Inputs!$B$238<>"",D$2>Inputs!$B$238,D$2<=Inputs!$B$238+Inputs!$B$240),(1/(1-Inputs!$B$239))^(1/Inputs!$B$240)-1,IF(AND(Inputs!$B$243<>"",D$2=Inputs!$B$243),-Inputs!$B$244,IF(AND(Inputs!$B$243<>"",D$2>Inputs!$B$243,D$2<=Inputs!$B$243+Inputs!$B$245),(1/(1-Inputs!$B$244))^(1/Inputs!$B$245)-1,IF(AND(Inputs!$B$248<>"",D$2=Inputs!$B$248),-Inputs!$B$249,IF(AND(Inputs!$B$248<>"",D$2>Inputs!$B$248,D$2<=Inputs!$B$248+Inputs!$B$250),(1/(1-Inputs!$B$249))^(1/Inputs!$B$250)-1,stinc))))))))))) -> 27015.188 | E82: =D82*(1+IF(AND(Inputs!$B$228<>"",E$2=Inputs!$B$228),-Inputs!$B$229,IF(AND(Inputs!$B$228<>"",E$2>Inputs!$B$228,E$2<=Inputs!$B$228+Inputs!$B$230),(1/(1-Inputs!$B$229))^(1/Inputs!$B$230)-1,IF(AND(Inputs!$B$233<>"",E$2=Inputs!$B$233),-Inputs!$B$234,IF(AND(Inputs!$B$233<>"",E$2>Inputs!$B$233,E$2<=Inputs!$B$233+Inputs!$B$235),(1/(1-Inputs!$B$234))^(1/Inputs!$B$235)-1,IF(AND(Inputs!$B$238<>"",E$2=Inputs!$B$238),-Inputs!$B$239,IF(AND(Inputs!$B$238<>"",E$2>Inputs!$B$238,E$2<=Inputs!$B$238+Inputs!$B$240),(1/(1-Inputs!$B$239))^(1/Inputs!$B$240)-1,IF(AND(Inputs!$B$243<>"",E$2=Inputs!$B$243),-Inputs!$B$244,IF(AND(Inputs!$B$243<>"",E$2>Inputs!$B$243,E$2<=Inputs!$B$243+Inputs!$B$245),(1/(1-Inputs!$B$244))^(1/Inputs!$B$245)-1,IF(AND(Inputs!$B$248<>"",E$2=Inputs!$B$248),-Inputs!$B$249,IF(AND(Inputs!$B$248<>"",E$2>Inputs!$B$248,E$2<=Inputs!$B$248+Inputs!$B$250),(1/(1-Inputs!$B$249))^(1/Inputs!$B$250)-1,stinc))))))))))) -> 31782.574 | F82: =E82*(1+IF(AND(Inputs!$B$228<>"",F$2=Inputs!$B$228),-Inputs!$B$229,IF(AND(Inputs!$B$228<>"",F$2>Inputs!$B$228,F$2<=Inputs!$B$228+Inputs!$B$230),(1/(1-Inputs!$B$229))^(1/Inputs!$B$230)-1,IF(AND(Inputs!$B$233<>"",F$2=Inputs!$B$233),-Inputs!$B$234,IF(AND(Inputs!$B$233<>"",F$2>Inputs!$B$233,F$2<=Inputs!$B$233+Inputs!$B$235),(1/(1-Inputs!$B$234))^(1/Inputs!$B$235)-1,IF(AND(Inputs!$B$238<>"",F$2=Inputs!$B$238),-Inputs!$B$239,IF(AND(Inputs!$B$238<>"",F$2>Inputs!$B$238,F$2<=Inputs!$B$238+Inputs!$B$240),(1/(1-Inputs!$B$239))^(1/Inputs!$B$240)-1,IF(AND(Inputs!$B$243<>"",F$2=Inputs!$B$243),-Inputs!$B$244,IF(AND(Inputs!$B$243<>"",F$2>Inputs!$B$243,F$2<=Inputs!$B$243+Inputs!$B$245),(1/(1-Inputs!$B$244))^(1/Inputs!$B$245)-1,IF(AND(Inputs!$B$248<>"",F$2=Inputs!$B$248),-Inputs!$B$249,IF(AND(Inputs!$B$248<>"",F$2>Inputs!$B$248,F$2<=Inputs!$B$248+Inputs!$B$250),(1/(1-Inputs!$B$249))^(1/Inputs!$B$250)-1,stinc))))))))))) -> 34325.18 | G82: =F82*(1+IF(AND(Inputs!$B$228<>"",G$2=Inputs!$B$228),-Inputs!$B$229,IF(AND(Inputs!$B$228<>"",G$2>Inputs!$B$228,G$2<=Inputs!$B$228+Inputs!$B$230),(1/(1-Inputs!$B$229))^(1/Inputs!$B$230)-1,IF(AND(Inputs!$B$233<>"",G$2=Inputs!$B$233),-Inputs!$B$234,IF(AND(Inputs!$B$233<>"",G$2>Inputs!$B$233,G$2<=Inputs!$B$233+Inputs!$B$235),(1/(1-Inputs!$B$234))^(1/Inputs!$B$235)-1,IF(AND(Inputs!$B$238<>"",G$2=Inputs!$B$238),-Inputs!$B$239,IF(AND(Inputs!$B$238<>"",G$2>Inputs!$B$238,G$2<=Inputs!$B$238+Inputs!$B$240),(1/(1-Inputs!$B$239))^(1/Inputs!$B$240)-1,IF(AND(Inputs!$B$243<>"",G$2=Inputs!$B$243),-Inputs!$B$244,IF(AND(Inputs!$B$243<>"",G$2>Inputs!$B$243,G$2<=Inputs!$B$243+Inputs!$B$245),(1/(1-Inputs!$B$244))^(1/Inputs!$B$245)-1,IF(AND(Inputs!$B$248<>"",G$2=Inputs!$B$248),-Inputs!$B$249,IF(AND(Inputs!$B$248<>"",G$2>Inputs!$B$248,G$2<=Inputs!$B$248+Inputs!$B$250),(1/(1-Inputs!$B$249))^(1/Inputs!$B$250)-1,stinc))))))))))) -> 37071.195 | H82: =G82*(1+IF(AND(Inputs!$B$228<>"",H$2=Inputs!$B$228),-Inputs!$B$229,IF(AND(Inputs!$B$228<>"",H$2>Inputs!$B$228,H$2<=Inputs!$B$228+Inputs!$B$230),(1/(1-Inputs!$B$229))^(1/Inputs!$B$230)-1,IF(AND(Inputs!$B$233<>"",H$2=Inputs!$B$233),-Inputs!$B$234,IF(AND(Inputs!$B$233<>"",H$2>Inputs!$B$233,H$2<=Inputs!$B$233+Inputs!$B$235),(1/(1-Inputs!$B$234))^(1/Inputs!$B$235)-1,IF(AND(Inputs!$B$238<>"",H$2=Inputs!$B$238),-Inputs!$B$239,IF(AND(Inputs!$B$238<>"",H$2>Inputs!$B$238,H$2<=Inputs!$B$238+Inputs!$B$240),(1/(1-Inputs!$B$239))^(1/Inputs!$B$240)-1,IF(AND(Inputs!$B$243<>"",H$2=Inputs!$B$243),-Inputs!$B$244,IF(AND(Inputs!$B$243<>"",H$2>Inputs!$B$243,H$2<=Inputs!$B$243+Inputs!$B$245),(1/(1-Inputs!$B$244))^(1/Inputs!$B$245)-1,IF(AND(Inputs!$B$248<>"",H$2=Inputs!$B$248),-Inputs!$B$249,IF(AND(Inputs!$B$248<>"",H$2>Inputs!$B$248,H$2<=Inputs!$B$248+Inputs!$B$250),(1/(1-Inputs!$B$249))^(1/Inputs!$B$250)-1,stinc))))))))))) -> 40036.89 | I82: =H82*(1+IF(AND(Inputs!$B$228<>"",I$2=Inputs!$B$228),-Inputs!$B$229,IF(AND(Inputs!$B$228<>"",I$2>Inputs!$B$228,I$2<=Inputs!$B$228+Inputs!$B$230),(1/(1-Inputs!$B$229))^(1/Inputs!$B$230)-1,IF(AND(Inputs!$B$233<>"",I$2=Inputs!$B$233),-Inputs!$B$234,IF(AND(Inputs!$B$233<>"",I$2>Inputs!$B$233,I$2<=Inputs!$B$233+Inputs!$B$235),(1/(1-Inputs!$B$234))^(1/Inputs!$B$235)-1,IF(AND(Inputs!$B$238<>"",I$2=Inputs!$B$238),-Inputs!$B$239,IF(AND(Inputs!$B$238<>"",I$2>Inputs!$B$238,I$2<=Inputs!$B$238+Inputs!$B$240),(1/(1-Inputs!$B$239))^(1/Inputs!$B$240)-1,IF(AND(Inputs!$B$243<>"",I$2=Inputs!$B$243),-Inputs!$B$244,IF(AND(Inputs!$B$243<>"",I$2>Inputs!$B$243,I$2<=Inputs!$B$243+Inputs!$B$245),(1/(1-Inputs!$B$244))^(1/Inputs!$B$245)-1,IF(AND(Inputs!$B$248<>"",I$2=Inputs!$B$248),-Inputs!$B$249,IF(AND(Inputs!$B$248<>"",I$2>Inputs!$B$248,I$2<=Inputs!$B$248+Inputs!$B$250),(1/(1-Inputs!$B$249))^(1/Inputs!$B$250)-1,stinc))))))))))) -> 32029.512 | J82: =I82*(1+IF(AND(Inputs!$B$228<>"",J$2=Inputs!$B$228),-Inputs!$B$229,IF(AND(Inputs!$B$228<>"",J$2>Inputs!$B$228,J$2<=Inputs!$B$228+Inputs!$B$230),(1/(1-Inputs!$B$229))^(1/Inputs!$B$230)-1,IF(AND(Inputs!$B$233<>"",J$2=Inputs!$B$233),-Inputs!$B$234,IF(AND(Inputs!$B$233<>"",J$2>Inputs!$B$233,J$2<=Inputs!$B$233+Inputs!$B$235),(1/(1-Inputs!$B$234))^(1/Inputs!$B$235)-1,IF(AND(Inputs!$B$238<>"",J$2=Inputs!$B$238),-Inputs!$B$239,IF(AND(Inputs!$B$238<>"",J$2>Inputs!$B$238,J$2<=Inputs!$B$238+Inputs!$B$240),(1/(1-Inputs!$B$239))^(1/Inputs!$B$240)-1,IF(AND(Inputs!$B$243<>"",J$2=Inputs!$B$243),-Inputs!$B$244,IF(AND(Inputs!$B$243<>"",J$2>Inputs!$B$243,J$2<=Inputs!$B$243+Inputs!$B$245),(1/(1-Inputs!$B$244))^(1/Inputs!$B$245)-1,IF(AND(Inputs!$B$248<>"",J$2=Inputs!$B$248),-Inputs!$B$249,IF(AND(Inputs!$B$248<>"",J$2>Inputs!$B$248,J$2<=Inputs!$B$248+Inputs!$B$250),(1/(1-Inputs!$B$249))^(1/Inputs!$B$250)-1,stinc))))))))))) -> 34502.746 | K82: =J82*(1+IF(AND(Inputs!$B$228<>"",K$2=Inputs!$B$228),-Inputs!$B$229,IF(AND(Inputs!$B$228<>"",K$2>Inputs!$B$228,K$2<=Inputs!$B$228+Inputs!$B$230),(1/(1-Inputs!$B$229))^(1/Inputs!$B$230)-1,IF(AND(Inputs!$B$233<>"",K$2=Inputs!$B$233),-Inputs!$B$234,IF(AND(Inputs!$B$233<>"",K$2>Inputs!$B$233,K$2<=Inputs!$B$233+Inputs!$B$235),(1/(1-Inputs!$B$234))^(1/Inputs!$B$235)-1,IF(AND(Inputs!$B$238<>"",K$2=Inputs!$B$238),-Inputs!$B$239,IF(AND(Inputs!$B$238<>"",K$2>Inputs!$B$238,K$2<=Inputs!$B$238+Inputs!$B$240),(1/(1-Inputs!$B$239))^(1/Inputs!$B$240)-1,IF(AND(Inputs!$B$243<>"",K$2=Inputs!$B$243),-Inputs!$B$244,IF(AND(Inputs!$B$243<>"",K$2>Inputs!$B$243,K$2<=Inputs!$B$243+Inputs!$B$245),(1/(1-Inputs!$B$244))^(1/Inputs!$B$245)-1,IF(AND(Inputs!$B$248<>"",K$2=Inputs!$B$248),-Inputs!$B$249,IF(AND(Inputs!$B$248<>"",K$2>Inputs!$B$248,K$2<=Inputs!$B$248+Inputs!$B$250),(1/(1-Inputs!$B$249))^(1/Inputs!$B$250)-1,stinc))))))))))) -> 37166.957 | ... AM82: =AL82*(1+IF(AND(Inputs!$B$228<>"",AM$2=Inputs!$B$228),-Inputs!$B$229,IF(AND(Inputs!$B$228<>"",AM$2>Inputs!$B$228,AM$2<=Inputs!$B$228+Inputs!$B$230),(1/(1-Inputs!$B$229))^(1/Inputs!$B$230)-1,IF(AND(Inputs!$B$233<>"",AM$2=Inputs!$B$233),-Inputs!$B$234,IF(AND(Inputs!$B$233<>"",AM$2>Inputs!$B$233,AM$2<=Inputs!$B$233+Inputs!$B$235),(1/(1-Inputs!$B$234))^(1/Inputs!$B$235)-1,IF(AND(Inputs!$B$238<>"",AM$2=Inputs!$B$238),-Inputs!$B$239,IF(AND(Inputs!$B$238<>"",AM$2>Inputs!$B$238,AM$2<=Inputs!$B$238+Inputs!$B$240),(1/(1-Inputs!$B$239))^(1/Inputs!$B$240)-1,IF(AND(Inputs!$B$243<>"",AM$2=Inputs!$B$243),-Inputs!$B$244,IF(AND(Inputs!$B$243<>"",AM$2>Inputs!$B$243,AM$2<=Inputs!$B$243+Inputs!$B$245),(1/(1-Inputs!$B$244))^(1/Inputs!$B$245)-1,IF(AND(Inputs!$B$248<>"",AM$2=Inputs!$B$248),-Inputs!$B$249,IF(AND(Inputs!$B$248<>"",AM$2>Inputs!$B$248,AM$2<=Inputs!$B$248+Inputs!$B$250),(1/(1-Inputs!$B$249))^(1/Inputs!$B$250)-1,stinc))))))))))) -> 108885.28
A83: Home loan | C83: =IF(AND(Inputs!$B$217<>"",C$2>=Inputs!$B$217,Inputs!$B$12>0),0,-MAX(FV(Inputs!$B$16/12,C$1*12+MthOff,Inputs!$B$17,-Inputs!$B$15),0)) -> -48409.158 | D83: =IF(AND(Inputs!$B$217<>"",D$2>=Inputs!$B$217,Inputs!$B$12>0),0,-MAX(FV(Inputs!$B$16/12,D$1*12+MthOff,Inputs!$B$17,-Inputs!$B$15),0)) -> -46231.654 | E83: =IF(AND(Inputs!$B$217<>"",E$2>=Inputs!$B$217,Inputs!$B$12>0),0,-MAX(FV(Inputs!$B$16/12,E$1*12+MthOff,Inputs!$B$17,-Inputs!$B$15),0)) -> -43987.919 | F83: =IF(AND(Inputs!$B$217<>"",F$2>=Inputs!$B$217,Inputs!$B$12>0),0,-MAX(FV(Inputs!$B$16/12,F$1*12+MthOff,Inputs!$B$17,-Inputs!$B$15),0)) -> -41675.939 | G83: =IF(AND(Inputs!$B$217<>"",G$2>=Inputs!$B$217,Inputs!$B$12>0),0,-MAX(FV(Inputs!$B$16/12,G$1*12+MthOff,Inputs!$B$17,-Inputs!$B$15),0)) -> 0 | H83: =IF(AND(Inputs!$B$217<>"",H$2>=Inputs!$B$217,Inputs!$B$12>0),0,-MAX(FV(Inputs!$B$16/12,H$1*12+MthOff,Inputs!$B$17,-Inputs!$B$15),0)) -> 0 | I83: =IF(AND(Inputs!$B$217<>"",I$2>=Inputs!$B$217,Inputs!$B$12>0),0,-MAX(FV(Inputs!$B$16/12,I$1*12+MthOff,Inputs!$B$17,-Inputs!$B$15),0)) -> 0 | J83: =IF(AND(Inputs!$B$217<>"",J$2>=Inputs!$B$217,Inputs!$B$12>0),0,-MAX(FV(Inputs!$B$16/12,J$1*12+MthOff,Inputs!$B$17,-Inputs!$B$15),0)) -> 0 | ... AM83: =IF(AND(Inputs!$B$217<>"",AM$2>=Inputs!$B$217,Inputs!$B$12>0),0,-MAX(FV(Inputs!$B$16/12,AM$1*12+MthOff,Inputs!$B$17,-Inputs!$B$15),0)) -> 0
A84: Other asset loans
A85: =TEXT(Inputs!$B$60,"") -> Sliema | C85: =-MAX(FV(Inputs!$B128/12,C$1*12+MthOff,Inputs!$B129,-Inputs!$B127),0) -> -46591.052 | D85: =-MAX(FV(Inputs!$B128/12,D$1*12+MthOff,Inputs!$B129,-Inputs!$B127),0) -> -41924.972 | E85: =-MAX(FV(Inputs!$B128/12,E$1*12+MthOff,Inputs!$B129,-Inputs!$B127),0) -> -37116.969 | F85: =-MAX(FV(Inputs!$B128/12,F$1*12+MthOff,Inputs!$B129,-Inputs!$B127),0) -> -32162.726 | G85: =-MAX(FV(Inputs!$B128/12,G$1*12+MthOff,Inputs!$B129,-Inputs!$B127),0) -> -27057.795 | H85: =-MAX(FV(Inputs!$B128/12,H$1*12+MthOff,Inputs!$B129,-Inputs!$B127),0) -> -21797.592 | I85: =-MAX(FV(Inputs!$B128/12,I$1*12+MthOff,Inputs!$B129,-Inputs!$B127),0) -> -16377.395 | J85: =-MAX(FV(Inputs!$B128/12,J$1*12+MthOff,Inputs!$B129,-Inputs!$B127),0) -> -10792.338 | ... AM85: =-MAX(FV(Inputs!$B128/12,AM$1*12+MthOff,Inputs!$B129,-Inputs!$B127),0) -> 0
A86: =TEXT(Inputs!$B$65,"") -> Gzira | C86: =-MAX(FV(Inputs!$B133/12,C$1*12+MthOff,Inputs!$B134,-Inputs!$B132),0) -> -6816.3065 | D86: =-MAX(FV(Inputs!$B133/12,D$1*12+MthOff,Inputs!$B134,-Inputs!$B132),0) -> -4531.7666 | E86: =-MAX(FV(Inputs!$B133/12,E$1*12+MthOff,Inputs!$B134,-Inputs!$B132),0) -> -2201.1147 | F86: =-MAX(FV(Inputs!$B133/12,F$1*12+MthOff,Inputs!$B134,-Inputs!$B132),0) -> 0 | G86: =-MAX(FV(Inputs!$B133/12,G$1*12+MthOff,Inputs!$B134,-Inputs!$B132),0) -> 0 | H86: =-MAX(FV(Inputs!$B133/12,H$1*12+MthOff,Inputs!$B134,-Inputs!$B132),0) -> 0 | I86: =-MAX(FV(Inputs!$B133/12,I$1*12+MthOff,Inputs!$B134,-Inputs!$B132),0) -> 0 | J86: =-MAX(FV(Inputs!$B133/12,J$1*12+MthOff,Inputs!$B134,-Inputs!$B132),0) -> 0 | ... AM86: =-MAX(FV(Inputs!$B133/12,AM$1*12+MthOff,Inputs!$B134,-Inputs!$B132),0) -> 0
A87: =TEXT(Inputs!$B$70,"") -> Qormi | C87: =-MAX(FV(Inputs!$B138/12,C$1*12+MthOff,Inputs!$B139,-Inputs!$B137),0) -> -13284.1 | D87: =-MAX(FV(Inputs!$B138/12,D$1*12+MthOff,Inputs!$B139,-Inputs!$B137),0) -> -10894.026 | E87: =-MAX(FV(Inputs!$B138/12,E$1*12+MthOff,Inputs!$B139,-Inputs!$B137),0) -> -8381.6709 | F87: =-MAX(FV(Inputs!$B138/12,F$1*12+MthOff,Inputs!$B139,-Inputs!$B137),0) -> -5740.7792 | G87: =-MAX(FV(Inputs!$B138/12,G$1*12+MthOff,Inputs!$B139,-Inputs!$B137),0) -> -2964.7745 | H87: =-MAX(FV(Inputs!$B138/12,H$1*12+MthOff,Inputs!$B139,-Inputs!$B137),0) -> -46.744114 | I87: =-MAX(FV(Inputs!$B138/12,I$1*12+MthOff,Inputs!$B139,-Inputs!$B137),0) -> 0 | J87: =-MAX(FV(Inputs!$B138/12,J$1*12+MthOff,Inputs!$B139,-Inputs!$B137),0) -> 0 | ... AM87: =-MAX(FV(Inputs!$B138/12,AM$1*12+MthOff,Inputs!$B139,-Inputs!$B137),0) -> 0
A88: =TEXT(Inputs!$B$75,"") -> Gudja | C88: =-MAX(FV(Inputs!$B143/12,C$1*12+MthOff,Inputs!$B144,-Inputs!$B142),0) -> -4025.8511 | D88: =-MAX(FV(Inputs!$B143/12,D$1*12+MthOff,Inputs!$B144,-Inputs!$B142),0) -> -3138.2612 | E88: =-MAX(FV(Inputs!$B143/12,E$1*12+MthOff,Inputs!$B144,-Inputs!$B142),0) -> -2232.756 | F88: =-MAX(FV(Inputs!$B143/12,F$1*12+MthOff,Inputs!$B144,-Inputs!$B142),0) -> -1308.9736 | G88: =-MAX(FV(Inputs!$B143/12,G$1*12+MthOff,Inputs!$B144,-Inputs!$B142),0) -> -366.54534 | H88: =-MAX(FV(Inputs!$B143/12,H$1*12+MthOff,Inputs!$B144,-Inputs!$B142),0) -> 0 | I88: =-MAX(FV(Inputs!$B143/12,I$1*12+MthOff,Inputs!$B144,-Inputs!$B142),0) -> 0 | J88: =-MAX(FV(Inputs!$B143/12,J$1*12+MthOff,Inputs!$B144,-Inputs!$B142),0) -> 0 | ... AM88: =-MAX(FV(Inputs!$B143/12,AM$1*12+MthOff,Inputs!$B144,-Inputs!$B142),0) -> 0
A89: =TEXT(Inputs!$B$80,"") -> Marsa | C89: =-MAX(FV(Inputs!$B148/12,C$1*12+MthOff,Inputs!$B149,-Inputs!$B147),0) -> -8649.5822 | D89: =-MAX(FV(Inputs!$B148/12,D$1*12+MthOff,Inputs!$B149,-Inputs!$B147),0) -> -7452.7016 | E89: =-MAX(FV(Inputs!$B148/12,E$1*12+MthOff,Inputs!$B149,-Inputs!$B147),0) -> -6219.4167 | F89: =-MAX(FV(Inputs!$B148/12,F$1*12+MthOff,Inputs!$B149,-Inputs!$B147),0) -> -4948.6203 | G89: =-MAX(FV(Inputs!$B148/12,G$1*12+MthOff,Inputs!$B149,-Inputs!$B147),0) -> -3639.1714 | H89: =-MAX(FV(Inputs!$B148/12,H$1*12+MthOff,Inputs!$B149,-Inputs!$B147),0) -> -2289.8943 | I89: =-MAX(FV(Inputs!$B148/12,I$1*12+MthOff,Inputs!$B149,-Inputs!$B147),0) -> -899.57773 | J89: =-MAX(FV(Inputs!$B148/12,J$1*12+MthOff,Inputs!$B149,-Inputs!$B147),0) -> 0 | ... AM89: =-MAX(FV(Inputs!$B148/12,AM$1*12+MthOff,Inputs!$B149,-Inputs!$B147),0) -> 0
A90: =TEXT(Inputs!$B$87,"") -> Jewelry | C90: =-MAX(FV(Inputs!$B153/12,C$1*12+MthOff,Inputs!$B154,-Inputs!$B152),0) -> -1875.0263 | D90: =-MAX(FV(Inputs!$B153/12,D$1*12+MthOff,Inputs!$B154,-Inputs!$B152),0) -> -1019.5783 | E90: =-MAX(FV(Inputs!$B153/12,E$1*12+MthOff,Inputs!$B154,-Inputs!$B152),0) -> -138.11102 | F90: =-MAX(FV(Inputs!$B153/12,F$1*12+MthOff,Inputs!$B154,-Inputs!$B152),0) -> 0 | G90: =-MAX(FV(Inputs!$B153/12,G$1*12+MthOff,Inputs!$B154,-Inputs!$B152),0) -> 0 | H90: =-MAX(FV(Inputs!$B153/12,H$1*12+MthOff,Inputs!$B154,-Inputs!$B152),0) -> 0 | I90: =-MAX(FV(Inputs!$B153/12,I$1*12+MthOff,Inputs!$B154,-Inputs!$B152),0) -> 0 | J90: =-MAX(FV(Inputs!$B153/12,J$1*12+MthOff,Inputs!$B154,-Inputs!$B152),0) -> 0 | ... AM90: =-MAX(FV(Inputs!$B153/12,AM$1*12+MthOff,Inputs!$B154,-Inputs!$B152),0) -> 0
A91: =TEXT(Inputs!$B$92,"") -> Car | C91: =-MAX(FV(Inputs!$B158/12,C$1*12+MthOff,Inputs!$B159,-Inputs!$B157),0) -> -5311.4222 | D91: =-MAX(FV(Inputs!$B158/12,D$1*12+MthOff,Inputs!$B159,-Inputs!$B157),0) -> -4377.1171 | E91: =-MAX(FV(Inputs!$B158/12,E$1*12+MthOff,Inputs!$B159,-Inputs!$B157),0) -> -3423.9536 | F91: =-MAX(FV(Inputs!$B158/12,F$1*12+MthOff,Inputs!$B159,-Inputs!$B157),0) -> -2451.5512 | G91: =-MAX(FV(Inputs!$B158/12,G$1*12+MthOff,Inputs!$B159,-Inputs!$B157),0) -> -1459.5214 | H91: =-MAX(FV(Inputs!$B158/12,H$1*12+MthOff,Inputs!$B159,-Inputs!$B157),0) -> -447.46816 | I91: =-MAX(FV(Inputs!$B158/12,I$1*12+MthOff,Inputs!$B159,-Inputs!$B157),0) -> 0 | J91: =-MAX(FV(Inputs!$B158/12,J$1*12+MthOff,Inputs!$B159,-Inputs!$B157),0) -> 0 | ... AM91: =-MAX(FV(Inputs!$B158/12,AM$1*12+MthOff,Inputs!$B159,-Inputs!$B157),0) -> 0
A92: =TEXT(Inputs!$B$97,"") -> Painting | C92: =-MAX(FV(Inputs!$B163/12,C$1*12+MthOff,Inputs!$B164,-Inputs!$B162),0) -> -6642.0499 | D92: =-MAX(FV(Inputs!$B163/12,D$1*12+MthOff,Inputs!$B164,-Inputs!$B162),0) -> -5447.0129 | E92: =-MAX(FV(Inputs!$B163/12,E$1*12+MthOff,Inputs!$B164,-Inputs!$B162),0) -> -4190.8354 | F92: =-MAX(FV(Inputs!$B163/12,F$1*12+MthOff,Inputs!$B164,-Inputs!$B162),0) -> -2870.3896 | G92: =-MAX(FV(Inputs!$B163/12,G$1*12+MthOff,Inputs!$B164,-Inputs!$B162),0) -> -1482.3872 | H92: =-MAX(FV(Inputs!$B163/12,H$1*12+MthOff,Inputs!$B164,-Inputs!$B162),0) -> -23.372057 | I92: =-MAX(FV(Inputs!$B163/12,I$1*12+MthOff,Inputs!$B164,-Inputs!$B162),0) -> 0 | J92: =-MAX(FV(Inputs!$B163/12,J$1*12+MthOff,Inputs!$B164,-Inputs!$B162),0) -> 0 | ... AM92: =-MAX(FV(Inputs!$B163/12,AM$1*12+MthOff,Inputs!$B164,-Inputs!$B162),0) -> 0
A93: =TEXT(Inputs!$B$102,"") -> Boat | C93: =-MAX(FV(Inputs!$B168/12,C$1*12+MthOff,Inputs!$B169,-Inputs!$B167),0) -> -36106.783 | D93: =-MAX(FV(Inputs!$B168/12,D$1*12+MthOff,Inputs!$B169,-Inputs!$B167),0) -> -30636.379 | E93: =-MAX(FV(Inputs!$B168/12,E$1*12+MthOff,Inputs!$B169,-Inputs!$B167),0) -> -24828.573 | F93: =-MAX(FV(Inputs!$B168/12,F$1*12+MthOff,Inputs!$B169,-Inputs!$B167),0) -> -18662.554 | G93: =-MAX(FV(Inputs!$B168/12,G$1*12+MthOff,Inputs!$B169,-Inputs!$B167),0) -> -12116.229 | H93: =-MAX(FV(Inputs!$B168/12,H$1*12+MthOff,Inputs!$B169,-Inputs!$B167),0) -> -5166.1406 | I93: =-MAX(FV(Inputs!$B168/12,I$1*12+MthOff,Inputs!$B169,-Inputs!$B167),0) -> 0 | J93: =-MAX(FV(Inputs!$B168/12,J$1*12+MthOff,Inputs!$B169,-Inputs!$B167),0) -> 0 | ... AM93: =-MAX(FV(Inputs!$B168/12,AM$1*12+MthOff,Inputs!$B169,-Inputs!$B167),0) -> 0
A94: =TEXT(Inputs!$B$107,"") -> Antiques | C94: =-MAX(FV(Inputs!$B173/12,C$1*12+MthOff,Inputs!$B174,-Inputs!$B172),0) -> -2886.402 | D94: =-MAX(FV(Inputs!$B173/12,D$1*12+MthOff,Inputs!$B174,-Inputs!$B172),0) -> -1635.8926 | E94: =-MAX(FV(Inputs!$B173/12,E$1*12+MthOff,Inputs!$B174,-Inputs!$B172),0) -> -347.34775 | F94: =-MAX(FV(Inputs!$B173/12,F$1*12+MthOff,Inputs!$B174,-Inputs!$B172),0) -> 0 | G94: =-MAX(FV(Inputs!$B173/12,G$1*12+MthOff,Inputs!$B174,-Inputs!$B172),0) -> 0 | H94: =-MAX(FV(Inputs!$B173/12,H$1*12+MthOff,Inputs!$B174,-Inputs!$B172),0) -> 0 | I94: =-MAX(FV(Inputs!$B173/12,I$1*12+MthOff,Inputs!$B174,-Inputs!$B172),0) -> 0 | J94: =-MAX(FV(Inputs!$B173/12,J$1*12+MthOff,Inputs!$B174,-Inputs!$B172),0) -> 0 | ... AM94: =-MAX(FV(Inputs!$B173/12,AM$1*12+MthOff,Inputs!$B174,-Inputs!$B172),0) -> 0
A95: Other loan | C95: =-MAX(FV(Inputs!$B178/12,C$1*12+MthOff,Inputs!$B179,-Inputs!$B177),0) -> -3724.5365 | D95: =-MAX(FV(Inputs!$B178/12,D$1*12+MthOff,Inputs!$B179,-Inputs!$B177),0) -> -3337.4797 | E95: =-MAX(FV(Inputs!$B178/12,E$1*12+MthOff,Inputs!$B179,-Inputs!$B177),0) -> -2926.55 | F95: =-MAX(FV(Inputs!$B178/12,F$1*12+MthOff,Inputs!$B179,-Inputs!$B177),0) -> -2490.2751 | G95: =-MAX(FV(Inputs!$B178/12,G$1*12+MthOff,Inputs!$B179,-Inputs!$B177),0) -> -2027.0917 | H95: =-MAX(FV(Inputs!$B178/12,H$1*12+MthOff,Inputs!$B179,-Inputs!$B177),0) -> -1535.3401 | I95: =-MAX(FV(Inputs!$B178/12,I$1*12+MthOff,Inputs!$B179,-Inputs!$B177),0) -> -1013.2584 | J95: =-MAX(FV(Inputs!$B178/12,J$1*12+MthOff,Inputs!$B179,-Inputs!$B177),0) -> -458.97588 | ... AM95: =-MAX(FV(Inputs!$B178/12,AM$1*12+MthOff,Inputs!$B179,-Inputs!$B177),0) -> 0
C96: =SUM(C67:C95) -> 1680400.3 | D96: =SUM(D67:D95) -> 1664531.5 | E96: =SUM(E67:E95) -> 1663582.8 | F96: =SUM(F67:F95) -> 1640416.2 | G96: =SUM(G67:G95) -> 1560247.5 | H96: =SUM(H67:H95) -> 1562451.1 | I96: =SUM(I67:I95) -> 1564615.7 | J96: =SUM(J67:J95) -> 1572943.4 | ... AM96: =SUM(AM67:AM95) -> 3253424
A98: Cash available (after buffer) | C98: =C68-buffer -> 16108.438 | D98: =D68-buffer -> -53417.855 | E98: =E68-buffer -> -120356.82 | F98: =F68-buffer -> -208215.58 | G98: =G68-buffer -> -105000.3 | H98: =H68-buffer -> -159203.66 | I98: =I68-buffer -> -197351.91 | J98: =J68-buffer -> -235525.1 | ... AM98: =AM68-buffer -> -590259.55
A99: Liquidation required | C99: =IF(C98<0,-C98,0) -> 0 | D99: =IF(D98+SUM($C99:C99)<0,-(D98+SUM($C99:C99)),0) -> 53417.855 | E99: =IF(E98+SUM($C99:D99)<0,-(E98+SUM($C99:D99)),0) -> 66938.962 | F99: =IF(F98+SUM($C99:E99)<0,-(F98+SUM($C99:E99)),0) -> 87858.759 | G99: =IF(G98+SUM($C99:F99)<0,-(G98+SUM($C99:F99)),0) -> 0 | H99: =IF(H98+SUM($C99:G99)<0,-(H98+SUM($C99:G99)),0) -> 0 | I99: =IF(I98+SUM($C99:H99)<0,-(I98+SUM($C99:H99)),0) -> 0 | J99: =IF(J98+SUM($C99:I99)<0,-(J98+SUM($C99:I99)),0) -> 27309.528 | K99: =IF(K98+SUM($C99:J99)<0,-(K98+SUM($C99:J99)),0) -> 55986.209 | ... AM99: =IF(AM98+SUM($C99:AL99)<0,-(AM98+SUM($C99:AL99)),0) -> 4173.4573
A101: Liquidations
A103: Stock market equity
A104: b/fwd | C104: =C82 -> 31782.574 | D104: =C107 -> 31782.574 | E104: =D107 -> 0 | F104: =E107 -> 0 | G104: =F107 -> 0 | H104: =G107 -> 0 | I104: =H107 -> 0 | J104: =I107 -> 0 | K104: =J107 -> 0 | ... AM104: =AL107 -> 0
A105: Disposals | C105: =-MIN(C104, C99/(1-Inputs!$B$283)) -> 0 | D105: =-MIN(D104, D99/(1-Inputs!$B$283)) -> -31782.574 | E105: =-MIN(E104, E99/(1-Inputs!$B$283)) -> 0 | F105: =-MIN(F104, F99/(1-Inputs!$B$283)) -> 0 | G105: =-MIN(G104, G99/(1-Inputs!$B$283)) -> 0 | H105: =-MIN(H104, H99/(1-Inputs!$B$283)) -> 0 | I105: =-MIN(I104, I99/(1-Inputs!$B$283)) -> 0 | J105: =-MIN(J104, J99/(1-Inputs!$B$283)) -> 0 | ... AM105: =-MIN(AM104, AM99/(1-Inputs!$B$283)) -> 0
...
