Workbook
Name AgeRange: RetNorm_Engine!$C$3:INDEX(RetNorm_Engine!$C$3:$XFD$3, COUNTA(RetNorm_Engine!$C$3:$XFD$3))
Name buffer: Inputs!$B$159
Name ChartCash_Early: RetEarly_Engine!$C$201:INDEX(RetEarly_Engine!$C$201:$XFD$201, COUNTA(RetEarly_Engine!$C$201:$XFD$201))
Name ChartCash_Norm: RetNorm_Engine!$C$201:INDEX(RetNorm_Engine!$C$201:$XFD$201, COUNTA(RetNorm_Engine!$C$201:$XFD$201))
Name ChartNW_Early: RetEarly_Engine!$C$202:INDEX(RetEarly_Engine!$C$202:$XFD$202, COUNTA(RetEarly_Engine!$C$202:$XFD$202))
Name ChartNW_Norm: RetNorm_Engine!$C$202:INDEX(RetNorm_Engine!$C$202:$XFD$202, COUNTA(RetNorm_Engine!$C$202:$XFD$202))
Name EndAge: Inputs!$B$134
Name inf: Inputs!$B$145
Name princ: Inputs!$B$147
Name RetAge: Inputs!$B$19
Name rinc: Inputs!$B$155
Name sincr: Inputs!$B$153
Name stinc: Inputs!$B$151

Sheet Inputs
B1: User inputs | D1: User Tooltips | E1: UI Notes | F1: Excel helpers
A2: QUICK START
A4: Your age | B4: 48 | D4: Must be entered
A6: Current net annual income | B6: 80000 | D6: Net of tax, from employment or self-employment
A8: Total cash balances | B8: 50000 | D8: current and savings accounts, bonds, term deposits
A10: Stock market investments | B10: 30000 | D10: Current market value of equity portfolio
A12: Home current market value | B12: 600000 | D12: Leave blank if not a home owner
A14: Home loan (mortgage)
A15: Balance | B15: 50000 | D15: Leave blank if no mortgage | F15: Months remaining | G15: =IFERROR(NPER(B16/12,-B17,B15),"") -> 68.044529
A16: Interest rate | B16: 0.03 | F16: Years remaining | G16: =IFERROR(G15/12,"") -> 5.6703774
A17: Monthly repayment | B17: 800
A19: Statutory retirement age | B19: 65 | D19: Year at which pension starts
A21: Annual pension at retirement | B21: 16000 | D21: Net annual state pension entitlement
A23: Housing rent | D23: if not a home owner | E23: show only if not a home owner (B12="")
A25: Annual living expenses | B25: 50000
A28: DEEPER DIVE | E28: Activated only if user wants to
A30: Dependents
A32: Dependent 1
A33: Name | B33: John | D33: Leave blank if none
A34: Annual cost | B34: 2000 | D34: Food, education, healthcare, etc. | E34: Hide until user enters dependent name
A35: Years to support | B35: 3 | D35: Years from now | E35: Hide until user enters dependent name
A37: Dependent 2
A38: Name | B38: Jack | D38: Leave blank if none
A39: Annual cost | B39: 1000 | D39: Food, education, healthcare, etc. | E39: Hide until user enters dependent name
A40: Years to support | B40: 5 | D40: Years from now | E40: Hide until user enters dependent name
A42: Dependent 3
A43: Name | B43: Bill | D43: Leave blank if none
A44: Annual cost | B44: 4000 | D44: Food, education, healthcare, etc. | E44: Hide until user enters dependent name
A45: Years to support | B45: 2 | D45: Years from now | E45: Hide until user enters dependent name
A47: Investment Properties
A49: Property 1
A50: Name | B50: Sliema | D50: Leave blank if none
A51: Market value | B51: 300000 | E51: Hide until user enters property name
A52: Annual costs | B52: 5000 | D52: Repairs, maintenance, etc. | E52: Hide until user enters property name
A54: Property 2
A55: Name | B55: Gzira | D55: Leave blank if none
A56: Market value | B56: 150000 | E56: Hide until user enters property name
A57: Annual costs | B57: 2000 | D57: Repairs, maintenance, etc. | E57: Hide until user enters property name
A59: Property 3
A60: Name | B60: Qormi | D60: Leave blank if none
A61: Market value | B61: 220000 | E61: Hide until user enters property name
A62: Annual costs | B62: 1200 | D62: Repairs, maintenance, etc. | E62: Hide until user enters property name
A64: Other income
A66: ="Rental income: "&B50 -> Rental income: Sliema | B66: 12000 | D66: net annual after all costs and tax | E66: Show with property name only if name was entered
A67: ="Rental income: "&B55 -> Rental income: Gzira | B67: 10000 | D67: net annual after all costs and tax | E67: Show with property name only if name was entered
A68: ="Rental income: "&B60 -> Rental income: Qormi | B68: 8000 | D68: net annual after all costs and tax | E68: Show with property name only if name was entered
A70: Other work income (net annual) | B70: 2000 | D70: Part-time / consulting / side projects etc. Leave blank if none
A71: Continue other work until age | B71: 58 | E71: Show only if other work income entered
A73: Other loans
A75: Credit card balances | B75: 1000 | D75: Assumed cleared in Year 1. Leave blank if none
A77: =B50 & " Property" -> Sliema Property
A78: Balance | B78: 50000 | D78: Enter 0 or leave blank if none | F78: Months remaining | G78: =IFERROR(NPER(B79/12,-B80,B78),"") -> 115.21661
A79: Interest rate | B79: 0.03 | F79: Years remaining | G79: =IFERROR(G78/12,"") -> 9.6013842
A80: Monthly repayment | B80: 500
A82: =B55 & " Property" -> Gzira Property
A83: Balance | B83: 8500 | D83: Enter 0 or leave blank if none | F83: Months remaining | G83: =IFERROR(NPER(B84/12,-B85,B83),"") -> 44.117015
A84: Interest rate | B84: 0.02 | F84: Years remaining | G84: =IFERROR(G83/12,"") -> 3.6764179
A85: Monthly repayment | B85: 200
A87: =B60& " Property" -> Qormi Property
A88: Balance | B88: 15000 | D88: Enter 0 or leave blank if none | F88: Months remaining | G88: =IFERROR(NPER(B89/12,-B90,B88),"") -> 69.187439
A89: Interest rate | B89: 0.05 | F89: Years remaining | G89: =IFERROR(G88/12,"") -> 5.7656199
A90: Monthly repayment | B90: 250
A92: Other loan
A93: Balance | B93: 4000 | D93: Leave blank if none | F93: Months remaining | G93: =IFERROR(NPER(B94/12,-B95,B93),"") -> 102.42033
A94: Interest rate | B94: 0.06 | F94: Years remaining | G94: =IFERROR(G93/12,"") -> 8.5350271
A95: Monthly repayment | B95: 50
A97: Major life income events
A99: Income Event 1
A100: Name | B100: Inheritance | D100: Leave blank if none
A101: Amount | B101: 50000 | D101: Enter 0 or leave blank if none
A102: Year | B102: 2035
A104: Income Event 2
A105: Name | B105: Sell Painting | D105: Leave blank if none
A106: Amount | B106: 10000 | D106: Enter 0 or leave blank if none
A107: Year | B107: 2029
A109: Income Event 3
A110: Name | B110: Sell Jewels | D110: Leave blank if none
A111: Amount | B111: 5000 | D111: Enter 0 or leave blank if none
A112: Year | B112: 2032
A114: Major life expense events
A116: Expense Event 1
A117: Name | B117: Wedding | D117: Leave blank if none
A118: Amount | B118: 40000 | D118: Enter 0 or leave blank if none
A119: Year | B119: 2036
A121: Expense Event 2
A122: Name | B122: New Car | D122: Leave blank if none
A123: Amount | B123: 35000 | D123: Enter 0 or leave blank if none
A124: Year | B124: 2029
A126: Expense Event 3
A127: Name | B127: New AC | D127: Leave blank if none
A128: Amount | B128: 15000 | D128: Enter 0 or leave blank if none
A129: Year | B129: 2034
A132: FINER DETAILS | C132: Defaults | E132: Works behind the scenes, show and allow edit if user wants to
A134: Plan to live until age | B134: 85 | C134: 85
A136: Spending adjustment (at today's euros)
A137: from now to 65 | B137: 0 | C137: 0 | D137: more / less than current
A138: from 66-75 | B138: -0.1 | C138: -0.1 | D138: more / less than current
A139: from age 76 | B139: -0.2 | C139: -0.2 | D139: more / less than current
A141: Other post-retirement income | B141: 12000 | D141: Enter 0 or leave blank if none
A142: From age | B142: 58
...

Sheet Output
V2: Retire at | AA2: ="Retire at "&RetEarly_Engine!B3 -> Retire at 55
V3: =RetEarly_Engine!B3 -> 55 | AA3: ="Retire at "&RetAge -> Retire at 65

Sheet RetNorm_Engine
B1: 0 | C1: 1 | D1: =C1+1 -> 2 | E1: =D1+1 -> 3 | F1: =E1+1 -> 4 | G1: =F1+1 -> 5 | H1: =G1+1 -> 6 | I1: =H1+1 -> 7 | J1: =I1+1 -> 8 | K1: =J1+1 -> 9 | ... AM1: =AL1+1 -> 37
B2: Year | C2: =YEAR(TODAY())+1 -> 2027 | D2: =C2+1 -> 2028 | E2: =D2+1 -> 2029 | F2: =E2+1 -> 2030 | G2: =F2+1 -> 2031 | H2: =G2+1 -> 2032 | I2: =H2+1 -> 2033 | J2: =I2+1 -> 2034 | K2: =J2+1 -> 2035 | ... AM2: =AL2+1 -> 2063
B3: =Inputs!B19 -> 65 | C3: =Inputs!B4+1 -> 49 | D3: =C3+1 -> 50 | E3: =D3+1 -> 51 | F3: =E3+1 -> 52 | G3: =F3+1 -> 53 | H3: =G3+1 -> 54 | I3: =H3+1 -> 55 | J3: =I3+1 -> 56 | K3: =J3+1 -> 57 | ... AM3: =AL3+1 -> 85
A4: Inflows
A5: Net employment / self-employment income | C5: =IF(AND(Inputs!$B$19>C3,$B$3>C3),Inputs!$B$6*(1+sincr)^B1,0) -> 80000 | D5: =IF(AND(Inputs!$B$19>D3,$B$3>D3),Inputs!$B$6*(1+sincr)^C1,0) -> 82400 | E5: =IF(AND(Inputs!$B$19>E3,$B$3>E3),Inputs!$B$6*(1+sincr)^D1,0) -> 84872 | F5: =IF(AND(Inputs!$B$19>F3,$B$3>F3),Inputs!$B$6*(1+sincr)^E1,0) -> 87418.16 | G5: =IF(AND(Inputs!$B$19>G3,$B$3>G3),Inputs!$B$6*(1+sincr)^F1,0) -> 90040.705 | H5: =IF(AND(Inputs!$B$19>H3,$B$3>H3),Inputs!$B$6*(1+sincr)^G1,0) -> 92741.926 | I5: =IF(AND(Inputs!$B$19>I3,$B$3>I3),Inputs!$B$6*(1+sincr)^H1,0) -> 95524.184 | J5: =IF(AND(Inputs!$B$19>J3,$B$3>J3),Inputs!$B$6*(1+sincr)^I1,0) -> 98389.909 | ... AM5: =IF(AND(Inputs!$B$19>AM3,$B$3>AM3),Inputs!$B$6*(1+sincr)^AL1,0) -> 0
A6: Net from other work | C6: =IF(C$3<=Inputs!$B$71,Inputs!$B$70,0)*(1+inf)^B$1 -> 2000 | D6: =IF(D$3<=Inputs!$B$71,Inputs!$B$70,0)*(1+inf)^C$1 -> 2050 | E6: =IF(E$3<=Inputs!$B$71,Inputs!$B$70,0)*(1+inf)^D$1 -> 2101.25 | F6: =IF(F$3<=Inputs!$B$71,Inputs!$B$70,0)*(1+inf)^E$1 -> 2153.7812 | G6: =IF(G$3<=Inputs!$B$71,Inputs!$B$70,0)*(1+inf)^F$1 -> 2207.6258 | H6: =IF(H$3<=Inputs!$B$71,Inputs!$B$70,0)*(1+inf)^G$1 -> 2262.8164 | I6: =IF(I$3<=Inputs!$B$71,Inputs!$B$70,0)*(1+inf)^H$1 -> 2319.3868 | J6: =IF(J$3<=Inputs!$B$71,Inputs!$B$70,0)*(1+inf)^I$1 -> 2377.3715 | ... AM6: =IF(AM$3<=Inputs!$B$71,Inputs!$B$70,0)*(1+inf)^AL$1 -> 0
A7: Net rental income from other properties
A8: =TEXT(Inputs!$B$50,"") -> Sliema | C8: =Inputs!B66 -> 12000 | D8: =C8*(1+rinc) -> 12360 | E8: =D8*(1+rinc) -> 12730.8 | F8: =E8*(1+rinc) -> 13112.724 | G8: =F8*(1+rinc) -> 13506.106 | H8: =G8*(1+rinc) -> 13911.289 | I8: =H8*(1+rinc) -> 14328.628 | J8: =I8*(1+rinc) -> 14758.486 | K8: =J8*(1+rinc) -> 15201.241 | ... AM8: =AL8*(1+rinc) -> 34779.34
A9: =TEXT(Inputs!$B$55,"") -> Gzira | C9: =Inputs!B67 -> 10000 | D9: =C9*(1+rinc) -> 10300 | E9: =D9*(1+rinc) -> 10609 | F9: =E9*(1+rinc) -> 10927.27 | G9: =F9*(1+rinc) -> 11255.088 | H9: =G9*(1+rinc) -> 11592.741 | I9: =H9*(1+rinc) -> 11940.523 | J9: =I9*(1+rinc) -> 12298.739 | K9: =J9*(1+rinc) -> 12667.701 | ... AM9: =AL9*(1+rinc) -> 28982.783
A10: =TEXT(Inputs!$B$60,"") -> Qormi | C10: =Inputs!B68 -> 8000 | D10: =C10*(1+rinc) -> 8240 | E10: =D10*(1+rinc) -> 8487.2 | F10: =E10*(1+rinc) -> 8741.816 | G10: =F10*(1+rinc) -> 9004.0705 | H10: =G10*(1+rinc) -> 9274.1926 | I10: =H10*(1+rinc) -> 9552.4184 | J10: =I10*(1+rinc) -> 9838.9909 | K10: =J10*(1+rinc) -> 10134.161 | ... AM10: =AL10*(1+rinc) -> 23186.227
A11: Full pension | C11: =IF(C$3<Inputs!$B$19,0,Inputs!$B$21)*(1+inf)^B$1 -> 0 | D11: =IF(D$3<Inputs!$B$19,0,Inputs!$B$21)*(1+inf)^C$1 -> 0 | E11: =IF(E$3<Inputs!$B$19,0,Inputs!$B$21)*(1+inf)^D$1 -> 0 | F11: =IF(F$3<Inputs!$B$19,0,Inputs!$B$21)*(1+inf)^E$1 -> 0 | G11: =IF(G$3<Inputs!$B$19,0,Inputs!$B$21)*(1+inf)^F$1 -> 0 | H11: =IF(H$3<Inputs!$B$19,0,Inputs!$B$21)*(1+inf)^G$1 -> 0 | I11: =IF(I$3<Inputs!$B$19,0,Inputs!$B$21)*(1+inf)^H$1 -> 0 | J11: =IF(J$3<Inputs!$B$19,0,Inputs!$B$21)*(1+inf)^I$1 -> 0 | ... AM11: =IF(AM$3<Inputs!$B$19,0,Inputs!$B$21)*(1+inf)^AL$1 -> 38920.565
A12: Pension reduction from early retirement | C12: =MIN(0,MAX(-IF(C11=0,0,(Inputs!$B$19-INDEX(3:3,MATCH(0,5:5,0))))*Inputs!$B$157*(1+inf)^B$1,-C11)) -> 0 | D12: =MIN(0,MAX(-IF(D11=0,0,(Inputs!$B$19-INDEX(3:3,MATCH(0,5:5,0))))*Inputs!$B$157*(1+inf)^C$1,-D11)) -> 0 | E12: =MIN(0,MAX(-IF(E11=0,0,(Inputs!$B$19-INDEX(3:3,MATCH(0,5:5,0))))*Inputs!$B$157*(1+inf)^D$1,-E11)) -> 0 | F12: =MIN(0,MAX(-IF(F11=0,0,(Inputs!$B$19-INDEX(3:3,MATCH(0,5:5,0))))*Inputs!$B$157*(1+inf)^E$1,-F11)) -> 0 | G12: =MIN(0,MAX(-IF(G11=0,0,(Inputs!$B$19-INDEX(3:3,MATCH(0,5:5,0))))*Inputs!$B$157*(1+inf)^F$1,-G11)) -> 0 | H12: =MIN(0,MAX(-IF(H11=0,0,(Inputs!$B$19-INDEX(3:3,MATCH(0,5:5,0))))*Inputs!$B$157*(1+inf)^G$1,-H11)) -> 0 | I12: =MIN(0,MAX(-IF(I11=0,0,(Inputs!$B$19-INDEX(3:3,MATCH(0,5:5,0))))*Inputs!$B$157*(1+inf)^H$1,-I11)) -> 0 | J12: =MIN(0,MAX(-IF(J11=0,0,(Inputs!$B$19-INDEX(3:3,MATCH(0,5:5,0))))*Inputs!$B$157*(1+inf)^I$1,-J11)) -> 0 | ... AM12: =MIN(0,MAX(-IF(AM11=0,0,(Inputs!$B$19-INDEX(3:3,MATCH(0,5:5,0))))*Inputs!$B$157*(1+inf)^AL$1,-AM11)) -> 0
A13: Other post-retirement income | C13: =IF(AND(C$3>=Inputs!$B$142,C$3<=Inputs!$B$143),Inputs!$B$141*(1+inf)^B$1,0) -> 0 | D13: =IF(AND(D$3>=Inputs!$B$142,D$3<=Inputs!$B$143),Inputs!$B$141*(1+inf)^C$1,0) -> 0 | E13: =IF(AND(E$3>=Inputs!$B$142,E$3<=Inputs!$B$143),Inputs!$B$141*(1+inf)^D$1,0) -> 0 | F13: =IF(AND(F$3>=Inputs!$B$142,F$3<=Inputs!$B$143),Inputs!$B$141*(1+inf)^E$1,0) -> 0 | G13: =IF(AND(G$3>=Inputs!$B$142,G$3<=Inputs!$B$143),Inputs!$B$141*(1+inf)^F$1,0) -> 0 | H13: =IF(AND(H$3>=Inputs!$B$142,H$3<=Inputs!$B$143),Inputs!$B$141*(1+inf)^G$1,0) -> 0 | I13: =IF(AND(I$3>=Inputs!$B$142,I$3<=Inputs!$B$143),Inputs!$B$141*(1+inf)^H$1,0) -> 0 | J13: =IF(AND(J$3>=Inputs!$B$142,J$3<=Inputs!$B$143),Inputs!$B$141*(1+inf)^I$1,0) -> 0 | ... AM13: =IF(AND(AM$3>=Inputs!$B$142,AM$3<=Inputs!$B$143),Inputs!$B$141*(1+inf)^AL$1,0) -> 0
A14: Major one-off income events
A15: =TEXT(Inputs!B100,"") -> Inheritance | C15: =IF(C$2=Inputs!$B102,Inputs!$B101,0)*(1+inf)^B$1 -> 0 | D15: =IF(D$2=Inputs!$B102,Inputs!$B101,0)*(1+inf)^C$1 -> 0 | E15: =IF(E$2=Inputs!$B102,Inputs!$B101,0)*(1+inf)^D$1 -> 0 | F15: =IF(F$2=Inputs!$B102,Inputs!$B101,0)*(1+inf)^E$1 -> 0 | G15: =IF(G$2=Inputs!$B102,Inputs!$B101,0)*(1+inf)^F$1 -> 0 | H15: =IF(H$2=Inputs!$B102,Inputs!$B101,0)*(1+inf)^G$1 -> 0 | I15: =IF(I$2=Inputs!$B102,Inputs!$B101,0)*(1+inf)^H$1 -> 0 | J15: =IF(J$2=Inputs!$B102,Inputs!$B101,0)*(1+inf)^I$1 -> 0 | ... AM15: =IF(AM$2=Inputs!$B102,Inputs!$B101,0)*(1+inf)^AL$1 -> 0
A16: =TEXT(Inputs!B105,"") -> Sell Painting | C16: =IF(C$2=Inputs!$B107,Inputs!$B106,0)*(1+inf)^B$1 -> 0 | D16: =IF(D$2=Inputs!$B107,Inputs!$B106,0)*(1+inf)^C$1 -> 0 | E16: =IF(E$2=Inputs!$B107,Inputs!$B106,0)*(1+inf)^D$1 -> 10506.25 | F16: =IF(F$2=Inputs!$B107,Inputs!$B106,0)*(1+inf)^E$1 -> 0 | G16: =IF(G$2=Inputs!$B107,Inputs!$B106,0)*(1+inf)^F$1 -> 0 | H16: =IF(H$2=Inputs!$B107,Inputs!$B106,0)*(1+inf)^G$1 -> 0 | I16: =IF(I$2=Inputs!$B107,Inputs!$B106,0)*(1+inf)^H$1 -> 0 | J16: =IF(J$2=Inputs!$B107,Inputs!$B106,0)*(1+inf)^I$1 -> 0 | ... AM16: =IF(AM$2=Inputs!$B107,Inputs!$B106,0)*(1+inf)^AL$1 -> 0
A17: =TEXT(Inputs!B110,"") -> Sell Jewels | C17: =IF(C$2=Inputs!$B112,Inputs!$B111,0)*(1+inf)^B$1 -> 0 | D17: =IF(D$2=Inputs!$B112,Inputs!$B111,0)*(1+inf)^C$1 -> 0 | E17: =IF(E$2=Inputs!$B112,Inputs!$B111,0)*(1+inf)^D$1 -> 0 | F17: =IF(F$2=Inputs!$B112,Inputs!$B111,0)*(1+inf)^E$1 -> 0 | G17: =IF(G$2=Inputs!$B112,Inputs!$B111,0)*(1+inf)^F$1 -> 0 | H17: =IF(H$2=Inputs!$B112,Inputs!$B111,0)*(1+inf)^G$1 -> 5657.0411 | I17: =IF(I$2=Inputs!$B112,Inputs!$B111,0)*(1+inf)^H$1 -> 0 | J17: =IF(J$2=Inputs!$B112,Inputs!$B111,0)*(1+inf)^I$1 -> 0 | ... AM17: =IF(AM$2=Inputs!$B112,Inputs!$B111,0)*(1+inf)^AL$1 -> 0
A18: Interest on cash balances | C18: =MAX(AVERAGE(C49,C49+SUM(C5:C17)-C46)*Inputs!$B$149,0) -> 1552.5 | D18: =MAX(AVERAGE(D49,D49+SUM(D5:D17)-D46)*Inputs!$B$149,0) -> 2230.3125 | E18: =MAX(AVERAGE(E49,E49+SUM(E5:E17)-E46)*Inputs!$B$149,0) -> 2705.525 | F18: =MAX(AVERAGE(F49,F49+SUM(F5:F17)-F46)*Inputs!$B$149,0) -> 3328.3481 | G18: =MAX(AVERAGE(G49,G49+SUM(G5:G17)-G46)*Inputs!$B$149,0) -> 4402.1355 | H18: =MAX(AVERAGE(H49,H49+SUM(H5:H17)-H46)*Inputs!$B$149,0) -> 5708.7818 | I18: =MAX(AVERAGE(I49,I49+SUM(I5:I17)-I46)*Inputs!$B$149,0) -> 7274.3832 | J18: =MAX(AVERAGE(J49,J49+SUM(J5:J17)-J46)*Inputs!$B$149,0) -> 8751.5263 | ... AM18: =MAX(AVERAGE(AM49,AM49+SUM(AM5:AM17)-AM46)*Inputs!$B$149,0) -> 54592.712
C19: =SUM(C4:C18) -> 113552.5 | D19: =SUM(D4:D18) -> 117580.31 | E19: =SUM(E4:E18) -> 132012.02 | F19: =SUM(F4:F18) -> 125682.1 | G19: =SUM(G4:G18) -> 130415.73 | H19: =SUM(H4:H18) -> 141148.79 | I19: =SUM(I4:I18) -> 140939.52 | J19: =SUM(J4:J18) -> 146415.02 | ... AM19: =SUM(AM4:AM18) -> 180461.63
A20: Outflows
A21: Credit cards cleared | C21: =Inputs!B75 -> 1000 | D21: 0 | E21: 0 | F21: 0 | G21: 0 | H21: 0 | I21: 0 | J21: 0 | K21: 0 | L21: 0 | M21: 0 | N21: 0 | O21: 0 | P21: 0 | Q21: 0 | R21: 0 | S21: 0 | T21: 0 | U21: 0 | V21: 0 | W21: 0 | X21: 0 | Y21: 0 | Z21: 0 | AA21: 0 | AB21: 0 | AC21: 0 | AD21: 0 | AE21: 0 | AF21: 0 | AG21: 0 | AH21: 0 | AI21: 0 | AJ21: 0 | AK21: 0 | AL21: 0 | AM21: 0
A22: Home loan repayment | C22: =MAX(IF(C$1*12<=Inputs!$G$15,12,(Inputs!$G$15-B$1*12)),0)*Inputs!$B$17 -> 9600 | D22: =MAX(IF(D$1*12<=Inputs!$G$15,12,(Inputs!$G$15-C$1*12)),0)*Inputs!$B$17 -> 9600 | E22: =MAX(IF(E$1*12<=Inputs!$G$15,12,(Inputs!$G$15-D$1*12)),0)*Inputs!$B$17 -> 9600 | F22: =MAX(IF(F$1*12<=Inputs!$G$15,12,(Inputs!$G$15-E$1*12)),0)*Inputs!$B$17 -> 9600 | G22: =MAX(IF(G$1*12<=Inputs!$G$15,12,(Inputs!$G$15-F$1*12)),0)*Inputs!$B$17 -> 9600 | H22: =MAX(IF(H$1*12<=Inputs!$G$15,12,(Inputs!$G$15-G$1*12)),0)*Inputs!$B$17 -> 6435.6231 | I22: =MAX(IF(I$1*12<=Inputs!$G$15,12,(Inputs!$G$15-H$1*12)),0)*Inputs!$B$17 -> 0 | J22: =MAX(IF(J$1*12<=Inputs!$G$15,12,(Inputs!$G$15-I$1*12)),0)*Inputs!$B$17 -> 0 | ... AM22: =MAX(IF(AM$1*12<=Inputs!$G$15,12,(Inputs!$G$15-AL$1*12)),0)*Inputs!$B$17 -> 0
A23: Other property loans repayments
A24: =TEXT(Inputs!$B$50,"") -> Sliema | C24: =MAX(IF(C$1*12<=Inputs!$G$78,12,(Inputs!$G$78-B$1*12)),0)*Inputs!$B$80 -> 6000 | D24: =MAX(IF(D$1*12<=Inputs!$G$78,12,(Inputs!$G$78-C$1*12)),0)*Inputs!$B$80 -> 6000 | E24: =MAX(IF(E$1*12<=Inputs!$G$78,12,(Inputs!$G$78-D$1*12)),0)*Inputs!$B$80 -> 6000 | F24: =MAX(IF(F$1*12<=Inputs!$G$78,12,(Inputs!$G$78-E$1*12)),0)*Inputs!$B$80 -> 6000 | G24: =MAX(IF(G$1*12<=Inputs!$G$78,12,(Inputs!$G$78-F$1*12)),0)*Inputs!$B$80 -> 6000 | H24: =MAX(IF(H$1*12<=Inputs!$G$78,12,(Inputs!$G$78-G$1*12)),0)*Inputs!$B$80 -> 6000 | I24: =MAX(IF(I$1*12<=Inputs!$G$78,12,(Inputs!$G$78-H$1*12)),0)*Inputs!$B$80 -> 6000 | J24: =MAX(IF(J$1*12<=Inputs!$G$78,12,(Inputs!$G$78-I$1*12)),0)*Inputs!$B$80 -> 6000 | ... AM24: =MAX(IF(AM$1*12<=Inputs!$G$78,12,(Inputs!$G$78-AL$1*12)),0)*Inputs!$B$80 -> 0
A25: =TEXT(Inputs!$B$55,"") -> Gzira | C25: =MAX(IF(C$1*12<=Inputs!$G$83,12,(Inputs!$G$83-B$1*12)),0)*Inputs!$B$85 -> 2400 | D25: =MAX(IF(D$1*12<=Inputs!$G$83,12,(Inputs!$G$83-C$1*12)),0)*Inputs!$B$85 -> 2400 | E25: =MAX(IF(E$1*12<=Inputs!$G$83,12,(Inputs!$G$83-D$1*12)),0)*Inputs!$B$85 -> 2400 | F25: =MAX(IF(F$1*12<=Inputs!$G$83,12,(Inputs!$G$83-E$1*12)),0)*Inputs!$B$85 -> 1623.4029 | G25: =MAX(IF(G$1*12<=Inputs!$G$83,12,(Inputs!$G$83-F$1*12)),0)*Inputs!$B$85 -> 0 | H25: =MAX(IF(H$1*12<=Inputs!$G$83,12,(Inputs!$G$83-G$1*12)),0)*Inputs!$B$85 -> 0 | I25: =MAX(IF(I$1*12<=Inputs!$G$83,12,(Inputs!$G$83-H$1*12)),0)*Inputs!$B$85 -> 0 | J25: =MAX(IF(J$1*12<=Inputs!$G$83,12,(Inputs!$G$83-I$1*12)),0)*Inputs!$B$85 -> 0 | ... AM25: =MAX(IF(AM$1*12<=Inputs!$G$83,12,(Inputs!$G$83-AL$1*12)),0)*Inputs!$B$85 -> 0
A26: =TEXT(Inputs!$B$60,"") -> Qormi | C26: =MAX(IF(C$1*12<=Inputs!$G$88,12,(Inputs!$G$88-B$1*12)),0)*Inputs!$B$90 -> 3000 | D26: =MAX(IF(D$1*12<=Inputs!$G$88,12,(Inputs!$G$88-C$1*12)),0)*Inputs!$B$90 -> 3000 | E26: =MAX(IF(E$1*12<=Inputs!$G$88,12,(Inputs!$G$88-D$1*12)),0)*Inputs!$B$90 -> 3000 | F26: =MAX(IF(F$1*12<=Inputs!$G$88,12,(Inputs!$G$88-E$1*12)),0)*Inputs!$B$90 -> 3000 | G26: =MAX(IF(G$1*12<=Inputs!$G$88,12,(Inputs!$G$88-F$1*12)),0)*Inputs!$B$90 -> 3000 | H26: =MAX(IF(H$1*12<=Inputs!$G$88,12,(Inputs!$G$88-G$1*12)),0)*Inputs!$B$90 -> 2296.8597 | I26: =MAX(IF(I$1*12<=Inputs!$G$88,12,(Inputs!$G$88-H$1*12)),0)*Inputs!$B$90 -> 0 | J26: =MAX(IF(J$1*12<=Inputs!$G$88,12,(Inputs!$G$88-I$1*12)),0)*Inputs!$B$90 -> 0 | ... AM26: =MAX(IF(AM$1*12<=Inputs!$G$88,12,(Inputs!$G$88-AL$1*12)),0)*Inputs!$B$90 -> 0
A27: Other loan repayment | C27: =MAX(IF(C$1*12<=Inputs!$G$93,12,(Inputs!$G$93-B$1*12)),0)*Inputs!$B$95 -> 600 | D27: =MAX(IF(D$1*12<=Inputs!$G$93,12,(Inputs!$G$93-C$1*12)),0)*Inputs!$B$95 -> 600 | E27: =MAX(IF(E$1*12<=Inputs!$G$93,12,(Inputs!$G$93-D$1*12)),0)*Inputs!$B$95 -> 600 | F27: =MAX(IF(F$1*12<=Inputs!$G$93,12,(Inputs!$G$93-E$1*12)),0)*Inputs!$B$95 -> 600 | G27: =MAX(IF(G$1*12<=Inputs!$G$93,12,(Inputs!$G$93-F$1*12)),0)*Inputs!$B$95 -> 600 | H27: =MAX(IF(H$1*12<=Inputs!$G$93,12,(Inputs!$G$93-G$1*12)),0)*Inputs!$B$95 -> 600 | I27: =MAX(IF(I$1*12<=Inputs!$G$93,12,(Inputs!$G$93-H$1*12)),0)*Inputs!$B$95 -> 600 | J27: =MAX(IF(J$1*12<=Inputs!$G$93,12,(Inputs!$G$93-I$1*12)),0)*Inputs!$B$95 -> 600 | ... AM27: =MAX(IF(AM$1*12<=Inputs!$G$93,12,(Inputs!$G$93-AL$1*12)),0)*Inputs!$B$95 -> 0
A28: Dependents cost
A29: =TEXT(Inputs!B33,"") -> John | C29: =IF(Inputs!$B$35>=C$1,Inputs!$B$34,0)*(1+inf)^B$1 -> 2000 | D29: =IF(Inputs!$B$35>=D$1,Inputs!$B$34,0)*(1+inf)^C$1 -> 2050 | E29: =IF(Inputs!$B$35>=E$1,Inputs!$B$34,0)*(1+inf)^D$1 -> 2101.25 | F29: =IF(Inputs!$B$35>=F$1,Inputs!$B$34,0)*(1+inf)^E$1 -> 0 | G29: =IF(Inputs!$B$35>=G$1,Inputs!$B$34,0)*(1+inf)^F$1 -> 0 | H29: =IF(Inputs!$B$35>=H$1,Inputs!$B$34,0)*(1+inf)^G$1 -> 0 | I29: =IF(Inputs!$B$35>=I$1,Inputs!$B$34,0)*(1+inf)^H$1 -> 0 | J29: =IF(Inputs!$B$35>=J$1,Inputs!$B$34,0)*(1+inf)^I$1 -> 0 | ... AM29: =IF(Inputs!$B$35>=AM$1,Inputs!$B$34,0)*(1+inf)^AL$1 -> 0
A30: =TEXT(Inputs!B38,"") -> Jack | C30: =IF(Inputs!$B$40>=C$1,Inputs!$B$39,0)*(1+inf)^B$1 -> 1000 | D30: =IF(Inputs!$B$40>=D$1,Inputs!$B$39,0)*(1+inf)^C$1 -> 1025 | E30: =IF(Inputs!$B$40>=E$1,Inputs!$B$39,0)*(1+inf)^D$1 -> 1050.625 | F30: =IF(Inputs!$B$40>=F$1,Inputs!$B$39,0)*(1+inf)^E$1 -> 1076.8906 | G30: =IF(Inputs!$B$40>=G$1,Inputs!$B$39,0)*(1+inf)^F$1 -> 1103.8129 | H30: =IF(Inputs!$B$40>=H$1,Inputs!$B$39,0)*(1+inf)^G$1 -> 0 | I30: =IF(Inputs!$B$40>=I$1,Inputs!$B$39,0)*(1+inf)^H$1 -> 0 | J30: =IF(Inputs!$B$40>=J$1,Inputs!$B$39,0)*(1+inf)^I$1 -> 0 | ... AM30: =IF(Inputs!$B$40>=AM$1,Inputs!$B$39,0)*(1+inf)^AL$1 -> 0
A31: =TEXT(Inputs!B43,"") -> Bill | C31: =IF(Inputs!$B$45>=C$1,Inputs!$B$44,0)*(1+inf)^B$1 -> 4000 | D31: =IF(Inputs!$B$45>=D$1,Inputs!$B$44,0)*(1+inf)^C$1 -> 4100 | E31: =IF(Inputs!$B$45>=E$1,Inputs!$B$44,0)*(1+inf)^D$1 -> 0 | F31: =IF(Inputs!$B$45>=F$1,Inputs!$B$44,0)*(1+inf)^E$1 -> 0 | G31: =IF(Inputs!$B$45>=G$1,Inputs!$B$44,0)*(1+inf)^F$1 -> 0 | H31: =IF(Inputs!$B$45>=H$1,Inputs!$B$44,0)*(1+inf)^G$1 -> 0 | I31: =IF(Inputs!$B$45>=I$1,Inputs!$B$44,0)*(1+inf)^H$1 -> 0 | J31: =IF(Inputs!$B$45>=J$1,Inputs!$B$44,0)*(1+inf)^I$1 -> 0 | ... AM31: =IF(Inputs!$B$45>=AM$1,Inputs!$B$44,0)*(1+inf)^AL$1 -> 0
A32: Housing rent | C32: =Inputs!$B$23*(1+inf)^B$1 -> 0 | D32: =Inputs!$B$23*(1+inf)^C$1 -> 0 | E32: =Inputs!$B$23*(1+inf)^D$1 -> 0 | F32: =Inputs!$B$23*(1+inf)^E$1 -> 0 | G32: =Inputs!$B$23*(1+inf)^F$1 -> 0 | H32: =Inputs!$B$23*(1+inf)^G$1 -> 0 | I32: =Inputs!$B$23*(1+inf)^H$1 -> 0 | J32: =Inputs!$B$23*(1+inf)^I$1 -> 0 | ... AM32: =Inputs!$B$23*(1+inf)^AL$1 -> 0
A33: Other property costs
A34: =TEXT(Inputs!$B$50,"") -> Sliema | C34: =Inputs!$B52*(1+inf)^B$1 -> 5000 | D34: =Inputs!$B52*(1+inf)^C$1 -> 5125 | E34: =Inputs!$B52*(1+inf)^D$1 -> 5253.125 | F34: =Inputs!$B52*(1+inf)^E$1 -> 5384.4531 | G34: =Inputs!$B52*(1+inf)^F$1 -> 5519.0645 | H34: =Inputs!$B52*(1+inf)^G$1 -> 5657.0411 | I34: =Inputs!$B52*(1+inf)^H$1 -> 5798.4671 | J34: =Inputs!$B52*(1+inf)^I$1 -> 5943.4288 | ... AM34: =Inputs!$B52*(1+inf)^AL$1 -> 12162.677
A35: =TEXT(Inputs!$B$55,"") -> Gzira | C35: =Inputs!$B57*(1+inf)^B$1 -> 2000 | D35: =Inputs!$B57*(1+inf)^C$1 -> 2050 | E35: =Inputs!$B57*(1+inf)^D$1 -> 2101.25 | F35: =Inputs!$B57*(1+inf)^E$1 -> 2153.7812 | G35: =Inputs!$B57*(1+inf)^F$1 -> 2207.6258 | H35: =Inputs!$B57*(1+inf)^G$1 -> 2262.8164 | I35: =Inputs!$B57*(1+inf)^H$1 -> 2319.3868 | J35: =Inputs!$B57*(1+inf)^I$1 -> 2377.3715 | ... AM35: =Inputs!$B57*(1+inf)^AL$1 -> 4865.0706
A36: =TEXT(Inputs!$B$60,"") -> Qormi | C36: =Inputs!$B62*(1+inf)^B$1 -> 1200 | D36: =Inputs!$B62*(1+inf)^C$1 -> 1230 | E36: =Inputs!$B62*(1+inf)^D$1 -> 1260.75 | F36: =Inputs!$B62*(1+inf)^E$1 -> 1292.2687 | G36: =Inputs!$B62*(1+inf)^F$1 -> 1324.5755 | H36: =Inputs!$B62*(1+inf)^G$1 -> 1357.6899 | I36: =Inputs!$B62*(1+inf)^H$1 -> 1391.6321 | J36: =Inputs!$B62*(1+inf)^I$1 -> 1426.4229 | ... AM36: =Inputs!$B62*(1+inf)^AL$1 -> 2919.0424
A37: Living expenses
A38: Current baseline | C38: =Inputs!$B$25*(1+inf)^B$1 -> 50000 | D38: =Inputs!$B$25*(1+inf)^C$1 -> 51250 | E38: =Inputs!$B$25*(1+inf)^D$1 -> 52531.25 | F38: =Inputs!$B$25*(1+inf)^E$1 -> 53844.531 | G38: =Inputs!$B$25*(1+inf)^F$1 -> 55190.645 | H38: =Inputs!$B$25*(1+inf)^G$1 -> 56570.411 | I38: =Inputs!$B$25*(1+inf)^H$1 -> 57984.671 | J38: =Inputs!$B$25*(1+inf)^I$1 -> 59434.288 | ... AM38: =Inputs!$B$25*(1+inf)^AL$1 -> 121626.77
A39: ="Adjustment "&Inputs!A137 -> Adjustment from now to 65 | C39: =IF(C$3<=65,Inputs!$B$137*C$38,0) -> 0 | D39: =IF(D$3<=65,Inputs!$B$137*D$38,0) -> 0 | E39: =IF(E$3<=65,Inputs!$B$137*E$38,0) -> 0 | F39: =IF(F$3<=65,Inputs!$B$137*F$38,0) -> 0 | G39: =IF(G$3<=65,Inputs!$B$137*G$38,0) -> 0 | H39: =IF(H$3<=65,Inputs!$B$137*H$38,0) -> 0 | I39: =IF(I$3<=65,Inputs!$B$137*I$38,0) -> 0 | J39: =IF(J$3<=65,Inputs!$B$137*J$38,0) -> 0 | ... AM39: =IF(AM$3<=65,Inputs!$B$137*AM$38,0) -> 0
A40: ="Adjustment "&Inputs!A138 -> Adjustment from 66-75 | C40: =IF(AND(C$3>65,C$3<=75),Inputs!$B$138*C38,0) -> 0 | D40: =IF(AND(D$3>65,D$3<=75),Inputs!$B$138*D38,0) -> 0 | E40: =IF(AND(E$3>65,E$3<=75),Inputs!$B$138*E38,0) -> 0 | F40: =IF(AND(F$3>65,F$3<=75),Inputs!$B$138*F38,0) -> 0 | G40: =IF(AND(G$3>65,G$3<=75),Inputs!$B$138*G38,0) -> 0 | H40: =IF(AND(H$3>65,H$3<=75),Inputs!$B$138*H38,0) -> 0 | I40: =IF(AND(I$3>65,I$3<=75),Inputs!$B$138*I38,0) -> 0 | J40: =IF(AND(J$3>65,J$3<=75),Inputs!$B$138*J38,0) -> 0 | ... AM40: =IF(AND(AM$3>65,AM$3<=75),Inputs!$B$138*AM38,0) -> 0
A41: ="Adjustment "&Inputs!A139 -> Adjustment from age 76 | C41: =IF(C$3>75,Inputs!$B$139*C$38,0) -> 0 | D41: =IF(D$3>75,Inputs!$B$139*D$38,0) -> 0 | E41: =IF(E$3>75,Inputs!$B$139*E$38,0) -> 0 | F41: =IF(F$3>75,Inputs!$B$139*F$38,0) -> 0 | G41: =IF(G$3>75,Inputs!$B$139*G$38,0) -> 0 | H41: =IF(H$3>75,Inputs!$B$139*H$38,0) -> 0 | I41: =IF(I$3>75,Inputs!$B$139*I$38,0) -> 0 | J41: =IF(J$3>75,Inputs!$B$139*J$38,0) -> 0 | ... AM41: =IF(AM$3>75,Inputs!$B$139*AM$38,0) -> -24325.353
A42: Major one-off expense events
A43: =TEXT(Inputs!$B$117,"") -> Wedding | C43: =IF(C$2=Inputs!$B119,Inputs!$B118,0)*(1+inf)^B$1 -> 0 | D43: =IF(D$2=Inputs!$B119,Inputs!$B118,0)*(1+inf)^C$1 -> 0 | E43: =IF(E$2=Inputs!$B119,Inputs!$B118,0)*(1+inf)^D$1 -> 0 | F43: =IF(F$2=Inputs!$B119,Inputs!$B118,0)*(1+inf)^E$1 -> 0 | G43: =IF(G$2=Inputs!$B119,Inputs!$B118,0)*(1+inf)^F$1 -> 0 | H43: =IF(H$2=Inputs!$B119,Inputs!$B118,0)*(1+inf)^G$1 -> 0 | I43: =IF(I$2=Inputs!$B119,Inputs!$B118,0)*(1+inf)^H$1 -> 0 | J43: =IF(J$2=Inputs!$B119,Inputs!$B118,0)*(1+inf)^I$1 -> 0 | ... AM43: =IF(AM$2=Inputs!$B119,Inputs!$B118,0)*(1+inf)^AL$1 -> 0
A44: =TEXT(Inputs!$B$122,"") -> New Car | C44: =IF(C$2=Inputs!$B124,Inputs!$B123,0)*(1+inf)^B$1 -> 0 | D44: =IF(D$2=Inputs!$B124,Inputs!$B123,0)*(1+inf)^C$1 -> 0 | E44: =IF(E$2=Inputs!$B124,Inputs!$B123,0)*(1+inf)^D$1 -> 36771.875 | F44: =IF(F$2=Inputs!$B124,Inputs!$B123,0)*(1+inf)^E$1 -> 0 | G44: =IF(G$2=Inputs!$B124,Inputs!$B123,0)*(1+inf)^F$1 -> 0 | H44: =IF(H$2=Inputs!$B124,Inputs!$B123,0)*(1+inf)^G$1 -> 0 | I44: =IF(I$2=Inputs!$B124,Inputs!$B123,0)*(1+inf)^H$1 -> 0 | J44: =IF(J$2=Inputs!$B124,Inputs!$B123,0)*(1+inf)^I$1 -> 0 | ... AM44: =IF(AM$2=Inputs!$B124,Inputs!$B123,0)*(1+inf)^AL$1 -> 0
A45: =TEXT(Inputs!$B$127,"") -> New AC | C45: =IF(C$2=Inputs!$B129,Inputs!$B128,0)*(1+inf)^B$1 -> 0 | D45: =IF(D$2=Inputs!$B129,Inputs!$B128,0)*(1+inf)^C$1 -> 0 | E45: =IF(E$2=Inputs!$B129,Inputs!$B128,0)*(1+inf)^D$1 -> 0 | F45: =IF(F$2=Inputs!$B129,Inputs!$B128,0)*(1+inf)^E$1 -> 0 | G45: =IF(G$2=Inputs!$B129,Inputs!$B128,0)*(1+inf)^F$1 -> 0 | H45: =IF(H$2=Inputs!$B129,Inputs!$B128,0)*(1+inf)^G$1 -> 0 | I45: =IF(I$2=Inputs!$B129,Inputs!$B128,0)*(1+inf)^H$1 -> 0 | J45: =IF(J$2=Inputs!$B129,Inputs!$B128,0)*(1+inf)^I$1 -> 17830.286 | ... AM45: =IF(AM$2=Inputs!$B129,Inputs!$B128,0)*(1+inf)^AL$1 -> 0
C46: =SUM(C20:C45) -> 87800 | D46: =SUM(D20:D45) -> 88430 | E46: =SUM(E20:E45) -> 122670.12 | F46: =SUM(F20:F45) -> 84575.328 | G46: =SUM(G20:G45) -> 84545.723 | H46: =SUM(H20:H45) -> 81180.441 | I46: =SUM(I20:I45) -> 74094.157 | J46: =SUM(J20:J45) -> 93611.797 | ... AM46: =SUM(AM20:AM45) -> 117248.2
A48: Net Cash Flow | C48: =C19-C46 -> 25752.5 | D48: =D19-D46 -> 29150.312 | E48: =E19-E46 -> 9341.9 | F48: =F19-F46 -> 41106.771 | G48: =G19-G46 -> 45870.007 | H48: =H19-H46 -> 59968.347 | I48: =I19-I46 -> 66845.366 | J48: =J19-J46 -> 52803.226 | ... AM48: =AM19-AM46 -> 63213.424
A49: Cash b/fwd | C49: =Inputs!B8 -> 50000 | D49: =C50 -> 75752.5 | E49: =D50 -> 104902.81 | F49: =E50 -> 114244.71 | G49: =F50 -> 155351.48 | H49: =G50 -> 201221.49 | I49: =H50 -> 261189.84 | J49: =I50 -> 328035.2 | K49: =J50 -> 380838.43 | ... AM49: =AL50 -> 2179398.1
A50: Cash c/fwd | C50: =SUM(C48:C49) -> 75752.5 | D50: =SUM(D48:D49) -> 104902.81 | E50: =SUM(E48:E49) -> 114244.71 | F50: =SUM(F48:F49) -> 155351.48 | G50: =SUM(G48:G49) -> 201221.49 | H50: =SUM(H48:H49) -> 261189.84 | I50: =SUM(I48:I49) -> 328035.2 | J50: =SUM(J48:J49) -> 380838.43 | ... AM50: =SUM(AM48:AM49) -> 2242611.5
A52: Net Worth before liquidations
A53: Cash | C53: =C50 -> 75752.5 | D53: =D50 -> 104902.81 | E53: =E50 -> 114244.71 | F53: =F50 -> 155351.48 | G53: =G50 -> 201221.49 | H53: =H50 -> 261189.84 | I53: =I50 -> 328035.2 | J53: =J50 -> 380838.43 | ... AM53: =AM50 -> 2242611.5
A54: Home | C54: =Inputs!B12*(1+princ) -> 618000 | D54: =C54*(1+princ) -> 636540 | E54: =D54*(1+princ) -> 655636.2 | F54: =E54*(1+princ) -> 675305.29 | G54: =F54*(1+princ) -> 695564.44 | H54: =G54*(1+princ) -> 716431.38 | I54: =H54*(1+princ) -> 737924.32 | J54: =I54*(1+princ) -> 760062.05 | K54: =J54*(1+princ) -> 782863.91 | ... AM54: =AL54*(1+princ) -> 1791136
A55: Other property
A56: =TEXT(Inputs!$B$50,"") -> Sliema | C56: =Inputs!B51*(1+princ) -> 309000 | D56: =C56*(1+princ) -> 318270 | E56: =D56*(1+princ) -> 327818.1 | F56: =E56*(1+princ) -> 337652.64 | G56: =F56*(1+princ) -> 347782.22 | H56: =G56*(1+princ) -> 358215.69 | I56: =H56*(1+princ) -> 368962.16 | J56: =I56*(1+princ) -> 380031.02 | K56: =J56*(1+princ) -> 391431.96 | ... AM56: =AL56*(1+princ) -> 895568
A57: =TEXT(Inputs!$B$55,"") -> Gzira | C57: =Inputs!B56*(1+princ) -> 154500 | D57: =C57*(1+princ) -> 159135 | E57: =D57*(1+princ) -> 163909.05 | F57: =E57*(1+princ) -> 168826.32 | G57: =F57*(1+princ) -> 173891.11 | H57: =G57*(1+princ) -> 179107.84 | I57: =H57*(1+princ) -> 184481.08 | J57: =I57*(1+princ) -> 190015.51 | K57: =J57*(1+princ) -> 195715.98 | ... AM57: =AL57*(1+princ) -> 447784
A58: =TEXT(Inputs!$B$60,"") -> Qormi | C58: =Inputs!B61*(1+princ) -> 226600 | D58: =C58*(1+princ) -> 233398 | E58: =D58*(1+princ) -> 240399.94 | F58: =E58*(1+princ) -> 247611.94 | G58: =F58*(1+princ) -> 255040.3 | H58: =G58*(1+princ) -> 262691.51 | I58: =H58*(1+princ) -> 270572.25 | J58: =I58*(1+princ) -> 278689.42 | K58: =J58*(1+princ) -> 287050.1 | ... AM58: =AL58*(1+princ) -> 656749.87
A59: Stock market equity investments | C59: =Inputs!B10*(1+stinc) -> 32400 | D59: =C59*(1+stinc) -> 34992 | E59: =D59*(1+stinc) -> 37791.36 | F59: =E59*(1+stinc) -> 40814.669 | G59: =F59*(1+stinc) -> 44079.842 | H59: =G59*(1+stinc) -> 47606.23 | I59: =H59*(1+stinc) -> 51414.728 | J59: =I59*(1+stinc) -> 55527.906 | K59: =J59*(1+stinc) -> 59970.139 | ... AM59: =AL59*(1+stinc) -> 517368.77
A60: Home loan | C60: =-MAX(FV(Inputs!$B16/12,C$1*12,Inputs!$B17,-Inputs!$B15),0) -> -41787.692 | D60: =-MAX(FV(Inputs!$B16/12,D$1*12,Inputs!$B17,-Inputs!$B15),0) -> -33325.598 | E60: =-MAX(FV(Inputs!$B16/12,E$1*12,Inputs!$B17,-Inputs!$B15),0) -> -24606.122 | F60: =-MAX(FV(Inputs!$B16/12,F$1*12,Inputs!$B17,-Inputs!$B15),0) -> -15621.434 | G60: =-MAX(FV(Inputs!$B16/12,G$1*12,Inputs!$B17,-Inputs!$B15),0) -> -6363.469 | H60: =-MAX(FV(Inputs!$B16/12,H$1*12,Inputs!$B17,-Inputs!$B15),0) -> 0 | I60: =-MAX(FV(Inputs!$B16/12,I$1*12,Inputs!$B17,-Inputs!$B15),0) -> 0 | J60: =-MAX(FV(Inputs!$B16/12,J$1*12,Inputs!$B17,-Inputs!$B15),0) -> 0 | ... AM60: =-MAX(FV(Inputs!$B16/12,AM$1*12,Inputs!$B17,-Inputs!$B15),0) -> 0
A61: Other property loans
A62: =TEXT(Inputs!$B$50,"") -> Sliema | C62: =-MAX(FV(Inputs!$B79/12,C$1*12,Inputs!$B80,-Inputs!$B78),0) -> -45437.606 | D62: =-MAX(FV(Inputs!$B79/12,D$1*12,Inputs!$B80,-Inputs!$B78),0) -> -40736.443 | E62: =-MAX(FV(Inputs!$B79/12,E$1*12,Inputs!$B80,-Inputs!$B78),0) -> -35892.29 | F62: =-MAX(FV(Inputs!$B79/12,F$1*12,Inputs!$B80,-Inputs!$B78),0) -> -30900.797 | G62: =-MAX(FV(Inputs!$B79/12,G$1*12,Inputs!$B80,-Inputs!$B78),0) -> -25757.483 | H62: =-MAX(FV(Inputs!$B79/12,H$1*12,Inputs!$B80,-Inputs!$B78),0) -> -20457.73 | I62: =-MAX(FV(Inputs!$B79/12,I$1*12,Inputs!$B80,-Inputs!$B78),0) -> -14996.78 | J62: =-MAX(FV(Inputs!$B79/12,J$1*12,Inputs!$B80,-Inputs!$B78),0) -> -9369.7299 | ... AM62: =-MAX(FV(Inputs!$B79/12,AM$1*12,Inputs!$B80,-Inputs!$B78),0) -> 0
A63: =TEXT(Inputs!$B$55,"") -> Gzira | C63: =-MAX(FV(Inputs!$B84/12,C$1*12,Inputs!$B85,-Inputs!$B83),0) -> -6249.4443 | D63: =-MAX(FV(Inputs!$B84/12,D$1*12,Inputs!$B85,-Inputs!$B83),0) -> -3953.4627 | E63: =-MAX(FV(Inputs!$B84/12,E$1*12,Inputs!$B85,-Inputs!$B83),0) -> -1611.1381 | F63: =-MAX(FV(Inputs!$B84/12,F$1*12,Inputs!$B85,-Inputs!$B83),0) -> 0 | G63: =-MAX(FV(Inputs!$B84/12,G$1*12,Inputs!$B85,-Inputs!$B83),0) -> 0 | H63: =-MAX(FV(Inputs!$B84/12,H$1*12,Inputs!$B85,-Inputs!$B83),0) -> 0 | I63: =-MAX(FV(Inputs!$B84/12,I$1*12,Inputs!$B85,-Inputs!$B83),0) -> 0 | J63: =-MAX(FV(Inputs!$B84/12,J$1*12,Inputs!$B85,-Inputs!$B83),0) -> 0 | ... AM63: =-MAX(FV(Inputs!$B84/12,AM$1*12,Inputs!$B85,-Inputs!$B83),0) -> 0
A64: =TEXT(Inputs!$B$60,"") -> Qormi | C64: =-MAX(FV(Inputs!$B89/12,C$1*12,Inputs!$B90,-Inputs!$B88),0) -> -12697.715 | D64: =-MAX(FV(Inputs!$B89/12,D$1*12,Inputs!$B90,-Inputs!$B88),0) -> -10277.64 | E64: =-MAX(FV(Inputs!$B89/12,E$1*12,Inputs!$B90,-Inputs!$B88),0) -> -7733.7496 | F64: =-MAX(FV(Inputs!$B89/12,F$1*12,Inputs!$B90,-Inputs!$B88),0) -> -5059.709 | G64: =-MAX(FV(Inputs!$B89/12,G$1*12,Inputs!$B90,-Inputs!$B88),0) -> -2248.8595 | H64: =-MAX(FV(Inputs!$B89/12,H$1*12,Inputs!$B90,-Inputs!$B88),0) -> 0 | I64: =-MAX(FV(Inputs!$B89/12,I$1*12,Inputs!$B90,-Inputs!$B88),0) -> 0 | J64: =-MAX(FV(Inputs!$B89/12,J$1*12,Inputs!$B90,-Inputs!$B88),0) -> 0 | ... AM64: =-MAX(FV(Inputs!$B89/12,AM$1*12,Inputs!$B90,-Inputs!$B88),0) -> 0
A65: Other loan | C65: =-MAX(FV(Inputs!$B94/12,C$1*12,Inputs!$B95,-Inputs!$B93),0) -> -3629.9331 | D65: =-MAX(FV(Inputs!$B94/12,D$1*12,Inputs!$B95,-Inputs!$B93),0) -> -3237.0413 | E65: =-MAX(FV(Inputs!$B94/12,E$1*12,Inputs!$B95,-Inputs!$B93),0) -> -2819.9169 | F65: =-MAX(FV(Inputs!$B94/12,F$1*12,Inputs!$B95,-Inputs!$B93),0) -> -2377.065 | G65: =-MAX(FV(Inputs!$B94/12,G$1*12,Inputs!$B95,-Inputs!$B93),0) -> -1906.8991 | H65: =-MAX(FV(Inputs!$B94/12,H$1*12,Inputs!$B95,-Inputs!$B93),0) -> -1407.7343 | I65: =-MAX(FV(Inputs!$B94/12,I$1*12,Inputs!$B95,-Inputs!$B93),0) -> -877.78218 | J65: =-MAX(FV(Inputs!$B94/12,J$1*12,Inputs!$B95,-Inputs!$B93),0) -> -315.14375 | ... AM65: =-MAX(FV(Inputs!$B94/12,AM$1*12,Inputs!$B95,-Inputs!$B93),0) -> 0
C66: =SUM(C52:C65) -> 1306450.1 | D66: =SUM(D52:D65) -> 1395707.6 | E66: =SUM(E52:E65) -> 1467136.1 | F66: =SUM(F52:F65) -> 1571603.3 | G66: =SUM(G52:G65) -> 1681302.7 | H66: =SUM(H52:H65) -> 1803377 | I66: =SUM(I52:I65) -> 1925515.2 | J66: =SUM(J52:J65) -> 2035479.5 | ... AM66: =SUM(AM52:AM65) -> 6551218.2
A68: Cash available (after buffer) | C68: =C53-buffer -> 35752.5 | D68: =D53-buffer -> 64902.812 | E68: =E53-buffer -> 74244.712 | F68: =F53-buffer -> 115351.48 | G68: =G53-buffer -> 161221.49 | H68: =H53-buffer -> 221189.84 | I68: =I53-buffer -> 288035.2 | J68: =J53-buffer -> 340838.43 | ... AM68: =AM53-buffer -> 2202611.5
A69: Liquidation required | C69: =IF(C68<0,-C68,0) -> 0 | D69: =IF(D68+SUM($C69:C69)<0,-(D68+SUM($C69:C69)),0) -> 0 | E69: =IF(E68+SUM($C69:D69)<0,-(E68+SUM($C69:D69)),0) -> 0 | F69: =IF(F68+SUM($C69:E69)<0,-(F68+SUM($C69:E69)),0) -> 0 | G69: =IF(G68+SUM($C69:F69)<0,-(G68+SUM($C69:F69)),0) -> 0 | H69: =IF(H68+SUM($C69:G69)<0,-(H68+SUM($C69:G69)),0) -> 0 | I69: =IF(I68+SUM($C69:H69)<0,-(I68+SUM($C69:H69)),0) -> 0 | J69: =IF(J68+SUM($C69:I69)<0,-(J68+SUM($C69:I69)),0) -> 0 | K69: =IF(K68+SUM($C69:J69)<0,-(K68+SUM($C69:J69)),0) -> 0 | ... AM69: =IF(AM68+SUM($C69:AL69)<0,-(AM68+SUM($C69:AL69)),0) -> 0
A71: Liquidations
A73: Stock market equity
A74: b/fwd | C74: =C59 -> 32400 | D74: =C77 -> 32400 | E74: =D77 -> 34992 | F74: =E77 -> 37791.36 | G74: =F77 -> 40814.669 | H74: =G77 -> 44079.842 | I74: =H77 -> 47606.23 | J74: =I77 -> 51414.728 | K74: =J77 -> 55527.906 | ... AM74: =AL77 -> 479045.16
A75: Disposals | C75: =-MIN( IF(C74>C69/ (1 - Inputs!$B$161), C69/ (1 - Inputs!$B$161), C74), C74/ (1 - Inputs!$B$161) ) -> 0 | D75: =-MIN( IF(D74>D69/ (1 - Inputs!$B$161), D69/ (1 - Inputs!$B$161), D74), D74/ (1 - Inputs!$B$161) ) -> 0 | E75: =-MIN( IF(E74>E69/ (1 - Inputs!$B$161), E69/ (1 - Inputs!$B$161), E74), E74/ (1 - Inputs!$B$161) ) -> 0 | F75: =-MIN( IF(F74>F69/ (1 - Inputs!$B$161), F69/ (1 - Inputs!$B$161), F74), F74/ (1 - Inputs!$B$161) ) -> 0 | G75: =-MIN( IF(G74>G69/ (1 - Inputs!$B$161), G69/ (1 - Inputs!$B$161), G74), G74/ (1 - Inputs!$B$161) ) -> 0 | H75: =-MIN( IF(H74>H69/ (1 - Inputs!$B$161), H69/ (1 - Inputs!$B$161), H74), H74/ (1 - Inputs!$B$161) ) -> 0 | I75: =-MIN( IF(I74>I69/ (1 - Inputs!$B$161), I69/ (1 - Inputs!$B$161), I74), I74/ (1 - Inputs!$B$161) ) -> 0 | J75: =-MIN( IF(J74>J69/ (1 - Inputs!$B$161), J69/ (1 - Inputs!$B$161), J74), J74/ (1 - Inputs!$B$161) ) -> 0 | ... AM75: =-MIN( IF(AM74>AM69/ (1 - Inputs!$B$161), AM69/ (1 - Inputs!$B$161), AM74), AM74/ (1 - Inputs!$B$161) ) -> 0
A76: Growth | C76: 0 | D76: =SUM(D74:D75)*stinc -> 2592 | E76: =SUM(E74:E75)*stinc -> 2799.36 | F76: =SUM(F74:F75)*stinc -> 3023.3088 | G76: =SUM(G74:G75)*stinc -> 3265.1735 | H76: =SUM(H74:H75)*stinc -> 3526.3874 | I76: =SUM(I74:I75)*stinc -> 3808.4984 | J76: =SUM(J74:J75)*stinc -> 4113.1782 | K76: =SUM(K74:K75)*stinc -> 4442.2325 | ... AM76: =SUM(AM74:AM75)*stinc -> 38323.612
A77: c/fwd | C77: =SUM(C74:C76) -> 32400 | D77: =SUM(D74:D76) -> 34992 | E77: =SUM(E74:E76) -> 37791.36 | F77: =SUM(F74:F76) -> 40814.669 | G77: =SUM(G74:G76) -> 44079.842 | H77: =SUM(H74:H76) -> 47606.23 | I77: =SUM(I74:I76) -> 51414.728 | J77: =SUM(J74:J76) -> 55527.906 | ... AM77: =SUM(AM74:AM76) -> 517368.77
A78: Disposal costs | C78: =C75*Inputs!$B$161 -> 0 | D78: =D75*Inputs!$B$161 -> 0 | E78: =E75*Inputs!$B$161 -> 0 | F78: =F75*Inputs!$B$161 -> 0 | G78: =G75*Inputs!$B$161 -> 0 | H78: =H75*Inputs!$B$161 -> 0 | I78: =I75*Inputs!$B$161 -> 0 | J78: =J75*Inputs!$B$161 -> 0 | ... AM78: =AM75*Inputs!$B$161 -> 0
A79: Net proceeds | C79: =-C75+C78 -> 0 | D79: =-D75+D78 -> 0 | E79: =-E75+E78 -> 0 | F79: =-F75+F78 -> 0 | G79: =-G75+G78 -> 0 | H79: =-H75+H78 -> 0 | I79: =-I75+I78 -> 0 | J79: =-J75+J78 -> 0 | ... AM79: =-AM75+AM78 -> 0
A81: Cash available (after buffer) | C81: =C68+SUM($C79:C79) -> 35752.5 | D81: =D68+SUM($C79:D79) -> 64902.812 | E81: =E68+SUM($C79:E79) -> 74244.712 | F81: =F68+SUM($C79:F79) -> 115351.48 | G81: =G68+SUM($C79:G79) -> 161221.49 | H81: =H68+SUM($C79:H79) -> 221189.84 | I81: =I68+SUM($C79:I79) -> 288035.2 | J81: =J68+SUM($C79:J79) -> 340838.43 | ... AM81: =AM68+SUM($C79:AM79) -> 2202611.5
A82: Liquidation required | C82: =IF(C81<0,C81,0) -> 0 | D82: =IF(D81+SUM($C82:C82)<0,-(D81+SUM($C82:C82)),0) -> 0 | E82: =IF(E81+SUM($C82:D82)<0,-(E81+SUM($C82:D82)),0) -> 0 | F82: =IF(F81+SUM($C82:E82)<0,-(F81+SUM($C82:E82)),0) -> 0 | G82: =IF(G81+SUM($C82:F82)<0,-(G81+SUM($C82:F82)),0) -> 0 | H82: =IF(H81+SUM($C82:G82)<0,-(H81+SUM($C82:G82)),0) -> 0 | I82: =IF(I81+SUM($C82:H82)<0,-(I81+SUM($C82:H82)),0) -> 0 | J82: =IF(J81+SUM($C82:I82)<0,-(J81+SUM($C82:I82)),0) -> 0 | K82: =IF(K81+SUM($C82:J82)<0,-(K81+SUM($C82:J82)),0) -> 0 | ... AM82: =IF(AM81+SUM($C82:AL82)<0,-(AM81+SUM($C82:AL82)),0) -> 0
A84: =IF(Inputs!$B$165=6,IFERROR(_xlfn.XLOOKUP($B84,Inputs!$B$166:$B$168,Inputs!$A$166:$A$168,,0,1),""),IFERROR(_xlfn.XLOOKUP($B84,Inputs!$C$166:$C$168,Inputs!$A$166:$A$168,,0,1),"")) -> Gzira | B84: 1
A85: b/fwd | C85: =IFERROR(VLOOKUP($A84,$A$52:$H$66,C$1+2,FALSE),0) -> 154500 | D85: =C88 -> 154500 | E85: =D88 -> 159135 | F85: =E88 -> 163909.05 | G85: =F88 -> 168826.32 | H85: =G88 -> 173891.11 | I85: =H88 -> 179107.84 | J85: =I88 -> 184481.08 | K85: =J88 -> 190015.51 | ... AM85: =AL88 -> 434741.75
A86: Disposals | C86: =-IF(SUM(C82:D82)>0,C85,0) -> 0 | D86: =-IF(E82>0,D85,0) -> 0 | E86: =-IF(F82>0,E85,0) -> 0 | F86: =-IF(G82>0,F85,0) -> 0 | G86: =-IF(H82>0,G85,0) -> 0 | H86: =-IF(I82>0,H85,0) -> 0 | I86: =-IF(J82>0,I85,0) -> 0 | J86: =-IF(K82>0,J85,0) -> 0 | K86: =-IF(L82>0,K85,0) -> 0 | ... AM86: =-IF(AN82>0,AM85,0) -> 0
A87: Growth | C87: 0 | D87: =SUM(D85:D86)*princ -> 4635 | E87: =SUM(E85:E86)*princ -> 4774.05 | F87: =SUM(F85:F86)*princ -> 4917.2715 | G87: =SUM(G85:G86)*princ -> 5064.7896 | H87: =SUM(H85:H86)*princ -> 5216.7333 | I87: =SUM(I85:I86)*princ -> 5373.2353 | J87: =SUM(J85:J86)*princ -> 5534.4324 | K87: =SUM(K85:K86)*princ -> 5700.4654 | ... AM87: =SUM(AM85:AM86)*princ -> 13042.252
A88: c/fwd | C88: =SUM(C85:C87) -> 154500 | D88: =SUM(D85:D87) -> 159135 | E88: =SUM(E85:E87) -> 163909.05 | F88: =SUM(F85:F87) -> 168826.32 | G88: =SUM(G85:G87) -> 173891.11 | H88: =SUM(H85:H87) -> 179107.84 | I88: =SUM(I85:I87) -> 184481.08 | J88: =SUM(J85:J87) -> 190015.51 | ... AM88: =SUM(AM85:AM87) -> 447784
A89: Disposal costs | C89: =C86*Inputs!$B$163 -> 0 | D89: =D86*Inputs!$B$163 -> 0 | E89: =E86*Inputs!$B$163 -> 0 | F89: =F86*Inputs!$B$163 -> 0 | G89: =G86*Inputs!$B$163 -> 0 | H89: =H86*Inputs!$B$163 -> 0 | I89: =I86*Inputs!$B$163 -> 0 | J89: =J86*Inputs!$B$163 -> 0 | ... AM89: =AM86*Inputs!$B$163 -> 0
A90: Rental income foregone | C90: =IFERROR(-IF(C85=0,VLOOKUP($A84,$7:$10,C$1+2,FALSE),0),0) -> 0 | D90: =IFERROR(-IF(D85=0,VLOOKUP($A84,$7:$10,D$1+2,FALSE),0),0) -> 0 | E90: =IFERROR(-IF(E85=0,VLOOKUP($A84,$7:$10,E$1+2,FALSE),0),0) -> 0 | F90: =IFERROR(-IF(F85=0,VLOOKUP($A84,$7:$10,F$1+2,FALSE),0),0) -> 0 | G90: =IFERROR(-IF(G85=0,VLOOKUP($A84,$7:$10,G$1+2,FALSE),0),0) -> 0 | H90: =IFERROR(-IF(H85=0,VLOOKUP($A84,$7:$10,H$1+2,FALSE),0),0) -> 0 | I90: =IFERROR(-IF(I85=0,VLOOKUP($A84,$7:$10,I$1+2,FALSE),0),0) -> 0 | J90: =IFERROR(-IF(J85=0,VLOOKUP($A84,$7:$10,J$1+2,FALSE),0),0) -> 0 | ... AM90: =IFERROR(-IF(AM85=0,VLOOKUP($A84,$7:$10,AM$1+2,FALSE),0),0) -> 0
A91: Annual cost saved | C91: =IFERROR(IF(C85=0,VLOOKUP($A84,$33:$36,C$1+2,FALSE),0),0) -> 0 | D91: =IFERROR(IF(D85=0,VLOOKUP($A84,$33:$36,D$1+2,FALSE),0),0) -> 0 | E91: =IFERROR(IF(E85=0,VLOOKUP($A84,$33:$36,E$1+2,FALSE),0),0) -> 0 | F91: =IFERROR(IF(F85=0,VLOOKUP($A84,$33:$36,F$1+2,FALSE),0),0) -> 0 | G91: =IFERROR(IF(G85=0,VLOOKUP($A84,$33:$36,G$1+2,FALSE),0),0) -> 0 | H91: =IFERROR(IF(H85=0,VLOOKUP($A84,$33:$36,H$1+2,FALSE),0),0) -> 0 | I91: =IFERROR(IF(I85=0,VLOOKUP($A84,$33:$36,I$1+2,FALSE),0),0) -> 0 | J91: =IFERROR(IF(J85=0,VLOOKUP($A84,$33:$36,J$1+2,FALSE),0),0) -> 0 | ... AM91: =IFERROR(IF(AM85=0,VLOOKUP($A84,$33:$36,AM$1+2,FALSE),0),0) -> 0
A92: Loan repayment | B92: =A84 -> Gzira | C92: =IF(AND(C85>0,C88=0),VLOOKUP($A84,$61:$64,C$1+2,FALSE),0) -> 0 | D92: =IF(AND(D85>0,D88=0),VLOOKUP($A84,$61:$64,D$1+2,FALSE),0) -> 0 | E92: =IF(AND(E85>0,E88=0),VLOOKUP($A84,$61:$64,E$1+2,FALSE),0) -> 0 | F92: =IF(AND(F85>0,F88=0),VLOOKUP($A84,$61:$64,F$1+2,FALSE),0) -> 0 | G92: =IF(AND(G85>0,G88=0),VLOOKUP($A84,$61:$64,G$1+2,FALSE),0) -> 0 | H92: =IF(AND(H85>0,H88=0),VLOOKUP($A84,$61:$64,H$1+2,FALSE),0) -> 0 | I92: =IF(AND(I85>0,I88=0),VLOOKUP($A84,$61:$64,I$1+2,FALSE),0) -> 0 | J92: =IF(AND(J85>0,J88=0),VLOOKUP($A84,$61:$64,J$1+2,FALSE),0) -> 0 | ... AM92: =IF(AND(AM85>0,AM88=0),VLOOKUP($A84,$61:$64,AM$1+2,FALSE),0) -> 0
A93: Net proceeds | C93: =-C86+SUM(C89:C92) -> 0 | D93: =-D86+SUM(D89:D92) -> 0 | E93: =-E86+SUM(E89:E92) -> 0 | F93: =-F86+SUM(F89:F92) -> 0 | G93: =-G86+SUM(G89:G92) -> 0 | H93: =-H86+SUM(H89:H92) -> 0 | I93: =-I86+SUM(I89:I92) -> 0 | J93: =-J86+SUM(J89:J92) -> 0 | ... AM93: =-AM86+SUM(AM89:AM92) -> 0
A95: Cash available (after buffer) | C95: =C81+SUM($C93:C93) -> 35752.5 | D95: =D81+SUM($C93:D93) -> 64902.812 | E95: =E81+SUM($C93:E93) -> 74244.712 | F95: =F81+SUM($C93:F93) -> 115351.48 | G95: =G81+SUM($C93:G93) -> 161221.49 | H95: =H81+SUM($C93:H93) -> 221189.84 | I95: =I81+SUM($C93:I93) -> 288035.2 | J95: =J81+SUM($C93:J93) -> 340838.43 | ... AM95: =AM81+SUM($C93:AM93) -> 2202611.5
A96: Extra cash | C96: =MAX(C95+buffer,0)-MAX(C$81+buffer,0) -> 0 | D96: =MAX(D95+buffer,0)-MAX(D$81+buffer,0) -> 0 | E96: =MAX(E95+buffer,0)-MAX(E$81+buffer,0) -> 0 | F96: =MAX(F95+buffer,0)-MAX(F$81+buffer,0) -> 0 | G96: =MAX(G95+buffer,0)-MAX(G$81+buffer,0) -> 0 | H96: =MAX(H95+buffer,0)-MAX(H$81+buffer,0) -> 0 | I96: =MAX(I95+buffer,0)-MAX(I$81+buffer,0) -> 0 | J96: =MAX(J95+buffer,0)-MAX(J$81+buffer,0) -> 0 | ... AM96: =MAX(AM95+buffer,0)-MAX(AM$81+buffer,0) -> 0
A97: Extra interest | C97: =C96*Inputs!$B$149 -> 0 | D97: =D96*Inputs!$B$149 -> 0 | E97: =E96*Inputs!$B$149 -> 0 | F97: =F96*Inputs!$B$149 -> 0 | G97: =G96*Inputs!$B$149 -> 0 | H97: =H96*Inputs!$B$149 -> 0 | I97: =I96*Inputs!$B$149 -> 0 | J97: =J96*Inputs!$B$149 -> 0 | ... AM97: =AM96*Inputs!$B$149 -> 0
A98: Cash available (after extra interest) | C98: =C95+SUM($C97:C97) -> 35752.5 | D98: =D95+SUM($C97:D97) -> 64902.812 | E98: =E95+SUM($C97:E97) -> 74244.712 | F98: =F95+SUM($C97:F97) -> 115351.48 | G98: =G95+SUM($C97:G97) -> 161221.49 | H98: =H95+SUM($C97:H97) -> 221189.84 | I98: =I95+SUM($C97:I97) -> 288035.2 | J98: =J95+SUM($C97:J97) -> 340838.43 | ... AM98: =AM95+SUM($C97:AM97) -> 2202611.5
A99: Liquidation required | C99: =IF(C98<0,C95,0) -> 0 | D99: =IF(D98+SUM($C99:C99)<0,-(D98+SUM($C99:C99)),0) -> 0 | E99: =IF(E98+SUM($C99:D99)<0,-(E98+SUM($C99:D99)),0) -> 0 | F99: =IF(F98+SUM($C99:E99)<0,-(F98+SUM($C99:E99)),0) -> 0 | G99: =IF(G98+SUM($C99:F99)<0,-(G98+SUM($C99:F99)),0) -> 0 | H99: =IF(H98+SUM($C99:G99)<0,-(H98+SUM($C99:G99)),0) -> 0 | I99: =IF(I98+SUM($C99:H99)<0,-(I98+SUM($C99:H99)),0) -> 0 | J99: =IF(J98+SUM($C99:I99)<0,-(J98+SUM($C99:I99)),0) -> 0 | K99: =IF(K98+SUM($C99:J99)<0,-(K98+SUM($C99:J99)),0) -> 0 | ... AM99: =IF(AM98+SUM($C99:AL99)<0,-(AM98+SUM($C99:AL99)),0) -> 0
A101: =IF(Inputs!$B$165=6,IFERROR(_xlfn.XLOOKUP($B101,Inputs!$B$166:$B$168,Inputs!$A$166:$A$168,,0,1),""),IFERROR(_xlfn.XLOOKUP($B101,Inputs!$C$166:$C$168,Inputs!$A$166:$A$168,,0,1),"")) -> Qormi | B101: 2
A102: b/fwd | C102: =IFERROR(VLOOKUP($A101,$A$52:$H$66,C$1+2,FALSE),0) -> 226600 | D102: =C105 -> 226600 | E102: =D105 -> 233398 | F102: =E105 -> 240399.94 | G102: =F105 -> 247611.94 | H102: =G105 -> 255040.3 | I102: =H105 -> 262691.51 | J102: =I105 -> 270572.25 | K102: =J105 -> 278689.42 | ... AM102: =AL105 -> 637621.23
A103: Disposals | C103: =-IF(SUM(C99:D99)>0,C102,0) -> 0 | D103: =-IF(E99>0,D102,0) -> 0 | E103: =-IF(F99>0,E102,0) -> 0 | F103: =-IF(G99>0,F102,0) -> 0 | G103: =-IF(H99>0,G102,0) -> 0 | H103: =-IF(I99>0,H102,0) -> 0 | I103: =-IF(J99>0,I102,0) -> 0 | J103: =-IF(K99>0,J102,0) -> 0 | K103: =-IF(L99>0,K102,0) -> 0 | ... AM103: =-IF(AN99>0,AM102,0) -> 0
A104: Growth | C104: 0 | D104: =SUM(D102:D103)*princ -> 6798 | E104: =SUM(E102:E103)*princ -> 7001.94 | F104: =SUM(F102:F103)*princ -> 7211.9982 | G104: =SUM(G102:G103)*princ -> 7428.3581 | H104: =SUM(H102:H103)*princ -> 7651.2089 | I104: =SUM(I102:I103)*princ -> 7880.7452 | J104: =SUM(J102:J103)*princ -> 8117.1675 | K104: =SUM(K102:K103)*princ -> 8360.6825 | ... AM104: =SUM(AM102:AM103)*princ -> 19128.637
A105: c/fwd | C105: =SUM(C102:C104) -> 226600 | D105: =SUM(D102:D104) -> 233398 | E105: =SUM(E102:E104) -> 240399.94 | F105: =SUM(F102:F104) -> 247611.94 | G105: =SUM(G102:G104) -> 255040.3 | H105: =SUM(H102:H104) -> 262691.51 | I105: =SUM(I102:I104) -> 270572.25 | J105: =SUM(J102:J104) -> 278689.42 | ... AM105: =SUM(AM102:AM104) -> 656749.87
A106: Disposal costs | C106: =C103*Inputs!$B$163 -> 0 | D106: =D103*Inputs!$B$163 -> 0 | E106: =E103*Inputs!$B$163 -> 0 | F106: =F103*Inputs!$B$163 -> 0 | G106: =G103*Inputs!$B$163 -> 0 | H106: =H103*Inputs!$B$163 -> 0 | I106: =I103*Inputs!$B$163 -> 0 | J106: =J103*Inputs!$B$163 -> 0 | ... AM106: =AM103*Inputs!$B$163 -> 0
A107: Rental income foregone | C107: =IFERROR(-IF(C102=0,VLOOKUP($A101,$7:$10,C$1+2,FALSE),0),0) -> 0 | D107: =IFERROR(-IF(D102=0,VLOOKUP($A101,$7:$10,D$1+2,FALSE),0),0) -> 0 | E107: =IFERROR(-IF(E102=0,VLOOKUP($A101,$7:$10,E$1+2,FALSE),0),0) -> 0 | F107: =IFERROR(-IF(F102=0,VLOOKUP($A101,$7:$10,F$1+2,FALSE),0),0) -> 0 | G107: =IFERROR(-IF(G102=0,VLOOKUP($A101,$7:$10,G$1+2,FALSE),0),0) -> 0 | H107: =IFERROR(-IF(H102=0,VLOOKUP($A101,$7:$10,H$1+2,FALSE),0),0) -> 0 | I107: =IFERROR(-IF(I102=0,VLOOKUP($A101,$7:$10,I$1+2,FALSE),0),0) -> 0 | J107: =IFERROR(-IF(J102=0,VLOOKUP($A101,$7:$10,J$1+2,FALSE),0),0) -> 0 | ... AM107: =IFERROR(-IF(AM102=0,VLOOKUP($A101,$7:$10,AM$1+2,FALSE),0),0) -> 0
A108: Annual cost saved | C108: =IFERROR(IF(C102=0,VLOOKUP($A101,$33:$36,C$1+2,FALSE),0),0) -> 0 | D108: =IFERROR(IF(D102=0,VLOOKUP($A101,$33:$36,D$1+2,FALSE),0),0) -> 0 | E108: =IFERROR(IF(E102=0,VLOOKUP($A101,$33:$36,E$1+2,FALSE),0),0) -> 0 | F108: =IFERROR(IF(F102=0,VLOOKUP($A101,$33:$36,F$1+2,FALSE),0),0) -> 0 | G108: =IFERROR(IF(G102=0,VLOOKUP($A101,$33:$36,G$1+2,FALSE),0),0) -> 0 | H108: =IFERROR(IF(H102=0,VLOOKUP($A101,$33:$36,H$1+2,FALSE),0),0) -> 0 | I108: =IFERROR(IF(I102=0,VLOOKUP($A101,$33:$36,I$1+2,FALSE),0),0) -> 0 | J108: =IFERROR(IF(J102=0,VLOOKUP($A101,$33:$36,J$1+2,FALSE),0),0) -> 0 | ... AM108: =IFERROR(IF(AM102=0,VLOOKUP($A101,$33:$36,AM$1+2,FALSE),0),0) -> 0
A109: Loan repayment | B109: =A101 -> Qormi | C109: =IF(AND(C102>0,C105=0),VLOOKUP($A101,$61:$64,C$1+2,FALSE),0) -> 0 | D109: =IF(AND(D102>0,D105=0),VLOOKUP($A101,$61:$64,D$1+2,FALSE),0) -> 0 | E109: =IF(AND(E102>0,E105=0),VLOOKUP($A101,$61:$64,E$1+2,FALSE),0) -> 0 | F109: =IF(AND(F102>0,F105=0),VLOOKUP($A101,$61:$64,F$1+2,FALSE),0) -> 0 | G109: =IF(AND(G102>0,G105=0),VLOOKUP($A101,$61:$64,G$1+2,FALSE),0) -> 0 | H109: =IF(AND(H102>0,H105=0),VLOOKUP($A101,$61:$64,H$1+2,FALSE),0) -> 0 | I109: =IF(AND(I102>0,I105=0),VLOOKUP($A101,$61:$64,I$1+2,FALSE),0) -> 0 | J109: =IF(AND(J102>0,J105=0),VLOOKUP($A101,$61:$64,J$1+2,FALSE),0) -> 0 | ... AM109: =IF(AND(AM102>0,AM105=0),VLOOKUP($A101,$61:$64,AM$1+2,FALSE),0) -> 0
...

Sheet RetEarly_Engine
B1: 0 | C1: 1 | D1: =C1+1 -> 2 | E1: =D1+1 -> 3 | F1: =E1+1 -> 4 | G1: =F1+1 -> 5 | H1: =G1+1 -> 6 | I1: =H1+1 -> 7 | J1: =I1+1 -> 8 | K1: =J1+1 -> 9 | ... AM1: =AL1+1 -> 37
B2: Year | C2: =YEAR(TODAY())+1 -> 2027 | D2: =C2+1 -> 2028 | E2: =D2+1 -> 2029 | F2: =E2+1 -> 2030 | G2: =F2+1 -> 2031 | H2: =G2+1 -> 2032 | I2: =H2+1 -> 2033 | J2: =I2+1 -> 2034 | K2: =J2+1 -> 2035 | ... AM2: =AL2+1 -> 2063
B3: 55 | C3: =Inputs!B4+1 -> 49 | D3: =C3+1 -> 50 | E3: =D3+1 -> 51 | F3: =E3+1 -> 52 | G3: =F3+1 -> 53 | H3: =G3+1 -> 54 | I3: =H3+1 -> 55 | J3: =I3+1 -> 56 | K3: =J3+1 -> 57 | ... AM3: =AL3+1 -> 85
A4: Inflows
A5: Net employment / self-employment income | C5: =IF(AND(Inputs!$B$19>C3,$B$3>C3),Inputs!$B$6*(1+sincr)^B1,0) -> 80000 | D5: =IF(AND(Inputs!$B$19>D3,$B$3>D3),Inputs!$B$6*(1+sincr)^C1,0) -> 82400 | E5: =IF(AND(Inputs!$B$19>E3,$B$3>E3),Inputs!$B$6*(1+sincr)^D1,0) -> 84872 | F5: =IF(AND(Inputs!$B$19>F3,$B$3>F3),Inputs!$B$6*(1+sincr)^E1,0) -> 87418.16 | G5: =IF(AND(Inputs!$B$19>G3,$B$3>G3),Inputs!$B$6*(1+sincr)^F1,0) -> 90040.705 | H5: =IF(AND(Inputs!$B$19>H3,$B$3>H3),Inputs!$B$6*(1+sincr)^G1,0) -> 92741.926 | I5: =IF(AND(Inputs!$B$19>I3,$B$3>I3),Inputs!$B$6*(1+sincr)^H1,0) -> 0 | J5: =IF(AND(Inputs!$B$19>J3,$B$3>J3),Inputs!$B$6*(1+sincr)^I1,0) -> 0 | ... AM5: =IF(AND(Inputs!$B$19>AM3,$B$3>AM3),Inputs!$B$6*(1+sincr)^AL1,0) -> 0
A6: Net from other work | C6: =IF(C$3<=Inputs!$B$71,Inputs!$B$70,0)*(1+inf)^B$1 -> 2000 | D6: =IF(D$3<=Inputs!$B$71,Inputs!$B$70,0)*(1+inf)^C$1 -> 2050 | E6: =IF(E$3<=Inputs!$B$71,Inputs!$B$70,0)*(1+inf)^D$1 -> 2101.25 | F6: =IF(F$3<=Inputs!$B$71,Inputs!$B$70,0)*(1+inf)^E$1 -> 2153.7812 | G6: =IF(G$3<=Inputs!$B$71,Inputs!$B$70,0)*(1+inf)^F$1 -> 2207.6258 | H6: =IF(H$3<=Inputs!$B$71,Inputs!$B$70,0)*(1+inf)^G$1 -> 2262.8164 | I6: =IF(I$3<=Inputs!$B$71,Inputs!$B$70,0)*(1+inf)^H$1 -> 2319.3868 | J6: =IF(J$3<=Inputs!$B$71,Inputs!$B$70,0)*(1+inf)^I$1 -> 2377.3715 | ... AM6: =IF(AM$3<=Inputs!$B$71,Inputs!$B$70,0)*(1+inf)^AL$1 -> 0
A7: Net rental income from other properties
A8: =TEXT(Inputs!$B$50,"") -> Sliema | C8: =Inputs!B66 -> 12000 | D8: =C8*(1+rinc) -> 12360 | E8: =D8*(1+rinc) -> 12730.8 | F8: =E8*(1+rinc) -> 13112.724 | G8: =F8*(1+rinc) -> 13506.106 | H8: =G8*(1+rinc) -> 13911.289 | I8: =H8*(1+rinc) -> 14328.628 | J8: =I8*(1+rinc) -> 14758.486 | K8: =J8*(1+rinc) -> 15201.241 | ... AM8: =AL8*(1+rinc) -> 34779.34
A9: =TEXT(Inputs!$B$55,"") -> Gzira | C9: =Inputs!B67 -> 10000 | D9: =C9*(1+rinc) -> 10300 | E9: =D9*(1+rinc) -> 10609 | F9: =E9*(1+rinc) -> 10927.27 | G9: =F9*(1+rinc) -> 11255.088 | H9: =G9*(1+rinc) -> 11592.741 | I9: =H9*(1+rinc) -> 11940.523 | J9: =I9*(1+rinc) -> 12298.739 | K9: =J9*(1+rinc) -> 12667.701 | ... AM9: =AL9*(1+rinc) -> 28982.783
A10: =TEXT(Inputs!$B$60,"") -> Qormi | C10: =Inputs!B68 -> 8000 | D10: =C10*(1+rinc) -> 8240 | E10: =D10*(1+rinc) -> 8487.2 | F10: =E10*(1+rinc) -> 8741.816 | G10: =F10*(1+rinc) -> 9004.0705 | H10: =G10*(1+rinc) -> 9274.1926 | I10: =H10*(1+rinc) -> 9552.4184 | J10: =I10*(1+rinc) -> 9838.9909 | K10: =J10*(1+rinc) -> 10134.161 | ... AM10: =AL10*(1+rinc) -> 23186.227
A11: Full pension | C11: =IF(C$3<Inputs!$B$19,0,Inputs!$B$21)*(1+inf)^B$1 -> 0 | D11: =IF(D$3<Inputs!$B$19,0,Inputs!$B$21)*(1+inf)^C$1 -> 0 | E11: =IF(E$3<Inputs!$B$19,0,Inputs!$B$21)*(1+inf)^D$1 -> 0 | F11: =IF(F$3<Inputs!$B$19,0,Inputs!$B$21)*(1+inf)^E$1 -> 0 | G11: =IF(G$3<Inputs!$B$19,0,Inputs!$B$21)*(1+inf)^F$1 -> 0 | H11: =IF(H$3<Inputs!$B$19,0,Inputs!$B$21)*(1+inf)^G$1 -> 0 | I11: =IF(I$3<Inputs!$B$19,0,Inputs!$B$21)*(1+inf)^H$1 -> 0 | J11: =IF(J$3<Inputs!$B$19,0,Inputs!$B$21)*(1+inf)^I$1 -> 0 | ... AM11: =IF(AM$3<Inputs!$B$19,0,Inputs!$B$21)*(1+inf)^AL$1 -> 38920.565
A12: Pension reduction from early retirement | C12: =MIN(0,MAX(-IF(C11=0,0,(Inputs!$B$19-INDEX(3:3,MATCH(0,5:5,0))))*Inputs!$B$157*(1+inf)^B$1,-C11)) -> 0 | D12: =MIN(0,MAX(-IF(D11=0,0,(Inputs!$B$19-INDEX(3:3,MATCH(0,5:5,0))))*Inputs!$B$157*(1+inf)^C$1,-D11)) -> 0 | E12: =MIN(0,MAX(-IF(E11=0,0,(Inputs!$B$19-INDEX(3:3,MATCH(0,5:5,0))))*Inputs!$B$157*(1+inf)^D$1,-E11)) -> 0 | F12: =MIN(0,MAX(-IF(F11=0,0,(Inputs!$B$19-INDEX(3:3,MATCH(0,5:5,0))))*Inputs!$B$157*(1+inf)^E$1,-F11)) -> 0 | G12: =MIN(0,MAX(-IF(G11=0,0,(Inputs!$B$19-INDEX(3:3,MATCH(0,5:5,0))))*Inputs!$B$157*(1+inf)^F$1,-G11)) -> 0 | H12: =MIN(0,MAX(-IF(H11=0,0,(Inputs!$B$19-INDEX(3:3,MATCH(0,5:5,0))))*Inputs!$B$157*(1+inf)^G$1,-H11)) -> 0 | I12: =MIN(0,MAX(-IF(I11=0,0,(Inputs!$B$19-INDEX(3:3,MATCH(0,5:5,0))))*Inputs!$B$157*(1+inf)^H$1,-I11)) -> 0 | J12: =MIN(0,MAX(-IF(J11=0,0,(Inputs!$B$19-INDEX(3:3,MATCH(0,5:5,0))))*Inputs!$B$157*(1+inf)^I$1,-J11)) -> 0 | ... AM12: =MIN(0,MAX(-IF(AM11=0,0,(Inputs!$B$19-INDEX(3:3,MATCH(0,5:5,0))))*Inputs!$B$157*(1+inf)^AL$1,-AM11)) -> -7297.6059
A13: Other post-retirement income | C13: =IF(AND(C$3>=Inputs!$B$142,C$3<=Inputs!$B$143),Inputs!$B$141*(1+inf)^B$1,0) -> 0 | D13: =IF(AND(D$3>=Inputs!$B$142,D$3<=Inputs!$B$143),Inputs!$B$141*(1+inf)^C$1,0) -> 0 | E13: =IF(AND(E$3>=Inputs!$B$142,E$3<=Inputs!$B$143),Inputs!$B$141*(1+inf)^D$1,0) -> 0 | F13: =IF(AND(F$3>=Inputs!$B$142,F$3<=Inputs!$B$143),Inputs!$B$141*(1+inf)^E$1,0) -> 0 | G13: =IF(AND(G$3>=Inputs!$B$142,G$3<=Inputs!$B$143),Inputs!$B$141*(1+inf)^F$1,0) -> 0 | H13: =IF(AND(H$3>=Inputs!$B$142,H$3<=Inputs!$B$143),Inputs!$B$141*(1+inf)^G$1,0) -> 0 | I13: =IF(AND(I$3>=Inputs!$B$142,I$3<=Inputs!$B$143),Inputs!$B$141*(1+inf)^H$1,0) -> 0 | J13: =IF(AND(J$3>=Inputs!$B$142,J$3<=Inputs!$B$143),Inputs!$B$141*(1+inf)^I$1,0) -> 0 | ... AM13: =IF(AND(AM$3>=Inputs!$B$142,AM$3<=Inputs!$B$143),Inputs!$B$141*(1+inf)^AL$1,0) -> 0
A14: Major one-off income events
A15: =TEXT(Inputs!B100,"") -> Inheritance | C15: =IF(C$2=Inputs!$B102,Inputs!$B101,0)*(1+inf)^B$1 -> 0 | D15: =IF(D$2=Inputs!$B102,Inputs!$B101,0)*(1+inf)^C$1 -> 0 | E15: =IF(E$2=Inputs!$B102,Inputs!$B101,0)*(1+inf)^D$1 -> 0 | F15: =IF(F$2=Inputs!$B102,Inputs!$B101,0)*(1+inf)^E$1 -> 0 | G15: =IF(G$2=Inputs!$B102,Inputs!$B101,0)*(1+inf)^F$1 -> 0 | H15: =IF(H$2=Inputs!$B102,Inputs!$B101,0)*(1+inf)^G$1 -> 0 | I15: =IF(I$2=Inputs!$B102,Inputs!$B101,0)*(1+inf)^H$1 -> 0 | J15: =IF(J$2=Inputs!$B102,Inputs!$B101,0)*(1+inf)^I$1 -> 0 | ... AM15: =IF(AM$2=Inputs!$B102,Inputs!$B101,0)*(1+inf)^AL$1 -> 0
A16: =TEXT(Inputs!B105,"") -> Sell Painting | C16: =IF(C$2=Inputs!$B107,Inputs!$B106,0)*(1+inf)^B$1 -> 0 | D16: =IF(D$2=Inputs!$B107,Inputs!$B106,0)*(1+inf)^C$1 -> 0 | E16: =IF(E$2=Inputs!$B107,Inputs!$B106,0)*(1+inf)^D$1 -> 10506.25 | F16: =IF(F$2=Inputs!$B107,Inputs!$B106,0)*(1+inf)^E$1 -> 0 | G16: =IF(G$2=Inputs!$B107,Inputs!$B106,0)*(1+inf)^F$1 -> 0 | H16: =IF(H$2=Inputs!$B107,Inputs!$B106,0)*(1+inf)^G$1 -> 0 | I16: =IF(I$2=Inputs!$B107,Inputs!$B106,0)*(1+inf)^H$1 -> 0 | J16: =IF(J$2=Inputs!$B107,Inputs!$B106,0)*(1+inf)^I$1 -> 0 | ... AM16: =IF(AM$2=Inputs!$B107,Inputs!$B106,0)*(1+inf)^AL$1 -> 0
A17: =TEXT(Inputs!B110,"") -> Sell Jewels | C17: =IF(C$2=Inputs!$B112,Inputs!$B111,0)*(1+inf)^B$1 -> 0 | D17: =IF(D$2=Inputs!$B112,Inputs!$B111,0)*(1+inf)^C$1 -> 0 | E17: =IF(E$2=Inputs!$B112,Inputs!$B111,0)*(1+inf)^D$1 -> 0 | F17: =IF(F$2=Inputs!$B112,Inputs!$B111,0)*(1+inf)^E$1 -> 0 | G17: =IF(G$2=Inputs!$B112,Inputs!$B111,0)*(1+inf)^F$1 -> 0 | H17: =IF(H$2=Inputs!$B112,Inputs!$B111,0)*(1+inf)^G$1 -> 5657.0411 | I17: =IF(I$2=Inputs!$B112,Inputs!$B111,0)*(1+inf)^H$1 -> 0 | J17: =IF(J$2=Inputs!$B112,Inputs!$B111,0)*(1+inf)^I$1 -> 0 | ... AM17: =IF(AM$2=Inputs!$B112,Inputs!$B111,0)*(1+inf)^AL$1 -> 0
A18: Interest on cash balances | C18: =MAX(AVERAGE(C49,C49+SUM(C5:C17)-C46)*Inputs!$B$149,0) -> 1552.5 | D18: =MAX(AVERAGE(D49,D49+SUM(D5:D17)-D46)*Inputs!$B$149,0) -> 2230.3125 | E18: =MAX(AVERAGE(E49,E49+SUM(E5:E17)-E46)*Inputs!$B$149,0) -> 2705.525 | F18: =MAX(AVERAGE(F49,F49+SUM(F5:F17)-F46)*Inputs!$B$149,0) -> 3328.3481 | G18: =MAX(AVERAGE(G49,G49+SUM(G5:G17)-G46)*Inputs!$B$149,0) -> 4402.1355 | H18: =MAX(AVERAGE(H49,H49+SUM(H5:H17)-H46)*Inputs!$B$149,0) -> 5708.7818 | I18: =MAX(AVERAGE(I49,I49+SUM(I5:I17)-I46)*Inputs!$B$149,0) -> 6080.3309 | J18: =MAX(AVERAGE(J49,J49+SUM(J5:J17)-J46)*Inputs!$B$149,0) -> 5103.6966 | ... AM18: =MAX(AVERAGE(AM49,AM49+SUM(AM5:AM17)-AM46)*Inputs!$B$149,0) -> 315.53424
C19: =SUM(C4:C18) -> 113552.5 | D19: =SUM(D4:D18) -> 117580.31 | E19: =SUM(E4:E18) -> 132012.02 | F19: =SUM(F4:F18) -> 125682.1 | G19: =SUM(G4:G18) -> 130415.73 | H19: =SUM(H4:H18) -> 141148.79 | I19: =SUM(I4:I18) -> 44221.287 | J19: =SUM(J4:J18) -> 44377.284 | ... AM19: =SUM(AM4:AM18) -> 118886.84
A20: Outflows
A21: Credit cards cleared | C21: =Inputs!B75 -> 1000 | D21: 0 | E21: 0 | F21: 0 | G21: 0 | H21: 0 | I21: 0 | J21: 0 | K21: 0 | L21: 0 | M21: 0 | N21: 0 | O21: 0 | P21: 0 | Q21: 0 | R21: 0 | S21: 0 | T21: 0 | U21: 0 | V21: 0 | W21: 0 | X21: 0 | Y21: 0 | Z21: 0 | AA21: 0 | AB21: 0 | AC21: 0 | AD21: 0 | AE21: 0 | AF21: 0 | AG21: 0 | AH21: 0 | AI21: 0 | AJ21: 0 | AK21: 0 | AL21: 0 | AM21: 0
A22: Home loan repayment | C22: =MAX(IF(C$1*12<=Inputs!$G$15,12,(Inputs!$G$15-B$1*12)),0)*Inputs!$B$17 -> 9600 | D22: =MAX(IF(D$1*12<=Inputs!$G$15,12,(Inputs!$G$15-C$1*12)),0)*Inputs!$B$17 -> 9600 | E22: =MAX(IF(E$1*12<=Inputs!$G$15,12,(Inputs!$G$15-D$1*12)),0)*Inputs!$B$17 -> 9600 | F22: =MAX(IF(F$1*12<=Inputs!$G$15,12,(Inputs!$G$15-E$1*12)),0)*Inputs!$B$17 -> 9600 | G22: =MAX(IF(G$1*12<=Inputs!$G$15,12,(Inputs!$G$15-F$1*12)),0)*Inputs!$B$17 -> 9600 | H22: =MAX(IF(H$1*12<=Inputs!$G$15,12,(Inputs!$G$15-G$1*12)),0)*Inputs!$B$17 -> 6435.6231 | I22: =MAX(IF(I$1*12<=Inputs!$G$15,12,(Inputs!$G$15-H$1*12)),0)*Inputs!$B$17 -> 0 | J22: =MAX(IF(J$1*12<=Inputs!$G$15,12,(Inputs!$G$15-I$1*12)),0)*Inputs!$B$17 -> 0 | ... AM22: =MAX(IF(AM$1*12<=Inputs!$G$15,12,(Inputs!$G$15-AL$1*12)),0)*Inputs!$B$17 -> 0
A23: Other property loans repayments
A24: =TEXT(Inputs!$B$50,"") -> Sliema | C24: =MAX(IF(C$1*12<=Inputs!$G$78,12,(Inputs!$G$78-B$1*12)),0)*Inputs!$B$80 -> 6000 | D24: =MAX(IF(D$1*12<=Inputs!$G$78,12,(Inputs!$G$78-C$1*12)),0)*Inputs!$B$80 -> 6000 | E24: =MAX(IF(E$1*12<=Inputs!$G$78,12,(Inputs!$G$78-D$1*12)),0)*Inputs!$B$80 -> 6000 | F24: =MAX(IF(F$1*12<=Inputs!$G$78,12,(Inputs!$G$78-E$1*12)),0)*Inputs!$B$80 -> 6000 | G24: =MAX(IF(G$1*12<=Inputs!$G$78,12,(Inputs!$G$78-F$1*12)),0)*Inputs!$B$80 -> 6000 | H24: =MAX(IF(H$1*12<=Inputs!$G$78,12,(Inputs!$G$78-G$1*12)),0)*Inputs!$B$80 -> 6000 | I24: =MAX(IF(I$1*12<=Inputs!$G$78,12,(Inputs!$G$78-H$1*12)),0)*Inputs!$B$80 -> 6000 | J24: =MAX(IF(J$1*12<=Inputs!$G$78,12,(Inputs!$G$78-I$1*12)),0)*Inputs!$B$80 -> 6000 | ... AM24: =MAX(IF(AM$1*12<=Inputs!$G$78,12,(Inputs!$G$78-AL$1*12)),0)*Inputs!$B$80 -> 0
A25: =TEXT(Inputs!$B$55,"") -> Gzira | C25: =MAX(IF(C$1*12<=Inputs!$G$83,12,(Inputs!$G$83-B$1*12)),0)*Inputs!$B$85 -> 2400 | D25: =MAX(IF(D$1*12<=Inputs!$G$83,12,(Inputs!$G$83-C$1*12)),0)*Inputs!$B$85 -> 2400 | E25: =MAX(IF(E$1*12<=Inputs!$G$83,12,(Inputs!$G$83-D$1*12)),0)*Inputs!$B$85 -> 2400 | F25: =MAX(IF(F$1*12<=Inputs!$G$83,12,(Inputs!$G$83-E$1*12)),0)*Inputs!$B$85 -> 1623.4029 | G25: =MAX(IF(G$1*12<=Inputs!$G$83,12,(Inputs!$G$83-F$1*12)),0)*Inputs!$B$85 -> 0 | H25: =MAX(IF(H$1*12<=Inputs!$G$83,12,(Inputs!$G$83-G$1*12)),0)*Inputs!$B$85 -> 0 | I25: =MAX(IF(I$1*12<=Inputs!$G$83,12,(Inputs!$G$83-H$1*12)),0)*Inputs!$B$85 -> 0 | J25: =MAX(IF(J$1*12<=Inputs!$G$83,12,(Inputs!$G$83-I$1*12)),0)*Inputs!$B$85 -> 0 | ... AM25: =MAX(IF(AM$1*12<=Inputs!$G$83,12,(Inputs!$G$83-AL$1*12)),0)*Inputs!$B$85 -> 0
A26: =TEXT(Inputs!$B$60,"") -> Qormi | C26: =MAX(IF(C$1*12<=Inputs!$G$88,12,(Inputs!$G$88-B$1*12)),0)*Inputs!$B$90 -> 3000 | D26: =MAX(IF(D$1*12<=Inputs!$G$88,12,(Inputs!$G$88-C$1*12)),0)*Inputs!$B$90 -> 3000 | E26: =MAX(IF(E$1*12<=Inputs!$G$88,12,(Inputs!$G$88-D$1*12)),0)*Inputs!$B$90 -> 3000 | F26: =MAX(IF(F$1*12<=Inputs!$G$88,12,(Inputs!$G$88-E$1*12)),0)*Inputs!$B$90 -> 3000 | G26: =MAX(IF(G$1*12<=Inputs!$G$88,12,(Inputs!$G$88-F$1*12)),0)*Inputs!$B$90 -> 3000 | H26: =MAX(IF(H$1*12<=Inputs!$G$88,12,(Inputs!$G$88-G$1*12)),0)*Inputs!$B$90 -> 2296.8597 | I26: =MAX(IF(I$1*12<=Inputs!$G$88,12,(Inputs!$G$88-H$1*12)),0)*Inputs!$B$90 -> 0 | J26: =MAX(IF(J$1*12<=Inputs!$G$88,12,(Inputs!$G$88-I$1*12)),0)*Inputs!$B$90 -> 0 | ... AM26: =MAX(IF(AM$1*12<=Inputs!$G$88,12,(Inputs!$G$88-AL$1*12)),0)*Inputs!$B$90 -> 0
A27: Other loan repayment | C27: =MAX(IF(C$1*12<=Inputs!$G$93,12,(Inputs!$G$93-B$1*12)),0)*Inputs!$B$95 -> 600 | D27: =MAX(IF(D$1*12<=Inputs!$G$93,12,(Inputs!$G$93-C$1*12)),0)*Inputs!$B$95 -> 600 | E27: =MAX(IF(E$1*12<=Inputs!$G$93,12,(Inputs!$G$93-D$1*12)),0)*Inputs!$B$95 -> 600 | F27: =MAX(IF(F$1*12<=Inputs!$G$93,12,(Inputs!$G$93-E$1*12)),0)*Inputs!$B$95 -> 600 | G27: =MAX(IF(G$1*12<=Inputs!$G$93,12,(Inputs!$G$93-F$1*12)),0)*Inputs!$B$95 -> 600 | H27: =MAX(IF(H$1*12<=Inputs!$G$93,12,(Inputs!$G$93-G$1*12)),0)*Inputs!$B$95 -> 600 | I27: =MAX(IF(I$1*12<=Inputs!$G$93,12,(Inputs!$G$93-H$1*12)),0)*Inputs!$B$95 -> 600 | J27: =MAX(IF(J$1*12<=Inputs!$G$93,12,(Inputs!$G$93-I$1*12)),0)*Inputs!$B$95 -> 600 | ... AM27: =MAX(IF(AM$1*12<=Inputs!$G$93,12,(Inputs!$G$93-AL$1*12)),0)*Inputs!$B$95 -> 0
A28: Dependents cost
A29: =TEXT(Inputs!B33,"") -> John | C29: =IF(Inputs!$B$35>=C$1,Inputs!$B$34,0)*(1+inf)^B$1 -> 2000 | D29: =IF(Inputs!$B$35>=D$1,Inputs!$B$34,0)*(1+inf)^C$1 -> 2050 | E29: =IF(Inputs!$B$35>=E$1,Inputs!$B$34,0)*(1+inf)^D$1 -> 2101.25 | F29: =IF(Inputs!$B$35>=F$1,Inputs!$B$34,0)*(1+inf)^E$1 -> 0 | G29: =IF(Inputs!$B$35>=G$1,Inputs!$B$34,0)*(1+inf)^F$1 -> 0 | H29: =IF(Inputs!$B$35>=H$1,Inputs!$B$34,0)*(1+inf)^G$1 -> 0 | I29: =IF(Inputs!$B$35>=I$1,Inputs!$B$34,0)*(1+inf)^H$1 -> 0 | J29: =IF(Inputs!$B$35>=J$1,Inputs!$B$34,0)*(1+inf)^I$1 -> 0 | ... AM29: =IF(Inputs!$B$35>=AM$1,Inputs!$B$34,0)*(1+inf)^AL$1 -> 0
A30: =TEXT(Inputs!B38,"") -> Jack | C30: =IF(Inputs!$B$40>=C$1,Inputs!$B$39,0)*(1+inf)^B$1 -> 1000 | D30: =IF(Inputs!$B$40>=D$1,Inputs!$B$39,0)*(1+inf)^C$1 -> 1025 | E30: =IF(Inputs!$B$40>=E$1,Inputs!$B$39,0)*(1+inf)^D$1 -> 1050.625 | F30: =IF(Inputs!$B$40>=F$1,Inputs!$B$39,0)*(1+inf)^E$1 -> 1076.8906 | G30: =IF(Inputs!$B$40>=G$1,Inputs!$B$39,0)*(1+inf)^F$1 -> 1103.8129 | H30: =IF(Inputs!$B$40>=H$1,Inputs!$B$39,0)*(1+inf)^G$1 -> 0 | I30: =IF(Inputs!$B$40>=I$1,Inputs!$B$39,0)*(1+inf)^H$1 -> 0 | J30: =IF(Inputs!$B$40>=J$1,Inputs!$B$39,0)*(1+inf)^I$1 -> 0 | ... AM30: =IF(Inputs!$B$40>=AM$1,Inputs!$B$39,0)*(1+inf)^AL$1 -> 0
A31: =TEXT(Inputs!B43,"") -> Bill | C31: =IF(Inputs!$B$45>=C$1,Inputs!$B$44,0)*(1+inf)^B$1 -> 4000 | D31: =IF(Inputs!$B$45>=D$1,Inputs!$B$44,0)*(1+inf)^C$1 -> 4100 | E31: =IF(Inputs!$B$45>=E$1,Inputs!$B$44,0)*(1+inf)^D$1 -> 0 | F31: =IF(Inputs!$B$45>=F$1,Inputs!$B$44,0)*(1+inf)^E$1 -> 0 | G31: =IF(Inputs!$B$45>=G$1,Inputs!$B$44,0)*(1+inf)^F$1 -> 0 | H31: =IF(Inputs!$B$45>=H$1,Inputs!$B$44,0)*(1+inf)^G$1 -> 0 | I31: =IF(Inputs!$B$45>=I$1,Inputs!$B$44,0)*(1+inf)^H$1 -> 0 | J31: =IF(Inputs!$B$45>=J$1,Inputs!$B$44,0)*(1+inf)^I$1 -> 0 | ... AM31: =IF(Inputs!$B$45>=AM$1,Inputs!$B$44,0)*(1+inf)^AL$1 -> 0
A32: Housing rent | C32: =Inputs!$B$23*(1+inf)^B$1 -> 0 | D32: =Inputs!$B$23*(1+inf)^C$1 -> 0 | E32: =Inputs!$B$23*(1+inf)^D$1 -> 0 | F32: =Inputs!$B$23*(1+inf)^E$1 -> 0 | G32: =Inputs!$B$23*(1+inf)^F$1 -> 0 | H32: =Inputs!$B$23*(1+inf)^G$1 -> 0 | I32: =Inputs!$B$23*(1+inf)^H$1 -> 0 | J32: =Inputs!$B$23*(1+inf)^I$1 -> 0 | ... AM32: =Inputs!$B$23*(1+inf)^AL$1 -> 0
A33: Other property costs
A34: =TEXT(Inputs!$B$50,"") -> Sliema | C34: =Inputs!$B52*(1+inf)^B$1 -> 5000 | D34: =Inputs!$B52*(1+inf)^C$1 -> 5125 | E34: =Inputs!$B52*(1+inf)^D$1 -> 5253.125 | F34: =Inputs!$B52*(1+inf)^E$1 -> 5384.4531 | G34: =Inputs!$B52*(1+inf)^F$1 -> 5519.0645 | H34: =Inputs!$B52*(1+inf)^G$1 -> 5657.0411 | I34: =Inputs!$B52*(1+inf)^H$1 -> 5798.4671 | J34: =Inputs!$B52*(1+inf)^I$1 -> 5943.4288 | ... AM34: =Inputs!$B52*(1+inf)^AL$1 -> 12162.677
A35: =TEXT(Inputs!$B$55,"") -> Gzira | C35: =Inputs!$B57*(1+inf)^B$1 -> 2000 | D35: =Inputs!$B57*(1+inf)^C$1 -> 2050 | E35: =Inputs!$B57*(1+inf)^D$1 -> 2101.25 | F35: =Inputs!$B57*(1+inf)^E$1 -> 2153.7812 | G35: =Inputs!$B57*(1+inf)^F$1 -> 2207.6258 | H35: =Inputs!$B57*(1+inf)^G$1 -> 2262.8164 | I35: =Inputs!$B57*(1+inf)^H$1 -> 2319.3868 | J35: =Inputs!$B57*(1+inf)^I$1 -> 2377.3715 | ... AM35: =Inputs!$B57*(1+inf)^AL$1 -> 4865.0706
A36: =TEXT(Inputs!$B$60,"") -> Qormi | C36: =Inputs!$B62*(1+inf)^B$1 -> 1200 | D36: =Inputs!$B62*(1+inf)^C$1 -> 1230 | E36: =Inputs!$B62*(1+inf)^D$1 -> 1260.75 | F36: =Inputs!$B62*(1+inf)^E$1 -> 1292.2687 | G36: =Inputs!$B62*(1+inf)^F$1 -> 1324.5755 | H36: =Inputs!$B62*(1+inf)^G$1 -> 1357.6899 | I36: =Inputs!$B62*(1+inf)^H$1 -> 1391.6321 | J36: =Inputs!$B62*(1+inf)^I$1 -> 1426.4229 | ... AM36: =Inputs!$B62*(1+inf)^AL$1 -> 2919.0424
A37: Living expenses
A38: Current baseline | C38: =Inputs!$B$25*(1+inf)^B$1 -> 50000 | D38: =Inputs!$B$25*(1+inf)^C$1 -> 51250 | E38: =Inputs!$B$25*(1+inf)^D$1 -> 52531.25 | F38: =Inputs!$B$25*(1+inf)^E$1 -> 53844.531 | G38: =Inputs!$B$25*(1+inf)^F$1 -> 55190.645 | H38: =Inputs!$B$25*(1+inf)^G$1 -> 56570.411 | I38: =Inputs!$B$25*(1+inf)^H$1 -> 57984.671 | J38: =Inputs!$B$25*(1+inf)^I$1 -> 59434.288 | ... AM38: =Inputs!$B$25*(1+inf)^AL$1 -> 121626.77
A39: ="Adjustment "&Inputs!A137 -> Adjustment from now to 65 | C39: =IF(C$3<=65,Inputs!$B$137*C$38,0) -> 0 | D39: =IF(D$3<=65,Inputs!$B$137*D$38,0) -> 0 | E39: =IF(E$3<=65,Inputs!$B$137*E$38,0) -> 0 | F39: =IF(F$3<=65,Inputs!$B$137*F$38,0) -> 0 | G39: =IF(G$3<=65,Inputs!$B$137*G$38,0) -> 0 | H39: =IF(H$3<=65,Inputs!$B$137*H$38,0) -> 0 | I39: =IF(I$3<=65,Inputs!$B$137*I$38,0) -> 0 | J39: =IF(J$3<=65,Inputs!$B$137*J$38,0) -> 0 | ... AM39: =IF(AM$3<=65,Inputs!$B$137*AM$38,0) -> 0
A40: ="Adjustment "&Inputs!A138 -> Adjustment from 66-75 | C40: =IF(AND(C$3>65,C$3<=75),Inputs!$B$138*C38,0) -> 0 | D40: =IF(AND(D$3>65,D$3<=75),Inputs!$B$138*D38,0) -> 0 | E40: =IF(AND(E$3>65,E$3<=75),Inputs!$B$138*E38,0) -> 0 | F40: =IF(AND(F$3>65,F$3<=75),Inputs!$B$138*F38,0) -> 0 | G40: =IF(AND(G$3>65,G$3<=75),Inputs!$B$138*G38,0) -> 0 | H40: =IF(AND(H$3>65,H$3<=75),Inputs!$B$138*H38,0) -> 0 | I40: =IF(AND(I$3>65,I$3<=75),Inputs!$B$138*I38,0) -> 0 | J40: =IF(AND(J$3>65,J$3<=75),Inputs!$B$138*J38,0) -> 0 | ... AM40: =IF(AND(AM$3>65,AM$3<=75),Inputs!$B$138*AM38,0) -> 0
A41: ="Adjustment "&Inputs!A139 -> Adjustment from age 76 | C41: =IF(C$3>75,Inputs!$B$139*C$38,0) -> 0 | D41: =IF(D$3>75,Inputs!$B$139*D$38,0) -> 0 | E41: =IF(E$3>75,Inputs!$B$139*E$38,0) -> 0 | F41: =IF(F$3>75,Inputs!$B$139*F$38,0) -> 0 | G41: =IF(G$3>75,Inputs!$B$139*G$38,0) -> 0 | H41: =IF(H$3>75,Inputs!$B$139*H$38,0) -> 0 | I41: =IF(I$3>75,Inputs!$B$139*I$38,0) -> 0 | J41: =IF(J$3>75,Inputs!$B$139*J$38,0) -> 0 | ... AM41: =IF(AM$3>75,Inputs!$B$139*AM$38,0) -> -24325.353
A42: Major one-off expense events
A43: =TEXT(Inputs!$B$117,"") -> Wedding | C43: =IF(C$2=Inputs!$B119,Inputs!$B118,0)*(1+inf)^B$1 -> 0 | D43: =IF(D$2=Inputs!$B119,Inputs!$B118,0)*(1+inf)^C$1 -> 0 | E43: =IF(E$2=Inputs!$B119,Inputs!$B118,0)*(1+inf)^D$1 -> 0 | F43: =IF(F$2=Inputs!$B119,Inputs!$B118,0)*(1+inf)^E$1 -> 0 | G43: =IF(G$2=Inputs!$B119,Inputs!$B118,0)*(1+inf)^F$1 -> 0 | H43: =IF(H$2=Inputs!$B119,Inputs!$B118,0)*(1+inf)^G$1 -> 0 | I43: =IF(I$2=Inputs!$B119,Inputs!$B118,0)*(1+inf)^H$1 -> 0 | J43: =IF(J$2=Inputs!$B119,Inputs!$B118,0)*(1+inf)^I$1 -> 0 | ... AM43: =IF(AM$2=Inputs!$B119,Inputs!$B118,0)*(1+inf)^AL$1 -> 0
A44: =TEXT(Inputs!$B$122,"") -> New Car | C44: =IF(C$2=Inputs!$B124,Inputs!$B123,0)*(1+inf)^B$1 -> 0 | D44: =IF(D$2=Inputs!$B124,Inputs!$B123,0)*(1+inf)^C$1 -> 0 | E44: =IF(E$2=Inputs!$B124,Inputs!$B123,0)*(1+inf)^D$1 -> 36771.875 | F44: =IF(F$2=Inputs!$B124,Inputs!$B123,0)*(1+inf)^E$1 -> 0 | G44: =IF(G$2=Inputs!$B124,Inputs!$B123,0)*(1+inf)^F$1 -> 0 | H44: =IF(H$2=Inputs!$B124,Inputs!$B123,0)*(1+inf)^G$1 -> 0 | I44: =IF(I$2=Inputs!$B124,Inputs!$B123,0)*(1+inf)^H$1 -> 0 | J44: =IF(J$2=Inputs!$B124,Inputs!$B123,0)*(1+inf)^I$1 -> 0 | ... AM44: =IF(AM$2=Inputs!$B124,Inputs!$B123,0)*(1+inf)^AL$1 -> 0
A45: =TEXT(Inputs!$B$127,"") -> New AC | C45: =IF(C$2=Inputs!$B129,Inputs!$B128,0)*(1+inf)^B$1 -> 0 | D45: =IF(D$2=Inputs!$B129,Inputs!$B128,0)*(1+inf)^C$1 -> 0 | E45: =IF(E$2=Inputs!$B129,Inputs!$B128,0)*(1+inf)^D$1 -> 0 | F45: =IF(F$2=Inputs!$B129,Inputs!$B128,0)*(1+inf)^E$1 -> 0 | G45: =IF(G$2=Inputs!$B129,Inputs!$B128,0)*(1+inf)^F$1 -> 0 | H45: =IF(H$2=Inputs!$B129,Inputs!$B128,0)*(1+inf)^G$1 -> 0 | I45: =IF(I$2=Inputs!$B129,Inputs!$B128,0)*(1+inf)^H$1 -> 0 | J45: =IF(J$2=Inputs!$B129,Inputs!$B128,0)*(1+inf)^I$1 -> 17830.286 | ... AM45: =IF(AM$2=Inputs!$B129,Inputs!$B128,0)*(1+inf)^AL$1 -> 0
C46: =SUM(C20:C45) -> 87800 | D46: =SUM(D20:D45) -> 88430 | E46: =SUM(E20:E45) -> 122670.12 | F46: =SUM(F20:F45) -> 84575.328 | G46: =SUM(G20:G45) -> 84545.723 | H46: =SUM(H20:H45) -> 81180.441 | I46: =SUM(I20:I45) -> 74094.157 | J46: =SUM(J20:J45) -> 93611.797 | ... AM46: =SUM(AM20:AM45) -> 117248.2
A48: Net Cash Flow | C48: =C19-C46 -> 25752.5 | D48: =D19-D46 -> 29150.312 | E48: =E19-E46 -> 9341.9 | F48: =F19-F46 -> 41106.771 | G48: =G19-G46 -> 45870.007 | H48: =H19-H46 -> 59968.347 | I48: =I19-I46 -> -29872.87 | J48: =J19-J46 -> -49234.513 | ... AM48: =AM19-AM46 -> 1638.641
A49: Cash b/fwd | C49: =Inputs!B8 -> 50000 | D49: =C50 -> 75752.5 | E49: =D50 -> 104902.81 | F49: =E50 -> 114244.71 | G49: =F50 -> 155351.48 | H49: =G50 -> 201221.49 | I49: =H50 -> 261189.84 | J49: =I50 -> 231316.97 | K49: =J50 -> 182082.45 | ... AM49: =AL50 -> 11959.816
A50: Cash c/fwd | C50: =SUM(C48:C49) -> 75752.5 | D50: =SUM(D48:D49) -> 104902.81 | E50: =SUM(E48:E49) -> 114244.71 | F50: =SUM(F48:F49) -> 155351.48 | G50: =SUM(G48:G49) -> 201221.49 | H50: =SUM(H48:H49) -> 261189.84 | I50: =SUM(I48:I49) -> 231316.97 | J50: =SUM(J48:J49) -> 182082.45 | ... AM50: =SUM(AM48:AM49) -> 13598.457
A52: Net Worth before liquidations
A53: Cash | C53: =C50 -> 75752.5 | D53: =D50 -> 104902.81 | E53: =E50 -> 114244.71 | F53: =F50 -> 155351.48 | G53: =G50 -> 201221.49 | H53: =H50 -> 261189.84 | I53: =I50 -> 231316.97 | J53: =J50 -> 182082.45 | ... AM53: =AM50 -> 13598.457
A54: Home | C54: =Inputs!B12*(1+princ) -> 618000 | D54: =C54*(1+princ) -> 636540 | E54: =D54*(1+princ) -> 655636.2 | F54: =E54*(1+princ) -> 675305.29 | G54: =F54*(1+princ) -> 695564.44 | H54: =G54*(1+princ) -> 716431.38 | I54: =H54*(1+princ) -> 737924.32 | J54: =I54*(1+princ) -> 760062.05 | K54: =J54*(1+princ) -> 782863.91 | ... AM54: =AL54*(1+princ) -> 1791136
A55: Other property
A56: =TEXT(Inputs!$B$50,"") -> Sliema | C56: =Inputs!B51*(1+princ) -> 309000 | D56: =C56*(1+princ) -> 318270 | E56: =D56*(1+princ) -> 327818.1 | F56: =E56*(1+princ) -> 337652.64 | G56: =F56*(1+princ) -> 347782.22 | H56: =G56*(1+princ) -> 358215.69 | I56: =H56*(1+princ) -> 368962.16 | J56: =I56*(1+princ) -> 380031.02 | K56: =J56*(1+princ) -> 391431.96 | ... AM56: =AL56*(1+princ) -> 895568
A57: =TEXT(Inputs!$B$55,"") -> Gzira | C57: =Inputs!B56*(1+princ) -> 154500 | D57: =C57*(1+princ) -> 159135 | E57: =D57*(1+princ) -> 163909.05 | F57: =E57*(1+princ) -> 168826.32 | G57: =F57*(1+princ) -> 173891.11 | H57: =G57*(1+princ) -> 179107.84 | I57: =H57*(1+princ) -> 184481.08 | J57: =I57*(1+princ) -> 190015.51 | K57: =J57*(1+princ) -> 195715.98 | ... AM57: =AL57*(1+princ) -> 447784
A58: =TEXT(Inputs!$B$60,"") -> Qormi | C58: =Inputs!B61*(1+princ) -> 226600 | D58: =C58*(1+princ) -> 233398 | E58: =D58*(1+princ) -> 240399.94 | F58: =E58*(1+princ) -> 247611.94 | G58: =F58*(1+princ) -> 255040.3 | H58: =G58*(1+princ) -> 262691.51 | I58: =H58*(1+princ) -> 270572.25 | J58: =I58*(1+princ) -> 278689.42 | K58: =J58*(1+princ) -> 287050.1 | ... AM58: =AL58*(1+princ) -> 656749.87
A59: Stock market equity investments | C59: =Inputs!B10*(1+stinc) -> 32400 | D59: =C59*(1+stinc) -> 34992 | E59: =D59*(1+stinc) -> 37791.36 | F59: =E59*(1+stinc) -> 40814.669 | G59: =F59*(1+stinc) -> 44079.842 | H59: =G59*(1+stinc) -> 47606.23 | I59: =H59*(1+stinc) -> 51414.728 | J59: =I59*(1+stinc) -> 55527.906 | K59: =J59*(1+stinc) -> 59970.139 | ... AM59: =AL59*(1+stinc) -> 517368.77
A60: Home loan | C60: =-MAX(FV(Inputs!$B16/12,C$1*12,Inputs!$B17,-Inputs!$B15),0) -> -41787.692 | D60: =-MAX(FV(Inputs!$B16/12,D$1*12,Inputs!$B17,-Inputs!$B15),0) -> -33325.598 | E60: =-MAX(FV(Inputs!$B16/12,E$1*12,Inputs!$B17,-Inputs!$B15),0) -> -24606.122 | F60: =-MAX(FV(Inputs!$B16/12,F$1*12,Inputs!$B17,-Inputs!$B15),0) -> -15621.434 | G60: =-MAX(FV(Inputs!$B16/12,G$1*12,Inputs!$B17,-Inputs!$B15),0) -> -6363.469 | H60: =-MAX(FV(Inputs!$B16/12,H$1*12,Inputs!$B17,-Inputs!$B15),0) -> 0 | I60: =-MAX(FV(Inputs!$B16/12,I$1*12,Inputs!$B17,-Inputs!$B15),0) -> 0 | J60: =-MAX(FV(Inputs!$B16/12,J$1*12,Inputs!$B17,-Inputs!$B15),0) -> 0 | ... AM60: =-MAX(FV(Inputs!$B16/12,AM$1*12,Inputs!$B17,-Inputs!$B15),0) -> 0
A61: Other property loans
A62: =TEXT(Inputs!$B$50,"") -> Sliema | C62: =-MAX(FV(Inputs!$B79/12,C$1*12,Inputs!$B80,-Inputs!$B78),0) -> -45437.606 | D62: =-MAX(FV(Inputs!$B79/12,D$1*12,Inputs!$B80,-Inputs!$B78),0) -> -40736.443 | E62: =-MAX(FV(Inputs!$B79/12,E$1*12,Inputs!$B80,-Inputs!$B78),0) -> -35892.29 | F62: =-MAX(FV(Inputs!$B79/12,F$1*12,Inputs!$B80,-Inputs!$B78),0) -> -30900.797 | G62: =-MAX(FV(Inputs!$B79/12,G$1*12,Inputs!$B80,-Inputs!$B78),0) -> -25757.483 | H62: =-MAX(FV(Inputs!$B79/12,H$1*12,Inputs!$B80,-Inputs!$B78),0) -> -20457.73 | I62: =-MAX(FV(Inputs!$B79/12,I$1*12,Inputs!$B80,-Inputs!$B78),0) -> -14996.78 | J62: =-MAX(FV(Inputs!$B79/12,J$1*12,Inputs!$B80,-Inputs!$B78),0) -> -9369.7299 | ... AM62: =-MAX(FV(Inputs!$B79/12,AM$1*12,Inputs!$B80,-Inputs!$B78),0) -> 0
A63: =TEXT(Inputs!$B$55,"") -> Gzira | C63: =-MAX(FV(Inputs!$B84/12,C$1*12,Inputs!$B85,-Inputs!$B83),0) -> -6249.4443 | D63: =-MAX(FV(Inputs!$B84/12,D$1*12,Inputs!$B85,-Inputs!$B83),0) -> -3953.4627 | E63: =-MAX(FV(Inputs!$B84/12,E$1*12,Inputs!$B85,-Inputs!$B83),0) -> -1611.1381 | F63: =-MAX(FV(Inputs!$B84/12,F$1*12,Inputs!$B85,-Inputs!$B83),0) -> 0 | G63: =-MAX(FV(Inputs!$B84/12,G$1*12,Inputs!$B85,-Inputs!$B83),0) -> 0 | H63: =-MAX(FV(Inputs!$B84/12,H$1*12,Inputs!$B85,-Inputs!$B83),0) -> 0 | I63: =-MAX(FV(Inputs!$B84/12,I$1*12,Inputs!$B85,-Inputs!$B83),0) -> 0 | J63: =-MAX(FV(Inputs!$B84/12,J$1*12,Inputs!$B85,-Inputs!$B83),0) -> 0 | ... AM63: =-MAX(FV(Inputs!$B84/12,AM$1*12,Inputs!$B85,-Inputs!$B83),0) -> 0
A64: =TEXT(Inputs!$B$60,"") -> Qormi | C64: =-MAX(FV(Inputs!$B89/12,C$1*12,Inputs!$B90,-Inputs!$B88),0) -> -12697.715 | D64: =-MAX(FV(Inputs!$B89/12,D$1*12,Inputs!$B90,-Inputs!$B88),0) -> -10277.64 | E64: =-MAX(FV(Inputs!$B89/12,E$1*12,Inputs!$B90,-Inputs!$B88),0) -> -7733.7496 | F64: =-MAX(FV(Inputs!$B89/12,F$1*12,Inputs!$B90,-Inputs!$B88),0) -> -5059.709 | G64: =-MAX(FV(Inputs!$B89/12,G$1*12,Inputs!$B90,-Inputs!$B88),0) -> -2248.8595 | H64: =-MAX(FV(Inputs!$B89/12,H$1*12,Inputs!$B90,-Inputs!$B88),0) -> 0 | I64: =-MAX(FV(Inputs!$B89/12,I$1*12,Inputs!$B90,-Inputs!$B88),0) -> 0 | J64: =-MAX(FV(Inputs!$B89/12,J$1*12,Inputs!$B90,-Inputs!$B88),0) -> 0 | ... AM64: =-MAX(FV(Inputs!$B89/12,AM$1*12,Inputs!$B90,-Inputs!$B88),0) -> 0
A65: Other loan | C65: =-MAX(FV(Inputs!$B94/12,C$1*12,Inputs!$B95,-Inputs!$B93),0) -> -3629.9331 | D65: =-MAX(FV(Inputs!$B94/12,D$1*12,Inputs!$B95,-Inputs!$B93),0) -> -3237.0413 | E65: =-MAX(FV(Inputs!$B94/12,E$1*12,Inputs!$B95,-Inputs!$B93),0) -> -2819.9169 | F65: =-MAX(FV(Inputs!$B94/12,F$1*12,Inputs!$B95,-Inputs!$B93),0) -> -2377.065 | G65: =-MAX(FV(Inputs!$B94/12,G$1*12,Inputs!$B95,-Inputs!$B93),0) -> -1906.8991 | H65: =-MAX(FV(Inputs!$B94/12,H$1*12,Inputs!$B95,-Inputs!$B93),0) -> -1407.7343 | I65: =-MAX(FV(Inputs!$B94/12,I$1*12,Inputs!$B95,-Inputs!$B93),0) -> -877.78218 | J65: =-MAX(FV(Inputs!$B94/12,J$1*12,Inputs!$B95,-Inputs!$B93),0) -> -315.14375 | ... AM65: =-MAX(FV(Inputs!$B94/12,AM$1*12,Inputs!$B95,-Inputs!$B93),0) -> 0
C66: =SUM(C52:C65) -> 1306450.1 | D66: =SUM(D52:D65) -> 1395707.6 | E66: =SUM(E52:E65) -> 1467136.1 | F66: =SUM(F52:F65) -> 1571603.3 | G66: =SUM(G52:G65) -> 1681302.7 | H66: =SUM(H52:H65) -> 1803377 | I66: =SUM(I52:I65) -> 1828796.9 | J66: =SUM(J52:J65) -> 1836723.5 | ... AM66: =SUM(AM52:AM65) -> 4322205.1
A68: Cash available (after buffer) | C68: =C53-buffer -> 35752.5 | D68: =D53-buffer -> 64902.812 | E68: =E53-buffer -> 74244.712 | F68: =F53-buffer -> 115351.48 | G68: =G53-buffer -> 161221.49 | H68: =H53-buffer -> 221189.84 | I68: =I53-buffer -> 191316.97 | J68: =J53-buffer -> 142082.45 | ... AM68: =AM53-buffer -> -26401.543
A69: Liquidation required | C69: =IF(C68<0,-C68,0) -> 0 | D69: =IF(D68+SUM($C69:C69)<0,-(D68+SUM($C69:C69)),0) -> 0 | E69: =IF(E68+SUM($C69:D69)<0,-(E68+SUM($C69:D69)),0) -> 0 | F69: =IF(F68+SUM($C69:E69)<0,-(F68+SUM($C69:E69)),0) -> 0 | G69: =IF(G68+SUM($C69:F69)<0,-(G68+SUM($C69:F69)),0) -> 0 | H69: =IF(H68+SUM($C69:G69)<0,-(H68+SUM($C69:G69)),0) -> 0 | I69: =IF(I68+SUM($C69:H69)<0,-(I68+SUM($C69:H69)),0) -> 0 | J69: =IF(J68+SUM($C69:I69)<0,-(J68+SUM($C69:I69)),0) -> 0 | K69: =IF(K68+SUM($C69:J69)<0,-(K68+SUM($C69:J69)),0) -> 0 | ... AM69: =IF(AM68+SUM($C69:AL69)<0,-(AM68+SUM($C69:AL69)),0) -> 0
A71: Liquidations
A73: Stock market equity
A74: b/fwd | C74: =C59 -> 32400 | D74: =C77 -> 32400 | E74: =D77 -> 34992 | F74: =E77 -> 37791.36 | G74: =F77 -> 40814.669 | H74: =G77 -> 44079.842 | I74: =H77 -> 47606.23 | J74: =I77 -> 51414.728 | K74: =J77 -> 55527.906 | ... AM74: =AL77 -> 409304.55
A75: Disposals | C75: =-MIN( IF(C74>C69/ (1 - Inputs!$B$161), C69/ (1 - Inputs!$B$161), C74), C74/ (1 - Inputs!$B$161) ) -> 0 | D75: =-MIN( IF(D74>D69/ (1 - Inputs!$B$161), D69/ (1 - Inputs!$B$161), D74), D74/ (1 - Inputs!$B$161) ) -> 0 | E75: =-MIN( IF(E74>E69/ (1 - Inputs!$B$161), E69/ (1 - Inputs!$B$161), E74), E74/ (1 - Inputs!$B$161) ) -> 0 | F75: =-MIN( IF(F74>F69/ (1 - Inputs!$B$161), F69/ (1 - Inputs!$B$161), F74), F74/ (1 - Inputs!$B$161) ) -> 0 | G75: =-MIN( IF(G74>G69/ (1 - Inputs!$B$161), G69/ (1 - Inputs!$B$161), G74), G74/ (1 - Inputs!$B$161) ) -> 0 | H75: =-MIN( IF(H74>H69/ (1 - Inputs!$B$161), H69/ (1 - Inputs!$B$161), H74), H74/ (1 - Inputs!$B$161) ) -> 0 | I75: =-MIN( IF(I74>I69/ (1 - Inputs!$B$161), I69/ (1 - Inputs!$B$161), I74), I74/ (1 - Inputs!$B$161) ) -> 0 | J75: =-MIN( IF(J74>J69/ (1 - Inputs!$B$161), J69/ (1 - Inputs!$B$161), J74), J74/ (1 - Inputs!$B$161) ) -> 0 | ... AM75: =-MIN( IF(AM74>AM69/ (1 - Inputs!$B$161), AM69/ (1 - Inputs!$B$161), AM74), AM74/ (1 - Inputs!$B$161) ) -> 0
A76: Growth | C76: 0 | D76: =SUM(D74:D75)*stinc -> 2592 | E76: =SUM(E74:E75)*stinc -> 2799.36 | F76: =SUM(F74:F75)*stinc -> 3023.3088 | G76: =SUM(G74:G75)*stinc -> 3265.1735 | H76: =SUM(H74:H75)*stinc -> 3526.3874 | I76: =SUM(I74:I75)*stinc -> 3808.4984 | J76: =SUM(J74:J75)*stinc -> 4113.1782 | K76: =SUM(K74:K75)*stinc -> 4442.2325 | ... AM76: =SUM(AM74:AM75)*stinc -> 32744.364
A77: c/fwd | C77: =SUM(C74:C76) -> 32400 | D77: =SUM(D74:D76) -> 34992 | E77: =SUM(E74:E76) -> 37791.36 | F77: =SUM(F74:F76) -> 40814.669 | G77: =SUM(G74:G76) -> 44079.842 | H77: =SUM(H74:H76) -> 47606.23 | I77: =SUM(I74:I76) -> 51414.728 | J77: =SUM(J74:J76) -> 55527.906 | ... AM77: =SUM(AM74:AM76) -> 442048.91
A78: Disposal costs | C78: =C75*Inputs!$B$161 -> 0 | D78: =D75*Inputs!$B$161 -> 0 | E78: =E75*Inputs!$B$161 -> 0 | F78: =F75*Inputs!$B$161 -> 0 | G78: =G75*Inputs!$B$161 -> 0 | H78: =H75*Inputs!$B$161 -> 0 | I78: =I75*Inputs!$B$161 -> 0 | J78: =J75*Inputs!$B$161 -> 0 | ... AM78: =AM75*Inputs!$B$161 -> 0
A79: Net proceeds | C79: =-C75+C78 -> 0 | D79: =-D75+D78 -> 0 | E79: =-E75+E78 -> 0 | F79: =-F75+F78 -> 0 | G79: =-G75+G78 -> 0 | H79: =-H75+H78 -> 0 | I79: =-I75+I78 -> 0 | J79: =-J75+J78 -> 0 | ... AM79: =-AM75+AM78 -> 0
A81: Cash available (after buffer) | C81: =C68+SUM($C79:C79) -> 35752.5 | D81: =D68+SUM($C79:D79) -> 64902.812 | E81: =E68+SUM($C79:E79) -> 74244.712 | F81: =F68+SUM($C79:F79) -> 115351.48 | G81: =G68+SUM($C79:G79) -> 161221.49 | H81: =H68+SUM($C79:H79) -> 221189.84 | I81: =I68+SUM($C79:I79) -> 191316.97 | J81: =J68+SUM($C79:J79) -> 142082.45 | ... AM81: =AM68+SUM($C79:AM79) -> 3818.0686
A82: Liquidation required | C82: =IF(C81<0,C81,0) -> 0 | D82: =IF(D81+SUM($C82:C82)<0,-(D81+SUM($C82:C82)),0) -> 0 | E82: =IF(E81+SUM($C82:D82)<0,-(E81+SUM($C82:D82)),0) -> 0 | F82: =IF(F81+SUM($C82:E82)<0,-(F81+SUM($C82:E82)),0) -> 0 | G82: =IF(G81+SUM($C82:F82)<0,-(G81+SUM($C82:F82)),0) -> 0 | H82: =IF(H81+SUM($C82:G82)<0,-(H81+SUM($C82:G82)),0) -> 0 | I82: =IF(I81+SUM($C82:H82)<0,-(I81+SUM($C82:H82)),0) -> 0 | J82: =IF(J81+SUM($C82:I82)<0,-(J81+SUM($C82:I82)),0) -> 0 | K82: =IF(K81+SUM($C82:J82)<0,-(K81+SUM($C82:J82)),0) -> 0 | ... AM82: =IF(AM81+SUM($C82:AL82)<0,-(AM81+SUM($C82:AL82)),0) -> 0
A84: =IF(Inputs!$B$165=6,IFERROR(_xlfn.XLOOKUP($B84,Inputs!$B$166:$B$168,Inputs!$A$166:$A$168,,0,1),""),IFERROR(_xlfn.XLOOKUP($B84,Inputs!$C$166:$C$168,Inputs!$A$166:$A$168,,0,1),"")) -> Gzira | B84: 1
A85: b/fwd | C85: =IFERROR(VLOOKUP($A84,$A$52:$H$66,C$1+2,FALSE),0) -> 154500 | D85: =C88 -> 154500 | E85: =D88 -> 159135 | F85: =E88 -> 163909.05 | G85: =F88 -> 168826.32 | H85: =G88 -> 173891.11 | I85: =H88 -> 179107.84 | J85: =I88 -> 184481.08 | K85: =J88 -> 190015.51 | ... AM85: =AL88 -> 434741.75
A86: Disposals | C86: =-IF(SUM(C82:D82)>0,C85,0) -> 0 | D86: =-IF(E82>0,D85,0) -> 0 | E86: =-IF(F82>0,E85,0) -> 0 | F86: =-IF(G82>0,F85,0) -> 0 | G86: =-IF(H82>0,G85,0) -> 0 | H86: =-IF(I82>0,H85,0) -> 0 | I86: =-IF(J82>0,I85,0) -> 0 | J86: =-IF(K82>0,J85,0) -> 0 | K86: =-IF(L82>0,K85,0) -> 0 | ... AM86: =-IF(AN82>0,AM85,0) -> 0
A87: Growth | C87: 0 | D87: =SUM(D85:D86)*princ -> 4635 | E87: =SUM(E85:E86)*princ -> 4774.05 | F87: =SUM(F85:F86)*princ -> 4917.2715 | G87: =SUM(G85:G86)*princ -> 5064.7896 | H87: =SUM(H85:H86)*princ -> 5216.7333 | I87: =SUM(I85:I86)*princ -> 5373.2353 | J87: =SUM(J85:J86)*princ -> 5534.4324 | K87: =SUM(K85:K86)*princ -> 5700.4654 | ... AM87: =SUM(AM85:AM86)*princ -> 13042.252
A88: c/fwd | C88: =SUM(C85:C87) -> 154500 | D88: =SUM(D85:D87) -> 159135 | E88: =SUM(E85:E87) -> 163909.05 | F88: =SUM(F85:F87) -> 168826.32 | G88: =SUM(G85:G87) -> 173891.11 | H88: =SUM(H85:H87) -> 179107.84 | I88: =SUM(I85:I87) -> 184481.08 | J88: =SUM(J85:J87) -> 190015.51 | ... AM88: =SUM(AM85:AM87) -> 447784
A89: Disposal costs | C89: =C86*Inputs!$B$163 -> 0 | D89: =D86*Inputs!$B$163 -> 0 | E89: =E86*Inputs!$B$163 -> 0 | F89: =F86*Inputs!$B$163 -> 0 | G89: =G86*Inputs!$B$163 -> 0 | H89: =H86*Inputs!$B$163 -> 0 | I89: =I86*Inputs!$B$163 -> 0 | J89: =J86*Inputs!$B$163 -> 0 | ... AM89: =AM86*Inputs!$B$163 -> 0
A90: Rental income foregone | C90: =IFERROR(-IF(C85=0,VLOOKUP($A84,$7:$10,C$1+2,FALSE),0),0) -> 0 | D90: =IFERROR(-IF(D85=0,VLOOKUP($A84,$7:$10,D$1+2,FALSE),0),0) -> 0 | E90: =IFERROR(-IF(E85=0,VLOOKUP($A84,$7:$10,E$1+2,FALSE),0),0) -> 0 | F90: =IFERROR(-IF(F85=0,VLOOKUP($A84,$7:$10,F$1+2,FALSE),0),0) -> 0 | G90: =IFERROR(-IF(G85=0,VLOOKUP($A84,$7:$10,G$1+2,FALSE),0),0) -> 0 | H90: =IFERROR(-IF(H85=0,VLOOKUP($A84,$7:$10,H$1+2,FALSE),0),0) -> 0 | I90: =IFERROR(-IF(I85=0,VLOOKUP($A84,$7:$10,I$1+2,FALSE),0),0) -> 0 | J90: =IFERROR(-IF(J85=0,VLOOKUP($A84,$7:$10,J$1+2,FALSE),0),0) -> 0 | ... AM90: =IFERROR(-IF(AM85=0,VLOOKUP($A84,$7:$10,AM$1+2,FALSE),0),0) -> 0
A91: Annual cost saved | C91: =IFERROR(IF(C85=0,VLOOKUP($A84,$33:$36,C$1+2,FALSE),0),0) -> 0 | D91: =IFERROR(IF(D85=0,VLOOKUP($A84,$33:$36,D$1+2,FALSE),0),0) -> 0 | E91: =IFERROR(IF(E85=0,VLOOKUP($A84,$33:$36,E$1+2,FALSE),0),0) -> 0 | F91: =IFERROR(IF(F85=0,VLOOKUP($A84,$33:$36,F$1+2,FALSE),0),0) -> 0 | G91: =IFERROR(IF(G85=0,VLOOKUP($A84,$33:$36,G$1+2,FALSE),0),0) -> 0 | H91: =IFERROR(IF(H85=0,VLOOKUP($A84,$33:$36,H$1+2,FALSE),0),0) -> 0 | I91: =IFERROR(IF(I85=0,VLOOKUP($A84,$33:$36,I$1+2,FALSE),0),0) -> 0 | J91: =IFERROR(IF(J85=0,VLOOKUP($A84,$33:$36,J$1+2,FALSE),0),0) -> 0 | ... AM91: =IFERROR(IF(AM85=0,VLOOKUP($A84,$33:$36,AM$1+2,FALSE),0),0) -> 0
A92: Loan repayment | B92: =A84 -> Gzira | C92: =IF(AND(C85>0,C88=0),VLOOKUP($A84,$61:$64,C$1+2,FALSE),0) -> 0 | D92: =IF(AND(D85>0,D88=0),VLOOKUP($A84,$61:$64,D$1+2,FALSE),0) -> 0 | E92: =IF(AND(E85>0,E88=0),VLOOKUP($A84,$61:$64,E$1+2,FALSE),0) -> 0 | F92: =IF(AND(F85>0,F88=0),VLOOKUP($A84,$61:$64,F$1+2,FALSE),0) -> 0 | G92: =IF(AND(G85>0,G88=0),VLOOKUP($A84,$61:$64,G$1+2,FALSE),0) -> 0 | H92: =IF(AND(H85>0,H88=0),VLOOKUP($A84,$61:$64,H$1+2,FALSE),0) -> 0 | I92: =IF(AND(I85>0,I88=0),VLOOKUP($A84,$61:$64,I$1+2,FALSE),0) -> 0 | J92: =IF(AND(J85>0,J88=0),VLOOKUP($A84,$61:$64,J$1+2,FALSE),0) -> 0 | ... AM92: =IF(AND(AM85>0,AM88=0),VLOOKUP($A84,$61:$64,AM$1+2,FALSE),0) -> 0
A93: Net proceeds | C93: =-C86+SUM(C89:C92) -> 0 | D93: =-D86+SUM(D89:D92) -> 0 | E93: =-E86+SUM(E89:E92) -> 0 | F93: =-F86+SUM(F89:F92) -> 0 | G93: =-G86+SUM(G89:G92) -> 0 | H93: =-H86+SUM(H89:H92) -> 0 | I93: =-I86+SUM(I89:I92) -> 0 | J93: =-J86+SUM(J89:J92) -> 0 | ... AM93: =-AM86+SUM(AM89:AM92) -> 0
A95: Cash available (after buffer) | C95: =C81+SUM($C93:C93) -> 35752.5 | D95: =D81+SUM($C93:D93) -> 64902.812 | E95: =E81+SUM($C93:E93) -> 74244.712 | F95: =F81+SUM($C93:F93) -> 115351.48 | G95: =G81+SUM($C93:G93) -> 161221.49 | H95: =H81+SUM($C93:H93) -> 221189.84 | I95: =I81+SUM($C93:I93) -> 191316.97 | J95: =J81+SUM($C93:J93) -> 142082.45 | ... AM95: =AM81+SUM($C93:AM93) -> 3818.0686
A96: Extra cash | C96: =MAX(C95+buffer,0)-MAX(C$81+buffer,0) -> 0 | D96: =MAX(D95+buffer,0)-MAX(D$81+buffer,0) -> 0 | E96: =MAX(E95+buffer,0)-MAX(E$81+buffer,0) -> 0 | F96: =MAX(F95+buffer,0)-MAX(F$81+buffer,0) -> 0 | G96: =MAX(G95+buffer,0)-MAX(G$81+buffer,0) -> 0 | H96: =MAX(H95+buffer,0)-MAX(H$81+buffer,0) -> 0 | I96: =MAX(I95+buffer,0)-MAX(I$81+buffer,0) -> 0 | J96: =MAX(J95+buffer,0)-MAX(J$81+buffer,0) -> 0 | ... AM96: =MAX(AM95+buffer,0)-MAX(AM$81+buffer,0) -> 0
A97: Extra interest | C97: =C96*Inputs!$B$149 -> 0 | D97: =D96*Inputs!$B$149 -> 0 | E97: =E96*Inputs!$B$149 -> 0 | F97: =F96*Inputs!$B$149 -> 0 | G97: =G96*Inputs!$B$149 -> 0 | H97: =H96*Inputs!$B$149 -> 0 | I97: =I96*Inputs!$B$149 -> 0 | J97: =J96*Inputs!$B$149 -> 0 | ... AM97: =AM96*Inputs!$B$149 -> 0
A98: Cash available (after extra interest) | C98: =C95+SUM($C97:C97) -> 35752.5 | D98: =D95+SUM($C97:D97) -> 64902.812 | E98: =E95+SUM($C97:E97) -> 74244.712 | F98: =F95+SUM($C97:F97) -> 115351.48 | G98: =G95+SUM($C97:G97) -> 161221.49 | H98: =H95+SUM($C97:H97) -> 221189.84 | I98: =I95+SUM($C97:I97) -> 191316.97 | J98: =J95+SUM($C97:J97) -> 142082.45 | ... AM98: =AM95+SUM($C97:AM97) -> 3818.0686
A99: Liquidation required | C99: =IF(C98<0,C95,0) -> 0 | D99: =IF(D98+SUM($C99:C99)<0,-(D98+SUM($C99:C99)),0) -> 0 | E99: =IF(E98+SUM($C99:D99)<0,-(E98+SUM($C99:D99)),0) -> 0 | F99: =IF(F98+SUM($C99:E99)<0,-(F98+SUM($C99:E99)),0) -> 0 | G99: =IF(G98+SUM($C99:F99)<0,-(G98+SUM($C99:F99)),0) -> 0 | H99: =IF(H98+SUM($C99:G99)<0,-(H98+SUM($C99:G99)),0) -> 0 | I99: =IF(I98+SUM($C99:H99)<0,-(I98+SUM($C99:H99)),0) -> 0 | J99: =IF(J98+SUM($C99:I99)<0,-(J98+SUM($C99:I99)),0) -> 0 | K99: =IF(K98+SUM($C99:J99)<0,-(K98+SUM($C99:J99)),0) -> 0 | ... AM99: =IF(AM98+SUM($C99:AL99)<0,-(AM98+SUM($C99:AL99)),0) -> 0
A101: =IF(Inputs!$B$165=6,IFERROR(_xlfn.XLOOKUP($B101,Inputs!$B$166:$B$168,Inputs!$A$166:$A$168,,0,1),""),IFERROR(_xlfn.XLOOKUP($B101,Inputs!$C$166:$C$168,Inputs!$A$166:$A$168,,0,1),"")) -> Qormi | B101: 2
A102: b/fwd | C102: =IFERROR(VLOOKUP($A101,$A$52:$H$66,C$1+2,FALSE),0) -> 226600 | D102: =C105 -> 226600 | E102: =D105 -> 233398 | F102: =E105 -> 240399.94 | G102: =F105 -> 247611.94 | H102: =G105 -> 255040.3 | I102: =H105 -> 262691.51 | J102: =I105 -> 270572.25 | K102: =J105 -> 278689.42 | ... AM102: =AL105 -> 637621.23
A103: Disposals | C103: =-IF(SUM(C99:D99)>0,C102,0) -> 0 | D103: =-IF(E99>0,D102,0) -> 0 | E103: =-IF(F99>0,E102,0) -> 0 | F103: =-IF(G99>0,F102,0) -> 0 | G103: =-IF(H99>0,G102,0) -> 0 | H103: =-IF(I99>0,H102,0) -> 0 | I103: =-IF(J99>0,I102,0) -> 0 | J103: =-IF(K99>0,J102,0) -> 0 | K103: =-IF(L99>0,K102,0) -> 0 | ... AM103: =-IF(AN99>0,AM102,0) -> 0
A104: Growth | C104: 0 | D104: =SUM(D102:D103)*princ -> 6798 | E104: =SUM(E102:E103)*princ -> 7001.94 | F104: =SUM(F102:F103)*princ -> 7211.9982 | G104: =SUM(G102:G103)*princ -> 7428.3581 | H104: =SUM(H102:H103)*princ -> 7651.2089 | I104: =SUM(I102:I103)*princ -> 7880.7452 | J104: =SUM(J102:J103)*princ -> 8117.1675 | K104: =SUM(K102:K103)*princ -> 8360.6825 | ... AM104: =SUM(AM102:AM103)*princ -> 19128.637
A105: c/fwd | C105: =SUM(C102:C104) -> 226600 | D105: =SUM(D102:D104) -> 233398 | E105: =SUM(E102:E104) -> 240399.94 | F105: =SUM(F102:F104) -> 247611.94 | G105: =SUM(G102:G104) -> 255040.3 | H105: =SUM(H102:H104) -> 262691.51 | I105: =SUM(I102:I104) -> 270572.25 | J105: =SUM(J102:J104) -> 278689.42 | ... AM105: =SUM(AM102:AM104) -> 656749.87
A106: Disposal costs | C106: =C103*Inputs!$B$163 -> 0 | D106: =D103*Inputs!$B$163 -> 0 | E106: =E103*Inputs!$B$163 -> 0 | F106: =F103*Inputs!$B$163 -> 0 | G106: =G103*Inputs!$B$163 -> 0 | H106: =H103*Inputs!$B$163 -> 0 | I106: =I103*Inputs!$B$163 -> 0 | J106: =J103*Inputs!$B$163 -> 0 | ... AM106: =AM103*Inputs!$B$163 -> 0
A107: Rental income foregone | C107: =IFERROR(-IF(C102=0,VLOOKUP($A101,$7:$10,C$1+2,FALSE),0),0) -> 0 | D107: =IFERROR(-IF(D102=0,VLOOKUP($A101,$7:$10,D$1+2,FALSE),0),0) -> 0 | E107: =IFERROR(-IF(E102=0,VLOOKUP($A101,$7:$10,E$1+2,FALSE),0),0) -> 0 | F107: =IFERROR(-IF(F102=0,VLOOKUP($A101,$7:$10,F$1+2,FALSE),0),0) -> 0 | G107: =IFERROR(-IF(G102=0,VLOOKUP($A101,$7:$10,G$1+2,FALSE),0),0) -> 0 | H107: =IFERROR(-IF(H102=0,VLOOKUP($A101,$7:$10,H$1+2,FALSE),0),0) -> 0 | I107: =IFERROR(-IF(I102=0,VLOOKUP($A101,$7:$10,I$1+2,FALSE),0),0) -> 0 | J107: =IFERROR(-IF(J102=0,VLOOKUP($A101,$7:$10,J$1+2,FALSE),0),0) -> 0 | ... AM107: =IFERROR(-IF(AM102=0,VLOOKUP($A101,$7:$10,AM$1+2,FALSE),0),0) -> 0
A108: Annual cost saved | C108: =IFERROR(IF(C102=0,VLOOKUP($A101,$33:$36,C$1+2,FALSE),0),0) -> 0 | D108: =IFERROR(IF(D102=0,VLOOKUP($A101,$33:$36,D$1+2,FALSE),0),0) -> 0 | E108: =IFERROR(IF(E102=0,VLOOKUP($A101,$33:$36,E$1+2,FALSE),0),0) -> 0 | F108: =IFERROR(IF(F102=0,VLOOKUP($A101,$33:$36,F$1+2,FALSE),0),0) -> 0 | G108: =IFERROR(IF(G102=0,VLOOKUP($A101,$33:$36,G$1+2,FALSE),0),0) -> 0 | H108: =IFERROR(IF(H102=0,VLOOKUP($A101,$33:$36,H$1+2,FALSE),0),0) -> 0 | I108: =IFERROR(IF(I102=0,VLOOKUP($A101,$33:$36,I$1+2,FALSE),0),0) -> 0 | J108: =IFERROR(IF(J102=0,VLOOKUP($A101,$33:$36,J$1+2,FALSE),0),0) -> 0 | ... AM108: =IFERROR(IF(AM102=0,VLOOKUP($A101,$33:$36,AM$1+2,FALSE),0),0) -> 0
A109: Loan repayment | B109: =A101 -> Qormi | C109: =IF(AND(C102>0,C105=0),VLOOKUP($A101,$61:$64,C$1+2,FALSE),0) -> 0 | D109: =IF(AND(D102>0,D105=0),VLOOKUP($A101,$61:$64,D$1+2,FALSE),0) -> 0 | E109: =IF(AND(E102>0,E105=0),VLOOKUP($A101,$61:$64,E$1+2,FALSE),0) -> 0 | F109: =IF(AND(F102>0,F105=0),VLOOKUP($A101,$61:$64,F$1+2,FALSE),0) -> 0 | G109: =IF(AND(G102>0,G105=0),VLOOKUP($A101,$61:$64,G$1+2,FALSE),0) -> 0 | H109: =IF(AND(H102>0,H105=0),VLOOKUP($A101,$61:$64,H$1+2,FALSE),0) -> 0 | I109: =IF(AND(I102>0,I105=0),VLOOKUP($A101,$61:$64,I$1+2,FALSE),0) -> 0 | J109: =IF(AND(J102>0,J105=0),VLOOKUP($A101,$61:$64,J$1+2,FALSE),0) -> 0 | ... AM109: =IF(AND(AM102>0,AM105=0),VLOOKUP($A101,$61:$64,AM$1+2,FALSE),0) -> 0
...
