Workbook
Name A1inc: Inputs!$B$89
Name A2inc: Inputs!$B$94
Name A3inc: Inputs!$B$99
Name A4inc: Inputs!$B$104
Name A5inc: Inputs!$B$109
Name AgeRange: RetNorm_Engine!$C$3:INDEX(RetNorm_Engine!$C$3:$XFD$3, COUNTA(RetNorm_Engine!$C$3:$XFD$3))
Name AssVar: Inputs!$A$297:$C$306
Name buffer: Inputs!$B$269
Name ChartCash_Early: RetEarly_Engine!$C$379:INDEX(RetEarly_Engine!$C$379:$XFD$379, COUNTA(RetEarly_Engine!$C$379:$XFD$379))
Name ChartCash_Norm: RetNorm_Engine!$C$379:INDEX(RetNorm_Engine!$C$379:$XFD$379, COUNTA(RetNorm_Engine!$C$379:$XFD$379))
Name ChartNW_Early: RetEarly_Engine!$C$380:INDEX(RetEarly_Engine!$C$380:$XFD$380, COUNTA(RetEarly_Engine!$C$380:$XFD$380))
Name ChartNW_Norm: RetNorm_Engine!$C$380:INDEX(RetNorm_Engine!$C$380:$XFD$380, COUNTA(RetNorm_Engine!$C$380:$XFD$380))
Name DCoth: Inputs!$B$277
Name DCprop: Inputs!$B$275
Name EndAge: Inputs!$B$244
Name inf: Inputs!$B$255
Name legacy: Inputs!$B$271
Name MthOff: Inputs!$B$293
Name MthRem: Inputs!$B$292
Name princ: Inputs!$B$257
Name ProRate: Inputs!$B$294
Name RetAge: Inputs!$B$19
Name rinc: Inputs!$B$265
Name sincr: Inputs!$B$263
Name stinc: Inputs!$B$261

Sheet Inputs
B1: User inputs | D1: User Tooltips | E1: UI Notes | F1: Excel helpers
A2: QUICK START
A4: Your age | B4: 48 | D4: Must be entered
A6: Current net annual income | B6: 80000 | D6: Net of tax, from employment or self-employment
A8: Total cash balances | B8: 50000 | D8: current and savings accounts, bonds, term deposits
A10: Stock market investments | B10: 30000 | D10: Current market value of equity portfolio
A12: Home current market value | B12: 600000 | D12: Leave blank if not a home owner
A14: Home loan (mortgage)
A15: Balance | B15: 50000 | D15: Leave blank if no mortgage | F15: Months remaining | G15: =IFERROR(NPER(B16/12,-B17,B15),"") -> 68.044529
A16: Interest rate | B16: 0.03 | F16: Years remaining | G16: =IFERROR(G15/12,"") -> 5.6703774
A17: Monthly repayment | B17: 800
A19: Statutory retirement age | B19: 65 | D19: Year at which pension starts
A21: Annual pension at retirement | B21: 16000 | D21: Net annual state pension entitlement
A23: Housing rent | D23: if not a home owner | E23: show only if not a home owner (B12="")
A25: Annual living expenses | B25: 50000
A28: DEEPER DIVE | E28: Activated only if user wants to
A30: Dependents
A32: Dependent 1
A33: Name | B33: John | D33: Leave blank if none
A34: Annual cost | B34: 2000 | D34: Food, education, healthcare, etc. | E34: Hide until user enters dependent name
A35: Years to support | B35: 3 | D35: Years from now | E35: Hide until user enters dependent name
A37: Dependent 2
A38: Name | B38: Jack | D38: Leave blank if none
A39: Annual cost | B39: 1000 | D39: Food, education, healthcare, etc. | E39: Hide until user enters dependent name
A40: Years to support | B40: 5 | D40: Years from now | E40: Hide until user enters dependent name
A42: Dependent 3
A43: Name | B43: Bill | D43: Leave blank if none
A44: Annual cost | B44: 4000 | D44: Food, education, healthcare, etc. | E44: Hide until user enters dependent name
A45: Years to support | B45: 2 | D45: Years from now | E45: Hide until user enters dependent name
A47: Dependent 4
A48: Name | B48: Stephen | D48: Leave blank if none
A49: Annual cost | B49: 2500 | D49: Food, education, healthcare, etc. | E49: Hide until user enters dependent name
A50: Years to support | B50: 3 | D50: Years from now | E50: Hide until user enters dependent name
A52: Dependent 5
A53: Name | B53: Jane | D53: Leave blank if none
A54: Annual cost | B54: 2860 | D54: Food, education, healthcare, etc. | E54: Hide until user enters dependent name
A55: Years to support | B55: 6 | D55: Years from now | E55: Hide until user enters dependent name
A57: Investment Properties
A59: Property 1
A60: Name | B60: Sliema | D60: Leave blank if none
A61: Market value | B61: 300000 | E61: Hide until user enters property name
A62: Annual costs | B62: 5000 | D62: Repairs, maintenance, etc. | E62: Hide until user enters property name
A64: Property 2
A65: Name | B65: Gzira | D65: Leave blank if none
A66: Market value | B66: 150000 | E66: Hide until user enters property name
A67: Annual costs | B67: 2000 | D67: Repairs, maintenance, etc. | E67: Hide until user enters property name
A69: Property 3
A70: Name | B70: Qormi | D70: Leave blank if none
A71: Market value | B71: 220000 | E71: Hide until user enters property name
A72: Annual costs | B72: 1200 | D72: Repairs, maintenance, etc. | E72: Hide until user enters property name
A74: Property 4
A75: Name | B75: Gudja | D75: Leave blank if none
A76: Market value | B76: 80000 | E76: Hide until user enters property name
A77: Annual costs | B77: 1000 | D77: Repairs, maintenance, etc. | E77: Hide until user enters property name
A79: Property 5
A80: Name | B80: Marsa | D80: Leave blank if none
A81: Market value | B81: 120000 | E81: Hide until user enters property name
A82: Annual costs | B82: 800 | D82: Repairs, maintenance, etc. | E82: Hide until user enters property name
A84: Other Assets of Value
A86: Asset 1
A87: Name | B87: Jewelry | D87: Leave blank if none
A88: Market value | B88: 50000 | E88: Hide until user enters asset name
A89: Annual appreciation / depreciation | B89: 0.02 | D89: posiytive if it asset value grows, negative if asset depreciates | E89: Hide until user enters asset name
A91: Asset 2
A92: Name | B92: Car | D92: Leave blank if none
A93: Market value | B93: 40000 | E93: Hide until user enters asset name
A94: Annual appreciation / depreciation | B94: -0.05 | D94: posiytive if it asset value grows, negative if asset depreciates | E94: Hide until user enters asset name
A96: Asset 3
A97: Name | B97: Painting | D97: Leave blank if none
A98: Market value | B98: 20000 | E98: Hide until user enters asset name
A99: Annual appreciation / depreciation | B99: 0.03 | D99: posiytive if it asset value grows, negative if asset depreciates | E99: Hide until user enters asset name
A101: Asset 4
A102: Name | B102: Boat | D102: Leave blank if none
A103: Market value | B103: 180000 | E103: Hide until user enters asset name
A104: Annual appreciation / depreciation | B104: -0.05 | D104: posiytive if it asset value grows, negative if asset depreciates | E104: Hide until user enters asset name
A106: Asset 5
A107: Name | B107: Antiques | D107: Leave blank if none
A108: Market value | B108: 82000 | E108: Hide until user enters asset name
A109: Annual appreciation / depreciation | B109: 0.02 | D109: posiytive if it asset value grows, negative if asset depreciates | E109: Hide until user enters asset name
A111: Other income
A113: ="Rental income: "&B60 -> Rental income: Sliema | B113: 12000 | D113: net annual after all costs and tax | E113: Show with property name only if name was entered
A114: ="Rental income: "&B65 -> Rental income: Gzira | B114: 10000 | D114: net annual after all costs and tax | E114: Show with property name only if name was entered
A115: ="Rental income: "&B70 -> Rental income: Qormi | B115: 8000 | D115: net annual after all costs and tax | E115: Show with property name only if name was entered
A116: ="Rental income: "&B75 -> Rental income: Gudja | B116: 5000 | D116: net annual after all costs and tax | E116: Show with property name only if name was entered
A117: ="Rental income: "&B80 -> Rental income: Marsa | B117: 6500 | D117: net annual after all costs and tax | E117: Show with property name only if name was entered
A119: Other work income (net annual) | B119: 2000 | D119: Part-time / consulting / side projects etc. Leave blank if none
A120: Continue other work until age | B120: 58 | E120: Show only if other work income entered
A122: Loans
A124: Credit card balances | B124: 1000 | D124: Assumed cleared in Year 1. Leave blank if none
A126: =B60 & " Property" -> Sliema Property
A127: Balance | B127: 50000 | D127: Enter 0 or leave blank if none | F127: Months remaining | G127: =IFERROR(NPER(B128/12,-B129,B127),"") -> 115.21661
A128: Interest rate | B128: 0.03 | F128: Years remaining | G128: =IFERROR(G127/12,"") -> 9.6013842
A129: Monthly repayment | B129: 500
A131: =B65 & " Property" -> Gzira Property
A132: Balance | B132: 8500 | D132: Enter 0 or leave blank if none | F132: Months remaining | G132: =IFERROR(NPER(B133/12,-B134,B132),"") -> 44.117015
A133: Interest rate | B133: 0.02 | F133: Years remaining | G133: =IFERROR(G132/12,"") -> 3.6764179
A134: Monthly repayment | B134: 200
A136: =B70& " Property" -> Qormi Property
A137: Balance | B137: 15000 | D137: Enter 0 or leave blank if none | F137: Months remaining | G137: =IFERROR(NPER(B138/12,-B139,B137),"") -> 69.187439
A138: Interest rate | B138: 0.05 | F138: Years remaining | G138: =IFERROR(G137/12,"") -> 5.7656199
...

Sheet Output
V2: Retire at | AA2: ="Retire at "&RetEarly_Engine!B3 -> Retire at 51
V3: =RetEarly_Engine!B3 -> 51 | AA3: ="Retire at "&RetAge -> Retire at 65

Sheet RetNorm_Engine
B1: 0 | C1: 1 | D1: =C1+1 -> 2 | E1: =D1+1 -> 3 | F1: =E1+1 -> 4 | G1: =F1+1 -> 5 | H1: =G1+1 -> 6 | I1: =H1+1 -> 7 | J1: =I1+1 -> 8 | K1: =J1+1 -> 9 | ... AM1: =AL1+1 -> 37
B2: Year | C2: =YEAR(TODAY()) -> 2026 | D2: =C2+1 -> 2027 | E2: =D2+1 -> 2028 | F2: =E2+1 -> 2029 | G2: =F2+1 -> 2030 | H2: =G2+1 -> 2031 | I2: =H2+1 -> 2032 | J2: =I2+1 -> 2033 | K2: =J2+1 -> 2034 | ... AM2: =AL2+1 -> 2062
B3: =Inputs!B19 -> 65 | C3: =Inputs!B4 -> 48 | D3: =C3+1 -> 49 | E3: =D3+1 -> 50 | F3: =E3+1 -> 51 | G3: =F3+1 -> 52 | H3: =G3+1 -> 53 | I3: =H3+1 -> 54 | J3: =I3+1 -> 55 | K3: =J3+1 -> 56 | ... AM3: =AL3+1 -> 84
A4: Inflows
A5: Net employment / self-employment income | C5: =IF(AND(Inputs!$B$19>C3,$B$3>C3),Inputs!$B$6*(1+sincr)^B1,0)*ProRate -> 66666.667 | D5: =IF(AND(Inputs!$B$19>D3,$B$3>D3),Inputs!$B$6*(1+sincr)^C1,0) -> 82400 | E5: =IF(AND(Inputs!$B$19>E3,$B$3>E3),Inputs!$B$6*(1+sincr)^D1,0) -> 84872 | F5: =IF(AND(Inputs!$B$19>F3,$B$3>F3),Inputs!$B$6*(1+sincr)^E1,0) -> 87418.16 | G5: =IF(AND(Inputs!$B$19>G3,$B$3>G3),Inputs!$B$6*(1+sincr)^F1,0) -> 90040.705 | H5: =IF(AND(Inputs!$B$19>H3,$B$3>H3),Inputs!$B$6*(1+sincr)^G1,0) -> 92741.926 | I5: =IF(AND(Inputs!$B$19>I3,$B$3>I3),Inputs!$B$6*(1+sincr)^H1,0) -> 95524.184 | J5: =IF(AND(Inputs!$B$19>J3,$B$3>J3),Inputs!$B$6*(1+sincr)^I1,0) -> 98389.909 | K5: =IF(AND(Inputs!$B$19>K3,$B$3>K3),Inputs!$B$6*(1+sincr)^J1,0) -> 101341.61 | ... AM5: =IF(AND(Inputs!$B$19>AM3,$B$3>AM3),Inputs!$B$6*(1+sincr)^AL1,0) -> 0
A6: Net from other work | C6: =IF(C$3<=Inputs!$B$120,Inputs!$B$119,0)*(1+inf)^B$1*ProRate -> 1666.6667 | D6: =IF(D$3<=Inputs!$B$120,Inputs!$B$119,0)*(1+inf)^C$1 -> 2050 | E6: =IF(E$3<=Inputs!$B$120,Inputs!$B$119,0)*(1+inf)^D$1 -> 2101.25 | F6: =IF(F$3<=Inputs!$B$120,Inputs!$B$119,0)*(1+inf)^E$1 -> 2153.7812 | G6: =IF(G$3<=Inputs!$B$120,Inputs!$B$119,0)*(1+inf)^F$1 -> 2207.6258 | H6: =IF(H$3<=Inputs!$B$120,Inputs!$B$119,0)*(1+inf)^G$1 -> 2262.8164 | I6: =IF(I$3<=Inputs!$B$120,Inputs!$B$119,0)*(1+inf)^H$1 -> 2319.3868 | J6: =IF(J$3<=Inputs!$B$120,Inputs!$B$119,0)*(1+inf)^I$1 -> 2377.3715 | K6: =IF(K$3<=Inputs!$B$120,Inputs!$B$119,0)*(1+inf)^J$1 -> 2436.8058 | ... AM6: =IF(AM$3<=Inputs!$B$120,Inputs!$B$119,0)*(1+inf)^AL$1 -> 0
A7: Net rental income from other properties
A8: =TEXT(Inputs!$B$60,"") -> Sliema | C8: =Inputs!B113*ProRate -> 10000 | D8: =C8*(1+rinc) -> 10300 | E8: =D8*(1+rinc) -> 10609 | F8: =E8*(1+rinc) -> 10927.27 | G8: =F8*(1+rinc) -> 11255.088 | H8: =G8*(1+rinc) -> 11592.741 | I8: =H8*(1+rinc) -> 11940.523 | J8: =I8*(1+rinc) -> 12298.739 | K8: =J8*(1+rinc) -> 12667.701 | ... AM8: =AL8*(1+rinc) -> 28982.783
A9: =TEXT(Inputs!$B$65,"") -> Gzira | C9: =Inputs!B114*ProRate -> 8333.3333 | D9: =C9*(1+rinc) -> 8583.3333 | E9: =D9*(1+rinc) -> 8840.8333 | F9: =E9*(1+rinc) -> 9106.0583 | G9: =F9*(1+rinc) -> 9379.2401 | H9: =G9*(1+rinc) -> 9660.6173 | I9: =H9*(1+rinc) -> 9950.4358 | J9: =I9*(1+rinc) -> 10248.949 | K9: =J9*(1+rinc) -> 10556.417 | ... AM9: =AL9*(1+rinc) -> 24152.319
A10: =TEXT(Inputs!$B$70,"") -> Qormi | C10: =Inputs!B115*ProRate -> 6666.6667 | D10: =C10*(1+rinc) -> 6866.6667 | E10: =D10*(1+rinc) -> 7072.6667 | F10: =E10*(1+rinc) -> 7284.8467 | G10: =F10*(1+rinc) -> 7503.3921 | H10: =G10*(1+rinc) -> 7728.4938 | I10: =H10*(1+rinc) -> 7960.3486 | J10: =I10*(1+rinc) -> 8199.1591 | K10: =J10*(1+rinc) -> 8445.1339 | ... AM10: =AL10*(1+rinc) -> 19321.856
A11: =TEXT(Inputs!$B$75,"") -> Gudja | C11: =Inputs!B116*ProRate -> 4166.6667 | D11: =C11*(1+rinc) -> 4291.6667 | E11: =D11*(1+rinc) -> 4420.4167 | F11: =E11*(1+rinc) -> 4553.0292 | G11: =F11*(1+rinc) -> 4689.62 | H11: =G11*(1+rinc) -> 4830.3086 | I11: =H11*(1+rinc) -> 4975.2179 | J11: =I11*(1+rinc) -> 5124.4744 | K11: =J11*(1+rinc) -> 5278.2087 | ... AM11: =AL11*(1+rinc) -> 12076.16
A12: =TEXT(Inputs!$B$80,"") -> Marsa | C12: =Inputs!B117*ProRate -> 5416.6667 | D12: =C12*(1+rinc) -> 5579.1667 | E12: =D12*(1+rinc) -> 5746.5417 | F12: =E12*(1+rinc) -> 5918.9379 | G12: =F12*(1+rinc) -> 6096.5061 | H12: =G12*(1+rinc) -> 6279.4012 | I12: =H12*(1+rinc) -> 6467.7833 | J12: =I12*(1+rinc) -> 6661.8168 | K12: =J12*(1+rinc) -> 6861.6713 | ... AM12: =AL12*(1+rinc) -> 15699.008
A13: Full pension | C13: =IF(C$3<Inputs!$B$19,0,Inputs!$B$21)*(1+inf)^B$1*ProRate -> 0 | D13: =IF(D$3<Inputs!$B$19,0,Inputs!$B$21)*(1+inf)^C$1 -> 0 | E13: =IF(E$3<Inputs!$B$19,0,Inputs!$B$21)*(1+inf)^D$1 -> 0 | F13: =IF(F$3<Inputs!$B$19,0,Inputs!$B$21)*(1+inf)^E$1 -> 0 | G13: =IF(G$3<Inputs!$B$19,0,Inputs!$B$21)*(1+inf)^F$1 -> 0 | H13: =IF(H$3<Inputs!$B$19,0,Inputs!$B$21)*(1+inf)^G$1 -> 0 | I13: =IF(I$3<Inputs!$B$19,0,Inputs!$B$21)*(1+inf)^H$1 -> 0 | J13: =IF(J$3<Inputs!$B$19,0,Inputs!$B$21)*(1+inf)^I$1 -> 0 | K13: =IF(K$3<Inputs!$B$19,0,Inputs!$B$21)*(1+inf)^J$1 -> 0 | ... AM13: =IF(AM$3<Inputs!$B$19,0,Inputs!$B$21)*(1+inf)^AL$1 -> 38920.565
A14: Pension reduction from early retirement | C14: =MIN(0,MAX(-IF(C13=0,0,(Inputs!$B$19-INDEX(3:3,MATCH(0,5:5,0))))*Inputs!$B$267*(1+inf)^B$1*ProRate,-C13)) -> 0 | D14: =MIN(0,MAX(-IF(D13=0,0,(Inputs!$B$19-INDEX(3:3,MATCH(0,5:5,0))))*Inputs!$B$267*(1+inf)^C$1,-D13)) -> 0 | E14: =MIN(0,MAX(-IF(E13=0,0,(Inputs!$B$19-INDEX(3:3,MATCH(0,5:5,0))))*Inputs!$B$267*(1+inf)^D$1,-E13)) -> 0 | F14: =MIN(0,MAX(-IF(F13=0,0,(Inputs!$B$19-INDEX(3:3,MATCH(0,5:5,0))))*Inputs!$B$267*(1+inf)^E$1,-F13)) -> 0 | G14: =MIN(0,MAX(-IF(G13=0,0,(Inputs!$B$19-INDEX(3:3,MATCH(0,5:5,0))))*Inputs!$B$267*(1+inf)^F$1,-G13)) -> 0 | H14: =MIN(0,MAX(-IF(H13=0,0,(Inputs!$B$19-INDEX(3:3,MATCH(0,5:5,0))))*Inputs!$B$267*(1+inf)^G$1,-H13)) -> 0 | I14: =MIN(0,MAX(-IF(I13=0,0,(Inputs!$B$19-INDEX(3:3,MATCH(0,5:5,0))))*Inputs!$B$267*(1+inf)^H$1,-I13)) -> 0 | J14: =MIN(0,MAX(-IF(J13=0,0,(Inputs!$B$19-INDEX(3:3,MATCH(0,5:5,0))))*Inputs!$B$267*(1+inf)^I$1,-J13)) -> 0 | K14: =MIN(0,MAX(-IF(K13=0,0,(Inputs!$B$19-INDEX(3:3,MATCH(0,5:5,0))))*Inputs!$B$267*(1+inf)^J$1,-K13)) -> 0 | ... AM14: =MIN(0,MAX(-IF(AM13=0,0,(Inputs!$B$19-INDEX(3:3,MATCH(0,5:5,0))))*Inputs!$B$267*(1+inf)^AL$1,-AM13)) -> 0
A15: Other post-retirement income | C15: =IF(AND(C$3>=Inputs!$B$252,C$3<=Inputs!$B$253),Inputs!$B$251*(1+inf)^B$1,0)*ProRate -> 0 | D15: =IF(AND(D$3>=Inputs!$B$252,D$3<=Inputs!$B$253),Inputs!$B$251*(1+inf)^C$1,0) -> 0 | E15: =IF(AND(E$3>=Inputs!$B$252,E$3<=Inputs!$B$253),Inputs!$B$251*(1+inf)^D$1,0) -> 0 | F15: =IF(AND(F$3>=Inputs!$B$252,F$3<=Inputs!$B$253),Inputs!$B$251*(1+inf)^E$1,0) -> 0 | G15: =IF(AND(G$3>=Inputs!$B$252,G$3<=Inputs!$B$253),Inputs!$B$251*(1+inf)^F$1,0) -> 0 | H15: =IF(AND(H$3>=Inputs!$B$252,H$3<=Inputs!$B$253),Inputs!$B$251*(1+inf)^G$1,0) -> 0 | I15: =IF(AND(I$3>=Inputs!$B$252,I$3<=Inputs!$B$253),Inputs!$B$251*(1+inf)^H$1,0) -> 0 | J15: =IF(AND(J$3>=Inputs!$B$252,J$3<=Inputs!$B$253),Inputs!$B$251*(1+inf)^I$1,0) -> 0 | K15: =IF(AND(K$3>=Inputs!$B$252,K$3<=Inputs!$B$253),Inputs!$B$251*(1+inf)^J$1,0) -> 0 | ... AM15: =IF(AND(AM$3>=Inputs!$B$252,AM$3<=Inputs!$B$253),Inputs!$B$251*(1+inf)^AL$1,0) -> 0
A16: Major one-off income events
A17: =TEXT(Inputs!B184,"") -> Inheritance | C17: =IF(C$2=Inputs!$B186,Inputs!$B185,0)*(1+inf)^B$1 -> 0 | D17: =IF(D$2=Inputs!$B186,Inputs!$B185,0)*(1+inf)^C$1 -> 0 | E17: =IF(E$2=Inputs!$B186,Inputs!$B185,0)*(1+inf)^D$1 -> 0 | F17: =IF(F$2=Inputs!$B186,Inputs!$B185,0)*(1+inf)^E$1 -> 0 | G17: =IF(G$2=Inputs!$B186,Inputs!$B185,0)*(1+inf)^F$1 -> 0 | H17: =IF(H$2=Inputs!$B186,Inputs!$B185,0)*(1+inf)^G$1 -> 0 | I17: =IF(I$2=Inputs!$B186,Inputs!$B185,0)*(1+inf)^H$1 -> 0 | J17: =IF(J$2=Inputs!$B186,Inputs!$B185,0)*(1+inf)^I$1 -> 0 | ... AM17: =IF(AM$2=Inputs!$B186,Inputs!$B185,0)*(1+inf)^AL$1 -> 0
A18: =TEXT(Inputs!B189,"") -> Sell Painting | C18: =IF(C$2=Inputs!$B191,Inputs!$B190,0)*(1+inf)^B$1 -> 0 | D18: =IF(D$2=Inputs!$B191,Inputs!$B190,0)*(1+inf)^C$1 -> 0 | E18: =IF(E$2=Inputs!$B191,Inputs!$B190,0)*(1+inf)^D$1 -> 0 | F18: =IF(F$2=Inputs!$B191,Inputs!$B190,0)*(1+inf)^E$1 -> 10768.906 | G18: =IF(G$2=Inputs!$B191,Inputs!$B190,0)*(1+inf)^F$1 -> 0 | H18: =IF(H$2=Inputs!$B191,Inputs!$B190,0)*(1+inf)^G$1 -> 0 | I18: =IF(I$2=Inputs!$B191,Inputs!$B190,0)*(1+inf)^H$1 -> 0 | J18: =IF(J$2=Inputs!$B191,Inputs!$B190,0)*(1+inf)^I$1 -> 0 | ... AM18: =IF(AM$2=Inputs!$B191,Inputs!$B190,0)*(1+inf)^AL$1 -> 0
A19: =TEXT(Inputs!B194,"") -> Sell Jewels | C19: =IF(C$2=Inputs!$B196,Inputs!$B195,0)*(1+inf)^B$1 -> 0 | D19: =IF(D$2=Inputs!$B196,Inputs!$B195,0)*(1+inf)^C$1 -> 0 | E19: =IF(E$2=Inputs!$B196,Inputs!$B195,0)*(1+inf)^D$1 -> 0 | F19: =IF(F$2=Inputs!$B196,Inputs!$B195,0)*(1+inf)^E$1 -> 0 | G19: =IF(G$2=Inputs!$B196,Inputs!$B195,0)*(1+inf)^F$1 -> 0 | H19: =IF(H$2=Inputs!$B196,Inputs!$B195,0)*(1+inf)^G$1 -> 0 | I19: =IF(I$2=Inputs!$B196,Inputs!$B195,0)*(1+inf)^H$1 -> 5798.4671 | J19: =IF(J$2=Inputs!$B196,Inputs!$B195,0)*(1+inf)^I$1 -> 0 | ... AM19: =IF(AM$2=Inputs!$B196,Inputs!$B195,0)*(1+inf)^AL$1 -> 0
A20: Interest on cash balances | C20: =MAX(AVERAGE(C62,C62+SUM(C5:C19)-C59)*Inputs!$B$259,0) -> 1392.7083 | D20: =MAX(AVERAGE(D62,D62+SUM(D5:D19)-D59)*Inputs!$B$259,0) -> 1691.0073 | E20: =MAX(AVERAGE(E62,E62+SUM(E5:E19)-E59)*Inputs!$B$259,0) -> 2049.0802 | F20: =MAX(AVERAGE(F62,F62+SUM(F5:F19)-F59)*Inputs!$B$259,0) -> 2266.8747 | G20: =MAX(AVERAGE(G62,G62+SUM(G5:G19)-G59)*Inputs!$B$259,0) -> 2658.3728 | H20: =MAX(AVERAGE(H62,H62+SUM(H5:H19)-H59)*Inputs!$B$259,0) -> 3524.3258 | I20: =MAX(AVERAGE(I62,I62+SUM(I5:I19)-I59)*Inputs!$B$259,0) -> 4827.2148 | J20: =MAX(AVERAGE(J62,J62+SUM(J5:J19)-J59)*Inputs!$B$259,0) -> 6533.8412 | ... AM20: =MAX(AVERAGE(AM62,AM62+SUM(AM5:AM19)-AM59)*Inputs!$B$259,0) -> 59015.801
C21: =SUM(C4:C20) -> 104309.38 | D21: =SUM(D4:D20) -> 121761.84 | E21: =SUM(E4:E20) -> 125711.79 | F21: =SUM(F4:F20) -> 140397.86 | G21: =SUM(G4:G20) -> 133830.55 | H21: =SUM(H4:H20) -> 138620.63 | I21: =SUM(I4:I20) -> 149763.56 | J21: =SUM(J4:J20) -> 149834.26 | ... AM21: =SUM(AM4:AM20) -> 198168.49
A22: Outflows
A23: Credit cards cleared | C23: =Inputs!B124 -> 1000 | D23: 0 | E23: 0 | F23: 0 | G23: 0 | H23: 0 | I23: 0 | J23: 0 | K23: 0 | L23: 0 | M23: 0 | N23: 0 | O23: 0 | P23: 0 | Q23: 0 | R23: 0 | S23: 0 | T23: 0 | U23: 0 | V23: 0 | W23: 0 | X23: 0 | Y23: 0 | Z23: 0 | AA23: 0 | AB23: 0 | AC23: 0 | AD23: 0 | AE23: 0 | AF23: 0 | AG23: 0 | AH23: 0 | AI23: 0 | AJ23: 0 | AK23: 0 | AL23: 0 | AM23: 0
A24: Home loan repayment | C24: =MIN(IF(B$1=0,MthRem,12), MAX(Inputs!$G$15-IF(B$1=0,0,B$1*12+MthOff), 0))*Inputs!$B$17 -> 8000 | D24: =MIN(IF(C$1=0,MthRem,12), MAX(Inputs!$G$15-IF(C$1=0,0,C$1*12+MthOff), 0))*Inputs!$B$17 -> 9600 | E24: =MIN(IF(D$1=0,MthRem,12), MAX(Inputs!$G$15-IF(D$1=0,0,D$1*12+MthOff), 0))*Inputs!$B$17 -> 9600 | F24: =MIN(IF(E$1=0,MthRem,12), MAX(Inputs!$G$15-IF(E$1=0,0,E$1*12+MthOff), 0))*Inputs!$B$17 -> 9600 | G24: =MIN(IF(F$1=0,MthRem,12), MAX(Inputs!$G$15-IF(F$1=0,0,F$1*12+MthOff), 0))*Inputs!$B$17 -> 9600 | H24: =MIN(IF(G$1=0,MthRem,12), MAX(Inputs!$G$15-IF(G$1=0,0,G$1*12+MthOff), 0))*Inputs!$B$17 -> 8035.6231 | I24: =MIN(IF(H$1=0,MthRem,12), MAX(Inputs!$G$15-IF(H$1=0,0,H$1*12+MthOff), 0))*Inputs!$B$17 -> 0 | J24: =MIN(IF(I$1=0,MthRem,12), MAX(Inputs!$G$15-IF(I$1=0,0,I$1*12+MthOff), 0))*Inputs!$B$17 -> 0 | ... AM24: =MIN(IF(AL$1=0,MthRem,12), MAX(Inputs!$G$15-IF(AL$1=0,0,AL$1*12+MthOff), 0))*Inputs!$B$17 -> 0
A25: Other asset loans repayments
A26: =TEXT(Inputs!$B$60,"") -> Sliema | C26: =MIN(IF(B$1=0,MthRem,12), MAX(Inputs!$G$127-IF(B$1=0,0,B$1*12+MthOff), 0))*Inputs!$B$129 -> 5000 | D26: =MIN(IF(C$1=0,MthRem,12), MAX(Inputs!$G$127-IF(C$1=0,0,C$1*12+MthOff), 0))*Inputs!$B$129 -> 6000 | E26: =MIN(IF(D$1=0,MthRem,12), MAX(Inputs!$G$127-IF(D$1=0,0,D$1*12+MthOff), 0))*Inputs!$B$129 -> 6000 | F26: =MIN(IF(E$1=0,MthRem,12), MAX(Inputs!$G$127-IF(E$1=0,0,E$1*12+MthOff), 0))*Inputs!$B$129 -> 6000 | G26: =MIN(IF(F$1=0,MthRem,12), MAX(Inputs!$G$127-IF(F$1=0,0,F$1*12+MthOff), 0))*Inputs!$B$129 -> 6000 | H26: =MIN(IF(G$1=0,MthRem,12), MAX(Inputs!$G$127-IF(G$1=0,0,G$1*12+MthOff), 0))*Inputs!$B$129 -> 6000 | I26: =MIN(IF(H$1=0,MthRem,12), MAX(Inputs!$G$127-IF(H$1=0,0,H$1*12+MthOff), 0))*Inputs!$B$129 -> 6000 | J26: =MIN(IF(I$1=0,MthRem,12), MAX(Inputs!$G$127-IF(I$1=0,0,I$1*12+MthOff), 0))*Inputs!$B$129 -> 6000 | ... AM26: =MIN(IF(AL$1=0,MthRem,12), MAX(Inputs!$G$127-IF(AL$1=0,0,AL$1*12+MthOff), 0))*Inputs!$B$129 -> 0
A27: =TEXT(Inputs!$B$65,"") -> Gzira | C27: =MIN(IF(B$1=0,MthRem,12), MAX(Inputs!$G$132-IF(B$1=0,0,B$1*12+MthOff), 0))*Inputs!$B$134 -> 2000 | D27: =MIN(IF(C$1=0,MthRem,12), MAX(Inputs!$G$132-IF(C$1=0,0,C$1*12+MthOff), 0))*Inputs!$B$134 -> 2400 | E27: =MIN(IF(D$1=0,MthRem,12), MAX(Inputs!$G$132-IF(D$1=0,0,D$1*12+MthOff), 0))*Inputs!$B$134 -> 2400 | F27: =MIN(IF(E$1=0,MthRem,12), MAX(Inputs!$G$132-IF(E$1=0,0,E$1*12+MthOff), 0))*Inputs!$B$134 -> 2023.4029 | G27: =MIN(IF(F$1=0,MthRem,12), MAX(Inputs!$G$132-IF(F$1=0,0,F$1*12+MthOff), 0))*Inputs!$B$134 -> 0 | H27: =MIN(IF(G$1=0,MthRem,12), MAX(Inputs!$G$132-IF(G$1=0,0,G$1*12+MthOff), 0))*Inputs!$B$134 -> 0 | I27: =MIN(IF(H$1=0,MthRem,12), MAX(Inputs!$G$132-IF(H$1=0,0,H$1*12+MthOff), 0))*Inputs!$B$134 -> 0 | J27: =MIN(IF(I$1=0,MthRem,12), MAX(Inputs!$G$132-IF(I$1=0,0,I$1*12+MthOff), 0))*Inputs!$B$134 -> 0 | ... AM27: =MIN(IF(AL$1=0,MthRem,12), MAX(Inputs!$G$132-IF(AL$1=0,0,AL$1*12+MthOff), 0))*Inputs!$B$134 -> 0
A28: =TEXT(Inputs!$B$70,"") -> Qormi | C28: =MIN(IF(B$1=0,MthRem,12), MAX(Inputs!$G$137-IF(B$1=0,0,B$1*12+MthOff), 0))*Inputs!$B$139 -> 2500 | D28: =MIN(IF(C$1=0,MthRem,12), MAX(Inputs!$G$137-IF(C$1=0,0,C$1*12+MthOff), 0))*Inputs!$B$139 -> 3000 | E28: =MIN(IF(D$1=0,MthRem,12), MAX(Inputs!$G$137-IF(D$1=0,0,D$1*12+MthOff), 0))*Inputs!$B$139 -> 3000 | F28: =MIN(IF(E$1=0,MthRem,12), MAX(Inputs!$G$137-IF(E$1=0,0,E$1*12+MthOff), 0))*Inputs!$B$139 -> 3000 | G28: =MIN(IF(F$1=0,MthRem,12), MAX(Inputs!$G$137-IF(F$1=0,0,F$1*12+MthOff), 0))*Inputs!$B$139 -> 3000 | H28: =MIN(IF(G$1=0,MthRem,12), MAX(Inputs!$G$137-IF(G$1=0,0,G$1*12+MthOff), 0))*Inputs!$B$139 -> 2796.8597 | I28: =MIN(IF(H$1=0,MthRem,12), MAX(Inputs!$G$137-IF(H$1=0,0,H$1*12+MthOff), 0))*Inputs!$B$139 -> 0 | J28: =MIN(IF(I$1=0,MthRem,12), MAX(Inputs!$G$137-IF(I$1=0,0,I$1*12+MthOff), 0))*Inputs!$B$139 -> 0 | ... AM28: =MIN(IF(AL$1=0,MthRem,12), MAX(Inputs!$G$137-IF(AL$1=0,0,AL$1*12+MthOff), 0))*Inputs!$B$139 -> 0
A29: =TEXT(Inputs!$B$75,"") -> Gudja | C29: =MIN(IF(B$1=0,MthRem,12), MAX(Inputs!$G$142-IF(B$1=0,0,B$1*12+MthOff), 0))*Inputs!$B$144 -> 800 | D29: =MIN(IF(C$1=0,MthRem,12), MAX(Inputs!$G$142-IF(C$1=0,0,C$1*12+MthOff), 0))*Inputs!$B$144 -> 960 | E29: =MIN(IF(D$1=0,MthRem,12), MAX(Inputs!$G$142-IF(D$1=0,0,D$1*12+MthOff), 0))*Inputs!$B$144 -> 960 | F29: =MIN(IF(E$1=0,MthRem,12), MAX(Inputs!$G$142-IF(E$1=0,0,E$1*12+MthOff), 0))*Inputs!$B$144 -> 960 | G29: =MIN(IF(F$1=0,MthRem,12), MAX(Inputs!$G$142-IF(F$1=0,0,F$1*12+MthOff), 0))*Inputs!$B$144 -> 960 | H29: =MIN(IF(G$1=0,MthRem,12), MAX(Inputs!$G$142-IF(G$1=0,0,G$1*12+MthOff), 0))*Inputs!$B$144 -> 288.25859 | I29: =MIN(IF(H$1=0,MthRem,12), MAX(Inputs!$G$142-IF(H$1=0,0,H$1*12+MthOff), 0))*Inputs!$B$144 -> 0 | J29: =MIN(IF(I$1=0,MthRem,12), MAX(Inputs!$G$142-IF(I$1=0,0,I$1*12+MthOff), 0))*Inputs!$B$144 -> 0 | ... AM29: =MIN(IF(AL$1=0,MthRem,12), MAX(Inputs!$G$142-IF(AL$1=0,0,AL$1*12+MthOff), 0))*Inputs!$B$144 -> 0
A30: =TEXT(Inputs!$B$80,"") -> Marsa | C30: =MIN(IF(B$1=0,MthRem,12), MAX(Inputs!$G$147-IF(B$1=0,0,B$1*12+MthOff), 0))*Inputs!$B$149 -> 1200 | D30: =MIN(IF(C$1=0,MthRem,12), MAX(Inputs!$G$147-IF(C$1=0,0,C$1*12+MthOff), 0))*Inputs!$B$149 -> 1440 | E30: =MIN(IF(D$1=0,MthRem,12), MAX(Inputs!$G$147-IF(D$1=0,0,D$1*12+MthOff), 0))*Inputs!$B$149 -> 1440 | F30: =MIN(IF(E$1=0,MthRem,12), MAX(Inputs!$G$147-IF(E$1=0,0,E$1*12+MthOff), 0))*Inputs!$B$149 -> 1440 | G30: =MIN(IF(F$1=0,MthRem,12), MAX(Inputs!$G$147-IF(F$1=0,0,F$1*12+MthOff), 0))*Inputs!$B$149 -> 1440 | H30: =MIN(IF(G$1=0,MthRem,12), MAX(Inputs!$G$147-IF(G$1=0,0,G$1*12+MthOff), 0))*Inputs!$B$149 -> 1440 | I30: =MIN(IF(H$1=0,MthRem,12), MAX(Inputs!$G$147-IF(H$1=0,0,H$1*12+MthOff), 0))*Inputs!$B$149 -> 1440 | J30: =MIN(IF(I$1=0,MthRem,12), MAX(Inputs!$G$147-IF(I$1=0,0,I$1*12+MthOff), 0))*Inputs!$B$149 -> 789.24881 | ... AM30: =MIN(IF(AL$1=0,MthRem,12), MAX(Inputs!$G$147-IF(AL$1=0,0,AL$1*12+MthOff), 0))*Inputs!$B$149 -> 0
A31: =TEXT(Inputs!$B$87,"") -> Jewelry | C31: =MIN(IF(B$1=0,MthRem,12), MAX(Inputs!$G$152-IF(B$1=0,0,B$1*12+MthOff), 0))*Inputs!$B$154 -> 750 | D31: =MIN(IF(C$1=0,MthRem,12), MAX(Inputs!$G$152-IF(C$1=0,0,C$1*12+MthOff), 0))*Inputs!$B$154 -> 900 | E31: =MIN(IF(D$1=0,MthRem,12), MAX(Inputs!$G$152-IF(D$1=0,0,D$1*12+MthOff), 0))*Inputs!$B$154 -> 900 | F31: =MIN(IF(E$1=0,MthRem,12), MAX(Inputs!$G$152-IF(E$1=0,0,E$1*12+MthOff), 0))*Inputs!$B$154 -> 63.602878 | G31: =MIN(IF(F$1=0,MthRem,12), MAX(Inputs!$G$152-IF(F$1=0,0,F$1*12+MthOff), 0))*Inputs!$B$154 -> 0 | H31: =MIN(IF(G$1=0,MthRem,12), MAX(Inputs!$G$152-IF(G$1=0,0,G$1*12+MthOff), 0))*Inputs!$B$154 -> 0 | I31: =MIN(IF(H$1=0,MthRem,12), MAX(Inputs!$G$152-IF(H$1=0,0,H$1*12+MthOff), 0))*Inputs!$B$154 -> 0 | J31: =MIN(IF(I$1=0,MthRem,12), MAX(Inputs!$G$152-IF(I$1=0,0,I$1*12+MthOff), 0))*Inputs!$B$154 -> 0 | ... AM31: =MIN(IF(AL$1=0,MthRem,12), MAX(Inputs!$G$152-IF(AL$1=0,0,AL$1*12+MthOff), 0))*Inputs!$B$154 -> 0
A32: =TEXT(Inputs!$B$92,"") -> Car | C32: =MIN(IF(B$1=0,MthRem,12), MAX(Inputs!$G$157-IF(B$1=0,0,B$1*12+MthOff), 0))*Inputs!$B$159 -> 860 | D32: =MIN(IF(C$1=0,MthRem,12), MAX(Inputs!$G$157-IF(C$1=0,0,C$1*12+MthOff), 0))*Inputs!$B$159 -> 1032 | E32: =MIN(IF(D$1=0,MthRem,12), MAX(Inputs!$G$157-IF(D$1=0,0,D$1*12+MthOff), 0))*Inputs!$B$159 -> 1032 | F32: =MIN(IF(E$1=0,MthRem,12), MAX(Inputs!$G$157-IF(E$1=0,0,E$1*12+MthOff), 0))*Inputs!$B$159 -> 1032 | G32: =MIN(IF(F$1=0,MthRem,12), MAX(Inputs!$G$157-IF(F$1=0,0,F$1*12+MthOff), 0))*Inputs!$B$159 -> 1032 | H32: =MIN(IF(G$1=0,MthRem,12), MAX(Inputs!$G$157-IF(G$1=0,0,G$1*12+MthOff), 0))*Inputs!$B$159 -> 1032 | I32: =MIN(IF(H$1=0,MthRem,12), MAX(Inputs!$G$157-IF(H$1=0,0,H$1*12+MthOff), 0))*Inputs!$B$159 -> 363.79405 | J32: =MIN(IF(I$1=0,MthRem,12), MAX(Inputs!$G$157-IF(I$1=0,0,I$1*12+MthOff), 0))*Inputs!$B$159 -> 0 | ... AM32: =MIN(IF(AL$1=0,MthRem,12), MAX(Inputs!$G$157-IF(AL$1=0,0,AL$1*12+MthOff), 0))*Inputs!$B$159 -> 0
A33: =TEXT(Inputs!$B$97,"") -> Painting | C33: =MIN(IF(B$1=0,MthRem,12), MAX(Inputs!$G$162-IF(B$1=0,0,B$1*12+MthOff), 0))*Inputs!$B$164 -> 1250 | D33: =MIN(IF(C$1=0,MthRem,12), MAX(Inputs!$G$162-IF(C$1=0,0,C$1*12+MthOff), 0))*Inputs!$B$164 -> 1500 | E33: =MIN(IF(D$1=0,MthRem,12), MAX(Inputs!$G$162-IF(D$1=0,0,D$1*12+MthOff), 0))*Inputs!$B$164 -> 1500 | F33: =MIN(IF(E$1=0,MthRem,12), MAX(Inputs!$G$162-IF(E$1=0,0,E$1*12+MthOff), 0))*Inputs!$B$164 -> 1500 | G33: =MIN(IF(F$1=0,MthRem,12), MAX(Inputs!$G$162-IF(F$1=0,0,F$1*12+MthOff), 0))*Inputs!$B$164 -> 1500 | H33: =MIN(IF(G$1=0,MthRem,12), MAX(Inputs!$G$162-IF(G$1=0,0,G$1*12+MthOff), 0))*Inputs!$B$164 -> 1398.4298 | I33: =MIN(IF(H$1=0,MthRem,12), MAX(Inputs!$G$162-IF(H$1=0,0,H$1*12+MthOff), 0))*Inputs!$B$164 -> 0 | J33: =MIN(IF(I$1=0,MthRem,12), MAX(Inputs!$G$162-IF(I$1=0,0,I$1*12+MthOff), 0))*Inputs!$B$164 -> 0 | ... AM33: =MIN(IF(AL$1=0,MthRem,12), MAX(Inputs!$G$162-IF(AL$1=0,0,AL$1*12+MthOff), 0))*Inputs!$B$164 -> 0
A34: =TEXT(Inputs!$B$102,"") -> Boat | C34: =MIN(IF(B$1=0,MthRem,12), MAX(Inputs!$G$167-IF(B$1=0,0,B$1*12+MthOff), 0))*Inputs!$B$169 -> 6240 | D34: =MIN(IF(C$1=0,MthRem,12), MAX(Inputs!$G$167-IF(C$1=0,0,C$1*12+MthOff), 0))*Inputs!$B$169 -> 7488 | E34: =MIN(IF(D$1=0,MthRem,12), MAX(Inputs!$G$167-IF(D$1=0,0,D$1*12+MthOff), 0))*Inputs!$B$169 -> 7488 | F34: =MIN(IF(E$1=0,MthRem,12), MAX(Inputs!$G$167-IF(E$1=0,0,E$1*12+MthOff), 0))*Inputs!$B$169 -> 7488 | G34: =MIN(IF(F$1=0,MthRem,12), MAX(Inputs!$G$167-IF(F$1=0,0,F$1*12+MthOff), 0))*Inputs!$B$169 -> 7488 | H34: =MIN(IF(G$1=0,MthRem,12), MAX(Inputs!$G$167-IF(G$1=0,0,G$1*12+MthOff), 0))*Inputs!$B$169 -> 7488 | I34: =MIN(IF(H$1=0,MthRem,12), MAX(Inputs!$G$167-IF(H$1=0,0,H$1*12+MthOff), 0))*Inputs!$B$169 -> 4665.2926 | J34: =MIN(IF(I$1=0,MthRem,12), MAX(Inputs!$G$167-IF(I$1=0,0,I$1*12+MthOff), 0))*Inputs!$B$169 -> 0 | ... AM34: =MIN(IF(AL$1=0,MthRem,12), MAX(Inputs!$G$167-IF(AL$1=0,0,AL$1*12+MthOff), 0))*Inputs!$B$169 -> 0
A35: =TEXT(Inputs!$B$107,"") -> Antiques | C35: =MIN(IF(B$1=0,MthRem,12), MAX(Inputs!$G$172-IF(B$1=0,0,B$1*12+MthOff), 0))*Inputs!$B$174 -> 1100 | D35: =MIN(IF(C$1=0,MthRem,12), MAX(Inputs!$G$172-IF(C$1=0,0,C$1*12+MthOff), 0))*Inputs!$B$174 -> 1320 | E35: =MIN(IF(D$1=0,MthRem,12), MAX(Inputs!$G$172-IF(D$1=0,0,D$1*12+MthOff), 0))*Inputs!$B$174 -> 1320 | F35: =MIN(IF(E$1=0,MthRem,12), MAX(Inputs!$G$172-IF(E$1=0,0,E$1*12+MthOff), 0))*Inputs!$B$174 -> 239.16176 | G35: =MIN(IF(F$1=0,MthRem,12), MAX(Inputs!$G$172-IF(F$1=0,0,F$1*12+MthOff), 0))*Inputs!$B$174 -> 0 | H35: =MIN(IF(G$1=0,MthRem,12), MAX(Inputs!$G$172-IF(G$1=0,0,G$1*12+MthOff), 0))*Inputs!$B$174 -> 0 | I35: =MIN(IF(H$1=0,MthRem,12), MAX(Inputs!$G$172-IF(H$1=0,0,H$1*12+MthOff), 0))*Inputs!$B$174 -> 0 | J35: =MIN(IF(I$1=0,MthRem,12), MAX(Inputs!$G$172-IF(I$1=0,0,I$1*12+MthOff), 0))*Inputs!$B$174 -> 0 | ... AM35: =MIN(IF(AL$1=0,MthRem,12), MAX(Inputs!$G$172-IF(AL$1=0,0,AL$1*12+MthOff), 0))*Inputs!$B$174 -> 0
A36: Other loan repayment | C36: =MIN(IF(B$1=0,MthRem,12), MAX(Inputs!$G$177-IF(B$1=0,0,B$1*12+MthOff), 0))*Inputs!$B$179 -> 500 | D36: =MIN(IF(C$1=0,MthRem,12), MAX(Inputs!$G$177-IF(C$1=0,0,C$1*12+MthOff), 0))*Inputs!$B$179 -> 600 | E36: =MIN(IF(D$1=0,MthRem,12), MAX(Inputs!$G$177-IF(D$1=0,0,D$1*12+MthOff), 0))*Inputs!$B$179 -> 600 | F36: =MIN(IF(E$1=0,MthRem,12), MAX(Inputs!$G$177-IF(E$1=0,0,E$1*12+MthOff), 0))*Inputs!$B$179 -> 600 | G36: =MIN(IF(F$1=0,MthRem,12), MAX(Inputs!$G$177-IF(F$1=0,0,F$1*12+MthOff), 0))*Inputs!$B$179 -> 600 | H36: =MIN(IF(G$1=0,MthRem,12), MAX(Inputs!$G$177-IF(G$1=0,0,G$1*12+MthOff), 0))*Inputs!$B$179 -> 600 | I36: =MIN(IF(H$1=0,MthRem,12), MAX(Inputs!$G$177-IF(H$1=0,0,H$1*12+MthOff), 0))*Inputs!$B$179 -> 600 | J36: =MIN(IF(I$1=0,MthRem,12), MAX(Inputs!$G$177-IF(I$1=0,0,I$1*12+MthOff), 0))*Inputs!$B$179 -> 600 | ... AM36: =MIN(IF(AL$1=0,MthRem,12), MAX(Inputs!$G$177-IF(AL$1=0,0,AL$1*12+MthOff), 0))*Inputs!$B$179 -> 0
A37: Dependents cost
A38: =TEXT(Inputs!B33,"") -> John | C38: =IF(Inputs!$B$35>=C$1,Inputs!$B$34,0)*(1+inf)^B$1*ProRate -> 1666.6667 | D38: =IF(Inputs!$B$35>=D$1,Inputs!$B$34,0)*(1+inf)^C$1 -> 2050 | E38: =IF(Inputs!$B$35>=E$1,Inputs!$B$34,0)*(1+inf)^D$1 -> 2101.25 | F38: =IF(Inputs!$B$35>=F$1,Inputs!$B$34,0)*(1+inf)^E$1 -> 0 | G38: =IF(Inputs!$B$35>=G$1,Inputs!$B$34,0)*(1+inf)^F$1 -> 0 | H38: =IF(Inputs!$B$35>=H$1,Inputs!$B$34,0)*(1+inf)^G$1 -> 0 | I38: =IF(Inputs!$B$35>=I$1,Inputs!$B$34,0)*(1+inf)^H$1 -> 0 | J38: =IF(Inputs!$B$35>=J$1,Inputs!$B$34,0)*(1+inf)^I$1 -> 0 | K38: =IF(Inputs!$B$35>=K$1,Inputs!$B$34,0)*(1+inf)^J$1 -> 0 | ... AM38: =IF(Inputs!$B$35>=AM$1,Inputs!$B$34,0)*(1+inf)^AL$1 -> 0
A39: =TEXT(Inputs!B38,"") -> Jack | C39: =IF(Inputs!$B$40>=C$1,Inputs!$B$39,0)*(1+inf)^B$1*ProRate -> 833.33333 | D39: =IF(Inputs!$B$40>=D$1,Inputs!$B$39,0)*(1+inf)^C$1 -> 1025 | E39: =IF(Inputs!$B$40>=E$1,Inputs!$B$39,0)*(1+inf)^D$1 -> 1050.625 | F39: =IF(Inputs!$B$40>=F$1,Inputs!$B$39,0)*(1+inf)^E$1 -> 1076.8906 | G39: =IF(Inputs!$B$40>=G$1,Inputs!$B$39,0)*(1+inf)^F$1 -> 1103.8129 | H39: =IF(Inputs!$B$40>=H$1,Inputs!$B$39,0)*(1+inf)^G$1 -> 0 | I39: =IF(Inputs!$B$40>=I$1,Inputs!$B$39,0)*(1+inf)^H$1 -> 0 | J39: =IF(Inputs!$B$40>=J$1,Inputs!$B$39,0)*(1+inf)^I$1 -> 0 | K39: =IF(Inputs!$B$40>=K$1,Inputs!$B$39,0)*(1+inf)^J$1 -> 0 | ... AM39: =IF(Inputs!$B$40>=AM$1,Inputs!$B$39,0)*(1+inf)^AL$1 -> 0
A40: =TEXT(Inputs!B43,"") -> Bill | C40: =IF(Inputs!$B$45>=C$1,Inputs!$B$44,0)*(1+inf)^B$1*ProRate -> 3333.3333 | D40: =IF(Inputs!$B$45>=D$1,Inputs!$B$44,0)*(1+inf)^C$1 -> 4100 | E40: =IF(Inputs!$B$45>=E$1,Inputs!$B$44,0)*(1+inf)^D$1 -> 0 | F40: =IF(Inputs!$B$45>=F$1,Inputs!$B$44,0)*(1+inf)^E$1 -> 0 | G40: =IF(Inputs!$B$45>=G$1,Inputs!$B$44,0)*(1+inf)^F$1 -> 0 | H40: =IF(Inputs!$B$45>=H$1,Inputs!$B$44,0)*(1+inf)^G$1 -> 0 | I40: =IF(Inputs!$B$45>=I$1,Inputs!$B$44,0)*(1+inf)^H$1 -> 0 | J40: =IF(Inputs!$B$45>=J$1,Inputs!$B$44,0)*(1+inf)^I$1 -> 0 | K40: =IF(Inputs!$B$45>=K$1,Inputs!$B$44,0)*(1+inf)^J$1 -> 0 | ... AM40: =IF(Inputs!$B$45>=AM$1,Inputs!$B$44,0)*(1+inf)^AL$1 -> 0
A41: =TEXT(Inputs!B48,"") -> Stephen | C41: =IF(Inputs!$B$50>=C$1,Inputs!$B$49,0)*(1+inf)^B$1*ProRate -> 2083.3333 | D41: =IF(Inputs!$B$50>=D$1,Inputs!$B$49,0)*(1+inf)^C$1 -> 2562.5 | E41: =IF(Inputs!$B$50>=E$1,Inputs!$B$49,0)*(1+inf)^D$1 -> 2626.5625 | F41: =IF(Inputs!$B$50>=F$1,Inputs!$B$49,0)*(1+inf)^E$1 -> 0 | G41: =IF(Inputs!$B$50>=G$1,Inputs!$B$49,0)*(1+inf)^F$1 -> 0 | H41: =IF(Inputs!$B$50>=H$1,Inputs!$B$49,0)*(1+inf)^G$1 -> 0 | I41: =IF(Inputs!$B$50>=I$1,Inputs!$B$49,0)*(1+inf)^H$1 -> 0 | J41: =IF(Inputs!$B$50>=J$1,Inputs!$B$49,0)*(1+inf)^I$1 -> 0 | K41: =IF(Inputs!$B$50>=K$1,Inputs!$B$49,0)*(1+inf)^J$1 -> 0 | ... AM41: =IF(Inputs!$B$50>=AM$1,Inputs!$B$49,0)*(1+inf)^AL$1 -> 0
A42: =TEXT(Inputs!B53,"") -> Jane | C42: =IF(Inputs!$B$55>=C$1,Inputs!$B$54,0)*(1+inf)^B$1*ProRate -> 2383.3333 | D42: =IF(Inputs!$B$55>=D$1,Inputs!$B$54,0)*(1+inf)^C$1 -> 2931.5 | E42: =IF(Inputs!$B$55>=E$1,Inputs!$B$54,0)*(1+inf)^D$1 -> 3004.7875 | F42: =IF(Inputs!$B$55>=F$1,Inputs!$B$54,0)*(1+inf)^E$1 -> 3079.9072 | G42: =IF(Inputs!$B$55>=G$1,Inputs!$B$54,0)*(1+inf)^F$1 -> 3156.9049 | H42: =IF(Inputs!$B$55>=H$1,Inputs!$B$54,0)*(1+inf)^G$1 -> 3235.8275 | I42: =IF(Inputs!$B$55>=I$1,Inputs!$B$54,0)*(1+inf)^H$1 -> 0 | J42: =IF(Inputs!$B$55>=J$1,Inputs!$B$54,0)*(1+inf)^I$1 -> 0 | K42: =IF(Inputs!$B$55>=K$1,Inputs!$B$54,0)*(1+inf)^J$1 -> 0 | ... AM42: =IF(Inputs!$B$55>=AM$1,Inputs!$B$54,0)*(1+inf)^AL$1 -> 0
A43: Housing rent | C43: =Inputs!$B$23*(1+inf)^B$1*ProRate -> 0 | D43: =Inputs!$B$23*(1+inf)^C$1 -> 0 | E43: =Inputs!$B$23*(1+inf)^D$1 -> 0 | F43: =Inputs!$B$23*(1+inf)^E$1 -> 0 | G43: =Inputs!$B$23*(1+inf)^F$1 -> 0 | H43: =Inputs!$B$23*(1+inf)^G$1 -> 0 | I43: =Inputs!$B$23*(1+inf)^H$1 -> 0 | J43: =Inputs!$B$23*(1+inf)^I$1 -> 0 | K43: =Inputs!$B$23*(1+inf)^J$1 -> 0 | ... AM43: =Inputs!$B$23*(1+inf)^AL$1 -> 0
A44: Other property costs
A45: =TEXT(Inputs!$B$60,"") -> Sliema | C45: =Inputs!$B62*(1+inf)^B$1*ProRate -> 4166.6667 | D45: =Inputs!$B62*(1+inf)^C$1 -> 5125 | E45: =Inputs!$B62*(1+inf)^D$1 -> 5253.125 | F45: =Inputs!$B62*(1+inf)^E$1 -> 5384.4531 | G45: =Inputs!$B62*(1+inf)^F$1 -> 5519.0645 | H45: =Inputs!$B62*(1+inf)^G$1 -> 5657.0411 | I45: =Inputs!$B62*(1+inf)^H$1 -> 5798.4671 | J45: =Inputs!$B62*(1+inf)^I$1 -> 5943.4288 | K45: =Inputs!$B62*(1+inf)^J$1 -> 6092.0145 | ... AM45: =Inputs!$B62*(1+inf)^AL$1 -> 12162.677
A46: =TEXT(Inputs!$B$65,"") -> Gzira | C46: =Inputs!$B67*(1+inf)^B$1*ProRate -> 1666.6667 | D46: =Inputs!$B67*(1+inf)^C$1 -> 2050 | E46: =Inputs!$B67*(1+inf)^D$1 -> 2101.25 | F46: =Inputs!$B67*(1+inf)^E$1 -> 2153.7812 | G46: =Inputs!$B67*(1+inf)^F$1 -> 2207.6258 | H46: =Inputs!$B67*(1+inf)^G$1 -> 2262.8164 | I46: =Inputs!$B67*(1+inf)^H$1 -> 2319.3868 | J46: =Inputs!$B67*(1+inf)^I$1 -> 2377.3715 | K46: =Inputs!$B67*(1+inf)^J$1 -> 2436.8058 | ... AM46: =Inputs!$B67*(1+inf)^AL$1 -> 4865.0706
A47: =TEXT(Inputs!$B$70,"") -> Qormi | C47: =Inputs!$B72*(1+inf)^B$1*ProRate -> 1000 | D47: =Inputs!$B72*(1+inf)^C$1 -> 1230 | E47: =Inputs!$B72*(1+inf)^D$1 -> 1260.75 | F47: =Inputs!$B72*(1+inf)^E$1 -> 1292.2687 | G47: =Inputs!$B72*(1+inf)^F$1 -> 1324.5755 | H47: =Inputs!$B72*(1+inf)^G$1 -> 1357.6899 | I47: =Inputs!$B72*(1+inf)^H$1 -> 1391.6321 | J47: =Inputs!$B72*(1+inf)^I$1 -> 1426.4229 | K47: =Inputs!$B72*(1+inf)^J$1 -> 1462.0835 | ... AM47: =Inputs!$B72*(1+inf)^AL$1 -> 2919.0424
A48: =TEXT(Inputs!$B$75,"") -> Gudja | C48: =Inputs!$B77*(1+inf)^B$1*ProRate -> 833.33333 | D48: =Inputs!$B77*(1+inf)^C$1 -> 1025 | E48: =Inputs!$B77*(1+inf)^D$1 -> 1050.625 | F48: =Inputs!$B77*(1+inf)^E$1 -> 1076.8906 | G48: =Inputs!$B77*(1+inf)^F$1 -> 1103.8129 | H48: =Inputs!$B77*(1+inf)^G$1 -> 1131.4082 | I48: =Inputs!$B77*(1+inf)^H$1 -> 1159.6934 | J48: =Inputs!$B77*(1+inf)^I$1 -> 1188.6858 | K48: =Inputs!$B77*(1+inf)^J$1 -> 1218.4029 | ... AM48: =Inputs!$B77*(1+inf)^AL$1 -> 2432.5353
A49: =TEXT(Inputs!$B$80,"") -> Marsa | C49: =Inputs!$B82*(1+inf)^B$1*ProRate -> 666.66667 | D49: =Inputs!$B82*(1+inf)^C$1 -> 820 | E49: =Inputs!$B82*(1+inf)^D$1 -> 840.5 | F49: =Inputs!$B82*(1+inf)^E$1 -> 861.5125 | G49: =Inputs!$B82*(1+inf)^F$1 -> 883.05031 | H49: =Inputs!$B82*(1+inf)^G$1 -> 905.12657 | I49: =Inputs!$B82*(1+inf)^H$1 -> 927.75473 | J49: =Inputs!$B82*(1+inf)^I$1 -> 950.9486 | K49: =Inputs!$B82*(1+inf)^J$1 -> 974.72232 | ... AM49: =Inputs!$B82*(1+inf)^AL$1 -> 1946.0283
A50: Living expenses
A51: Current baseline | C51: =Inputs!$B$25*(1+inf)^B$1*ProRate -> 41666.667 | D51: =Inputs!$B$25*(1+inf)^C$1 -> 51250 | E51: =Inputs!$B$25*(1+inf)^D$1 -> 52531.25 | F51: =Inputs!$B$25*(1+inf)^E$1 -> 53844.531 | G51: =Inputs!$B$25*(1+inf)^F$1 -> 55190.645 | H51: =Inputs!$B$25*(1+inf)^G$1 -> 56570.411 | I51: =Inputs!$B$25*(1+inf)^H$1 -> 57984.671 | J51: =Inputs!$B$25*(1+inf)^I$1 -> 59434.288 | K51: =Inputs!$B$25*(1+inf)^J$1 -> 60920.145 | ... AM51: =Inputs!$B$25*(1+inf)^AL$1 -> 121626.77
A52: ="Adjustment "&Inputs!A247 -> Adjustment from now to 65 | C52: =IF(C$3<=65,Inputs!$B$247*C$51,0) -> 0 | D52: =IF(D$3<=65,Inputs!$B$247*D$51,0) -> 0 | E52: =IF(E$3<=65,Inputs!$B$247*E$51,0) -> 0 | F52: =IF(F$3<=65,Inputs!$B$247*F$51,0) -> 0 | G52: =IF(G$3<=65,Inputs!$B$247*G$51,0) -> 0 | H52: =IF(H$3<=65,Inputs!$B$247*H$51,0) -> 0 | I52: =IF(I$3<=65,Inputs!$B$247*I$51,0) -> 0 | J52: =IF(J$3<=65,Inputs!$B$247*J$51,0) -> 0 | ... AM52: =IF(AM$3<=65,Inputs!$B$247*AM$51,0) -> 0
A53: ="Adjustment "&Inputs!A248 -> Adjustment from 66-75 | C53: =IF(AND(C$3>65,C$3<=75),Inputs!$B$248*C51,0) -> 0 | D53: =IF(AND(D$3>65,D$3<=75),Inputs!$B$248*D51,0) -> 0 | E53: =IF(AND(E$3>65,E$3<=75),Inputs!$B$248*E51,0) -> 0 | F53: =IF(AND(F$3>65,F$3<=75),Inputs!$B$248*F51,0) -> 0 | G53: =IF(AND(G$3>65,G$3<=75),Inputs!$B$248*G51,0) -> 0 | H53: =IF(AND(H$3>65,H$3<=75),Inputs!$B$248*H51,0) -> 0 | I53: =IF(AND(I$3>65,I$3<=75),Inputs!$B$248*I51,0) -> 0 | J53: =IF(AND(J$3>65,J$3<=75),Inputs!$B$248*J51,0) -> 0 | ... AM53: =IF(AND(AM$3>65,AM$3<=75),Inputs!$B$248*AM51,0) -> 0
A54: ="Adjustment "&Inputs!A249 -> Adjustment from age 76 | C54: =IF(C$3>75,Inputs!$B$249*C$51,0) -> 0 | D54: =IF(D$3>75,Inputs!$B$249*D$51,0) -> 0 | E54: =IF(E$3>75,Inputs!$B$249*E$51,0) -> 0 | F54: =IF(F$3>75,Inputs!$B$249*F$51,0) -> 0 | G54: =IF(G$3>75,Inputs!$B$249*G$51,0) -> 0 | H54: =IF(H$3>75,Inputs!$B$249*H$51,0) -> 0 | I54: =IF(I$3>75,Inputs!$B$249*I$51,0) -> 0 | J54: =IF(J$3>75,Inputs!$B$249*J$51,0) -> 0 | ... AM54: =IF(AM$3>75,Inputs!$B$249*AM$51,0) -> -24325.353
A55: Major one-off expense events
A56: =TEXT(Inputs!$B$201,"") -> Wedding | C56: =IF(C$2=Inputs!$B203,Inputs!$B202,0)*(1+inf)^B$1 -> 0 | D56: =IF(D$2=Inputs!$B203,Inputs!$B202,0)*(1+inf)^C$1 -> 0 | E56: =IF(E$2=Inputs!$B203,Inputs!$B202,0)*(1+inf)^D$1 -> 0 | F56: =IF(F$2=Inputs!$B203,Inputs!$B202,0)*(1+inf)^E$1 -> 0 | G56: =IF(G$2=Inputs!$B203,Inputs!$B202,0)*(1+inf)^F$1 -> 0 | H56: =IF(H$2=Inputs!$B203,Inputs!$B202,0)*(1+inf)^G$1 -> 0 | I56: =IF(I$2=Inputs!$B203,Inputs!$B202,0)*(1+inf)^H$1 -> 0 | J56: =IF(J$2=Inputs!$B203,Inputs!$B202,0)*(1+inf)^I$1 -> 0 | ... AM56: =IF(AM$2=Inputs!$B203,Inputs!$B202,0)*(1+inf)^AL$1 -> 0
A57: =TEXT(Inputs!$B$206,"") -> New Car | C57: =IF(C$2=Inputs!$B208,Inputs!$B207,0)*(1+inf)^B$1 -> 0 | D57: =IF(D$2=Inputs!$B208,Inputs!$B207,0)*(1+inf)^C$1 -> 0 | E57: =IF(E$2=Inputs!$B208,Inputs!$B207,0)*(1+inf)^D$1 -> 0 | F57: =IF(F$2=Inputs!$B208,Inputs!$B207,0)*(1+inf)^E$1 -> 37691.172 | G57: =IF(G$2=Inputs!$B208,Inputs!$B207,0)*(1+inf)^F$1 -> 0 | H57: =IF(H$2=Inputs!$B208,Inputs!$B207,0)*(1+inf)^G$1 -> 0 | I57: =IF(I$2=Inputs!$B208,Inputs!$B207,0)*(1+inf)^H$1 -> 0 | J57: =IF(J$2=Inputs!$B208,Inputs!$B207,0)*(1+inf)^I$1 -> 0 | ... AM57: =IF(AM$2=Inputs!$B208,Inputs!$B207,0)*(1+inf)^AL$1 -> 0
A58: =TEXT(Inputs!$B$211,"") -> New AC | C58: =IF(C$2=Inputs!$B213,Inputs!$B212,0)*(1+inf)^B$1 -> 0 | D58: =IF(D$2=Inputs!$B213,Inputs!$B212,0)*(1+inf)^C$1 -> 0 | E58: =IF(E$2=Inputs!$B213,Inputs!$B212,0)*(1+inf)^D$1 -> 0 | F58: =IF(F$2=Inputs!$B213,Inputs!$B212,0)*(1+inf)^E$1 -> 0 | G58: =IF(G$2=Inputs!$B213,Inputs!$B212,0)*(1+inf)^F$1 -> 0 | H58: =IF(H$2=Inputs!$B213,Inputs!$B212,0)*(1+inf)^G$1 -> 0 | I58: =IF(I$2=Inputs!$B213,Inputs!$B212,0)*(1+inf)^H$1 -> 0 | J58: =IF(J$2=Inputs!$B213,Inputs!$B212,0)*(1+inf)^I$1 -> 0 | ... AM58: =IF(AM$2=Inputs!$B213,Inputs!$B212,0)*(1+inf)^AL$1 -> 0
C59: =SUM(C22:C58) -> 91500 | D59: =SUM(D22:D58) -> 110409 | E59: =SUM(E22:E58) -> 108060.72 | F59: =SUM(F22:F58) -> 140407.57 | G59: =SUM(G22:G58) -> 102109.49 | H59: =SUM(H22:H58) -> 100199.49 | I59: =SUM(I22:I58) -> 82650.692 | J59: =SUM(J22:J58) -> 78710.394 | ... AM59: =SUM(AM22:AM58) -> 121626.77
A61: Net Cash Flow | C61: =C21-C59 -> 12809.375 | D61: =D21-D59 -> 11352.841 | E61: =E21-E59 -> 17651.064 | F61: =F21-F59 -> -9.7104831 | G61: =G21-G59 -> 31721.059 | H61: =H21-H59 -> 38421.138 | I61: =I21-I59 -> 67112.869 | J61: =J21-J59 -> 71123.866 | ... AM61: =AM21-AM59 -> 76541.726
A62: Cash b/fwd | C62: =Inputs!B8 -> 50000 | D62: =C63 -> 62809.375 | E62: =D63 -> 74162.216 | F62: =E63 -> 91813.279 | G62: =F63 -> 91803.569 | H62: =G63 -> 123524.63 | I62: =H63 -> 161945.77 | J62: =I63 -> 229058.63 | K62: =J63 -> 300182.5 | ... AM62: =AL63 -> 2351869.1
A63: Cash c/fwd | C63: =SUM(C61:C62) -> 62809.375 | D63: =SUM(D61:D62) -> 74162.216 | E63: =SUM(E61:E62) -> 91813.279 | F63: =SUM(F61:F62) -> 91803.569 | G63: =SUM(G61:G62) -> 123524.63 | H63: =SUM(H61:H62) -> 161945.77 | I63: =SUM(I61:I62) -> 229058.63 | J63: =SUM(J61:J62) -> 300182.5 | ... AM63: =SUM(AM61:AM62) -> 2428410.8
A65: Net Worth before liquidations
A66: Cash | C66: =C63 -> 62809.375 | D66: =D63 -> 74162.216 | E66: =E63 -> 91813.279 | F66: =F63 -> 91803.569 | G66: =G63 -> 123524.63 | H66: =H63 -> 161945.77 | I66: =I63 -> 229058.63 | J66: =J63 -> 300182.5 | ... AM66: =AM63 -> 2428410.8
A67: Home | C67: =Inputs!B12*(1+princ)^ProRate -> 614962.93 | D67: =C67*(1+princ) -> 633411.82 | E67: =D67*(1+princ) -> 652414.17 | F67: =E67*(1+princ) -> 671986.6 | G67: =F67*(1+princ) -> 692146.2 | H67: =G67*(1+princ) -> 712910.58 | I67: =H67*(1+princ) -> 734297.9 | J67: =I67*(1+princ) -> 756326.84 | K67: =J67*(1+princ) -> 779016.64 | ... AM67: =AL67*(1+princ) -> 1782333.7
A68: Other property
A69: =TEXT(Inputs!$B$60,"") -> Sliema | C69: =Inputs!B61*(1+princ)^ProRate -> 307481.47 | D69: =C69*(1+princ) -> 316705.91 | E69: =D69*(1+princ) -> 326207.09 | F69: =E69*(1+princ) -> 335993.3 | G69: =F69*(1+princ) -> 346073.1 | H69: =G69*(1+princ) -> 356455.29 | I69: =H69*(1+princ) -> 367148.95 | J69: =I69*(1+princ) -> 378163.42 | K69: =J69*(1+princ) -> 389508.32 | ... AM69: =AL69*(1+princ) -> 891166.87
A70: =TEXT(Inputs!$B$65,"") -> Gzira | C70: =Inputs!B66*(1+princ)^ProRate -> 153740.73 | D70: =C70*(1+princ) -> 158352.95 | E70: =D70*(1+princ) -> 163103.54 | F70: =E70*(1+princ) -> 167996.65 | G70: =F70*(1+princ) -> 173036.55 | H70: =G70*(1+princ) -> 178227.65 | I70: =H70*(1+princ) -> 183574.47 | J70: =I70*(1+princ) -> 189081.71 | K70: =J70*(1+princ) -> 194754.16 | ... AM70: =AL70*(1+princ) -> 445583.43
A71: =TEXT(Inputs!$B$70,"") -> Qormi | C71: =Inputs!B71*(1+princ)^ProRate -> 225486.41 | D71: =C71*(1+princ) -> 232251 | E71: =D71*(1+princ) -> 239218.53 | F71: =E71*(1+princ) -> 246395.09 | G71: =F71*(1+princ) -> 253786.94 | H71: =G71*(1+princ) -> 261400.55 | I71: =H71*(1+princ) -> 269242.56 | J71: =I71*(1+princ) -> 277319.84 | K71: =J71*(1+princ) -> 285639.44 | ... AM71: =AL71*(1+princ) -> 653522.37
A72: =TEXT(Inputs!$B$75,"") -> Gudja | C72: =Inputs!B76*(1+princ)^ProRate -> 81995.057 | D72: =C72*(1+princ) -> 84454.909 | E72: =D72*(1+princ) -> 86988.556 | F72: =E72*(1+princ) -> 89598.213 | G72: =F72*(1+princ) -> 92286.159 | H72: =G72*(1+princ) -> 95054.744 | I72: =H72*(1+princ) -> 97906.387 | J72: =I72*(1+princ) -> 100843.58 | K72: =J72*(1+princ) -> 103868.89 | ... AM72: =AL72*(1+princ) -> 237644.5
A73: =TEXT(Inputs!$B$80,"") -> Marsa | C73: =Inputs!B81*(1+princ)^ProRate -> 122992.59 | D73: =C73*(1+princ) -> 126682.36 | E73: =D73*(1+princ) -> 130482.83 | F73: =E73*(1+princ) -> 134397.32 | G73: =F73*(1+princ) -> 138429.24 | H73: =G73*(1+princ) -> 142582.12 | I73: =H73*(1+princ) -> 146859.58 | J73: =I73*(1+princ) -> 151265.37 | K73: =J73*(1+princ) -> 155803.33 | ... AM73: =AL73*(1+princ) -> 356466.75
A74: Other assets of value
A75: =TEXT(Inputs!$B$87,"") -> Jewelry | C75: =Inputs!B88*(1+A1inc)^ProRate -> 50831.955 | D75: =C75*(1+A1inc) -> 51848.594 | E75: =D75*(1+A1inc) -> 52885.566 | F75: =E75*(1+A1inc) -> 53943.277 | G75: =F75*(1+A1inc) -> 55022.143 | H75: =G75*(1+A1inc) -> 56122.586 | I75: =H75*(1+A1inc) -> 57245.038 | J75: =I75*(1+A1inc) -> 58389.938 | K75: =J75*(1+A1inc) -> 59557.737 | ... AM75: =AL75*(1+A1inc) -> 103691.46
A76: =TEXT(Inputs!$B$92,"") -> Car | C76: =Inputs!B93*(1+A2inc)^ProRate -> 38326.25 | D76: =C76*(1+A2inc) -> 36409.938 | E76: =D76*(1+A2inc) -> 34589.441 | F76: =E76*(1+A2inc) -> 32859.969 | G76: =F76*(1+A2inc) -> 31216.97 | H76: =G76*(1+A2inc) -> 29656.122 | I76: =H76*(1+A2inc) -> 28173.316 | J76: =I76*(1+A2inc) -> 26764.65 | K76: =J76*(1+A2inc) -> 25426.417 | ... AM76: =AL76*(1+A2inc) -> 6047.0856
A77: =TEXT(Inputs!$B$97,"") -> Painting | C77: =Inputs!B98*(1+A3inc)^ProRate -> 20498.764 | D77: =C77*(1+A3inc) -> 21113.727 | E77: =D77*(1+A3inc) -> 21747.139 | F77: =E77*(1+A3inc) -> 22399.553 | G77: =F77*(1+A3inc) -> 23071.54 | H77: =G77*(1+A3inc) -> 23763.686 | I77: =H77*(1+A3inc) -> 24476.597 | J77: =I77*(1+A3inc) -> 25210.895 | K77: =J77*(1+A3inc) -> 25967.221 | ... AM77: =AL77*(1+A3inc) -> 59411.124
A78: =TEXT(Inputs!$B$102,"") -> Boat | C78: =Inputs!B103*(1+A4inc)^ProRate -> 172468.13 | D78: =C78*(1+A4inc) -> 163844.72 | E78: =D78*(1+A4inc) -> 155652.48 | F78: =E78*(1+A4inc) -> 147869.86 | G78: =F78*(1+A4inc) -> 140476.37 | H78: =G78*(1+A4inc) -> 133452.55 | I78: =H78*(1+A4inc) -> 126779.92 | J78: =I78*(1+A4inc) -> 120440.92 | K78: =J78*(1+A4inc) -> 114418.88 | ... AM78: =AL78*(1+A4inc) -> 27211.885
A79: =TEXT(Inputs!$B$107,"") -> Antiques | C79: =Inputs!B108*(1+A5inc)^ProRate -> 83364.406 | D79: =C79*(1+A5inc) -> 85031.695 | E79: =D79*(1+A5inc) -> 86732.328 | F79: =E79*(1+A5inc) -> 88466.975 | G79: =F79*(1+A5inc) -> 90236.315 | H79: =G79*(1+A5inc) -> 92041.041 | I79: =H79*(1+A5inc) -> 93881.862 | J79: =I79*(1+A5inc) -> 95759.499 | K79: =J79*(1+A5inc) -> 97674.689 | ... AM79: =AL79*(1+A5inc) -> 170054
A80: Stock market equity investments | C80: =Inputs!B10*(1+stinc)^ProRate -> 31987.064 | D80: =C80*(1+IF(AND(Inputs!$B$218<>"",D$2=Inputs!$B$218),-Inputs!$B$219,IF(AND(Inputs!$B$218<>"",D$2>Inputs!$B$218,D$2<=Inputs!$B$218+Inputs!$B$220),(1/(1-Inputs!$B$219))^(1/Inputs!$B$220)-1,IF(AND(Inputs!$B$223<>"",D$2=Inputs!$B$223),-Inputs!$B$224,IF(AND(Inputs!$B$223<>"",D$2>Inputs!$B$223,D$2<=Inputs!$B$223+Inputs!$B$225),(1/(1-Inputs!$B$224))^(1/Inputs!$B$225)-1,IF(AND(Inputs!$B$228<>"",D$2=Inputs!$B$228),-Inputs!$B$229,IF(AND(Inputs!$B$228<>"",D$2>Inputs!$B$228,D$2<=Inputs!$B$228+Inputs!$B$230),(1/(1-Inputs!$B$229))^(1/Inputs!$B$230)-1,IF(AND(Inputs!$B$233<>"",D$2=Inputs!$B$233),-Inputs!$B$234,IF(AND(Inputs!$B$233<>"",D$2>Inputs!$B$233,D$2<=Inputs!$B$233+Inputs!$B$235),(1/(1-Inputs!$B$234))^(1/Inputs!$B$235)-1,IF(AND(Inputs!$B$238<>"",D$2=Inputs!$B$238),-Inputs!$B$239,IF(AND(Inputs!$B$238<>"",D$2>Inputs!$B$238,D$2<=Inputs!$B$238+Inputs!$B$240),(1/(1-Inputs!$B$239))^(1/Inputs!$B$240)-1,stinc))))))))))) -> 27189.005 | E80: =D80*(1+IF(AND(Inputs!$B$218<>"",E$2=Inputs!$B$218),-Inputs!$B$219,IF(AND(Inputs!$B$218<>"",E$2>Inputs!$B$218,E$2<=Inputs!$B$218+Inputs!$B$220),(1/(1-Inputs!$B$219))^(1/Inputs!$B$220)-1,IF(AND(Inputs!$B$223<>"",E$2=Inputs!$B$223),-Inputs!$B$224,IF(AND(Inputs!$B$223<>"",E$2>Inputs!$B$223,E$2<=Inputs!$B$223+Inputs!$B$225),(1/(1-Inputs!$B$224))^(1/Inputs!$B$225)-1,IF(AND(Inputs!$B$228<>"",E$2=Inputs!$B$228),-Inputs!$B$229,IF(AND(Inputs!$B$228<>"",E$2>Inputs!$B$228,E$2<=Inputs!$B$228+Inputs!$B$230),(1/(1-Inputs!$B$229))^(1/Inputs!$B$230)-1,IF(AND(Inputs!$B$233<>"",E$2=Inputs!$B$233),-Inputs!$B$234,IF(AND(Inputs!$B$233<>"",E$2>Inputs!$B$233,E$2<=Inputs!$B$233+Inputs!$B$235),(1/(1-Inputs!$B$234))^(1/Inputs!$B$235)-1,IF(AND(Inputs!$B$238<>"",E$2=Inputs!$B$238),-Inputs!$B$239,IF(AND(Inputs!$B$238<>"",E$2>Inputs!$B$238,E$2<=Inputs!$B$238+Inputs!$B$240),(1/(1-Inputs!$B$239))^(1/Inputs!$B$240)-1,stinc))))))))))) -> 31987.064 | F80: =E80*(1+IF(AND(Inputs!$B$218<>"",F$2=Inputs!$B$218),-Inputs!$B$219,IF(AND(Inputs!$B$218<>"",F$2>Inputs!$B$218,F$2<=Inputs!$B$218+Inputs!$B$220),(1/(1-Inputs!$B$219))^(1/Inputs!$B$220)-1,IF(AND(Inputs!$B$223<>"",F$2=Inputs!$B$223),-Inputs!$B$224,IF(AND(Inputs!$B$223<>"",F$2>Inputs!$B$223,F$2<=Inputs!$B$223+Inputs!$B$225),(1/(1-Inputs!$B$224))^(1/Inputs!$B$225)-1,IF(AND(Inputs!$B$228<>"",F$2=Inputs!$B$228),-Inputs!$B$229,IF(AND(Inputs!$B$228<>"",F$2>Inputs!$B$228,F$2<=Inputs!$B$228+Inputs!$B$230),(1/(1-Inputs!$B$229))^(1/Inputs!$B$230)-1,IF(AND(Inputs!$B$233<>"",F$2=Inputs!$B$233),-Inputs!$B$234,IF(AND(Inputs!$B$233<>"",F$2>Inputs!$B$233,F$2<=Inputs!$B$233+Inputs!$B$235),(1/(1-Inputs!$B$234))^(1/Inputs!$B$235)-1,IF(AND(Inputs!$B$238<>"",F$2=Inputs!$B$238),-Inputs!$B$239,IF(AND(Inputs!$B$238<>"",F$2>Inputs!$B$238,F$2<=Inputs!$B$238+Inputs!$B$240),(1/(1-Inputs!$B$239))^(1/Inputs!$B$240)-1,stinc))))))))))) -> 34546.03 | G80: =F80*(1+IF(AND(Inputs!$B$218<>"",G$2=Inputs!$B$218),-Inputs!$B$219,IF(AND(Inputs!$B$218<>"",G$2>Inputs!$B$218,G$2<=Inputs!$B$218+Inputs!$B$220),(1/(1-Inputs!$B$219))^(1/Inputs!$B$220)-1,IF(AND(Inputs!$B$223<>"",G$2=Inputs!$B$223),-Inputs!$B$224,IF(AND(Inputs!$B$223<>"",G$2>Inputs!$B$223,G$2<=Inputs!$B$223+Inputs!$B$225),(1/(1-Inputs!$B$224))^(1/Inputs!$B$225)-1,IF(AND(Inputs!$B$228<>"",G$2=Inputs!$B$228),-Inputs!$B$229,IF(AND(Inputs!$B$228<>"",G$2>Inputs!$B$228,G$2<=Inputs!$B$228+Inputs!$B$230),(1/(1-Inputs!$B$229))^(1/Inputs!$B$230)-1,IF(AND(Inputs!$B$233<>"",G$2=Inputs!$B$233),-Inputs!$B$234,IF(AND(Inputs!$B$233<>"",G$2>Inputs!$B$233,G$2<=Inputs!$B$233+Inputs!$B$235),(1/(1-Inputs!$B$234))^(1/Inputs!$B$235)-1,IF(AND(Inputs!$B$238<>"",G$2=Inputs!$B$238),-Inputs!$B$239,IF(AND(Inputs!$B$238<>"",G$2>Inputs!$B$238,G$2<=Inputs!$B$238+Inputs!$B$240),(1/(1-Inputs!$B$239))^(1/Inputs!$B$240)-1,stinc))))))))))) -> 37309.712 | H80: =G80*(1+IF(AND(Inputs!$B$218<>"",H$2=Inputs!$B$218),-Inputs!$B$219,IF(AND(Inputs!$B$218<>"",H$2>Inputs!$B$218,H$2<=Inputs!$B$218+Inputs!$B$220),(1/(1-Inputs!$B$219))^(1/Inputs!$B$220)-1,IF(AND(Inputs!$B$223<>"",H$2=Inputs!$B$223),-Inputs!$B$224,IF(AND(Inputs!$B$223<>"",H$2>Inputs!$B$223,H$2<=Inputs!$B$223+Inputs!$B$225),(1/(1-Inputs!$B$224))^(1/Inputs!$B$225)-1,IF(AND(Inputs!$B$228<>"",H$2=Inputs!$B$228),-Inputs!$B$229,IF(AND(Inputs!$B$228<>"",H$2>Inputs!$B$228,H$2<=Inputs!$B$228+Inputs!$B$230),(1/(1-Inputs!$B$229))^(1/Inputs!$B$230)-1,IF(AND(Inputs!$B$233<>"",H$2=Inputs!$B$233),-Inputs!$B$234,IF(AND(Inputs!$B$233<>"",H$2>Inputs!$B$233,H$2<=Inputs!$B$233+Inputs!$B$235),(1/(1-Inputs!$B$234))^(1/Inputs!$B$235)-1,IF(AND(Inputs!$B$238<>"",H$2=Inputs!$B$238),-Inputs!$B$239,IF(AND(Inputs!$B$238<>"",H$2>Inputs!$B$238,H$2<=Inputs!$B$238+Inputs!$B$240),(1/(1-Inputs!$B$239))^(1/Inputs!$B$240)-1,stinc))))))))))) -> 40294.489 | I80: =H80*(1+IF(AND(Inputs!$B$218<>"",I$2=Inputs!$B$218),-Inputs!$B$219,IF(AND(Inputs!$B$218<>"",I$2>Inputs!$B$218,I$2<=Inputs!$B$218+Inputs!$B$220),(1/(1-Inputs!$B$219))^(1/Inputs!$B$220)-1,IF(AND(Inputs!$B$223<>"",I$2=Inputs!$B$223),-Inputs!$B$224,IF(AND(Inputs!$B$223<>"",I$2>Inputs!$B$223,I$2<=Inputs!$B$223+Inputs!$B$225),(1/(1-Inputs!$B$224))^(1/Inputs!$B$225)-1,IF(AND(Inputs!$B$228<>"",I$2=Inputs!$B$228),-Inputs!$B$229,IF(AND(Inputs!$B$228<>"",I$2>Inputs!$B$228,I$2<=Inputs!$B$228+Inputs!$B$230),(1/(1-Inputs!$B$229))^(1/Inputs!$B$230)-1,IF(AND(Inputs!$B$233<>"",I$2=Inputs!$B$233),-Inputs!$B$234,IF(AND(Inputs!$B$233<>"",I$2>Inputs!$B$233,I$2<=Inputs!$B$233+Inputs!$B$235),(1/(1-Inputs!$B$234))^(1/Inputs!$B$235)-1,IF(AND(Inputs!$B$238<>"",I$2=Inputs!$B$238),-Inputs!$B$239,IF(AND(Inputs!$B$238<>"",I$2>Inputs!$B$238,I$2<=Inputs!$B$238+Inputs!$B$240),(1/(1-Inputs!$B$239))^(1/Inputs!$B$240)-1,stinc))))))))))) -> 32235.591 | J80: =I80*(1+IF(AND(Inputs!$B$218<>"",J$2=Inputs!$B$218),-Inputs!$B$219,IF(AND(Inputs!$B$218<>"",J$2>Inputs!$B$218,J$2<=Inputs!$B$218+Inputs!$B$220),(1/(1-Inputs!$B$219))^(1/Inputs!$B$220)-1,IF(AND(Inputs!$B$223<>"",J$2=Inputs!$B$223),-Inputs!$B$224,IF(AND(Inputs!$B$223<>"",J$2>Inputs!$B$223,J$2<=Inputs!$B$223+Inputs!$B$225),(1/(1-Inputs!$B$224))^(1/Inputs!$B$225)-1,IF(AND(Inputs!$B$228<>"",J$2=Inputs!$B$228),-Inputs!$B$229,IF(AND(Inputs!$B$228<>"",J$2>Inputs!$B$228,J$2<=Inputs!$B$228+Inputs!$B$230),(1/(1-Inputs!$B$229))^(1/Inputs!$B$230)-1,IF(AND(Inputs!$B$233<>"",J$2=Inputs!$B$233),-Inputs!$B$234,IF(AND(Inputs!$B$233<>"",J$2>Inputs!$B$233,J$2<=Inputs!$B$233+Inputs!$B$235),(1/(1-Inputs!$B$234))^(1/Inputs!$B$235)-1,IF(AND(Inputs!$B$238<>"",J$2=Inputs!$B$238),-Inputs!$B$239,IF(AND(Inputs!$B$238<>"",J$2>Inputs!$B$238,J$2<=Inputs!$B$238+Inputs!$B$240),(1/(1-Inputs!$B$239))^(1/Inputs!$B$240)-1,stinc))))))))))) -> 34724.738 | K80: =J80*(1+IF(AND(Inputs!$B$218<>"",K$2=Inputs!$B$218),-Inputs!$B$219,IF(AND(Inputs!$B$218<>"",K$2>Inputs!$B$218,K$2<=Inputs!$B$218+Inputs!$B$220),(1/(1-Inputs!$B$219))^(1/Inputs!$B$220)-1,IF(AND(Inputs!$B$223<>"",K$2=Inputs!$B$223),-Inputs!$B$224,IF(AND(Inputs!$B$223<>"",K$2>Inputs!$B$223,K$2<=Inputs!$B$223+Inputs!$B$225),(1/(1-Inputs!$B$224))^(1/Inputs!$B$225)-1,IF(AND(Inputs!$B$228<>"",K$2=Inputs!$B$228),-Inputs!$B$229,IF(AND(Inputs!$B$228<>"",K$2>Inputs!$B$228,K$2<=Inputs!$B$228+Inputs!$B$230),(1/(1-Inputs!$B$229))^(1/Inputs!$B$230)-1,IF(AND(Inputs!$B$233<>"",K$2=Inputs!$B$233),-Inputs!$B$234,IF(AND(Inputs!$B$233<>"",K$2>Inputs!$B$233,K$2<=Inputs!$B$233+Inputs!$B$235),(1/(1-Inputs!$B$234))^(1/Inputs!$B$235)-1,IF(AND(Inputs!$B$238<>"",K$2=Inputs!$B$238),-Inputs!$B$239,IF(AND(Inputs!$B$238<>"",K$2>Inputs!$B$238,K$2<=Inputs!$B$238+Inputs!$B$240),(1/(1-Inputs!$B$239))^(1/Inputs!$B$240)-1,stinc))))))))))) -> 37406.09 | ... AM80: =AL80*(1+IF(AND(Inputs!$B$218<>"",AM$2=Inputs!$B$218),-Inputs!$B$219,IF(AND(Inputs!$B$218<>"",AM$2>Inputs!$B$218,AM$2<=Inputs!$B$218+Inputs!$B$220),(1/(1-Inputs!$B$219))^(1/Inputs!$B$220)-1,IF(AND(Inputs!$B$223<>"",AM$2=Inputs!$B$223),-Inputs!$B$224,IF(AND(Inputs!$B$223<>"",AM$2>Inputs!$B$223,AM$2<=Inputs!$B$223+Inputs!$B$225),(1/(1-Inputs!$B$224))^(1/Inputs!$B$225)-1,IF(AND(Inputs!$B$228<>"",AM$2=Inputs!$B$228),-Inputs!$B$229,IF(AND(Inputs!$B$228<>"",AM$2>Inputs!$B$228,AM$2<=Inputs!$B$228+Inputs!$B$230),(1/(1-Inputs!$B$229))^(1/Inputs!$B$230)-1,IF(AND(Inputs!$B$233<>"",AM$2=Inputs!$B$233),-Inputs!$B$234,IF(AND(Inputs!$B$233<>"",AM$2>Inputs!$B$233,AM$2<=Inputs!$B$233+Inputs!$B$235),(1/(1-Inputs!$B$234))^(1/Inputs!$B$235)-1,IF(AND(Inputs!$B$238<>"",AM$2=Inputs!$B$238),-Inputs!$B$239,IF(AND(Inputs!$B$238<>"",AM$2>Inputs!$B$238,AM$2<=Inputs!$B$238+Inputs!$B$240),(1/(1-Inputs!$B$239))^(1/Inputs!$B$240)-1,stinc))))))))))) -> 109585.85
A81: Home loan | C81: =-MAX(FV(Inputs!$B16/12,C$1*12+MthOff,Inputs!$B17,-Inputs!$B15),0) -> -43173.554 | D81: =-MAX(FV(Inputs!$B16/12,D$1*12+MthOff,Inputs!$B17,-Inputs!$B15),0) -> -34753.613 | E81: =-MAX(FV(Inputs!$B16/12,E$1*12+MthOff,Inputs!$B17,-Inputs!$B15),0) -> -26077.571 | F81: =-MAX(FV(Inputs!$B16/12,F$1*12+MthOff,Inputs!$B17,-Inputs!$B15),0) -> -17137.639 | G81: =-MAX(FV(Inputs!$B16/12,G$1*12+MthOff,Inputs!$B17,-Inputs!$B15),0) -> -7925.7905 | H81: =-MAX(FV(Inputs!$B16/12,H$1*12+MthOff,Inputs!$B17,-Inputs!$B15),0) -> 0 | I81: =-MAX(FV(Inputs!$B16/12,I$1*12+MthOff,Inputs!$B17,-Inputs!$B15),0) -> 0 | J81: =-MAX(FV(Inputs!$B16/12,J$1*12+MthOff,Inputs!$B17,-Inputs!$B15),0) -> 0 | ... AM81: =-MAX(FV(Inputs!$B16/12,AM$1*12+MthOff,Inputs!$B17,-Inputs!$B15),0) -> 0
A82: Other asset loans
A83: =TEXT(Inputs!$B$60,"") -> Sliema | C83: =-MAX(FV(Inputs!$B128/12,C$1*12+MthOff,Inputs!$B129,-Inputs!$B127),0) -> -46207.53 | D83: =-MAX(FV(Inputs!$B128/12,D$1*12+MthOff,Inputs!$B129,-Inputs!$B127),0) -> -41529.785 | E83: =-MAX(FV(Inputs!$B128/12,E$1*12+MthOff,Inputs!$B129,-Inputs!$B127),0) -> -36709.762 | F83: =-MAX(FV(Inputs!$B128/12,F$1*12+MthOff,Inputs!$B129,-Inputs!$B127),0) -> -31743.133 | G83: =-MAX(FV(Inputs!$B128/12,G$1*12+MthOff,Inputs!$B129,-Inputs!$B127),0) -> -26625.439 | H83: =-MAX(FV(Inputs!$B128/12,H$1*12+MthOff,Inputs!$B129,-Inputs!$B127),0) -> -21352.086 | I83: =-MAX(FV(Inputs!$B128/12,I$1*12+MthOff,Inputs!$B129,-Inputs!$B127),0) -> -15918.339 | J83: =-MAX(FV(Inputs!$B128/12,J$1*12+MthOff,Inputs!$B129,-Inputs!$B127),0) -> -10319.319 | ... AM83: =-MAX(FV(Inputs!$B128/12,AM$1*12+MthOff,Inputs!$B129,-Inputs!$B127),0) -> 0
A84: =TEXT(Inputs!$B$65,"") -> Gzira | C84: =-MAX(FV(Inputs!$B133/12,C$1*12+MthOff,Inputs!$B134,-Inputs!$B132),0) -> -6627.667 | D84: =-MAX(FV(Inputs!$B133/12,D$1*12+MthOff,Inputs!$B134,-Inputs!$B132),0) -> -4339.3195 | E84: =-MAX(FV(Inputs!$B133/12,E$1*12+MthOff,Inputs!$B134,-Inputs!$B132),0) -> -2004.7832 | F84: =-MAX(FV(Inputs!$B133/12,F$1*12+MthOff,Inputs!$B134,-Inputs!$B132),0) -> 0 | G84: =-MAX(FV(Inputs!$B133/12,G$1*12+MthOff,Inputs!$B134,-Inputs!$B132),0) -> 0 | H84: =-MAX(FV(Inputs!$B133/12,H$1*12+MthOff,Inputs!$B134,-Inputs!$B132),0) -> 0 | I84: =-MAX(FV(Inputs!$B133/12,I$1*12+MthOff,Inputs!$B134,-Inputs!$B132),0) -> 0 | J84: =-MAX(FV(Inputs!$B133/12,J$1*12+MthOff,Inputs!$B134,-Inputs!$B132),0) -> 0 | ... AM84: =-MAX(FV(Inputs!$B133/12,AM$1*12+MthOff,Inputs!$B134,-Inputs!$B132),0) -> 0
A85: =TEXT(Inputs!$B$70,"") -> Qormi | C85: =-MAX(FV(Inputs!$B138/12,C$1*12+MthOff,Inputs!$B139,-Inputs!$B137),0) -> -13089.45 | D85: =-MAX(FV(Inputs!$B138/12,D$1*12+MthOff,Inputs!$B139,-Inputs!$B137),0) -> -10689.418 | E85: =-MAX(FV(Inputs!$B138/12,E$1*12+MthOff,Inputs!$B139,-Inputs!$B137),0) -> -8166.5945 | F85: =-MAX(FV(Inputs!$B138/12,F$1*12+MthOff,Inputs!$B139,-Inputs!$B137),0) -> -5514.6991 | G85: =-MAX(FV(Inputs!$B138/12,G$1*12+MthOff,Inputs!$B139,-Inputs!$B137),0) -> -2727.1277 | H85: =-MAX(FV(Inputs!$B138/12,H$1*12+MthOff,Inputs!$B139,-Inputs!$B137),0) -> 0 | I85: =-MAX(FV(Inputs!$B138/12,I$1*12+MthOff,Inputs!$B139,-Inputs!$B137),0) -> 0 | J85: =-MAX(FV(Inputs!$B138/12,J$1*12+MthOff,Inputs!$B139,-Inputs!$B137),0) -> 0 | ... AM85: =-MAX(FV(Inputs!$B138/12,AM$1*12+MthOff,Inputs!$B139,-Inputs!$B137),0) -> 0
A86: =TEXT(Inputs!$B$75,"") -> Gudja | C86: =-MAX(FV(Inputs!$B143/12,C$1*12+MthOff,Inputs!$B144,-Inputs!$B142),0) -> -3952.5609 | D86: =-MAX(FV(Inputs!$B143/12,D$1*12+MthOff,Inputs!$B144,-Inputs!$B142),0) -> -3063.4917 | E86: =-MAX(FV(Inputs!$B143/12,E$1*12+MthOff,Inputs!$B144,-Inputs!$B142),0) -> -2156.4772 | F86: =-MAX(FV(Inputs!$B143/12,F$1*12+MthOff,Inputs!$B144,-Inputs!$B142),0) -> -1231.1552 | G86: =-MAX(FV(Inputs!$B143/12,G$1*12+MthOff,Inputs!$B144,-Inputs!$B142),0) -> -287.15625 | H86: =-MAX(FV(Inputs!$B143/12,H$1*12+MthOff,Inputs!$B144,-Inputs!$B142),0) -> 0 | I86: =-MAX(FV(Inputs!$B143/12,I$1*12+MthOff,Inputs!$B144,-Inputs!$B142),0) -> 0 | J86: =-MAX(FV(Inputs!$B143/12,J$1*12+MthOff,Inputs!$B144,-Inputs!$B142),0) -> 0 | ... AM86: =-MAX(FV(Inputs!$B143/12,AM$1*12+MthOff,Inputs!$B144,-Inputs!$B142),0) -> 0
A87: =TEXT(Inputs!$B$80,"") -> Marsa | C87: =-MAX(FV(Inputs!$B148/12,C$1*12+MthOff,Inputs!$B149,-Inputs!$B147),0) -> -8551.2062 | D87: =-MAX(FV(Inputs!$B148/12,D$1*12+MthOff,Inputs!$B149,-Inputs!$B147),0) -> -7351.3334 | E87: =-MAX(FV(Inputs!$B148/12,E$1*12+MthOff,Inputs!$B149,-Inputs!$B147),0) -> -6114.9653 | F87: =-MAX(FV(Inputs!$B148/12,F$1*12+MthOff,Inputs!$B149,-Inputs!$B147),0) -> -4840.9918 | G87: =-MAX(FV(Inputs!$B148/12,G$1*12+MthOff,Inputs!$B149,-Inputs!$B147),0) -> -3528.2693 | H87: =-MAX(FV(Inputs!$B148/12,H$1*12+MthOff,Inputs!$B149,-Inputs!$B147),0) -> -2175.6191 | I87: =-MAX(FV(Inputs!$B148/12,I$1*12+MthOff,Inputs!$B149,-Inputs!$B147),0) -> -781.82667 | J87: =-MAX(FV(Inputs!$B148/12,J$1*12+MthOff,Inputs!$B149,-Inputs!$B147),0) -> 0 | ... AM87: =-MAX(FV(Inputs!$B148/12,AM$1*12+MthOff,Inputs!$B149,-Inputs!$B147),0) -> 0
A88: =TEXT(Inputs!$B$87,"") -> Jewelry | C88: =-MAX(FV(Inputs!$B153/12,C$1*12+MthOff,Inputs!$B154,-Inputs!$B152),0) -> -1804.7138 | D88: =-MAX(FV(Inputs!$B153/12,D$1*12+MthOff,Inputs!$B154,-Inputs!$B152),0) -> -947.12723 | E88: =-MAX(FV(Inputs!$B153/12,E$1*12+MthOff,Inputs!$B154,-Inputs!$B152),0) -> -63.456301 | F88: =-MAX(FV(Inputs!$B153/12,F$1*12+MthOff,Inputs!$B154,-Inputs!$B152),0) -> 0 | G88: =-MAX(FV(Inputs!$B153/12,G$1*12+MthOff,Inputs!$B154,-Inputs!$B152),0) -> 0 | H88: =-MAX(FV(Inputs!$B153/12,H$1*12+MthOff,Inputs!$B154,-Inputs!$B152),0) -> 0 | I88: =-MAX(FV(Inputs!$B153/12,I$1*12+MthOff,Inputs!$B154,-Inputs!$B152),0) -> 0 | J88: =-MAX(FV(Inputs!$B153/12,J$1*12+MthOff,Inputs!$B154,-Inputs!$B152),0) -> 0 | ... AM88: =-MAX(FV(Inputs!$B153/12,AM$1*12+MthOff,Inputs!$B154,-Inputs!$B152),0) -> 0
A89: =TEXT(Inputs!$B$92,"") -> Car | C89: =-MAX(FV(Inputs!$B158/12,C$1*12+MthOff,Inputs!$B159,-Inputs!$B157),0) -> -5234.2746 | D89: =-MAX(FV(Inputs!$B158/12,D$1*12+MthOff,Inputs!$B159,-Inputs!$B157),0) -> -4298.4123 | E89: =-MAX(FV(Inputs!$B158/12,E$1*12+MthOff,Inputs!$B159,-Inputs!$B157),0) -> -3343.6602 | F89: =-MAX(FV(Inputs!$B158/12,F$1*12+MthOff,Inputs!$B159,-Inputs!$B157),0) -> -2369.6371 | G89: =-MAX(FV(Inputs!$B158/12,G$1*12+MthOff,Inputs!$B159,-Inputs!$B157),0) -> -1375.9539 | H89: =-MAX(FV(Inputs!$B158/12,H$1*12+MthOff,Inputs!$B159,-Inputs!$B157),0) -> -362.21394 | I89: =-MAX(FV(Inputs!$B158/12,I$1*12+MthOff,Inputs!$B159,-Inputs!$B157),0) -> 0 | J89: =-MAX(FV(Inputs!$B158/12,J$1*12+MthOff,Inputs!$B159,-Inputs!$B157),0) -> 0 | ... AM89: =-MAX(FV(Inputs!$B158/12,AM$1*12+MthOff,Inputs!$B159,-Inputs!$B157),0) -> 0
A90: =TEXT(Inputs!$B$97,"") -> Painting | C90: =-MAX(FV(Inputs!$B163/12,C$1*12+MthOff,Inputs!$B164,-Inputs!$B162),0) -> -6544.7251 | D90: =-MAX(FV(Inputs!$B163/12,D$1*12+MthOff,Inputs!$B164,-Inputs!$B162),0) -> -5344.7088 | E90: =-MAX(FV(Inputs!$B163/12,E$1*12+MthOff,Inputs!$B164,-Inputs!$B162),0) -> -4083.2973 | F90: =-MAX(FV(Inputs!$B163/12,F$1*12+MthOff,Inputs!$B164,-Inputs!$B162),0) -> -2757.3496 | G90: =-MAX(FV(Inputs!$B163/12,G$1*12+MthOff,Inputs!$B164,-Inputs!$B162),0) -> -1363.5639 | H90: =-MAX(FV(Inputs!$B163/12,H$1*12+MthOff,Inputs!$B164,-Inputs!$B162),0) -> 0 | I90: =-MAX(FV(Inputs!$B163/12,I$1*12+MthOff,Inputs!$B164,-Inputs!$B162),0) -> 0 | J90: =-MAX(FV(Inputs!$B163/12,J$1*12+MthOff,Inputs!$B164,-Inputs!$B162),0) -> 0 | ... AM90: =-MAX(FV(Inputs!$B163/12,AM$1*12+MthOff,Inputs!$B164,-Inputs!$B162),0) -> 0
A91: =TEXT(Inputs!$B$102,"") -> Boat | C91: =-MAX(FV(Inputs!$B168/12,C$1*12+MthOff,Inputs!$B169,-Inputs!$B167),0) -> -35663.317 | D91: =-MAX(FV(Inputs!$B168/12,D$1*12+MthOff,Inputs!$B169,-Inputs!$B167),0) -> -30165.561 | E91: =-MAX(FV(Inputs!$B168/12,E$1*12+MthOff,Inputs!$B169,-Inputs!$B167),0) -> -24328.716 | F91: =-MAX(FV(Inputs!$B168/12,F$1*12+MthOff,Inputs!$B169,-Inputs!$B167),0) -> -18131.867 | G91: =-MAX(FV(Inputs!$B168/12,G$1*12+MthOff,Inputs!$B169,-Inputs!$B167),0) -> -11552.81 | H91: =-MAX(FV(Inputs!$B168/12,H$1*12+MthOff,Inputs!$B169,-Inputs!$B167),0) -> -4567.9713 | I91: =-MAX(FV(Inputs!$B168/12,I$1*12+MthOff,Inputs!$B169,-Inputs!$B167),0) -> 0 | J91: =-MAX(FV(Inputs!$B168/12,J$1*12+MthOff,Inputs!$B169,-Inputs!$B167),0) -> 0 | ... AM91: =-MAX(FV(Inputs!$B168/12,AM$1*12+MthOff,Inputs!$B169,-Inputs!$B167),0) -> 0
A92: =TEXT(Inputs!$B$107,"") -> Antiques | C92: =-MAX(FV(Inputs!$B173/12,C$1*12+MthOff,Inputs!$B174,-Inputs!$B172),0) -> -2783.618 | D92: =-MAX(FV(Inputs!$B173/12,D$1*12+MthOff,Inputs!$B174,-Inputs!$B172),0) -> -1529.9823 | E92: =-MAX(FV(Inputs!$B173/12,E$1*12+MthOff,Inputs!$B174,-Inputs!$B172),0) -> -238.21612 | F92: =-MAX(FV(Inputs!$B173/12,F$1*12+MthOff,Inputs!$B174,-Inputs!$B172),0) -> 0 | G92: =-MAX(FV(Inputs!$B173/12,G$1*12+MthOff,Inputs!$B174,-Inputs!$B172),0) -> 0 | H92: =-MAX(FV(Inputs!$B173/12,H$1*12+MthOff,Inputs!$B174,-Inputs!$B172),0) -> 0 | I92: =-MAX(FV(Inputs!$B173/12,I$1*12+MthOff,Inputs!$B174,-Inputs!$B172),0) -> 0 | J92: =-MAX(FV(Inputs!$B173/12,J$1*12+MthOff,Inputs!$B174,-Inputs!$B172),0) -> 0 | ... AM92: =-MAX(FV(Inputs!$B173/12,AM$1*12+MthOff,Inputs!$B174,-Inputs!$B172),0) -> 0
A93: Other loan | C93: =-MAX(FV(Inputs!$B178/12,C$1*12+MthOff,Inputs!$B179,-Inputs!$B177),0) -> -3693.1592 | D93: =-MAX(FV(Inputs!$B178/12,D$1*12+MthOff,Inputs!$B179,-Inputs!$B177),0) -> -3304.1671 | E93: =-MAX(FV(Inputs!$B178/12,E$1*12+MthOff,Inputs!$B179,-Inputs!$B177),0) -> -2891.1827 | F93: =-MAX(FV(Inputs!$B178/12,F$1*12+MthOff,Inputs!$B179,-Inputs!$B177),0) -> -2452.7265 | G93: =-MAX(FV(Inputs!$B178/12,G$1*12+MthOff,Inputs!$B179,-Inputs!$B177),0) -> -1987.2271 | H93: =-MAX(FV(Inputs!$B178/12,H$1*12+MthOff,Inputs!$B179,-Inputs!$B177),0) -> -1493.0168 | I93: =-MAX(FV(Inputs!$B178/12,I$1*12+MthOff,Inputs!$B179,-Inputs!$B177),0) -> -968.32473 | J93: =-MAX(FV(Inputs!$B178/12,J$1*12+MthOff,Inputs!$B179,-Inputs!$B177),0) -> -411.27076 | ... AM93: =-MAX(FV(Inputs!$B178/12,AM$1*12+MthOff,Inputs!$B179,-Inputs!$B177),0) -> 0
C94: =SUM(C65:C93) -> 1789619.3 | D94: =SUM(D65:D93) -> 1864141.9 | E94: =SUM(E65:E93) -> 1957643.3 | F94: =SUM(F65:F93) -> 2032077.2 | G94: =SUM(G65:G93) -> 2139242.5 | H94: =SUM(H65:H93) -> 2253956.3 | I94: =SUM(I65:I93) -> 2373212.3 | J94: =SUM(J65:J93) -> 2503743.3 | ... AM94: =SUM(AM65:AM93) -> 7271129.9
A96: Cash available (after buffer) | C96: =C66-buffer -> 12809.375 | D96: =D66-buffer -> 24162.216 | E96: =E66-buffer -> 41813.279 | F96: =F66-buffer -> 41803.569 | G96: =G66-buffer -> 73524.627 | H96: =H66-buffer -> 111945.77 | I96: =I66-buffer -> 179058.63 | J96: =J66-buffer -> 250182.5 | ... AM96: =AM66-buffer -> 2378410.8
A97: Liquidation required | C97: =IF(C96<0,-C96,0) -> 0 | D97: =IF(D96+SUM($C97:C97)<0,-(D96+SUM($C97:C97)),0) -> 0 | E97: =IF(E96+SUM($C97:D97)<0,-(E96+SUM($C97:D97)),0) -> 0 | F97: =IF(F96+SUM($C97:E97)<0,-(F96+SUM($C97:E97)),0) -> 0 | G97: =IF(G96+SUM($C97:F97)<0,-(G96+SUM($C97:F97)),0) -> 0 | H97: =IF(H96+SUM($C97:G97)<0,-(H96+SUM($C97:G97)),0) -> 0 | I97: =IF(I96+SUM($C97:H97)<0,-(I96+SUM($C97:H97)),0) -> 0 | J97: =IF(J96+SUM($C97:I97)<0,-(J96+SUM($C97:I97)),0) -> 0 | K97: =IF(K96+SUM($C97:J97)<0,-(K96+SUM($C97:J97)),0) -> 0 | ... AM97: =IF(AM96+SUM($C97:AL97)<0,-(AM96+SUM($C97:AL97)),0) -> 0
A99: Liquidations
A101: Stock market equity
A102: b/fwd | C102: =C80 -> 31987.064 | D102: =C105 -> 31987.064 | E102: =D105 -> 27189.005 | F102: =E105 -> 31987.064 | G102: =F105 -> 34546.03 | H102: =G105 -> 37309.712 | I102: =H105 -> 40294.489 | J102: =I105 -> 32235.591 | K102: =J105 -> 34724.738 | ... AM102: =AL105 -> 101468.38
A103: Disposals | C103: =-MIN(C102, C97/(1-Inputs!$B$273)) -> 0 | D103: =-MIN(D102, D97/(1-Inputs!$B$273)) -> 0 | E103: =-MIN(E102, E97/(1-Inputs!$B$273)) -> 0 | F103: =-MIN(F102, F97/(1-Inputs!$B$273)) -> 0 | G103: =-MIN(G102, G97/(1-Inputs!$B$273)) -> 0 | H103: =-MIN(H102, H97/(1-Inputs!$B$273)) -> 0 | I103: =-MIN(I102, I97/(1-Inputs!$B$273)) -> 0 | J103: =-MIN(J102, J97/(1-Inputs!$B$273)) -> 0 | ... AM103: =-MIN(AM102, AM97/(1-Inputs!$B$273)) -> 0
A104: Growth | C104: 0 | D104: =SUM(D102:D103)*IF(AND(Inputs!$B$218<>"",D$2=Inputs!$B$218),-Inputs!$B$219,IF(AND(Inputs!$B$218<>"",D$2>Inputs!$B$218,D$2<=Inputs!$B$218+Inputs!$B$220),(1/(1-Inputs!$B$219))^(1/Inputs!$B$220)-1,IF(AND(Inputs!$B$223<>"",D$2=Inputs!$B$223),-Inputs!$B$224,IF(AND(Inputs!$B$223<>"",D$2>Inputs!$B$223,D$2<=Inputs!$B$223+Inputs!$B$225),(1/(1-Inputs!$B$224))^(1/Inputs!$B$225)-1,IF(AND(Inputs!$B$228<>"",D$2=Inputs!$B$228),-Inputs!$B$229,IF(AND(Inputs!$B$228<>"",D$2>Inputs!$B$228,D$2<=Inputs!$B$228+Inputs!$B$230),(1/(1-Inputs!$B$229))^(1/Inputs!$B$230)-1,IF(AND(Inputs!$B$233<>"",D$2=Inputs!$B$233),-Inputs!$B$234,IF(AND(Inputs!$B$233<>"",D$2>Inputs!$B$233,D$2<=Inputs!$B$233+Inputs!$B$235),(1/(1-Inputs!$B$234))^(1/Inputs!$B$235)-1,IF(AND(Inputs!$B$238<>"",D$2=Inputs!$B$238),-Inputs!$B$239,IF(AND(Inputs!$B$238<>"",D$2>Inputs!$B$238,D$2<=Inputs!$B$238+Inputs!$B$240),(1/(1-Inputs!$B$239))^(1/Inputs!$B$240)-1,stinc)))))))))) -> -4798.0597 | E104: =SUM(E102:E103)*IF(AND(Inputs!$B$218<>"",E$2=Inputs!$B$218),-Inputs!$B$219,IF(AND(Inputs!$B$218<>"",E$2>Inputs!$B$218,E$2<=Inputs!$B$218+Inputs!$B$220),(1/(1-Inputs!$B$219))^(1/Inputs!$B$220)-1,IF(AND(Inputs!$B$223<>"",E$2=Inputs!$B$223),-Inputs!$B$224,IF(AND(Inputs!$B$223<>"",E$2>Inputs!$B$223,E$2<=Inputs!$B$223+Inputs!$B$225),(1/(1-Inputs!$B$224))^(1/Inputs!$B$225)-1,IF(AND(Inputs!$B$228<>"",E$2=Inputs!$B$228),-Inputs!$B$229,IF(AND(Inputs!$B$228<>"",E$2>Inputs!$B$228,E$2<=Inputs!$B$228+Inputs!$B$230),(1/(1-Inputs!$B$229))^(1/Inputs!$B$230)-1,IF(AND(Inputs!$B$233<>"",E$2=Inputs!$B$233),-Inputs!$B$234,IF(AND(Inputs!$B$233<>"",E$2>Inputs!$B$233,E$2<=Inputs!$B$233+Inputs!$B$235),(1/(1-Inputs!$B$234))^(1/Inputs!$B$235)-1,IF(AND(Inputs!$B$238<>"",E$2=Inputs!$B$238),-Inputs!$B$239,IF(AND(Inputs!$B$238<>"",E$2>Inputs!$B$238,E$2<=Inputs!$B$238+Inputs!$B$240),(1/(1-Inputs!$B$239))^(1/Inputs!$B$240)-1,stinc)))))))))) -> 4798.0597 | F104: =SUM(F102:F103)*IF(AND(Inputs!$B$218<>"",F$2=Inputs!$B$218),-Inputs!$B$219,IF(AND(Inputs!$B$218<>"",F$2>Inputs!$B$218,F$2<=Inputs!$B$218+Inputs!$B$220),(1/(1-Inputs!$B$219))^(1/Inputs!$B$220)-1,IF(AND(Inputs!$B$223<>"",F$2=Inputs!$B$223),-Inputs!$B$224,IF(AND(Inputs!$B$223<>"",F$2>Inputs!$B$223,F$2<=Inputs!$B$223+Inputs!$B$225),(1/(1-Inputs!$B$224))^(1/Inputs!$B$225)-1,IF(AND(Inputs!$B$228<>"",F$2=Inputs!$B$228),-Inputs!$B$229,IF(AND(Inputs!$B$228<>"",F$2>Inputs!$B$228,F$2<=Inputs!$B$228+Inputs!$B$230),(1/(1-Inputs!$B$229))^(1/Inputs!$B$230)-1,IF(AND(Inputs!$B$233<>"",F$2=Inputs!$B$233),-Inputs!$B$234,IF(AND(Inputs!$B$233<>"",F$2>Inputs!$B$233,F$2<=Inputs!$B$233+Inputs!$B$235),(1/(1-Inputs!$B$234))^(1/Inputs!$B$235)-1,IF(AND(Inputs!$B$238<>"",F$2=Inputs!$B$238),-Inputs!$B$239,IF(AND(Inputs!$B$238<>"",F$2>Inputs!$B$238,F$2<=Inputs!$B$238+Inputs!$B$240),(1/(1-Inputs!$B$239))^(1/Inputs!$B$240)-1,stinc)))))))))) -> 2558.9651 | G104: =SUM(G102:G103)*IF(AND(Inputs!$B$218<>"",G$2=Inputs!$B$218),-Inputs!$B$219,IF(AND(Inputs!$B$218<>"",G$2>Inputs!$B$218,G$2<=Inputs!$B$218+Inputs!$B$220),(1/(1-Inputs!$B$219))^(1/Inputs!$B$220)-1,IF(AND(Inputs!$B$223<>"",G$2=Inputs!$B$223),-Inputs!$B$224,IF(AND(Inputs!$B$223<>"",G$2>Inputs!$B$223,G$2<=Inputs!$B$223+Inputs!$B$225),(1/(1-Inputs!$B$224))^(1/Inputs!$B$225)-1,IF(AND(Inputs!$B$228<>"",G$2=Inputs!$B$228),-Inputs!$B$229,IF(AND(Inputs!$B$228<>"",G$2>Inputs!$B$228,G$2<=Inputs!$B$228+Inputs!$B$230),(1/(1-Inputs!$B$229))^(1/Inputs!$B$230)-1,IF(AND(Inputs!$B$233<>"",G$2=Inputs!$B$233),-Inputs!$B$234,IF(AND(Inputs!$B$233<>"",G$2>Inputs!$B$233,G$2<=Inputs!$B$233+Inputs!$B$235),(1/(1-Inputs!$B$234))^(1/Inputs!$B$235)-1,IF(AND(Inputs!$B$238<>"",G$2=Inputs!$B$238),-Inputs!$B$239,IF(AND(Inputs!$B$238<>"",G$2>Inputs!$B$238,G$2<=Inputs!$B$238+Inputs!$B$240),(1/(1-Inputs!$B$239))^(1/Inputs!$B$240)-1,stinc)))))))))) -> 2763.6824 | H104: =SUM(H102:H103)*IF(AND(Inputs!$B$218<>"",H$2=Inputs!$B$218),-Inputs!$B$219,IF(AND(Inputs!$B$218<>"",H$2>Inputs!$B$218,H$2<=Inputs!$B$218+Inputs!$B$220),(1/(1-Inputs!$B$219))^(1/Inputs!$B$220)-1,IF(AND(Inputs!$B$223<>"",H$2=Inputs!$B$223),-Inputs!$B$224,IF(AND(Inputs!$B$223<>"",H$2>Inputs!$B$223,H$2<=Inputs!$B$223+Inputs!$B$225),(1/(1-Inputs!$B$224))^(1/Inputs!$B$225)-1,IF(AND(Inputs!$B$228<>"",H$2=Inputs!$B$228),-Inputs!$B$229,IF(AND(Inputs!$B$228<>"",H$2>Inputs!$B$228,H$2<=Inputs!$B$228+Inputs!$B$230),(1/(1-Inputs!$B$229))^(1/Inputs!$B$230)-1,IF(AND(Inputs!$B$233<>"",H$2=Inputs!$B$233),-Inputs!$B$234,IF(AND(Inputs!$B$233<>"",H$2>Inputs!$B$233,H$2<=Inputs!$B$233+Inputs!$B$235),(1/(1-Inputs!$B$234))^(1/Inputs!$B$235)-1,IF(AND(Inputs!$B$238<>"",H$2=Inputs!$B$238),-Inputs!$B$239,IF(AND(Inputs!$B$238<>"",H$2>Inputs!$B$238,H$2<=Inputs!$B$238+Inputs!$B$240),(1/(1-Inputs!$B$239))^(1/Inputs!$B$240)-1,stinc)))))))))) -> 2984.777 | I104: =SUM(I102:I103)*IF(AND(Inputs!$B$218<>"",I$2=Inputs!$B$218),-Inputs!$B$219,IF(AND(Inputs!$B$218<>"",I$2>Inputs!$B$218,I$2<=Inputs!$B$218+Inputs!$B$220),(1/(1-Inputs!$B$219))^(1/Inputs!$B$220)-1,IF(AND(Inputs!$B$223<>"",I$2=Inputs!$B$223),-Inputs!$B$224,IF(AND(Inputs!$B$223<>"",I$2>Inputs!$B$223,I$2<=Inputs!$B$223+Inputs!$B$225),(1/(1-Inputs!$B$224))^(1/Inputs!$B$225)-1,IF(AND(Inputs!$B$228<>"",I$2=Inputs!$B$228),-Inputs!$B$229,IF(AND(Inputs!$B$228<>"",I$2>Inputs!$B$228,I$2<=Inputs!$B$228+Inputs!$B$230),(1/(1-Inputs!$B$229))^(1/Inputs!$B$230)-1,IF(AND(Inputs!$B$233<>"",I$2=Inputs!$B$233),-Inputs!$B$234,IF(AND(Inputs!$B$233<>"",I$2>Inputs!$B$233,I$2<=Inputs!$B$233+Inputs!$B$235),(1/(1-Inputs!$B$234))^(1/Inputs!$B$235)-1,IF(AND(Inputs!$B$238<>"",I$2=Inputs!$B$238),-Inputs!$B$239,IF(AND(Inputs!$B$238<>"",I$2>Inputs!$B$238,I$2<=Inputs!$B$238+Inputs!$B$240),(1/(1-Inputs!$B$239))^(1/Inputs!$B$240)-1,stinc)))))))))) -> -8058.8978 | J104: =SUM(J102:J103)*IF(AND(Inputs!$B$218<>"",J$2=Inputs!$B$218),-Inputs!$B$219,IF(AND(Inputs!$B$218<>"",J$2>Inputs!$B$218,J$2<=Inputs!$B$218+Inputs!$B$220),(1/(1-Inputs!$B$219))^(1/Inputs!$B$220)-1,IF(AND(Inputs!$B$223<>"",J$2=Inputs!$B$223),-Inputs!$B$224,IF(AND(Inputs!$B$223<>"",J$2>Inputs!$B$223,J$2<=Inputs!$B$223+Inputs!$B$225),(1/(1-Inputs!$B$224))^(1/Inputs!$B$225)-1,IF(AND(Inputs!$B$228<>"",J$2=Inputs!$B$228),-Inputs!$B$229,IF(AND(Inputs!$B$228<>"",J$2>Inputs!$B$228,J$2<=Inputs!$B$228+Inputs!$B$230),(1/(1-Inputs!$B$229))^(1/Inputs!$B$230)-1,IF(AND(Inputs!$B$233<>"",J$2=Inputs!$B$233),-Inputs!$B$234,IF(AND(Inputs!$B$233<>"",J$2>Inputs!$B$233,J$2<=Inputs!$B$233+Inputs!$B$235),(1/(1-Inputs!$B$234))^(1/Inputs!$B$235)-1,IF(AND(Inputs!$B$238<>"",J$2=Inputs!$B$238),-Inputs!$B$239,IF(AND(Inputs!$B$238<>"",J$2>Inputs!$B$238,J$2<=Inputs!$B$238+Inputs!$B$240),(1/(1-Inputs!$B$239))^(1/Inputs!$B$240)-1,stinc)))))))))) -> 2489.1468 | K104: =SUM(K102:K103)*IF(AND(Inputs!$B$218<>"",K$2=Inputs!$B$218),-Inputs!$B$219,IF(AND(Inputs!$B$218<>"",K$2>Inputs!$B$218,K$2<=Inputs!$B$218+Inputs!$B$220),(1/(1-Inputs!$B$219))^(1/Inputs!$B$220)-1,IF(AND(Inputs!$B$223<>"",K$2=Inputs!$B$223),-Inputs!$B$224,IF(AND(Inputs!$B$223<>"",K$2>Inputs!$B$223,K$2<=Inputs!$B$223+Inputs!$B$225),(1/(1-Inputs!$B$224))^(1/Inputs!$B$225)-1,IF(AND(Inputs!$B$228<>"",K$2=Inputs!$B$228),-Inputs!$B$229,IF(AND(Inputs!$B$228<>"",K$2>Inputs!$B$228,K$2<=Inputs!$B$228+Inputs!$B$230),(1/(1-Inputs!$B$229))^(1/Inputs!$B$230)-1,IF(AND(Inputs!$B$233<>"",K$2=Inputs!$B$233),-Inputs!$B$234,IF(AND(Inputs!$B$233<>"",K$2>Inputs!$B$233,K$2<=Inputs!$B$233+Inputs!$B$235),(1/(1-Inputs!$B$234))^(1/Inputs!$B$235)-1,IF(AND(Inputs!$B$238<>"",K$2=Inputs!$B$238),-Inputs!$B$239,IF(AND(Inputs!$B$238<>"",K$2>Inputs!$B$238,K$2<=Inputs!$B$238+Inputs!$B$240),(1/(1-Inputs!$B$239))^(1/Inputs!$B$240)-1,stinc)))))))))) -> 2681.3521 | ... AM104: =SUM(AM102:AM103)*IF(AND(Inputs!$B$218<>"",AM$2=Inputs!$B$218),-Inputs!$B$219,IF(AND(Inputs!$B$218<>"",AM$2>Inputs!$B$218,AM$2<=Inputs!$B$218+Inputs!$B$220),(1/(1-Inputs!$B$219))^(1/Inputs!$B$220)-1,IF(AND(Inputs!$B$223<>"",AM$2=Inputs!$B$223),-Inputs!$B$224,IF(AND(Inputs!$B$223<>"",AM$2>Inputs!$B$223,AM$2<=Inputs!$B$223+Inputs!$B$225),(1/(1-Inputs!$B$224))^(1/Inputs!$B$225)-1,IF(AND(Inputs!$B$228<>"",AM$2=Inputs!$B$228),-Inputs!$B$229,IF(AND(Inputs!$B$228<>"",AM$2>Inputs!$B$228,AM$2<=Inputs!$B$228+Inputs!$B$230),(1/(1-Inputs!$B$229))^(1/Inputs!$B$230)-1,IF(AND(Inputs!$B$233<>"",AM$2=Inputs!$B$233),-Inputs!$B$234,IF(AND(Inputs!$B$233<>"",AM$2>Inputs!$B$233,AM$2<=Inputs!$B$233+Inputs!$B$235),(1/(1-Inputs!$B$234))^(1/Inputs!$B$235)-1,IF(AND(Inputs!$B$238<>"",AM$2=Inputs!$B$238),-Inputs!$B$239,IF(AND(Inputs!$B$238<>"",AM$2>Inputs!$B$238,AM$2<=Inputs!$B$238+Inputs!$B$240),(1/(1-Inputs!$B$239))^(1/Inputs!$B$240)-1,stinc)))))))))) -> 8117.4702
A105: c/fwd | C105: =SUM(C102:C104) -> 31987.064 | D105: =SUM(D102:D104) -> 27189.005 | E105: =SUM(E102:E104) -> 31987.064 | F105: =SUM(F102:F104) -> 34546.03 | G105: =SUM(G102:G104) -> 37309.712 | H105: =SUM(H102:H104) -> 40294.489 | I105: =SUM(I102:I104) -> 32235.591 | J105: =SUM(J102:J104) -> 34724.738 | ... AM105: =SUM(AM102:AM104) -> 109585.85
...

Sheet RetEarly_Engine
B1: 0 | C1: 1 | D1: =C1+1 -> 2 | E1: =D1+1 -> 3 | F1: =E1+1 -> 4 | G1: =F1+1 -> 5 | H1: =G1+1 -> 6 | I1: =H1+1 -> 7 | J1: =I1+1 -> 8 | K1: =J1+1 -> 9 | ... AM1: =AL1+1 -> 37
B2: Year | C2: =YEAR(TODAY()) -> 2026 | D2: =C2+1 -> 2027 | E2: =D2+1 -> 2028 | F2: =E2+1 -> 2029 | G2: =F2+1 -> 2030 | H2: =G2+1 -> 2031 | I2: =H2+1 -> 2032 | J2: =I2+1 -> 2033 | K2: =J2+1 -> 2034 | ... AM2: =AL2+1 -> 2062
B3: 51 | C3: =Inputs!B4 -> 48 | D3: =C3+1 -> 49 | E3: =D3+1 -> 50 | F3: =E3+1 -> 51 | G3: =F3+1 -> 52 | H3: =G3+1 -> 53 | I3: =H3+1 -> 54 | J3: =I3+1 -> 55 | K3: =J3+1 -> 56 | ... AM3: =AL3+1 -> 84
A4: Inflows
A5: Net employment / self-employment income | C5: =IF(AND(Inputs!$B$19>C3,$B$3>C3),Inputs!$B$6*(1+sincr)^B1,0)*ProRate -> 66666.667 | D5: =IF(AND(Inputs!$B$19>D3,$B$3>D3),Inputs!$B$6*(1+sincr)^C1,0) -> 82400 | E5: =IF(AND(Inputs!$B$19>E3,$B$3>E3),Inputs!$B$6*(1+sincr)^D1,0) -> 84872 | F5: =IF(AND(Inputs!$B$19>F3,$B$3>F3),Inputs!$B$6*(1+sincr)^E1,0) -> 0 | G5: =IF(AND(Inputs!$B$19>G3,$B$3>G3),Inputs!$B$6*(1+sincr)^F1,0) -> 0 | H5: =IF(AND(Inputs!$B$19>H3,$B$3>H3),Inputs!$B$6*(1+sincr)^G1,0) -> 0 | I5: =IF(AND(Inputs!$B$19>I3,$B$3>I3),Inputs!$B$6*(1+sincr)^H1,0) -> 0 | J5: =IF(AND(Inputs!$B$19>J3,$B$3>J3),Inputs!$B$6*(1+sincr)^I1,0) -> 0 | K5: =IF(AND(Inputs!$B$19>K3,$B$3>K3),Inputs!$B$6*(1+sincr)^J1,0) -> 0 | ... AM5: =IF(AND(Inputs!$B$19>AM3,$B$3>AM3),Inputs!$B$6*(1+sincr)^AL1,0) -> 0
A6: Net from other work | C6: =IF(C$3<=Inputs!$B$120,Inputs!$B$119,0)*(1+inf)^B$1*ProRate -> 1666.6667 | D6: =IF(D$3<=Inputs!$B$120,Inputs!$B$119,0)*(1+inf)^C$1 -> 2050 | E6: =IF(E$3<=Inputs!$B$120,Inputs!$B$119,0)*(1+inf)^D$1 -> 2101.25 | F6: =IF(F$3<=Inputs!$B$120,Inputs!$B$119,0)*(1+inf)^E$1 -> 2153.7812 | G6: =IF(G$3<=Inputs!$B$120,Inputs!$B$119,0)*(1+inf)^F$1 -> 2207.6258 | H6: =IF(H$3<=Inputs!$B$120,Inputs!$B$119,0)*(1+inf)^G$1 -> 2262.8164 | I6: =IF(I$3<=Inputs!$B$120,Inputs!$B$119,0)*(1+inf)^H$1 -> 2319.3868 | J6: =IF(J$3<=Inputs!$B$120,Inputs!$B$119,0)*(1+inf)^I$1 -> 2377.3715 | K6: =IF(K$3<=Inputs!$B$120,Inputs!$B$119,0)*(1+inf)^J$1 -> 2436.8058 | ... AM6: =IF(AM$3<=Inputs!$B$120,Inputs!$B$119,0)*(1+inf)^AL$1 -> 0
A7: Net rental income from other properties
A8: =TEXT(Inputs!$B$60,"") -> Sliema | C8: =Inputs!B113*ProRate -> 10000 | D8: =C8*(1+rinc) -> 10300 | E8: =D8*(1+rinc) -> 10609 | F8: =E8*(1+rinc) -> 10927.27 | G8: =F8*(1+rinc) -> 11255.088 | H8: =G8*(1+rinc) -> 11592.741 | I8: =H8*(1+rinc) -> 11940.523 | J8: =I8*(1+rinc) -> 12298.739 | K8: =J8*(1+rinc) -> 12667.701 | ... AM8: =AL8*(1+rinc) -> 28982.783
A9: =TEXT(Inputs!$B$65,"") -> Gzira | C9: =Inputs!B114*ProRate -> 8333.3333 | D9: =C9*(1+rinc) -> 8583.3333 | E9: =D9*(1+rinc) -> 8840.8333 | F9: =E9*(1+rinc) -> 9106.0583 | G9: =F9*(1+rinc) -> 9379.2401 | H9: =G9*(1+rinc) -> 9660.6173 | I9: =H9*(1+rinc) -> 9950.4358 | J9: =I9*(1+rinc) -> 10248.949 | K9: =J9*(1+rinc) -> 10556.417 | ... AM9: =AL9*(1+rinc) -> 24152.319
A10: =TEXT(Inputs!$B$70,"") -> Qormi | C10: =Inputs!B115*ProRate -> 6666.6667 | D10: =C10*(1+rinc) -> 6866.6667 | E10: =D10*(1+rinc) -> 7072.6667 | F10: =E10*(1+rinc) -> 7284.8467 | G10: =F10*(1+rinc) -> 7503.3921 | H10: =G10*(1+rinc) -> 7728.4938 | I10: =H10*(1+rinc) -> 7960.3486 | J10: =I10*(1+rinc) -> 8199.1591 | K10: =J10*(1+rinc) -> 8445.1339 | ... AM10: =AL10*(1+rinc) -> 19321.856
A11: =TEXT(Inputs!$B$75,"") -> Gudja | C11: =Inputs!B116*ProRate -> 4166.6667 | D11: =C11*(1+rinc) -> 4291.6667 | E11: =D11*(1+rinc) -> 4420.4167 | F11: =E11*(1+rinc) -> 4553.0292 | G11: =F11*(1+rinc) -> 4689.62 | H11: =G11*(1+rinc) -> 4830.3086 | I11: =H11*(1+rinc) -> 4975.2179 | J11: =I11*(1+rinc) -> 5124.4744 | K11: =J11*(1+rinc) -> 5278.2087 | ... AM11: =AL11*(1+rinc) -> 12076.16
A12: =TEXT(Inputs!$B$80,"") -> Marsa | C12: =Inputs!B117*ProRate -> 5416.6667 | D12: =C12*(1+rinc) -> 5579.1667 | E12: =D12*(1+rinc) -> 5746.5417 | F12: =E12*(1+rinc) -> 5918.9379 | G12: =F12*(1+rinc) -> 6096.5061 | H12: =G12*(1+rinc) -> 6279.4012 | I12: =H12*(1+rinc) -> 6467.7833 | J12: =I12*(1+rinc) -> 6661.8168 | K12: =J12*(1+rinc) -> 6861.6713 | ... AM12: =AL12*(1+rinc) -> 15699.008
A13: Full pension | C13: =IF(C$3<Inputs!$B$19,0,Inputs!$B$21)*(1+inf)^B$1*ProRate -> 0 | D13: =IF(D$3<Inputs!$B$19,0,Inputs!$B$21)*(1+inf)^C$1 -> 0 | E13: =IF(E$3<Inputs!$B$19,0,Inputs!$B$21)*(1+inf)^D$1 -> 0 | F13: =IF(F$3<Inputs!$B$19,0,Inputs!$B$21)*(1+inf)^E$1 -> 0 | G13: =IF(G$3<Inputs!$B$19,0,Inputs!$B$21)*(1+inf)^F$1 -> 0 | H13: =IF(H$3<Inputs!$B$19,0,Inputs!$B$21)*(1+inf)^G$1 -> 0 | I13: =IF(I$3<Inputs!$B$19,0,Inputs!$B$21)*(1+inf)^H$1 -> 0 | J13: =IF(J$3<Inputs!$B$19,0,Inputs!$B$21)*(1+inf)^I$1 -> 0 | K13: =IF(K$3<Inputs!$B$19,0,Inputs!$B$21)*(1+inf)^J$1 -> 0 | ... AM13: =IF(AM$3<Inputs!$B$19,0,Inputs!$B$21)*(1+inf)^AL$1 -> 38920.565
A14: Pension reduction from early retirement | C14: =MIN(0,MAX(-IF(C13=0,0,(Inputs!$B$19-INDEX(3:3,MATCH(0,5:5,0))))*Inputs!$B$267*(1+inf)^B$1*ProRate,-C13)) -> 0 | D14: =MIN(0,MAX(-IF(D13=0,0,(Inputs!$B$19-INDEX(3:3,MATCH(0,5:5,0))))*Inputs!$B$267*(1+inf)^C$1,-D13)) -> 0 | E14: =MIN(0,MAX(-IF(E13=0,0,(Inputs!$B$19-INDEX(3:3,MATCH(0,5:5,0))))*Inputs!$B$267*(1+inf)^D$1,-E13)) -> 0 | F14: =MIN(0,MAX(-IF(F13=0,0,(Inputs!$B$19-INDEX(3:3,MATCH(0,5:5,0))))*Inputs!$B$267*(1+inf)^E$1,-F13)) -> 0 | G14: =MIN(0,MAX(-IF(G13=0,0,(Inputs!$B$19-INDEX(3:3,MATCH(0,5:5,0))))*Inputs!$B$267*(1+inf)^F$1,-G13)) -> 0 | H14: =MIN(0,MAX(-IF(H13=0,0,(Inputs!$B$19-INDEX(3:3,MATCH(0,5:5,0))))*Inputs!$B$267*(1+inf)^G$1,-H13)) -> 0 | I14: =MIN(0,MAX(-IF(I13=0,0,(Inputs!$B$19-INDEX(3:3,MATCH(0,5:5,0))))*Inputs!$B$267*(1+inf)^H$1,-I13)) -> 0 | J14: =MIN(0,MAX(-IF(J13=0,0,(Inputs!$B$19-INDEX(3:3,MATCH(0,5:5,0))))*Inputs!$B$267*(1+inf)^I$1,-J13)) -> 0 | K14: =MIN(0,MAX(-IF(K13=0,0,(Inputs!$B$19-INDEX(3:3,MATCH(0,5:5,0))))*Inputs!$B$267*(1+inf)^J$1,-K13)) -> 0 | ... AM14: =MIN(0,MAX(-IF(AM13=0,0,(Inputs!$B$19-INDEX(3:3,MATCH(0,5:5,0))))*Inputs!$B$267*(1+inf)^AL$1,-AM13)) -> -10216.648
A15: Other post-retirement income | C15: =IF(AND(C$3>=Inputs!$B$252,C$3<=Inputs!$B$253),Inputs!$B$251*(1+inf)^B$1,0)*ProRate -> 0 | D15: =IF(AND(D$3>=Inputs!$B$252,D$3<=Inputs!$B$253),Inputs!$B$251*(1+inf)^C$1,0) -> 0 | E15: =IF(AND(E$3>=Inputs!$B$252,E$3<=Inputs!$B$253),Inputs!$B$251*(1+inf)^D$1,0) -> 0 | F15: =IF(AND(F$3>=Inputs!$B$252,F$3<=Inputs!$B$253),Inputs!$B$251*(1+inf)^E$1,0) -> 0 | G15: =IF(AND(G$3>=Inputs!$B$252,G$3<=Inputs!$B$253),Inputs!$B$251*(1+inf)^F$1,0) -> 0 | H15: =IF(AND(H$3>=Inputs!$B$252,H$3<=Inputs!$B$253),Inputs!$B$251*(1+inf)^G$1,0) -> 0 | I15: =IF(AND(I$3>=Inputs!$B$252,I$3<=Inputs!$B$253),Inputs!$B$251*(1+inf)^H$1,0) -> 0 | J15: =IF(AND(J$3>=Inputs!$B$252,J$3<=Inputs!$B$253),Inputs!$B$251*(1+inf)^I$1,0) -> 0 | K15: =IF(AND(K$3>=Inputs!$B$252,K$3<=Inputs!$B$253),Inputs!$B$251*(1+inf)^J$1,0) -> 0 | ... AM15: =IF(AND(AM$3>=Inputs!$B$252,AM$3<=Inputs!$B$253),Inputs!$B$251*(1+inf)^AL$1,0) -> 0
A16: Major one-off income events
A17: =TEXT(Inputs!B184,"") -> Inheritance | C17: =IF(C$2=Inputs!$B186,Inputs!$B185,0)*(1+inf)^B$1 -> 0 | D17: =IF(D$2=Inputs!$B186,Inputs!$B185,0)*(1+inf)^C$1 -> 0 | E17: =IF(E$2=Inputs!$B186,Inputs!$B185,0)*(1+inf)^D$1 -> 0 | F17: =IF(F$2=Inputs!$B186,Inputs!$B185,0)*(1+inf)^E$1 -> 0 | G17: =IF(G$2=Inputs!$B186,Inputs!$B185,0)*(1+inf)^F$1 -> 0 | H17: =IF(H$2=Inputs!$B186,Inputs!$B185,0)*(1+inf)^G$1 -> 0 | I17: =IF(I$2=Inputs!$B186,Inputs!$B185,0)*(1+inf)^H$1 -> 0 | J17: =IF(J$2=Inputs!$B186,Inputs!$B185,0)*(1+inf)^I$1 -> 0 | ... AM17: =IF(AM$2=Inputs!$B186,Inputs!$B185,0)*(1+inf)^AL$1 -> 0
A18: =TEXT(Inputs!B189,"") -> Sell Painting | C18: =IF(C$2=Inputs!$B191,Inputs!$B190,0)*(1+inf)^B$1 -> 0 | D18: =IF(D$2=Inputs!$B191,Inputs!$B190,0)*(1+inf)^C$1 -> 0 | E18: =IF(E$2=Inputs!$B191,Inputs!$B190,0)*(1+inf)^D$1 -> 0 | F18: =IF(F$2=Inputs!$B191,Inputs!$B190,0)*(1+inf)^E$1 -> 10768.906 | G18: =IF(G$2=Inputs!$B191,Inputs!$B190,0)*(1+inf)^F$1 -> 0 | H18: =IF(H$2=Inputs!$B191,Inputs!$B190,0)*(1+inf)^G$1 -> 0 | I18: =IF(I$2=Inputs!$B191,Inputs!$B190,0)*(1+inf)^H$1 -> 0 | J18: =IF(J$2=Inputs!$B191,Inputs!$B190,0)*(1+inf)^I$1 -> 0 | ... AM18: =IF(AM$2=Inputs!$B191,Inputs!$B190,0)*(1+inf)^AL$1 -> 0
A19: =TEXT(Inputs!B194,"") -> Sell Jewels | C19: =IF(C$2=Inputs!$B196,Inputs!$B195,0)*(1+inf)^B$1 -> 0 | D19: =IF(D$2=Inputs!$B196,Inputs!$B195,0)*(1+inf)^C$1 -> 0 | E19: =IF(E$2=Inputs!$B196,Inputs!$B195,0)*(1+inf)^D$1 -> 0 | F19: =IF(F$2=Inputs!$B196,Inputs!$B195,0)*(1+inf)^E$1 -> 0 | G19: =IF(G$2=Inputs!$B196,Inputs!$B195,0)*(1+inf)^F$1 -> 0 | H19: =IF(H$2=Inputs!$B196,Inputs!$B195,0)*(1+inf)^G$1 -> 0 | I19: =IF(I$2=Inputs!$B196,Inputs!$B195,0)*(1+inf)^H$1 -> 5798.4671 | J19: =IF(J$2=Inputs!$B196,Inputs!$B195,0)*(1+inf)^I$1 -> 0 | ... AM19: =IF(AM$2=Inputs!$B196,Inputs!$B195,0)*(1+inf)^AL$1 -> 0
A20: Interest on cash balances | C20: =MAX(AVERAGE(C62,C62+SUM(C5:C19)-C59)*Inputs!$B$259,0) -> 1392.7083 | D20: =MAX(AVERAGE(D62,D62+SUM(D5:D19)-D59)*Inputs!$B$259,0) -> 1691.0073 | E20: =MAX(AVERAGE(E62,E62+SUM(E5:E19)-E59)*Inputs!$B$259,0) -> 2049.0802 | F20: =MAX(AVERAGE(F62,F62+SUM(F5:F19)-F59)*Inputs!$B$259,0) -> 1174.1477 | G20: =MAX(AVERAGE(G62,G62+SUM(G5:G19)-G59)*Inputs!$B$259,0) -> 0 | H20: =MAX(AVERAGE(H62,H62+SUM(H5:H19)-H59)*Inputs!$B$259,0) -> 0 | I20: =MAX(AVERAGE(I62,I62+SUM(I5:I19)-I59)*Inputs!$B$259,0) -> 0 | J20: =MAX(AVERAGE(J62,J62+SUM(J5:J19)-J59)*Inputs!$B$259,0) -> 0 | ... AM20: =MAX(AVERAGE(AM62,AM62+SUM(AM5:AM19)-AM59)*Inputs!$B$259,0) -> 0
C21: =SUM(C4:C20) -> 104309.38 | D21: =SUM(D4:D20) -> 121761.84 | E21: =SUM(E4:E20) -> 125711.79 | F21: =SUM(F4:F20) -> 51886.977 | G21: =SUM(G4:G20) -> 41131.472 | H21: =SUM(H4:H20) -> 42354.378 | I21: =SUM(I4:I20) -> 49412.163 | J21: =SUM(J4:J20) -> 44910.509 | ... AM21: =SUM(AM4:AM20) -> 128936.04
A22: Outflows
A23: Credit cards cleared | C23: =Inputs!B124 -> 1000 | D23: 0 | E23: 0 | F23: 0 | G23: 0 | H23: 0 | I23: 0 | J23: 0 | K23: 0 | L23: 0 | M23: 0 | N23: 0 | O23: 0 | P23: 0 | Q23: 0 | R23: 0 | S23: 0 | T23: 0 | U23: 0 | V23: 0 | W23: 0 | X23: 0 | Y23: 0 | Z23: 0 | AA23: 0 | AB23: 0 | AC23: 0 | AD23: 0 | AE23: 0 | AF23: 0 | AG23: 0 | AH23: 0 | AI23: 0 | AJ23: 0 | AK23: 0 | AL23: 0 | AM23: 0
A24: Home loan repayment | C24: =MIN(IF(B$1=0,MthRem,12), MAX(Inputs!$G$15-IF(B$1=0,0,B$1*12+MthOff), 0))*Inputs!$B$17 -> 8000 | D24: =MIN(IF(C$1=0,MthRem,12), MAX(Inputs!$G$15-IF(C$1=0,0,C$1*12+MthOff), 0))*Inputs!$B$17 -> 9600 | E24: =MIN(IF(D$1=0,MthRem,12), MAX(Inputs!$G$15-IF(D$1=0,0,D$1*12+MthOff), 0))*Inputs!$B$17 -> 9600 | F24: =MIN(IF(E$1=0,MthRem,12), MAX(Inputs!$G$15-IF(E$1=0,0,E$1*12+MthOff), 0))*Inputs!$B$17 -> 9600 | G24: =MIN(IF(F$1=0,MthRem,12), MAX(Inputs!$G$15-IF(F$1=0,0,F$1*12+MthOff), 0))*Inputs!$B$17 -> 9600 | H24: =MIN(IF(G$1=0,MthRem,12), MAX(Inputs!$G$15-IF(G$1=0,0,G$1*12+MthOff), 0))*Inputs!$B$17 -> 8035.6231 | I24: =MIN(IF(H$1=0,MthRem,12), MAX(Inputs!$G$15-IF(H$1=0,0,H$1*12+MthOff), 0))*Inputs!$B$17 -> 0 | J24: =MIN(IF(I$1=0,MthRem,12), MAX(Inputs!$G$15-IF(I$1=0,0,I$1*12+MthOff), 0))*Inputs!$B$17 -> 0 | ... AM24: =MIN(IF(AL$1=0,MthRem,12), MAX(Inputs!$G$15-IF(AL$1=0,0,AL$1*12+MthOff), 0))*Inputs!$B$17 -> 0
A25: Other asset loans repayments
A26: =TEXT(Inputs!$B$60,"") -> Sliema | C26: =MIN(IF(B$1=0,MthRem,12), MAX(Inputs!$G$127-IF(B$1=0,0,B$1*12+MthOff), 0))*Inputs!$B$129 -> 5000 | D26: =MIN(IF(C$1=0,MthRem,12), MAX(Inputs!$G$127-IF(C$1=0,0,C$1*12+MthOff), 0))*Inputs!$B$129 -> 6000 | E26: =MIN(IF(D$1=0,MthRem,12), MAX(Inputs!$G$127-IF(D$1=0,0,D$1*12+MthOff), 0))*Inputs!$B$129 -> 6000 | F26: =MIN(IF(E$1=0,MthRem,12), MAX(Inputs!$G$127-IF(E$1=0,0,E$1*12+MthOff), 0))*Inputs!$B$129 -> 6000 | G26: =MIN(IF(F$1=0,MthRem,12), MAX(Inputs!$G$127-IF(F$1=0,0,F$1*12+MthOff), 0))*Inputs!$B$129 -> 6000 | H26: =MIN(IF(G$1=0,MthRem,12), MAX(Inputs!$G$127-IF(G$1=0,0,G$1*12+MthOff), 0))*Inputs!$B$129 -> 6000 | I26: =MIN(IF(H$1=0,MthRem,12), MAX(Inputs!$G$127-IF(H$1=0,0,H$1*12+MthOff), 0))*Inputs!$B$129 -> 6000 | J26: =MIN(IF(I$1=0,MthRem,12), MAX(Inputs!$G$127-IF(I$1=0,0,I$1*12+MthOff), 0))*Inputs!$B$129 -> 6000 | ... AM26: =MIN(IF(AL$1=0,MthRem,12), MAX(Inputs!$G$127-IF(AL$1=0,0,AL$1*12+MthOff), 0))*Inputs!$B$129 -> 0
A27: =TEXT(Inputs!$B$65,"") -> Gzira | C27: =MIN(IF(B$1=0,MthRem,12), MAX(Inputs!$G$132-IF(B$1=0,0,B$1*12+MthOff), 0))*Inputs!$B$134 -> 2000 | D27: =MIN(IF(C$1=0,MthRem,12), MAX(Inputs!$G$132-IF(C$1=0,0,C$1*12+MthOff), 0))*Inputs!$B$134 -> 2400 | E27: =MIN(IF(D$1=0,MthRem,12), MAX(Inputs!$G$132-IF(D$1=0,0,D$1*12+MthOff), 0))*Inputs!$B$134 -> 2400 | F27: =MIN(IF(E$1=0,MthRem,12), MAX(Inputs!$G$132-IF(E$1=0,0,E$1*12+MthOff), 0))*Inputs!$B$134 -> 2023.4029 | G27: =MIN(IF(F$1=0,MthRem,12), MAX(Inputs!$G$132-IF(F$1=0,0,F$1*12+MthOff), 0))*Inputs!$B$134 -> 0 | H27: =MIN(IF(G$1=0,MthRem,12), MAX(Inputs!$G$132-IF(G$1=0,0,G$1*12+MthOff), 0))*Inputs!$B$134 -> 0 | I27: =MIN(IF(H$1=0,MthRem,12), MAX(Inputs!$G$132-IF(H$1=0,0,H$1*12+MthOff), 0))*Inputs!$B$134 -> 0 | J27: =MIN(IF(I$1=0,MthRem,12), MAX(Inputs!$G$132-IF(I$1=0,0,I$1*12+MthOff), 0))*Inputs!$B$134 -> 0 | ... AM27: =MIN(IF(AL$1=0,MthRem,12), MAX(Inputs!$G$132-IF(AL$1=0,0,AL$1*12+MthOff), 0))*Inputs!$B$134 -> 0
A28: =TEXT(Inputs!$B$70,"") -> Qormi | C28: =MIN(IF(B$1=0,MthRem,12), MAX(Inputs!$G$137-IF(B$1=0,0,B$1*12+MthOff), 0))*Inputs!$B$139 -> 2500 | D28: =MIN(IF(C$1=0,MthRem,12), MAX(Inputs!$G$137-IF(C$1=0,0,C$1*12+MthOff), 0))*Inputs!$B$139 -> 3000 | E28: =MIN(IF(D$1=0,MthRem,12), MAX(Inputs!$G$137-IF(D$1=0,0,D$1*12+MthOff), 0))*Inputs!$B$139 -> 3000 | F28: =MIN(IF(E$1=0,MthRem,12), MAX(Inputs!$G$137-IF(E$1=0,0,E$1*12+MthOff), 0))*Inputs!$B$139 -> 3000 | G28: =MIN(IF(F$1=0,MthRem,12), MAX(Inputs!$G$137-IF(F$1=0,0,F$1*12+MthOff), 0))*Inputs!$B$139 -> 3000 | H28: =MIN(IF(G$1=0,MthRem,12), MAX(Inputs!$G$137-IF(G$1=0,0,G$1*12+MthOff), 0))*Inputs!$B$139 -> 2796.8597 | I28: =MIN(IF(H$1=0,MthRem,12), MAX(Inputs!$G$137-IF(H$1=0,0,H$1*12+MthOff), 0))*Inputs!$B$139 -> 0 | J28: =MIN(IF(I$1=0,MthRem,12), MAX(Inputs!$G$137-IF(I$1=0,0,I$1*12+MthOff), 0))*Inputs!$B$139 -> 0 | ... AM28: =MIN(IF(AL$1=0,MthRem,12), MAX(Inputs!$G$137-IF(AL$1=0,0,AL$1*12+MthOff), 0))*Inputs!$B$139 -> 0
A29: =TEXT(Inputs!$B$75,"") -> Gudja | C29: =MIN(IF(B$1=0,MthRem,12), MAX(Inputs!$G$142-IF(B$1=0,0,B$1*12+MthOff), 0))*Inputs!$B$144 -> 800 | D29: =MIN(IF(C$1=0,MthRem,12), MAX(Inputs!$G$142-IF(C$1=0,0,C$1*12+MthOff), 0))*Inputs!$B$144 -> 960 | E29: =MIN(IF(D$1=0,MthRem,12), MAX(Inputs!$G$142-IF(D$1=0,0,D$1*12+MthOff), 0))*Inputs!$B$144 -> 960 | F29: =MIN(IF(E$1=0,MthRem,12), MAX(Inputs!$G$142-IF(E$1=0,0,E$1*12+MthOff), 0))*Inputs!$B$144 -> 960 | G29: =MIN(IF(F$1=0,MthRem,12), MAX(Inputs!$G$142-IF(F$1=0,0,F$1*12+MthOff), 0))*Inputs!$B$144 -> 960 | H29: =MIN(IF(G$1=0,MthRem,12), MAX(Inputs!$G$142-IF(G$1=0,0,G$1*12+MthOff), 0))*Inputs!$B$144 -> 288.25859 | I29: =MIN(IF(H$1=0,MthRem,12), MAX(Inputs!$G$142-IF(H$1=0,0,H$1*12+MthOff), 0))*Inputs!$B$144 -> 0 | J29: =MIN(IF(I$1=0,MthRem,12), MAX(Inputs!$G$142-IF(I$1=0,0,I$1*12+MthOff), 0))*Inputs!$B$144 -> 0 | ... AM29: =MIN(IF(AL$1=0,MthRem,12), MAX(Inputs!$G$142-IF(AL$1=0,0,AL$1*12+MthOff), 0))*Inputs!$B$144 -> 0
A30: =TEXT(Inputs!$B$80,"") -> Marsa | C30: =MIN(IF(B$1=0,MthRem,12), MAX(Inputs!$G$147-IF(B$1=0,0,B$1*12+MthOff), 0))*Inputs!$B$149 -> 1200 | D30: =MIN(IF(C$1=0,MthRem,12), MAX(Inputs!$G$147-IF(C$1=0,0,C$1*12+MthOff), 0))*Inputs!$B$149 -> 1440 | E30: =MIN(IF(D$1=0,MthRem,12), MAX(Inputs!$G$147-IF(D$1=0,0,D$1*12+MthOff), 0))*Inputs!$B$149 -> 1440 | F30: =MIN(IF(E$1=0,MthRem,12), MAX(Inputs!$G$147-IF(E$1=0,0,E$1*12+MthOff), 0))*Inputs!$B$149 -> 1440 | G30: =MIN(IF(F$1=0,MthRem,12), MAX(Inputs!$G$147-IF(F$1=0,0,F$1*12+MthOff), 0))*Inputs!$B$149 -> 1440 | H30: =MIN(IF(G$1=0,MthRem,12), MAX(Inputs!$G$147-IF(G$1=0,0,G$1*12+MthOff), 0))*Inputs!$B$149 -> 1440 | I30: =MIN(IF(H$1=0,MthRem,12), MAX(Inputs!$G$147-IF(H$1=0,0,H$1*12+MthOff), 0))*Inputs!$B$149 -> 1440 | J30: =MIN(IF(I$1=0,MthRem,12), MAX(Inputs!$G$147-IF(I$1=0,0,I$1*12+MthOff), 0))*Inputs!$B$149 -> 789.24881 | ... AM30: =MIN(IF(AL$1=0,MthRem,12), MAX(Inputs!$G$147-IF(AL$1=0,0,AL$1*12+MthOff), 0))*Inputs!$B$149 -> 0
A31: =TEXT(Inputs!$B$87,"") -> Jewelry | C31: =MIN(IF(B$1=0,MthRem,12), MAX(Inputs!$G$152-IF(B$1=0,0,B$1*12+MthOff), 0))*Inputs!$B$154 -> 750 | D31: =MIN(IF(C$1=0,MthRem,12), MAX(Inputs!$G$152-IF(C$1=0,0,C$1*12+MthOff), 0))*Inputs!$B$154 -> 900 | E31: =MIN(IF(D$1=0,MthRem,12), MAX(Inputs!$G$152-IF(D$1=0,0,D$1*12+MthOff), 0))*Inputs!$B$154 -> 900 | F31: =MIN(IF(E$1=0,MthRem,12), MAX(Inputs!$G$152-IF(E$1=0,0,E$1*12+MthOff), 0))*Inputs!$B$154 -> 63.602878 | G31: =MIN(IF(F$1=0,MthRem,12), MAX(Inputs!$G$152-IF(F$1=0,0,F$1*12+MthOff), 0))*Inputs!$B$154 -> 0 | H31: =MIN(IF(G$1=0,MthRem,12), MAX(Inputs!$G$152-IF(G$1=0,0,G$1*12+MthOff), 0))*Inputs!$B$154 -> 0 | I31: =MIN(IF(H$1=0,MthRem,12), MAX(Inputs!$G$152-IF(H$1=0,0,H$1*12+MthOff), 0))*Inputs!$B$154 -> 0 | J31: =MIN(IF(I$1=0,MthRem,12), MAX(Inputs!$G$152-IF(I$1=0,0,I$1*12+MthOff), 0))*Inputs!$B$154 -> 0 | ... AM31: =MIN(IF(AL$1=0,MthRem,12), MAX(Inputs!$G$152-IF(AL$1=0,0,AL$1*12+MthOff), 0))*Inputs!$B$154 -> 0
A32: =TEXT(Inputs!$B$92,"") -> Car | C32: =MIN(IF(B$1=0,MthRem,12), MAX(Inputs!$G$157-IF(B$1=0,0,B$1*12+MthOff), 0))*Inputs!$B$159 -> 860 | D32: =MIN(IF(C$1=0,MthRem,12), MAX(Inputs!$G$157-IF(C$1=0,0,C$1*12+MthOff), 0))*Inputs!$B$159 -> 1032 | E32: =MIN(IF(D$1=0,MthRem,12), MAX(Inputs!$G$157-IF(D$1=0,0,D$1*12+MthOff), 0))*Inputs!$B$159 -> 1032 | F32: =MIN(IF(E$1=0,MthRem,12), MAX(Inputs!$G$157-IF(E$1=0,0,E$1*12+MthOff), 0))*Inputs!$B$159 -> 1032 | G32: =MIN(IF(F$1=0,MthRem,12), MAX(Inputs!$G$157-IF(F$1=0,0,F$1*12+MthOff), 0))*Inputs!$B$159 -> 1032 | H32: =MIN(IF(G$1=0,MthRem,12), MAX(Inputs!$G$157-IF(G$1=0,0,G$1*12+MthOff), 0))*Inputs!$B$159 -> 1032 | I32: =MIN(IF(H$1=0,MthRem,12), MAX(Inputs!$G$157-IF(H$1=0,0,H$1*12+MthOff), 0))*Inputs!$B$159 -> 363.79405 | J32: =MIN(IF(I$1=0,MthRem,12), MAX(Inputs!$G$157-IF(I$1=0,0,I$1*12+MthOff), 0))*Inputs!$B$159 -> 0 | ... AM32: =MIN(IF(AL$1=0,MthRem,12), MAX(Inputs!$G$157-IF(AL$1=0,0,AL$1*12+MthOff), 0))*Inputs!$B$159 -> 0
A33: =TEXT(Inputs!$B$97,"") -> Painting | C33: =MIN(IF(B$1=0,MthRem,12), MAX(Inputs!$G$162-IF(B$1=0,0,B$1*12+MthOff), 0))*Inputs!$B$164 -> 1250 | D33: =MIN(IF(C$1=0,MthRem,12), MAX(Inputs!$G$162-IF(C$1=0,0,C$1*12+MthOff), 0))*Inputs!$B$164 -> 1500 | E33: =MIN(IF(D$1=0,MthRem,12), MAX(Inputs!$G$162-IF(D$1=0,0,D$1*12+MthOff), 0))*Inputs!$B$164 -> 1500 | F33: =MIN(IF(E$1=0,MthRem,12), MAX(Inputs!$G$162-IF(E$1=0,0,E$1*12+MthOff), 0))*Inputs!$B$164 -> 1500 | G33: =MIN(IF(F$1=0,MthRem,12), MAX(Inputs!$G$162-IF(F$1=0,0,F$1*12+MthOff), 0))*Inputs!$B$164 -> 1500 | H33: =MIN(IF(G$1=0,MthRem,12), MAX(Inputs!$G$162-IF(G$1=0,0,G$1*12+MthOff), 0))*Inputs!$B$164 -> 1398.4298 | I33: =MIN(IF(H$1=0,MthRem,12), MAX(Inputs!$G$162-IF(H$1=0,0,H$1*12+MthOff), 0))*Inputs!$B$164 -> 0 | J33: =MIN(IF(I$1=0,MthRem,12), MAX(Inputs!$G$162-IF(I$1=0,0,I$1*12+MthOff), 0))*Inputs!$B$164 -> 0 | ... AM33: =MIN(IF(AL$1=0,MthRem,12), MAX(Inputs!$G$162-IF(AL$1=0,0,AL$1*12+MthOff), 0))*Inputs!$B$164 -> 0
A34: =TEXT(Inputs!$B$102,"") -> Boat | C34: =MIN(IF(B$1=0,MthRem,12), MAX(Inputs!$G$167-IF(B$1=0,0,B$1*12+MthOff), 0))*Inputs!$B$169 -> 6240 | D34: =MIN(IF(C$1=0,MthRem,12), MAX(Inputs!$G$167-IF(C$1=0,0,C$1*12+MthOff), 0))*Inputs!$B$169 -> 7488 | E34: =MIN(IF(D$1=0,MthRem,12), MAX(Inputs!$G$167-IF(D$1=0,0,D$1*12+MthOff), 0))*Inputs!$B$169 -> 7488 | F34: =MIN(IF(E$1=0,MthRem,12), MAX(Inputs!$G$167-IF(E$1=0,0,E$1*12+MthOff), 0))*Inputs!$B$169 -> 7488 | G34: =MIN(IF(F$1=0,MthRem,12), MAX(Inputs!$G$167-IF(F$1=0,0,F$1*12+MthOff), 0))*Inputs!$B$169 -> 7488 | H34: =MIN(IF(G$1=0,MthRem,12), MAX(Inputs!$G$167-IF(G$1=0,0,G$1*12+MthOff), 0))*Inputs!$B$169 -> 7488 | I34: =MIN(IF(H$1=0,MthRem,12), MAX(Inputs!$G$167-IF(H$1=0,0,H$1*12+MthOff), 0))*Inputs!$B$169 -> 4665.2926 | J34: =MIN(IF(I$1=0,MthRem,12), MAX(Inputs!$G$167-IF(I$1=0,0,I$1*12+MthOff), 0))*Inputs!$B$169 -> 0 | ... AM34: =MIN(IF(AL$1=0,MthRem,12), MAX(Inputs!$G$167-IF(AL$1=0,0,AL$1*12+MthOff), 0))*Inputs!$B$169 -> 0
A35: =TEXT(Inputs!$B$107,"") -> Antiques | C35: =MIN(IF(B$1=0,MthRem,12), MAX(Inputs!$G$172-IF(B$1=0,0,B$1*12+MthOff), 0))*Inputs!$B$174 -> 1100 | D35: =MIN(IF(C$1=0,MthRem,12), MAX(Inputs!$G$172-IF(C$1=0,0,C$1*12+MthOff), 0))*Inputs!$B$174 -> 1320 | E35: =MIN(IF(D$1=0,MthRem,12), MAX(Inputs!$G$172-IF(D$1=0,0,D$1*12+MthOff), 0))*Inputs!$B$174 -> 1320 | F35: =MIN(IF(E$1=0,MthRem,12), MAX(Inputs!$G$172-IF(E$1=0,0,E$1*12+MthOff), 0))*Inputs!$B$174 -> 239.16176 | G35: =MIN(IF(F$1=0,MthRem,12), MAX(Inputs!$G$172-IF(F$1=0,0,F$1*12+MthOff), 0))*Inputs!$B$174 -> 0 | H35: =MIN(IF(G$1=0,MthRem,12), MAX(Inputs!$G$172-IF(G$1=0,0,G$1*12+MthOff), 0))*Inputs!$B$174 -> 0 | I35: =MIN(IF(H$1=0,MthRem,12), MAX(Inputs!$G$172-IF(H$1=0,0,H$1*12+MthOff), 0))*Inputs!$B$174 -> 0 | J35: =MIN(IF(I$1=0,MthRem,12), MAX(Inputs!$G$172-IF(I$1=0,0,I$1*12+MthOff), 0))*Inputs!$B$174 -> 0 | ... AM35: =MIN(IF(AL$1=0,MthRem,12), MAX(Inputs!$G$172-IF(AL$1=0,0,AL$1*12+MthOff), 0))*Inputs!$B$174 -> 0
A36: Other loan repayment | C36: =MIN(IF(B$1=0,MthRem,12), MAX(Inputs!$G$177-IF(B$1=0,0,B$1*12+MthOff), 0))*Inputs!$B$179 -> 500 | D36: =MIN(IF(C$1=0,MthRem,12), MAX(Inputs!$G$177-IF(C$1=0,0,C$1*12+MthOff), 0))*Inputs!$B$179 -> 600 | E36: =MIN(IF(D$1=0,MthRem,12), MAX(Inputs!$G$177-IF(D$1=0,0,D$1*12+MthOff), 0))*Inputs!$B$179 -> 600 | F36: =MIN(IF(E$1=0,MthRem,12), MAX(Inputs!$G$177-IF(E$1=0,0,E$1*12+MthOff), 0))*Inputs!$B$179 -> 600 | G36: =MIN(IF(F$1=0,MthRem,12), MAX(Inputs!$G$177-IF(F$1=0,0,F$1*12+MthOff), 0))*Inputs!$B$179 -> 600 | H36: =MIN(IF(G$1=0,MthRem,12), MAX(Inputs!$G$177-IF(G$1=0,0,G$1*12+MthOff), 0))*Inputs!$B$179 -> 600 | I36: =MIN(IF(H$1=0,MthRem,12), MAX(Inputs!$G$177-IF(H$1=0,0,H$1*12+MthOff), 0))*Inputs!$B$179 -> 600 | J36: =MIN(IF(I$1=0,MthRem,12), MAX(Inputs!$G$177-IF(I$1=0,0,I$1*12+MthOff), 0))*Inputs!$B$179 -> 600 | ... AM36: =MIN(IF(AL$1=0,MthRem,12), MAX(Inputs!$G$177-IF(AL$1=0,0,AL$1*12+MthOff), 0))*Inputs!$B$179 -> 0
A37: Dependents cost
A38: =TEXT(Inputs!B33,"") -> John | C38: =IF(Inputs!$B$35>=C$1,Inputs!$B$34,0)*(1+inf)^B$1*ProRate -> 1666.6667 | D38: =IF(Inputs!$B$35>=D$1,Inputs!$B$34,0)*(1+inf)^C$1 -> 2050 | E38: =IF(Inputs!$B$35>=E$1,Inputs!$B$34,0)*(1+inf)^D$1 -> 2101.25 | F38: =IF(Inputs!$B$35>=F$1,Inputs!$B$34,0)*(1+inf)^E$1 -> 0 | G38: =IF(Inputs!$B$35>=G$1,Inputs!$B$34,0)*(1+inf)^F$1 -> 0 | H38: =IF(Inputs!$B$35>=H$1,Inputs!$B$34,0)*(1+inf)^G$1 -> 0 | I38: =IF(Inputs!$B$35>=I$1,Inputs!$B$34,0)*(1+inf)^H$1 -> 0 | J38: =IF(Inputs!$B$35>=J$1,Inputs!$B$34,0)*(1+inf)^I$1 -> 0 | K38: =IF(Inputs!$B$35>=K$1,Inputs!$B$34,0)*(1+inf)^J$1 -> 0 | ... AM38: =IF(Inputs!$B$35>=AM$1,Inputs!$B$34,0)*(1+inf)^AL$1 -> 0
A39: =TEXT(Inputs!B38,"") -> Jack | C39: =IF(Inputs!$B$40>=C$1,Inputs!$B$39,0)*(1+inf)^B$1*ProRate -> 833.33333 | D39: =IF(Inputs!$B$40>=D$1,Inputs!$B$39,0)*(1+inf)^C$1 -> 1025 | E39: =IF(Inputs!$B$40>=E$1,Inputs!$B$39,0)*(1+inf)^D$1 -> 1050.625 | F39: =IF(Inputs!$B$40>=F$1,Inputs!$B$39,0)*(1+inf)^E$1 -> 1076.8906 | G39: =IF(Inputs!$B$40>=G$1,Inputs!$B$39,0)*(1+inf)^F$1 -> 1103.8129 | H39: =IF(Inputs!$B$40>=H$1,Inputs!$B$39,0)*(1+inf)^G$1 -> 0 | I39: =IF(Inputs!$B$40>=I$1,Inputs!$B$39,0)*(1+inf)^H$1 -> 0 | J39: =IF(Inputs!$B$40>=J$1,Inputs!$B$39,0)*(1+inf)^I$1 -> 0 | K39: =IF(Inputs!$B$40>=K$1,Inputs!$B$39,0)*(1+inf)^J$1 -> 0 | ... AM39: =IF(Inputs!$B$40>=AM$1,Inputs!$B$39,0)*(1+inf)^AL$1 -> 0
A40: =TEXT(Inputs!B43,"") -> Bill | C40: =IF(Inputs!$B$45>=C$1,Inputs!$B$44,0)*(1+inf)^B$1*ProRate -> 3333.3333 | D40: =IF(Inputs!$B$45>=D$1,Inputs!$B$44,0)*(1+inf)^C$1 -> 4100 | E40: =IF(Inputs!$B$45>=E$1,Inputs!$B$44,0)*(1+inf)^D$1 -> 0 | F40: =IF(Inputs!$B$45>=F$1,Inputs!$B$44,0)*(1+inf)^E$1 -> 0 | G40: =IF(Inputs!$B$45>=G$1,Inputs!$B$44,0)*(1+inf)^F$1 -> 0 | H40: =IF(Inputs!$B$45>=H$1,Inputs!$B$44,0)*(1+inf)^G$1 -> 0 | I40: =IF(Inputs!$B$45>=I$1,Inputs!$B$44,0)*(1+inf)^H$1 -> 0 | J40: =IF(Inputs!$B$45>=J$1,Inputs!$B$44,0)*(1+inf)^I$1 -> 0 | K40: =IF(Inputs!$B$45>=K$1,Inputs!$B$44,0)*(1+inf)^J$1 -> 0 | ... AM40: =IF(Inputs!$B$45>=AM$1,Inputs!$B$44,0)*(1+inf)^AL$1 -> 0
A41: =TEXT(Inputs!B48,"") -> Stephen | C41: =IF(Inputs!$B$50>=C$1,Inputs!$B$49,0)*(1+inf)^B$1*ProRate -> 2083.3333 | D41: =IF(Inputs!$B$50>=D$1,Inputs!$B$49,0)*(1+inf)^C$1 -> 2562.5 | E41: =IF(Inputs!$B$50>=E$1,Inputs!$B$49,0)*(1+inf)^D$1 -> 2626.5625 | F41: =IF(Inputs!$B$50>=F$1,Inputs!$B$49,0)*(1+inf)^E$1 -> 0 | G41: =IF(Inputs!$B$50>=G$1,Inputs!$B$49,0)*(1+inf)^F$1 -> 0 | H41: =IF(Inputs!$B$50>=H$1,Inputs!$B$49,0)*(1+inf)^G$1 -> 0 | I41: =IF(Inputs!$B$50>=I$1,Inputs!$B$49,0)*(1+inf)^H$1 -> 0 | J41: =IF(Inputs!$B$50>=J$1,Inputs!$B$49,0)*(1+inf)^I$1 -> 0 | K41: =IF(Inputs!$B$50>=K$1,Inputs!$B$49,0)*(1+inf)^J$1 -> 0 | ... AM41: =IF(Inputs!$B$50>=AM$1,Inputs!$B$49,0)*(1+inf)^AL$1 -> 0
A42: =TEXT(Inputs!B53,"") -> Jane | C42: =IF(Inputs!$B$55>=C$1,Inputs!$B$54,0)*(1+inf)^B$1*ProRate -> 2383.3333 | D42: =IF(Inputs!$B$55>=D$1,Inputs!$B$54,0)*(1+inf)^C$1 -> 2931.5 | E42: =IF(Inputs!$B$55>=E$1,Inputs!$B$54,0)*(1+inf)^D$1 -> 3004.7875 | F42: =IF(Inputs!$B$55>=F$1,Inputs!$B$54,0)*(1+inf)^E$1 -> 3079.9072 | G42: =IF(Inputs!$B$55>=G$1,Inputs!$B$54,0)*(1+inf)^F$1 -> 3156.9049 | H42: =IF(Inputs!$B$55>=H$1,Inputs!$B$54,0)*(1+inf)^G$1 -> 3235.8275 | I42: =IF(Inputs!$B$55>=I$1,Inputs!$B$54,0)*(1+inf)^H$1 -> 0 | J42: =IF(Inputs!$B$55>=J$1,Inputs!$B$54,0)*(1+inf)^I$1 -> 0 | K42: =IF(Inputs!$B$55>=K$1,Inputs!$B$54,0)*(1+inf)^J$1 -> 0 | ... AM42: =IF(Inputs!$B$55>=AM$1,Inputs!$B$54,0)*(1+inf)^AL$1 -> 0
A43: Housing rent | C43: =Inputs!$B$23*(1+inf)^B$1*ProRate -> 0 | D43: =Inputs!$B$23*(1+inf)^C$1 -> 0 | E43: =Inputs!$B$23*(1+inf)^D$1 -> 0 | F43: =Inputs!$B$23*(1+inf)^E$1 -> 0 | G43: =Inputs!$B$23*(1+inf)^F$1 -> 0 | H43: =Inputs!$B$23*(1+inf)^G$1 -> 0 | I43: =Inputs!$B$23*(1+inf)^H$1 -> 0 | J43: =Inputs!$B$23*(1+inf)^I$1 -> 0 | K43: =Inputs!$B$23*(1+inf)^J$1 -> 0 | ... AM43: =Inputs!$B$23*(1+inf)^AL$1 -> 0
A44: Other property costs
A45: =TEXT(Inputs!$B$60,"") -> Sliema | C45: =Inputs!$B62*(1+inf)^B$1*ProRate -> 4166.6667 | D45: =Inputs!$B62*(1+inf)^C$1 -> 5125 | E45: =Inputs!$B62*(1+inf)^D$1 -> 5253.125 | F45: =Inputs!$B62*(1+inf)^E$1 -> 5384.4531 | G45: =Inputs!$B62*(1+inf)^F$1 -> 5519.0645 | H45: =Inputs!$B62*(1+inf)^G$1 -> 5657.0411 | I45: =Inputs!$B62*(1+inf)^H$1 -> 5798.4671 | J45: =Inputs!$B62*(1+inf)^I$1 -> 5943.4288 | K45: =Inputs!$B62*(1+inf)^J$1 -> 6092.0145 | ... AM45: =Inputs!$B62*(1+inf)^AL$1 -> 12162.677
A46: =TEXT(Inputs!$B$65,"") -> Gzira | C46: =Inputs!$B67*(1+inf)^B$1*ProRate -> 1666.6667 | D46: =Inputs!$B67*(1+inf)^C$1 -> 2050 | E46: =Inputs!$B67*(1+inf)^D$1 -> 2101.25 | F46: =Inputs!$B67*(1+inf)^E$1 -> 2153.7812 | G46: =Inputs!$B67*(1+inf)^F$1 -> 2207.6258 | H46: =Inputs!$B67*(1+inf)^G$1 -> 2262.8164 | I46: =Inputs!$B67*(1+inf)^H$1 -> 2319.3868 | J46: =Inputs!$B67*(1+inf)^I$1 -> 2377.3715 | K46: =Inputs!$B67*(1+inf)^J$1 -> 2436.8058 | ... AM46: =Inputs!$B67*(1+inf)^AL$1 -> 4865.0706
A47: =TEXT(Inputs!$B$70,"") -> Qormi | C47: =Inputs!$B72*(1+inf)^B$1*ProRate -> 1000 | D47: =Inputs!$B72*(1+inf)^C$1 -> 1230 | E47: =Inputs!$B72*(1+inf)^D$1 -> 1260.75 | F47: =Inputs!$B72*(1+inf)^E$1 -> 1292.2687 | G47: =Inputs!$B72*(1+inf)^F$1 -> 1324.5755 | H47: =Inputs!$B72*(1+inf)^G$1 -> 1357.6899 | I47: =Inputs!$B72*(1+inf)^H$1 -> 1391.6321 | J47: =Inputs!$B72*(1+inf)^I$1 -> 1426.4229 | K47: =Inputs!$B72*(1+inf)^J$1 -> 1462.0835 | ... AM47: =Inputs!$B72*(1+inf)^AL$1 -> 2919.0424
A48: =TEXT(Inputs!$B$75,"") -> Gudja | C48: =Inputs!$B77*(1+inf)^B$1*ProRate -> 833.33333 | D48: =Inputs!$B77*(1+inf)^C$1 -> 1025 | E48: =Inputs!$B77*(1+inf)^D$1 -> 1050.625 | F48: =Inputs!$B77*(1+inf)^E$1 -> 1076.8906 | G48: =Inputs!$B77*(1+inf)^F$1 -> 1103.8129 | H48: =Inputs!$B77*(1+inf)^G$1 -> 1131.4082 | I48: =Inputs!$B77*(1+inf)^H$1 -> 1159.6934 | J48: =Inputs!$B77*(1+inf)^I$1 -> 1188.6858 | K48: =Inputs!$B77*(1+inf)^J$1 -> 1218.4029 | ... AM48: =Inputs!$B77*(1+inf)^AL$1 -> 2432.5353
A49: =TEXT(Inputs!$B$80,"") -> Marsa | C49: =Inputs!$B82*(1+inf)^B$1*ProRate -> 666.66667 | D49: =Inputs!$B82*(1+inf)^C$1 -> 820 | E49: =Inputs!$B82*(1+inf)^D$1 -> 840.5 | F49: =Inputs!$B82*(1+inf)^E$1 -> 861.5125 | G49: =Inputs!$B82*(1+inf)^F$1 -> 883.05031 | H49: =Inputs!$B82*(1+inf)^G$1 -> 905.12657 | I49: =Inputs!$B82*(1+inf)^H$1 -> 927.75473 | J49: =Inputs!$B82*(1+inf)^I$1 -> 950.9486 | K49: =Inputs!$B82*(1+inf)^J$1 -> 974.72232 | ... AM49: =Inputs!$B82*(1+inf)^AL$1 -> 1946.0283
A50: Living expenses
A51: Current baseline | C51: =Inputs!$B$25*(1+inf)^B$1*ProRate -> 41666.667 | D51: =Inputs!$B$25*(1+inf)^C$1 -> 51250 | E51: =Inputs!$B$25*(1+inf)^D$1 -> 52531.25 | F51: =Inputs!$B$25*(1+inf)^E$1 -> 53844.531 | G51: =Inputs!$B$25*(1+inf)^F$1 -> 55190.645 | H51: =Inputs!$B$25*(1+inf)^G$1 -> 56570.411 | I51: =Inputs!$B$25*(1+inf)^H$1 -> 57984.671 | J51: =Inputs!$B$25*(1+inf)^I$1 -> 59434.288 | K51: =Inputs!$B$25*(1+inf)^J$1 -> 60920.145 | ... AM51: =Inputs!$B$25*(1+inf)^AL$1 -> 121626.77
A52: ="Adjustment "&Inputs!A247 -> Adjustment from now to 65 | C52: =IF(C$3<=65,Inputs!$B$247*C$51,0) -> 0 | D52: =IF(D$3<=65,Inputs!$B$247*D$51,0) -> 0 | E52: =IF(E$3<=65,Inputs!$B$247*E$51,0) -> 0 | F52: =IF(F$3<=65,Inputs!$B$247*F$51,0) -> 0 | G52: =IF(G$3<=65,Inputs!$B$247*G$51,0) -> 0 | H52: =IF(H$3<=65,Inputs!$B$247*H$51,0) -> 0 | I52: =IF(I$3<=65,Inputs!$B$247*I$51,0) -> 0 | J52: =IF(J$3<=65,Inputs!$B$247*J$51,0) -> 0 | ... AM52: =IF(AM$3<=65,Inputs!$B$247*AM$51,0) -> 0
A53: ="Adjustment "&Inputs!A248 -> Adjustment from 66-75 | C53: =IF(AND(C$3>65,C$3<=75),Inputs!$B$248*C51,0) -> 0 | D53: =IF(AND(D$3>65,D$3<=75),Inputs!$B$248*D51,0) -> 0 | E53: =IF(AND(E$3>65,E$3<=75),Inputs!$B$248*E51,0) -> 0 | F53: =IF(AND(F$3>65,F$3<=75),Inputs!$B$248*F51,0) -> 0 | G53: =IF(AND(G$3>65,G$3<=75),Inputs!$B$248*G51,0) -> 0 | H53: =IF(AND(H$3>65,H$3<=75),Inputs!$B$248*H51,0) -> 0 | I53: =IF(AND(I$3>65,I$3<=75),Inputs!$B$248*I51,0) -> 0 | J53: =IF(AND(J$3>65,J$3<=75),Inputs!$B$248*J51,0) -> 0 | ... AM53: =IF(AND(AM$3>65,AM$3<=75),Inputs!$B$248*AM51,0) -> 0
A54: ="Adjustment "&Inputs!A249 -> Adjustment from age 76 | C54: =IF(C$3>75,Inputs!$B$249*C$51,0) -> 0 | D54: =IF(D$3>75,Inputs!$B$249*D$51,0) -> 0 | E54: =IF(E$3>75,Inputs!$B$249*E$51,0) -> 0 | F54: =IF(F$3>75,Inputs!$B$249*F$51,0) -> 0 | G54: =IF(G$3>75,Inputs!$B$249*G$51,0) -> 0 | H54: =IF(H$3>75,Inputs!$B$249*H$51,0) -> 0 | I54: =IF(I$3>75,Inputs!$B$249*I$51,0) -> 0 | J54: =IF(J$3>75,Inputs!$B$249*J$51,0) -> 0 | ... AM54: =IF(AM$3>75,Inputs!$B$249*AM$51,0) -> -24325.353
A55: Major one-off expense events
A56: =TEXT(Inputs!$B$201,"") -> Wedding | C56: =IF(C$2=Inputs!$B203,Inputs!$B202,0)*(1+inf)^B$1 -> 0 | D56: =IF(D$2=Inputs!$B203,Inputs!$B202,0)*(1+inf)^C$1 -> 0 | E56: =IF(E$2=Inputs!$B203,Inputs!$B202,0)*(1+inf)^D$1 -> 0 | F56: =IF(F$2=Inputs!$B203,Inputs!$B202,0)*(1+inf)^E$1 -> 0 | G56: =IF(G$2=Inputs!$B203,Inputs!$B202,0)*(1+inf)^F$1 -> 0 | H56: =IF(H$2=Inputs!$B203,Inputs!$B202,0)*(1+inf)^G$1 -> 0 | I56: =IF(I$2=Inputs!$B203,Inputs!$B202,0)*(1+inf)^H$1 -> 0 | J56: =IF(J$2=Inputs!$B203,Inputs!$B202,0)*(1+inf)^I$1 -> 0 | ... AM56: =IF(AM$2=Inputs!$B203,Inputs!$B202,0)*(1+inf)^AL$1 -> 0
A57: =TEXT(Inputs!$B$206,"") -> New Car | C57: =IF(C$2=Inputs!$B208,Inputs!$B207,0)*(1+inf)^B$1 -> 0 | D57: =IF(D$2=Inputs!$B208,Inputs!$B207,0)*(1+inf)^C$1 -> 0 | E57: =IF(E$2=Inputs!$B208,Inputs!$B207,0)*(1+inf)^D$1 -> 0 | F57: =IF(F$2=Inputs!$B208,Inputs!$B207,0)*(1+inf)^E$1 -> 37691.172 | G57: =IF(G$2=Inputs!$B208,Inputs!$B207,0)*(1+inf)^F$1 -> 0 | H57: =IF(H$2=Inputs!$B208,Inputs!$B207,0)*(1+inf)^G$1 -> 0 | I57: =IF(I$2=Inputs!$B208,Inputs!$B207,0)*(1+inf)^H$1 -> 0 | J57: =IF(J$2=Inputs!$B208,Inputs!$B207,0)*(1+inf)^I$1 -> 0 | ... AM57: =IF(AM$2=Inputs!$B208,Inputs!$B207,0)*(1+inf)^AL$1 -> 0
A58: =TEXT(Inputs!$B$211,"") -> New AC | C58: =IF(C$2=Inputs!$B213,Inputs!$B212,0)*(1+inf)^B$1 -> 0 | D58: =IF(D$2=Inputs!$B213,Inputs!$B212,0)*(1+inf)^C$1 -> 0 | E58: =IF(E$2=Inputs!$B213,Inputs!$B212,0)*(1+inf)^D$1 -> 0 | F58: =IF(F$2=Inputs!$B213,Inputs!$B212,0)*(1+inf)^E$1 -> 0 | G58: =IF(G$2=Inputs!$B213,Inputs!$B212,0)*(1+inf)^F$1 -> 0 | H58: =IF(H$2=Inputs!$B213,Inputs!$B212,0)*(1+inf)^G$1 -> 0 | I58: =IF(I$2=Inputs!$B213,Inputs!$B212,0)*(1+inf)^H$1 -> 0 | J58: =IF(J$2=Inputs!$B213,Inputs!$B212,0)*(1+inf)^I$1 -> 0 | ... AM58: =IF(AM$2=Inputs!$B213,Inputs!$B212,0)*(1+inf)^AL$1 -> 0
C59: =SUM(C22:C58) -> 91500 | D59: =SUM(D22:D58) -> 110409 | E59: =SUM(E22:E58) -> 108060.72 | F59: =SUM(F22:F58) -> 140407.57 | G59: =SUM(G22:G58) -> 102109.49 | H59: =SUM(H22:H58) -> 100199.49 | I59: =SUM(I22:I58) -> 82650.692 | J59: =SUM(J22:J58) -> 78710.394 | ... AM59: =SUM(AM22:AM58) -> 121626.77
A61: Net Cash Flow | C61: =C21-C59 -> 12809.375 | D61: =D21-D59 -> 11352.841 | E61: =E21-E59 -> 17651.064 | F61: =F21-F59 -> -88520.597 | G61: =G21-G59 -> -60978.019 | H61: =H21-H59 -> -57845.113 | I61: =I21-I59 -> -33238.529 | J61: =J21-J59 -> -33799.885 | ... AM61: =AM21-AM59 -> 7309.2764
A62: Cash b/fwd | C62: =Inputs!B8 -> 50000 | D62: =C63 -> 62809.375 | E62: =D63 -> 74162.216 | F62: =E63 -> 91813.279 | G62: =F63 -> 3292.6817 | H62: =G63 -> -57685.337 | I62: =H63 -> -115530.45 | J62: =I63 -> -148768.98 | K62: =J63 -> -182568.86 | ... AM62: =AL63 -> -322641.2
A63: Cash c/fwd | C63: =SUM(C61:C62) -> 62809.375 | D63: =SUM(D61:D62) -> 74162.216 | E63: =SUM(E61:E62) -> 91813.279 | F63: =SUM(F61:F62) -> 3292.6817 | G63: =SUM(G61:G62) -> -57685.337 | H63: =SUM(H61:H62) -> -115530.45 | I63: =SUM(I61:I62) -> -148768.98 | J63: =SUM(J61:J62) -> -182568.86 | ... AM63: =SUM(AM61:AM62) -> -315331.92
A65: Net Worth before liquidations
A66: Cash | C66: =C63 -> 62809.375 | D66: =D63 -> 74162.216 | E66: =E63 -> 91813.279 | F66: =F63 -> 3292.6817 | G66: =G63 -> -57685.337 | H66: =H63 -> -115530.45 | I66: =I63 -> -148768.98 | J66: =J63 -> -182568.86 | ... AM66: =AM63 -> -315331.92
A67: Home | C67: =Inputs!B12*(1+princ)^ProRate -> 614962.93 | D67: =C67*(1+princ) -> 633411.82 | E67: =D67*(1+princ) -> 652414.17 | F67: =E67*(1+princ) -> 671986.6 | G67: =F67*(1+princ) -> 692146.2 | H67: =G67*(1+princ) -> 712910.58 | I67: =H67*(1+princ) -> 734297.9 | J67: =I67*(1+princ) -> 756326.84 | K67: =J67*(1+princ) -> 779016.64 | ... AM67: =AL67*(1+princ) -> 1782333.7
A68: Other property
A69: =TEXT(Inputs!$B$60,"") -> Sliema | C69: =Inputs!B61*(1+princ)^ProRate -> 307481.47 | D69: =C69*(1+princ) -> 316705.91 | E69: =D69*(1+princ) -> 326207.09 | F69: =E69*(1+princ) -> 335993.3 | G69: =F69*(1+princ) -> 346073.1 | H69: =G69*(1+princ) -> 356455.29 | I69: =H69*(1+princ) -> 367148.95 | J69: =I69*(1+princ) -> 378163.42 | K69: =J69*(1+princ) -> 389508.32 | ... AM69: =AL69*(1+princ) -> 891166.87
A70: =TEXT(Inputs!$B$65,"") -> Gzira | C70: =Inputs!B66*(1+princ)^ProRate -> 153740.73 | D70: =C70*(1+princ) -> 158352.95 | E70: =D70*(1+princ) -> 163103.54 | F70: =E70*(1+princ) -> 167996.65 | G70: =F70*(1+princ) -> 173036.55 | H70: =G70*(1+princ) -> 178227.65 | I70: =H70*(1+princ) -> 183574.47 | J70: =I70*(1+princ) -> 189081.71 | K70: =J70*(1+princ) -> 194754.16 | ... AM70: =AL70*(1+princ) -> 445583.43
A71: =TEXT(Inputs!$B$70,"") -> Qormi | C71: =Inputs!B71*(1+princ)^ProRate -> 225486.41 | D71: =C71*(1+princ) -> 232251 | E71: =D71*(1+princ) -> 239218.53 | F71: =E71*(1+princ) -> 246395.09 | G71: =F71*(1+princ) -> 253786.94 | H71: =G71*(1+princ) -> 261400.55 | I71: =H71*(1+princ) -> 269242.56 | J71: =I71*(1+princ) -> 277319.84 | K71: =J71*(1+princ) -> 285639.44 | ... AM71: =AL71*(1+princ) -> 653522.37
A72: =TEXT(Inputs!$B$75,"") -> Gudja | C72: =Inputs!B76*(1+princ)^ProRate -> 81995.057 | D72: =C72*(1+princ) -> 84454.909 | E72: =D72*(1+princ) -> 86988.556 | F72: =E72*(1+princ) -> 89598.213 | G72: =F72*(1+princ) -> 92286.159 | H72: =G72*(1+princ) -> 95054.744 | I72: =H72*(1+princ) -> 97906.387 | J72: =I72*(1+princ) -> 100843.58 | K72: =J72*(1+princ) -> 103868.89 | ... AM72: =AL72*(1+princ) -> 237644.5
A73: =TEXT(Inputs!$B$80,"") -> Marsa | C73: =Inputs!B81*(1+princ)^ProRate -> 122992.59 | D73: =C73*(1+princ) -> 126682.36 | E73: =D73*(1+princ) -> 130482.83 | F73: =E73*(1+princ) -> 134397.32 | G73: =F73*(1+princ) -> 138429.24 | H73: =G73*(1+princ) -> 142582.12 | I73: =H73*(1+princ) -> 146859.58 | J73: =I73*(1+princ) -> 151265.37 | K73: =J73*(1+princ) -> 155803.33 | ... AM73: =AL73*(1+princ) -> 356466.75
A74: Other assets of value
A75: =TEXT(Inputs!$B$87,"") -> Jewelry | C75: =Inputs!B88*(1+A1inc)^ProRate -> 50831.955 | D75: =C75*(1+A1inc) -> 51848.594 | E75: =D75*(1+A1inc) -> 52885.566 | F75: =E75*(1+A1inc) -> 53943.277 | G75: =F75*(1+A1inc) -> 55022.143 | H75: =G75*(1+A1inc) -> 56122.586 | I75: =H75*(1+A1inc) -> 57245.038 | J75: =I75*(1+A1inc) -> 58389.938 | K75: =J75*(1+A1inc) -> 59557.737 | ... AM75: =AL75*(1+A1inc) -> 103691.46
A76: =TEXT(Inputs!$B$92,"") -> Car | C76: =Inputs!B93*(1+A2inc)^ProRate -> 38326.25 | D76: =C76*(1+A2inc) -> 36409.938 | E76: =D76*(1+A2inc) -> 34589.441 | F76: =E76*(1+A2inc) -> 32859.969 | G76: =F76*(1+A2inc) -> 31216.97 | H76: =G76*(1+A2inc) -> 29656.122 | I76: =H76*(1+A2inc) -> 28173.316 | J76: =I76*(1+A2inc) -> 26764.65 | K76: =J76*(1+A2inc) -> 25426.417 | ... AM76: =AL76*(1+A2inc) -> 6047.0856
A77: =TEXT(Inputs!$B$97,"") -> Painting | C77: =Inputs!B98*(1+A3inc)^ProRate -> 20498.764 | D77: =C77*(1+A3inc) -> 21113.727 | E77: =D77*(1+A3inc) -> 21747.139 | F77: =E77*(1+A3inc) -> 22399.553 | G77: =F77*(1+A3inc) -> 23071.54 | H77: =G77*(1+A3inc) -> 23763.686 | I77: =H77*(1+A3inc) -> 24476.597 | J77: =I77*(1+A3inc) -> 25210.895 | K77: =J77*(1+A3inc) -> 25967.221 | ... AM77: =AL77*(1+A3inc) -> 59411.124
A78: =TEXT(Inputs!$B$102,"") -> Boat | C78: =Inputs!B103*(1+A4inc)^ProRate -> 172468.13 | D78: =C78*(1+A4inc) -> 163844.72 | E78: =D78*(1+A4inc) -> 155652.48 | F78: =E78*(1+A4inc) -> 147869.86 | G78: =F78*(1+A4inc) -> 140476.37 | H78: =G78*(1+A4inc) -> 133452.55 | I78: =H78*(1+A4inc) -> 126779.92 | J78: =I78*(1+A4inc) -> 120440.92 | K78: =J78*(1+A4inc) -> 114418.88 | ... AM78: =AL78*(1+A4inc) -> 27211.885
A79: =TEXT(Inputs!$B$107,"") -> Antiques | C79: =Inputs!B108*(1+A5inc)^ProRate -> 83364.406 | D79: =C79*(1+A5inc) -> 85031.695 | E79: =D79*(1+A5inc) -> 86732.328 | F79: =E79*(1+A5inc) -> 88466.975 | G79: =F79*(1+A5inc) -> 90236.315 | H79: =G79*(1+A5inc) -> 92041.041 | I79: =H79*(1+A5inc) -> 93881.862 | J79: =I79*(1+A5inc) -> 95759.499 | K79: =J79*(1+A5inc) -> 97674.689 | ... AM79: =AL79*(1+A5inc) -> 170054
A80: Stock market equity investments | C80: =Inputs!B10*(1+stinc)^ProRate -> 31987.064 | D80: =C80*(1+IF(AND(Inputs!$B$218<>"",D$2=Inputs!$B$218),-Inputs!$B$219,IF(AND(Inputs!$B$218<>"",D$2>Inputs!$B$218,D$2<=Inputs!$B$218+Inputs!$B$220),(1/(1-Inputs!$B$219))^(1/Inputs!$B$220)-1,IF(AND(Inputs!$B$223<>"",D$2=Inputs!$B$223),-Inputs!$B$224,IF(AND(Inputs!$B$223<>"",D$2>Inputs!$B$223,D$2<=Inputs!$B$223+Inputs!$B$225),(1/(1-Inputs!$B$224))^(1/Inputs!$B$225)-1,IF(AND(Inputs!$B$228<>"",D$2=Inputs!$B$228),-Inputs!$B$229,IF(AND(Inputs!$B$228<>"",D$2>Inputs!$B$228,D$2<=Inputs!$B$228+Inputs!$B$230),(1/(1-Inputs!$B$229))^(1/Inputs!$B$230)-1,IF(AND(Inputs!$B$233<>"",D$2=Inputs!$B$233),-Inputs!$B$234,IF(AND(Inputs!$B$233<>"",D$2>Inputs!$B$233,D$2<=Inputs!$B$233+Inputs!$B$235),(1/(1-Inputs!$B$234))^(1/Inputs!$B$235)-1,IF(AND(Inputs!$B$238<>"",D$2=Inputs!$B$238),-Inputs!$B$239,IF(AND(Inputs!$B$238<>"",D$2>Inputs!$B$238,D$2<=Inputs!$B$238+Inputs!$B$240),(1/(1-Inputs!$B$239))^(1/Inputs!$B$240)-1,stinc))))))))))) -> 27189.005 | E80: =D80*(1+IF(AND(Inputs!$B$218<>"",E$2=Inputs!$B$218),-Inputs!$B$219,IF(AND(Inputs!$B$218<>"",E$2>Inputs!$B$218,E$2<=Inputs!$B$218+Inputs!$B$220),(1/(1-Inputs!$B$219))^(1/Inputs!$B$220)-1,IF(AND(Inputs!$B$223<>"",E$2=Inputs!$B$223),-Inputs!$B$224,IF(AND(Inputs!$B$223<>"",E$2>Inputs!$B$223,E$2<=Inputs!$B$223+Inputs!$B$225),(1/(1-Inputs!$B$224))^(1/Inputs!$B$225)-1,IF(AND(Inputs!$B$228<>"",E$2=Inputs!$B$228),-Inputs!$B$229,IF(AND(Inputs!$B$228<>"",E$2>Inputs!$B$228,E$2<=Inputs!$B$228+Inputs!$B$230),(1/(1-Inputs!$B$229))^(1/Inputs!$B$230)-1,IF(AND(Inputs!$B$233<>"",E$2=Inputs!$B$233),-Inputs!$B$234,IF(AND(Inputs!$B$233<>"",E$2>Inputs!$B$233,E$2<=Inputs!$B$233+Inputs!$B$235),(1/(1-Inputs!$B$234))^(1/Inputs!$B$235)-1,IF(AND(Inputs!$B$238<>"",E$2=Inputs!$B$238),-Inputs!$B$239,IF(AND(Inputs!$B$238<>"",E$2>Inputs!$B$238,E$2<=Inputs!$B$238+Inputs!$B$240),(1/(1-Inputs!$B$239))^(1/Inputs!$B$240)-1,stinc))))))))))) -> 31987.064 | F80: =E80*(1+IF(AND(Inputs!$B$218<>"",F$2=Inputs!$B$218),-Inputs!$B$219,IF(AND(Inputs!$B$218<>"",F$2>Inputs!$B$218,F$2<=Inputs!$B$218+Inputs!$B$220),(1/(1-Inputs!$B$219))^(1/Inputs!$B$220)-1,IF(AND(Inputs!$B$223<>"",F$2=Inputs!$B$223),-Inputs!$B$224,IF(AND(Inputs!$B$223<>"",F$2>Inputs!$B$223,F$2<=Inputs!$B$223+Inputs!$B$225),(1/(1-Inputs!$B$224))^(1/Inputs!$B$225)-1,IF(AND(Inputs!$B$228<>"",F$2=Inputs!$B$228),-Inputs!$B$229,IF(AND(Inputs!$B$228<>"",F$2>Inputs!$B$228,F$2<=Inputs!$B$228+Inputs!$B$230),(1/(1-Inputs!$B$229))^(1/Inputs!$B$230)-1,IF(AND(Inputs!$B$233<>"",F$2=Inputs!$B$233),-Inputs!$B$234,IF(AND(Inputs!$B$233<>"",F$2>Inputs!$B$233,F$2<=Inputs!$B$233+Inputs!$B$235),(1/(1-Inputs!$B$234))^(1/Inputs!$B$235)-1,IF(AND(Inputs!$B$238<>"",F$2=Inputs!$B$238),-Inputs!$B$239,IF(AND(Inputs!$B$238<>"",F$2>Inputs!$B$238,F$2<=Inputs!$B$238+Inputs!$B$240),(1/(1-Inputs!$B$239))^(1/Inputs!$B$240)-1,stinc))))))))))) -> 34546.03 | G80: =F80*(1+IF(AND(Inputs!$B$218<>"",G$2=Inputs!$B$218),-Inputs!$B$219,IF(AND(Inputs!$B$218<>"",G$2>Inputs!$B$218,G$2<=Inputs!$B$218+Inputs!$B$220),(1/(1-Inputs!$B$219))^(1/Inputs!$B$220)-1,IF(AND(Inputs!$B$223<>"",G$2=Inputs!$B$223),-Inputs!$B$224,IF(AND(Inputs!$B$223<>"",G$2>Inputs!$B$223,G$2<=Inputs!$B$223+Inputs!$B$225),(1/(1-Inputs!$B$224))^(1/Inputs!$B$225)-1,IF(AND(Inputs!$B$228<>"",G$2=Inputs!$B$228),-Inputs!$B$229,IF(AND(Inputs!$B$228<>"",G$2>Inputs!$B$228,G$2<=Inputs!$B$228+Inputs!$B$230),(1/(1-Inputs!$B$229))^(1/Inputs!$B$230)-1,IF(AND(Inputs!$B$233<>"",G$2=Inputs!$B$233),-Inputs!$B$234,IF(AND(Inputs!$B$233<>"",G$2>Inputs!$B$233,G$2<=Inputs!$B$233+Inputs!$B$235),(1/(1-Inputs!$B$234))^(1/Inputs!$B$235)-1,IF(AND(Inputs!$B$238<>"",G$2=Inputs!$B$238),-Inputs!$B$239,IF(AND(Inputs!$B$238<>"",G$2>Inputs!$B$238,G$2<=Inputs!$B$238+Inputs!$B$240),(1/(1-Inputs!$B$239))^(1/Inputs!$B$240)-1,stinc))))))))))) -> 37309.712 | H80: =G80*(1+IF(AND(Inputs!$B$218<>"",H$2=Inputs!$B$218),-Inputs!$B$219,IF(AND(Inputs!$B$218<>"",H$2>Inputs!$B$218,H$2<=Inputs!$B$218+Inputs!$B$220),(1/(1-Inputs!$B$219))^(1/Inputs!$B$220)-1,IF(AND(Inputs!$B$223<>"",H$2=Inputs!$B$223),-Inputs!$B$224,IF(AND(Inputs!$B$223<>"",H$2>Inputs!$B$223,H$2<=Inputs!$B$223+Inputs!$B$225),(1/(1-Inputs!$B$224))^(1/Inputs!$B$225)-1,IF(AND(Inputs!$B$228<>"",H$2=Inputs!$B$228),-Inputs!$B$229,IF(AND(Inputs!$B$228<>"",H$2>Inputs!$B$228,H$2<=Inputs!$B$228+Inputs!$B$230),(1/(1-Inputs!$B$229))^(1/Inputs!$B$230)-1,IF(AND(Inputs!$B$233<>"",H$2=Inputs!$B$233),-Inputs!$B$234,IF(AND(Inputs!$B$233<>"",H$2>Inputs!$B$233,H$2<=Inputs!$B$233+Inputs!$B$235),(1/(1-Inputs!$B$234))^(1/Inputs!$B$235)-1,IF(AND(Inputs!$B$238<>"",H$2=Inputs!$B$238),-Inputs!$B$239,IF(AND(Inputs!$B$238<>"",H$2>Inputs!$B$238,H$2<=Inputs!$B$238+Inputs!$B$240),(1/(1-Inputs!$B$239))^(1/Inputs!$B$240)-1,stinc))))))))))) -> 40294.489 | I80: =H80*(1+IF(AND(Inputs!$B$218<>"",I$2=Inputs!$B$218),-Inputs!$B$219,IF(AND(Inputs!$B$218<>"",I$2>Inputs!$B$218,I$2<=Inputs!$B$218+Inputs!$B$220),(1/(1-Inputs!$B$219))^(1/Inputs!$B$220)-1,IF(AND(Inputs!$B$223<>"",I$2=Inputs!$B$223),-Inputs!$B$224,IF(AND(Inputs!$B$223<>"",I$2>Inputs!$B$223,I$2<=Inputs!$B$223+Inputs!$B$225),(1/(1-Inputs!$B$224))^(1/Inputs!$B$225)-1,IF(AND(Inputs!$B$228<>"",I$2=Inputs!$B$228),-Inputs!$B$229,IF(AND(Inputs!$B$228<>"",I$2>Inputs!$B$228,I$2<=Inputs!$B$228+Inputs!$B$230),(1/(1-Inputs!$B$229))^(1/Inputs!$B$230)-1,IF(AND(Inputs!$B$233<>"",I$2=Inputs!$B$233),-Inputs!$B$234,IF(AND(Inputs!$B$233<>"",I$2>Inputs!$B$233,I$2<=Inputs!$B$233+Inputs!$B$235),(1/(1-Inputs!$B$234))^(1/Inputs!$B$235)-1,IF(AND(Inputs!$B$238<>"",I$2=Inputs!$B$238),-Inputs!$B$239,IF(AND(Inputs!$B$238<>"",I$2>Inputs!$B$238,I$2<=Inputs!$B$238+Inputs!$B$240),(1/(1-Inputs!$B$239))^(1/Inputs!$B$240)-1,stinc))))))))))) -> 32235.591 | J80: =I80*(1+IF(AND(Inputs!$B$218<>"",J$2=Inputs!$B$218),-Inputs!$B$219,IF(AND(Inputs!$B$218<>"",J$2>Inputs!$B$218,J$2<=Inputs!$B$218+Inputs!$B$220),(1/(1-Inputs!$B$219))^(1/Inputs!$B$220)-1,IF(AND(Inputs!$B$223<>"",J$2=Inputs!$B$223),-Inputs!$B$224,IF(AND(Inputs!$B$223<>"",J$2>Inputs!$B$223,J$2<=Inputs!$B$223+Inputs!$B$225),(1/(1-Inputs!$B$224))^(1/Inputs!$B$225)-1,IF(AND(Inputs!$B$228<>"",J$2=Inputs!$B$228),-Inputs!$B$229,IF(AND(Inputs!$B$228<>"",J$2>Inputs!$B$228,J$2<=Inputs!$B$228+Inputs!$B$230),(1/(1-Inputs!$B$229))^(1/Inputs!$B$230)-1,IF(AND(Inputs!$B$233<>"",J$2=Inputs!$B$233),-Inputs!$B$234,IF(AND(Inputs!$B$233<>"",J$2>Inputs!$B$233,J$2<=Inputs!$B$233+Inputs!$B$235),(1/(1-Inputs!$B$234))^(1/Inputs!$B$235)-1,IF(AND(Inputs!$B$238<>"",J$2=Inputs!$B$238),-Inputs!$B$239,IF(AND(Inputs!$B$238<>"",J$2>Inputs!$B$238,J$2<=Inputs!$B$238+Inputs!$B$240),(1/(1-Inputs!$B$239))^(1/Inputs!$B$240)-1,stinc))))))))))) -> 34724.738 | K80: =J80*(1+IF(AND(Inputs!$B$218<>"",K$2=Inputs!$B$218),-Inputs!$B$219,IF(AND(Inputs!$B$218<>"",K$2>Inputs!$B$218,K$2<=Inputs!$B$218+Inputs!$B$220),(1/(1-Inputs!$B$219))^(1/Inputs!$B$220)-1,IF(AND(Inputs!$B$223<>"",K$2=Inputs!$B$223),-Inputs!$B$224,IF(AND(Inputs!$B$223<>"",K$2>Inputs!$B$223,K$2<=Inputs!$B$223+Inputs!$B$225),(1/(1-Inputs!$B$224))^(1/Inputs!$B$225)-1,IF(AND(Inputs!$B$228<>"",K$2=Inputs!$B$228),-Inputs!$B$229,IF(AND(Inputs!$B$228<>"",K$2>Inputs!$B$228,K$2<=Inputs!$B$228+Inputs!$B$230),(1/(1-Inputs!$B$229))^(1/Inputs!$B$230)-1,IF(AND(Inputs!$B$233<>"",K$2=Inputs!$B$233),-Inputs!$B$234,IF(AND(Inputs!$B$233<>"",K$2>Inputs!$B$233,K$2<=Inputs!$B$233+Inputs!$B$235),(1/(1-Inputs!$B$234))^(1/Inputs!$B$235)-1,IF(AND(Inputs!$B$238<>"",K$2=Inputs!$B$238),-Inputs!$B$239,IF(AND(Inputs!$B$238<>"",K$2>Inputs!$B$238,K$2<=Inputs!$B$238+Inputs!$B$240),(1/(1-Inputs!$B$239))^(1/Inputs!$B$240)-1,stinc))))))))))) -> 37406.09 | ... AM80: =AL80*(1+IF(AND(Inputs!$B$218<>"",AM$2=Inputs!$B$218),-Inputs!$B$219,IF(AND(Inputs!$B$218<>"",AM$2>Inputs!$B$218,AM$2<=Inputs!$B$218+Inputs!$B$220),(1/(1-Inputs!$B$219))^(1/Inputs!$B$220)-1,IF(AND(Inputs!$B$223<>"",AM$2=Inputs!$B$223),-Inputs!$B$224,IF(AND(Inputs!$B$223<>"",AM$2>Inputs!$B$223,AM$2<=Inputs!$B$223+Inputs!$B$225),(1/(1-Inputs!$B$224))^(1/Inputs!$B$225)-1,IF(AND(Inputs!$B$228<>"",AM$2=Inputs!$B$228),-Inputs!$B$229,IF(AND(Inputs!$B$228<>"",AM$2>Inputs!$B$228,AM$2<=Inputs!$B$228+Inputs!$B$230),(1/(1-Inputs!$B$229))^(1/Inputs!$B$230)-1,IF(AND(Inputs!$B$233<>"",AM$2=Inputs!$B$233),-Inputs!$B$234,IF(AND(Inputs!$B$233<>"",AM$2>Inputs!$B$233,AM$2<=Inputs!$B$233+Inputs!$B$235),(1/(1-Inputs!$B$234))^(1/Inputs!$B$235)-1,IF(AND(Inputs!$B$238<>"",AM$2=Inputs!$B$238),-Inputs!$B$239,IF(AND(Inputs!$B$238<>"",AM$2>Inputs!$B$238,AM$2<=Inputs!$B$238+Inputs!$B$240),(1/(1-Inputs!$B$239))^(1/Inputs!$B$240)-1,stinc))))))))))) -> 109585.85
A81: Home loan | C81: =-MAX(FV(Inputs!$B16/12,C$1*12+MthOff,Inputs!$B17,-Inputs!$B15),0) -> -43173.554 | D81: =-MAX(FV(Inputs!$B16/12,D$1*12+MthOff,Inputs!$B17,-Inputs!$B15),0) -> -34753.613 | E81: =-MAX(FV(Inputs!$B16/12,E$1*12+MthOff,Inputs!$B17,-Inputs!$B15),0) -> -26077.571 | F81: =-MAX(FV(Inputs!$B16/12,F$1*12+MthOff,Inputs!$B17,-Inputs!$B15),0) -> -17137.639 | G81: =-MAX(FV(Inputs!$B16/12,G$1*12+MthOff,Inputs!$B17,-Inputs!$B15),0) -> -7925.7905 | H81: =-MAX(FV(Inputs!$B16/12,H$1*12+MthOff,Inputs!$B17,-Inputs!$B15),0) -> 0 | I81: =-MAX(FV(Inputs!$B16/12,I$1*12+MthOff,Inputs!$B17,-Inputs!$B15),0) -> 0 | J81: =-MAX(FV(Inputs!$B16/12,J$1*12+MthOff,Inputs!$B17,-Inputs!$B15),0) -> 0 | ... AM81: =-MAX(FV(Inputs!$B16/12,AM$1*12+MthOff,Inputs!$B17,-Inputs!$B15),0) -> 0
A82: Other asset loans
A83: =TEXT(Inputs!$B$60,"") -> Sliema | C83: =-MAX(FV(Inputs!$B128/12,C$1*12+MthOff,Inputs!$B129,-Inputs!$B127),0) -> -46207.53 | D83: =-MAX(FV(Inputs!$B128/12,D$1*12+MthOff,Inputs!$B129,-Inputs!$B127),0) -> -41529.785 | E83: =-MAX(FV(Inputs!$B128/12,E$1*12+MthOff,Inputs!$B129,-Inputs!$B127),0) -> -36709.762 | F83: =-MAX(FV(Inputs!$B128/12,F$1*12+MthOff,Inputs!$B129,-Inputs!$B127),0) -> -31743.133 | G83: =-MAX(FV(Inputs!$B128/12,G$1*12+MthOff,Inputs!$B129,-Inputs!$B127),0) -> -26625.439 | H83: =-MAX(FV(Inputs!$B128/12,H$1*12+MthOff,Inputs!$B129,-Inputs!$B127),0) -> -21352.086 | I83: =-MAX(FV(Inputs!$B128/12,I$1*12+MthOff,Inputs!$B129,-Inputs!$B127),0) -> -15918.339 | J83: =-MAX(FV(Inputs!$B128/12,J$1*12+MthOff,Inputs!$B129,-Inputs!$B127),0) -> -10319.319 | ... AM83: =-MAX(FV(Inputs!$B128/12,AM$1*12+MthOff,Inputs!$B129,-Inputs!$B127),0) -> 0
A84: =TEXT(Inputs!$B$65,"") -> Gzira | C84: =-MAX(FV(Inputs!$B133/12,C$1*12+MthOff,Inputs!$B134,-Inputs!$B132),0) -> -6627.667 | D84: =-MAX(FV(Inputs!$B133/12,D$1*12+MthOff,Inputs!$B134,-Inputs!$B132),0) -> -4339.3195 | E84: =-MAX(FV(Inputs!$B133/12,E$1*12+MthOff,Inputs!$B134,-Inputs!$B132),0) -> -2004.7832 | F84: =-MAX(FV(Inputs!$B133/12,F$1*12+MthOff,Inputs!$B134,-Inputs!$B132),0) -> 0 | G84: =-MAX(FV(Inputs!$B133/12,G$1*12+MthOff,Inputs!$B134,-Inputs!$B132),0) -> 0 | H84: =-MAX(FV(Inputs!$B133/12,H$1*12+MthOff,Inputs!$B134,-Inputs!$B132),0) -> 0 | I84: =-MAX(FV(Inputs!$B133/12,I$1*12+MthOff,Inputs!$B134,-Inputs!$B132),0) -> 0 | J84: =-MAX(FV(Inputs!$B133/12,J$1*12+MthOff,Inputs!$B134,-Inputs!$B132),0) -> 0 | ... AM84: =-MAX(FV(Inputs!$B133/12,AM$1*12+MthOff,Inputs!$B134,-Inputs!$B132),0) -> 0
A85: =TEXT(Inputs!$B$70,"") -> Qormi | C85: =-MAX(FV(Inputs!$B138/12,C$1*12+MthOff,Inputs!$B139,-Inputs!$B137),0) -> -13089.45 | D85: =-MAX(FV(Inputs!$B138/12,D$1*12+MthOff,Inputs!$B139,-Inputs!$B137),0) -> -10689.418 | E85: =-MAX(FV(Inputs!$B138/12,E$1*12+MthOff,Inputs!$B139,-Inputs!$B137),0) -> -8166.5945 | F85: =-MAX(FV(Inputs!$B138/12,F$1*12+MthOff,Inputs!$B139,-Inputs!$B137),0) -> -5514.6991 | G85: =-MAX(FV(Inputs!$B138/12,G$1*12+MthOff,Inputs!$B139,-Inputs!$B137),0) -> -2727.1277 | H85: =-MAX(FV(Inputs!$B138/12,H$1*12+MthOff,Inputs!$B139,-Inputs!$B137),0) -> 0 | I85: =-MAX(FV(Inputs!$B138/12,I$1*12+MthOff,Inputs!$B139,-Inputs!$B137),0) -> 0 | J85: =-MAX(FV(Inputs!$B138/12,J$1*12+MthOff,Inputs!$B139,-Inputs!$B137),0) -> 0 | ... AM85: =-MAX(FV(Inputs!$B138/12,AM$1*12+MthOff,Inputs!$B139,-Inputs!$B137),0) -> 0
A86: =TEXT(Inputs!$B$75,"") -> Gudja | C86: =-MAX(FV(Inputs!$B143/12,C$1*12+MthOff,Inputs!$B144,-Inputs!$B142),0) -> -3952.5609 | D86: =-MAX(FV(Inputs!$B143/12,D$1*12+MthOff,Inputs!$B144,-Inputs!$B142),0) -> -3063.4917 | E86: =-MAX(FV(Inputs!$B143/12,E$1*12+MthOff,Inputs!$B144,-Inputs!$B142),0) -> -2156.4772 | F86: =-MAX(FV(Inputs!$B143/12,F$1*12+MthOff,Inputs!$B144,-Inputs!$B142),0) -> -1231.1552 | G86: =-MAX(FV(Inputs!$B143/12,G$1*12+MthOff,Inputs!$B144,-Inputs!$B142),0) -> -287.15625 | H86: =-MAX(FV(Inputs!$B143/12,H$1*12+MthOff,Inputs!$B144,-Inputs!$B142),0) -> 0 | I86: =-MAX(FV(Inputs!$B143/12,I$1*12+MthOff,Inputs!$B144,-Inputs!$B142),0) -> 0 | J86: =-MAX(FV(Inputs!$B143/12,J$1*12+MthOff,Inputs!$B144,-Inputs!$B142),0) -> 0 | ... AM86: =-MAX(FV(Inputs!$B143/12,AM$1*12+MthOff,Inputs!$B144,-Inputs!$B142),0) -> 0
A87: =TEXT(Inputs!$B$80,"") -> Marsa | C87: =-MAX(FV(Inputs!$B148/12,C$1*12+MthOff,Inputs!$B149,-Inputs!$B147),0) -> -8551.2062 | D87: =-MAX(FV(Inputs!$B148/12,D$1*12+MthOff,Inputs!$B149,-Inputs!$B147),0) -> -7351.3334 | E87: =-MAX(FV(Inputs!$B148/12,E$1*12+MthOff,Inputs!$B149,-Inputs!$B147),0) -> -6114.9653 | F87: =-MAX(FV(Inputs!$B148/12,F$1*12+MthOff,Inputs!$B149,-Inputs!$B147),0) -> -4840.9918 | G87: =-MAX(FV(Inputs!$B148/12,G$1*12+MthOff,Inputs!$B149,-Inputs!$B147),0) -> -3528.2693 | H87: =-MAX(FV(Inputs!$B148/12,H$1*12+MthOff,Inputs!$B149,-Inputs!$B147),0) -> -2175.6191 | I87: =-MAX(FV(Inputs!$B148/12,I$1*12+MthOff,Inputs!$B149,-Inputs!$B147),0) -> -781.82667 | J87: =-MAX(FV(Inputs!$B148/12,J$1*12+MthOff,Inputs!$B149,-Inputs!$B147),0) -> 0 | ... AM87: =-MAX(FV(Inputs!$B148/12,AM$1*12+MthOff,Inputs!$B149,-Inputs!$B147),0) -> 0
A88: =TEXT(Inputs!$B$87,"") -> Jewelry | C88: =-MAX(FV(Inputs!$B153/12,C$1*12+MthOff,Inputs!$B154,-Inputs!$B152),0) -> -1804.7138 | D88: =-MAX(FV(Inputs!$B153/12,D$1*12+MthOff,Inputs!$B154,-Inputs!$B152),0) -> -947.12723 | E88: =-MAX(FV(Inputs!$B153/12,E$1*12+MthOff,Inputs!$B154,-Inputs!$B152),0) -> -63.456301 | F88: =-MAX(FV(Inputs!$B153/12,F$1*12+MthOff,Inputs!$B154,-Inputs!$B152),0) -> 0 | G88: =-MAX(FV(Inputs!$B153/12,G$1*12+MthOff,Inputs!$B154,-Inputs!$B152),0) -> 0 | H88: =-MAX(FV(Inputs!$B153/12,H$1*12+MthOff,Inputs!$B154,-Inputs!$B152),0) -> 0 | I88: =-MAX(FV(Inputs!$B153/12,I$1*12+MthOff,Inputs!$B154,-Inputs!$B152),0) -> 0 | J88: =-MAX(FV(Inputs!$B153/12,J$1*12+MthOff,Inputs!$B154,-Inputs!$B152),0) -> 0 | ... AM88: =-MAX(FV(Inputs!$B153/12,AM$1*12+MthOff,Inputs!$B154,-Inputs!$B152),0) -> 0
A89: =TEXT(Inputs!$B$92,"") -> Car | C89: =-MAX(FV(Inputs!$B158/12,C$1*12+MthOff,Inputs!$B159,-Inputs!$B157),0) -> -5234.2746 | D89: =-MAX(FV(Inputs!$B158/12,D$1*12+MthOff,Inputs!$B159,-Inputs!$B157),0) -> -4298.4123 | E89: =-MAX(FV(Inputs!$B158/12,E$1*12+MthOff,Inputs!$B159,-Inputs!$B157),0) -> -3343.6602 | F89: =-MAX(FV(Inputs!$B158/12,F$1*12+MthOff,Inputs!$B159,-Inputs!$B157),0) -> -2369.6371 | G89: =-MAX(FV(Inputs!$B158/12,G$1*12+MthOff,Inputs!$B159,-Inputs!$B157),0) -> -1375.9539 | H89: =-MAX(FV(Inputs!$B158/12,H$1*12+MthOff,Inputs!$B159,-Inputs!$B157),0) -> -362.21394 | I89: =-MAX(FV(Inputs!$B158/12,I$1*12+MthOff,Inputs!$B159,-Inputs!$B157),0) -> 0 | J89: =-MAX(FV(Inputs!$B158/12,J$1*12+MthOff,Inputs!$B159,-Inputs!$B157),0) -> 0 | ... AM89: =-MAX(FV(Inputs!$B158/12,AM$1*12+MthOff,Inputs!$B159,-Inputs!$B157),0) -> 0
A90: =TEXT(Inputs!$B$97,"") -> Painting | C90: =-MAX(FV(Inputs!$B163/12,C$1*12+MthOff,Inputs!$B164,-Inputs!$B162),0) -> -6544.7251 | D90: =-MAX(FV(Inputs!$B163/12,D$1*12+MthOff,Inputs!$B164,-Inputs!$B162),0) -> -5344.7088 | E90: =-MAX(FV(Inputs!$B163/12,E$1*12+MthOff,Inputs!$B164,-Inputs!$B162),0) -> -4083.2973 | F90: =-MAX(FV(Inputs!$B163/12,F$1*12+MthOff,Inputs!$B164,-Inputs!$B162),0) -> -2757.3496 | G90: =-MAX(FV(Inputs!$B163/12,G$1*12+MthOff,Inputs!$B164,-Inputs!$B162),0) -> -1363.5639 | H90: =-MAX(FV(Inputs!$B163/12,H$1*12+MthOff,Inputs!$B164,-Inputs!$B162),0) -> 0 | I90: =-MAX(FV(Inputs!$B163/12,I$1*12+MthOff,Inputs!$B164,-Inputs!$B162),0) -> 0 | J90: =-MAX(FV(Inputs!$B163/12,J$1*12+MthOff,Inputs!$B164,-Inputs!$B162),0) -> 0 | ... AM90: =-MAX(FV(Inputs!$B163/12,AM$1*12+MthOff,Inputs!$B164,-Inputs!$B162),0) -> 0
A91: =TEXT(Inputs!$B$102,"") -> Boat | C91: =-MAX(FV(Inputs!$B168/12,C$1*12+MthOff,Inputs!$B169,-Inputs!$B167),0) -> -35663.317 | D91: =-MAX(FV(Inputs!$B168/12,D$1*12+MthOff,Inputs!$B169,-Inputs!$B167),0) -> -30165.561 | E91: =-MAX(FV(Inputs!$B168/12,E$1*12+MthOff,Inputs!$B169,-Inputs!$B167),0) -> -24328.716 | F91: =-MAX(FV(Inputs!$B168/12,F$1*12+MthOff,Inputs!$B169,-Inputs!$B167),0) -> -18131.867 | G91: =-MAX(FV(Inputs!$B168/12,G$1*12+MthOff,Inputs!$B169,-Inputs!$B167),0) -> -11552.81 | H91: =-MAX(FV(Inputs!$B168/12,H$1*12+MthOff,Inputs!$B169,-Inputs!$B167),0) -> -4567.9713 | I91: =-MAX(FV(Inputs!$B168/12,I$1*12+MthOff,Inputs!$B169,-Inputs!$B167),0) -> 0 | J91: =-MAX(FV(Inputs!$B168/12,J$1*12+MthOff,Inputs!$B169,-Inputs!$B167),0) -> 0 | ... AM91: =-MAX(FV(Inputs!$B168/12,AM$1*12+MthOff,Inputs!$B169,-Inputs!$B167),0) -> 0
A92: =TEXT(Inputs!$B$107,"") -> Antiques | C92: =-MAX(FV(Inputs!$B173/12,C$1*12+MthOff,Inputs!$B174,-Inputs!$B172),0) -> -2783.618 | D92: =-MAX(FV(Inputs!$B173/12,D$1*12+MthOff,Inputs!$B174,-Inputs!$B172),0) -> -1529.9823 | E92: =-MAX(FV(Inputs!$B173/12,E$1*12+MthOff,Inputs!$B174,-Inputs!$B172),0) -> -238.21612 | F92: =-MAX(FV(Inputs!$B173/12,F$1*12+MthOff,Inputs!$B174,-Inputs!$B172),0) -> 0 | G92: =-MAX(FV(Inputs!$B173/12,G$1*12+MthOff,Inputs!$B174,-Inputs!$B172),0) -> 0 | H92: =-MAX(FV(Inputs!$B173/12,H$1*12+MthOff,Inputs!$B174,-Inputs!$B172),0) -> 0 | I92: =-MAX(FV(Inputs!$B173/12,I$1*12+MthOff,Inputs!$B174,-Inputs!$B172),0) -> 0 | J92: =-MAX(FV(Inputs!$B173/12,J$1*12+MthOff,Inputs!$B174,-Inputs!$B172),0) -> 0 | ... AM92: =-MAX(FV(Inputs!$B173/12,AM$1*12+MthOff,Inputs!$B174,-Inputs!$B172),0) -> 0
A93: Other loan | C93: =-MAX(FV(Inputs!$B178/12,C$1*12+MthOff,Inputs!$B179,-Inputs!$B177),0) -> -3693.1592 | D93: =-MAX(FV(Inputs!$B178/12,D$1*12+MthOff,Inputs!$B179,-Inputs!$B177),0) -> -3304.1671 | E93: =-MAX(FV(Inputs!$B178/12,E$1*12+MthOff,Inputs!$B179,-Inputs!$B177),0) -> -2891.1827 | F93: =-MAX(FV(Inputs!$B178/12,F$1*12+MthOff,Inputs!$B179,-Inputs!$B177),0) -> -2452.7265 | G93: =-MAX(FV(Inputs!$B178/12,G$1*12+MthOff,Inputs!$B179,-Inputs!$B177),0) -> -1987.2271 | H93: =-MAX(FV(Inputs!$B178/12,H$1*12+MthOff,Inputs!$B179,-Inputs!$B177),0) -> -1493.0168 | I93: =-MAX(FV(Inputs!$B178/12,I$1*12+MthOff,Inputs!$B179,-Inputs!$B177),0) -> -968.32473 | J93: =-MAX(FV(Inputs!$B178/12,J$1*12+MthOff,Inputs!$B179,-Inputs!$B177),0) -> -411.27076 | ... AM93: =-MAX(FV(Inputs!$B178/12,AM$1*12+MthOff,Inputs!$B179,-Inputs!$B177),0) -> 0
C94: =SUM(C65:C93) -> 1789619.3 | D94: =SUM(D65:D93) -> 1864141.9 | E94: =SUM(E65:E93) -> 1957643.3 | F94: =SUM(F65:F93) -> 1943566.3 | G94: =SUM(G65:G93) -> 1958032.6 | H94: =SUM(H65:H93) -> 1976480 | I94: =SUM(I65:I93) -> 1995384.7 | J94: =SUM(J65:J93) -> 2020991.9 | ... AM94: =SUM(AM65:AM93) -> 4527387.1
A96: Cash available (after buffer) | C96: =C66-buffer -> 12809.375 | D96: =D66-buffer -> 24162.216 | E96: =E66-buffer -> 41813.279 | F96: =F66-buffer -> -46707.318 | G96: =G66-buffer -> -107685.34 | H96: =H66-buffer -> -165530.45 | I96: =I66-buffer -> -198768.98 | J96: =J66-buffer -> -232568.86 | ... AM96: =AM66-buffer -> -365331.92
A97: Liquidation required | C97: =IF(C96<0,-C96,0) -> 0 | D97: =IF(D96+SUM($C97:C97)<0,-(D96+SUM($C97:C97)),0) -> 0 | E97: =IF(E96+SUM($C97:D97)<0,-(E96+SUM($C97:D97)),0) -> 0 | F97: =IF(F96+SUM($C97:E97)<0,-(F96+SUM($C97:E97)),0) -> 46707.318 | G97: =IF(G96+SUM($C97:F97)<0,-(G96+SUM($C97:F97)),0) -> 60978.019 | H97: =IF(H96+SUM($C97:G97)<0,-(H96+SUM($C97:G97)),0) -> 57845.113 | I97: =IF(I96+SUM($C97:H97)<0,-(I96+SUM($C97:H97)),0) -> 33238.529 | J97: =IF(J96+SUM($C97:I97)<0,-(J96+SUM($C97:I97)),0) -> 33799.885 | K97: =IF(K96+SUM($C97:J97)<0,-(K96+SUM($C97:J97)),0) -> 51555.296 | ... AM97: =IF(AM96+SUM($C97:AL97)<0,-(AM96+SUM($C97:AL97)),0) -> 0
A99: Liquidations
A101: Stock market equity
A102: b/fwd | C102: =C80 -> 31987.064 | D102: =C105 -> 31987.064 | E102: =D105 -> 27189.005 | F102: =E105 -> 31987.064 | G102: =F105 -> 0 | H102: =G105 -> 0 | I102: =H105 -> 0 | J102: =I105 -> 0 | K102: =J105 -> 0 | ... AM102: =AL105 -> 0
A103: Disposals | C103: =-MIN(C102, C97/(1-Inputs!$B$273)) -> 0 | D103: =-MIN(D102, D97/(1-Inputs!$B$273)) -> 0 | E103: =-MIN(E102, E97/(1-Inputs!$B$273)) -> 0 | F103: =-MIN(F102, F97/(1-Inputs!$B$273)) -> -31987.064 | G103: =-MIN(G102, G97/(1-Inputs!$B$273)) -> 0 | H103: =-MIN(H102, H97/(1-Inputs!$B$273)) -> 0 | I103: =-MIN(I102, I97/(1-Inputs!$B$273)) -> 0 | J103: =-MIN(J102, J97/(1-Inputs!$B$273)) -> 0 | ... AM103: =-MIN(AM102, AM97/(1-Inputs!$B$273)) -> 0
A104: Growth | C104: 0 | D104: =SUM(D102:D103)*IF(AND(Inputs!$B$218<>"",D$2=Inputs!$B$218),-Inputs!$B$219,IF(AND(Inputs!$B$218<>"",D$2>Inputs!$B$218,D$2<=Inputs!$B$218+Inputs!$B$220),(1/(1-Inputs!$B$219))^(1/Inputs!$B$220)-1,IF(AND(Inputs!$B$223<>"",D$2=Inputs!$B$223),-Inputs!$B$224,IF(AND(Inputs!$B$223<>"",D$2>Inputs!$B$223,D$2<=Inputs!$B$223+Inputs!$B$225),(1/(1-Inputs!$B$224))^(1/Inputs!$B$225)-1,IF(AND(Inputs!$B$228<>"",D$2=Inputs!$B$228),-Inputs!$B$229,IF(AND(Inputs!$B$228<>"",D$2>Inputs!$B$228,D$2<=Inputs!$B$228+Inputs!$B$230),(1/(1-Inputs!$B$229))^(1/Inputs!$B$230)-1,IF(AND(Inputs!$B$233<>"",D$2=Inputs!$B$233),-Inputs!$B$234,IF(AND(Inputs!$B$233<>"",D$2>Inputs!$B$233,D$2<=Inputs!$B$233+Inputs!$B$235),(1/(1-Inputs!$B$234))^(1/Inputs!$B$235)-1,IF(AND(Inputs!$B$238<>"",D$2=Inputs!$B$238),-Inputs!$B$239,IF(AND(Inputs!$B$238<>"",D$2>Inputs!$B$238,D$2<=Inputs!$B$238+Inputs!$B$240),(1/(1-Inputs!$B$239))^(1/Inputs!$B$240)-1,stinc)))))))))) -> -4798.0597 | E104: =SUM(E102:E103)*IF(AND(Inputs!$B$218<>"",E$2=Inputs!$B$218),-Inputs!$B$219,IF(AND(Inputs!$B$218<>"",E$2>Inputs!$B$218,E$2<=Inputs!$B$218+Inputs!$B$220),(1/(1-Inputs!$B$219))^(1/Inputs!$B$220)-1,IF(AND(Inputs!$B$223<>"",E$2=Inputs!$B$223),-Inputs!$B$224,IF(AND(Inputs!$B$223<>"",E$2>Inputs!$B$223,E$2<=Inputs!$B$223+Inputs!$B$225),(1/(1-Inputs!$B$224))^(1/Inputs!$B$225)-1,IF(AND(Inputs!$B$228<>"",E$2=Inputs!$B$228),-Inputs!$B$229,IF(AND(Inputs!$B$228<>"",E$2>Inputs!$B$228,E$2<=Inputs!$B$228+Inputs!$B$230),(1/(1-Inputs!$B$229))^(1/Inputs!$B$230)-1,IF(AND(Inputs!$B$233<>"",E$2=Inputs!$B$233),-Inputs!$B$234,IF(AND(Inputs!$B$233<>"",E$2>Inputs!$B$233,E$2<=Inputs!$B$233+Inputs!$B$235),(1/(1-Inputs!$B$234))^(1/Inputs!$B$235)-1,IF(AND(Inputs!$B$238<>"",E$2=Inputs!$B$238),-Inputs!$B$239,IF(AND(Inputs!$B$238<>"",E$2>Inputs!$B$238,E$2<=Inputs!$B$238+Inputs!$B$240),(1/(1-Inputs!$B$239))^(1/Inputs!$B$240)-1,stinc)))))))))) -> 4798.0597 | F104: =SUM(F102:F103)*IF(AND(Inputs!$B$218<>"",F$2=Inputs!$B$218),-Inputs!$B$219,IF(AND(Inputs!$B$218<>"",F$2>Inputs!$B$218,F$2<=Inputs!$B$218+Inputs!$B$220),(1/(1-Inputs!$B$219))^(1/Inputs!$B$220)-1,IF(AND(Inputs!$B$223<>"",F$2=Inputs!$B$223),-Inputs!$B$224,IF(AND(Inputs!$B$223<>"",F$2>Inputs!$B$223,F$2<=Inputs!$B$223+Inputs!$B$225),(1/(1-Inputs!$B$224))^(1/Inputs!$B$225)-1,IF(AND(Inputs!$B$228<>"",F$2=Inputs!$B$228),-Inputs!$B$229,IF(AND(Inputs!$B$228<>"",F$2>Inputs!$B$228,F$2<=Inputs!$B$228+Inputs!$B$230),(1/(1-Inputs!$B$229))^(1/Inputs!$B$230)-1,IF(AND(Inputs!$B$233<>"",F$2=Inputs!$B$233),-Inputs!$B$234,IF(AND(Inputs!$B$233<>"",F$2>Inputs!$B$233,F$2<=Inputs!$B$233+Inputs!$B$235),(1/(1-Inputs!$B$234))^(1/Inputs!$B$235)-1,IF(AND(Inputs!$B$238<>"",F$2=Inputs!$B$238),-Inputs!$B$239,IF(AND(Inputs!$B$238<>"",F$2>Inputs!$B$238,F$2<=Inputs!$B$238+Inputs!$B$240),(1/(1-Inputs!$B$239))^(1/Inputs!$B$240)-1,stinc)))))))))) -> 0 | G104: =SUM(G102:G103)*IF(AND(Inputs!$B$218<>"",G$2=Inputs!$B$218),-Inputs!$B$219,IF(AND(Inputs!$B$218<>"",G$2>Inputs!$B$218,G$2<=Inputs!$B$218+Inputs!$B$220),(1/(1-Inputs!$B$219))^(1/Inputs!$B$220)-1,IF(AND(Inputs!$B$223<>"",G$2=Inputs!$B$223),-Inputs!$B$224,IF(AND(Inputs!$B$223<>"",G$2>Inputs!$B$223,G$2<=Inputs!$B$223+Inputs!$B$225),(1/(1-Inputs!$B$224))^(1/Inputs!$B$225)-1,IF(AND(Inputs!$B$228<>"",G$2=Inputs!$B$228),-Inputs!$B$229,IF(AND(Inputs!$B$228<>"",G$2>Inputs!$B$228,G$2<=Inputs!$B$228+Inputs!$B$230),(1/(1-Inputs!$B$229))^(1/Inputs!$B$230)-1,IF(AND(Inputs!$B$233<>"",G$2=Inputs!$B$233),-Inputs!$B$234,IF(AND(Inputs!$B$233<>"",G$2>Inputs!$B$233,G$2<=Inputs!$B$233+Inputs!$B$235),(1/(1-Inputs!$B$234))^(1/Inputs!$B$235)-1,IF(AND(Inputs!$B$238<>"",G$2=Inputs!$B$238),-Inputs!$B$239,IF(AND(Inputs!$B$238<>"",G$2>Inputs!$B$238,G$2<=Inputs!$B$238+Inputs!$B$240),(1/(1-Inputs!$B$239))^(1/Inputs!$B$240)-1,stinc)))))))))) -> 0 | H104: =SUM(H102:H103)*IF(AND(Inputs!$B$218<>"",H$2=Inputs!$B$218),-Inputs!$B$219,IF(AND(Inputs!$B$218<>"",H$2>Inputs!$B$218,H$2<=Inputs!$B$218+Inputs!$B$220),(1/(1-Inputs!$B$219))^(1/Inputs!$B$220)-1,IF(AND(Inputs!$B$223<>"",H$2=Inputs!$B$223),-Inputs!$B$224,IF(AND(Inputs!$B$223<>"",H$2>Inputs!$B$223,H$2<=Inputs!$B$223+Inputs!$B$225),(1/(1-Inputs!$B$224))^(1/Inputs!$B$225)-1,IF(AND(Inputs!$B$228<>"",H$2=Inputs!$B$228),-Inputs!$B$229,IF(AND(Inputs!$B$228<>"",H$2>Inputs!$B$228,H$2<=Inputs!$B$228+Inputs!$B$230),(1/(1-Inputs!$B$229))^(1/Inputs!$B$230)-1,IF(AND(Inputs!$B$233<>"",H$2=Inputs!$B$233),-Inputs!$B$234,IF(AND(Inputs!$B$233<>"",H$2>Inputs!$B$233,H$2<=Inputs!$B$233+Inputs!$B$235),(1/(1-Inputs!$B$234))^(1/Inputs!$B$235)-1,IF(AND(Inputs!$B$238<>"",H$2=Inputs!$B$238),-Inputs!$B$239,IF(AND(Inputs!$B$238<>"",H$2>Inputs!$B$238,H$2<=Inputs!$B$238+Inputs!$B$240),(1/(1-Inputs!$B$239))^(1/Inputs!$B$240)-1,stinc)))))))))) -> 0 | I104: =SUM(I102:I103)*IF(AND(Inputs!$B$218<>"",I$2=Inputs!$B$218),-Inputs!$B$219,IF(AND(Inputs!$B$218<>"",I$2>Inputs!$B$218,I$2<=Inputs!$B$218+Inputs!$B$220),(1/(1-Inputs!$B$219))^(1/Inputs!$B$220)-1,IF(AND(Inputs!$B$223<>"",I$2=Inputs!$B$223),-Inputs!$B$224,IF(AND(Inputs!$B$223<>"",I$2>Inputs!$B$223,I$2<=Inputs!$B$223+Inputs!$B$225),(1/(1-Inputs!$B$224))^(1/Inputs!$B$225)-1,IF(AND(Inputs!$B$228<>"",I$2=Inputs!$B$228),-Inputs!$B$229,IF(AND(Inputs!$B$228<>"",I$2>Inputs!$B$228,I$2<=Inputs!$B$228+Inputs!$B$230),(1/(1-Inputs!$B$229))^(1/Inputs!$B$230)-1,IF(AND(Inputs!$B$233<>"",I$2=Inputs!$B$233),-Inputs!$B$234,IF(AND(Inputs!$B$233<>"",I$2>Inputs!$B$233,I$2<=Inputs!$B$233+Inputs!$B$235),(1/(1-Inputs!$B$234))^(1/Inputs!$B$235)-1,IF(AND(Inputs!$B$238<>"",I$2=Inputs!$B$238),-Inputs!$B$239,IF(AND(Inputs!$B$238<>"",I$2>Inputs!$B$238,I$2<=Inputs!$B$238+Inputs!$B$240),(1/(1-Inputs!$B$239))^(1/Inputs!$B$240)-1,stinc)))))))))) -> 0 | J104: =SUM(J102:J103)*IF(AND(Inputs!$B$218<>"",J$2=Inputs!$B$218),-Inputs!$B$219,IF(AND(Inputs!$B$218<>"",J$2>Inputs!$B$218,J$2<=Inputs!$B$218+Inputs!$B$220),(1/(1-Inputs!$B$219))^(1/Inputs!$B$220)-1,IF(AND(Inputs!$B$223<>"",J$2=Inputs!$B$223),-Inputs!$B$224,IF(AND(Inputs!$B$223<>"",J$2>Inputs!$B$223,J$2<=Inputs!$B$223+Inputs!$B$225),(1/(1-Inputs!$B$224))^(1/Inputs!$B$225)-1,IF(AND(Inputs!$B$228<>"",J$2=Inputs!$B$228),-Inputs!$B$229,IF(AND(Inputs!$B$228<>"",J$2>Inputs!$B$228,J$2<=Inputs!$B$228+Inputs!$B$230),(1/(1-Inputs!$B$229))^(1/Inputs!$B$230)-1,IF(AND(Inputs!$B$233<>"",J$2=Inputs!$B$233),-Inputs!$B$234,IF(AND(Inputs!$B$233<>"",J$2>Inputs!$B$233,J$2<=Inputs!$B$233+Inputs!$B$235),(1/(1-Inputs!$B$234))^(1/Inputs!$B$235)-1,IF(AND(Inputs!$B$238<>"",J$2=Inputs!$B$238),-Inputs!$B$239,IF(AND(Inputs!$B$238<>"",J$2>Inputs!$B$238,J$2<=Inputs!$B$238+Inputs!$B$240),(1/(1-Inputs!$B$239))^(1/Inputs!$B$240)-1,stinc)))))))))) -> 0 | K104: =SUM(K102:K103)*IF(AND(Inputs!$B$218<>"",K$2=Inputs!$B$218),-Inputs!$B$219,IF(AND(Inputs!$B$218<>"",K$2>Inputs!$B$218,K$2<=Inputs!$B$218+Inputs!$B$220),(1/(1-Inputs!$B$219))^(1/Inputs!$B$220)-1,IF(AND(Inputs!$B$223<>"",K$2=Inputs!$B$223),-Inputs!$B$224,IF(AND(Inputs!$B$223<>"",K$2>Inputs!$B$223,K$2<=Inputs!$B$223+Inputs!$B$225),(1/(1-Inputs!$B$224))^(1/Inputs!$B$225)-1,IF(AND(Inputs!$B$228<>"",K$2=Inputs!$B$228),-Inputs!$B$229,IF(AND(Inputs!$B$228<>"",K$2>Inputs!$B$228,K$2<=Inputs!$B$228+Inputs!$B$230),(1/(1-Inputs!$B$229))^(1/Inputs!$B$230)-1,IF(AND(Inputs!$B$233<>"",K$2=Inputs!$B$233),-Inputs!$B$234,IF(AND(Inputs!$B$233<>"",K$2>Inputs!$B$233,K$2<=Inputs!$B$233+Inputs!$B$235),(1/(1-Inputs!$B$234))^(1/Inputs!$B$235)-1,IF(AND(Inputs!$B$238<>"",K$2=Inputs!$B$238),-Inputs!$B$239,IF(AND(Inputs!$B$238<>"",K$2>Inputs!$B$238,K$2<=Inputs!$B$238+Inputs!$B$240),(1/(1-Inputs!$B$239))^(1/Inputs!$B$240)-1,stinc)))))))))) -> 0 | ... AM104: =SUM(AM102:AM103)*IF(AND(Inputs!$B$218<>"",AM$2=Inputs!$B$218),-Inputs!$B$219,IF(AND(Inputs!$B$218<>"",AM$2>Inputs!$B$218,AM$2<=Inputs!$B$218+Inputs!$B$220),(1/(1-Inputs!$B$219))^(1/Inputs!$B$220)-1,IF(AND(Inputs!$B$223<>"",AM$2=Inputs!$B$223),-Inputs!$B$224,IF(AND(Inputs!$B$223<>"",AM$2>Inputs!$B$223,AM$2<=Inputs!$B$223+Inputs!$B$225),(1/(1-Inputs!$B$224))^(1/Inputs!$B$225)-1,IF(AND(Inputs!$B$228<>"",AM$2=Inputs!$B$228),-Inputs!$B$229,IF(AND(Inputs!$B$228<>"",AM$2>Inputs!$B$228,AM$2<=Inputs!$B$228+Inputs!$B$230),(1/(1-Inputs!$B$229))^(1/Inputs!$B$230)-1,IF(AND(Inputs!$B$233<>"",AM$2=Inputs!$B$233),-Inputs!$B$234,IF(AND(Inputs!$B$233<>"",AM$2>Inputs!$B$233,AM$2<=Inputs!$B$233+Inputs!$B$235),(1/(1-Inputs!$B$234))^(1/Inputs!$B$235)-1,IF(AND(Inputs!$B$238<>"",AM$2=Inputs!$B$238),-Inputs!$B$239,IF(AND(Inputs!$B$238<>"",AM$2>Inputs!$B$238,AM$2<=Inputs!$B$238+Inputs!$B$240),(1/(1-Inputs!$B$239))^(1/Inputs!$B$240)-1,stinc)))))))))) -> 0
A105: c/fwd | C105: =SUM(C102:C104) -> 31987.064 | D105: =SUM(D102:D104) -> 27189.005 | E105: =SUM(E102:E104) -> 31987.064 | F105: =SUM(F102:F104) -> 0 | G105: =SUM(G102:G104) -> 0 | H105: =SUM(H102:H104) -> 0 | I105: =SUM(I102:I104) -> 0 | J105: =SUM(J102:J104) -> 0 | ... AM105: =SUM(AM102:AM104) -> 0
...
