Workbook
Name AgeRange: RetNorm_Engine!$C$3:INDEX(RetNorm_Engine!$C$3:$XFD$3, COUNTA(RetNorm_Engine!$C$3:$XFD$3))
Name buffer: Inputs!$B$191
Name ChartCash_Early: RetEarly_Engine!$C$247:INDEX(RetEarly_Engine!$C$247:$XFD$247, COUNTA(RetEarly_Engine!$C$247:$XFD$247))
Name ChartCash_Norm: RetNorm_Engine!$C$247:INDEX(RetNorm_Engine!$C$247:$XFD$247, COUNTA(RetNorm_Engine!$C$247:$XFD$247))
Name ChartNW_Early: RetEarly_Engine!$C$248:INDEX(RetEarly_Engine!$C$248:$XFD$248, COUNTA(RetEarly_Engine!$C$248:$XFD$248))
Name ChartNW_Norm: RetNorm_Engine!$C$248:INDEX(RetNorm_Engine!$C$248:$XFD$248, COUNTA(RetNorm_Engine!$C$248:$XFD$248))
Name EndAge: Inputs!$B$166
Name inf: Inputs!$B$177
Name MthOff: Inputs!$B$206
Name MthRem: Inputs!$B$205
Name princ: Inputs!$B$179
Name ProRate: Inputs!$B$207
Name RetAge: Inputs!$B$19
Name rinc: Inputs!$B$187
Name sincr: Inputs!$B$185
Name stinc: Inputs!$B$183

Sheet Inputs
B1: User inputs | D1: User Tooltips | E1: UI Notes | F1: Excel helpers
A2: QUICK START
A4: Your age | B4: 48 | D4: Must be entered
A6: Current net annual income | B6: 80000 | D6: Net of tax, from employment or self-employment
A8: Total cash balances | B8: 50000 | D8: current and savings accounts, bonds, term deposits
A10: Stock market investments | B10: 30000 | D10: Current market value of equity portfolio
A12: Home current market value | B12: 600000 | D12: Leave blank if not a home owner
A14: Home loan (mortgage)
A15: Balance | B15: 50000 | D15: Leave blank if no mortgage | F15: Months remaining | G15: =IFERROR(NPER(B16/12,-B17,B15),"") -> 68.044529
A16: Interest rate | B16: 0.03 | F16: Years remaining | G16: =IFERROR(G15/12,"") -> 5.6703774
A17: Monthly repayment | B17: 800
A19: Statutory retirement age | B19: 65 | D19: Year at which pension starts
A21: Annual pension at retirement | B21: 16000 | D21: Net annual state pension entitlement
A23: Housing rent | D23: if not a home owner | E23: show only if not a home owner (B12="")
A25: Annual living expenses | B25: 50000
A28: DEEPER DIVE | E28: Activated only if user wants to
A30: Dependents
A32: Dependent 1
A33: Name | B33: John | D33: Leave blank if none
A34: Annual cost | B34: 2000 | D34: Food, education, healthcare, etc. | E34: Hide until user enters dependent name
A35: Years to support | B35: 3 | D35: Years from now | E35: Hide until user enters dependent name
A37: Dependent 2
A38: Name | B38: Jack | D38: Leave blank if none
A39: Annual cost | B39: 1000 | D39: Food, education, healthcare, etc. | E39: Hide until user enters dependent name
A40: Years to support | B40: 5 | D40: Years from now | E40: Hide until user enters dependent name
A42: Dependent 3
A43: Name | B43: Bill | D43: Leave blank if none
A44: Annual cost | B44: 4000 | D44: Food, education, healthcare, etc. | E44: Hide until user enters dependent name
A45: Years to support | B45: 2 | D45: Years from now | E45: Hide until user enters dependent name
A47: Dependent 4
A48: Name | B48: Stephen | D48: Leave blank if none
A49: Annual cost | B49: 2500 | D49: Food, education, healthcare, etc. | E49: Hide until user enters dependent name
A50: Years to support | B50: 3 | D50: Years from now | E50: Hide until user enters dependent name
A52: Dependent 5
A53: Name | B53: Jane | D53: Leave blank if none
A54: Annual cost | B54: 2860 | D54: Food, education, healthcare, etc. | E54: Hide until user enters dependent name
A55: Years to support | B55: 6 | D55: Years from now | E55: Hide until user enters dependent name
A57: Investment Properties
A59: Property 1
A60: Name | B60: Sliema | D60: Leave blank if none
A61: Market value | B61: 300000 | E61: Hide until user enters property name
A62: Annual costs | B62: 5000 | D62: Repairs, maintenance, etc. | E62: Hide until user enters property name
A64: Property 2
A65: Name | B65: Gzira | D65: Leave blank if none
A66: Market value | B66: 150000 | E66: Hide until user enters property name
A67: Annual costs | B67: 2000 | D67: Repairs, maintenance, etc. | E67: Hide until user enters property name
A69: Property 3
A70: Name | B70: Qormi | D70: Leave blank if none
A71: Market value | B71: 220000 | E71: Hide until user enters property name
A72: Annual costs | B72: 1200 | D72: Repairs, maintenance, etc. | E72: Hide until user enters property name
A74: Property 4
A75: Name | B75: Gudja | D75: Leave blank if none
A76: Market value | B76: 80000 | E76: Hide until user enters property name
A77: Annual costs | B77: 1000 | D77: Repairs, maintenance, etc. | E77: Hide until user enters property name
A79: Property 5
A80: Name | B80: Marsa | D80: Leave blank if none
A81: Market value | B81: 120000 | E81: Hide until user enters property name
A82: Annual costs | B82: 800 | D82: Repairs, maintenance, etc. | E82: Hide until user enters property name
A84: Other income
A86: ="Rental income: "&B60 -> Rental income: Sliema | B86: 12000 | D86: net annual after all costs and tax | E86: Show with property name only if name was entered
A87: ="Rental income: "&B65 -> Rental income: Gzira | B87: 10000 | D87: net annual after all costs and tax | E87: Show with property name only if name was entered
A88: ="Rental income: "&B70 -> Rental income: Qormi | B88: 8000 | D88: net annual after all costs and tax | E88: Show with property name only if name was entered
A89: ="Rental income: "&B75 -> Rental income: Gudja | B89: 5000 | D89: net annual after all costs and tax | E89: Show with property name only if name was entered
A90: ="Rental income: "&B80 -> Rental income: Marsa | B90: 6500 | D90: net annual after all costs and tax | E90: Show with property name only if name was entered
A92: Other work income (net annual) | B92: 2000 | D92: Part-time / consulting / side projects etc. Leave blank if none
A93: Continue other work until age | B93: 58 | E93: Show only if other work income entered
A95: Other loans
A97: Credit card balances | B97: 1000 | D97: Assumed cleared in Year 1. Leave blank if none
A99: =B60 & " Property" -> Sliema Property
A100: Balance | B100: 50000 | D100: Enter 0 or leave blank if none | F100: Months remaining | G100: =IFERROR(NPER(B101/12,-B102,B100),"") -> 115.21661
A101: Interest rate | B101: 0.03 | F101: Years remaining | G101: =IFERROR(G100/12,"") -> 9.6013842
A102: Monthly repayment | B102: 500
A104: =B65 & " Property" -> Gzira Property
A105: Balance | B105: 8500 | D105: Enter 0 or leave blank if none | F105: Months remaining | G105: =IFERROR(NPER(B106/12,-B107,B105),"") -> 44.117015
A106: Interest rate | B106: 0.02 | F106: Years remaining | G106: =IFERROR(G105/12,"") -> 3.6764179
A107: Monthly repayment | B107: 200
A109: =B70& " Property" -> Qormi Property
A110: Balance | B110: 15000 | D110: Enter 0 or leave blank if none | F110: Months remaining | G110: =IFERROR(NPER(B111/12,-B112,B110),"") -> 69.187439
A111: Interest rate | B111: 0.05 | F111: Years remaining | G111: =IFERROR(G110/12,"") -> 5.7656199
A112: Monthly repayment | B112: 250
A114: =B75 & " Property" -> Gudja Property
A115: Balance | B115: 4680 | D115: Enter 0 or leave blank if none | F115: Months remaining | G115: =IFERROR(NPER(B116/12,-B117,B115),"") -> 61.603232
A116: Interest rate | B116: 0.02 | F116: Years remaining | G116: =IFERROR(G115/12,"") -> 5.1336027
A117: Monthly repayment | B117: 80
A119: =B80& " Property" -> Marsa Property
A120: Balance | B120: 9524 | D120: Enter 0 or leave blank if none | F120: Months remaining | G120: =IFERROR(NPER(B121/12,-B122,B120),"") -> 88.577073
A121: Interest rate | B121: 0.03 | F121: Years remaining | G121: =IFERROR(G120/12,"") -> 7.3814228
A122: Monthly repayment | B122: 120
A124: Other loan
A125: Balance | B125: 4000 | D125: Leave blank if none | F125: Months remaining | G125: =IFERROR(NPER(B126/12,-B127,B125),"") -> 102.42033
A126: Interest rate | B126: 0.06 | F126: Years remaining | G126: =IFERROR(G125/12,"") -> 8.5350271
A127: Monthly repayment | B127: 50
A129: Major life income events
A131: Income Event 1
A132: Name | B132: Inheritance | D132: Leave blank if none
A133: Amount | B133: 50000 | D133: Enter 0 or leave blank if none
A134: Year | B134: 2035
A136: Income Event 2
A137: Name | B137: Sell Painting | D137: Leave blank if none
A138: Amount | B138: 10000 | D138: Enter 0 or leave blank if none
...

Sheet Output
V2: Retire at | AA2: ="Retire at "&RetEarly_Engine!B3 -> Retire at 52
V3: =RetEarly_Engine!B3 -> 52 | AA3: ="Retire at "&RetAge -> Retire at 65

Sheet RetNorm_Engine
B1: 0 | C1: 1 | D1: =C1+1 -> 2 | E1: =D1+1 -> 3 | F1: =E1+1 -> 4 | G1: =F1+1 -> 5 | H1: =G1+1 -> 6 | I1: =H1+1 -> 7 | J1: =I1+1 -> 8 | K1: =J1+1 -> 9 | ... AM1: =AL1+1 -> 37
B2: Year | C2: =YEAR(TODAY()) -> 2026 | D2: =C2+1 -> 2027 | E2: =D2+1 -> 2028 | F2: =E2+1 -> 2029 | G2: =F2+1 -> 2030 | H2: =G2+1 -> 2031 | I2: =H2+1 -> 2032 | J2: =I2+1 -> 2033 | K2: =J2+1 -> 2034 | ... AM2: =AL2+1 -> 2062
B3: =Inputs!B19 -> 65 | C3: =Inputs!B4 -> 48 | D3: =C3+1 -> 49 | E3: =D3+1 -> 50 | F3: =E3+1 -> 51 | G3: =F3+1 -> 52 | H3: =G3+1 -> 53 | I3: =H3+1 -> 54 | J3: =I3+1 -> 55 | K3: =J3+1 -> 56 | ... AM3: =AL3+1 -> 84
A4: Inflows
A5: Net employment / self-employment income | C5: =IF(AND(Inputs!$B$19>C3,$B$3>C3),Inputs!$B$6*(1+sincr)^B1,0)*ProRate -> 66666.667 | D5: =IF(AND(Inputs!$B$19>D3,$B$3>D3),Inputs!$B$6*(1+sincr)^C1,0) -> 82400 | E5: =IF(AND(Inputs!$B$19>E3,$B$3>E3),Inputs!$B$6*(1+sincr)^D1,0) -> 84872 | F5: =IF(AND(Inputs!$B$19>F3,$B$3>F3),Inputs!$B$6*(1+sincr)^E1,0) -> 87418.16 | G5: =IF(AND(Inputs!$B$19>G3,$B$3>G3),Inputs!$B$6*(1+sincr)^F1,0) -> 90040.705 | H5: =IF(AND(Inputs!$B$19>H3,$B$3>H3),Inputs!$B$6*(1+sincr)^G1,0) -> 92741.926 | I5: =IF(AND(Inputs!$B$19>I3,$B$3>I3),Inputs!$B$6*(1+sincr)^H1,0) -> 95524.184 | J5: =IF(AND(Inputs!$B$19>J3,$B$3>J3),Inputs!$B$6*(1+sincr)^I1,0) -> 98389.909 | K5: =IF(AND(Inputs!$B$19>K3,$B$3>K3),Inputs!$B$6*(1+sincr)^J1,0) -> 101341.61 | ... AM5: =IF(AND(Inputs!$B$19>AM3,$B$3>AM3),Inputs!$B$6*(1+sincr)^AL1,0) -> 0
A6: Net from other work | C6: =IF(C$3<=Inputs!$B$93,Inputs!$B$92,0)*(1+inf)^B$1*ProRate -> 1666.6667 | D6: =IF(D$3<=Inputs!$B$93,Inputs!$B$92,0)*(1+inf)^C$1 -> 2050 | E6: =IF(E$3<=Inputs!$B$93,Inputs!$B$92,0)*(1+inf)^D$1 -> 2101.25 | F6: =IF(F$3<=Inputs!$B$93,Inputs!$B$92,0)*(1+inf)^E$1 -> 2153.7812 | G6: =IF(G$3<=Inputs!$B$93,Inputs!$B$92,0)*(1+inf)^F$1 -> 2207.6258 | H6: =IF(H$3<=Inputs!$B$93,Inputs!$B$92,0)*(1+inf)^G$1 -> 2262.8164 | I6: =IF(I$3<=Inputs!$B$93,Inputs!$B$92,0)*(1+inf)^H$1 -> 2319.3868 | J6: =IF(J$3<=Inputs!$B$93,Inputs!$B$92,0)*(1+inf)^I$1 -> 2377.3715 | K6: =IF(K$3<=Inputs!$B$93,Inputs!$B$92,0)*(1+inf)^J$1 -> 2436.8058 | ... AM6: =IF(AM$3<=Inputs!$B$93,Inputs!$B$92,0)*(1+inf)^AL$1 -> 0
A7: Net rental income from other properties
A8: =TEXT(Inputs!$B$60,"") -> Sliema | C8: =Inputs!B86*ProRate -> 10000 | D8: =C8*(1+rinc) -> 10300 | E8: =D8*(1+rinc) -> 10609 | F8: =E8*(1+rinc) -> 10927.27 | G8: =F8*(1+rinc) -> 11255.088 | H8: =G8*(1+rinc) -> 11592.741 | I8: =H8*(1+rinc) -> 11940.523 | J8: =I8*(1+rinc) -> 12298.739 | K8: =J8*(1+rinc) -> 12667.701 | ... AM8: =AL8*(1+rinc) -> 28982.783
A9: =TEXT(Inputs!$B$65,"") -> Gzira | C9: =Inputs!B87*ProRate -> 8333.3333 | D9: =C9*(1+rinc) -> 8583.3333 | E9: =D9*(1+rinc) -> 8840.8333 | F9: =E9*(1+rinc) -> 9106.0583 | G9: =F9*(1+rinc) -> 9379.2401 | H9: =G9*(1+rinc) -> 9660.6173 | I9: =H9*(1+rinc) -> 9950.4358 | J9: =I9*(1+rinc) -> 10248.949 | K9: =J9*(1+rinc) -> 10556.417 | ... AM9: =AL9*(1+rinc) -> 24152.319
A10: =TEXT(Inputs!$B$70,"") -> Qormi | C10: =Inputs!B88*ProRate -> 6666.6667 | D10: =C10*(1+rinc) -> 6866.6667 | E10: =D10*(1+rinc) -> 7072.6667 | F10: =E10*(1+rinc) -> 7284.8467 | G10: =F10*(1+rinc) -> 7503.3921 | H10: =G10*(1+rinc) -> 7728.4938 | I10: =H10*(1+rinc) -> 7960.3486 | J10: =I10*(1+rinc) -> 8199.1591 | K10: =J10*(1+rinc) -> 8445.1339 | ... AM10: =AL10*(1+rinc) -> 19321.856
A11: =TEXT(Inputs!$B$75,"") -> Gudja | C11: =Inputs!B89*ProRate -> 4166.6667 | D11: =C11*(1+rinc) -> 4291.6667 | E11: =D11*(1+rinc) -> 4420.4167 | F11: =E11*(1+rinc) -> 4553.0292 | G11: =F11*(1+rinc) -> 4689.62 | H11: =G11*(1+rinc) -> 4830.3086 | I11: =H11*(1+rinc) -> 4975.2179 | J11: =I11*(1+rinc) -> 5124.4744 | K11: =J11*(1+rinc) -> 5278.2087 | ... AM11: =AL11*(1+rinc) -> 12076.16
A12: =TEXT(Inputs!$B$80,"") -> Marsa | C12: =Inputs!B90*ProRate -> 5416.6667 | D12: =C12*(1+rinc) -> 5579.1667 | E12: =D12*(1+rinc) -> 5746.5417 | F12: =E12*(1+rinc) -> 5918.9379 | G12: =F12*(1+rinc) -> 6096.5061 | H12: =G12*(1+rinc) -> 6279.4012 | I12: =H12*(1+rinc) -> 6467.7833 | J12: =I12*(1+rinc) -> 6661.8168 | K12: =J12*(1+rinc) -> 6861.6713 | ... AM12: =AL12*(1+rinc) -> 15699.008
A13: Full pension | C13: =IF(C$3<Inputs!$B$19,0,Inputs!$B$21)*(1+inf)^B$1*ProRate -> 0 | D13: =IF(D$3<Inputs!$B$19,0,Inputs!$B$21)*(1+inf)^C$1 -> 0 | E13: =IF(E$3<Inputs!$B$19,0,Inputs!$B$21)*(1+inf)^D$1 -> 0 | F13: =IF(F$3<Inputs!$B$19,0,Inputs!$B$21)*(1+inf)^E$1 -> 0 | G13: =IF(G$3<Inputs!$B$19,0,Inputs!$B$21)*(1+inf)^F$1 -> 0 | H13: =IF(H$3<Inputs!$B$19,0,Inputs!$B$21)*(1+inf)^G$1 -> 0 | I13: =IF(I$3<Inputs!$B$19,0,Inputs!$B$21)*(1+inf)^H$1 -> 0 | J13: =IF(J$3<Inputs!$B$19,0,Inputs!$B$21)*(1+inf)^I$1 -> 0 | K13: =IF(K$3<Inputs!$B$19,0,Inputs!$B$21)*(1+inf)^J$1 -> 0 | ... AM13: =IF(AM$3<Inputs!$B$19,0,Inputs!$B$21)*(1+inf)^AL$1 -> 38920.565
A14: Pension reduction from early retirement | C14: =MIN(0,MAX(-IF(C13=0,0,(Inputs!$B$19-INDEX(3:3,MATCH(0,5:5,0))))*Inputs!$B$189*(1+inf)^B$1*ProRate,-C13)) -> 0 | D14: =MIN(0,MAX(-IF(D13=0,0,(Inputs!$B$19-INDEX(3:3,MATCH(0,5:5,0))))*Inputs!$B$189*(1+inf)^C$1,-D13)) -> 0 | E14: =MIN(0,MAX(-IF(E13=0,0,(Inputs!$B$19-INDEX(3:3,MATCH(0,5:5,0))))*Inputs!$B$189*(1+inf)^D$1,-E13)) -> 0 | F14: =MIN(0,MAX(-IF(F13=0,0,(Inputs!$B$19-INDEX(3:3,MATCH(0,5:5,0))))*Inputs!$B$189*(1+inf)^E$1,-F13)) -> 0 | G14: =MIN(0,MAX(-IF(G13=0,0,(Inputs!$B$19-INDEX(3:3,MATCH(0,5:5,0))))*Inputs!$B$189*(1+inf)^F$1,-G13)) -> 0 | H14: =MIN(0,MAX(-IF(H13=0,0,(Inputs!$B$19-INDEX(3:3,MATCH(0,5:5,0))))*Inputs!$B$189*(1+inf)^G$1,-H13)) -> 0 | I14: =MIN(0,MAX(-IF(I13=0,0,(Inputs!$B$19-INDEX(3:3,MATCH(0,5:5,0))))*Inputs!$B$189*(1+inf)^H$1,-I13)) -> 0 | J14: =MIN(0,MAX(-IF(J13=0,0,(Inputs!$B$19-INDEX(3:3,MATCH(0,5:5,0))))*Inputs!$B$189*(1+inf)^I$1,-J13)) -> 0 | K14: =MIN(0,MAX(-IF(K13=0,0,(Inputs!$B$19-INDEX(3:3,MATCH(0,5:5,0))))*Inputs!$B$189*(1+inf)^J$1,-K13)) -> 0 | ... AM14: =MIN(0,MAX(-IF(AM13=0,0,(Inputs!$B$19-INDEX(3:3,MATCH(0,5:5,0))))*Inputs!$B$189*(1+inf)^AL$1,-AM13)) -> 0
A15: Other post-retirement income | C15: =IF(AND(C$3>=Inputs!$B$174,C$3<=Inputs!$B$175),Inputs!$B$173*(1+inf)^B$1,0)*ProRate -> 0 | D15: =IF(AND(D$3>=Inputs!$B$174,D$3<=Inputs!$B$175),Inputs!$B$173*(1+inf)^C$1,0) -> 0 | E15: =IF(AND(E$3>=Inputs!$B$174,E$3<=Inputs!$B$175),Inputs!$B$173*(1+inf)^D$1,0) -> 0 | F15: =IF(AND(F$3>=Inputs!$B$174,F$3<=Inputs!$B$175),Inputs!$B$173*(1+inf)^E$1,0) -> 0 | G15: =IF(AND(G$3>=Inputs!$B$174,G$3<=Inputs!$B$175),Inputs!$B$173*(1+inf)^F$1,0) -> 0 | H15: =IF(AND(H$3>=Inputs!$B$174,H$3<=Inputs!$B$175),Inputs!$B$173*(1+inf)^G$1,0) -> 0 | I15: =IF(AND(I$3>=Inputs!$B$174,I$3<=Inputs!$B$175),Inputs!$B$173*(1+inf)^H$1,0) -> 0 | J15: =IF(AND(J$3>=Inputs!$B$174,J$3<=Inputs!$B$175),Inputs!$B$173*(1+inf)^I$1,0) -> 0 | K15: =IF(AND(K$3>=Inputs!$B$174,K$3<=Inputs!$B$175),Inputs!$B$173*(1+inf)^J$1,0) -> 0 | ... AM15: =IF(AND(AM$3>=Inputs!$B$174,AM$3<=Inputs!$B$175),Inputs!$B$173*(1+inf)^AL$1,0) -> 0
A16: Major one-off income events
A17: =TEXT(Inputs!B132,"") -> Inheritance | C17: =IF(C$2=Inputs!$B134,Inputs!$B133,0)*(1+inf)^B$1 -> 0 | D17: =IF(D$2=Inputs!$B134,Inputs!$B133,0)*(1+inf)^C$1 -> 0 | E17: =IF(E$2=Inputs!$B134,Inputs!$B133,0)*(1+inf)^D$1 -> 0 | F17: =IF(F$2=Inputs!$B134,Inputs!$B133,0)*(1+inf)^E$1 -> 0 | G17: =IF(G$2=Inputs!$B134,Inputs!$B133,0)*(1+inf)^F$1 -> 0 | H17: =IF(H$2=Inputs!$B134,Inputs!$B133,0)*(1+inf)^G$1 -> 0 | I17: =IF(I$2=Inputs!$B134,Inputs!$B133,0)*(1+inf)^H$1 -> 0 | J17: =IF(J$2=Inputs!$B134,Inputs!$B133,0)*(1+inf)^I$1 -> 0 | ... AM17: =IF(AM$2=Inputs!$B134,Inputs!$B133,0)*(1+inf)^AL$1 -> 0
A18: =TEXT(Inputs!B137,"") -> Sell Painting | C18: =IF(C$2=Inputs!$B139,Inputs!$B138,0)*(1+inf)^B$1 -> 0 | D18: =IF(D$2=Inputs!$B139,Inputs!$B138,0)*(1+inf)^C$1 -> 0 | E18: =IF(E$2=Inputs!$B139,Inputs!$B138,0)*(1+inf)^D$1 -> 0 | F18: =IF(F$2=Inputs!$B139,Inputs!$B138,0)*(1+inf)^E$1 -> 10768.906 | G18: =IF(G$2=Inputs!$B139,Inputs!$B138,0)*(1+inf)^F$1 -> 0 | H18: =IF(H$2=Inputs!$B139,Inputs!$B138,0)*(1+inf)^G$1 -> 0 | I18: =IF(I$2=Inputs!$B139,Inputs!$B138,0)*(1+inf)^H$1 -> 0 | J18: =IF(J$2=Inputs!$B139,Inputs!$B138,0)*(1+inf)^I$1 -> 0 | ... AM18: =IF(AM$2=Inputs!$B139,Inputs!$B138,0)*(1+inf)^AL$1 -> 0
A19: =TEXT(Inputs!B142,"") -> Sell Jewels | C19: =IF(C$2=Inputs!$B144,Inputs!$B143,0)*(1+inf)^B$1 -> 0 | D19: =IF(D$2=Inputs!$B144,Inputs!$B143,0)*(1+inf)^C$1 -> 0 | E19: =IF(E$2=Inputs!$B144,Inputs!$B143,0)*(1+inf)^D$1 -> 0 | F19: =IF(F$2=Inputs!$B144,Inputs!$B143,0)*(1+inf)^E$1 -> 0 | G19: =IF(G$2=Inputs!$B144,Inputs!$B143,0)*(1+inf)^F$1 -> 0 | H19: =IF(H$2=Inputs!$B144,Inputs!$B143,0)*(1+inf)^G$1 -> 0 | I19: =IF(I$2=Inputs!$B144,Inputs!$B143,0)*(1+inf)^H$1 -> 5798.4671 | J19: =IF(J$2=Inputs!$B144,Inputs!$B143,0)*(1+inf)^I$1 -> 0 | ... AM19: =IF(AM$2=Inputs!$B144,Inputs!$B143,0)*(1+inf)^AL$1 -> 0
A20: Interest on cash balances | C20: =MAX(AVERAGE(C57,C57+SUM(C5:C19)-C54)*Inputs!$B$181,0) -> 1520.2083 | D20: =MAX(AVERAGE(D57,D57+SUM(D5:D19)-D54)*Inputs!$B$181,0) -> 2102.1948 | E20: =MAX(AVERAGE(E57,E57+SUM(E5:E19)-E54)*Inputs!$B$181,0) -> 2776.5474 | F20: =MAX(AVERAGE(F57,F57+SUM(F5:F19)-F54)*Inputs!$B$181,0) -> 3294.5631 | G20: =MAX(AVERAGE(G57,G57+SUM(G5:G19)-G54)*Inputs!$B$181,0) -> 3966.038 | H20: =MAX(AVERAGE(H57,H57+SUM(H5:H19)-H54)*Inputs!$B$181,0) -> 5113.913 | I20: =MAX(AVERAGE(I57,I57+SUM(I5:I19)-I54)*Inputs!$B$181,0) -> 6643.3857 | J20: =MAX(AVERAGE(J57,J57+SUM(J5:J19)-J54)*Inputs!$B$181,0) -> 8458.2799 | ... AM20: =MAX(AVERAGE(AM57,AM57+SUM(AM5:AM19)-AM54)*Inputs!$B$181,0) -> 62953.987
C21: =SUM(C4:C20) -> 104436.88 | D21: =SUM(D4:D20) -> 122173.03 | E21: =SUM(E4:E20) -> 126439.26 | F21: =SUM(F4:F20) -> 141425.55 | G21: =SUM(G4:G20) -> 135138.21 | H21: =SUM(H4:H20) -> 140210.22 | I21: =SUM(I4:I20) -> 151579.73 | J21: =SUM(J4:J20) -> 151758.7 | ... AM21: =SUM(AM4:AM20) -> 202106.68
A22: Outflows
A23: Credit cards cleared | C23: =Inputs!B97 -> 1000 | D23: 0 | E23: 0 | F23: 0 | G23: 0 | H23: 0 | I23: 0 | J23: 0 | K23: 0 | L23: 0 | M23: 0 | N23: 0 | O23: 0 | P23: 0 | Q23: 0 | R23: 0 | S23: 0 | T23: 0 | U23: 0 | V23: 0 | W23: 0 | X23: 0 | Y23: 0 | Z23: 0 | AA23: 0 | AB23: 0 | AC23: 0 | AD23: 0 | AE23: 0 | AF23: 0 | AG23: 0 | AH23: 0 | AI23: 0 | AJ23: 0 | AK23: 0 | AL23: 0 | AM23: 0
A24: Home loan repayment | C24: =MIN(IF(B$1=0,MthRem,12), MAX(Inputs!$G$15-IF(B$1=0,0,B$1*12+MthOff), 0))*Inputs!$B$17 -> 8000 | D24: =MIN(IF(C$1=0,MthRem,12), MAX(Inputs!$G$15-IF(C$1=0,0,C$1*12+MthOff), 0))*Inputs!$B$17 -> 9600 | E24: =MIN(IF(D$1=0,MthRem,12), MAX(Inputs!$G$15-IF(D$1=0,0,D$1*12+MthOff), 0))*Inputs!$B$17 -> 9600 | F24: =MIN(IF(E$1=0,MthRem,12), MAX(Inputs!$G$15-IF(E$1=0,0,E$1*12+MthOff), 0))*Inputs!$B$17 -> 9600 | G24: =MIN(IF(F$1=0,MthRem,12), MAX(Inputs!$G$15-IF(F$1=0,0,F$1*12+MthOff), 0))*Inputs!$B$17 -> 9600 | H24: =MIN(IF(G$1=0,MthRem,12), MAX(Inputs!$G$15-IF(G$1=0,0,G$1*12+MthOff), 0))*Inputs!$B$17 -> 8035.6231 | I24: =MIN(IF(H$1=0,MthRem,12), MAX(Inputs!$G$15-IF(H$1=0,0,H$1*12+MthOff), 0))*Inputs!$B$17 -> 0 | J24: =MIN(IF(I$1=0,MthRem,12), MAX(Inputs!$G$15-IF(I$1=0,0,I$1*12+MthOff), 0))*Inputs!$B$17 -> 0 | ... AM24: =MIN(IF(AL$1=0,MthRem,12), MAX(Inputs!$G$15-IF(AL$1=0,0,AL$1*12+MthOff), 0))*Inputs!$B$17 -> 0
A25: Other property loans repayments
A26: =TEXT(Inputs!$B$60,"") -> Sliema | C26: =MIN(IF(B$1=0,MthRem,12), MAX(Inputs!$G$100-IF(B$1=0,0,B$1*12+MthOff), 0))*Inputs!$B$102 -> 5000 | D26: =MIN(IF(C$1=0,MthRem,12), MAX(Inputs!$G$100-IF(C$1=0,0,C$1*12+MthOff), 0))*Inputs!$B$102 -> 6000 | E26: =MIN(IF(D$1=0,MthRem,12), MAX(Inputs!$G$100-IF(D$1=0,0,D$1*12+MthOff), 0))*Inputs!$B$102 -> 6000 | F26: =MIN(IF(E$1=0,MthRem,12), MAX(Inputs!$G$100-IF(E$1=0,0,E$1*12+MthOff), 0))*Inputs!$B$102 -> 6000 | G26: =MIN(IF(F$1=0,MthRem,12), MAX(Inputs!$G$100-IF(F$1=0,0,F$1*12+MthOff), 0))*Inputs!$B$102 -> 6000 | H26: =MIN(IF(G$1=0,MthRem,12), MAX(Inputs!$G$100-IF(G$1=0,0,G$1*12+MthOff), 0))*Inputs!$B$102 -> 6000 | I26: =MIN(IF(H$1=0,MthRem,12), MAX(Inputs!$G$100-IF(H$1=0,0,H$1*12+MthOff), 0))*Inputs!$B$102 -> 6000 | J26: =MIN(IF(I$1=0,MthRem,12), MAX(Inputs!$G$100-IF(I$1=0,0,I$1*12+MthOff), 0))*Inputs!$B$102 -> 6000 | ... AM26: =MIN(IF(AL$1=0,MthRem,12), MAX(Inputs!$G$100-IF(AL$1=0,0,AL$1*12+MthOff), 0))*Inputs!$B$102 -> 0
A27: =TEXT(Inputs!$B$65,"") -> Gzira | C27: =MIN(IF(B$1=0,MthRem,12), MAX(Inputs!$G$105-IF(B$1=0,0,B$1*12+MthOff), 0))*Inputs!$B$107 -> 2000 | D27: =MIN(IF(C$1=0,MthRem,12), MAX(Inputs!$G$105-IF(C$1=0,0,C$1*12+MthOff), 0))*Inputs!$B$107 -> 2400 | E27: =MIN(IF(D$1=0,MthRem,12), MAX(Inputs!$G$105-IF(D$1=0,0,D$1*12+MthOff), 0))*Inputs!$B$107 -> 2400 | F27: =MIN(IF(E$1=0,MthRem,12), MAX(Inputs!$G$105-IF(E$1=0,0,E$1*12+MthOff), 0))*Inputs!$B$107 -> 2023.4029 | G27: =MIN(IF(F$1=0,MthRem,12), MAX(Inputs!$G$105-IF(F$1=0,0,F$1*12+MthOff), 0))*Inputs!$B$107 -> 0 | H27: =MIN(IF(G$1=0,MthRem,12), MAX(Inputs!$G$105-IF(G$1=0,0,G$1*12+MthOff), 0))*Inputs!$B$107 -> 0 | I27: =MIN(IF(H$1=0,MthRem,12), MAX(Inputs!$G$105-IF(H$1=0,0,H$1*12+MthOff), 0))*Inputs!$B$107 -> 0 | J27: =MIN(IF(I$1=0,MthRem,12), MAX(Inputs!$G$105-IF(I$1=0,0,I$1*12+MthOff), 0))*Inputs!$B$107 -> 0 | ... AM27: =MIN(IF(AL$1=0,MthRem,12), MAX(Inputs!$G$105-IF(AL$1=0,0,AL$1*12+MthOff), 0))*Inputs!$B$107 -> 0
A28: =TEXT(Inputs!$B$70,"") -> Qormi | C28: =MIN(IF(B$1=0,MthRem,12), MAX(Inputs!$G$110-IF(B$1=0,0,B$1*12+MthOff), 0))*Inputs!$B$112 -> 2500 | D28: =MIN(IF(C$1=0,MthRem,12), MAX(Inputs!$G$110-IF(C$1=0,0,C$1*12+MthOff), 0))*Inputs!$B$112 -> 3000 | E28: =MIN(IF(D$1=0,MthRem,12), MAX(Inputs!$G$110-IF(D$1=0,0,D$1*12+MthOff), 0))*Inputs!$B$112 -> 3000 | F28: =MIN(IF(E$1=0,MthRem,12), MAX(Inputs!$G$110-IF(E$1=0,0,E$1*12+MthOff), 0))*Inputs!$B$112 -> 3000 | G28: =MIN(IF(F$1=0,MthRem,12), MAX(Inputs!$G$110-IF(F$1=0,0,F$1*12+MthOff), 0))*Inputs!$B$112 -> 3000 | H28: =MIN(IF(G$1=0,MthRem,12), MAX(Inputs!$G$110-IF(G$1=0,0,G$1*12+MthOff), 0))*Inputs!$B$112 -> 2796.8597 | I28: =MIN(IF(H$1=0,MthRem,12), MAX(Inputs!$G$110-IF(H$1=0,0,H$1*12+MthOff), 0))*Inputs!$B$112 -> 0 | J28: =MIN(IF(I$1=0,MthRem,12), MAX(Inputs!$G$110-IF(I$1=0,0,I$1*12+MthOff), 0))*Inputs!$B$112 -> 0 | ... AM28: =MIN(IF(AL$1=0,MthRem,12), MAX(Inputs!$G$110-IF(AL$1=0,0,AL$1*12+MthOff), 0))*Inputs!$B$112 -> 0
A29: =TEXT(Inputs!$B$75,"") -> Gudja | C29: =MIN(IF(B$1=0,MthRem,12), MAX(Inputs!$G$115-IF(B$1=0,0,B$1*12+MthOff), 0))*Inputs!$B$117 -> 800 | D29: =MIN(IF(C$1=0,MthRem,12), MAX(Inputs!$G$115-IF(C$1=0,0,C$1*12+MthOff), 0))*Inputs!$B$117 -> 960 | E29: =MIN(IF(D$1=0,MthRem,12), MAX(Inputs!$G$115-IF(D$1=0,0,D$1*12+MthOff), 0))*Inputs!$B$117 -> 960 | F29: =MIN(IF(E$1=0,MthRem,12), MAX(Inputs!$G$115-IF(E$1=0,0,E$1*12+MthOff), 0))*Inputs!$B$117 -> 960 | G29: =MIN(IF(F$1=0,MthRem,12), MAX(Inputs!$G$115-IF(F$1=0,0,F$1*12+MthOff), 0))*Inputs!$B$117 -> 960 | H29: =MIN(IF(G$1=0,MthRem,12), MAX(Inputs!$G$115-IF(G$1=0,0,G$1*12+MthOff), 0))*Inputs!$B$117 -> 288.25859 | I29: =MIN(IF(H$1=0,MthRem,12), MAX(Inputs!$G$115-IF(H$1=0,0,H$1*12+MthOff), 0))*Inputs!$B$117 -> 0 | J29: =MIN(IF(I$1=0,MthRem,12), MAX(Inputs!$G$115-IF(I$1=0,0,I$1*12+MthOff), 0))*Inputs!$B$117 -> 0 | ... AM29: =MIN(IF(AL$1=0,MthRem,12), MAX(Inputs!$G$115-IF(AL$1=0,0,AL$1*12+MthOff), 0))*Inputs!$B$117 -> 0
A30: =TEXT(Inputs!$B$80,"") -> Marsa | C30: =MIN(IF(B$1=0,MthRem,12), MAX(Inputs!$G$120-IF(B$1=0,0,B$1*12+MthOff), 0))*Inputs!$B$122 -> 1200 | D30: =MIN(IF(C$1=0,MthRem,12), MAX(Inputs!$G$120-IF(C$1=0,0,C$1*12+MthOff), 0))*Inputs!$B$122 -> 1440 | E30: =MIN(IF(D$1=0,MthRem,12), MAX(Inputs!$G$120-IF(D$1=0,0,D$1*12+MthOff), 0))*Inputs!$B$122 -> 1440 | F30: =MIN(IF(E$1=0,MthRem,12), MAX(Inputs!$G$120-IF(E$1=0,0,E$1*12+MthOff), 0))*Inputs!$B$122 -> 1440 | G30: =MIN(IF(F$1=0,MthRem,12), MAX(Inputs!$G$120-IF(F$1=0,0,F$1*12+MthOff), 0))*Inputs!$B$122 -> 1440 | H30: =MIN(IF(G$1=0,MthRem,12), MAX(Inputs!$G$120-IF(G$1=0,0,G$1*12+MthOff), 0))*Inputs!$B$122 -> 1440 | I30: =MIN(IF(H$1=0,MthRem,12), MAX(Inputs!$G$120-IF(H$1=0,0,H$1*12+MthOff), 0))*Inputs!$B$122 -> 1440 | J30: =MIN(IF(I$1=0,MthRem,12), MAX(Inputs!$G$120-IF(I$1=0,0,I$1*12+MthOff), 0))*Inputs!$B$122 -> 789.24881 | ... AM30: =MIN(IF(AL$1=0,MthRem,12), MAX(Inputs!$G$120-IF(AL$1=0,0,AL$1*12+MthOff), 0))*Inputs!$B$122 -> 0
A31: Other loan repayment | C31: =MIN(IF(B$1=0,MthRem,12), MAX(Inputs!$G$125-IF(B$1=0,0,B$1*12+MthOff), 0))*Inputs!$B$127 -> 500 | D31: =MIN(IF(C$1=0,MthRem,12), MAX(Inputs!$G$125-IF(C$1=0,0,C$1*12+MthOff), 0))*Inputs!$B$127 -> 600 | E31: =MIN(IF(D$1=0,MthRem,12), MAX(Inputs!$G$125-IF(D$1=0,0,D$1*12+MthOff), 0))*Inputs!$B$127 -> 600 | F31: =MIN(IF(E$1=0,MthRem,12), MAX(Inputs!$G$125-IF(E$1=0,0,E$1*12+MthOff), 0))*Inputs!$B$127 -> 600 | G31: =MIN(IF(F$1=0,MthRem,12), MAX(Inputs!$G$125-IF(F$1=0,0,F$1*12+MthOff), 0))*Inputs!$B$127 -> 600 | H31: =MIN(IF(G$1=0,MthRem,12), MAX(Inputs!$G$125-IF(G$1=0,0,G$1*12+MthOff), 0))*Inputs!$B$127 -> 600 | I31: =MIN(IF(H$1=0,MthRem,12), MAX(Inputs!$G$125-IF(H$1=0,0,H$1*12+MthOff), 0))*Inputs!$B$127 -> 600 | J31: =MIN(IF(I$1=0,MthRem,12), MAX(Inputs!$G$125-IF(I$1=0,0,I$1*12+MthOff), 0))*Inputs!$B$127 -> 600 | ... AM31: =MIN(IF(AL$1=0,MthRem,12), MAX(Inputs!$G$125-IF(AL$1=0,0,AL$1*12+MthOff), 0))*Inputs!$B$127 -> 0
A32: Dependents cost
A33: =TEXT(Inputs!B33,"") -> John | C33: =IF(Inputs!$B$35>=C$1,Inputs!$B$34,0)*(1+inf)^B$1*ProRate -> 1666.6667 | D33: =IF(Inputs!$B$35>=D$1,Inputs!$B$34,0)*(1+inf)^C$1 -> 2050 | E33: =IF(Inputs!$B$35>=E$1,Inputs!$B$34,0)*(1+inf)^D$1 -> 2101.25 | F33: =IF(Inputs!$B$35>=F$1,Inputs!$B$34,0)*(1+inf)^E$1 -> 0 | G33: =IF(Inputs!$B$35>=G$1,Inputs!$B$34,0)*(1+inf)^F$1 -> 0 | H33: =IF(Inputs!$B$35>=H$1,Inputs!$B$34,0)*(1+inf)^G$1 -> 0 | I33: =IF(Inputs!$B$35>=I$1,Inputs!$B$34,0)*(1+inf)^H$1 -> 0 | J33: =IF(Inputs!$B$35>=J$1,Inputs!$B$34,0)*(1+inf)^I$1 -> 0 | K33: =IF(Inputs!$B$35>=K$1,Inputs!$B$34,0)*(1+inf)^J$1 -> 0 | ... AM33: =IF(Inputs!$B$35>=AM$1,Inputs!$B$34,0)*(1+inf)^AL$1 -> 0
A34: =TEXT(Inputs!B38,"") -> Jack | C34: =IF(Inputs!$B$40>=C$1,Inputs!$B$39,0)*(1+inf)^B$1*ProRate -> 833.33333 | D34: =IF(Inputs!$B$40>=D$1,Inputs!$B$39,0)*(1+inf)^C$1 -> 1025 | E34: =IF(Inputs!$B$40>=E$1,Inputs!$B$39,0)*(1+inf)^D$1 -> 1050.625 | F34: =IF(Inputs!$B$40>=F$1,Inputs!$B$39,0)*(1+inf)^E$1 -> 1076.8906 | G34: =IF(Inputs!$B$40>=G$1,Inputs!$B$39,0)*(1+inf)^F$1 -> 1103.8129 | H34: =IF(Inputs!$B$40>=H$1,Inputs!$B$39,0)*(1+inf)^G$1 -> 0 | I34: =IF(Inputs!$B$40>=I$1,Inputs!$B$39,0)*(1+inf)^H$1 -> 0 | J34: =IF(Inputs!$B$40>=J$1,Inputs!$B$39,0)*(1+inf)^I$1 -> 0 | K34: =IF(Inputs!$B$40>=K$1,Inputs!$B$39,0)*(1+inf)^J$1 -> 0 | ... AM34: =IF(Inputs!$B$40>=AM$1,Inputs!$B$39,0)*(1+inf)^AL$1 -> 0
A35: =TEXT(Inputs!B43,"") -> Bill | C35: =IF(Inputs!$B$45>=C$1,Inputs!$B$44,0)*(1+inf)^B$1*ProRate -> 3333.3333 | D35: =IF(Inputs!$B$45>=D$1,Inputs!$B$44,0)*(1+inf)^C$1 -> 4100 | E35: =IF(Inputs!$B$45>=E$1,Inputs!$B$44,0)*(1+inf)^D$1 -> 0 | F35: =IF(Inputs!$B$45>=F$1,Inputs!$B$44,0)*(1+inf)^E$1 -> 0 | G35: =IF(Inputs!$B$45>=G$1,Inputs!$B$44,0)*(1+inf)^F$1 -> 0 | H35: =IF(Inputs!$B$45>=H$1,Inputs!$B$44,0)*(1+inf)^G$1 -> 0 | I35: =IF(Inputs!$B$45>=I$1,Inputs!$B$44,0)*(1+inf)^H$1 -> 0 | J35: =IF(Inputs!$B$45>=J$1,Inputs!$B$44,0)*(1+inf)^I$1 -> 0 | K35: =IF(Inputs!$B$45>=K$1,Inputs!$B$44,0)*(1+inf)^J$1 -> 0 | ... AM35: =IF(Inputs!$B$45>=AM$1,Inputs!$B$44,0)*(1+inf)^AL$1 -> 0
A36: =TEXT(Inputs!B48,"") -> Stephen | C36: =IF(Inputs!$B$50>=C$1,Inputs!$B$49,0)*(1+inf)^B$1*ProRate -> 2083.3333 | D36: =IF(Inputs!$B$50>=D$1,Inputs!$B$49,0)*(1+inf)^C$1 -> 2562.5 | E36: =IF(Inputs!$B$50>=E$1,Inputs!$B$49,0)*(1+inf)^D$1 -> 2626.5625 | F36: =IF(Inputs!$B$50>=F$1,Inputs!$B$49,0)*(1+inf)^E$1 -> 0 | G36: =IF(Inputs!$B$50>=G$1,Inputs!$B$49,0)*(1+inf)^F$1 -> 0 | H36: =IF(Inputs!$B$50>=H$1,Inputs!$B$49,0)*(1+inf)^G$1 -> 0 | I36: =IF(Inputs!$B$50>=I$1,Inputs!$B$49,0)*(1+inf)^H$1 -> 0 | J36: =IF(Inputs!$B$50>=J$1,Inputs!$B$49,0)*(1+inf)^I$1 -> 0 | K36: =IF(Inputs!$B$50>=K$1,Inputs!$B$49,0)*(1+inf)^J$1 -> 0 | ... AM36: =IF(Inputs!$B$50>=AM$1,Inputs!$B$49,0)*(1+inf)^AL$1 -> 0
A37: =TEXT(Inputs!B53,"") -> Jane | C37: =IF(Inputs!$B$55>=C$1,Inputs!$B$54,0)*(1+inf)^B$1*ProRate -> 2383.3333 | D37: =IF(Inputs!$B$55>=D$1,Inputs!$B$54,0)*(1+inf)^C$1 -> 2931.5 | E37: =IF(Inputs!$B$55>=E$1,Inputs!$B$54,0)*(1+inf)^D$1 -> 3004.7875 | F37: =IF(Inputs!$B$55>=F$1,Inputs!$B$54,0)*(1+inf)^E$1 -> 3079.9072 | G37: =IF(Inputs!$B$55>=G$1,Inputs!$B$54,0)*(1+inf)^F$1 -> 3156.9049 | H37: =IF(Inputs!$B$55>=H$1,Inputs!$B$54,0)*(1+inf)^G$1 -> 3235.8275 | I37: =IF(Inputs!$B$55>=I$1,Inputs!$B$54,0)*(1+inf)^H$1 -> 0 | J37: =IF(Inputs!$B$55>=J$1,Inputs!$B$54,0)*(1+inf)^I$1 -> 0 | K37: =IF(Inputs!$B$55>=K$1,Inputs!$B$54,0)*(1+inf)^J$1 -> 0 | ... AM37: =IF(Inputs!$B$55>=AM$1,Inputs!$B$54,0)*(1+inf)^AL$1 -> 0
A38: Housing rent | C38: =Inputs!$B$23*(1+inf)^B$1*ProRate -> 0 | D38: =Inputs!$B$23*(1+inf)^C$1 -> 0 | E38: =Inputs!$B$23*(1+inf)^D$1 -> 0 | F38: =Inputs!$B$23*(1+inf)^E$1 -> 0 | G38: =Inputs!$B$23*(1+inf)^F$1 -> 0 | H38: =Inputs!$B$23*(1+inf)^G$1 -> 0 | I38: =Inputs!$B$23*(1+inf)^H$1 -> 0 | J38: =Inputs!$B$23*(1+inf)^I$1 -> 0 | K38: =Inputs!$B$23*(1+inf)^J$1 -> 0 | ... AM38: =Inputs!$B$23*(1+inf)^AL$1 -> 0
A39: Other property costs
A40: =TEXT(Inputs!$B$60,"") -> Sliema | C40: =Inputs!$B62*(1+inf)^B$1*ProRate -> 4166.6667 | D40: =Inputs!$B62*(1+inf)^C$1 -> 5125 | E40: =Inputs!$B62*(1+inf)^D$1 -> 5253.125 | F40: =Inputs!$B62*(1+inf)^E$1 -> 5384.4531 | G40: =Inputs!$B62*(1+inf)^F$1 -> 5519.0645 | H40: =Inputs!$B62*(1+inf)^G$1 -> 5657.0411 | I40: =Inputs!$B62*(1+inf)^H$1 -> 5798.4671 | J40: =Inputs!$B62*(1+inf)^I$1 -> 5943.4288 | K40: =Inputs!$B62*(1+inf)^J$1 -> 6092.0145 | ... AM40: =Inputs!$B62*(1+inf)^AL$1 -> 12162.677
A41: =TEXT(Inputs!$B$65,"") -> Gzira | C41: =Inputs!$B67*(1+inf)^B$1*ProRate -> 1666.6667 | D41: =Inputs!$B67*(1+inf)^C$1 -> 2050 | E41: =Inputs!$B67*(1+inf)^D$1 -> 2101.25 | F41: =Inputs!$B67*(1+inf)^E$1 -> 2153.7812 | G41: =Inputs!$B67*(1+inf)^F$1 -> 2207.6258 | H41: =Inputs!$B67*(1+inf)^G$1 -> 2262.8164 | I41: =Inputs!$B67*(1+inf)^H$1 -> 2319.3868 | J41: =Inputs!$B67*(1+inf)^I$1 -> 2377.3715 | K41: =Inputs!$B67*(1+inf)^J$1 -> 2436.8058 | ... AM41: =Inputs!$B67*(1+inf)^AL$1 -> 4865.0706
A42: =TEXT(Inputs!$B$70,"") -> Qormi | C42: =Inputs!$B72*(1+inf)^B$1*ProRate -> 1000 | D42: =Inputs!$B72*(1+inf)^C$1 -> 1230 | E42: =Inputs!$B72*(1+inf)^D$1 -> 1260.75 | F42: =Inputs!$B72*(1+inf)^E$1 -> 1292.2687 | G42: =Inputs!$B72*(1+inf)^F$1 -> 1324.5755 | H42: =Inputs!$B72*(1+inf)^G$1 -> 1357.6899 | I42: =Inputs!$B72*(1+inf)^H$1 -> 1391.6321 | J42: =Inputs!$B72*(1+inf)^I$1 -> 1426.4229 | K42: =Inputs!$B72*(1+inf)^J$1 -> 1462.0835 | ... AM42: =Inputs!$B72*(1+inf)^AL$1 -> 2919.0424
A43: =TEXT(Inputs!$B$75,"") -> Gudja | C43: =Inputs!$B77*(1+inf)^B$1*ProRate -> 833.33333 | D43: =Inputs!$B77*(1+inf)^C$1 -> 1025 | E43: =Inputs!$B77*(1+inf)^D$1 -> 1050.625 | F43: =Inputs!$B77*(1+inf)^E$1 -> 1076.8906 | G43: =Inputs!$B77*(1+inf)^F$1 -> 1103.8129 | H43: =Inputs!$B77*(1+inf)^G$1 -> 1131.4082 | I43: =Inputs!$B77*(1+inf)^H$1 -> 1159.6934 | J43: =Inputs!$B77*(1+inf)^I$1 -> 1188.6858 | K43: =Inputs!$B77*(1+inf)^J$1 -> 1218.4029 | ... AM43: =Inputs!$B77*(1+inf)^AL$1 -> 2432.5353
A44: =TEXT(Inputs!$B$80,"") -> Marsa | C44: =Inputs!$B82*(1+inf)^B$1*ProRate -> 666.66667 | D44: =Inputs!$B82*(1+inf)^C$1 -> 820 | E44: =Inputs!$B82*(1+inf)^D$1 -> 840.5 | F44: =Inputs!$B82*(1+inf)^E$1 -> 861.5125 | G44: =Inputs!$B82*(1+inf)^F$1 -> 883.05031 | H44: =Inputs!$B82*(1+inf)^G$1 -> 905.12657 | I44: =Inputs!$B82*(1+inf)^H$1 -> 927.75473 | J44: =Inputs!$B82*(1+inf)^I$1 -> 950.9486 | K44: =Inputs!$B82*(1+inf)^J$1 -> 974.72232 | ... AM44: =Inputs!$B82*(1+inf)^AL$1 -> 1946.0283
A45: Living expenses
A46: Current baseline | C46: =Inputs!$B$25*(1+inf)^B$1*ProRate -> 41666.667 | D46: =Inputs!$B$25*(1+inf)^C$1 -> 51250 | E46: =Inputs!$B$25*(1+inf)^D$1 -> 52531.25 | F46: =Inputs!$B$25*(1+inf)^E$1 -> 53844.531 | G46: =Inputs!$B$25*(1+inf)^F$1 -> 55190.645 | H46: =Inputs!$B$25*(1+inf)^G$1 -> 56570.411 | I46: =Inputs!$B$25*(1+inf)^H$1 -> 57984.671 | J46: =Inputs!$B$25*(1+inf)^I$1 -> 59434.288 | K46: =Inputs!$B$25*(1+inf)^J$1 -> 60920.145 | ... AM46: =Inputs!$B$25*(1+inf)^AL$1 -> 121626.77
A47: ="Adjustment "&Inputs!A169 -> Adjustment from now to 65 | C47: =IF(C$3<=65,Inputs!$B$169*C$46,0) -> 0 | D47: =IF(D$3<=65,Inputs!$B$169*D$46,0) -> 0 | E47: =IF(E$3<=65,Inputs!$B$169*E$46,0) -> 0 | F47: =IF(F$3<=65,Inputs!$B$169*F$46,0) -> 0 | G47: =IF(G$3<=65,Inputs!$B$169*G$46,0) -> 0 | H47: =IF(H$3<=65,Inputs!$B$169*H$46,0) -> 0 | I47: =IF(I$3<=65,Inputs!$B$169*I$46,0) -> 0 | J47: =IF(J$3<=65,Inputs!$B$169*J$46,0) -> 0 | ... AM47: =IF(AM$3<=65,Inputs!$B$169*AM$46,0) -> 0
A48: ="Adjustment "&Inputs!A170 -> Adjustment from 66-75 | C48: =IF(AND(C$3>65,C$3<=75),Inputs!$B$170*C46,0) -> 0 | D48: =IF(AND(D$3>65,D$3<=75),Inputs!$B$170*D46,0) -> 0 | E48: =IF(AND(E$3>65,E$3<=75),Inputs!$B$170*E46,0) -> 0 | F48: =IF(AND(F$3>65,F$3<=75),Inputs!$B$170*F46,0) -> 0 | G48: =IF(AND(G$3>65,G$3<=75),Inputs!$B$170*G46,0) -> 0 | H48: =IF(AND(H$3>65,H$3<=75),Inputs!$B$170*H46,0) -> 0 | I48: =IF(AND(I$3>65,I$3<=75),Inputs!$B$170*I46,0) -> 0 | J48: =IF(AND(J$3>65,J$3<=75),Inputs!$B$170*J46,0) -> 0 | ... AM48: =IF(AND(AM$3>65,AM$3<=75),Inputs!$B$170*AM46,0) -> 0
A49: ="Adjustment "&Inputs!A171 -> Adjustment from age 76 | C49: =IF(C$3>75,Inputs!$B$171*C$46,0) -> 0 | D49: =IF(D$3>75,Inputs!$B$171*D$46,0) -> 0 | E49: =IF(E$3>75,Inputs!$B$171*E$46,0) -> 0 | F49: =IF(F$3>75,Inputs!$B$171*F$46,0) -> 0 | G49: =IF(G$3>75,Inputs!$B$171*G$46,0) -> 0 | H49: =IF(H$3>75,Inputs!$B$171*H$46,0) -> 0 | I49: =IF(I$3>75,Inputs!$B$171*I$46,0) -> 0 | J49: =IF(J$3>75,Inputs!$B$171*J$46,0) -> 0 | ... AM49: =IF(AM$3>75,Inputs!$B$171*AM$46,0) -> -24325.353
A50: Major one-off expense events
A51: =TEXT(Inputs!$B$149,"") -> Wedding | C51: =IF(C$2=Inputs!$B151,Inputs!$B150,0)*(1+inf)^B$1 -> 0 | D51: =IF(D$2=Inputs!$B151,Inputs!$B150,0)*(1+inf)^C$1 -> 0 | E51: =IF(E$2=Inputs!$B151,Inputs!$B150,0)*(1+inf)^D$1 -> 0 | F51: =IF(F$2=Inputs!$B151,Inputs!$B150,0)*(1+inf)^E$1 -> 0 | G51: =IF(G$2=Inputs!$B151,Inputs!$B150,0)*(1+inf)^F$1 -> 0 | H51: =IF(H$2=Inputs!$B151,Inputs!$B150,0)*(1+inf)^G$1 -> 0 | I51: =IF(I$2=Inputs!$B151,Inputs!$B150,0)*(1+inf)^H$1 -> 0 | J51: =IF(J$2=Inputs!$B151,Inputs!$B150,0)*(1+inf)^I$1 -> 0 | ... AM51: =IF(AM$2=Inputs!$B151,Inputs!$B150,0)*(1+inf)^AL$1 -> 0
A52: =TEXT(Inputs!$B$154,"") -> New Car | C52: =IF(C$2=Inputs!$B156,Inputs!$B155,0)*(1+inf)^B$1 -> 0 | D52: =IF(D$2=Inputs!$B156,Inputs!$B155,0)*(1+inf)^C$1 -> 0 | E52: =IF(E$2=Inputs!$B156,Inputs!$B155,0)*(1+inf)^D$1 -> 0 | F52: =IF(F$2=Inputs!$B156,Inputs!$B155,0)*(1+inf)^E$1 -> 37691.172 | G52: =IF(G$2=Inputs!$B156,Inputs!$B155,0)*(1+inf)^F$1 -> 0 | H52: =IF(H$2=Inputs!$B156,Inputs!$B155,0)*(1+inf)^G$1 -> 0 | I52: =IF(I$2=Inputs!$B156,Inputs!$B155,0)*(1+inf)^H$1 -> 0 | J52: =IF(J$2=Inputs!$B156,Inputs!$B155,0)*(1+inf)^I$1 -> 0 | ... AM52: =IF(AM$2=Inputs!$B156,Inputs!$B155,0)*(1+inf)^AL$1 -> 0
A53: =TEXT(Inputs!$B$159,"") -> New AC | C53: =IF(C$2=Inputs!$B161,Inputs!$B160,0)*(1+inf)^B$1 -> 0 | D53: =IF(D$2=Inputs!$B161,Inputs!$B160,0)*(1+inf)^C$1 -> 0 | E53: =IF(E$2=Inputs!$B161,Inputs!$B160,0)*(1+inf)^D$1 -> 0 | F53: =IF(F$2=Inputs!$B161,Inputs!$B160,0)*(1+inf)^E$1 -> 0 | G53: =IF(G$2=Inputs!$B161,Inputs!$B160,0)*(1+inf)^F$1 -> 0 | H53: =IF(H$2=Inputs!$B161,Inputs!$B160,0)*(1+inf)^G$1 -> 0 | I53: =IF(I$2=Inputs!$B161,Inputs!$B160,0)*(1+inf)^H$1 -> 0 | J53: =IF(J$2=Inputs!$B161,Inputs!$B160,0)*(1+inf)^I$1 -> 0 | ... AM53: =IF(AM$2=Inputs!$B161,Inputs!$B160,0)*(1+inf)^AL$1 -> 0
C54: =SUM(C22:C53) -> 81300 | D54: =SUM(D22:D53) -> 98169 | E54: =SUM(E22:E53) -> 95820.725 | F54: =SUM(F22:F53) -> 130084.81 | G54: =SUM(G22:G53) -> 92089.491 | H54: =SUM(H22:H53) -> 90281.062 | I54: =SUM(I22:I53) -> 77621.605 | J54: =SUM(J22:J53) -> 78710.394 | ... AM54: =SUM(AM22:AM53) -> 121626.77
A56: Net Cash Flow | C56: =C21-C54 -> 23136.875 | D56: =D21-D54 -> 24004.028 | E56: =E21-E54 -> 30618.531 | F56: =F21-F54 -> 11340.743 | G56: =G21-G54 -> 43048.724 | H56: =H21-H54 -> 49929.155 | I56: =I21-I54 -> 73958.127 | J56: =J21-J54 -> 73048.304 | ... AM56: =AM21-AM54 -> 80479.912
A57: Cash b/fwd | C57: =Inputs!B8 -> 50000 | D57: =C58 -> 73136.875 | E57: =D58 -> 97140.903 | F57: =E58 -> 127759.43 | G57: =F58 -> 139100.18 | H57: =G58 -> 182148.9 | I57: =H58 -> 232078.06 | J57: =I58 -> 306036.18 | K57: =J58 -> 379084.49 | ... AM57: =AL58 -> 2509396.5
A58: Cash c/fwd | C58: =SUM(C56:C57) -> 73136.875 | D58: =SUM(D56:D57) -> 97140.903 | E58: =SUM(E56:E57) -> 127759.43 | F58: =SUM(F56:F57) -> 139100.18 | G58: =SUM(G56:G57) -> 182148.9 | H58: =SUM(H56:H57) -> 232078.06 | I58: =SUM(I56:I57) -> 306036.18 | J58: =SUM(J56:J57) -> 379084.49 | ... AM58: =SUM(AM56:AM57) -> 2589876.4
A60: Net Worth before liquidations
A61: Cash | C61: =C58 -> 73136.875 | D61: =D58 -> 97140.903 | E61: =E58 -> 127759.43 | F61: =F58 -> 139100.18 | G61: =G58 -> 182148.9 | H61: =H58 -> 232078.06 | I61: =I58 -> 306036.18 | J61: =J58 -> 379084.49 | ... AM61: =AM58 -> 2589876.4
A62: Home | C62: =Inputs!B12*(1+princ)^ProRate -> 614962.93 | D62: =C62*(1+princ) -> 633411.82 | E62: =D62*(1+princ) -> 652414.17 | F62: =E62*(1+princ) -> 671986.6 | G62: =F62*(1+princ) -> 692146.2 | H62: =G62*(1+princ) -> 712910.58 | I62: =H62*(1+princ) -> 734297.9 | J62: =I62*(1+princ) -> 756326.84 | K62: =J62*(1+princ) -> 779016.64 | ... AM62: =AL62*(1+princ) -> 1782333.7
A63: Other property
A64: =TEXT(Inputs!$B$60,"") -> Sliema | C64: =Inputs!B61*(1+princ)^ProRate -> 307481.47 | D64: =C64*(1+princ) -> 316705.91 | E64: =D64*(1+princ) -> 326207.09 | F64: =E64*(1+princ) -> 335993.3 | G64: =F64*(1+princ) -> 346073.1 | H64: =G64*(1+princ) -> 356455.29 | I64: =H64*(1+princ) -> 367148.95 | J64: =I64*(1+princ) -> 378163.42 | K64: =J64*(1+princ) -> 389508.32 | ... AM64: =AL64*(1+princ) -> 891166.87
A65: =TEXT(Inputs!$B$65,"") -> Gzira | C65: =Inputs!B66*(1+princ)^ProRate -> 153740.73 | D65: =C65*(1+princ) -> 158352.95 | E65: =D65*(1+princ) -> 163103.54 | F65: =E65*(1+princ) -> 167996.65 | G65: =F65*(1+princ) -> 173036.55 | H65: =G65*(1+princ) -> 178227.65 | I65: =H65*(1+princ) -> 183574.47 | J65: =I65*(1+princ) -> 189081.71 | K65: =J65*(1+princ) -> 194754.16 | ... AM65: =AL65*(1+princ) -> 445583.43
A66: =TEXT(Inputs!$B$70,"") -> Qormi | C66: =Inputs!B71*(1+princ)^ProRate -> 225486.41 | D66: =C66*(1+princ) -> 232251 | E66: =D66*(1+princ) -> 239218.53 | F66: =E66*(1+princ) -> 246395.09 | G66: =F66*(1+princ) -> 253786.94 | H66: =G66*(1+princ) -> 261400.55 | I66: =H66*(1+princ) -> 269242.56 | J66: =I66*(1+princ) -> 277319.84 | K66: =J66*(1+princ) -> 285639.44 | ... AM66: =AL66*(1+princ) -> 653522.37
A67: =TEXT(Inputs!$B$75,"") -> Gudja | C67: =Inputs!B76*(1+princ)^ProRate -> 81995.057 | D67: =C67*(1+princ) -> 84454.909 | E67: =D67*(1+princ) -> 86988.556 | F67: =E67*(1+princ) -> 89598.213 | G67: =F67*(1+princ) -> 92286.159 | H67: =G67*(1+princ) -> 95054.744 | I67: =H67*(1+princ) -> 97906.387 | J67: =I67*(1+princ) -> 100843.58 | K67: =J67*(1+princ) -> 103868.89 | ... AM67: =AL67*(1+princ) -> 237644.5
A68: =TEXT(Inputs!$B$80,"") -> Marsa | C68: =Inputs!B81*(1+princ)^ProRate -> 122992.59 | D68: =C68*(1+princ) -> 126682.36 | E68: =D68*(1+princ) -> 130482.83 | F68: =E68*(1+princ) -> 134397.32 | G68: =F68*(1+princ) -> 138429.24 | H68: =G68*(1+princ) -> 142582.12 | I68: =H68*(1+princ) -> 146859.58 | J68: =I68*(1+princ) -> 151265.37 | K68: =J68*(1+princ) -> 155803.33 | ... AM68: =AL68*(1+princ) -> 356466.75
A69: Stock market equity investments | C69: =Inputs!B10*(1+stinc)^ProRate -> 31987.064 | D69: =C69*(1+stinc) -> 34546.03 | E69: =D69*(1+stinc) -> 37309.712 | F69: =E69*(1+stinc) -> 40294.489 | G69: =F69*(1+stinc) -> 43518.048 | H69: =G69*(1+stinc) -> 46999.492 | I69: =H69*(1+stinc) -> 50759.451 | J69: =I69*(1+stinc) -> 54820.207 | K69: =J69*(1+stinc) -> 59205.824 | ... AM69: =AL69*(1+stinc) -> 510774.94
A70: Home loan | C70: =-MAX(FV(Inputs!$B16/12,C$1*12+MthOff,Inputs!$B17,-Inputs!$B15),0) -> -43173.554 | D70: =-MAX(FV(Inputs!$B16/12,D$1*12+MthOff,Inputs!$B17,-Inputs!$B15),0) -> -34753.613 | E70: =-MAX(FV(Inputs!$B16/12,E$1*12+MthOff,Inputs!$B17,-Inputs!$B15),0) -> -26077.571 | F70: =-MAX(FV(Inputs!$B16/12,F$1*12+MthOff,Inputs!$B17,-Inputs!$B15),0) -> -17137.639 | G70: =-MAX(FV(Inputs!$B16/12,G$1*12+MthOff,Inputs!$B17,-Inputs!$B15),0) -> -7925.7905 | H70: =-MAX(FV(Inputs!$B16/12,H$1*12+MthOff,Inputs!$B17,-Inputs!$B15),0) -> 0 | I70: =-MAX(FV(Inputs!$B16/12,I$1*12+MthOff,Inputs!$B17,-Inputs!$B15),0) -> 0 | J70: =-MAX(FV(Inputs!$B16/12,J$1*12+MthOff,Inputs!$B17,-Inputs!$B15),0) -> 0 | ... AM70: =-MAX(FV(Inputs!$B16/12,AM$1*12+MthOff,Inputs!$B17,-Inputs!$B15),0) -> 0
A71: Other property loans
A72: =TEXT(Inputs!$B$60,"") -> Sliema | C72: =-MAX(FV(Inputs!$B101/12,C$1*12+MthOff,Inputs!$B102,-Inputs!$B100),0) -> -46207.53 | D72: =-MAX(FV(Inputs!$B101/12,D$1*12+MthOff,Inputs!$B102,-Inputs!$B100),0) -> -41529.785 | E72: =-MAX(FV(Inputs!$B101/12,E$1*12+MthOff,Inputs!$B102,-Inputs!$B100),0) -> -36709.762 | F72: =-MAX(FV(Inputs!$B101/12,F$1*12+MthOff,Inputs!$B102,-Inputs!$B100),0) -> -31743.133 | G72: =-MAX(FV(Inputs!$B101/12,G$1*12+MthOff,Inputs!$B102,-Inputs!$B100),0) -> -26625.439 | H72: =-MAX(FV(Inputs!$B101/12,H$1*12+MthOff,Inputs!$B102,-Inputs!$B100),0) -> -21352.086 | I72: =-MAX(FV(Inputs!$B101/12,I$1*12+MthOff,Inputs!$B102,-Inputs!$B100),0) -> -15918.339 | J72: =-MAX(FV(Inputs!$B101/12,J$1*12+MthOff,Inputs!$B102,-Inputs!$B100),0) -> -10319.319 | ... AM72: =-MAX(FV(Inputs!$B101/12,AM$1*12+MthOff,Inputs!$B102,-Inputs!$B100),0) -> 0
A73: =TEXT(Inputs!$B$65,"") -> Gzira | C73: =-MAX(FV(Inputs!$B106/12,C$1*12+MthOff,Inputs!$B107,-Inputs!$B105),0) -> -6627.667 | D73: =-MAX(FV(Inputs!$B106/12,D$1*12+MthOff,Inputs!$B107,-Inputs!$B105),0) -> -4339.3195 | E73: =-MAX(FV(Inputs!$B106/12,E$1*12+MthOff,Inputs!$B107,-Inputs!$B105),0) -> -2004.7832 | F73: =-MAX(FV(Inputs!$B106/12,F$1*12+MthOff,Inputs!$B107,-Inputs!$B105),0) -> 0 | G73: =-MAX(FV(Inputs!$B106/12,G$1*12+MthOff,Inputs!$B107,-Inputs!$B105),0) -> 0 | H73: =-MAX(FV(Inputs!$B106/12,H$1*12+MthOff,Inputs!$B107,-Inputs!$B105),0) -> 0 | I73: =-MAX(FV(Inputs!$B106/12,I$1*12+MthOff,Inputs!$B107,-Inputs!$B105),0) -> 0 | J73: =-MAX(FV(Inputs!$B106/12,J$1*12+MthOff,Inputs!$B107,-Inputs!$B105),0) -> 0 | ... AM73: =-MAX(FV(Inputs!$B106/12,AM$1*12+MthOff,Inputs!$B107,-Inputs!$B105),0) -> 0
A74: =TEXT(Inputs!$B$70,"") -> Qormi | C74: =-MAX(FV(Inputs!$B111/12,C$1*12+MthOff,Inputs!$B112,-Inputs!$B110),0) -> -13089.45 | D74: =-MAX(FV(Inputs!$B111/12,D$1*12+MthOff,Inputs!$B112,-Inputs!$B110),0) -> -10689.418 | E74: =-MAX(FV(Inputs!$B111/12,E$1*12+MthOff,Inputs!$B112,-Inputs!$B110),0) -> -8166.5945 | F74: =-MAX(FV(Inputs!$B111/12,F$1*12+MthOff,Inputs!$B112,-Inputs!$B110),0) -> -5514.6991 | G74: =-MAX(FV(Inputs!$B111/12,G$1*12+MthOff,Inputs!$B112,-Inputs!$B110),0) -> -2727.1277 | H74: =-MAX(FV(Inputs!$B111/12,H$1*12+MthOff,Inputs!$B112,-Inputs!$B110),0) -> 0 | I74: =-MAX(FV(Inputs!$B111/12,I$1*12+MthOff,Inputs!$B112,-Inputs!$B110),0) -> 0 | J74: =-MAX(FV(Inputs!$B111/12,J$1*12+MthOff,Inputs!$B112,-Inputs!$B110),0) -> 0 | ... AM74: =-MAX(FV(Inputs!$B111/12,AM$1*12+MthOff,Inputs!$B112,-Inputs!$B110),0) -> 0
A75: =TEXT(Inputs!$B$75,"") -> Gudja | C75: =-MAX(FV(Inputs!$B116/12,C$1*12+MthOff,Inputs!$B117,-Inputs!$B115),0) -> -3952.5609 | D75: =-MAX(FV(Inputs!$B116/12,D$1*12+MthOff,Inputs!$B117,-Inputs!$B115),0) -> -3063.4917 | E75: =-MAX(FV(Inputs!$B116/12,E$1*12+MthOff,Inputs!$B117,-Inputs!$B115),0) -> -2156.4772 | F75: =-MAX(FV(Inputs!$B116/12,F$1*12+MthOff,Inputs!$B117,-Inputs!$B115),0) -> -1231.1552 | G75: =-MAX(FV(Inputs!$B116/12,G$1*12+MthOff,Inputs!$B117,-Inputs!$B115),0) -> -287.15625 | H75: =-MAX(FV(Inputs!$B116/12,H$1*12+MthOff,Inputs!$B117,-Inputs!$B115),0) -> 0 | I75: =-MAX(FV(Inputs!$B116/12,I$1*12+MthOff,Inputs!$B117,-Inputs!$B115),0) -> 0 | J75: =-MAX(FV(Inputs!$B116/12,J$1*12+MthOff,Inputs!$B117,-Inputs!$B115),0) -> 0 | ... AM75: =-MAX(FV(Inputs!$B116/12,AM$1*12+MthOff,Inputs!$B117,-Inputs!$B115),0) -> 0
A76: =TEXT(Inputs!$B$80,"") -> Marsa | C76: =-MAX(FV(Inputs!$B121/12,C$1*12+MthOff,Inputs!$B122,-Inputs!$B120),0) -> -8551.2062 | D76: =-MAX(FV(Inputs!$B121/12,D$1*12+MthOff,Inputs!$B122,-Inputs!$B120),0) -> -7351.3334 | E76: =-MAX(FV(Inputs!$B121/12,E$1*12+MthOff,Inputs!$B122,-Inputs!$B120),0) -> -6114.9653 | F76: =-MAX(FV(Inputs!$B121/12,F$1*12+MthOff,Inputs!$B122,-Inputs!$B120),0) -> -4840.9918 | G76: =-MAX(FV(Inputs!$B121/12,G$1*12+MthOff,Inputs!$B122,-Inputs!$B120),0) -> -3528.2693 | H76: =-MAX(FV(Inputs!$B121/12,H$1*12+MthOff,Inputs!$B122,-Inputs!$B120),0) -> -2175.6191 | I76: =-MAX(FV(Inputs!$B121/12,I$1*12+MthOff,Inputs!$B122,-Inputs!$B120),0) -> -781.82667 | J76: =-MAX(FV(Inputs!$B121/12,J$1*12+MthOff,Inputs!$B122,-Inputs!$B120),0) -> 0 | ... AM76: =-MAX(FV(Inputs!$B121/12,AM$1*12+MthOff,Inputs!$B122,-Inputs!$B120),0) -> 0
A77: Other loan | C77: =-MAX(FV(Inputs!$B126/12,C$1*12+MthOff,Inputs!$B127,-Inputs!$B125),0) -> -3693.1592 | D77: =-MAX(FV(Inputs!$B126/12,D$1*12+MthOff,Inputs!$B127,-Inputs!$B125),0) -> -3304.1671 | E77: =-MAX(FV(Inputs!$B126/12,E$1*12+MthOff,Inputs!$B127,-Inputs!$B125),0) -> -2891.1827 | F77: =-MAX(FV(Inputs!$B126/12,F$1*12+MthOff,Inputs!$B127,-Inputs!$B125),0) -> -2452.7265 | G77: =-MAX(FV(Inputs!$B126/12,G$1*12+MthOff,Inputs!$B127,-Inputs!$B125),0) -> -1987.2271 | H77: =-MAX(FV(Inputs!$B126/12,H$1*12+MthOff,Inputs!$B127,-Inputs!$B125),0) -> -1493.0168 | I77: =-MAX(FV(Inputs!$B126/12,I$1*12+MthOff,Inputs!$B127,-Inputs!$B125),0) -> -968.32473 | J77: =-MAX(FV(Inputs!$B126/12,J$1*12+MthOff,Inputs!$B127,-Inputs!$B125),0) -> -411.27076 | ... AM77: =-MAX(FV(Inputs!$B126/12,AM$1*12+MthOff,Inputs!$B127,-Inputs!$B125),0) -> 0
C78: =SUM(C60:C77) -> 1486488 | D78: =SUM(D60:D77) -> 1578514.8 | E78: =SUM(E60:E77) -> 1679362.5 | F78: =SUM(F60:F77) -> 1762841.5 | G78: =SUM(G60:G77) -> 1878344.1 | H78: =SUM(H60:H77) -> 2000687.8 | I78: =SUM(I60:I77) -> 2138157 | J78: =SUM(J60:J77) -> 2276174.9 | ... AM78: =SUM(AM60:AM77) -> 7467369
A80: Cash available (after buffer) | C80: =C61-buffer -> 33136.875 | D80: =D61-buffer -> 57140.903 | E80: =E61-buffer -> 87759.434 | F80: =F61-buffer -> 99100.176 | G80: =G61-buffer -> 142148.9 | H80: =H61-buffer -> 192078.06 | I80: =I61-buffer -> 266036.18 | J80: =J61-buffer -> 339084.49 | ... AM80: =AM61-buffer -> 2549876.4
A81: Liquidation required | C81: =IF(C80<0,-C80,0) -> 0 | D81: =IF(D80+SUM($C81:C81)<0,-(D80+SUM($C81:C81)),0) -> 0 | E81: =IF(E80+SUM($C81:D81)<0,-(E80+SUM($C81:D81)),0) -> 0 | F81: =IF(F80+SUM($C81:E81)<0,-(F80+SUM($C81:E81)),0) -> 0 | G81: =IF(G80+SUM($C81:F81)<0,-(G80+SUM($C81:F81)),0) -> 0 | H81: =IF(H80+SUM($C81:G81)<0,-(H80+SUM($C81:G81)),0) -> 0 | I81: =IF(I80+SUM($C81:H81)<0,-(I80+SUM($C81:H81)),0) -> 0 | J81: =IF(J80+SUM($C81:I81)<0,-(J80+SUM($C81:I81)),0) -> 0 | K81: =IF(K80+SUM($C81:J81)<0,-(K80+SUM($C81:J81)),0) -> 0 | ... AM81: =IF(AM80+SUM($C81:AL81)<0,-(AM80+SUM($C81:AL81)),0) -> 0
A83: Liquidations
A85: Stock market equity
A86: b/fwd | C86: =C69 -> 31987.064 | D86: =C89 -> 31987.064 | E86: =D89 -> 34546.03 | F86: =E89 -> 37309.712 | G86: =F89 -> 40294.489 | H86: =G89 -> 43518.048 | I86: =H89 -> 46999.492 | J86: =I89 -> 50759.451 | K86: =J89 -> 54820.207 | ... AM86: =AL89 -> 472939.76
A87: Disposals | C87: =-MIN(C86, C81/(1-Inputs!$B$193)) -> 0 | D87: =-MIN(D86, D81/(1-Inputs!$B$193)) -> 0 | E87: =-MIN(E86, E81/(1-Inputs!$B$193)) -> 0 | F87: =-MIN(F86, F81/(1-Inputs!$B$193)) -> 0 | G87: =-MIN(G86, G81/(1-Inputs!$B$193)) -> 0 | H87: =-MIN(H86, H81/(1-Inputs!$B$193)) -> 0 | I87: =-MIN(I86, I81/(1-Inputs!$B$193)) -> 0 | J87: =-MIN(J86, J81/(1-Inputs!$B$193)) -> 0 | ... AM87: =-MIN(AM86, AM81/(1-Inputs!$B$193)) -> 0
A88: Growth | C88: 0 | D88: =SUM(D86:D87)*stinc -> 2558.9651 | E88: =SUM(E86:E87)*stinc -> 2763.6824 | F88: =SUM(F86:F87)*stinc -> 2984.777 | G88: =SUM(G86:G87)*stinc -> 3223.5591 | H88: =SUM(H86:H87)*stinc -> 3481.4438 | I88: =SUM(I86:I87)*stinc -> 3759.9593 | J88: =SUM(J86:J87)*stinc -> 4060.7561 | K88: =SUM(K86:K87)*stinc -> 4385.6166 | ... AM88: =SUM(AM86:AM87)*stinc -> 37835.181
A89: c/fwd | C89: =SUM(C86:C88) -> 31987.064 | D89: =SUM(D86:D88) -> 34546.03 | E89: =SUM(E86:E88) -> 37309.712 | F89: =SUM(F86:F88) -> 40294.489 | G89: =SUM(G86:G88) -> 43518.048 | H89: =SUM(H86:H88) -> 46999.492 | I89: =SUM(I86:I88) -> 50759.451 | J89: =SUM(J86:J88) -> 54820.207 | ... AM89: =SUM(AM86:AM88) -> 510774.94
A90: Disposal costs | C90: =C87*Inputs!$B$193 -> 0 | D90: =D87*Inputs!$B$193 -> 0 | E90: =E87*Inputs!$B$193 -> 0 | F90: =F87*Inputs!$B$193 -> 0 | G90: =G87*Inputs!$B$193 -> 0 | H90: =H87*Inputs!$B$193 -> 0 | I90: =I87*Inputs!$B$193 -> 0 | J90: =J87*Inputs!$B$193 -> 0 | ... AM90: =AM87*Inputs!$B$193 -> 0
A91: Net proceeds | C91: =-C87+C90 -> 0 | D91: =-D87+D90 -> 0 | E91: =-E87+E90 -> 0 | F91: =-F87+F90 -> 0 | G91: =-G87+G90 -> 0 | H91: =-H87+H90 -> 0 | I91: =-I87+I90 -> 0 | J91: =-J87+J90 -> 0 | ... AM91: =-AM87+AM90 -> 0
A93: Cash available (after buffer) | C93: =C80+SUM($C91:C91) -> 33136.875 | D93: =D80+SUM($C91:D91) -> 57140.903 | E93: =E80+SUM($C91:E91) -> 87759.434 | F93: =F80+SUM($C91:F91) -> 99100.176 | G93: =G80+SUM($C91:G91) -> 142148.9 | H93: =H80+SUM($C91:H91) -> 192078.06 | I93: =I80+SUM($C91:I91) -> 266036.18 | J93: =J80+SUM($C91:J91) -> 339084.49 | ... AM93: =AM80+SUM($C91:AM91) -> 2549876.4
A94: Liquidation required | C94: =IF(C93<0,-C93,0) -> 0 | D94: =IF(D93+SUM($C94:C94)<0,-(D93+SUM($C94:C94)),0) -> 0 | E94: =IF(E93+SUM($C94:D94)<0,-(E93+SUM($C94:D94)),0) -> 0 | F94: =IF(F93+SUM($C94:E94)<0,-(F93+SUM($C94:E94)),0) -> 0 | G94: =IF(G93+SUM($C94:F94)<0,-(G93+SUM($C94:F94)),0) -> 0 | H94: =IF(H93+SUM($C94:G94)<0,-(H93+SUM($C94:G94)),0) -> 0 | I94: =IF(I93+SUM($C94:H94)<0,-(I93+SUM($C94:H94)),0) -> 0 | J94: =IF(J93+SUM($C94:I94)<0,-(J93+SUM($C94:I94)),0) -> 0 | K94: =IF(K93+SUM($C94:J94)<0,-(K93+SUM($C94:J94)),0) -> 0 | ... AM94: =IF(AM93+SUM($C94:AL94)<0,-(AM93+SUM($C94:AL94)),0) -> 0
A96: =IF(Inputs!$B$197=6,IFERROR(_xlfn.XLOOKUP($B96,Inputs!$B$198:$B$202,Inputs!$A$198:$A$202,,0,1),""),IFERROR(_xlfn.XLOOKUP($B96,Inputs!$C$198:$C$202,Inputs!$A$198:$A$202,,0,1),"")) -> Gudja | B96: 1
A97: b/fwd | C97: =IFERROR(VLOOKUP($A96,$A$60:$H$78,C$1+2,FALSE),0) -> 81995.057 | D97: =C100 -> 81995.057 | E97: =D100 -> 84454.909 | F97: =E100 -> 86988.556 | G97: =F100 -> 89598.213 | H97: =G100 -> 92286.159 | I97: =H100 -> 95054.744 | J97: =I100 -> 97906.387 | K97: =J100 -> 100843.58 | ... AM97: =AL100 -> 230722.81
A98: Disposals | C98: =-IF(SUM(C94:D94)>0,C97,0) -> 0 | D98: =-IF(E94>0,D97,0) -> 0 | E98: =-IF(F94>0,E97,0) -> 0 | F98: =-IF(G94>0,F97,0) -> 0 | G98: =-IF(H94>0,G97,0) -> 0 | H98: =-IF(I94>0,H97,0) -> 0 | I98: =-IF(J94>0,I97,0) -> 0 | J98: =-IF(K94>0,J97,0) -> 0 | K98: =-IF(L94>0,K97,0) -> 0 | ... AM98: =-IF(AN94>0,AM97,0) -> 0
A99: Growth | C99: 0 | D99: =SUM(D97:D98)*princ -> 2459.8517 | E99: =SUM(E97:E98)*princ -> 2533.6473 | F99: =SUM(F97:F98)*princ -> 2609.6567 | G99: =SUM(G97:G98)*princ -> 2687.9464 | H99: =SUM(H97:H98)*princ -> 2768.5848 | I99: =SUM(I97:I98)*princ -> 2851.6423 | J99: =SUM(J97:J98)*princ -> 2937.1916 | K99: =SUM(K97:K98)*princ -> 3025.3073 | ... AM99: =SUM(AM97:AM98)*princ -> 6921.6844
A100: c/fwd | C100: =SUM(C97:C99) -> 81995.057 | D100: =SUM(D97:D99) -> 84454.909 | E100: =SUM(E97:E99) -> 86988.556 | F100: =SUM(F97:F99) -> 89598.213 | G100: =SUM(G97:G99) -> 92286.159 | H100: =SUM(H97:H99) -> 95054.744 | I100: =SUM(I97:I99) -> 97906.387 | J100: =SUM(J97:J99) -> 100843.58 | ... AM100: =SUM(AM97:AM99) -> 237644.5
A101: Disposal costs | C101: =C98*Inputs!$B$195 -> 0 | D101: =D98*Inputs!$B$195 -> 0 | E101: =E98*Inputs!$B$195 -> 0 | F101: =F98*Inputs!$B$195 -> 0 | G101: =G98*Inputs!$B$195 -> 0 | H101: =H98*Inputs!$B$195 -> 0 | I101: =I98*Inputs!$B$195 -> 0 | J101: =J98*Inputs!$B$195 -> 0 | ... AM101: =AM98*Inputs!$B$195 -> 0
A102: Rental income foregone | C102: =IFERROR(-IF(C97=0,VLOOKUP($A96,$8:$12,C$1+2,FALSE),0),0) -> 0 | D102: =IFERROR(-IF(D97=0,VLOOKUP($A96,$8:$12,D$1+2,FALSE),0),0) -> 0 | E102: =IFERROR(-IF(E97=0,VLOOKUP($A96,$8:$12,E$1+2,FALSE),0),0) -> 0 | F102: =IFERROR(-IF(F97=0,VLOOKUP($A96,$8:$12,F$1+2,FALSE),0),0) -> 0 | G102: =IFERROR(-IF(G97=0,VLOOKUP($A96,$8:$12,G$1+2,FALSE),0),0) -> 0 | H102: =IFERROR(-IF(H97=0,VLOOKUP($A96,$8:$12,H$1+2,FALSE),0),0) -> 0 | I102: =IFERROR(-IF(I97=0,VLOOKUP($A96,$8:$12,I$1+2,FALSE),0),0) -> 0 | J102: =IFERROR(-IF(J97=0,VLOOKUP($A96,$8:$12,J$1+2,FALSE),0),0) -> 0 | ... AM102: =IFERROR(-IF(AM97=0,VLOOKUP($A96,$8:$12,AM$1+2,FALSE),0),0) -> 0
A103: Annual cost saved | C103: =IFERROR(IF(C97=0,VLOOKUP($A96,$40:$44,C$1+2,FALSE),0),0) -> 0 | D103: =IFERROR(IF(D97=0,VLOOKUP($A96,$40:$44,D$1+2,FALSE),0),0) -> 0 | E103: =IFERROR(IF(E97=0,VLOOKUP($A96,$40:$44,E$1+2,FALSE),0),0) -> 0 | F103: =IFERROR(IF(F97=0,VLOOKUP($A96,$40:$44,F$1+2,FALSE),0),0) -> 0 | G103: =IFERROR(IF(G97=0,VLOOKUP($A96,$40:$44,G$1+2,FALSE),0),0) -> 0 | H103: =IFERROR(IF(H97=0,VLOOKUP($A96,$40:$44,H$1+2,FALSE),0),0) -> 0 | I103: =IFERROR(IF(I97=0,VLOOKUP($A96,$40:$44,I$1+2,FALSE),0),0) -> 0 | J103: =IFERROR(IF(J97=0,VLOOKUP($A96,$40:$44,J$1+2,FALSE),0),0) -> 0 | ... AM103: =IFERROR(IF(AM97=0,VLOOKUP($A96,$40:$44,AM$1+2,FALSE),0),0) -> 0
A104: Loan repayment | B104: =A96 -> Gudja | C104: =IF(AND(C97>0,C100=0),VLOOKUP($A96,$72:$76,C$1+2,FALSE),0) -> 0 | D104: =IF(AND(D97>0,D100=0),VLOOKUP($A96,$72:$76,D$1+2,FALSE),0) -> 0 | E104: =IF(AND(E97>0,E100=0),VLOOKUP($A96,$72:$76,E$1+2,FALSE),0) -> 0 | F104: =IF(AND(F97>0,F100=0),VLOOKUP($A96,$72:$76,F$1+2,FALSE),0) -> 0 | G104: =IF(AND(G97>0,G100=0),VLOOKUP($A96,$72:$76,G$1+2,FALSE),0) -> 0 | H104: =IF(AND(H97>0,H100=0),VLOOKUP($A96,$72:$76,H$1+2,FALSE),0) -> 0 | I104: =IF(AND(I97>0,I100=0),VLOOKUP($A96,$72:$76,I$1+2,FALSE),0) -> 0 | J104: =IF(AND(J97>0,J100=0),VLOOKUP($A96,$72:$76,J$1+2,FALSE),0) -> 0 | ... AM104: =IF(AND(AM97>0,AM100=0),VLOOKUP($A96,$72:$76,AM$1+2,FALSE),0) -> 0
A105: Net proceeds | C105: =-C98+SUM(C101:C104) -> 0 | D105: =-D98+SUM(D101:D104) -> 0 | E105: =-E98+SUM(E101:E104) -> 0 | F105: =-F98+SUM(F101:F104) -> 0 | G105: =-G98+SUM(G101:G104) -> 0 | H105: =-H98+SUM(H101:H104) -> 0 | I105: =-I98+SUM(I101:I104) -> 0 | J105: =-J98+SUM(J101:J104) -> 0 | ... AM105: =-AM98+SUM(AM101:AM104) -> 0
A107: Cash available (after buffer) | C107: =C93+SUM($C105:C105) -> 33136.875 | D107: =D93+SUM($C105:D105) -> 57140.903 | E107: =E93+SUM($C105:E105) -> 87759.434 | F107: =F93+SUM($C105:F105) -> 99100.176 | G107: =G93+SUM($C105:G105) -> 142148.9 | H107: =H93+SUM($C105:H105) -> 192078.06 | I107: =I93+SUM($C105:I105) -> 266036.18 | J107: =J93+SUM($C105:J105) -> 339084.49 | ... AM107: =AM93+SUM($C105:AM105) -> 2549876.4
A108: Extra cash | C108: =MAX(C107+buffer,0)-MAX(C$93+buffer,0) -> 0 | D108: =MAX(D107+buffer,0)-MAX(D$93+buffer,0) -> 0 | E108: =MAX(E107+buffer,0)-MAX(E$93+buffer,0) -> 0 | F108: =MAX(F107+buffer,0)-MAX(F$93+buffer,0) -> 0 | G108: =MAX(G107+buffer,0)-MAX(G$93+buffer,0) -> 0 | H108: =MAX(H107+buffer,0)-MAX(H$93+buffer,0) -> 0 | I108: =MAX(I107+buffer,0)-MAX(I$93+buffer,0) -> 0 | J108: =MAX(J107+buffer,0)-MAX(J$93+buffer,0) -> 0 | ... AM108: =MAX(AM107+buffer,0)-MAX(AM$93+buffer,0) -> 0
...

Sheet RetEarly_Engine
B1: 0 | C1: 1 | D1: =C1+1 -> 2 | E1: =D1+1 -> 3 | F1: =E1+1 -> 4 | G1: =F1+1 -> 5 | H1: =G1+1 -> 6 | I1: =H1+1 -> 7 | J1: =I1+1 -> 8 | K1: =J1+1 -> 9 | ... AM1: =AL1+1 -> 37
B2: Year | C2: =YEAR(TODAY()) -> 2026 | D2: =C2+1 -> 2027 | E2: =D2+1 -> 2028 | F2: =E2+1 -> 2029 | G2: =F2+1 -> 2030 | H2: =G2+1 -> 2031 | I2: =H2+1 -> 2032 | J2: =I2+1 -> 2033 | K2: =J2+1 -> 2034 | ... AM2: =AL2+1 -> 2062
B3: 52 | C3: =Inputs!B4 -> 48 | D3: =C3+1 -> 49 | E3: =D3+1 -> 50 | F3: =E3+1 -> 51 | G3: =F3+1 -> 52 | H3: =G3+1 -> 53 | I3: =H3+1 -> 54 | J3: =I3+1 -> 55 | K3: =J3+1 -> 56 | ... AM3: =AL3+1 -> 84
A4: Inflows
A5: Net employment / self-employment income | C5: =IF(AND(Inputs!$B$19>C3,$B$3>C3),Inputs!$B$6*(1+sincr)^B1,0)*ProRate -> 66666.667 | D5: =IF(AND(Inputs!$B$19>D3,$B$3>D3),Inputs!$B$6*(1+sincr)^C1,0) -> 82400 | E5: =IF(AND(Inputs!$B$19>E3,$B$3>E3),Inputs!$B$6*(1+sincr)^D1,0) -> 84872 | F5: =IF(AND(Inputs!$B$19>F3,$B$3>F3),Inputs!$B$6*(1+sincr)^E1,0) -> 87418.16 | G5: =IF(AND(Inputs!$B$19>G3,$B$3>G3),Inputs!$B$6*(1+sincr)^F1,0) -> 0 | H5: =IF(AND(Inputs!$B$19>H3,$B$3>H3),Inputs!$B$6*(1+sincr)^G1,0) -> 0 | I5: =IF(AND(Inputs!$B$19>I3,$B$3>I3),Inputs!$B$6*(1+sincr)^H1,0) -> 0 | J5: =IF(AND(Inputs!$B$19>J3,$B$3>J3),Inputs!$B$6*(1+sincr)^I1,0) -> 0 | K5: =IF(AND(Inputs!$B$19>K3,$B$3>K3),Inputs!$B$6*(1+sincr)^J1,0) -> 0 | ... AM5: =IF(AND(Inputs!$B$19>AM3,$B$3>AM3),Inputs!$B$6*(1+sincr)^AL1,0) -> 0
A6: Net from other work | C6: =IF(C$3<=Inputs!$B$93,Inputs!$B$92,0)*(1+inf)^B$1*ProRate -> 1666.6667 | D6: =IF(D$3<=Inputs!$B$93,Inputs!$B$92,0)*(1+inf)^C$1 -> 2050 | E6: =IF(E$3<=Inputs!$B$93,Inputs!$B$92,0)*(1+inf)^D$1 -> 2101.25 | F6: =IF(F$3<=Inputs!$B$93,Inputs!$B$92,0)*(1+inf)^E$1 -> 2153.7812 | G6: =IF(G$3<=Inputs!$B$93,Inputs!$B$92,0)*(1+inf)^F$1 -> 2207.6258 | H6: =IF(H$3<=Inputs!$B$93,Inputs!$B$92,0)*(1+inf)^G$1 -> 2262.8164 | I6: =IF(I$3<=Inputs!$B$93,Inputs!$B$92,0)*(1+inf)^H$1 -> 2319.3868 | J6: =IF(J$3<=Inputs!$B$93,Inputs!$B$92,0)*(1+inf)^I$1 -> 2377.3715 | K6: =IF(K$3<=Inputs!$B$93,Inputs!$B$92,0)*(1+inf)^J$1 -> 2436.8058 | ... AM6: =IF(AM$3<=Inputs!$B$93,Inputs!$B$92,0)*(1+inf)^AL$1 -> 0
A7: Net rental income from other properties
A8: =TEXT(Inputs!$B$60,"") -> Sliema | C8: =Inputs!B86*ProRate -> 10000 | D8: =C8*(1+rinc) -> 10300 | E8: =D8*(1+rinc) -> 10609 | F8: =E8*(1+rinc) -> 10927.27 | G8: =F8*(1+rinc) -> 11255.088 | H8: =G8*(1+rinc) -> 11592.741 | I8: =H8*(1+rinc) -> 11940.523 | J8: =I8*(1+rinc) -> 12298.739 | K8: =J8*(1+rinc) -> 12667.701 | ... AM8: =AL8*(1+rinc) -> 28982.783
A9: =TEXT(Inputs!$B$65,"") -> Gzira | C9: =Inputs!B87*ProRate -> 8333.3333 | D9: =C9*(1+rinc) -> 8583.3333 | E9: =D9*(1+rinc) -> 8840.8333 | F9: =E9*(1+rinc) -> 9106.0583 | G9: =F9*(1+rinc) -> 9379.2401 | H9: =G9*(1+rinc) -> 9660.6173 | I9: =H9*(1+rinc) -> 9950.4358 | J9: =I9*(1+rinc) -> 10248.949 | K9: =J9*(1+rinc) -> 10556.417 | ... AM9: =AL9*(1+rinc) -> 24152.319
A10: =TEXT(Inputs!$B$70,"") -> Qormi | C10: =Inputs!B88*ProRate -> 6666.6667 | D10: =C10*(1+rinc) -> 6866.6667 | E10: =D10*(1+rinc) -> 7072.6667 | F10: =E10*(1+rinc) -> 7284.8467 | G10: =F10*(1+rinc) -> 7503.3921 | H10: =G10*(1+rinc) -> 7728.4938 | I10: =H10*(1+rinc) -> 7960.3486 | J10: =I10*(1+rinc) -> 8199.1591 | K10: =J10*(1+rinc) -> 8445.1339 | ... AM10: =AL10*(1+rinc) -> 19321.856
A11: =TEXT(Inputs!$B$75,"") -> Gudja | C11: =Inputs!B89*ProRate -> 4166.6667 | D11: =C11*(1+rinc) -> 4291.6667 | E11: =D11*(1+rinc) -> 4420.4167 | F11: =E11*(1+rinc) -> 4553.0292 | G11: =F11*(1+rinc) -> 4689.62 | H11: =G11*(1+rinc) -> 4830.3086 | I11: =H11*(1+rinc) -> 4975.2179 | J11: =I11*(1+rinc) -> 5124.4744 | K11: =J11*(1+rinc) -> 5278.2087 | ... AM11: =AL11*(1+rinc) -> 12076.16
A12: =TEXT(Inputs!$B$80,"") -> Marsa | C12: =Inputs!B90*ProRate -> 5416.6667 | D12: =C12*(1+rinc) -> 5579.1667 | E12: =D12*(1+rinc) -> 5746.5417 | F12: =E12*(1+rinc) -> 5918.9379 | G12: =F12*(1+rinc) -> 6096.5061 | H12: =G12*(1+rinc) -> 6279.4012 | I12: =H12*(1+rinc) -> 6467.7833 | J12: =I12*(1+rinc) -> 6661.8168 | K12: =J12*(1+rinc) -> 6861.6713 | ... AM12: =AL12*(1+rinc) -> 15699.008
A13: Full pension | C13: =IF(C$3<Inputs!$B$19,0,Inputs!$B$21)*(1+inf)^B$1*ProRate -> 0 | D13: =IF(D$3<Inputs!$B$19,0,Inputs!$B$21)*(1+inf)^C$1 -> 0 | E13: =IF(E$3<Inputs!$B$19,0,Inputs!$B$21)*(1+inf)^D$1 -> 0 | F13: =IF(F$3<Inputs!$B$19,0,Inputs!$B$21)*(1+inf)^E$1 -> 0 | G13: =IF(G$3<Inputs!$B$19,0,Inputs!$B$21)*(1+inf)^F$1 -> 0 | H13: =IF(H$3<Inputs!$B$19,0,Inputs!$B$21)*(1+inf)^G$1 -> 0 | I13: =IF(I$3<Inputs!$B$19,0,Inputs!$B$21)*(1+inf)^H$1 -> 0 | J13: =IF(J$3<Inputs!$B$19,0,Inputs!$B$21)*(1+inf)^I$1 -> 0 | K13: =IF(K$3<Inputs!$B$19,0,Inputs!$B$21)*(1+inf)^J$1 -> 0 | ... AM13: =IF(AM$3<Inputs!$B$19,0,Inputs!$B$21)*(1+inf)^AL$1 -> 38920.565
A14: Pension reduction from early retirement | C14: =MIN(0,MAX(-IF(C13=0,0,(Inputs!$B$19-INDEX(3:3,MATCH(0,5:5,0))))*Inputs!$B$189*(1+inf)^B$1*ProRate,-C13)) -> 0 | D14: =MIN(0,MAX(-IF(D13=0,0,(Inputs!$B$19-INDEX(3:3,MATCH(0,5:5,0))))*Inputs!$B$189*(1+inf)^C$1,-D13)) -> 0 | E14: =MIN(0,MAX(-IF(E13=0,0,(Inputs!$B$19-INDEX(3:3,MATCH(0,5:5,0))))*Inputs!$B$189*(1+inf)^D$1,-E13)) -> 0 | F14: =MIN(0,MAX(-IF(F13=0,0,(Inputs!$B$19-INDEX(3:3,MATCH(0,5:5,0))))*Inputs!$B$189*(1+inf)^E$1,-F13)) -> 0 | G14: =MIN(0,MAX(-IF(G13=0,0,(Inputs!$B$19-INDEX(3:3,MATCH(0,5:5,0))))*Inputs!$B$189*(1+inf)^F$1,-G13)) -> 0 | H14: =MIN(0,MAX(-IF(H13=0,0,(Inputs!$B$19-INDEX(3:3,MATCH(0,5:5,0))))*Inputs!$B$189*(1+inf)^G$1,-H13)) -> 0 | I14: =MIN(0,MAX(-IF(I13=0,0,(Inputs!$B$19-INDEX(3:3,MATCH(0,5:5,0))))*Inputs!$B$189*(1+inf)^H$1,-I13)) -> 0 | J14: =MIN(0,MAX(-IF(J13=0,0,(Inputs!$B$19-INDEX(3:3,MATCH(0,5:5,0))))*Inputs!$B$189*(1+inf)^I$1,-J13)) -> 0 | K14: =MIN(0,MAX(-IF(K13=0,0,(Inputs!$B$19-INDEX(3:3,MATCH(0,5:5,0))))*Inputs!$B$189*(1+inf)^J$1,-K13)) -> 0 | ... AM14: =MIN(0,MAX(-IF(AM13=0,0,(Inputs!$B$19-INDEX(3:3,MATCH(0,5:5,0))))*Inputs!$B$189*(1+inf)^AL$1,-AM13)) -> -9486.8877
A15: Other post-retirement income | C15: =IF(AND(C$3>=Inputs!$B$174,C$3<=Inputs!$B$175),Inputs!$B$173*(1+inf)^B$1,0)*ProRate -> 0 | D15: =IF(AND(D$3>=Inputs!$B$174,D$3<=Inputs!$B$175),Inputs!$B$173*(1+inf)^C$1,0) -> 0 | E15: =IF(AND(E$3>=Inputs!$B$174,E$3<=Inputs!$B$175),Inputs!$B$173*(1+inf)^D$1,0) -> 0 | F15: =IF(AND(F$3>=Inputs!$B$174,F$3<=Inputs!$B$175),Inputs!$B$173*(1+inf)^E$1,0) -> 0 | G15: =IF(AND(G$3>=Inputs!$B$174,G$3<=Inputs!$B$175),Inputs!$B$173*(1+inf)^F$1,0) -> 0 | H15: =IF(AND(H$3>=Inputs!$B$174,H$3<=Inputs!$B$175),Inputs!$B$173*(1+inf)^G$1,0) -> 0 | I15: =IF(AND(I$3>=Inputs!$B$174,I$3<=Inputs!$B$175),Inputs!$B$173*(1+inf)^H$1,0) -> 0 | J15: =IF(AND(J$3>=Inputs!$B$174,J$3<=Inputs!$B$175),Inputs!$B$173*(1+inf)^I$1,0) -> 0 | K15: =IF(AND(K$3>=Inputs!$B$174,K$3<=Inputs!$B$175),Inputs!$B$173*(1+inf)^J$1,0) -> 0 | ... AM15: =IF(AND(AM$3>=Inputs!$B$174,AM$3<=Inputs!$B$175),Inputs!$B$173*(1+inf)^AL$1,0) -> 0
A16: Major one-off income events
A17: =TEXT(Inputs!B132,"") -> Inheritance | C17: =IF(C$2=Inputs!$B134,Inputs!$B133,0)*(1+inf)^B$1 -> 0 | D17: =IF(D$2=Inputs!$B134,Inputs!$B133,0)*(1+inf)^C$1 -> 0 | E17: =IF(E$2=Inputs!$B134,Inputs!$B133,0)*(1+inf)^D$1 -> 0 | F17: =IF(F$2=Inputs!$B134,Inputs!$B133,0)*(1+inf)^E$1 -> 0 | G17: =IF(G$2=Inputs!$B134,Inputs!$B133,0)*(1+inf)^F$1 -> 0 | H17: =IF(H$2=Inputs!$B134,Inputs!$B133,0)*(1+inf)^G$1 -> 0 | I17: =IF(I$2=Inputs!$B134,Inputs!$B133,0)*(1+inf)^H$1 -> 0 | J17: =IF(J$2=Inputs!$B134,Inputs!$B133,0)*(1+inf)^I$1 -> 0 | ... AM17: =IF(AM$2=Inputs!$B134,Inputs!$B133,0)*(1+inf)^AL$1 -> 0
A18: =TEXT(Inputs!B137,"") -> Sell Painting | C18: =IF(C$2=Inputs!$B139,Inputs!$B138,0)*(1+inf)^B$1 -> 0 | D18: =IF(D$2=Inputs!$B139,Inputs!$B138,0)*(1+inf)^C$1 -> 0 | E18: =IF(E$2=Inputs!$B139,Inputs!$B138,0)*(1+inf)^D$1 -> 0 | F18: =IF(F$2=Inputs!$B139,Inputs!$B138,0)*(1+inf)^E$1 -> 10768.906 | G18: =IF(G$2=Inputs!$B139,Inputs!$B138,0)*(1+inf)^F$1 -> 0 | H18: =IF(H$2=Inputs!$B139,Inputs!$B138,0)*(1+inf)^G$1 -> 0 | I18: =IF(I$2=Inputs!$B139,Inputs!$B138,0)*(1+inf)^H$1 -> 0 | J18: =IF(J$2=Inputs!$B139,Inputs!$B138,0)*(1+inf)^I$1 -> 0 | ... AM18: =IF(AM$2=Inputs!$B139,Inputs!$B138,0)*(1+inf)^AL$1 -> 0
A19: =TEXT(Inputs!B142,"") -> Sell Jewels | C19: =IF(C$2=Inputs!$B144,Inputs!$B143,0)*(1+inf)^B$1 -> 0 | D19: =IF(D$2=Inputs!$B144,Inputs!$B143,0)*(1+inf)^C$1 -> 0 | E19: =IF(E$2=Inputs!$B144,Inputs!$B143,0)*(1+inf)^D$1 -> 0 | F19: =IF(F$2=Inputs!$B144,Inputs!$B143,0)*(1+inf)^E$1 -> 0 | G19: =IF(G$2=Inputs!$B144,Inputs!$B143,0)*(1+inf)^F$1 -> 0 | H19: =IF(H$2=Inputs!$B144,Inputs!$B143,0)*(1+inf)^G$1 -> 0 | I19: =IF(I$2=Inputs!$B144,Inputs!$B143,0)*(1+inf)^H$1 -> 5798.4671 | J19: =IF(J$2=Inputs!$B144,Inputs!$B143,0)*(1+inf)^I$1 -> 0 | ... AM19: =IF(AM$2=Inputs!$B144,Inputs!$B143,0)*(1+inf)^AL$1 -> 0
A20: Interest on cash balances | C20: =MAX(AVERAGE(C57,C57+SUM(C5:C19)-C54)*Inputs!$B$181,0) -> 1520.2083 | D20: =MAX(AVERAGE(D57,D57+SUM(D5:D19)-D54)*Inputs!$B$181,0) -> 2102.1948 | E20: =MAX(AVERAGE(E57,E57+SUM(E5:E19)-E54)*Inputs!$B$181,0) -> 2776.5474 | F20: =MAX(AVERAGE(F57,F57+SUM(F5:F19)-F54)*Inputs!$B$181,0) -> 3294.5631 | G20: =MAX(AVERAGE(G57,G57+SUM(G5:G19)-G54)*Inputs!$B$181,0) -> 2840.5292 | H20: =MAX(AVERAGE(H57,H57+SUM(H5:H19)-H54)*Inputs!$B$181,0) -> 1675.4836 | I20: =MAX(AVERAGE(I57,I57+SUM(I5:I19)-I54)*Inputs!$B$181,0) -> 765.66913 | J20: =MAX(AVERAGE(J57,J57+SUM(J5:J19)-J54)*Inputs!$B$181,0) -> 9.6942719 | ... AM20: =MAX(AVERAGE(AM57,AM57+SUM(AM5:AM19)-AM54)*Inputs!$B$181,0) -> 0
C21: =SUM(C4:C20) -> 104436.88 | D21: =SUM(D4:D20) -> 122173.03 | E21: =SUM(E4:E20) -> 126439.26 | F21: =SUM(F4:F20) -> 141425.55 | G21: =SUM(G4:G20) -> 43972.001 | H21: =SUM(H4:H20) -> 44029.862 | I21: =SUM(I4:I20) -> 50177.832 | J21: =SUM(J4:J20) -> 44920.204 | ... AM21: =SUM(AM4:AM20) -> 129665.8
A22: Outflows
A23: Credit cards cleared | C23: =Inputs!B97 -> 1000 | D23: 0 | E23: 0 | F23: 0 | G23: 0 | H23: 0 | I23: 0 | J23: 0 | K23: 0 | L23: 0 | M23: 0 | N23: 0 | O23: 0 | P23: 0 | Q23: 0 | R23: 0 | S23: 0 | T23: 0 | U23: 0 | V23: 0 | W23: 0 | X23: 0 | Y23: 0 | Z23: 0 | AA23: 0 | AB23: 0 | AC23: 0 | AD23: 0 | AE23: 0 | AF23: 0 | AG23: 0 | AH23: 0 | AI23: 0 | AJ23: 0 | AK23: 0 | AL23: 0 | AM23: 0
A24: Home loan repayment | C24: =MIN(IF(B$1=0,MthRem,12), MAX(Inputs!$G$15-IF(B$1=0,0,B$1*12+MthOff), 0))*Inputs!$B$17 -> 8000 | D24: =MIN(IF(C$1=0,MthRem,12), MAX(Inputs!$G$15-IF(C$1=0,0,C$1*12+MthOff), 0))*Inputs!$B$17 -> 9600 | E24: =MIN(IF(D$1=0,MthRem,12), MAX(Inputs!$G$15-IF(D$1=0,0,D$1*12+MthOff), 0))*Inputs!$B$17 -> 9600 | F24: =MIN(IF(E$1=0,MthRem,12), MAX(Inputs!$G$15-IF(E$1=0,0,E$1*12+MthOff), 0))*Inputs!$B$17 -> 9600 | G24: =MIN(IF(F$1=0,MthRem,12), MAX(Inputs!$G$15-IF(F$1=0,0,F$1*12+MthOff), 0))*Inputs!$B$17 -> 9600 | H24: =MIN(IF(G$1=0,MthRem,12), MAX(Inputs!$G$15-IF(G$1=0,0,G$1*12+MthOff), 0))*Inputs!$B$17 -> 8035.6231 | I24: =MIN(IF(H$1=0,MthRem,12), MAX(Inputs!$G$15-IF(H$1=0,0,H$1*12+MthOff), 0))*Inputs!$B$17 -> 0 | J24: =MIN(IF(I$1=0,MthRem,12), MAX(Inputs!$G$15-IF(I$1=0,0,I$1*12+MthOff), 0))*Inputs!$B$17 -> 0 | ... AM24: =MIN(IF(AL$1=0,MthRem,12), MAX(Inputs!$G$15-IF(AL$1=0,0,AL$1*12+MthOff), 0))*Inputs!$B$17 -> 0
A25: Other property loans repayments
A26: =TEXT(Inputs!$B$60,"") -> Sliema | C26: =MIN(IF(B$1=0,MthRem,12), MAX(Inputs!$G$100-IF(B$1=0,0,B$1*12+MthOff), 0))*Inputs!$B$102 -> 5000 | D26: =MIN(IF(C$1=0,MthRem,12), MAX(Inputs!$G$100-IF(C$1=0,0,C$1*12+MthOff), 0))*Inputs!$B$102 -> 6000 | E26: =MIN(IF(D$1=0,MthRem,12), MAX(Inputs!$G$100-IF(D$1=0,0,D$1*12+MthOff), 0))*Inputs!$B$102 -> 6000 | F26: =MIN(IF(E$1=0,MthRem,12), MAX(Inputs!$G$100-IF(E$1=0,0,E$1*12+MthOff), 0))*Inputs!$B$102 -> 6000 | G26: =MIN(IF(F$1=0,MthRem,12), MAX(Inputs!$G$100-IF(F$1=0,0,F$1*12+MthOff), 0))*Inputs!$B$102 -> 6000 | H26: =MIN(IF(G$1=0,MthRem,12), MAX(Inputs!$G$100-IF(G$1=0,0,G$1*12+MthOff), 0))*Inputs!$B$102 -> 6000 | I26: =MIN(IF(H$1=0,MthRem,12), MAX(Inputs!$G$100-IF(H$1=0,0,H$1*12+MthOff), 0))*Inputs!$B$102 -> 6000 | J26: =MIN(IF(I$1=0,MthRem,12), MAX(Inputs!$G$100-IF(I$1=0,0,I$1*12+MthOff), 0))*Inputs!$B$102 -> 6000 | ... AM26: =MIN(IF(AL$1=0,MthRem,12), MAX(Inputs!$G$100-IF(AL$1=0,0,AL$1*12+MthOff), 0))*Inputs!$B$102 -> 0
A27: =TEXT(Inputs!$B$65,"") -> Gzira | C27: =MIN(IF(B$1=0,MthRem,12), MAX(Inputs!$G$105-IF(B$1=0,0,B$1*12+MthOff), 0))*Inputs!$B$107 -> 2000 | D27: =MIN(IF(C$1=0,MthRem,12), MAX(Inputs!$G$105-IF(C$1=0,0,C$1*12+MthOff), 0))*Inputs!$B$107 -> 2400 | E27: =MIN(IF(D$1=0,MthRem,12), MAX(Inputs!$G$105-IF(D$1=0,0,D$1*12+MthOff), 0))*Inputs!$B$107 -> 2400 | F27: =MIN(IF(E$1=0,MthRem,12), MAX(Inputs!$G$105-IF(E$1=0,0,E$1*12+MthOff), 0))*Inputs!$B$107 -> 2023.4029 | G27: =MIN(IF(F$1=0,MthRem,12), MAX(Inputs!$G$105-IF(F$1=0,0,F$1*12+MthOff), 0))*Inputs!$B$107 -> 0 | H27: =MIN(IF(G$1=0,MthRem,12), MAX(Inputs!$G$105-IF(G$1=0,0,G$1*12+MthOff), 0))*Inputs!$B$107 -> 0 | I27: =MIN(IF(H$1=0,MthRem,12), MAX(Inputs!$G$105-IF(H$1=0,0,H$1*12+MthOff), 0))*Inputs!$B$107 -> 0 | J27: =MIN(IF(I$1=0,MthRem,12), MAX(Inputs!$G$105-IF(I$1=0,0,I$1*12+MthOff), 0))*Inputs!$B$107 -> 0 | ... AM27: =MIN(IF(AL$1=0,MthRem,12), MAX(Inputs!$G$105-IF(AL$1=0,0,AL$1*12+MthOff), 0))*Inputs!$B$107 -> 0
A28: =TEXT(Inputs!$B$70,"") -> Qormi | C28: =MIN(IF(B$1=0,MthRem,12), MAX(Inputs!$G$110-IF(B$1=0,0,B$1*12+MthOff), 0))*Inputs!$B$112 -> 2500 | D28: =MIN(IF(C$1=0,MthRem,12), MAX(Inputs!$G$110-IF(C$1=0,0,C$1*12+MthOff), 0))*Inputs!$B$112 -> 3000 | E28: =MIN(IF(D$1=0,MthRem,12), MAX(Inputs!$G$110-IF(D$1=0,0,D$1*12+MthOff), 0))*Inputs!$B$112 -> 3000 | F28: =MIN(IF(E$1=0,MthRem,12), MAX(Inputs!$G$110-IF(E$1=0,0,E$1*12+MthOff), 0))*Inputs!$B$112 -> 3000 | G28: =MIN(IF(F$1=0,MthRem,12), MAX(Inputs!$G$110-IF(F$1=0,0,F$1*12+MthOff), 0))*Inputs!$B$112 -> 3000 | H28: =MIN(IF(G$1=0,MthRem,12), MAX(Inputs!$G$110-IF(G$1=0,0,G$1*12+MthOff), 0))*Inputs!$B$112 -> 2796.8597 | I28: =MIN(IF(H$1=0,MthRem,12), MAX(Inputs!$G$110-IF(H$1=0,0,H$1*12+MthOff), 0))*Inputs!$B$112 -> 0 | J28: =MIN(IF(I$1=0,MthRem,12), MAX(Inputs!$G$110-IF(I$1=0,0,I$1*12+MthOff), 0))*Inputs!$B$112 -> 0 | ... AM28: =MIN(IF(AL$1=0,MthRem,12), MAX(Inputs!$G$110-IF(AL$1=0,0,AL$1*12+MthOff), 0))*Inputs!$B$112 -> 0
A29: =TEXT(Inputs!$B$75,"") -> Gudja | C29: =MIN(IF(B$1=0,MthRem,12), MAX(Inputs!$G$115-IF(B$1=0,0,B$1*12+MthOff), 0))*Inputs!$B$117 -> 800 | D29: =MIN(IF(C$1=0,MthRem,12), MAX(Inputs!$G$115-IF(C$1=0,0,C$1*12+MthOff), 0))*Inputs!$B$117 -> 960 | E29: =MIN(IF(D$1=0,MthRem,12), MAX(Inputs!$G$115-IF(D$1=0,0,D$1*12+MthOff), 0))*Inputs!$B$117 -> 960 | F29: =MIN(IF(E$1=0,MthRem,12), MAX(Inputs!$G$115-IF(E$1=0,0,E$1*12+MthOff), 0))*Inputs!$B$117 -> 960 | G29: =MIN(IF(F$1=0,MthRem,12), MAX(Inputs!$G$115-IF(F$1=0,0,F$1*12+MthOff), 0))*Inputs!$B$117 -> 960 | H29: =MIN(IF(G$1=0,MthRem,12), MAX(Inputs!$G$115-IF(G$1=0,0,G$1*12+MthOff), 0))*Inputs!$B$117 -> 288.25859 | I29: =MIN(IF(H$1=0,MthRem,12), MAX(Inputs!$G$115-IF(H$1=0,0,H$1*12+MthOff), 0))*Inputs!$B$117 -> 0 | J29: =MIN(IF(I$1=0,MthRem,12), MAX(Inputs!$G$115-IF(I$1=0,0,I$1*12+MthOff), 0))*Inputs!$B$117 -> 0 | ... AM29: =MIN(IF(AL$1=0,MthRem,12), MAX(Inputs!$G$115-IF(AL$1=0,0,AL$1*12+MthOff), 0))*Inputs!$B$117 -> 0
A30: =TEXT(Inputs!$B$80,"") -> Marsa | C30: =MIN(IF(B$1=0,MthRem,12), MAX(Inputs!$G$120-IF(B$1=0,0,B$1*12+MthOff), 0))*Inputs!$B$122 -> 1200 | D30: =MIN(IF(C$1=0,MthRem,12), MAX(Inputs!$G$120-IF(C$1=0,0,C$1*12+MthOff), 0))*Inputs!$B$122 -> 1440 | E30: =MIN(IF(D$1=0,MthRem,12), MAX(Inputs!$G$120-IF(D$1=0,0,D$1*12+MthOff), 0))*Inputs!$B$122 -> 1440 | F30: =MIN(IF(E$1=0,MthRem,12), MAX(Inputs!$G$120-IF(E$1=0,0,E$1*12+MthOff), 0))*Inputs!$B$122 -> 1440 | G30: =MIN(IF(F$1=0,MthRem,12), MAX(Inputs!$G$120-IF(F$1=0,0,F$1*12+MthOff), 0))*Inputs!$B$122 -> 1440 | H30: =MIN(IF(G$1=0,MthRem,12), MAX(Inputs!$G$120-IF(G$1=0,0,G$1*12+MthOff), 0))*Inputs!$B$122 -> 1440 | I30: =MIN(IF(H$1=0,MthRem,12), MAX(Inputs!$G$120-IF(H$1=0,0,H$1*12+MthOff), 0))*Inputs!$B$122 -> 1440 | J30: =MIN(IF(I$1=0,MthRem,12), MAX(Inputs!$G$120-IF(I$1=0,0,I$1*12+MthOff), 0))*Inputs!$B$122 -> 789.24881 | ... AM30: =MIN(IF(AL$1=0,MthRem,12), MAX(Inputs!$G$120-IF(AL$1=0,0,AL$1*12+MthOff), 0))*Inputs!$B$122 -> 0
A31: Other loan repayment | C31: =MIN(IF(B$1=0,MthRem,12), MAX(Inputs!$G$125-IF(B$1=0,0,B$1*12+MthOff), 0))*Inputs!$B$127 -> 500 | D31: =MIN(IF(C$1=0,MthRem,12), MAX(Inputs!$G$125-IF(C$1=0,0,C$1*12+MthOff), 0))*Inputs!$B$127 -> 600 | E31: =MIN(IF(D$1=0,MthRem,12), MAX(Inputs!$G$125-IF(D$1=0,0,D$1*12+MthOff), 0))*Inputs!$B$127 -> 600 | F31: =MIN(IF(E$1=0,MthRem,12), MAX(Inputs!$G$125-IF(E$1=0,0,E$1*12+MthOff), 0))*Inputs!$B$127 -> 600 | G31: =MIN(IF(F$1=0,MthRem,12), MAX(Inputs!$G$125-IF(F$1=0,0,F$1*12+MthOff), 0))*Inputs!$B$127 -> 600 | H31: =MIN(IF(G$1=0,MthRem,12), MAX(Inputs!$G$125-IF(G$1=0,0,G$1*12+MthOff), 0))*Inputs!$B$127 -> 600 | I31: =MIN(IF(H$1=0,MthRem,12), MAX(Inputs!$G$125-IF(H$1=0,0,H$1*12+MthOff), 0))*Inputs!$B$127 -> 600 | J31: =MIN(IF(I$1=0,MthRem,12), MAX(Inputs!$G$125-IF(I$1=0,0,I$1*12+MthOff), 0))*Inputs!$B$127 -> 600 | ... AM31: =MIN(IF(AL$1=0,MthRem,12), MAX(Inputs!$G$125-IF(AL$1=0,0,AL$1*12+MthOff), 0))*Inputs!$B$127 -> 0
A32: Dependents cost
A33: =TEXT(Inputs!B33,"") -> John | C33: =IF(Inputs!$B$35>=C$1,Inputs!$B$34,0)*(1+inf)^B$1*ProRate -> 1666.6667 | D33: =IF(Inputs!$B$35>=D$1,Inputs!$B$34,0)*(1+inf)^C$1 -> 2050 | E33: =IF(Inputs!$B$35>=E$1,Inputs!$B$34,0)*(1+inf)^D$1 -> 2101.25 | F33: =IF(Inputs!$B$35>=F$1,Inputs!$B$34,0)*(1+inf)^E$1 -> 0 | G33: =IF(Inputs!$B$35>=G$1,Inputs!$B$34,0)*(1+inf)^F$1 -> 0 | H33: =IF(Inputs!$B$35>=H$1,Inputs!$B$34,0)*(1+inf)^G$1 -> 0 | I33: =IF(Inputs!$B$35>=I$1,Inputs!$B$34,0)*(1+inf)^H$1 -> 0 | J33: =IF(Inputs!$B$35>=J$1,Inputs!$B$34,0)*(1+inf)^I$1 -> 0 | K33: =IF(Inputs!$B$35>=K$1,Inputs!$B$34,0)*(1+inf)^J$1 -> 0 | ... AM33: =IF(Inputs!$B$35>=AM$1,Inputs!$B$34,0)*(1+inf)^AL$1 -> 0
A34: =TEXT(Inputs!B38,"") -> Jack | C34: =IF(Inputs!$B$40>=C$1,Inputs!$B$39,0)*(1+inf)^B$1*ProRate -> 833.33333 | D34: =IF(Inputs!$B$40>=D$1,Inputs!$B$39,0)*(1+inf)^C$1 -> 1025 | E34: =IF(Inputs!$B$40>=E$1,Inputs!$B$39,0)*(1+inf)^D$1 -> 1050.625 | F34: =IF(Inputs!$B$40>=F$1,Inputs!$B$39,0)*(1+inf)^E$1 -> 1076.8906 | G34: =IF(Inputs!$B$40>=G$1,Inputs!$B$39,0)*(1+inf)^F$1 -> 1103.8129 | H34: =IF(Inputs!$B$40>=H$1,Inputs!$B$39,0)*(1+inf)^G$1 -> 0 | I34: =IF(Inputs!$B$40>=I$1,Inputs!$B$39,0)*(1+inf)^H$1 -> 0 | J34: =IF(Inputs!$B$40>=J$1,Inputs!$B$39,0)*(1+inf)^I$1 -> 0 | K34: =IF(Inputs!$B$40>=K$1,Inputs!$B$39,0)*(1+inf)^J$1 -> 0 | ... AM34: =IF(Inputs!$B$40>=AM$1,Inputs!$B$39,0)*(1+inf)^AL$1 -> 0
A35: =TEXT(Inputs!B43,"") -> Bill | C35: =IF(Inputs!$B$45>=C$1,Inputs!$B$44,0)*(1+inf)^B$1*ProRate -> 3333.3333 | D35: =IF(Inputs!$B$45>=D$1,Inputs!$B$44,0)*(1+inf)^C$1 -> 4100 | E35: =IF(Inputs!$B$45>=E$1,Inputs!$B$44,0)*(1+inf)^D$1 -> 0 | F35: =IF(Inputs!$B$45>=F$1,Inputs!$B$44,0)*(1+inf)^E$1 -> 0 | G35: =IF(Inputs!$B$45>=G$1,Inputs!$B$44,0)*(1+inf)^F$1 -> 0 | H35: =IF(Inputs!$B$45>=H$1,Inputs!$B$44,0)*(1+inf)^G$1 -> 0 | I35: =IF(Inputs!$B$45>=I$1,Inputs!$B$44,0)*(1+inf)^H$1 -> 0 | J35: =IF(Inputs!$B$45>=J$1,Inputs!$B$44,0)*(1+inf)^I$1 -> 0 | K35: =IF(Inputs!$B$45>=K$1,Inputs!$B$44,0)*(1+inf)^J$1 -> 0 | ... AM35: =IF(Inputs!$B$45>=AM$1,Inputs!$B$44,0)*(1+inf)^AL$1 -> 0
A36: =TEXT(Inputs!B48,"") -> Stephen | C36: =IF(Inputs!$B$50>=C$1,Inputs!$B$49,0)*(1+inf)^B$1*ProRate -> 2083.3333 | D36: =IF(Inputs!$B$50>=D$1,Inputs!$B$49,0)*(1+inf)^C$1 -> 2562.5 | E36: =IF(Inputs!$B$50>=E$1,Inputs!$B$49,0)*(1+inf)^D$1 -> 2626.5625 | F36: =IF(Inputs!$B$50>=F$1,Inputs!$B$49,0)*(1+inf)^E$1 -> 0 | G36: =IF(Inputs!$B$50>=G$1,Inputs!$B$49,0)*(1+inf)^F$1 -> 0 | H36: =IF(Inputs!$B$50>=H$1,Inputs!$B$49,0)*(1+inf)^G$1 -> 0 | I36: =IF(Inputs!$B$50>=I$1,Inputs!$B$49,0)*(1+inf)^H$1 -> 0 | J36: =IF(Inputs!$B$50>=J$1,Inputs!$B$49,0)*(1+inf)^I$1 -> 0 | K36: =IF(Inputs!$B$50>=K$1,Inputs!$B$49,0)*(1+inf)^J$1 -> 0 | ... AM36: =IF(Inputs!$B$50>=AM$1,Inputs!$B$49,0)*(1+inf)^AL$1 -> 0
A37: =TEXT(Inputs!B53,"") -> Jane | C37: =IF(Inputs!$B$55>=C$1,Inputs!$B$54,0)*(1+inf)^B$1*ProRate -> 2383.3333 | D37: =IF(Inputs!$B$55>=D$1,Inputs!$B$54,0)*(1+inf)^C$1 -> 2931.5 | E37: =IF(Inputs!$B$55>=E$1,Inputs!$B$54,0)*(1+inf)^D$1 -> 3004.7875 | F37: =IF(Inputs!$B$55>=F$1,Inputs!$B$54,0)*(1+inf)^E$1 -> 3079.9072 | G37: =IF(Inputs!$B$55>=G$1,Inputs!$B$54,0)*(1+inf)^F$1 -> 3156.9049 | H37: =IF(Inputs!$B$55>=H$1,Inputs!$B$54,0)*(1+inf)^G$1 -> 3235.8275 | I37: =IF(Inputs!$B$55>=I$1,Inputs!$B$54,0)*(1+inf)^H$1 -> 0 | J37: =IF(Inputs!$B$55>=J$1,Inputs!$B$54,0)*(1+inf)^I$1 -> 0 | K37: =IF(Inputs!$B$55>=K$1,Inputs!$B$54,0)*(1+inf)^J$1 -> 0 | ... AM37: =IF(Inputs!$B$55>=AM$1,Inputs!$B$54,0)*(1+inf)^AL$1 -> 0
A38: Housing rent | C38: =Inputs!$B$23*(1+inf)^B$1*ProRate -> 0 | D38: =Inputs!$B$23*(1+inf)^C$1 -> 0 | E38: =Inputs!$B$23*(1+inf)^D$1 -> 0 | F38: =Inputs!$B$23*(1+inf)^E$1 -> 0 | G38: =Inputs!$B$23*(1+inf)^F$1 -> 0 | H38: =Inputs!$B$23*(1+inf)^G$1 -> 0 | I38: =Inputs!$B$23*(1+inf)^H$1 -> 0 | J38: =Inputs!$B$23*(1+inf)^I$1 -> 0 | K38: =Inputs!$B$23*(1+inf)^J$1 -> 0 | ... AM38: =Inputs!$B$23*(1+inf)^AL$1 -> 0
A39: Other property costs
A40: =TEXT(Inputs!$B$60,"") -> Sliema | C40: =Inputs!$B62*(1+inf)^B$1*ProRate -> 4166.6667 | D40: =Inputs!$B62*(1+inf)^C$1 -> 5125 | E40: =Inputs!$B62*(1+inf)^D$1 -> 5253.125 | F40: =Inputs!$B62*(1+inf)^E$1 -> 5384.4531 | G40: =Inputs!$B62*(1+inf)^F$1 -> 5519.0645 | H40: =Inputs!$B62*(1+inf)^G$1 -> 5657.0411 | I40: =Inputs!$B62*(1+inf)^H$1 -> 5798.4671 | J40: =Inputs!$B62*(1+inf)^I$1 -> 5943.4288 | K40: =Inputs!$B62*(1+inf)^J$1 -> 6092.0145 | ... AM40: =Inputs!$B62*(1+inf)^AL$1 -> 12162.677
A41: =TEXT(Inputs!$B$65,"") -> Gzira | C41: =Inputs!$B67*(1+inf)^B$1*ProRate -> 1666.6667 | D41: =Inputs!$B67*(1+inf)^C$1 -> 2050 | E41: =Inputs!$B67*(1+inf)^D$1 -> 2101.25 | F41: =Inputs!$B67*(1+inf)^E$1 -> 2153.7812 | G41: =Inputs!$B67*(1+inf)^F$1 -> 2207.6258 | H41: =Inputs!$B67*(1+inf)^G$1 -> 2262.8164 | I41: =Inputs!$B67*(1+inf)^H$1 -> 2319.3868 | J41: =Inputs!$B67*(1+inf)^I$1 -> 2377.3715 | K41: =Inputs!$B67*(1+inf)^J$1 -> 2436.8058 | ... AM41: =Inputs!$B67*(1+inf)^AL$1 -> 4865.0706
A42: =TEXT(Inputs!$B$70,"") -> Qormi | C42: =Inputs!$B72*(1+inf)^B$1*ProRate -> 1000 | D42: =Inputs!$B72*(1+inf)^C$1 -> 1230 | E42: =Inputs!$B72*(1+inf)^D$1 -> 1260.75 | F42: =Inputs!$B72*(1+inf)^E$1 -> 1292.2687 | G42: =Inputs!$B72*(1+inf)^F$1 -> 1324.5755 | H42: =Inputs!$B72*(1+inf)^G$1 -> 1357.6899 | I42: =Inputs!$B72*(1+inf)^H$1 -> 1391.6321 | J42: =Inputs!$B72*(1+inf)^I$1 -> 1426.4229 | K42: =Inputs!$B72*(1+inf)^J$1 -> 1462.0835 | ... AM42: =Inputs!$B72*(1+inf)^AL$1 -> 2919.0424
A43: =TEXT(Inputs!$B$75,"") -> Gudja | C43: =Inputs!$B77*(1+inf)^B$1*ProRate -> 833.33333 | D43: =Inputs!$B77*(1+inf)^C$1 -> 1025 | E43: =Inputs!$B77*(1+inf)^D$1 -> 1050.625 | F43: =Inputs!$B77*(1+inf)^E$1 -> 1076.8906 | G43: =Inputs!$B77*(1+inf)^F$1 -> 1103.8129 | H43: =Inputs!$B77*(1+inf)^G$1 -> 1131.4082 | I43: =Inputs!$B77*(1+inf)^H$1 -> 1159.6934 | J43: =Inputs!$B77*(1+inf)^I$1 -> 1188.6858 | K43: =Inputs!$B77*(1+inf)^J$1 -> 1218.4029 | ... AM43: =Inputs!$B77*(1+inf)^AL$1 -> 2432.5353
A44: =TEXT(Inputs!$B$80,"") -> Marsa | C44: =Inputs!$B82*(1+inf)^B$1*ProRate -> 666.66667 | D44: =Inputs!$B82*(1+inf)^C$1 -> 820 | E44: =Inputs!$B82*(1+inf)^D$1 -> 840.5 | F44: =Inputs!$B82*(1+inf)^E$1 -> 861.5125 | G44: =Inputs!$B82*(1+inf)^F$1 -> 883.05031 | H44: =Inputs!$B82*(1+inf)^G$1 -> 905.12657 | I44: =Inputs!$B82*(1+inf)^H$1 -> 927.75473 | J44: =Inputs!$B82*(1+inf)^I$1 -> 950.9486 | K44: =Inputs!$B82*(1+inf)^J$1 -> 974.72232 | ... AM44: =Inputs!$B82*(1+inf)^AL$1 -> 1946.0283
A45: Living expenses
A46: Current baseline | C46: =Inputs!$B$25*(1+inf)^B$1*ProRate -> 41666.667 | D46: =Inputs!$B$25*(1+inf)^C$1 -> 51250 | E46: =Inputs!$B$25*(1+inf)^D$1 -> 52531.25 | F46: =Inputs!$B$25*(1+inf)^E$1 -> 53844.531 | G46: =Inputs!$B$25*(1+inf)^F$1 -> 55190.645 | H46: =Inputs!$B$25*(1+inf)^G$1 -> 56570.411 | I46: =Inputs!$B$25*(1+inf)^H$1 -> 57984.671 | J46: =Inputs!$B$25*(1+inf)^I$1 -> 59434.288 | K46: =Inputs!$B$25*(1+inf)^J$1 -> 60920.145 | ... AM46: =Inputs!$B$25*(1+inf)^AL$1 -> 121626.77
A47: ="Adjustment "&Inputs!A169 -> Adjustment from now to 65 | C47: =IF(C$3<=65,Inputs!$B$169*C$46,0) -> 0 | D47: =IF(D$3<=65,Inputs!$B$169*D$46,0) -> 0 | E47: =IF(E$3<=65,Inputs!$B$169*E$46,0) -> 0 | F47: =IF(F$3<=65,Inputs!$B$169*F$46,0) -> 0 | G47: =IF(G$3<=65,Inputs!$B$169*G$46,0) -> 0 | H47: =IF(H$3<=65,Inputs!$B$169*H$46,0) -> 0 | I47: =IF(I$3<=65,Inputs!$B$169*I$46,0) -> 0 | J47: =IF(J$3<=65,Inputs!$B$169*J$46,0) -> 0 | ... AM47: =IF(AM$3<=65,Inputs!$B$169*AM$46,0) -> 0
A48: ="Adjustment "&Inputs!A170 -> Adjustment from 66-75 | C48: =IF(AND(C$3>65,C$3<=75),Inputs!$B$170*C46,0) -> 0 | D48: =IF(AND(D$3>65,D$3<=75),Inputs!$B$170*D46,0) -> 0 | E48: =IF(AND(E$3>65,E$3<=75),Inputs!$B$170*E46,0) -> 0 | F48: =IF(AND(F$3>65,F$3<=75),Inputs!$B$170*F46,0) -> 0 | G48: =IF(AND(G$3>65,G$3<=75),Inputs!$B$170*G46,0) -> 0 | H48: =IF(AND(H$3>65,H$3<=75),Inputs!$B$170*H46,0) -> 0 | I48: =IF(AND(I$3>65,I$3<=75),Inputs!$B$170*I46,0) -> 0 | J48: =IF(AND(J$3>65,J$3<=75),Inputs!$B$170*J46,0) -> 0 | ... AM48: =IF(AND(AM$3>65,AM$3<=75),Inputs!$B$170*AM46,0) -> 0
A49: ="Adjustment "&Inputs!A171 -> Adjustment from age 76 | C49: =IF(C$3>75,Inputs!$B$171*C$46,0) -> 0 | D49: =IF(D$3>75,Inputs!$B$171*D$46,0) -> 0 | E49: =IF(E$3>75,Inputs!$B$171*E$46,0) -> 0 | F49: =IF(F$3>75,Inputs!$B$171*F$46,0) -> 0 | G49: =IF(G$3>75,Inputs!$B$171*G$46,0) -> 0 | H49: =IF(H$3>75,Inputs!$B$171*H$46,0) -> 0 | I49: =IF(I$3>75,Inputs!$B$171*I$46,0) -> 0 | J49: =IF(J$3>75,Inputs!$B$171*J$46,0) -> 0 | ... AM49: =IF(AM$3>75,Inputs!$B$171*AM$46,0) -> -24325.353
A50: Major one-off expense events
A51: =TEXT(Inputs!$B$149,"") -> Wedding | C51: =IF(C$2=Inputs!$B151,Inputs!$B150,0)*(1+inf)^B$1 -> 0 | D51: =IF(D$2=Inputs!$B151,Inputs!$B150,0)*(1+inf)^C$1 -> 0 | E51: =IF(E$2=Inputs!$B151,Inputs!$B150,0)*(1+inf)^D$1 -> 0 | F51: =IF(F$2=Inputs!$B151,Inputs!$B150,0)*(1+inf)^E$1 -> 0 | G51: =IF(G$2=Inputs!$B151,Inputs!$B150,0)*(1+inf)^F$1 -> 0 | H51: =IF(H$2=Inputs!$B151,Inputs!$B150,0)*(1+inf)^G$1 -> 0 | I51: =IF(I$2=Inputs!$B151,Inputs!$B150,0)*(1+inf)^H$1 -> 0 | J51: =IF(J$2=Inputs!$B151,Inputs!$B150,0)*(1+inf)^I$1 -> 0 | ... AM51: =IF(AM$2=Inputs!$B151,Inputs!$B150,0)*(1+inf)^AL$1 -> 0
A52: =TEXT(Inputs!$B$154,"") -> New Car | C52: =IF(C$2=Inputs!$B156,Inputs!$B155,0)*(1+inf)^B$1 -> 0 | D52: =IF(D$2=Inputs!$B156,Inputs!$B155,0)*(1+inf)^C$1 -> 0 | E52: =IF(E$2=Inputs!$B156,Inputs!$B155,0)*(1+inf)^D$1 -> 0 | F52: =IF(F$2=Inputs!$B156,Inputs!$B155,0)*(1+inf)^E$1 -> 37691.172 | G52: =IF(G$2=Inputs!$B156,Inputs!$B155,0)*(1+inf)^F$1 -> 0 | H52: =IF(H$2=Inputs!$B156,Inputs!$B155,0)*(1+inf)^G$1 -> 0 | I52: =IF(I$2=Inputs!$B156,Inputs!$B155,0)*(1+inf)^H$1 -> 0 | J52: =IF(J$2=Inputs!$B156,Inputs!$B155,0)*(1+inf)^I$1 -> 0 | ... AM52: =IF(AM$2=Inputs!$B156,Inputs!$B155,0)*(1+inf)^AL$1 -> 0
A53: =TEXT(Inputs!$B$159,"") -> New AC | C53: =IF(C$2=Inputs!$B161,Inputs!$B160,0)*(1+inf)^B$1 -> 0 | D53: =IF(D$2=Inputs!$B161,Inputs!$B160,0)*(1+inf)^C$1 -> 0 | E53: =IF(E$2=Inputs!$B161,Inputs!$B160,0)*(1+inf)^D$1 -> 0 | F53: =IF(F$2=Inputs!$B161,Inputs!$B160,0)*(1+inf)^E$1 -> 0 | G53: =IF(G$2=Inputs!$B161,Inputs!$B160,0)*(1+inf)^F$1 -> 0 | H53: =IF(H$2=Inputs!$B161,Inputs!$B160,0)*(1+inf)^G$1 -> 0 | I53: =IF(I$2=Inputs!$B161,Inputs!$B160,0)*(1+inf)^H$1 -> 0 | J53: =IF(J$2=Inputs!$B161,Inputs!$B160,0)*(1+inf)^I$1 -> 0 | ... AM53: =IF(AM$2=Inputs!$B161,Inputs!$B160,0)*(1+inf)^AL$1 -> 0
C54: =SUM(C22:C53) -> 81300 | D54: =SUM(D22:D53) -> 98169 | E54: =SUM(E22:E53) -> 95820.725 | F54: =SUM(F22:F53) -> 130084.81 | G54: =SUM(G22:G53) -> 92089.491 | H54: =SUM(H22:H53) -> 90281.062 | I54: =SUM(I22:I53) -> 77621.605 | J54: =SUM(J22:J53) -> 78710.394 | ... AM54: =SUM(AM22:AM53) -> 121626.77
A56: Net Cash Flow | C56: =C21-C54 -> 23136.875 | D56: =D21-D54 -> 24004.028 | E56: =E21-E54 -> 30618.531 | F56: =F21-F54 -> 11340.743 | G56: =G21-G54 -> -48117.49 | H56: =H21-H54 -> -46251.2 | I56: =I21-I54 -> -27443.773 | J56: =J21-J54 -> -33790.19 | ... AM56: =AM21-AM54 -> 8039.037
A57: Cash b/fwd | C57: =Inputs!B8 -> 50000 | D57: =C58 -> 73136.875 | E57: =D58 -> 97140.903 | F57: =E58 -> 127759.43 | G57: =F58 -> 139100.18 | H57: =G58 -> 90982.687 | I57: =H58 -> 44731.487 | J57: =I58 -> 17287.713 | K57: =J58 -> -16502.477 | ... AM57: =AL58 -> -145643.8
A58: Cash c/fwd | C58: =SUM(C56:C57) -> 73136.875 | D58: =SUM(D56:D57) -> 97140.903 | E58: =SUM(E56:E57) -> 127759.43 | F58: =SUM(F56:F57) -> 139100.18 | G58: =SUM(G56:G57) -> 90982.687 | H58: =SUM(H56:H57) -> 44731.487 | I58: =SUM(I56:I57) -> 17287.713 | J58: =SUM(J56:J57) -> -16502.477 | ... AM58: =SUM(AM56:AM57) -> -137604.77
A60: Net Worth before liquidations
A61: Cash | C61: =C58 -> 73136.875 | D61: =D58 -> 97140.903 | E61: =E58 -> 127759.43 | F61: =F58 -> 139100.18 | G61: =G58 -> 90982.687 | H61: =H58 -> 44731.487 | I61: =I58 -> 17287.713 | J61: =J58 -> -16502.477 | ... AM61: =AM58 -> -137604.77
A62: Home | C62: =Inputs!B12*(1+princ)^ProRate -> 614962.93 | D62: =C62*(1+princ) -> 633411.82 | E62: =D62*(1+princ) -> 652414.17 | F62: =E62*(1+princ) -> 671986.6 | G62: =F62*(1+princ) -> 692146.2 | H62: =G62*(1+princ) -> 712910.58 | I62: =H62*(1+princ) -> 734297.9 | J62: =I62*(1+princ) -> 756326.84 | K62: =J62*(1+princ) -> 779016.64 | ... AM62: =AL62*(1+princ) -> 1782333.7
A63: Other property
A64: =TEXT(Inputs!$B$60,"") -> Sliema | C64: =Inputs!B61*(1+princ)^ProRate -> 307481.47 | D64: =C64*(1+princ) -> 316705.91 | E64: =D64*(1+princ) -> 326207.09 | F64: =E64*(1+princ) -> 335993.3 | G64: =F64*(1+princ) -> 346073.1 | H64: =G64*(1+princ) -> 356455.29 | I64: =H64*(1+princ) -> 367148.95 | J64: =I64*(1+princ) -> 378163.42 | K64: =J64*(1+princ) -> 389508.32 | ... AM64: =AL64*(1+princ) -> 891166.87
A65: =TEXT(Inputs!$B$65,"") -> Gzira | C65: =Inputs!B66*(1+princ)^ProRate -> 153740.73 | D65: =C65*(1+princ) -> 158352.95 | E65: =D65*(1+princ) -> 163103.54 | F65: =E65*(1+princ) -> 167996.65 | G65: =F65*(1+princ) -> 173036.55 | H65: =G65*(1+princ) -> 178227.65 | I65: =H65*(1+princ) -> 183574.47 | J65: =I65*(1+princ) -> 189081.71 | K65: =J65*(1+princ) -> 194754.16 | ... AM65: =AL65*(1+princ) -> 445583.43
A66: =TEXT(Inputs!$B$70,"") -> Qormi | C66: =Inputs!B71*(1+princ)^ProRate -> 225486.41 | D66: =C66*(1+princ) -> 232251 | E66: =D66*(1+princ) -> 239218.53 | F66: =E66*(1+princ) -> 246395.09 | G66: =F66*(1+princ) -> 253786.94 | H66: =G66*(1+princ) -> 261400.55 | I66: =H66*(1+princ) -> 269242.56 | J66: =I66*(1+princ) -> 277319.84 | K66: =J66*(1+princ) -> 285639.44 | ... AM66: =AL66*(1+princ) -> 653522.37
A67: =TEXT(Inputs!$B$75,"") -> Gudja | C67: =Inputs!B76*(1+princ)^ProRate -> 81995.057 | D67: =C67*(1+princ) -> 84454.909 | E67: =D67*(1+princ) -> 86988.556 | F67: =E67*(1+princ) -> 89598.213 | G67: =F67*(1+princ) -> 92286.159 | H67: =G67*(1+princ) -> 95054.744 | I67: =H67*(1+princ) -> 97906.387 | J67: =I67*(1+princ) -> 100843.58 | K67: =J67*(1+princ) -> 103868.89 | ... AM67: =AL67*(1+princ) -> 237644.5
A68: =TEXT(Inputs!$B$80,"") -> Marsa | C68: =Inputs!B81*(1+princ)^ProRate -> 122992.59 | D68: =C68*(1+princ) -> 126682.36 | E68: =D68*(1+princ) -> 130482.83 | F68: =E68*(1+princ) -> 134397.32 | G68: =F68*(1+princ) -> 138429.24 | H68: =G68*(1+princ) -> 142582.12 | I68: =H68*(1+princ) -> 146859.58 | J68: =I68*(1+princ) -> 151265.37 | K68: =J68*(1+princ) -> 155803.33 | ... AM68: =AL68*(1+princ) -> 356466.75
A69: Stock market equity investments | C69: =Inputs!B10*(1+stinc)^ProRate -> 31987.064 | D69: =C69*(1+stinc) -> 34546.03 | E69: =D69*(1+stinc) -> 37309.712 | F69: =E69*(1+stinc) -> 40294.489 | G69: =F69*(1+stinc) -> 43518.048 | H69: =G69*(1+stinc) -> 46999.492 | I69: =H69*(1+stinc) -> 50759.451 | J69: =I69*(1+stinc) -> 54820.207 | K69: =J69*(1+stinc) -> 59205.824 | ... AM69: =AL69*(1+stinc) -> 510774.94
A70: Home loan | C70: =-MAX(FV(Inputs!$B16/12,C$1*12+MthOff,Inputs!$B17,-Inputs!$B15),0) -> -43173.554 | D70: =-MAX(FV(Inputs!$B16/12,D$1*12+MthOff,Inputs!$B17,-Inputs!$B15),0) -> -34753.613 | E70: =-MAX(FV(Inputs!$B16/12,E$1*12+MthOff,Inputs!$B17,-Inputs!$B15),0) -> -26077.571 | F70: =-MAX(FV(Inputs!$B16/12,F$1*12+MthOff,Inputs!$B17,-Inputs!$B15),0) -> -17137.639 | G70: =-MAX(FV(Inputs!$B16/12,G$1*12+MthOff,Inputs!$B17,-Inputs!$B15),0) -> -7925.7905 | H70: =-MAX(FV(Inputs!$B16/12,H$1*12+MthOff,Inputs!$B17,-Inputs!$B15),0) -> 0 | I70: =-MAX(FV(Inputs!$B16/12,I$1*12+MthOff,Inputs!$B17,-Inputs!$B15),0) -> 0 | J70: =-MAX(FV(Inputs!$B16/12,J$1*12+MthOff,Inputs!$B17,-Inputs!$B15),0) -> 0 | ... AM70: =-MAX(FV(Inputs!$B16/12,AM$1*12+MthOff,Inputs!$B17,-Inputs!$B15),0) -> 0
A71: Other property loans
A72: =TEXT(Inputs!$B$60,"") -> Sliema | C72: =-MAX(FV(Inputs!$B101/12,C$1*12+MthOff,Inputs!$B102,-Inputs!$B100),0) -> -46207.53 | D72: =-MAX(FV(Inputs!$B101/12,D$1*12+MthOff,Inputs!$B102,-Inputs!$B100),0) -> -41529.785 | E72: =-MAX(FV(Inputs!$B101/12,E$1*12+MthOff,Inputs!$B102,-Inputs!$B100),0) -> -36709.762 | F72: =-MAX(FV(Inputs!$B101/12,F$1*12+MthOff,Inputs!$B102,-Inputs!$B100),0) -> -31743.133 | G72: =-MAX(FV(Inputs!$B101/12,G$1*12+MthOff,Inputs!$B102,-Inputs!$B100),0) -> -26625.439 | H72: =-MAX(FV(Inputs!$B101/12,H$1*12+MthOff,Inputs!$B102,-Inputs!$B100),0) -> -21352.086 | I72: =-MAX(FV(Inputs!$B101/12,I$1*12+MthOff,Inputs!$B102,-Inputs!$B100),0) -> -15918.339 | J72: =-MAX(FV(Inputs!$B101/12,J$1*12+MthOff,Inputs!$B102,-Inputs!$B100),0) -> -10319.319 | ... AM72: =-MAX(FV(Inputs!$B101/12,AM$1*12+MthOff,Inputs!$B102,-Inputs!$B100),0) -> 0
A73: =TEXT(Inputs!$B$65,"") -> Gzira | C73: =-MAX(FV(Inputs!$B106/12,C$1*12+MthOff,Inputs!$B107,-Inputs!$B105),0) -> -6627.667 | D73: =-MAX(FV(Inputs!$B106/12,D$1*12+MthOff,Inputs!$B107,-Inputs!$B105),0) -> -4339.3195 | E73: =-MAX(FV(Inputs!$B106/12,E$1*12+MthOff,Inputs!$B107,-Inputs!$B105),0) -> -2004.7832 | F73: =-MAX(FV(Inputs!$B106/12,F$1*12+MthOff,Inputs!$B107,-Inputs!$B105),0) -> 0 | G73: =-MAX(FV(Inputs!$B106/12,G$1*12+MthOff,Inputs!$B107,-Inputs!$B105),0) -> 0 | H73: =-MAX(FV(Inputs!$B106/12,H$1*12+MthOff,Inputs!$B107,-Inputs!$B105),0) -> 0 | I73: =-MAX(FV(Inputs!$B106/12,I$1*12+MthOff,Inputs!$B107,-Inputs!$B105),0) -> 0 | J73: =-MAX(FV(Inputs!$B106/12,J$1*12+MthOff,Inputs!$B107,-Inputs!$B105),0) -> 0 | ... AM73: =-MAX(FV(Inputs!$B106/12,AM$1*12+MthOff,Inputs!$B107,-Inputs!$B105),0) -> 0
A74: =TEXT(Inputs!$B$70,"") -> Qormi | C74: =-MAX(FV(Inputs!$B111/12,C$1*12+MthOff,Inputs!$B112,-Inputs!$B110),0) -> -13089.45 | D74: =-MAX(FV(Inputs!$B111/12,D$1*12+MthOff,Inputs!$B112,-Inputs!$B110),0) -> -10689.418 | E74: =-MAX(FV(Inputs!$B111/12,E$1*12+MthOff,Inputs!$B112,-Inputs!$B110),0) -> -8166.5945 | F74: =-MAX(FV(Inputs!$B111/12,F$1*12+MthOff,Inputs!$B112,-Inputs!$B110),0) -> -5514.6991 | G74: =-MAX(FV(Inputs!$B111/12,G$1*12+MthOff,Inputs!$B112,-Inputs!$B110),0) -> -2727.1277 | H74: =-MAX(FV(Inputs!$B111/12,H$1*12+MthOff,Inputs!$B112,-Inputs!$B110),0) -> 0 | I74: =-MAX(FV(Inputs!$B111/12,I$1*12+MthOff,Inputs!$B112,-Inputs!$B110),0) -> 0 | J74: =-MAX(FV(Inputs!$B111/12,J$1*12+MthOff,Inputs!$B112,-Inputs!$B110),0) -> 0 | ... AM74: =-MAX(FV(Inputs!$B111/12,AM$1*12+MthOff,Inputs!$B112,-Inputs!$B110),0) -> 0
A75: =TEXT(Inputs!$B$75,"") -> Gudja | C75: =-MAX(FV(Inputs!$B116/12,C$1*12+MthOff,Inputs!$B117,-Inputs!$B115),0) -> -3952.5609 | D75: =-MAX(FV(Inputs!$B116/12,D$1*12+MthOff,Inputs!$B117,-Inputs!$B115),0) -> -3063.4917 | E75: =-MAX(FV(Inputs!$B116/12,E$1*12+MthOff,Inputs!$B117,-Inputs!$B115),0) -> -2156.4772 | F75: =-MAX(FV(Inputs!$B116/12,F$1*12+MthOff,Inputs!$B117,-Inputs!$B115),0) -> -1231.1552 | G75: =-MAX(FV(Inputs!$B116/12,G$1*12+MthOff,Inputs!$B117,-Inputs!$B115),0) -> -287.15625 | H75: =-MAX(FV(Inputs!$B116/12,H$1*12+MthOff,Inputs!$B117,-Inputs!$B115),0) -> 0 | I75: =-MAX(FV(Inputs!$B116/12,I$1*12+MthOff,Inputs!$B117,-Inputs!$B115),0) -> 0 | J75: =-MAX(FV(Inputs!$B116/12,J$1*12+MthOff,Inputs!$B117,-Inputs!$B115),0) -> 0 | ... AM75: =-MAX(FV(Inputs!$B116/12,AM$1*12+MthOff,Inputs!$B117,-Inputs!$B115),0) -> 0
A76: =TEXT(Inputs!$B$80,"") -> Marsa | C76: =-MAX(FV(Inputs!$B121/12,C$1*12+MthOff,Inputs!$B122,-Inputs!$B120),0) -> -8551.2062 | D76: =-MAX(FV(Inputs!$B121/12,D$1*12+MthOff,Inputs!$B122,-Inputs!$B120),0) -> -7351.3334 | E76: =-MAX(FV(Inputs!$B121/12,E$1*12+MthOff,Inputs!$B122,-Inputs!$B120),0) -> -6114.9653 | F76: =-MAX(FV(Inputs!$B121/12,F$1*12+MthOff,Inputs!$B122,-Inputs!$B120),0) -> -4840.9918 | G76: =-MAX(FV(Inputs!$B121/12,G$1*12+MthOff,Inputs!$B122,-Inputs!$B120),0) -> -3528.2693 | H76: =-MAX(FV(Inputs!$B121/12,H$1*12+MthOff,Inputs!$B122,-Inputs!$B120),0) -> -2175.6191 | I76: =-MAX(FV(Inputs!$B121/12,I$1*12+MthOff,Inputs!$B122,-Inputs!$B120),0) -> -781.82667 | J76: =-MAX(FV(Inputs!$B121/12,J$1*12+MthOff,Inputs!$B122,-Inputs!$B120),0) -> 0 | ... AM76: =-MAX(FV(Inputs!$B121/12,AM$1*12+MthOff,Inputs!$B122,-Inputs!$B120),0) -> 0
A77: Other loan | C77: =-MAX(FV(Inputs!$B126/12,C$1*12+MthOff,Inputs!$B127,-Inputs!$B125),0) -> -3693.1592 | D77: =-MAX(FV(Inputs!$B126/12,D$1*12+MthOff,Inputs!$B127,-Inputs!$B125),0) -> -3304.1671 | E77: =-MAX(FV(Inputs!$B126/12,E$1*12+MthOff,Inputs!$B127,-Inputs!$B125),0) -> -2891.1827 | F77: =-MAX(FV(Inputs!$B126/12,F$1*12+MthOff,Inputs!$B127,-Inputs!$B125),0) -> -2452.7265 | G77: =-MAX(FV(Inputs!$B126/12,G$1*12+MthOff,Inputs!$B127,-Inputs!$B125),0) -> -1987.2271 | H77: =-MAX(FV(Inputs!$B126/12,H$1*12+MthOff,Inputs!$B127,-Inputs!$B125),0) -> -1493.0168 | I77: =-MAX(FV(Inputs!$B126/12,I$1*12+MthOff,Inputs!$B127,-Inputs!$B125),0) -> -968.32473 | J77: =-MAX(FV(Inputs!$B126/12,J$1*12+MthOff,Inputs!$B127,-Inputs!$B125),0) -> -411.27076 | ... AM77: =-MAX(FV(Inputs!$B126/12,AM$1*12+MthOff,Inputs!$B127,-Inputs!$B125),0) -> 0
C78: =SUM(C60:C77) -> 1486488 | D78: =SUM(D60:D77) -> 1578514.8 | E78: =SUM(E60:E77) -> 1679362.5 | F78: =SUM(F60:F77) -> 1762841.5 | G78: =SUM(G60:G77) -> 1787177.9 | H78: =SUM(H60:H77) -> 1813341.2 | I78: =SUM(I60:I77) -> 1849408.5 | J78: =SUM(J60:J77) -> 1880587.9 | ... AM78: =SUM(AM60:AM77) -> 4739887.8
A80: Cash available (after buffer) | C80: =C61-buffer -> 33136.875 | D80: =D61-buffer -> 57140.903 | E80: =E61-buffer -> 87759.434 | F80: =F61-buffer -> 99100.176 | G80: =G61-buffer -> 50982.687 | H80: =H61-buffer -> 4731.4867 | I80: =I61-buffer -> -22712.287 | J80: =J61-buffer -> -56502.477 | ... AM80: =AM61-buffer -> -177604.77
A81: Liquidation required | C81: =IF(C80<0,-C80,0) -> 0 | D81: =IF(D80+SUM($C81:C81)<0,-(D80+SUM($C81:C81)),0) -> 0 | E81: =IF(E80+SUM($C81:D81)<0,-(E80+SUM($C81:D81)),0) -> 0 | F81: =IF(F80+SUM($C81:E81)<0,-(F80+SUM($C81:E81)),0) -> 0 | G81: =IF(G80+SUM($C81:F81)<0,-(G80+SUM($C81:F81)),0) -> 0 | H81: =IF(H80+SUM($C81:G81)<0,-(H80+SUM($C81:G81)),0) -> 0 | I81: =IF(I80+SUM($C81:H81)<0,-(I80+SUM($C81:H81)),0) -> 22712.287 | J81: =IF(J80+SUM($C81:I81)<0,-(J80+SUM($C81:I81)),0) -> 33790.19 | K81: =IF(K80+SUM($C81:J81)<0,-(K80+SUM($C81:J81)),0) -> 51555.296 | ... AM81: =IF(AM80+SUM($C81:AL81)<0,-(AM80+SUM($C81:AL81)),0) -> 0
A83: Liquidations
A85: Stock market equity
A86: b/fwd | C86: =C69 -> 31987.064 | D86: =C89 -> 31987.064 | E86: =D89 -> 34546.03 | F86: =E89 -> 37309.712 | G86: =F89 -> 40294.489 | H86: =G89 -> 43518.048 | I86: =H89 -> 46999.492 | J86: =I89 -> 24939.167 | K86: =J89 -> 0 | ... AM86: =AL89 -> 0
A87: Disposals | C87: =-MIN(C86, C81/(1-Inputs!$B$193)) -> 0 | D87: =-MIN(D86, D81/(1-Inputs!$B$193)) -> 0 | E87: =-MIN(E86, E81/(1-Inputs!$B$193)) -> 0 | F87: =-MIN(F86, F81/(1-Inputs!$B$193)) -> 0 | G87: =-MIN(G86, G81/(1-Inputs!$B$193)) -> 0 | H87: =-MIN(H86, H81/(1-Inputs!$B$193)) -> 0 | I87: =-MIN(I86, I81/(1-Inputs!$B$193)) -> -23907.67 | J87: =-MIN(J86, J81/(1-Inputs!$B$193)) -> -24939.167 | ... AM87: =-MIN(AM86, AM81/(1-Inputs!$B$193)) -> 0
A88: Growth | C88: 0 | D88: =SUM(D86:D87)*stinc -> 2558.9651 | E88: =SUM(E86:E87)*stinc -> 2763.6824 | F88: =SUM(F86:F87)*stinc -> 2984.777 | G88: =SUM(G86:G87)*stinc -> 3223.5591 | H88: =SUM(H86:H87)*stinc -> 3481.4438 | I88: =SUM(I86:I87)*stinc -> 1847.3457 | J88: =SUM(J86:J87)*stinc -> 0 | K88: =SUM(K86:K87)*stinc -> 0 | ... AM88: =SUM(AM86:AM87)*stinc -> 0
A89: c/fwd | C89: =SUM(C86:C88) -> 31987.064 | D89: =SUM(D86:D88) -> 34546.03 | E89: =SUM(E86:E88) -> 37309.712 | F89: =SUM(F86:F88) -> 40294.489 | G89: =SUM(G86:G88) -> 43518.048 | H89: =SUM(H86:H88) -> 46999.492 | I89: =SUM(I86:I88) -> 24939.167 | J89: =SUM(J86:J88) -> 0 | ... AM89: =SUM(AM86:AM88) -> 0
A90: Disposal costs | C90: =C87*Inputs!$B$193 -> 0 | D90: =D87*Inputs!$B$193 -> 0 | E90: =E87*Inputs!$B$193 -> 0 | F90: =F87*Inputs!$B$193 -> 0 | G90: =G87*Inputs!$B$193 -> 0 | H90: =H87*Inputs!$B$193 -> 0 | I90: =I87*Inputs!$B$193 -> -1195.3835 | J90: =J87*Inputs!$B$193 -> -1246.9584 | ... AM90: =AM87*Inputs!$B$193 -> 0
A91: Net proceeds | C91: =-C87+C90 -> 0 | D91: =-D87+D90 -> 0 | E91: =-E87+E90 -> 0 | F91: =-F87+F90 -> 0 | G91: =-G87+G90 -> 0 | H91: =-H87+H90 -> 0 | I91: =-I87+I90 -> 22712.287 | J91: =-J87+J90 -> 23692.209 | ... AM91: =-AM87+AM90 -> 0
A93: Cash available (after buffer) | C93: =C80+SUM($C91:C91) -> 33136.875 | D93: =D80+SUM($C91:D91) -> 57140.903 | E93: =E80+SUM($C91:E91) -> 87759.434 | F93: =F80+SUM($C91:F91) -> 99100.176 | G93: =G80+SUM($C91:G91) -> 50982.687 | H93: =H80+SUM($C91:H91) -> 4731.4867 | I93: =I80+SUM($C91:I91) -> 0 | J93: =J80+SUM($C91:J91) -> -10097.982 | ... AM93: =AM80+SUM($C91:AM91) -> -131200.27
A94: Liquidation required | C94: =IF(C93<0,-C93,0) -> 0 | D94: =IF(D93+SUM($C94:C94)<0,-(D93+SUM($C94:C94)),0) -> 0 | E94: =IF(E93+SUM($C94:D94)<0,-(E93+SUM($C94:D94)),0) -> 0 | F94: =IF(F93+SUM($C94:E94)<0,-(F93+SUM($C94:E94)),0) -> 0 | G94: =IF(G93+SUM($C94:F94)<0,-(G93+SUM($C94:F94)),0) -> 0 | H94: =IF(H93+SUM($C94:G94)<0,-(H93+SUM($C94:G94)),0) -> 0 | I94: =IF(I93+SUM($C94:H94)<0,-(I93+SUM($C94:H94)),0) -> 0 | J94: =IF(J93+SUM($C94:I94)<0,-(J93+SUM($C94:I94)),0) -> 10097.982 | K94: =IF(K93+SUM($C94:J94)<0,-(K93+SUM($C94:J94)),0) -> 51555.296 | ... AM94: =IF(AM93+SUM($C94:AL94)<0,-(AM93+SUM($C94:AL94)),0) -> 0
A96: =IF(Inputs!$B$197=6,IFERROR(_xlfn.XLOOKUP($B96,Inputs!$B$198:$B$202,Inputs!$A$198:$A$202,,0,1),""),IFERROR(_xlfn.XLOOKUP($B96,Inputs!$C$198:$C$202,Inputs!$A$198:$A$202,,0,1),"")) -> Gudja | B96: 1
A97: b/fwd | C97: =IFERROR(VLOOKUP($A96,$A$60:$H$78,C$1+2,FALSE),0) -> 81995.057 | D97: =C100 -> 81995.057 | E97: =D100 -> 84454.909 | F97: =E100 -> 86988.556 | G97: =F100 -> 89598.213 | H97: =G100 -> 92286.159 | I97: =H100 -> 95054.744 | J97: =I100 -> 0 | K97: =J100 -> 0 | ... AM97: =AL100 -> 0
A98: Disposals | C98: =-IF(SUM(C94:D94)>0,C97,0) -> 0 | D98: =-IF(E94>0,D97,0) -> 0 | E98: =-IF(F94>0,E97,0) -> 0 | F98: =-IF(G94>0,F97,0) -> 0 | G98: =-IF(H94>0,G97,0) -> 0 | H98: =-IF(I94>0,H97,0) -> 0 | I98: =-IF(J94>0,I97,0) -> -95054.744 | J98: =-IF(K94>0,J97,0) -> 0 | K98: =-IF(L94>0,K97,0) -> 0 | ... AM98: =-IF(AN94>0,AM97,0) -> 0
A99: Growth | C99: 0 | D99: =SUM(D97:D98)*princ -> 2459.8517 | E99: =SUM(E97:E98)*princ -> 2533.6473 | F99: =SUM(F97:F98)*princ -> 2609.6567 | G99: =SUM(G97:G98)*princ -> 2687.9464 | H99: =SUM(H97:H98)*princ -> 2768.5848 | I99: =SUM(I97:I98)*princ -> 0 | J99: =SUM(J97:J98)*princ -> 0 | K99: =SUM(K97:K98)*princ -> 0 | ... AM99: =SUM(AM97:AM98)*princ -> 0
A100: c/fwd | C100: =SUM(C97:C99) -> 81995.057 | D100: =SUM(D97:D99) -> 84454.909 | E100: =SUM(E97:E99) -> 86988.556 | F100: =SUM(F97:F99) -> 89598.213 | G100: =SUM(G97:G99) -> 92286.159 | H100: =SUM(H97:H99) -> 95054.744 | I100: =SUM(I97:I99) -> 0 | J100: =SUM(J97:J99) -> 0 | ... AM100: =SUM(AM97:AM99) -> 0
A101: Disposal costs | C101: =C98*Inputs!$B$195 -> 0 | D101: =D98*Inputs!$B$195 -> 0 | E101: =E98*Inputs!$B$195 -> 0 | F101: =F98*Inputs!$B$195 -> 0 | G101: =G98*Inputs!$B$195 -> 0 | H101: =H98*Inputs!$B$195 -> 0 | I101: =I98*Inputs!$B$195 -> -14258.212 | J101: =J98*Inputs!$B$195 -> 0 | ... AM101: =AM98*Inputs!$B$195 -> 0
A102: Rental income foregone | C102: =IFERROR(-IF(C97=0,VLOOKUP($A96,$8:$12,C$1+2,FALSE),0),0) -> 0 | D102: =IFERROR(-IF(D97=0,VLOOKUP($A96,$8:$12,D$1+2,FALSE),0),0) -> 0 | E102: =IFERROR(-IF(E97=0,VLOOKUP($A96,$8:$12,E$1+2,FALSE),0),0) -> 0 | F102: =IFERROR(-IF(F97=0,VLOOKUP($A96,$8:$12,F$1+2,FALSE),0),0) -> 0 | G102: =IFERROR(-IF(G97=0,VLOOKUP($A96,$8:$12,G$1+2,FALSE),0),0) -> 0 | H102: =IFERROR(-IF(H97=0,VLOOKUP($A96,$8:$12,H$1+2,FALSE),0),0) -> 0 | I102: =IFERROR(-IF(I97=0,VLOOKUP($A96,$8:$12,I$1+2,FALSE),0),0) -> 0 | J102: =IFERROR(-IF(J97=0,VLOOKUP($A96,$8:$12,J$1+2,FALSE),0),0) -> -5124.4744 | ... AM102: =IFERROR(-IF(AM97=0,VLOOKUP($A96,$8:$12,AM$1+2,FALSE),0),0) -> -12076.16
A103: Annual cost saved | C103: =IFERROR(IF(C97=0,VLOOKUP($A96,$40:$44,C$1+2,FALSE),0),0) -> 0 | D103: =IFERROR(IF(D97=0,VLOOKUP($A96,$40:$44,D$1+2,FALSE),0),0) -> 0 | E103: =IFERROR(IF(E97=0,VLOOKUP($A96,$40:$44,E$1+2,FALSE),0),0) -> 0 | F103: =IFERROR(IF(F97=0,VLOOKUP($A96,$40:$44,F$1+2,FALSE),0),0) -> 0 | G103: =IFERROR(IF(G97=0,VLOOKUP($A96,$40:$44,G$1+2,FALSE),0),0) -> 0 | H103: =IFERROR(IF(H97=0,VLOOKUP($A96,$40:$44,H$1+2,FALSE),0),0) -> 0 | I103: =IFERROR(IF(I97=0,VLOOKUP($A96,$40:$44,I$1+2,FALSE),0),0) -> 0 | J103: =IFERROR(IF(J97=0,VLOOKUP($A96,$40:$44,J$1+2,FALSE),0),0) -> 1188.6858 | ... AM103: =IFERROR(IF(AM97=0,VLOOKUP($A96,$40:$44,AM$1+2,FALSE),0),0) -> 2432.5353
A104: Loan repayment | B104: =A96 -> Gudja | C104: =IF(AND(C97>0,C100=0),VLOOKUP($A96,$72:$76,C$1+2,FALSE),0) -> 0 | D104: =IF(AND(D97>0,D100=0),VLOOKUP($A96,$72:$76,D$1+2,FALSE),0) -> 0 | E104: =IF(AND(E97>0,E100=0),VLOOKUP($A96,$72:$76,E$1+2,FALSE),0) -> 0 | F104: =IF(AND(F97>0,F100=0),VLOOKUP($A96,$72:$76,F$1+2,FALSE),0) -> 0 | G104: =IF(AND(G97>0,G100=0),VLOOKUP($A96,$72:$76,G$1+2,FALSE),0) -> 0 | H104: =IF(AND(H97>0,H100=0),VLOOKUP($A96,$72:$76,H$1+2,FALSE),0) -> 0 | I104: =IF(AND(I97>0,I100=0),VLOOKUP($A96,$72:$76,I$1+2,FALSE),0) -> 0 | J104: =IF(AND(J97>0,J100=0),VLOOKUP($A96,$72:$76,J$1+2,FALSE),0) -> 0 | ... AM104: =IF(AND(AM97>0,AM100=0),VLOOKUP($A96,$72:$76,AM$1+2,FALSE),0) -> 0
A105: Net proceeds | C105: =-C98+SUM(C101:C104) -> 0 | D105: =-D98+SUM(D101:D104) -> 0 | E105: =-E98+SUM(E101:E104) -> 0 | F105: =-F98+SUM(F101:F104) -> 0 | G105: =-G98+SUM(G101:G104) -> 0 | H105: =-H98+SUM(H101:H104) -> 0 | I105: =-I98+SUM(I101:I104) -> 80796.533 | J105: =-J98+SUM(J101:J104) -> -3935.7887 | ... AM105: =-AM98+SUM(AM101:AM104) -> -9643.6244
A107: Cash available (after buffer) | C107: =C93+SUM($C105:C105) -> 33136.875 | D107: =D93+SUM($C105:D105) -> 57140.903 | E107: =E93+SUM($C105:E105) -> 87759.434 | F107: =F93+SUM($C105:F105) -> 99100.176 | G107: =G93+SUM($C105:G105) -> 50982.687 | H107: =H93+SUM($C105:H105) -> 4731.4867 | I107: =I93+SUM($C105:I105) -> 80796.533 | J107: =J93+SUM($C105:J105) -> 66762.762 | ... AM107: =AM93+SUM($C105:AM105) -> -242016.22
A108: Extra cash | C108: =MAX(C107+buffer,0)-MAX(C$93+buffer,0) -> 0 | D108: =MAX(D107+buffer,0)-MAX(D$93+buffer,0) -> 0 | E108: =MAX(E107+buffer,0)-MAX(E$93+buffer,0) -> 0 | F108: =MAX(F107+buffer,0)-MAX(F$93+buffer,0) -> 0 | G108: =MAX(G107+buffer,0)-MAX(G$93+buffer,0) -> 0 | H108: =MAX(H107+buffer,0)-MAX(H$93+buffer,0) -> 0 | I108: =MAX(I107+buffer,0)-MAX(I$93+buffer,0) -> 80796.533 | J108: =MAX(J107+buffer,0)-MAX(J$93+buffer,0) -> 76860.744 | ... AM108: =MAX(AM107+buffer,0)-MAX(AM$93+buffer,0) -> 0
...
